Workbook

Sheet 05-01-2026 
A3: FV | E3: rto: 210 | F3: 46027 | I3: COMPRA
A5: CANTIDAD | B5: UNIDAD | C5: PRODUCTO | D5: PRECIO | E5: TOTAL | F5: TOTAL + IVA | I5: PRECIO | J5: TOTAL | K5: DIFERENCIA
A6: 1 | B6: CAJÓN | C6: HUEVOS | D6: 52000 | E6: =A6*D6 -> 52000 | F6: =E6*1.21 -> 62920 | I6: 45000 | J6: =I6*A6 -> 45000 | K6: =F6-J6 -> 17920
A7: 4 | B7: CAJA | C7: MANZANA VERDE | D7: 77000 | E7: =A7*D7 -> 308000 | F7: =E7*1.105 -> 340340 | I7: 38000 | J7: =I7*A7 -> 152000 | K7: =F7-J7 -> 188340
A8: 2 | B8: CAJÓN | C8: DURAZNO | D8: 42000 | E8: =A8*D8 -> 84000 | F8: =E8*1.105 -> 92820 | I8: 38000 | J8: =I8*A8 -> 76000 | K8: =F8-J8 -> 16820
A9: 2 | B9: CAJA | C9: MELÓN | D9: 30000 | E9: =A9*D9 -> 60000 | F9: =E9*1.105 -> 66300 | I9: 22000 | J9: =I9*A9 -> 44000 | K9: =F9-J9 -> 22300
A10: 30 | B10: KG | C10: SANDÍA | D10: 1500 | E10: =A10*D10 -> 45000 | F10: =E10*1.105 -> 49725 | I10: 600 | J10: =I10*A10 -> 18000 | K10: =F10-J10 -> 31725
A11: 4 | B11: CAJA | C11: BANANA | D11: 46000 | E11: =A11*D11 -> 184000 | F11: =E11*1.105 -> 203320 | I11: 37000 | J11: =I11*A11 -> 148000 | K11: =F11-J11 -> 55320
A12: 2 | B12: CAJÓN | C12: NARANJA | D12: 23000 | E12: =A12*D12 -> 46000 | F12: =E12*1.105 -> 50830 | I12: 13000 | J12: =I12*A12 -> 26000 | K12: =F12-J12 -> 24830
A13: 2 | B13: CAJÓN | C13: CIRUELAS | D13: 45000 | E13: =A13*D13 -> 90000 | F13: =E13*1.105 -> 99450 | I13: 38000 | J13: =I13*A13 -> 76000 | K13: =F13-J13 -> 23450
A14: 1 | B14: CAJÓN | C14: LIMÓN | D14: 48000 | E14: =A14*D14 -> 48000 | F14: =E14*1.105 -> 53040 | I14: 40000 | J14: =I14*A14 -> 40000 | K14: =F14-J14 -> 13040
A15: 1 | B15: CAJÓN | C15: MORRÓN ROJO | D15: 20000 | E15: =A15*D15 -> 20000 | F15: =E15*1.105 -> 22100 | I15: 15000 | J15: =I15*A15 -> 15000 | K15: =F15-J15 -> 7100
A16: 1 | B16: CAJÓN | C16: MORRÓN VERDE | D16: 19000 | E16: =A16*D16 -> 19000 | F16: =E16*1.105 -> 20995 | I16: 14000 | J16: =I16*A16 -> 14000 | K16: =F16-J16 -> 6995
A17: 2 | B17: CAJÓN | C17: ZAPALLITO REDONDO | D17: 13000 | E17: =A17*D17 -> 26000 | F17: =E17*1.105 -> 28730 | I17: 10000 | J17: =I17*A17 -> 20000 | K17: =F17-J17 -> 8730
A18: 2 | B18: PAQUETE | C18: BROTES DE SOJA | D18: 3000 | E18: =A18*D18 -> 6000 | F18: =E18*1.105 -> 6630 | I18: 1800 | J18: =I18*A18 -> 3600 | K18: =F18-J18 -> 3030
... A26: 2 | B26: KG | C26: JENGIBRE | D26: 5000 | E26: =A26*D26 -> 10000 | F26: =E26*1.105 -> 11050 | I26: 4000 | J26: =I26*A26 -> 8000 | K26: =F26-J26 -> 3050
A27: 15 | B27: UNIDAD | C27: PALTA | D27: 1300 | E27: =A27*D27 -> 19500 | F27: =E27*1.105 -> 21547.5 | I27: =50000/70 -> 714.28571 | J27: =I27*A27 -> 10714.286 | K27: =F27-J27 -> 10833.214
A28: 6 | B28: BANDEJA | C28: ARÁNDANOS | D28: 2500 | E28: =A28*D28 -> 15000 | F28: =E28*1.105 -> 16575 | I28: =16000/12 -> 1333.3333 | J28: =I28*A28 -> 8000 | K28: =F28-J28 -> 8575
A29: 5 | B29: KG | C29: CHAMPIÑÓN | D29: 20000 | E29: =A29*D29 -> 100000 | F29: =E29*1.105 -> 110500 | I29: =75000/5 -> 15000 | J29: =I29*A29 -> 75000 | K29: =F29-J29 -> 35500
A30: 2 | B30: CAJON | C30: TOMATE REDONDO | D30: 32000 | E30: =A30*D30 -> 64000 | F30: =E30*1.105 -> 70720 | G30: BOLSA | J30: =I30*A30 -> 0 | K30: =F30-J30 -> 70720
A31: 1 | B31: CAJA | C31: BANANA | D31: 46000 | E31: =A31*D31 -> 46000 | F31: =E31*1.105 -> 50830 | G31: BOLSA | J31: =I31*A31 -> 0 | K31: =F31-J31 -> 50830
A32: 0.5 | B32: CAJON | C32: HUEVOS | D32: 52000 | E32: =A32*D32 -> 26000 | F32: =E32*1.21 -> 31460 | G32: BOLSA | J32: =I32*A32 -> 0 | K32: =F32-J32 -> 31460
A33: 1 | B33: CAJON | C33: TOMATE CHERRY | D33: 35000 | E33: =A33*D33 -> 35000 | F33: =E33*1.105 -> 38675 | G33: BOLSA | J33: =I33*A33 -> 0 | K33: =F33-J33 -> 38675
A34: 1 | B34: CAJON | C34: PEPINO | D34: 16000 | E34: =A34*D34 -> 16000 | F34: =E34*1.105 -> 17680 | G34: BOLSA | J34: =I34*A34 -> 0 | K34: =F34-J34 -> 17680
A35: 1 | B35: CAJON | C35: MORRON VERDE | D35: 19000 | E35: =A35*D35 -> 19000 | F35: =E35*1.105 -> 20995 | G35: BOLSA | J35: =I35*A35 -> 0 | K35: =F35-J35 -> 20995
A36: 1 | B36: CAJON | C36: MORRON ROJO | D36: 20000 | E36: =A36*D36 -> 20000 | F36: =E36*1.105 -> 22100 | G36: BOLSA | J36: =I36*A36 -> 0 | K36: =F36-J36 -> 22100
A37: 1 | B37: CAJON | C37: LIMON | D37: 48000 | E37: =A37*D37 -> 48000 | F37: =E37*1.105 -> 53040 | G37: BOLSA | J37: =I37*A37 -> 0 | K37: =F37-J37 -> 53040
A38: 1 | B38: CAJON | C38: MANZANA VERDE | D38: 77000 | E38: =A38*D38 -> 77000 | F38: =E38*1.105 -> 85085 | G38: BOLSA PROPIA | J38: =I38*A38 -> 0 | K38: =F38-J38 -> 85085
E40: =SUM(E6:E38) -> 1723500 | F40: =SUM(F6:F38) -> 1912657.5 | K40: =SUM(K6:K38) -> 949343.21 | L40: =K40/F40 -> 0.49634773
A43: BRASOV | D43: rto: 1 | E43: 46027 | I43: COMPRA
A45: CANTIDAD | B45: UNIDAD | C45: PRODUCTO | D45: PRECIO | E45: TOTAL | I45: PRECIO | J45: TOTAL | K45: DIFERENCIA
A46: 2 | B46: UNIDAD | C46: APIO | D46: 1500 | E46: =A46*D46 -> 3000 | I46: 1000 | J46: =I46*A46 -> 2000 | K46: =E46-J46 -> 1000
A47: 1 | B47: BANDEJA | C47: CHERRY | D47: 17500 | E47: =A47*D47 -> 17500 | I47: 13000 | J47: =I47*A47 -> 13000 | K47: =E47-J47 -> 4500
A48: 2 | B48: ATADO | C48: CIBOULETTE | D48: 3000 | E48: =A48*D48 -> 6000 | I48: 2000 | J48: =I48*A48 -> 4000 | K48: =E48-J48 -> 2000
A49: 2 | B49: CAJA | C49: LIMÓN | D49: 45000 | E49: =A49*D49 -> 90000 | I49: 40000 | J49: =I49*A49 -> 80000 | K49: =E49-J49 -> 10000
A50: 2 | B50: CAJÓN | C50: NARANJA | D50: 16000 | E50: =A50*D50 -> 32000 | I50: 13000 | J50: =I50*A50 -> 26000 | K50: =E50-J50 -> 6000
A51: 1 | B51: CAJÓN | C51: LECHUGA MORADA | D51: 12000 | E51: =A51*D51 -> 12000 | I51: 7000 | J51: =I51*A51 -> 7000 | K51: =E51-J51 -> 5000
A52: 1 | B52: CAJA | C52: PALTA | D52: 60000 | E52: =A52*D52 -> 60000 | I52: 50000 | J52: =I52*A52 -> 50000 | K52: =E52-J52 -> 10000
A53: 2 | B53: ATADO | C53: PEREJIL | D53: 4000 | E53: =A53*D53 -> 8000 | I53: 2000 | J53: =I53*A53 -> 4000 | K53: =E53-J53 -> 4000
A54: 1 | B54: CAJÓN | C54: TOMATE REDONDO | D54: 35000 | E54: =A54*D54 -> 35000 | I54: 30000 | J54: =I54*A54 -> 30000 | K54: =E54-J54 -> 5000
A55: 3 | B55: ATADO | C55: CEBOLLA DE VERDEO | D55: 4000 | E55: =A55*D55 -> 12000 | I55: 3000 | J55: =I55*A55 -> 9000 | K55: =E55-J55 -> 3000
A56: 6 | B56: UNIDAD | C56: MANGO | D56: 2500 | E56: =A56*D56 -> 15000 | I56: =15000/12 -> 1250 | J56: =I56*A56 -> 7500 | K56: =E56-J56 -> 7500
E58: =SUM(E46:E56) -> 290500 | K58: =SUM(K46:K56) -> 58000 | L58: =K58/E58 -> 0.19965577
A63: PÍO | D63: rto: 1 | E63: 46027
A65: CANTIDAD | B65: UNIDAD | C65: PRODUCTO | D65: PRECIO | E65: TOTAL | I65: PRECIO | J65: TOTAL | K65: DIFERENCIA
A66: 1 | B66: ATADO | C66: PEREJIL | D66: 4000 | E66: =A66*D66 -> 4000 | I66: 2000 | J66: =I66*A66 -> 2000 | K66: =E66-J66 -> 2000
A67: 2 | B67: CAJÓN | C67: LIMÓN | D67: 45000 | E67: =A67*D67 -> 90000 | I67: 40000 | J67: =I67*A67 -> 80000 | K67: =E67-J67 -> 10000
E69: =SUM(E66:E67) -> 94000 | K69: =SUM(K66:K67) -> 12000 | L69: =K69/E69 -> 0.12765957
A74: COMO SIEMPRE LAGUNA | D74: rto: 18 | E74: 46027
A76: CANTIDAD | B76: UNIDAD | C76: PRODUCTO | D76: PRECIO | E76: TOTAL | I76: PRECIO | J76: TOTAL | K76: DIFERENCIA
A77: 1 | B77: CAJÓN | C77: TOMATE CHERRY | D77: 32000 | E77: =A77*D77 -> 32000 | I77: 26000 | J77: =I77*A77 -> 26000 | K77: =E77-J77 -> 6000
A78: 1 | B78: CAJÓN | C78: LECHUGA FRANCESA | D78: 15000 | E78: =A78*D78 -> 15000 | I78: 13000 | J78: =I78*A78 -> 13000 | K78: =E78-J78 -> 2000
A79: 1 | B79: CAJÓN | C79: LECHUGA MORADA | D79: 12000 | E79: =A79*D79 -> 12000 | I79: 7000 | J79: =I79*A79 -> 7000 | K79: =E79-J79 -> 5000
A80: 1 | B80: CAJÓN | C80: RÚCULA | D80: 15000 | E80: =A80*D80 -> 15000 | I80: 12000 | J80: =I80*A80 -> 12000 | K80: =E80-J80 -> 3000
A81: 5 | B81: KG | C81: MORRÓN AMARILLO | D81: 3000 | E81: =A81*D81 -> 15000 | I81: =16000/8 -> 2000 | J81: =I81*A81 -> 10000 | K81: =E81-J81 -> 5000
A82: 5 | B82: KG | C82: MORRÓN ROJO | D82: 2800 | E82: =A82*D82 -> 14000 | I82: =15000/8 -> 1875 | J82: =I82*A82 -> 9375 | K82: =E82-J82 -> 4625
A83: 5 | B83: KG | C83: MORRÓN VERDE | D83: 2800 | E83: =A83*D83 -> 14000 | I83: =14000/8 -> 1750 | J83: =I83*A83 -> 8750 | K83: =E83-J83 -> 5250
A84: 2 | B84: KG | C84: BERENJENA | D84: 1800 | E84: =A84*D84 -> 3600 | I84: 1100 | J84: =I84*A84 -> 2200 | K84: =E84-J84 -> 1400
A85: 2 | B85: KG | C85: ZUCCINI | D85: 1200 | E85: =A85*D85 -> 2400 | I85: =8000/15 -> 533.33333 | J85: =I85*A85 -> 1066.6667 | K85: =E85-J85 -> 1333.3333
A86: 2 | B86: KG | C86: ZAPALLITO REDONDO | D86: 1200 | E86: =A86*D86 -> 2400 | I86: 0 | J86: =I86*A86 -> 0 | K86: =E86-J86 -> 2400
A87: 1 | B87: ATADO | C87: CILANTRO | D87: 3000 | E87: =A87*D87 -> 3000 | I87: 1500 | J87: =I87*A87 -> 1500 | K87: =E87-J87 -> 1500
A88: 1 | B88: KG | C88: CHAMPIÑONES | D88: 18000 | E88: =A88*D88 -> 18000 | I88: 15000 | J88: =I88*A88 -> 15000 | K88: =E88-J88 -> 3000
A89: 1 | B89: ATADO | C89: REMOLACHA | D89: 1800 | E89: =A89*D89 -> 1800 | I89: 1000 | J89: =I89*A89 -> 1000 | K89: =E89-J89 -> 800
A90: 1 | B90: ATADO | C90: CIBOULETTE | D90: 3000 | E90: =A90*D90 -> 3000 | I90: 2000 | J90: =I90*A90 -> 2000 | K90: =E90-J90 -> 1000
A91: 1 | B91: KG | C91: PEPINO | D91: 1800 | E91: =A91*D91 -> 1800 | I91: 0 | J91: =I91*A91 -> 0 | K91: =E91-J91 -> 1800
A92: 1 | B92: CAJÓN | C92: TOMATE PERITA | D92: 26000 | E92: =A92*D92 -> 26000 | I92: 20000 | J92: =I92*A92 -> 20000 | K92: =E92-J92 -> 6000
A93: 1 | B93: BOLSA | C93: CEBOLLA | D93: 14000 | E93: =A93*D93 -> 14000 | I93: 10000 | J93: =I93*A93 -> 10000 | K93: =E93-J93 -> 4000
A94: 4 | B94: CAJÓN | C94: ESPINACA | D94: 17000 | E94: =A94*D94 -> 68000 | I94: 14000 | J94: =I94*A94 -> 56000 | K94: =E94-J94 -> 12000
A95: 1 | B95: CAJÓN | C95: HUEVOS | D95: 55000 | E95: =A95*D95 -> 55000 | I95: 45000 | J95: =I95*A95 -> 45000 | K95: =E95-J95 -> 10000
A96: 1 | B96: BOLSA | C96: ZANAHORIA | D96: 14000 | E96: =A96*D96 -> 14000 | I96: 12000 | J96: =I96*A96 -> 12000 | K96: =E96-J96 -> 2000
A97: 2 | B97: UNIDAD | C97: AJO | D97: 1200 | E97: =A97*D97 -> 2400 | I97: 600 | J97: =I97*A97 -> 1200 | K97: =E97-J97 -> 1200
A98: 1 | B98: ATADO | C98: PEREJIL | D98: 4000 | E98: =A98*D98 -> 4000 | I98: 2000 | J98: =I98*A98 -> 2000 | K98: =E98-J98 -> 2000
A99: 3 | B99: UNIDAD | C99: MANGO | D99: 2500 | E99: =A99*D99 -> 7500 | I99: =15000/12 -> 1250 | J99: =I99*A99 -> 3750 | K99: =E99-J99 -> 3750
A100: 1 | B100: BOLSA | C100: PAPA | D100: 16000 | E100: =A100*D100 -> 16000 | I100: 13000 | J100: =I100*A100 -> 13000 | K100: =E100-J100 -> 3000
A101: 1 | B101: CAJÓN | C101: LIMÓN | D101: 48000 | E101: =A101*D101 -> 48000 | I101: 40000 | J101: =I101*A101 -> 40000 | K101: =E101-J101 -> 8000
A102: 1 | B102: CAJÓN | C102: NARANJA | D102: 16000 | E102: =A102*D102 -> 16000 | I102: 13000 | J102: =I102*A102 -> 13000 | K102: =E102-J102 -> 3000
E104: =SUM(E77:E102) -> 423900 | K104: =SUM(K77:K102) -> 99058.333 | L104: =K104/E104 -> 0.23368326
A108: AUPA | D108: rto: 1 | E108: 46027
A110: CANTIDAD | B110: UNIDAD | C110: PRODUCTO | D110: PRECIO | E110: TOTAL | I110: PRECIO | J110: TOTAL | K110: DIFERENCIA
A111: 2 | B111: CAJA | C111: BANANA | D111: 44000 | E111: =A111*D111 -> 88000 | I111: 37000 | J111: =I111*A111 -> 74000 | K111: =E111-J111 -> 14000
A112: 2 | B112: CAJA | C112: MANZANA | D112: 55000 | E112: =A112*D112 -> 110000 | I112: 48000 | J112: =I112*A112 -> 96000 | K112: =E112-J112 -> 14000
A113: 1 | B113: CAJON | C113: NARANJA | D113: 16000 | E113: =A113*D113 -> 16000 | I113: 13000 | J113: =I113*A113 -> 13000 | K113: =E113-J113 -> 3000
A114: 2 | B114: BOLSA | C114: ZANAHORIA | D114: 14000 | E114: =A114*D114 -> 28000 | I114: 12000 | J114: =I114*A114 -> 24000 | K114: =E114-J114 -> 4000
A115: 4 | B115: KG | C115: BERENJENA | D115: 1800 | E115: =A115*D115 -> 7200 | I115: 1100 | J115: =I115*A115 -> 4400 | K115: =E115-J115 -> 2800
A116: 1 | B116: UNIDAD | C116: REPOLLO | D116: 1800 | E116: =A116*D116 -> 1800 | I116: 1000 | J116: =I116*A116 -> 1000 | K116: =E116-J116 -> 800
A117: 3 | B117: ATADO | C117: ALBAHACA | D117: 1000 | E117: =A117*D117 -> 3000 | I117: 700 | J117: =I117*A117 -> 2100 | K117: =E117-J117 -> 900
A118: 18 | B118: MAPLE | C118: HUEVOS | D118: 5000 | E118: =A118*D118 -> 90000 | I118: =45000/12 -> 3750 | J118: =I118*A118 -> 67500 | K118: =E118-J118 -> 22500
A119: 1 | B119: BOLSA | C119: CEBOLLA | D119: 14000 | E119: =A119*D119 -> 14000 | I119: 10000 | J119: =I119*A119 -> 10000 | K119: =E119-J119 -> 4000
A120: 1 | B120: BOLSA | C120: ANCO | D120: 13000 | E120: =A120*D120 -> 13000 | I120: 9000 | J120: =I120*A120 -> 9000 | K120: =E120-J120 -> 4000
A121: 1.5 | B121: CAJÓN | C121: ZAPALLITO REDONDO | D121: 16000 | E121: =A121*D121 -> 24000 | I121: 10000 | J121: =I121*A121 -> 15000 | K121: =E121-J121 -> 9000
A122: 4 | B122: KG | C122: TOMATE REDONDO | D122: 2800 | E122: =A122*D122 -> 11200 | I122: =30000/15 -> 2000 | J122: =I122*A122 -> 8000 | K122: =E122-J122 -> 3200
A123: 6 | B123: ATADO | C123: ACELGA | D123: 1400 | E123: =A123*D123 -> 8400 | I123: 1000 | J123: =I123*A123 -> 6000 | K123: =E123-J123 -> 2400
A124: 1 | B124: UNIDAD | C124: APIO | D124: 1500 | E124: =A124*D124 -> 1500 | I124: 1000 | J124: =I124*A124 -> 1000 | K124: =E124-J124 -> 500
A125: 1 | B125: ATADO | C125: CEB VERDEO | D125: 4000 | E125: =A125*D125 -> 4000 | I125: 3000 | J125: =I125*A125 -> 3000 | K125: =E125-J125 -> 1000
A126: 3 | B126: UNIDAD | C126: AJO | D126: 1200 | E126: =A126*D126 -> 3600 | I126: 600 | J126: =I126*A126 -> 1800 | K126: =E126-J126 -> 1800
A127: 0.75 | B127: KG | C127: MORRÓN ROJO | D127: 2800 | E127: =A127*D127 -> 2100 | I127: 1875 | J127: =I127*A127 -> 1406.25 | K127: =E127-J127 -> 693.75
A128: 2 | B128: KG | C128: LECHUGA | D128: 4000 | E128: =A128*D128 -> 8000 | I128: 3000 | J128: =I128*A128 -> 6000 | K128: =E128-J128 -> 2000
E130: =SUM(E111:E128) -> 433800 | K130: =SUM(K111:K128) -> 90593.75 | L130: =K130/E130 -> 0.2088376
A134: LA PIADINA | D134: rto: 1 | E134: 46027
A136: CANTIDAD | B136: UNIDAD | C136: PRODUCTO | D136: PRECIO | E136: TOTAL | I136: PRECIO | J136: TOTAL | K136: DIFERENCIA
...

Sheet 06-01-2026 
A3: FV | E3: rto: 211 | F3: 46028 | I3: COMPRA
A5: CANTIDAD | B5: UNIDAD | C5: PRODUCTO | D5: PRECIO | E5: TOTAL | F5: TOTAL + IVA | I5: PRECIO | J5: TOTAL | K5: DIFERENCIA
A6: 5 | B6: ATADO | C6: ALBAHACA | D6: 1000 | E6: =A6*D6 -> 5000 | F6: =E6*1.105 -> 5525 | I6: =3500/6 -> 583.33333 | J6: =I6*A6 -> 2916.6667 | K6: =F6-J6 -> 2608.3333
A7: 10 | B7: ATADO | C7: ROMERO | D7: 3000 | E7: =A7*D7 -> 30000 | F7: =E7*1.105 -> 33150 | I7: 1000 | J7: =I7*A7 -> 10000 | K7: =F7-J7 -> 23150
A8: 10 | B8: ATADO | C8: TOMILLO | D8: 3000 | E8: =A8*D8 -> 30000 | F8: =E8*1.105 -> 33150 | I8: 2000 | J8: =I8*A8 -> 20000 | K8: =F8-J8 -> 13150
A9: 2 | B9: CAJA | C9: MANZANA VERDE | D9: 77000 | E9: =A9*D9 -> 154000 | F9: =E9*1.105 -> 170170 | I9: 38000 | J9: =I9*A9 -> 76000 | K9: =F9-J9 -> 94170
A10: 1 | B10: CAJON | C10: CIRUELAS | D10: 45000 | E10: =A10*D10 -> 45000 | F10: =E10*1.105 -> 49725 | I10: 38000 | J10: =I10*A10 -> 38000 | K10: =F10-J10 -> 11725
A11: 1 | B11: CAJON | C11: NARANJA | D11: 23000 | E11: =A11*D11 -> 23000 | F11: =E11*1.105 -> 25415 | I11: 18000 | J11: =I11*A11 -> 18000 | K11: =F11-J11 -> 7415
A12: 2 | B12: CAJA | C12: BANANA | D12: 46000 | E12: =A12*D12 -> 92000 | F12: =E12*1.105 -> 101660 | I12: 36000 | J12: =I12*A12 -> 72000 | K12: =F12-J12 -> 29660
A13: 1 | B13: CAJON | C13: TOMATE REDONDO | D13: 32000 | E13: =A13*D13 -> 32000 | F13: =E13*1.105 -> 35360 | I13: 28000 | J13: =I13*A13 -> 28000 | K13: =F13-J13 -> 7360
A14: 1 | B14: CAJA | C14: MANZANA VERDE | D14: 77000 | E14: =A14*D14 -> 77000 | F14: =E14*1.105 -> 85085 | G14: BOLSA | I14: 0 | J14: =I14*A14 -> 0 | K14: =F14-J14 -> 85085
A15: 1 | B15: CAJA | C15: BANANA | D15: 46000 | E15: =A15*D15 -> 46000 | F15: =E15*1.105 -> 50830 | G15: BOLSA | I15: 0 | J15: =I15*A15 -> 0 | K15: =F15-J15 -> 50830
A16: 1 | B16: CAJON | C16: TOMATE REDONDO | D16: 32000 | E16: =A16*D16 -> 32000 | F16: =E16*1.105 -> 35360 | G16: BOLSA PROPIA | I16: 0 | J16: =I16*A16 -> 0 | K16: =F16-J16 -> 35360
E18: =SUM(E6:E16) -> 566000 | F18: =SUM(F6:F16) -> 625430 | K18: =SUM(K6:K16) -> 360513.33 | L18: =K18/F18 -> 0.57642475
A22: RAKUS CAFE - PADUA | D22: rto: 12 | E22: 46028
A24: CANTIDAD | B24: UNIDAD | C24: PRODUCTO | D24: PRECIO | E24: TOTAL | I24: PRECIO | J24: TOTAL | K24: DIFERENCIA
A25: 1 | B25: KG | C25: REMOLACHA | D25: 1800 | E25: =A25*D25 -> 1800 | I25: 1000 | J25: =I25*A25 -> 1000 | K25: =E25-J25 -> 800
A26: 1 | B26: CAJON | C26: HUEVO N1 | D26: 54000 | E26: =A26*D26 -> 54000 | I26: 45000 | J26: =I26*A26 -> 45000 | K26: =E26-J26 -> 9000
A27: 1 | B27: UNIDAD | C27: REPOLLO BLANCO | D27: 2000 | E27: =A27*D27 -> 2000 | I27: 1000 | J27: =I27*A27 -> 1000 | K27: =E27-J27 -> 1000
A28: 10 | B28: UNIDAD | C28: PALTA | D28: 1400 | E28: =A28*D28 -> 14000 | I28: 781 | J28: =I28*A28 -> 7810 | K28: =E28-J28 -> 6190
A29: 1 | B29: ATADO | C29: MENTA | D29: 3000 | E29: =A29*D29 -> 3000 | I29: 2000 | J29: =I29*A29 -> 2000 | K29: =E29-J29 -> 1000
A30: 0.5 | B30: KG | C30: JENGIBRE | D30: 5000 | E30: =A30*D30 -> 2500 | I30: 4000 | J30: =I30*A30 -> 2000 | K30: =E30-J30 -> 500
A31: 1 | B31: KG | C31: LIMA | D31: 4000 | E31: =A31*D31 -> 4000 | I31: 3000 | J31: =I31*A31 -> 3000 | K31: =E31-J31 -> 1000
A32: 1 | B32: CAJON | C32: NARANJA | D32: 20000 | E32: =A32*D32 -> 20000 | I32: 18000 | J32: =I32*A32 -> 18000 | K32: =E32-J32 -> 2000
A33: 1 | B33: BOLSA | C33: PAPA | D33: 16000 | E33: =A33*D33 -> 16000 | I33: 13000 | J33: =I33*A33 -> 13000 | K33: =E33-J33 -> 3000
A34: 1 | B34: ATADO | C34: PEREJIL | D34: 3500 | E34: =A34*D34 -> 3500 | I34: 2000 | J34: =I34*A34 -> 2000 | K34: =E34-J34 -> 1500
A35: 1 | B35: KG | C35: LEC CRIOLLA | D35: 3500 | E35: =A35*D35 -> 3500 | I35: 3000 | J35: =I35*A35 -> 3000 | K35: =E35-J35 -> 500
A36: 6 | B36: ATADOS | C36: RUCULA | D36: 800 | E36: =A36*D36 -> 4800 | I36: =5000/12 -> 416.66667 | J36: =I36*A36 -> 2500 | K36: =E36-J36 -> 2300
A37: 1 | B37: ATADO | C37: CEB VERDEO | D37: 4000 | E37: =A37*D37 -> 4000 | I37: 3000 | J37: =I37*A37 -> 3000 | K37: =E37-J37 -> 1000
A38: 4 | B38: CUBETAS | C38: ARANDANOS | D38: 2000 | E38: =A38*D38 -> 8000 | I38: 1333 | J38: =I38*A38 -> 5332 | K38: =E38-J38 -> 2668
A39: 3 | B39: ATADOS | C39: ALBAHACA | D39: 1000 | E39: =A39*D39 -> 3000 | I39: =3500/6 -> 583.33333 | J39: =I39*A39 -> 1750 | K39: =E39-J39 -> 1250
E41: =SUM(E25:E39) -> 144100 | K41: =SUM(K25:K39) -> 33708 | L41: =K41/E41 -> 0.23392089
A47: TOTAL DIA | B47: =E41+F18 -> 769530
A49: GANANCIA | B49: =K41+K18 -> 394221.33
A51: % | B51: =B49/B47 -> 0.51228845
A53: BULTOS COMPRADOS | C53: 18
B58: EFECTIVO | C58: MERCADO PAGO | D58: BANCO GALCIA | E58: BANCO RIO | F58: CHEQUES
B59: ='05-01-2026 '!B260 -> 2778150 | C59: ='05-01-2026 '!C260 -> 236114.49 | D59: ='05-01-2026 '!D260 -> 1401865.7 | F59: ='05-01-2026 '!F260 -> 8500000
A61: INGRESOS
A62: COBR. CTA. CTE | B62: 0 | C62: 0 | D62: 0 | E62: 0 | F62: 0
A63: RENDIMIENTO MP | B63: 0 | C63: 0.06 | D63: 0 | E63: 0 | F63: 0
A64: CHE ACREDITADO | B64: 0 | C64: 0 | D64: 0 | E64: 0 | F64: 0
A65: COBR. VACIOS | B65: 0 | C65: 0 | D65: 0 | E65: 0 | F65: 0
A66: PRESTAMOS | B66: 0 | C66: 0 | D66: 0 | E66: 0 | F66: 0
A67: IMP. CRED. 0,6% | B67: 0 | C67: =C62*0.6%+C65*0.6% -> 0 | D67: =SUM(D62:D64)*0.6% -> 0 | E67: 0 | F67: 0
A69: TOTAL | B69: =SUM(B59:B67) -> 2778150 | C69: =C59+C62+C65+C66-C67+C63 -> 236114.55 | D69: =D59+D62+D65+D66-D67+D64 -> 1401865.7 | E69: =E59+E62+E65+E66-E67 -> 0 | F69: =F59+F62+F65+F66-F67-D64 -> 8500000
A71: GASTOS
A72: ING. MERCADO | B72: 1000 | C72: 0 | D72: 0 | E72: 0
A73: CARGA / VACIOS | B73: 0 | C73: 0 | D73: 0 | E73: 0
A74: CHEQ DEBITADO | B74: 0 | C74: 0 | D74: 400000 | E74: 0
A75: PEAJE | B75: 16400 | C75: 0 | D75: 0 | E75: 0
A76: MERCADERIA | B76: =100000+33000+13000+7000 -> 153000 | C76: 127000 | D76: 0 | E76: 0
A77: COMBUSTIBLE | B77: 0 | C77: 0 | D77: 0 | E77: 0
A78: SUELDOS | B78: 0 | C78: 0 | D78: 0 | E78: 0
A79: DEV. PRESTAMOS | B79: 0 | C79: 0 | D79: 0 | E79: 0
A80: AGUA | B80: 0 | C80: 0 | D80: 0 | E80: 0
A81: FLETE JUAN | B81: 0 | C81: 0 | D81: 0 | E81: 0
A82: RETIRO JOAQUIN | B82: 0 | C82: 0 | D82: 0 | E82: 0
A83: RETIRO FEDERICO | B83: 0 | C83: 0 | D83: 0 | E83: 0
A84: ALQUILER LOCAL | B84: 0 | C84: 0 | D84: 0 | E84: 0
A85: CONTADOR | B85: 0 | C85: 0 | D85: 0 | E85: 0
A86: ACEITE/AGUA CHATA | B86: 0 | C86: 0 | D86: 0 | E86: 0
A87: REMIS | B87: 0 | C87: 0 | D87: 0 | E87: 0
A88: MECANICO | B88: 0 | C88: 0 | D88: 0 | E88: 0
... A91: MONOTRIB. LEO | B91: 0 | C91: 0 | D91: 0 | E91: 0
A92: IIBB CHEQUE | B92: 0 | C92: 0 | D92: =SUM(D62:D64)*2% -> 0 | E92: 0
A93: IIBB | B93: 0 | C93: 0 | D93: 0 | E93: 0
A94: IVA | B94: 0 | C94: 0 | D94: 0 | E94: 0
A95: GANANCIAS | B95: 0 | C95: 0 | D95: 0 | E95: 0
A96: MANT. CTA. | B96: 0 | C96: 0 | D96: 0 | E96: 0
A98: IMP. DEB. 0,6% | B98: 0 | C98: =SUM(C72:C95)*0.6% -> 762 | D98: =SUM(D72:D96)*0.6% -> 2400 | E98: =(E76*0.6%)+(E77*0.6%)+(E78*0.6%)+(E81*0.6%)+(E82*0.6%) -> 0
A99: PASE DE CUENTAS | B99: 0 | C99: 75000 | D99: 75000 | E99: =SUM(E73:E97)*0.6%+(E100*0.6%) -> 0
A101: TOTAL SALIDAS | B101: =SUM(B72:B100) -> 170400 | C101: =SUM(C72:C98) -> 127762 | D101: =SUM(D72:D98) -> 402400 | E101: =E83+E87+E98-E99 -> 0 | F101: =F76
A103: SALDOS | B103: =B69-B101 -> 2607750 | C103: =C69-C101-C99 -> 33352.55 | D103: =D69-D101+D99 -> 1074465.7 | E103: =E69-E101 -> 0 | F103: =F69-F101 -> 8500000
A105: fede | B105: =249800-153000-1000-B75 -> 79400
A106: joaquin | B106: 2528350
B108: =SUM(B105:B106) -> 2607750

Sheet 07-01-2026 
A3: FV | E3: rto: 212 | F3: 46029 | I3: COMPRA
A5: CANTIDAD | B5: UNIDAD | C5: PRODUCTO | D5: PRECIO | E5: TOTAL | F5: TOTAL + IVA | I5: PRECIO | J5: TOTAL | K5: DIFERENCIA
A6: 0.5 | B6: CAJON | C6: HUEVO | D6: 52000 | E6: =A6*D6 -> 26000 | F6: =E6*1.21 -> 31460 | I6: 40000 | J6: =I6*A6 -> 20000 | K6: =F6-J6 -> 11460
A7: 3 | B7: CAJON | C7: CIRUELA | D7: 45000 | E7: =A7*D7 -> 135000 | F7: =E7*1.105 -> 149175 | I7: 39000 | J7: =I7*A7 -> 117000 | K7: =F7-J7 -> 32175
A8: 2 | B8: CAJA | C8: BANANA | D8: 46000 | E8: =A8*D8 -> 92000 | F8: =E8*1.105 -> 101660 | I8: 36000 | J8: =I8*A8 -> 72000 | K8: =F8-J8 -> 29660
A9: 3 | B9: CAJON | C9: NARANJA | D9: 23000 | E9: =A9*D9 -> 69000 | F9: =E9*1.105 -> 76245 | I9: 18000 | J9: =I9*A9 -> 54000 | K9: =F9-J9 -> 22245
A10: 3 | B10: CAJA | C10: MANZANA VERDE | D10: 77000 | E10: =A10*D10 -> 231000 | F10: =E10*1.105 -> 255255 | I10: 38000 | J10: =I10*A10 -> 114000 | K10: =F10-J10 -> 141255
A11: 4 | B11: CAJON | C11: DURAZNO | D11: 42000 | E11: =A11*D11 -> 168000 | F11: =E11*1.105 -> 185640 | I11: 30000 | J11: =I11*A11 -> 120000 | K11: =F11-J11 -> 65640
A12: 2 | B12: CAJA | C12: MELON | D12: 30000 | E12: =A12*D12 -> 60000 | F12: =E12*1.105 -> 66300 | I12: 22000 | J12: =I12*A12 -> 44000 | K12: =F12-J12 -> 22300
A13: 20 | B13: KG | C13: SANDIA | D13: 1500 | E13: =A13*D13 -> 30000 | F13: =E13*1.105 -> 33150 | I13: 600 | J13: =I13*A13 -> 12000 | K13: =F13-J13 -> 21150
A14: 3 | B14: CAJON | C14: TOMATE REDONDO | D14: 32000 | E14: =A14*D14 -> 96000 | F14: =E14*1.105 -> 106080 | I14: 20000 | J14: =I14*A14 -> 60000 | K14: =F14-J14 -> 46080
A15: 3 | B15: CAJON | C15: TOMATE CHEERY | D15: 35000 | E15: =A15*D15 -> 105000 | F15: =E15*1.105 -> 116025 | I15: 18000 | J15: =I15*A15 -> 54000 | K15: =F15-J15 -> 62025
A16: 1 | B16: CAJON | C16: NARANJA | D16: 23000 | E16: =A16*D16 -> 23000 | F16: =E16*1.105 -> 25415 | G16: BOLSA | J16: =I16*A16 -> 0 | K16: =F16-J16 -> 25415
A17: 1 | B17: CAJA | C17: BANANA | D17: 46000 | E17: =A17*D17 -> 46000 | F17: =E17*1.105 -> 50830 | G17: BOLSA | J17: =I17*A17 -> 0 | K17: =F17-J17 -> 50830
A18: 1 | B18: CAJA | C18: MANZANA VERDE | D18: 77000 | E18: =A18*D18 -> 77000 | F18: =E18*1.105 -> 85085 | G18: BOLSA | J18: =I18*A18 -> 0 | K18: =F18-J18 -> 85085
A19: 1 | B19: CAJON | C19: CIRUELA | D19: 45000 | E19: =A19*D19 -> 45000 | F19: =E19*1.105 -> 49725 | G19: BOLSA | J19: =I19*A19 -> 0 | K19: =F19-J19 -> 49725
A20: 1 | B20: CAJON | C20: TOMATE CHERRY | D20: 35000 | E20: =A20*D20 -> 35000 | F20: =E20*1.105 -> 38675 | G20: BOLSA | J20: =I20*A20 -> 0 | K20: =F20-J20 -> 38675
A21: 1 | B21: CAJA | C21: MELON | D21: 30000 | E21: =A21*D21 -> 30000 | F21: =E21*1.105 -> 33150 | G21: BOLSA | J21: =I21*A21 -> 0 | K21: =F21-J21 -> 33150
A22: 0.5 | B22: CAJON | C22: HUEVO | D22: 52000 | E22: =A22*D22 -> 26000 | F22: =E22*1.21 -> 31460 | G22: BOLSA | J22: =I22*A22 -> 0 | K22: =F22-J22 -> 31460
A23: 1 | B23: CAJON | C23: TOMATE REDONDO | D23: 32000 | E23: =A23*D23 -> 32000 | F23: =E23*1.105 -> 35360 | G23: BOLSA PROPIA | J23: =I23*A23 -> 0 | K23: =F23-J23 -> 35360
E25: =SUM(E6:E23) -> 1326000 | F25: =SUM(F6:F23) -> 1470690 | K25: =SUM(K6:K23) -> 803690 | L25: =K25/F25 -> 0.54647138
A29: HOGAR | D29: rto: 1 | E29: 46029
A31: CANTIDAD | B31: UNIDAD | C31: PRODUCTO | D31: PRECIO | E31: TOTAL | I31: PRECIO | J31: TOTAL | K31: DIFERENCIA
A32: 4 | B32: ATADOS | C32: ACELGA | D32: 1200 | E32: =A32*D32 -> 4800 | I32: 1000 | J32: =I32*A32 -> 4000 | K32: =E32-J32 -> 800
A33: 1 | B33: UNIDAD | C33: APIO | D33: 2000 | E33: =A33*D33 -> 2000 | I33: 1000 | J33: =I33*A33 -> 1000 | K33: =E33-J33 -> 1000
A34: 4 | B34: UNIDAD | C34: AJO | D34: 1200 | E34: =A34*D34 -> 4800 | I34: =28000/50 -> 560 | J34: =I34*A34 -> 2240 | K34: =E34-J34 -> 2560
A35: 4 | B35: KG | C35: BATATA | D35: 1500 | E35: =A35*D35 -> 6000 | I35: =11000/10 -> 1100 | J35: =I35*A35 -> 4400 | K35: =E35-J35 -> 1600
A36: 4 | B36: KG | C36: BONIATO | D36: 4000 | E36: =A36*D36 -> 16000 | I36: =35000/11 -> 3181.8182 | J36: =I36*A36 -> 12727.273 | K36: =E36-J36 -> 3272.7273
A37: 2 | B37: KG | C37: BERENJENA | D37: 1800 | E37: =A37*D37 -> 3600 | I37: =11000/9 -> 1222.2222 | J37: =I37*A37 -> 2444.4444 | K37: =E37-J37 -> 1155.5556
A38: 4 | B38: UNIDAD | C38: BROCOLI | D38: 2200 | E38: =A38*D38 -> 8800 | I38: 2000 | J38: =I38*A38 -> 8000 | K38: =E38-J38 -> 800
A39: 2 | B39: KG | C39: CHAUCHA | D39: 5000 | E39: =A39*D39 -> 10000 | I39: 3000 | J39: =I39*A39 -> 6000 | K39: =E39-J39 -> 4000
A40: 3 | B40: KG | C40: TOMATE CHERRY | D40: 3000 | E40: =A40*D40 -> 9000 | I40: 0 | J40: =I40*A40 -> 0 | K40: =E40-J40 -> 9000
A41: 4 | B41: ATADO | C41: ESPINACA | D41: 1500 | E41: =A41*D41 -> 6000 | I41: =6000/4 -> 1500 | J41: =I41*A41 -> 6000 | K41: =E41-J41 -> 0
A42: 2 | B42: KG | C42: MORRÓN ROJO | D42: 3500 | E42: =A42*D42 -> 7000 | I42: =15000/8 -> 1875 | J42: =I42*A42 -> 3750 | K42: =E42-J42 -> 3250
A43: 1 | B43: KG | C43: LECHUGA | D43: 3500 | E43: =A43*D43 -> 3500 | I43: =14000/5 -> 2800 | J43: =I43*A43 -> 2800 | K43: =E43-J43 -> 700
A44: 2 | B44: UNIDAD | C44: PALTA | D44: 1400 | E44: =A44*D44 -> 2800 | I44: =60000/70 -> 857.14286 | J44: =I44*A44 -> 1714.2857 | K44: =E44-J44 -> 1085.7143
A45: 6 | B45: ATADOS | C45: REMOLACHA | D45: 1700 | E45: =A45*D45 -> 10200 | I45: 1000 | J45: =I45*A45 -> 6000 | K45: =E45-J45 -> 4200
A46: 1 | B46: UNIDAD | C46: REPOLLO | D46: 2000 | E46: =A46*D46 -> 2000 | I46: 1000 | J46: =I46*A46 -> 1000 | K46: =E46-J46 -> 1000
A47: 4 | B47: ATADO | C47: RÚCULA | D47: 600 | E47: =A47*D47 -> 2400 | I47: =5000/12 -> 416.66667 | J47: =I47*A47 -> 1666.6667 | K47: =E47-J47 -> 733.33333
A48: 4 | B48: KG | C48: TOMATE | D48: 2400 | E48: =A48*D48 -> 9600 | I48: =20000/15 -> 1333.3333 | J48: =I48*A48 -> 5333.3333 | K48: =E48-J48 -> 4266.6667
A49: 4 | B49: KG | C49: ZAPALLITO | D49: 1400 | E49: =A49*D49 -> 5600 | I49: 0 | J49: =I49*A49 -> 0 | K49: =E49-J49 -> 5600
A50: 2 | B50: KG | C50: ZUCCINI | D50: 2000 | E50: =A50*D50 -> 4000 | I50: 1300 | J50: =I50*A50 -> 2600 | K50: =E50-J50 -> 1400
A51: 1 | B51: BOLSA | C51: ANCO | D51: 14000 | E51: =A51*D51 -> 14000 | I51: 9000 | J51: =I51*A51 -> 9000 | K51: =E51-J51 -> 5000
A52: 0.5 | B52: BOLSA | C52: CEBOLLA | D52: 14000 | E52: =A52*D52 -> 7000 | I52: 10000 | J52: =I52*A52 -> 5000 | K52: =E52-J52 -> 2000
A53: 1 | B53: BOLSA | C53: PAPA | D53: 15000 | E53: =A53*D53 -> 15000 | I53: 12000 | J53: =I53*A53 -> 12000 | K53: =E53-J53 -> 3000
A54: 1 | B54: BOLSA | C54: ZANAHORIA | D54: 13000 | E54: =A54*D54 -> 13000 | I54: 11000 | J54: =I54*A54 -> 11000 | K54: =E54-J54 -> 2000
A55: 1 | B55: CAJA | C55: BANANA | D55: 42000 | E55: =A55*D55 -> 42000 | I55: 36000 | J55: =I55*A55 -> 36000 | K55: =E55-J55 -> 6000
A56: 3 | B56: KG | C56: DURAZNO | D56: 4000 | E56: =A56*D56 -> 12000 | I56: 0 | J56: =I56*A56 -> 0 | K56: =E56-J56 -> 12000
A57: 1 | B57: KG | C57: FRUTILLA | D57: 9000 | E57: =A57*D57 -> 9000 | I57: 9000 | J57: =I57*A57 -> 9000 | K57: =E57-J57 -> 0
A58: 0.5 | B58: KG | C58: KIWI | D58: 11000 | E58: =A58*D58 -> 5500 | I58: =70000/8 -> 8750 | J58: =I58*A58 -> 4375 | K58: =E58-J58 -> 1125
A59: 4 | B59: KG | C59: LIMÓN | D59: 3500 | E59: =A59*D59 -> 14000 | I59: =35000/15 -> 2333.3333 | J59: =I59*A59 -> 9333.3333 | K59: =E59-J59 -> 4666.6667
A60: 0.5 | B60: CAJA | C60: MANZANA ROJA | D60: 62000 | E60: =A60*D60 -> 31000 | I60: 55000 | J60: =I60*A60 -> 27500 | K60: =E60-J60 -> 3500
A61: 3 | B61: KG | C61: MANZANA VERDE | D61: 3200 | E61: =A61*D61 -> 9600 | I61: =21000/9 -> 2333.3333 | J61: =I61*A61 -> 7000 | K61: =E61-J61 -> 2600
A62: 6 | B62: KG | C62: NARANJA | D62: 1600 | E62: =A62*D62 -> 9600 | I62: =18000/15 -> 1200 | J62: =I62*A62 -> 7200 | K62: =E62-J62 -> 2400
A63: 2 | B63: UNIDAD | C63: MELON | D63: 5000 | E63: =A63*D63 -> 10000 | I63: 0 | J63: =I63*A63 -> 0 | K63: =E63-J63 -> 10000
A64: 12 | B64: KG | C64: SANDÍA | D64: 1200 | E64: =A64*D64 -> 14400 | I64: 600 | J64: =I64*A64 -> 7200 | K64: =E64-J64 -> 7200
E66: =SUM(E33:E64) -> 319400 | K66: =SUM(K33:K64) -> 107115.66 | L66: =K66/E66 -> 0.33536526
A69: LA PIADINA | D69: rto: 2 | E69: 46027
A71: CANTIDAD | B71: UNIDAD | C71: PRODUCTO | D71: PRECIO | E71: TOTAL | I71: PRECIO | J71: TOTAL | K71: DIFERENCIA
A72: 1 | B72: ATADO | C72: APIO | D72: 2000 | E72: =A72*D72 -> 2000 | I72: 1000 | J72: =I72*A72 -> 1000 | K72: =E72-J72 -> 1000
A73: 0.5 | B73: CAJON | C73: RUCULA | D73: 15000 | E73: =A73*D73 -> 7500 | I73: 10000 | J73: =I73*A73 -> 5000 | K73: =E73-J73 -> 2500
A74: 1 | B74: KG | C74: MORRON ROJO | D74: 4000 | E74: =A74*D74 -> 4000 | I74: 4000 | J74: =I74*A74 -> 4000 | K74: =E74-J74 -> 0
A75: 1 | B75: KG | C75: ZANAHORIA | D75: 1800 | E75: =A75*D75 -> 1800 | I75: 1400 | J75: =I75*A75 -> 1400 | K75: =E75-J75 -> 400
A76: 1 | B76: KG | C76: LEC FRANCESA | D76: 3500 | E76: =A76*D76 -> 3500 | I76: 3000 | J76: =I76*A76 -> 3000 | K76: =E76-J76 -> 500
E78: =SUM(E72:E76) -> 18800 | K78: =SUM(K72:K76) -> 4400 | L78: =K78/E78 -> 0.23404255
A82: TOTAL DIA | B82: =F25+E66+E78 -> 1808890
A84: GANANCIA | B84: =K78+K66+K25 -> 915205.66
A86: % | B86: =B84/B82 -> 0.50594877
A88: BULTOS COMPRADOS | C88: 32
B93: EFECTIVO | C93: MERCADO PAGO | D93: BANCO GALCIA | E93: BANCO RIO | F93: CHEQUES
B94: ='06-01-2026 '!B103 -> 2607750 | C94: ='06-01-2026 '!C103 -> 33352.55 | D94: ='06-01-2026 '!D103 -> 1074465.7 | F94: ='06-01-2026 '!F103 -> 8500000
A96: INGRESOS
A97: COBR. CTA. CTE | B97: 18800 | C97: 0 | D97: 0 | E97: 0 | F97: 0
A98: RENDIMIENTO MP | B98: 0 | C98: 23.21 | D98: 0 | E98: 0 | F98: 0
A99: CHE ACREDITADO | B99: 0 | C99: 0 | D99: 0 | E99: 0 | F99: 0
A100: COBR. VACIOS | B100: 0 | C100: 0 | D100: 0 | E100: 0 | F100: 0
A101: PRESTAMOS | B101: 0 | C101: 0 | D101: 0 | E101: 0 | F101: 0
A102: IMP. CRED. 0,6% | B102: 0 | C102: =C97*0.6%+C100*0.6% -> 0 | D102: =SUM(D97:D99)*0.6% -> 0 | E102: 0 | F102: 0
A104: TOTAL | B104: =SUM(B94:B102) -> 2626550 | C104: =C94+C97+C100+C101-C102+C98 -> 33375.76 | D104: =D94+D97+D100+D101-D102+D99 -> 1074465.7 | E104: =E94+E97+E100+E101-E102 -> 0 | F104: =F94+F97+F100+F101-F102-D99 -> 8500000
A106: GASTOS
A107: ING. MERCADO | B107: 1000 | C107: 0 | D107: 0 | E107: 0
A108: CARGA / VACIOS | B108: 0 | C108: 0 | D108: 0 | E108: 0
A109: CHEQ DEBITADO | B109: 0 | C109: 0 | D109: 0 | E109: 0
A110: PEAJE | B110: 5800 | C110: 0 | D110: 0 | E110: 0
A111: MERCADERIA | B111: 0 | C111: 615360 | D111: 0 | E111: 0
A112: COMBUSTIBLE | B112: 0 | C112: 40000 | D112: 0 | E112: 0
A113: SUELDOS | B113: 0 | C113: 0 | D113: 0 | E113: 0
A114: DEV. PRESTAMOS | B114: 0 | C114: 0 | D114: 0 | E114: 0
A115: AGUA | B115: 0 | C115: 0 | D115: 0 | E115: 0
A116: FLETE JUAN | B116: 0 | C116: 0 | D116: 0 | E116: 0
A117: RETIRO JOAQUIN | B117: 0 | C117: 0 | D117: 0 | E117: 0
A118: RETIRO FEDERICO | B118: 0 | C118: 0 | D118: 0 | E118: 0
... A126: MONOTRIB. LEO | B126: 0 | C126: 0 | D126: 0 | E126: 0
A127: IIBB CHEQUE | B127: 0 | C127: 0 | D127: =SUM(D97:D99)*2% -> 0 | E127: 0
A128: IIBB | B128: 0 | C128: 0 | D128: 0 | E128: 0
A129: IVA | B129: 0 | C129: 0 | D129: 0 | E129: 0
A130: GANANCIAS | B130: 0 | C130: 0 | D130: 0 | E130: 0
A131: MANT. CTA. | B131: 0 | C131: 0 | D131: 0 | E131: 0
A133: IMP. DEB. 0,6% | B133: 0 | C133: =SUM(C107:C130)*0.6% -> 3932.16 | D133: =SUM(D107:D130)*0.6%+(D134*0.6%) -> 3780 | E133: =(E111*0.6%)+(E112*0.6%)+(E113*0.6%)+(E116*0.6%)+(E117*0.6%) -> 0
A134: PASE DE CUENTAS | B134: 0 | C134: 630000 | D134: 630000 | E134: =SUM(E108:E132)*0.6%+(E135*0.6%) -> 0
...

Sheet 08-01-2026 
A3: FV | E3: rto: 213 | F3: 46030 | I3: COMPRA
A5: CANTIDAD | B5: UNIDAD | C5: PRODUCTO | D5: PRECIO | E5: TOTAL | F5: TOTAL + IVA | I5: PRECIO | J5: TOTAL | K5: DIFERENCIA
A6: 1 | B6: CAJON | C6: HUEVO | D6: 52000 | E6: =A6*D6 -> 52000 | F6: =E6*1.21 -> 62920 | I6: 45000 | J6: =I6*A6 -> 45000 | K6: =F6-J6 -> 17920
A7: 3 | B7: CAJA | C7: DURAZNO | D7: 42000 | E7: =A7*D7 -> 126000 | F7: =E7*1.105 -> 139230 | I7: 33000 | J7: =I7*A7 -> 99000 | K7: =F7-J7 -> 40230
A8: 3 | B8: CAJA | C8: BANANA | D8: 46000 | E8: =A8*D8 -> 138000 | F8: =E8*1.105 -> 152490 | I8: 36000 | J8: =I8*A8 -> 108000 | K8: =F8-J8 -> 44490
A9: 36 | B9: KG | C9: SANDIA | D9: 1500 | E9: =A9*D9 -> 54000 | F9: =E9*1.105 -> 59670 | I9: 600 | J9: =I9*A9 -> 21600 | K9: =F9-J9 -> 38070
A10: 3 | B10: CAJON | C10: MELON | D10: 30000 | E10: =A10*D10 -> 90000 | F10: =E10*1.105 -> 99450 | I10: 22000 | J10: =I10*A10 -> 66000 | K10: =F10-J10 -> 33450
A11: 3 | B11: CAJON | C11: NARANJA | D11: 23000 | E11: =A11*D11 -> 69000 | F11: =E11*1.105 -> 76245 | I11: 18000 | J11: =I11*A11 -> 54000 | K11: =F11-J11 -> 22245
A12: 2 | B12: CAJA | C12: UVA SUPERIOR NACIONAL | D12: 37000 | E12: =A12*D12 -> 74000 | F12: =E12*1.105 -> 81770 | I12: 27000 | J12: =I12*A12 -> 54000 | K12: =F12-J12 -> 27770
A13: 0.5 | B13: CAJON | C13: HUEVO | D13: 52000 | E13: =A13*D13 -> 26000 | F13: =E13*1.21 -> 31460 | G13: BOLSA | I13: 0 | J13: =I13*A13 -> 0 | K13: =F13-J13 -> 31460
A14: 1 | B14: CAJA | C14: BANANA | D14: 46000 | E14: =A14*D14 -> 46000 | F14: =E14*1.105 -> 50830 | G14: BOLSA | I14: 0 | J14: =I14*A14 -> 0 | K14: =F14-J14 -> 50830
A15: 1 | B15: CAJA | C15: UVA SUPERIOR NACIONAL | D15: 37000 | E15: =A15*D15 -> 37000 | F15: =E15*1.105 -> 40885 | G15: BOLSA | I15: 0 | J15: =I15*A15 -> 0 | K15: =F15-J15 -> 40885
A16: 1 | B16: CAJA | C16: DURAZNO | D16: 42000 | E16: =A16*D16 -> 42000 | F16: =E16*1.105 -> 46410 | G16: BOLSA | I16: 0 | J16: =I16*A16 -> 0 | K16: =F16-J16 -> 46410
E18: =SUM(E6:E16) -> 754000 | F18: =SUM(F6:F16) -> 841360 | K18: =SUM(K6:K17) -> 393760 | L18: =K18/F18 -> 0.46800418
A22: LA PIADINA | D22: rto: 3 | E22: 46030
A24: CANTIDAD | B24: UNIDAD | C24: PRODUCTO | D24: PRECIO | E24: TOTAL | I24: PRECIO | J24: TOTAL | K24: DIFERENCIA
A25: 1 | B25: KG | C25: UVA VERDE | D25: 4500 | E25: =A25*D25 -> 4500 | I25: 0 | J25: =I25*A25 -> 0 | K25: =E25-J25 -> 4500
A26: 2 | B26: KG | C26: BANANA | D26: 3000 | E26: =A26*D26 -> 6000 | I26: 0 | J26: =I26*A26 -> 0 | K26: =E26-J26 -> 6000
A27: 1.03 | B27: KG | C27: MANZANA | D27: 5000 | E27: =A27*D27 -> 5150 | I27: 5000 | J27: =I27*A27 -> 5150 | K27: =E27-J27 -> 0
A28: 1 | B28: KG | C28: FRUTILLA | D28: 9000 | E28: =A28*D28 -> 9000 | I28: 9000 | J28: =I28*A28 -> 9000 | K28: =E28-J28 -> 0
A29: 0.7 | B29: KG | C29: DURAZNO | D29: 4000 | E29: =A29*D29 -> 2800 | I29: 0 | J29: =I29*A29 -> 0 | K29: =E29-J29 -> 2800
A30: 1 | B30: KG | C30: NARANJA | D30: 1500 | E30: =A30*D30 -> 1500 | I30: 0 | J30: =I30*A30 -> 0 | K30: =E30-J30 -> 1500
A31: 3 | B31: BANDEJA | C31: ARANDANOS | D31: 2500 | E31: =A31*D31 -> 7500 | I31: =20000/12 -> 1666.6667 | J31: =I31*A31 -> 5000 | K31: =E31-J31 -> 2500
A32: 0.2 | B32: KG | C32: KIWI | D32: 11000 | E32: =A32*D32 -> 2200 | I32: =70000/7 -> 10000 | J32: =I32*A32 -> 2000 | K32: =E32-J32 -> 200
A33: 2 | B33: KG | C33: AJO | D33: 1200 | E33: =A33*D33 -> 2400 | I33: 560 | J33: =I33*A33 -> 1120 | K33: =E33-J33 -> 1280
E35: =SUM(E26:E33) -> 36550 | K35: =SUM(K25:K33) -> 18780 | L35: =K35/E35 -> 0.51381669
A38: PAULA CASERO | D38: rto: 2 | E38: 46030
A40: CANTIDAD | B40: UNIDAD | C40: PRODUCTO | D40: PRECIO | E40: TOTAL | I40: PRECIO | J40: TOTAL | K40: DIFERENCIA
A41: 1 | B41: BOLSA | C41: ANCO | D41: 14000 | E41: =A41*D41 -> 14000 | I41: 10000 | J41: =I41*A41 -> 10000 | K41: =E41-J41 -> 4000
A42: 1 | B42: BOLSA | C42: CEBOLLA | D42: 14000 | E42: =A42*D42 -> 14000 | I42: 9000 | J42: =I42*A42 -> 9000 | K42: =E42-J42 -> 5000
A43: 0.5 | B43: ATADO | C43: PUERRO | D43: 5500 | E43: =A43*D43 -> 2750 | I43: =2610*2 -> 5220 | J43: =I43*A43 -> 2610 | K43: =E43-J43 -> 140
A44: 2 | B44: KG | C44: ZUCCINI | D44: 1200 | E44: =A44*D44 -> 2400 | I44: =10000/14 -> 714.28571 | J44: =I44*A44 -> 1428.5714 | K44: =E44-J44 -> 971.42857
A45: 2.12 | B45: KG | C45: BERENJENA | D45: 2000 | E45: =A45*D45 -> 4240 | I45: 2000 | J45: =I45*A45 -> 4240 | K45: =E45-J45 -> 0
E47: =SUM(E41:E45) -> 37390 | K47: =SUM(K41:K45) -> 10111.429 | L47: =K47/E47 -> 0.27043136
A51: TOTAL DIA | B51: =F18+E35+E47 -> 915300
A53: GANANCIA | B53: =K47+K35+K18 -> 422651.43
A55: % | B55: =B53/B51 -> 0.46176273
A57: BULTOS COMPRADOS | C57: 31
B62: EFECTIVO | C62: MERCADO PAGO | D62: BANCO GALCIA | E62: BANCO RIO | F62: CHEQUES
B63: ='07-01-2026 '!B138 -> 2619750 | C63: ='07-01-2026 '!C138 -> 4083.6 | D63: ='07-01-2026 '!D138 -> 440685.67 | E63: ='07-01-2026 '!E138 -> 0 | F63: ='07-01-2026 '!F138 -> 8500000
A65: INGRESOS
A66: COBR. CTA. CTE | B66: 36000 | C66: 0 | D66: 0 | E66: 0 | F66: 0
A67: RENDIMIENTO MP | B67: 0 | C67: 0 | D67: 0 | E67: 0 | F67: 0
A68: CHE ACREDITADO | B68: 0 | C68: 0 | D68: 1000000 | E68: 0 | F68: 1000000
A69: COBR. VACIOS | B69: 115000 | C69: 0 | D69: 0 | E69: 0 | F69: 0
A70: PRESTAMOS | B70: 0 | C70: 0 | D70: 0 | E70: 0 | F70: 0
A71: IMP. CRED. 0,6% | B71: 0 | C71: =C66*0.6%+C69*0.6% -> 0 | D71: =SUM(D66:D68)*0.6% -> 6000 | E71: 0 | F71: 0
A73: TOTAL | B73: =SUM(B63:B71) -> 2770750 | C73: =C63+C66+C69+C70-C71+C67 -> 4083.6 | D73: =D63+D66+D69+D70-D71+D68 -> 1434685.7 | E73: =E63+E66+E69+E70-E71 -> 0 | F73: =F63+F66+F69+F70-F71-D68 -> 7500000
A75: GASTOS
A76: ING. MERCADO | B76: 1000 | C76: 0 | D76: 0 | E76: 0
A77: CARGA / VACIOS | B77: 9000 | C77: 0 | D77: 0 | E77: 0
A78: CHEQ DEBITADO | B78: 0 | C78: 0 | D78: 0 | E78: 0
A79: PEAJE | B79: 2800 | C79: 0 | D79: 0 | E79: 0
A80: MERCADERIA | B80: 0 | C80: =51500+153600 -> 205100 | D80: 0 | E80: 0 | F80: 3000000
A81: COMBUSTIBLE | B81: 0 | C81: 25000 | D81: 0 | E81: 0
A82: SUELDOS | B82: 30000 | C82: 0 | D82: 0 | E82: 0
A83: DEV. PRESTAMOS | B83: 0 | C83: 0 | D83: 0 | E83: 0
A84: AGUA | B84: 0 | C84: 0 | D84: 0 | E84: 0
A85: FLETE JUAN | B85: 0 | C85: 0 | D85: 0 | E85: 0
A86: RETIRO JOAQUIN | B86: 0 | C86: 0 | D86: 0 | E86: 0
A87: RETIRO FEDERICO | B87: 0 | C87: 0 | D87: 0 | E87: 0
A88: ALQUILER LOCAL | B88: 0 | C88: 0 | D88: 0 | E88: 0
A89: CONTADOR | B89: 0 | C89: 0 | D89: 0 | E89: 0
A90: ACEITE/AGUA CHATA | B90: 0 | C90: 0 | D90: 0 | E90: 0
A91: ART LIBRERIA | B91: 22000 | C91: 0 | D91: 0 | E91: 0 | M91: =9*30000 -> 270000
A92: MECANICO | B92: 0 | C92: 0 | D92: 0 | E92: 0 | M92: =4*42000 -> 168000
A93: BOLSAS | B93: 0 | C93: 0 | D93: 0 | E93: 0
A94: SEGURO LEO | B94: 0 | C94: 0 | D94: 0 | E94: 0
A95: MONOTRIB. LEO | B95: 0 | C95: 0 | D95: 0 | E95: 0
A96: IIBB CHEQUE | B96: 0 | C96: 0 | D96: =SUM(D66:D68)*2% -> 20000 | E96: 0
A97: IIBB | B97: 0 | C97: 0 | D97: 0 | E97: 0
A98: IVA | B98: 0 | C98: 0 | D98: 0 | E98: 0
A99: GANANCIAS | B99: 0 | C99: 0 | D99: 0 | E99: 0
A100: MANT. CTA. | B100: 0 | C100: 0 | D100: 0 | E100: 0
A102: IMP. DEB. 0,6% | B102: 0 | C102: =SUM(C76:C99)*0.6% -> 1380.6 | D102: =SUM(D76:D99)*0.6%+(D103*0.6%) -> 1920 | E102: =(E80*0.6%)+(E81*0.6%)+(E82*0.6%)+(E85*0.6%)+(E86*0.6%) -> 0
A103: PASE DE CUENTAS | B103: 0 | C103: 300000 | D103: 300000 | E103: =SUM(E77:E101)*0.6%+(E104*0.6%) -> 0
A105: TOTAL SALIDAS | B105: =SUM(B76:B104) -> 64800 | C105: =SUM(C76:C102) -> 231480.6 | D105: =SUM(D76:D103) -> 321920 | E105: =E87+E91+E102-E103 -> 0 | F105: =F80 -> 3000000
A107: SALDOS | B107: =B73-B105 -> 2705950 | C107: =C73-C105+C103 -> 72603 | D107: =D73-D105 -> 1112765.7 | E107: =E73-E105 -> 0 | F107: =F73-F105 -> 4500000
A109: fede | B109: =79400-B79-B76+B69-B77-B91 -> 159600
A110: joaquin | B110: =2528350+12000+B66-B82 -> 2546350
B112: =SUM(B109:B110) -> 2705950

Sheet 09-01-2026 
A3: FV | E3: rto: 214 | F3: 46031 | I3: COMPRA
A5: CANTIDAD | B5: UNIDAD | C5: PRODUCTO | D5: PRECIO | E5: TOTAL | F5: TOTAL + IVA | I5: PRECIO | J5: TOTAL | K5: DIFERENCIA
A6: 4 | B6: CAJA | C6: BANANA | D6: 46000 | E6: =A6*D6 -> 184000 | F6: =E6*1.105 -> 203320 | I6: 35000 | J6: =I6*A6 -> 140000 | K6: =F6-J6 -> 63320
A7: 4 | B7: CAJA | C7: PELON | D7: 42000 | E7: =A7*D7 -> 168000 | F7: =E7*1.105 -> 185640 | I7: 32000 | J7: =I7*A7 -> 128000 | K7: =F7-J7 -> 57640
A8: 2 | B8: CAJA | C8: CIRUELA RED | D8: 45000 | E8: =A8*D8 -> 90000 | F8: =E8*1.105 -> 99450 | I8: 45000 | J8: =I8*A8 -> 90000 | K8: =F8-J8 -> 9450
A9: 1 | B9: CAJON | C9: ZUCCINI | D9: 12000 | E9: =A9*D9 -> 12000 | F9: =E9*1.105 -> 13260 | I9: 8000 | J9: =I9*A9 -> 8000 | K9: =F9-J9 -> 5260
A10: 2 | B10: CAJA | C10: BANANA | D10: 46000 | E10: =A10*D10 -> 92000 | F10: =E10*1.105 -> 101660 | G10: BOLSA | J10: =I10*A10 -> 0 | K10: =F10-J10 -> 101660
A11: 1 | B11: CAJA | C11: PELON | D11: 42000 | E11: =A11*D11 -> 42000 | F11: =E11*1.105 -> 46410 | G11: BOLSA | J11: =I11*A11 -> 0 | K11: =F11-J11 -> 46410
A12: 1 | B12: CAJA | C12: CIRUELA RED | D12: 45000 | E12: =A12*D12 -> 45000 | F12: =E12*1.105 -> 49725 | G12: BOLSA | J12: =I12*A12 -> 0 | K12: =F12-J12 -> 49725
E14: =SUM(E6:E12) -> 633000 | F14: =SUM(F6:F12) -> 699465 | K14: =SUM(K6:K12) -> 333465 | L14: =K14/F14 -> 0.47674294
A17: BRASOV | D17: rto: 2 | E17: 46031 | I17: COMPRA
A19: CANTIDAD | B19: UNIDAD | C19: PRODUCTO | D19: PRECIO | E19: TOTAL | I19: PRECIO | J19: TOTAL | K19: DIFERENCIA
A20: 1 | B20: CAJA | C20: LIMON | D20: 46000 | E20: =A20*D20 -> 46000 | I20: 40000 | J20: =I20*A20 -> 40000 | K20: =E20-J20 -> 6000
A21: 1 | B21: CAJON | C21: NARANJA | D21: 22000 | E21: =A21*D21 -> 22000 | I21: 18000 | J21: =I21*A21 -> 18000 | K21: =E21-J21 -> 4000
A22: 0.5 | B22: CAJON | C22: MORRON ROJO | D22: 20000 | E22: =A22*D22 -> 10000 | I22: 12000 | J22: =I22*A22 -> 6000 | K22: =E22-J22 -> 4000
A23: 0.5 | B23: CAJON | C23: TOMATE REDONDO | D23: 35000 | E23: =A23*D23 -> 17500 | I23: 30000 | J23: =I23*A23 -> 15000 | K23: =E23-J23 -> 2500
A24: 1 | B24: CAJA | C24: PALTA | D24: 55000 | E24: =A24*D24 -> 55000 | I24: 35000 | J24: =I24*A24 -> 35000 | K24: =E24-J24 -> 20000
A25: 2 | B25: ATADO | C25: PEREJIL | D25: 4000 | E25: =A25*D25 -> 8000 | I25: 2000 | J25: =I25*A25 -> 4000 | K25: =E25-J25 -> 4000
A26: 2 | B26: ATADO | C26: CEB VERDEO | D26: 4000 | E26: =A26*D26 -> 8000 | I26: 3000 | J26: =I26*A26 -> 6000 | K26: =E26-J26 -> 2000
E28: =SUM(E20:E26) -> 166500 | K28: =SUM(K20:K26) -> 42500 | L28: =K28/E28 -> 0.25525526
A31: COMO SIEMPRE LAGUNA | D31: rto: 19 | E31: 46031
A33: CANTIDAD | B33: UNIDAD | C33: PRODUCTO | D33: PRECIO | E33: TOTAL | I33: PRECIO | J33: TOTAL | K33: DIFERENCIA
A34: 4 | B34: KG | C34: TOM PERITA | D34: 2800 | E34: =A34*D34 -> 11200 | I34: 3000 | J34: =I34*A34 -> 12000 | K34: =E34-J34 -> -800
A35: 1 | B35: UNIDAD | C35: APIO | D35: 1500 | E35: =A35*D35 -> 1500 | I35: 1000 | J35: =I35*A35 -> 1000 | K35: =E35-J35 -> 500
A36: 1 | B36: ATADO | C36: CILANTRO | D36: 2500 | E36: =A36*D36 -> 2500 | I36: 1500 | J36: =I36*A36 -> 1500 | K36: =E36-J36 -> 1000
A37: 1 | B37: ATADO | C37: CIBOULETTE | D37: 3000 | E37: =A37*D37 -> 3000 | I37: 2000 | J37: =I37*A37 -> 2000 | K37: =E37-J37 -> 1000
A38: 4.2 | B38: KG | C38: CEBOLLA MORADA | D38: 2200 | E38: =A38*D38 -> 9240 | I38: 1600 | J38: =I38*A38 -> 6720 | K38: =E38-J38 -> 2520
A39: 3 | B39: KG | C39: LIMA | D39: 3500 | E39: =A39*D39 -> 10500 | I39: 2500 | J39: =I39*A39 -> 7500 | K39: =E39-J39 -> 3000
A40: 3 | B40: KG | C40: LIMON | D40: 3000 | E40: =A40*D40 -> 9000 | I40: =35000/14 -> 2500 | J40: =I40*A40 -> 7500 | K40: =E40-J40 -> 1500
A41: 2 | B41: BOLSA | C41: PAPA GARLIC | D41: 21000 | E41: =A41*D41 -> 42000 | I41: 18000 | J41: =I41*A41 -> 36000 | K41: =E41-J41 -> 6000
A42: 12 | B42: UNIDAD | C42: PALTA | D42: 1400 | E42: =A42*D42 -> 16800 | I42: =60000/70 -> 857.14286 | J42: =I42*A42 -> 10285.714 | K42: =E42-J42 -> 6514.2857
A43: 0.25 | B43: KG | C43: FRUTILLA | D43: 6000 | E43: =A43*D43 -> 1500 | I43: 3500 | J43: =I43*A43 -> 875 | K43: =E43-J43 -> 625
A44: 4 | B44: UNIDAD | C44: AJO | D44: 1200 | E44: =A44*D44 -> 4800 | I44: 560 | J44: =I44*A44 -> 2240 | K44: =E44-J44 -> 2560
A45: 0.25 | B45: KG | C45: JENGIBRE | D45: 5000 | E45: =A45*D45 -> 1250 | I45: 4000 | J45: =I45*A45 -> 1000 | K45: =E45-J45 -> 250
A46: 1 | B46: ATADO | C46: TOMILLO | D46: 3000 | E46: =A46*D46 -> 3000 | I46: 2000 | J46: =I46*A46 -> 2000 | K46: =E46-J46 -> 1000
A47: 1 | B47: ATADO | C47: MENTA | D47: 3000 | E47: =A47*D47 -> 3000 | I47: 2000 | J47: =I47*A47 -> 2000 | K47: =E47-J47 -> 1000
A48: 1 | B48: ATADO | C48: PUERRO | D48: 5000 | E48: =A48*D48 -> 5000 | I48: 4000 | J48: =I48*A48 -> 4000 | K48: =E48-J48 -> 1000
A49: 3 | B49: ATADO | C49: ALBAHACA | D49: 1200 | E49: =A49*D49 -> 3600 | I49: 1000 | J49: =I49*A49 -> 3000 | K49: =E49-J49 -> 600
A50: 0.5 | B50: CAJON | C50: RUCULA | D50: 12000 | E50: =A50*D50 -> 6000 | I50: 6000 | J50: =I50*A50 -> 3000 | K50: =E50-J50 -> 3000
A51: 1 | B51: KG | C51: BATATA | D51: 1400 | E51: =A51*D51 -> 1400 | I51: =11000/10 -> 1100 | J51: =I51*A51 -> 1100 | K51: =E51-J51 -> 300
A52: 1 | B52: KG | C52: PORTOBELLO | D52: 20000 | E52: =A52*D52 -> 20000 | I52: 18000 | J52: =I52*A52 -> 18000 | K52: =E52-J52 -> 2000
A53: 1 | B53: CAJON | C53: LIMON | D53: 46000 | E53: =A53*D53 -> 46000 | I53: 40000 | J53: =I53*A53 -> 40000 | K53: =E53-J53 -> 6000
A54: 0.5 | B54: CAJA | C54: POMELO | D54: 46000 | E54: =A54*D54 -> 23000 | I54: 40000 | J54: =I54*A54 -> 20000 | K54: =E54-J54 -> 3000
A55: 1 | B55: CAJON | C55: NARANJA | D55: 22000 | E55: =A55*D55 -> 22000 | I55: 18000 | J55: =I55*A55 -> 18000 | K55: =E55-J55 -> 4000
A56: 2 | B56: ATADO | C56: MENTA | D56: 3000 | E56: =A56*D56 -> 6000 | I56: 2000 | J56: =I56*A56 -> 4000 | K56: =E56-J56 -> 2000
E58: =SUM(E34:E56) -> 252290 | K58: =SUM(K34:K56) -> 48569.286 | L58: =K58/E58 -> 0.19251372
A62: LA MARQUESA | D62: rto: 1 | E62: 46031
A64: CANTIDAD | B64: UNIDAD | C64: PRODUCTO | D64: PRECIO | E64: TOTAL | I64: PRECIO | J64: TOTAL | K64: DIFERENCIA
A65: 2 | B65: CUBETA | C65: ARANDANO | D65: 2500 | E65: =A65*D65 -> 5000 | I65: =20000/12 -> 1666.6667 | J65: =I65*A65 -> 3333.3333 | K65: =E65-J65 -> 1666.6667
A66: 2 | B66: ATADO | C66: ALBAHACA | D66: 1000 | E66: =A66*D66 -> 2000 | I66: =3500/6 -> 583.33333 | J66: =I66*A66 -> 1166.6667 | K66: =E66-J66 -> 833.33333
A67: 1 | B67: KG | C67: BANANA | D67: 3000 | E67: =A67*D67 -> 3000 | I67: 2333 | J67: =I67*A67 -> 2333 | K67: =E67-J67 -> 667
A68: 4 | B68: KG | C68: BERENJENA | D68: 1800 | E68: =A68*D68 -> 7200 | I68: 1000 | J68: =I68*A68 -> 4000 | K68: =E68-J68 -> 3200
A69: 1 | B69: BOLSA | C69: CEBOLLA | D69: 12000 | E69: =A69*D69 -> 12000 | I69: 9000 | J69: =I69*A69 -> 9000 | K69: =E69-J69 -> 3000
A70: 1 | B70: KG | C70: CHAMPI | D70: 19000 | E70: =A70*D70 -> 19000 | I70: 17000 | J70: =I70*A70 -> 17000 | K70: =E70-J70 -> 2000
A71: 1 | B71: CAJON | C71: ESPINACA | D71: 18000 | E71: =A71*D71 -> 18000 | I71: 15000 | J71: =I71*A71 -> 15000 | K71: =E71-J71 -> 3000
A72: 2.25 | B72: KG | C72: FRUTILLA | D72: 4500 | E72: =A72*D72 -> 10125 | I72: =13000/4 -> 3250 | J72: =I72*A72 -> 7312.5 | K72: =E72-J72 -> 2812.5
A73: 2 | B73: KG | C73: LIMA | D73: 4000 | E73: =A73*D73 -> 8000 | I73: 2500 | J73: =I73*A73 -> 5000 | K73: =E73-J73 -> 3000
A74: 0.5 | B74: CAJON | C74: LIMON | D74: 46000 | E74: =A74*D74 -> 23000 | I74: 40000 | J74: =I74*A74 -> 20000 | K74: =E74-J74 -> 3000
A75: 1 | B75: UNIDAD | C75: MANGO | D75: 2500 | E75: =A75*D75 -> 2500 | I75: 1333 | J75: =I75*A75 -> 1333 | K75: =E75-J75 -> 1167
A76: 1 | B76: ATADO | C76: MENTA | D76: 3000 | E76: =A76*D76 -> 3000 | I76: 2000 | J76: =I76*A76 -> 2000 | K76: =E76-J76 -> 1000
A77: 2 | B77: KG | C77: MORRON VERDE | D77: 3000 | E77: =A77*D77 -> 6000 | I77: 3000 | J77: =I77*A77 -> 6000 | K77: =E77-J77 -> 0
A78: 2 | B78: KG | C78: MORRON ROJO | D78: 3000 | E78: =A78*D78 -> 6000 | I78: =12000/8 -> 1500 | J78: =I78*A78 -> 3000 | K78: =E78-J78 -> 3000
A79: 10 | B79: UNIDAD | C79: PALTA | D79: 1400 | E79: =A79*D79 -> 14000 | I79: =60000/70 -> 857.14286 | J79: =I79*A79 -> 8571.4286 | K79: =E79-J79 -> 5428.5714
A80: 1 | B80: CAJON | C80: NARANJA | D80: 22000 | E80: =A80*D80 -> 22000 | I80: 18000 | J80: =I80*A80 -> 18000 | K80: =E80-J80 -> 4000
A81: 1 | B81: KG | C81: PEPINO | D81: 2200 | E81: =A81*D81 -> 2200 | I81: 1500 | J81: =I81*A81 -> 1500 | K81: =E81-J81 -> 700
A82: 2 | B82: ATADO | C82: PUERRO | D82: 5000 | E82: =A82*D82 -> 10000 | I82: 4000 | J82: =I82*A82 -> 8000 | K82: =E82-J82 -> 2000
A83: 1 | B83: UNIDAD | C83: REP ROJO | D83: 2000 | E83: =A83*D83 -> 2000 | I83: 1200 | J83: =I83*A83 -> 1200 | K83: =E83-J83 -> 800
A84: 1 | B84: UNIDAD | C84: REP BLANCO | D84: 2000 | E84: =A84*D84 -> 2000 | I84: 1200 | J84: =I84*A84 -> 1200 | K84: =E84-J84 -> 800
A85: 1 | B85: ATADO | C85: ROMERO | D85: 3000 | E85: =A85*D85 -> 3000 | I85: 2000 | J85: =I85*A85 -> 2000 | K85: =E85-J85 -> 1000
A86: 5 | B86: KG | C86: TOMATE | D86: 2800 | E86: =A86*D86 -> 14000 | I86: =30000/15 -> 2000 | J86: =I86*A86 -> 10000 | K86: =E86-J86 -> 4000
A87: 7.85 | B87: KG | C87: ZAPALLO ANCO | D87: 1200 | E87: =A87*D87 -> 9420 | I87: =9000/15 -> 600 | J87: =I87*A87 -> 4710 | K87: =E87-J87 -> 4710
A88: 1.5 | B88: KG | C88: ZAPALLITO LARGO | D88: 1200 | E88: =A88*D88 -> 1800 | I88: =10000/14 -> 714.28571 | J88: =I88*A88 -> 1071.4286 | K88: =E88-J88 -> 728.57143
A89: 3 | B89: CAJON | C89: HUEVO | D89: 50000 | E89: =A89*D89 -> 150000 | I89: 40000 | J89: =I89*A89 -> 120000 | K89: =E89-J89 -> 30000
E91: =SUM(E65:E89) -> 355245 | K91: =SUM(K65:K89) -> 82513.643 | L91: =K91/E91 -> 0.2322725
A95: LA PIADINA | D95: rto: 4 | E95: 46031
A97: CANTIDAD | B97: UNIDAD | C97: PRODUCTO | D97: PRECIO | E97: TOTAL | I97: PRECIO | J97: TOTAL | K97: DIFERENCIA
A98: 1 | B98: CAJON | C98: RUCULA | D98: 15000 | E98: =A98*D98 -> 15000 | I98: 6000 | J98: =I98*A98 -> 6000 | K98: =E98-J98 -> 9000
A99: 0.5 | B99: CAJON | C99: TOMATE REDONDO | D99: 36000 | E99: =A99*D99 -> 18000 | I99: 30000 | J99: =I99*A99 -> 15000 | K99: =E99-J99 -> 3000
A100: 1 | B100: KG | C100: LEC FRANCESA | D100: 4000 | E100: =A100*D100 -> 4000 | I100: 0 | J100: =I100*A100 -> 0 | K100: =E100-J100 -> 4000
A101: 3 | B101: UNIDAD | C101: PALTA | D101: 1400 | E101: =A101*D101 -> 4200 | I101: =60000/70 -> 857.14286 | J101: =I101*A101 -> 2571.4286 | K101: =E101-J101 -> 1628.5714
A102: 0.25 | B102: KG | C102: TOM CHERRY | D102: 4200 | E102: =A102*D102 -> 1050 | I102: =26000/8 -> 3250 | J102: =I102*A102 -> 812.5 | K102: =E102-J102 -> 237.5
E104: =SUM(E98:E102) -> 42250 | K104: =SUM(K98:K102) -> 17866.071 | L104: =K104/E104 -> 0.4228656
A108: MESTIZO | D108: rto: 2 | E108: 46031
A110: CANTIDAD | B110: UNIDAD | C110: ATADO | D110: PRECIO | E110: TOTAL | I110: PRECIO | J110: TOTAL | K110: DIFERENCIA
A111: 2 | B111: ATADO | C111: ALBAHACA | D111: 1000 | E111: =A111*D111 -> 2000 | I111: 583 | J111: =I111*A111 -> 1166 | K111: =E111-J111 -> 834
A112: 3 | B112: KG | C112: TOMATE REDONDO | D112: 2800 | E112: =A112*D112 -> 8400 | I112: =30000/15 -> 2000 | J112: =I112*A112 -> 6000 | K112: =E112-J112 -> 2400
A113: 1 | B113: ATADO | C113: ENELDO | D113: 3000 | E113: =A113*D113 -> 3000 | I113: 2000 | J113: =I113*A113 -> 2000 | K113: =E113-J113 -> 1000
A114: 1 | B114: ATADO | C114: TOMILLO | D114: 3000 | E114: =A114*D114 -> 3000 | I114: 2000 | J114: =I114*A114 -> 2000 | K114: =E114-J114 -> 1000
A115: 1 | B115: ATADO | C115: CEB VERDEO | D115: 4000 | E115: =A115*D115 -> 4000 | I115: 3000 | J115: =I115*A115 -> 3000 | K115: =E115-J115 -> 1000
A116: 2 | B116: KG | C116: PIM ROJO | D116: 3000 | E116: =A116*D116 -> 6000 | I116: =12000/8 -> 1500 | J116: =I116*A116 -> 3000 | K116: =E116-J116 -> 3000
A117: 2 | B117: KG | C117: PIM VERDE | D117: 3000 | E117: =A117*D117 -> 6000 | I117: 2000 | J117: =I117*A117 -> 4000 | K117: =E117-J117 -> 2000
A118: 1 | B118: BOLSA | C118: PAPA GARLIC | D118: 21000 | E118: =A118*D118 -> 21000 | I118: 18000 | J118: =I118*A118 -> 18000 | K118: =E118-J118 -> 3000
A119: 1 | B119: CAJON | C119: RUCULA | D119: 12000 | E119: =A119*D119 -> 12000 | I119: 6000 | J119: =I119*A119 -> 6000 | K119: =E119-J119 -> 6000
A120: 0.5 | B120: CAJON | C120: LEC FRANCESA | D120: 14000 | E120: =A120*D120 -> 7000 | I120: 10000 | J120: =I120*A120 -> 5000 | K120: =E120-J120 -> 2000
A121: 0.5 | B121: CAJON | C121: LEC MORADA | D121: 9000 | E121: =A121*D121 -> 4500 | I121: 5000 | J121: =I121*A121 -> 2500 | K121: =E121-J121 -> 2000
A122: 1 | B122: ATADO | C122: CIBOULLETE | D122: 3000 | E122: =A122*D122 -> 3000 | I122: 2000 | J122: =I122*A122 -> 2000 | K122: =E122-J122 -> 1000
A123: 2 | B123: KG | C123: ZAP LARGO | D123: 1200 | E123: =A123*D123 -> 2400 | I123: =10000/14 -> 714.28571 | J123: =I123*A123 -> 1428.5714 | K123: =E123-J123 -> 971.42857
A124: 1 | B124: CAJON | C124: POMELO | D124: 46000 | E124: =A124*D124 -> 46000 | I124: 40000 | J124: =I124*A124 -> 40000 | K124: =E124-J124 -> 6000
E126: =SUM(E111:E125) -> 128300 | K126: =SUM(K111:K124) -> 32205.429 | L126: =K126/E126 -> 0.25101659
A130: RAKUS CAFE | D130: rto: 13 | E130: 46031
...

Sheet 12-01-2026 
A3: FV | E3: rto: 215 | F3: 46034 | I3: COMPRA
A5: CANTIDAD | B5: UNIDAD | C5: PRODUCTO | D5: PRECIO | E5: TOTAL | F5: TOTAL + IVA | I5: PRECIO | J5: TOTAL | K5: DIFERENCIA
A6: 4 | B6: CAJA | C6: BANANA | D6: 38000 | E6: =A6*D6 -> 152000 | F6: =E6*1.105 -> 167960 | I6: 30000 | J6: =I6*A6 -> 120000 | K6: =F6-J6 -> 47960
A7: 3 | B7: CAJON | C7: NARANJA | D7: 22000 | E7: =A7*D7 -> 66000 | F7: =E7*1.105 -> 72930 | I7: 18000 | J7: =I7*A7 -> 54000 | K7: =F7-J7 -> 18930
A8: 32 | B8: KG | C8: SANDIA | D8: 1200 | E8: =A8*D8 -> 38400 | F8: =E8*1.105 -> 42432 | G8: (11 KG X 4 ARANDANO) | I8: 800 | J8: =I8*A8 -> 25600 | K8: =F8-J8 -> 16832
A9: 3 | B9: CAJON | C9: MELON | D9: 28000 | E9: =A9*D9 -> 84000 | F9: =E9*1.105 -> 92820 | I9: 20000 | J9: =I9*A9 -> 60000 | K9: =F9-J9 -> 32820
A10: 2 | B10: CAJA | C10: MANZANA GRANNY | D10: 70000 | E10: =A10*D10 -> 140000 | F10: =E10*1.105 -> 154700 | I10: 42000 | J10: =I10*A10 -> 84000 | K10: =F10-J10 -> 70700
A11: 2 | B11: CAJA | C11: DURAZNO | D11: 35000 | E11: =A11*D11 -> 70000 | F11: =E11*1.105 -> 77350 | I11: 30000 | J11: =I11*A11 -> 60000 | K11: =F11-J11 -> 17350
A12: 2 | B12: CAJON | C12: UVA BLANCA | D12: 32000 | E12: =A12*D12 -> 64000 | F12: =E12*1.105 -> 70720 | I12: 27000 | J12: =I12*A12 -> 54000 | K12: =F12-J12 -> 16720
A13: 2 | B13: CAJA | C13: PELON | D13: 38000 | E13: =A13*D13 -> 76000 | F13: =E13*1.105 -> 83980 | I13: 30000 | J13: =I13*A13 -> 60000 | K13: =F13-J13 -> 23980
A14: 1 | B14: CAJON | C14: HUEVO | D14: 50000 | E14: =A14*D14 -> 50000 | F14: =E14*1.21 -> 60500 | I14: 38000 | J14: =I14*A14 -> 38000 | K14: =F14-J14 -> 22500
A15: 1 | B15: CAJON | C15: MORRON ROJO | D15: 20000 | E15: =A15*D15 -> 20000 | F15: =E15*1.105 -> 22100 | I15: 12000 | J15: =I15*A15 -> 12000 | K15: =F15-J15 -> 10100
A16: 1 | B16: CAJON | C16: MORRON VERDE | D16: 20000 | E16: =A16*D16 -> 20000 | F16: =E16*1.105 -> 22100 | I16: 15000 | J16: =I16*A16 -> 15000 | K16: =F16-J16 -> 7100
A17: 1 | B17: CAJON | C17: MORRON AMARILLO | D17: 30000 | E17: =A17*D17 -> 30000 | F17: =E17*1.105 -> 33150 | I17: 16000 | J17: =I17*A17 -> 16000 | K17: =F17-J17 -> 17150
A18: 15 | B18: UNIDAD | C18: PALTA | D18: 1300 | E18: =A18*D18 -> 19500 | F18: =E18*1.105 -> 21547.5 | I18: =60000/70 -> 857.14286 | J18: =I18*A18 -> 12857.143 | K18: =F18-J18 -> 8690.3571
A19: 1 | B19: CAJON | C19: BANANA | D19: 38000 | E19: =A19*D19 -> 38000 | F19: =E19*1.105 -> 41990 | G19: BOLSA | J19: =I19*A19 -> 0 | K19: =F19-J19 -> 41990
A20: 2 | B20: CAJON | C20: NARANJA | D20: 22000 | E20: =A20*D20 -> 44000 | F20: =E20*1.105 -> 48620 | G20: BOLSA | J20: =I20*A20 -> 0 | K20: =F20-J20 -> 48620
A21: 1 | B21: CAJON | C21: DURAZNO | D21: 35000 | E21: =A21*D21 -> 35000 | F21: =E21*1.105 -> 38675 | G21: BOLSA | J21: =I21*A21 -> 0 | K21: =F21-J21 -> 38675
A22: 1 | B22: CAJON | C22: PELON | D22: 38000 | E22: =A22*D22 -> 38000 | F22: =E22*1.105 -> 41990 | G22: BOLSA | J22: =I22*A22 -> 0 | K22: =F22-J22 -> 41990
A23: 1 | B23: CAJON | C23: UVA BLANCA | D23: 32000 | E23: =A23*D23 -> 32000 | F23: =E23*1.105 -> 35360 | G23: BOLSA PROPIA | J23: =I23*A23 -> 0 | K23: =F23-J23 -> 35360
E25: =SUM(E6:E23) -> 1016900 | F25: =SUM(F6:F23) -> 1128924.5 | K25: =SUM(K6:K23) -> 517467.36 | L25: =K25/F25 -> 0.45837198
A28: COMO SIEMPRE LAGUNA | D28: rto: 20 | E28: 46034
A30: CANTIDAD | B30: UNIDAD | C30: PRODUCTO | D30: PRECIO | E30: TOTAL | I30: PRECIO | J30: TOTAL | K30: DIFERENCIA
A31: 3 | B31: BOLSA | C31: PAPA GARLIC | D31: 23000 | E31: =A31*D31 -> 69000 | I31: 20000 | J31: =I31*A31 -> 60000 | K31: =E31-J31 -> 9000
A32: 1 | B32: CAJON | C32: TOM CHERRY | D32: 34000 | E32: =A32*D32 -> 34000 | I32: 26000 | J32: =I32*A32 -> 26000 | K32: =E32-J32 -> 8000
A33: 3 | B33: UNIDAD | C33: AJO | D33: 1200 | E33: =A33*D33 -> 3600 | I33: =30000/50 -> 600 | J33: =I33*A33 -> 1800 | K33: =E33-J33 -> 1800
A34: 3 | B34: UNIDAD | C34: MANGO | D34: 2200 | E34: =A34*D34 -> 6600 | I34: =15000/9 -> 1666.6667 | J34: =I34*A34 -> 5000 | K34: =E34-J34 -> 1600
A35: 1 | B35: CAJON | C35: RUCULA | D35: 12000 | E35: =A35*D35 -> 12000 | I35: 8000 | J35: =I35*A35 -> 8000 | K35: =E35-J35 -> 4000
A36: 1 | B36: KG | C36: CHAMPI | D36: 19000 | E36: =A36*D36 -> 19000 | I36: 16000 | J36: =I36*A36 -> 16000 | K36: =E36-J36 -> 3000
A37: 1 | B37: KG | C37: PORTO | D37: 20000 | E37: =A37*D37 -> 20000 | I37: 17000 | J37: =I37*A37 -> 17000 | K37: =E37-J37 -> 3000
A38: 2 | B38: ATADO | C38: ALBAHACA | D38: 1200 | E38: =A38*D38 -> 2400 | I38: =4000/6 -> 666.66667 | J38: =I38*A38 -> 1333.3333 | K38: =E38-J38 -> 1066.6667
A39: 1 | B39: ATADO | C39: ENELDO | D39: 3000 | E39: =A39*D39 -> 3000 | I39: 2000 | J39: =I39*A39 -> 2000 | K39: =E39-J39 -> 1000
A40: 0.5 | B40: CAJON | C40: NARANJA | D40: 22000 | E40: =A40*D40 -> 11000 | I40: 18000 | J40: =I40*A40 -> 9000 | K40: =E40-J40 -> 2000
A41: 0.5 | B41: CAJON | C41: POMELO | D41: 46000 | E41: =A41*D41 -> 23000 | I41: 40000 | J41: =I41*A41 -> 20000 | K41: =E41-J41 -> 3000
A42: 0.5 | B42: CAJON | C42: LIMON | D42: 46000 | E42: =A42*D42 -> 23000 | I42: 40000 | J42: =I42*A42 -> 20000 | K42: =E42-J42 -> 3000
E44: =SUM(E31:E42) -> 226600 | K44: =SUM(K31:K42) -> 40466.667 | L44: =K44/E44 -> 0.17858194
A48: PAULA | D48: rto: 3 | E48: 46031
A50: CANTIDAD | B50: UNIDAD | C50: PRODUCTO | D50: PRECIO | E50: TOTAL | I50: PRECIO | J50: TOTAL | K50: DIFERENCIA
A51: 1 | B51: BOLSA | C51: CEBOLLA | D51: 13000 | E51: =A51*D51 -> 13000 | I51: 10000 | J51: =I51*A51 -> 10000 | K51: =E51-J51 -> 3000
A52: 1 | B52: BOLSA | C52: PAPA GARLIC | D52: 20000 | E52: =A52*D52 -> 20000 | I52: 18000 | J52: =I52*A52 -> 18000 | K52: =E52-J52 -> 2000
A53: 1 | B53: BOLSA | C53: ANCO | D53: 18000 | E53: =A53*D53 -> 18000 | I53: 15000 | J53: =I53*A53 -> 15000 | K53: =E53-J53 -> 3000
A54: 1 | B54: BOLSA | C54: BATATA | D54: 14000 | E54: =A54*D54 -> 14000 | I54: 11000 | J54: =I54*A54 -> 11000 | K54: =E54-J54 -> 3000
A55: 2 | B55: KG | C55: ZAPALLITO REDO | D55: 1200 | E55: =A55*D55 -> 2400 | I55: 1000 | J55: =I55*A55 -> 2000 | K55: =E55-J55 -> 400
A56: 2 | B56: KG | C56: BERENJENA | D56: 2000 | E56: =A56*D56 -> 4000 | I56: =10000/8 -> 1250 | J56: =I56*A56 -> 2500 | K56: =E56-J56 -> 1500
A57: 1 | B57: UNIDAD | C57: REP ROJO | D57: 1800 | E57: =A57*D57 -> 1800 | I57: 1200 | J57: =I57*A57 -> 1200 | K57: =E57-J57 -> 600
A58: 2.4 | B58: KG | C58: BANANA | D58: 3000 | E58: =A58*D58 -> 7200 | I58: 0 | J58: =I58*A58 -> 0 | K58: =E58-J58 -> 7200
A59: 3 | B59: ATADO | C59: RUCULA | D59: 500 | E59: =A59*D59 -> 1500 | I59: =8000/24 -> 333.33333 | J59: =I59*A59 -> 1000 | K59: =E59-J59 -> 500
A60: 1 | B60: KG | C60: LEC MANTECA | D60: 3000 | E60: =A60*D60 -> 3000 | I60: =15000/5 -> 3000 | J60: =I60*A60 -> 3000 | K60: =E60-J60 -> 0
A61: 2 | B61: KG | C61: TOMATE | D61: 2600 | E61: =A61*D61 -> 5200 | I61: =30000/15 -> 2000 | J61: =I61*A61 -> 4000 | K61: =E61-J61 -> 1200
A62: 1 | B62: UNIDAD | C62: REP BLANCO | D62: 1800 | E62: =A62*D62 -> 1800 | I62: 1200 | J62: =I62*A62 -> 1200 | K62: =E62-J62 -> 600
A63: 8 | B63: UNIDAD | C63: PALTA | D63: 1200 | E63: =A63*D63 -> 9600 | I63: =60000/70 -> 857.14286 | J63: =I63*A63 -> 6857.1429 | K63: =E63-J63 -> 2742.8571
A64: 1 | B64: KG | C64: TOM CHERRY | D64: 3700 | E64: =A64*D64 -> 3700 | I64: =25000/8 -> 3125 | J64: =I64*A64 -> 3125 | K64: =E64-J64 -> 575
A65: 0.3 | B65: KG | C65: LEC MORADA | D65: 3500 | E65: =A65*D65 -> 1050 | I65: 0 | J65: =I65*A65 -> 0 | K65: =E65-J65 -> 1050
E67: =SUM(E51:E65) -> 106250 | K67: =SUM(K51:K65) -> 27367.857 | L67: =K67/E67 -> 0.25757983
A71: LA PIADINA | D71: rto: 5 | E71: 46034
A73: CANTIDAD | B73: UNIDAD | C73: PRODUCTO | D73: PRECIO | E73: TOTAL | I73: PRECIO | J73: TOTAL | K73: DIFERENCIA
A74: 3 | B74: KG | C74: TOMATE REDONDO | D74: 2600 | E74: =A74*D74 -> 7800 | I74: 2000 | J74: =I74*A74 -> 6000 | K74: =E74-J74 -> 1800
A75: 0.5 | B75: CAJON | C75: RUCULA | D75: 15000 | E75: =A75*D75 -> 7500 | I75: 8000 | J75: =I75*A75 -> 4000 | K75: =E75-J75 -> 3500
A76: 3 | B76: UNIDAD | C76: PALTA | D76: 1300 | E76: =A76*D76 -> 3900 | I76: =60000/70 -> 857.14286 | J76: =I76*A76 -> 2571.4286 | K76: =E76-J76 -> 1328.5714
A77: 1 | B77: KG | C77: UVA | D77: 4500 | E77: =A77*D77 -> 4500 | I77: 0 | J77: =I77*A77 -> 0 | K77: =E77-J77 -> 4500
A78: 2 | B78: KG | C78: BANANA | D78: 3000 | E78: =A78*D78 -> 6000 | J78: =I78*A78 -> 0 | K78: =E78-J78 -> 6000
A79: 1 | B79: KG | C79: FRUTILLA | D79: 10000 | E79: =A79*D79 -> 10000 | I79: 9000 | J79: =I79*A79 -> 9000 | K79: =E79-J79 -> 1000
A80: 1 | B80: KG | C80: NARANJA | D80: 1600 | E80: =A80*D80 -> 1600 | I80: =18000/15 -> 1200 | J80: =I80*A80 -> 1200 | K80: =E80-J80 -> 400
A81: 3 | B81: CUBETA | C81: ARANDANO | D81: 2500 | E81: =A81*D81 -> 7500 | I81: =20000/12 -> 1666.6667 | J81: =I81*A81 -> 5000 | K81: =E81-J81 -> 2500
A82: 0.2 | B82: KG | C82: KIWI | D82: 13000 | E82: =A82*D82 -> 2600 | I82: =70000/7 -> 10000 | J82: =I82*A82 -> 2000 | K82: =E82-J82 -> 600
E84: =SUM(E74:E82) -> 51400 | K84: =SUM(K74:K82) -> 21628.571 | L84: =K84/E84 -> 0.42078933
A88: MESTIZO | D88: rto: 3 | E88: 46034
A90: CANTIDAD | B90: UNIDAD | C90: ATADO | D90: PRECIO | E90: TOTAL | I90: PRECIO | J90: TOTAL | K90: DIFERENCIA
A91: 2 | B91: BOLSA | C91: PAPA GARLIC | D91: 23000 | E91: =A91*D91 -> 46000 | I91: 20000 | J91: =I91*A91 -> 40000 | K91: =E91-J91 -> 6000
A92: 1 | B92: ATADO | C92: ALBAHACA | D92: 1200 | E92: =A92*D92 -> 1200 | I92: =4000/6 -> 666.66667 | J92: =I92*A92 -> 666.66667 | K92: =E92-J92 -> 533.33333
A93: 1 | B93: CAJON | C93: HUEVO | D93: 52000 | E93: =A93*D93 -> 52000 | I93: 38000 | J93: =I93*A93 -> 38000 | K93: =E93-J93 -> 14000
A94: 1 | B94: CAJON | C94: LEC FRANCESA | D94: 15000 | E94: =A94*D94 -> 15000 | I94: 15000 | J94: =I94*A94 -> 15000 | K94: =E94-J94 -> 0
A95: 1 | B95: CAJON | C95: RUCULA | D95: 12000 | E95: =A95*D95 -> 12000 | I95: 8000 | J95: =I95*A95 -> 8000 | K95: =E95-J95 -> 4000
A96: 1 | B96: CAJON | C96: LEC MORADA | D96: 12000 | E96: =A96*D96 -> 12000 | I96: 7000 | J96: =I96*A96 -> 7000 | K96: =E96-J96 -> 5000
A97: 1 | B97: BANDEJA | C97: BROTE | D97: 2500 | E97: =A97*D97 -> 2500 | I97: 1500 | J97: =I97*A97 -> 1500 | K97: =E97-J97 -> 1000
A98: 1 | B98: ATADO | C98: PEREJIL | D98: 4000 | E98: =A98*D98 -> 4000 | I98: 2000 | J98: =I98*A98 -> 2000 | K98: =E98-J98 -> 2000
A99: 3 | B99: KG | C99: TOM PERITA | D99: 2800 | E99: =A99*D99 -> 8400 | I99: 2000 | J99: =I99*A99 -> 6000 | K99: =E99-J99 -> 2400
A100: 1 | B100: CAJON | C100: ESPINACA | D100: 22000 | E100: =A100*D100 -> 22000 | I100: 18000 | J100: =I100*A100 -> 18000 | K100: =E100-J100 -> 4000
A101: 1 | B101: KG | C101: ZANAHORIA | D101: 1800 | E101: =A101*D101 -> 1800 | I101: =13000/9 -> 1444.4444 | J101: =I101*A101 -> 1444.4444 | K101: =E101-J101 -> 355.55556
A102: 1 | B102: ATADO | C102: TOMILLO | D102: 3000 | E102: =A102*D102 -> 3000 | I102: 2000 | J102: =I102*A102 -> 2000 | K102: =E102-J102 -> 1000
A103: 1 | B103: CAJON | C103: MORRON ROJO | D103: 20000 | E103: =A103*D103 -> 20000 | I103: 12000 | J103: =I103*A103 -> 12000 | K103: =E103-J103 -> 8000
A104: 1 | B104: CAJA | C104: LIMON | D104: 46000 | E104: =A104*D104 -> 46000 | I104: 40000 | J104: =I104*A104 -> 40000 | K104: =E104-J104 -> 6000
A105: 0.5 | B105: CAJON | C105: NARANJA | D105: 22000 | E105: =A105*D105 -> 11000 | I105: 18000 | J105: =I105*A105 -> 9000 | K105: =E105-J105 -> 2000
E107: =SUM(E91:E105) -> 256900 | K107: =SUM(K91:K105) -> 56288.889 | L107: =K107/E107 -> 0.21910817
A111: AUPA | D111: rto: 2 | E111: 46034
A113: CANTIDAD | B113: UNIDAD | C113: PRODUCTO | D113: PRECIO | E113: TOTAL | I113: PRECIO | J113: TOTAL | K113: DIFERENCIA
A114: 12 | B114: KG | C114: TOMATE | D114: 2700 | E114: =A114*D114 -> 32400 | I114: 2000 | J114: =I114*A114 -> 24000 | K114: =E114-J114 -> 8400
A115: 2 | B115: KG | C115: LECHUGA | D115: 3500 | E115: =A115*D115 -> 7000 | I115: 3000 | J115: =I115*A115 -> 6000 | K115: =E115-J115 -> 1000
A116: 1 | B116: BOLSA | C116: ZANAHORIA | D116: 16000 | E116: =A116*D116 -> 16000 | I116: 13000 | J116: =I116*A116 -> 13000 | K116: =E116-J116 -> 3000
A117: 2 | B117: CAJA | C117: BANANA | D117: 44000 | E117: =A117*D117 -> 88000 | I117: 30000 | J117: =I117*A117 -> 60000 | K117: =E117-J117 -> 28000
A118: 2 | B118: BOLSA | C118: ANCO | D118: 18000 | E118: =A118*D118 -> 36000 | I118: 15000 | J118: =I118*A118 -> 30000 | K118: =E118-J118 -> 6000
A119: 7.1 | B119: KG | C119: SANDIA | D119: 1000 | E119: =A119*D119 -> 7100 | I119: 600 | J119: =I119*A119 -> 4260 | K119: =E119-J119 -> 2840
A120: 1 | B120: KG | C120: LIMON | D120: 3200 | E120: =A120*D120 -> 3200 | I120: =40000/15 -> 2666.6667 | J120: =I120*A120 -> 2666.6667 | K120: =E120-J120 -> 533.33333
E122: =SUM(E114:E121) -> 189700 | K122: =SUM(K114:K120) -> 49773.333 | L122: =K122/E122 -> 0.2623792
A126: BRASOV | D126: rto: 3 | E126: 46034
A128: CANTIDAD | B128: UNIDAD | C128: PRODUCTO | D128: PRECIO | E128: TOTAL | I128: PRECIO | J128: TOTAL | K128: DIFERENCIA
A129: 1 | B129: CAJA | C129: LIMON | D129: 46000 | E129: =A129*D129 -> 46000 | I129: 40000 | J129: =I129*A129 -> 40000 | K129: =E129-J129 -> 6000
A130: 1 | B130: BOLSA | C130: ANCO | D130: 18000 | E130: =A130*D130 -> 18000 | I130: 15000 | J130: =I130*A130 -> 15000 | K130: =E130-J130 -> 3000
A131: 1 | B131: CAJA | C131: PALTA | D131: 60000 | E131: =A131*D131 -> 60000 | I131: 45000 | J131: =I131*A131 -> 45000 | K131: =E131-J131 -> 15000
A132: 1.5 | B132: KG | C132: LIMA | D132: 3500 | E132: =A132*D132 -> 5250 | I132: 2500 | J132: =I132*A132 -> 3750 | K132: =E132-J132 -> 1500
...

Sheet 13-01-2026 
A3: FV | E3: rto: 216 | F3: 46035 | I3: COMPRA
A5: CANTIDAD | B5: UNIDAD | C5: PRODUCTO | D5: PRECIO | E5: TOTAL | F5: TOTAL + IVA | I5: PRECIO | J5: TOTAL | K5: DIFERENCIA
A6: 2 | B6: CAJON | C6: TOMATE | D6: 32000 | E6: =A6*D6 -> 64000 | F6: =E6*1.105 -> 70720 | I6: =55000/2 -> 27500 | J6: =I6*A6 -> 55000 | K6: =F6-J6 -> 15720
A7: 2 | B7: CAJON | C7: TOM CHERRY | D7: 30000 | E7: =A7*D7 -> 60000 | F7: =E7*1.105 -> 66300 | I7: 15000 | J7: =I7*A7 -> 30000 | K7: =F7-J7 -> 36300
A8: 1 | B8: CAJON | C8: BERENJENA | D8: 13000 | E8: =A8*D8 -> 13000 | F8: =E8*1.105 -> 14365 | I8: 8000 | J8: =I8*A8 -> 8000 | K8: =F8-J8 -> 6365
A9: 3 | B9: CAJA | C9: CIRUELA | D9: 32000 | E9: =A9*D9 -> 96000 | F9: =E9*1.105 -> 106080 | I9: 25000 | J9: =I9*A9 -> 75000 | K9: =F9-J9 -> 31080
A10: 1 | B10: CAJON | C10: NARANJA | D10: 22000 | E10: =A10*D10 -> 22000 | F10: =E10*1.105 -> 24310 | I10: 18000 | J10: =I10*A10 -> 18000 | K10: =F10-J10 -> 6310
A11: 2 | B11: CAJON | C11: MELON | D11: 28000 | E11: =A11*D11 -> 56000 | F11: =E11*1.105 -> 61880 | I11: 25000 | J11: =I11*A11 -> 50000 | K11: =F11-J11 -> 11880
A12: 1 | B12: CAJA | C12: MANZANA GRANNY | D12: 70000 | E12: =A12*D12 -> 70000 | F12: =E12*1.105 -> 77350 | I12: 44000 | J12: =I12*A12 -> 44000 | K12: =F12-J12 -> 33350
A13: 2 | B13: CAJA | C13: BANANA | D13: 38000 | E13: =A13*D13 -> 76000 | F13: =E13*1.105 -> 83980 | I13: 30000 | J13: =I13*A13 -> 60000 | K13: =F13-J13 -> 23980
A14: 1 | B14: CAJA | C14: DURAZNO | D14: 35000 | E14: =A14*D14 -> 35000 | F14: =E14*1.105 -> 38675 | I14: 30000 | J14: =I14*A14 -> 30000 | K14: =F14-J14 -> 8675
A15: 1 | B15: CAJON | C15: UVA | D15: 32000 | E15: =A15*D15 -> 32000 | F15: =E15*1.105 -> 35360 | I15: 27000 | J15: =I15*A15 -> 27000 | K15: =F15-J15 -> 8360
A16: 41.9 | B16: KG | C16: SANDIA | D16: 1200 | E16: =A16*D16 -> 50280 | F16: =E16*1.105 -> 55559.4 | I16: 0 | J16: =I16*A16 -> 0 | K16: =F16-J16 -> 55559.4
A17: 1 | B17: CAJON | C17: TOMATE | D17: 32000 | E17: =A17*D17 -> 32000 | F17: =E17*1.105 -> 35360 | G17: BOLSA | I17: 0 | J17: =I17*A17 -> 0 | K17: =F17-J17 -> 35360
A18: 1 | B18: CAJON | C18: TOM CHERRY | D18: 30000 | E18: =A18*D18 -> 30000 | F18: =E18*1.105 -> 33150 | G18: BOLSA | I18: 0 | J18: =I18*A18 -> 0 | K18: =F18-J18 -> 33150
A19: 1 | B19: CAJON | C19: BERENJENA | D19: 13000 | E19: =A19*D19 -> 13000 | F19: =E19*1.105 -> 14365 | G19: BOLSA | I19: 0 | J19: =I19*A19 -> 0 | K19: =F19-J19 -> 14365
E21: =SUM(E6:E19) -> 649280 | F21: =SUM(F6:F19) -> 717454.4 | K21: =SUM(K6:K19) -> 320454.4 | L21: =K21/F21 -> 0.44665473
A24: RAKUS | D24: rto: 14 | E24: 46035
A26: CANTIDAD | B26: UNIDAD | C26: PRODUCTO | D26: PRECIO | E26: TOTAL | I26: PRECIO | J26: TOTAL | K26: DIFERENCIA
A27: 1 | B27: BANDEJA | C27: FLORES | D27: 5500 | E27: =A27*D27 -> 5500 | I27: 4000 | J27: =I27*A27 -> 4000 | K27: =E27-J27 -> 1500
A28: 3 | B28: KG | C28: LEC CRIOLLA | D28: 4000 | E28: =A28*D28 -> 12000 | I28: =15000/5 -> 3000 | J28: =I28*A28 -> 9000 | K28: =E28-J28 -> 3000
A29: 1 | B29: ATADOS | C29: ROMERO | D29: 3000 | E29: =A29*D29 -> 3000 | I29: 2000 | J29: =I29*A29 -> 2000 | K29: =E29-J29 -> 1000
A30: 1 | B30: ATADOS | C30: TOMILLO | D30: 3000 | E30: =A30*D30 -> 3000 | I30: 2000 | J30: =I30*A30 -> 2000 | K30: =E30-J30 -> 1000
A31: 1 | B31: CAJON | C31: HUEVO | D31: 55000 | E31: =A31*D31 -> 55000 | I31: 45000 | J31: =I31*A31 -> 45000 | K31: =E31-J31 -> 10000
A32: 1 | B32: KG | C32: CHAMPI | D32: 18500 | E32: =A32*D32 -> 18500 | I32: 16000 | J32: =I32*A32 -> 16000 | K32: =E32-J32 -> 2500
A33: 1 | B33: KG | C33: TOM CHERRY | D33: 3000 | E33: =A33*D33 -> 3000 | I33: =15000/8 -> 1875 | J33: =I33*A33 -> 1875 | K33: =E33-J33 -> 1125
A34: 1 | B34: CAJA | C34: PALTA CHILE | D34: 75000 | E34: =A34*D34 -> 75000 | I34: 65000 | J34: =I34*A34 -> 65000 | K34: =E34-J34 -> 10000
A35: 16 | B35: ATADOS | C35: ALBAHACA | D35: 1000 | E35: =A35*D35 -> 16000 | I35: =6000/12 -> 500 | J35: =I35*A35 -> 8000 | K35: =E35-J35 -> 8000
A36: 10 | B36: UNIDAD | C36: AJO | D36: 1200 | E36: =A36*D36 -> 12000 | I36: 560 | J36: =I36*A36 -> 5600 | K36: =E36-J36 -> 6400
A37: 1 | B37: ATADOS | C37: CEB VERDEO | D37: 5000 | E37: =A37*D37 -> 5000 | I37: 4000 | J37: =I37*A37 -> 4000 | K37: =E37-J37 -> 1000
A38: 1 | B38: KG | C38: CEB MORADA | D38: 1600 | E38: =A38*D38 -> 1600 | I38: 1600 | J38: =I38*A38 -> 1600 | K38: =E38-J38 -> 0
A39: 1 | B39: BOLSA | C39: CEBOLLON | D39: 13000 | E39: =A39*D39 -> 13000 | I39: 9000 | J39: =I39*A39 -> 9000 | K39: =E39-J39 -> 4000
A40: 1 | B40: CAJON | C40: FRUTILLA | D40: 22000 | E40: =A40*D40 -> 22000 | I40: 20000 | J40: =I40*A40 -> 20000 | K40: =E40-J40 -> 2000
A41: 2 | B41: KG | C41: MORRON ROJO | D41: 2300 | E41: =A41*D41 -> 4600 | I41: =12000/8 -> 1500 | J41: =I41*A41 -> 3000 | K41: =E41-J41 -> 1600
A42: 1 | B42: BOLSA | C42: PAPA CEPILLADA | D42: 14000 | E42: =A42*D42 -> 14000 | I42: 12000 | J42: =I42*A42 -> 12000 | K42: =E42-J42 -> 2000
A43: 1 | B43: ATADOS | C43: REMOLACHA | D43: 2000 | E43: =A43*D43 -> 2000 | I43: 1500 | J43: =I43*A43 -> 1500 | K43: =E43-J43 -> 500
A44: 1 | B44: BOLSA | C44: ZANAHORIA | D44: 13000 | E44: =A44*D44 -> 13000 | I44: 10000 | J44: =I44*A44 -> 10000 | K44: =E44-J44 -> 3000
A45: 0.5 | B45: KG | C45: JENGIBRE | D45: 6500 | E45: =A45*D45 -> 3250 | I45: 5000 | J45: =I45*A45 -> 2500 | K45: =E45-J45 -> 750
A46: 2 | B46: CAJON | C46: NARANJA | D46: 22000 | E46: =A46*D46 -> 44000 | I46: 18000 | J46: =I46*A46 -> 36000 | K46: =E46-J46 -> 8000
A47: 1 | B47: CAJA | C47: LIMON | D47: 44000 | E47: =A47*D47 -> 44000 | I47: 35000 | J47: =I47*A47 -> 35000 | K47: =E47-J47 -> 9000
A48: 2 | B48: KG | C48: LIMA | D48: 4000 | E48: =A48*D48 -> 8000 | I48: 3000 | J48: =I48*A48 -> 6000 | K48: =E48-J48 -> 2000
E50: =SUM(E27:E48) -> 377450 | K50: =SUM(K27:K48) -> 78375 | L50: =K50/E50 -> 0.2076434
A54: MUNCHIS | D54: rto: 1 | E54: 46035
A56: CANTIDAD | B56: UNIDAD | C56: PRODUCTO | D56: PRECIO | E56: TOTAL | F56: TOTAL + IVA | I56: PRECIO | J56: TOTAL | K56: DIFERENCIA
A57: 0.56 | B57: KG | C57: LEC MORADA | D57: 4000 | E57: =A57*D57 -> 2240 | F57: =E57*1.105 -> 2475.2 | I57: 3000 | J57: =I57*A57 -> 1680 | K57: =F57-J57 -> 795.2
A58: 0.5 | B58: KG | C58: LEC CRIOLLA | D58: 4000 | E58: =A58*D58 -> 2000 | F58: =E58*1.105 -> 2210 | I58: 3000 | J58: =I58*A58 -> 1500 | K58: =F58-J58 -> 710
A59: 2 | B59: KG | C59: TOM CHERRY | D59: 3000 | E59: =A59*D59 -> 6000 | F59: =E59*1.105 -> 6630 | I59: 1875 | J59: =I59*A59 -> 3750 | K59: =F59-J59 -> 2880
A60: 3 | B60: KG | C60: BANANA | D60: 3000 | E60: =A60*D60 -> 9000 | F60: =E60*1.105 -> 9945 | I60: 0 | J60: =I60*A60 -> 0 | K60: =F60-J60 -> 9945
A61: 1 | B61: KG | C61: KIWI | D61: 12500 | E61: =A61*D61 -> 12500 | F61: =E61*1.105 -> 13812.5 | I61: =70000/7 -> 10000 | J61: =I61*A61 -> 10000 | K61: =F61-J61 -> 3812.5
A62: 2 | B62: KG | C62: FRUTILLA | D62: 6000 | E62: =A62*D62 -> 12000 | F62: =E62*1.105 -> 13260 | I62: 0 | J62: =I62*A62 -> 0 | K62: =F62-J62 -> 13260
A63: 3 | B63: KG | C63: NARANJA | D63: 1600 | E63: =A63*D63 -> 4800 | F63: =E63*1.105 -> 5304 | I63: =18000/15 -> 1200 | J63: =I63*A63 -> 3600 | K63: =F63-J63 -> 1704
A64: 1 | B64: ATADO | C64: MENTA | D64: 3000 | E64: =A64*D64 -> 3000 | F64: =E64*1.105 -> 3315 | I64: 2000 | J64: =I64*A64 -> 2000 | K64: =F64-J64 -> 1315
A65: 0.2 | B65: KG | C65: JENGIBRE | D65: 6500 | E65: =A65*D65 -> 1300 | F65: =E65*1.105 -> 1436.5 | I65: 5000 | J65: =I65*A65 -> 1000 | K65: =F65-J65 -> 436.5
A66: 4 | B66: KG | C66: LIMON | D66: 3300 | E66: =A66*D66 -> 13200 | F66: =E66*1.105 -> 14586 | I66: =35000/15 -> 2333.3333 | J66: =I66*A66 -> 9333.3333 | K66: =F66-J66 -> 5252.6667
A67: 1 | B67: MAPLE | C67: HUEVO | D67: 4500 | E67: =A67*D67 -> 4500 | F67: =E67*1.21 -> 5445 | I67: =38000/12 -> 3166.6667 | J67: =I67*A67 -> 3166.6667 | K67: =F67-J67 -> 2278.3333
E69: =SUM(E57:E67) -> 70540 | F69: =SUM(F57:F67) -> 78419.2 | K69: =SUM(K57:K67) -> 42389.2 | L69: =K69/E69 -> 0.6009243
A73: BRASOV | D73: rto: 4 | E73: 46035
A75: CANTIDAD | B75: UNIDAD | C75: PRODUCTO | D75: PRECIO | E75: TOTAL | I75: PRECIO | J75: TOTAL | K75: DIFERENCIA
A76: 2.1 | B76: KG | C76: PEPINO | D76: 1800 | E76: =A76*D76 -> 3780 | I76: 1500 | J76: =I76*A76 -> 3150 | K76: =E76-J76 -> 630
A77: 1 | B77: CAJON | C77: NARANJA | D77: 22000 | E77: =A77*D77 -> 22000 | I77: 18000 | J77: =I77*A77 -> 18000 | K77: =E77-J77 -> 4000
A78: 1 | B78: CAJA | C78: LIMON | D78: 46000 | E78: =A78*D78 -> 46000 | I78: 35000 | J78: =I78*A78 -> 35000 | K78: =E78-J78 -> 11000
A79: 4 | B79: ATADO | C79: CEB VERDEO | D79: 5000 | E79: =A79*D79 -> 20000 | I79: 4000 | J79: =I79*A79 -> 16000 | K79: =E79-J79 -> 4000
A80: 2 | B80: ATADO | C80: PEREJIL | D80: 4000 | E80: =A80*D80 -> 8000 | I80: 2000 | J80: =I80*A80 -> 4000 | K80: =E80-J80 -> 4000
A81: 1 | B81: CAJON | C81: MORRON ROJO | D81: 20000 | E81: =A81*D81 -> 20000 | I81: 12000 | J81: =I81*A81 -> 12000 | K81: =E81-J81 -> 8000
A82: 2 | B82: ATADO | C82: CIBOULLETE | D82: 3000 | E82: =A82*D82 -> 6000 | I82: 2000 | J82: =I82*A82 -> 4000 | K82: =E82-J82 -> 2000
E84: =SUM(E76:E82) -> 125780 | K84: =SUM(K76:K82) -> 33630 | L84: =K84/E84 -> 0.2673716
A88: TOTAL DIA | B88: =E84+F69+E50+F21 -> 1299103.6
A90: GANANCIA | B90: =K84+K69+K50+K21 -> 474848.6
A92: % | B92: =B90/B88 -> 0.36552019
A94: BULTOS COMPRADOS | C94: 27
B99: EFECTIVO | C99: MERCADO PAGO | D99: BANCO GALCIA | E99: BANCO RIO | F99: CHEQUES
B100: ='12-01-2026 '!B196 -> 2928150 | C100: ='12-01-2026 '!C196 -> 644038.69 | D100: ='12-01-2026 '!D196 -> 346400.11 | F100: ='12-01-2026 '!F196 -> 2642589.7
A102: INGRESOS
A103: COBR. CTA. CTE | B103: 0 | C103: 443900 | D103: =239533.21+500000 -> 739533.21 | E103: 0 | F103: 0
A104: RENDIMIENTO MP | B104: 0 | C104: 0 | D104: 0 | E104: 0 | F104: 0
A105: CHE ACREDITADO | B105: 0 | C105: 0 | D105: 0 | E105: 0 | F105: 0
A106: COBR. VACIOS | B106: 0 | C106: 0 | D106: 0 | E106: 0 | F106: 0
A107: PRESTAMOS | B107: 0 | C107: 0 | D107: 0 | E107: 0 | F107: 0
A108: IMP. IIBB. 2% | B108: 0 | C108: =C103*2% -> 8878 | D108: =SUM(D102:D103)*2% -> 14790.664 | E108: 0 | F108: 0
A109: IMP. CRED. 0,6% | B109: 0 | C109: =C103*0.6%+C106*0.6% -> 2663.4 | D109: =SUM(D103:D105)*0.6% -> 4437.1993 | E109: 0 | F109: 0
A111: TOTAL | B111: =SUM(B100:B109) -> 2928150 | C111: =C100+C103+C106+C107-C109+C104-C108 -> 1076397.3 | D111: =D100+D103+D106+D107-D109+D105-D108 -> 1066705.5 | E111: =E100+E103+E106+E107-E109 -> 0 | F111: =F100+F103+F106+F107-F109-D105 -> 2642589.7
A113: GASTOS
A114: ING. MERCADO | B114: 1000 | C114: 0 | D114: 0 | E114: 0
A115: CARGA / VACIOS | B115: 0 | C115: 0 | D115: 0 | E115: 0
A116: CHEQ DEBITADO | B116: 0 | C116: 0 | D116: 400000 | E116: 0
A117: PEAJE | B117: 2800 | C117: 0 | D117: 0 | E117: 0
A118: MERCADERIA | B118: 0 | C118: =584760+16030 -> 600790 | D118: 0 | E118: 0
A119: COMBUSTIBLE | B119: 0 | C119: 45000 | D119: 0 | E119: 0
A120: SUELDOS | B120: 0 | C120: 0 | D120: 0 | E120: 0
A121: DEV. PRESTAMOS | B121: 0 | C121: 0 | D121: 0 | E121: 0
A122: AGUA | B122: 0 | C122: 0 | D122: 0 | E122: 0
A123: FLETE JUAN | B123: 0 | C123: 40000 | D123: 0 | E123: 0
A124: RETIRO JOAQUIN | B124: 0 | C124: 0 | D124: 0 | E124: 0
A125: RETIRO FEDERICO | B125: 0 | C125: 30000 | D125: 0 | E125: 0
A126: ALQUILER LOCAL | B126: 0 | C126: 0 | D126: 0 | E126: 0
A127: CONTADOR | B127: 0 | C127: 0 | D127: 0 | E127: 0
A128: ACEITE/AGUA CHATA | B128: 0 | C128: 23000 | D128: 0 | E128: 0
A129: REMIS | B129: 0 | C129: 0 | D129: 0 | E129: 0
A130: MECANICO | B130: 0 | C130: 0 | D130: 0 | E130: 0
... A139: MANT. CTA. | B139: 0 | C139: 0 | D139: 0 | E139: 0
...

Sheet 14-01-2026 
A3: FV | E3: rto: 217 | F3: 46036 | I3: COMPRA
A5: CANTIDAD | B5: UNIDAD | C5: PRODUCTO | D5: PRECIO | E5: TOTAL | F5: TOTAL + IVA | I5: PRECIO | J5: TOTAL | K5: DIFERENCIA
A6: 5 | B6: CAJON | C6: NARANJA | D6: 22000 | E6: =A6*D6 -> 110000 | F6: =E6*1.105 -> 121550 | I6: 18000 | J6: =I6*A6 -> 90000 | K6: =F6-J6 -> 31550
A7: 2 | B7: CAJA | C7: MANZANA GRANNY | D7: 70000 | E7: =A7*D7 -> 140000 | F7: =E7*1.105 -> 154700 | I7: 42000 | J7: =I7*A7 -> 84000 | K7: =F7-J7 -> 70700
A8: 1 | B8: CAJA | C8: BANANA | D8: 38000 | E8: =A8*D8 -> 38000 | F8: =E8*1.105 -> 41990 | I8: 30000 | J8: =I8*A8 -> 30000 | K8: =F8-J8 -> 11990
A9: 1 | B9: CAJON | C9: NARANJA | D9: 22000 | E9: =A9*D9 -> 22000 | F9: =E9*1.105 -> 24310 | G9: BOLSA | I9: 0 | J9: =I9*A9 -> 0 | K9: =F9-J9 -> 24310
A10: 1 | B10: CAJA | C10: MANZANA GRANNY | D10: 70000 | E10: =A10*D10 -> 70000 | F10: =E10*1.105 -> 77350 | G10: BOLSA | I10: 0 | J10: =I10*A10 -> 0 | K10: =F10-J10 -> 77350
E12: =SUM(E6:E10) -> 380000 | F12: =SUM(F6:F10) -> 419900 | K12: =SUM(K6:K10) -> 215900 | L12: =K12/F12 -> 0.51417004
A15: HOGAR | D15: rto: 2 | E15: 46036
A17: CANTIDAD | B17: UNIDAD | C17: PRODUCTO | D17: PRECIO | E17: TOTAL | I17: PRECIO | J17: TOTAL | K17: DIFERENCIA
A18: 1 | B18: UNIDAD | C18: APIO | D18: 1500 | E18: =A18*D18 -> 1500 | I18: 1600 | J18: =I18*A18 -> 1600 | K18: =E18-J18 -> -100
A19: 3 | B19: UNIDAD | C19: AJO | D19: 1200 | E19: =A19*D19 -> 3600 | I19: 560 | J19: =I19*A19 -> 1680 | K19: =E19-J19 -> 1920
A20: 4 | B20: KG | C20: BATATA | D20: 1500 | E20: =A20*D20 -> 6000 | I20: 1100 | J20: =I20*A20 -> 4400 | K20: =E20-J20 -> 1600
A21: 4 | B21: KG | C21: BONIATO | D21: 3800 | E21: =A21*D21 -> 15200 | I21: 2500 | J21: =I21*A21 -> 10000 | K21: =E21-J21 -> 5200
A22: 4 | B22: KG | C22: BERENJENA | D22: 1600 | E22: =A22*D22 -> 6400 | I22: =9000/8 -> 1125 | J22: =I22*A22 -> 4500 | K22: =E22-J22 -> 1900
A23: 3 | B23: KG | C23: TOMATE CHERRY | D23: 2800 | E23: =A23*D23 -> 8400 | I23: =15000/8 -> 1875 | J23: =I23*A23 -> 5625 | K23: =E23-J23 -> 2775
A24: 4 | B24: ATADO | C24: ESPINACA | D24: 1700 | E24: =A24*D24 -> 6800 | I24: =7200/4 -> 1800 | J24: =I24*A24 -> 7200 | K24: =E24-J24 -> -400
A25: 2 | B25: KG | C25: MORRÓN ROJO | D25: 3000 | E25: =A25*D25 -> 6000 | I25: =12000/8 -> 1500 | J25: =I25*A25 -> 3000 | K25: =E25-J25 -> 3000
A26: 1 | B26: KG | C26: LECHUGA | D26: 3500 | E26: =A26*D26 -> 3500 | I26: 3000 | J26: =I26*A26 -> 3000 | K26: =E26-J26 -> 500
A27: 2 | B27: UNIDAD | C27: PALTA | D27: 1300 | E27: =A27*D27 -> 2600 | I27: =65000/80 -> 812.5 | J27: =I27*A27 -> 1625 | K27: =E27-J27 -> 975
A28: 0.5 | B28: ATADOS | C28: PEREJIL | D28: 3500 | E28: =A28*D28 -> 1750 | I28: 2000 | J28: =I28*A28 -> 1000 | K28: =E28-J28 -> 750
A29: 6 | B29: ATADOS | C29: REMOLACHA | D29: 2000 | E29: =A29*D29 -> 12000 | I29: 1400 | J29: =I29*A29 -> 8400 | K29: =E29-J29 -> 3600
A30: 4 | B30: ATADO | C30: RÚCULA | D30: 500 | E30: =A30*D30 -> 2000 | I30: 350 | J30: =I30*A30 -> 1400 | K30: =E30-J30 -> 600
A31: 4 | B31: KG | C31: TOMATE | D31: 2000 | E31: =A31*D31 -> 8000 | I31: =28000/15 -> 1866.6667 | J31: =I31*A31 -> 7466.6667 | K31: =E31-J31 -> 533.33333
A32: 4 | B32: KG | C32: ZAPALLITO | D32: 900 | E32: =A32*D32 -> 3600 | I32: =18000/14 -> 1285.7143 | J32: =I32*A32 -> 5142.8571 | K32: =E32-J32 -> -1542.8571
A33: 2 | B33: KG | C33: ZUCCINI | D33: 1000 | E33: =A33*D33 -> 2000 | I33: 2000 | J33: =I33*A33 -> 4000 | K33: =E33-J33 -> -2000
A34: 1 | B34: BOLSA | C34: ANCO | D34: 12000 | E34: =A34*D34 -> 12000 | I34: 9000 | J34: =I34*A34 -> 9000 | K34: =E34-J34 -> 3000
A35: 0.5 | B35: BOLSA | C35: CEBOLLA | D35: 13000 | E35: =A35*D35 -> 6500 | I35: 9000 | J35: =I35*A35 -> 4500 | K35: =E35-J35 -> 2000
A36: 1 | B36: BOLSA | C36: PAPA | D36: 14000 | E36: =A36*D36 -> 14000 | I36: 13000 | J36: =I36*A36 -> 13000 | K36: =E36-J36 -> 1000
A37: 1 | B37: BOLSA | C37: ZANAHORIA | D37: 13000 | E37: =A37*D37 -> 13000 | I37: 12000 | J37: =I37*A37 -> 12000 | K37: =E37-J37 -> 1000
A38: 1 | B38: CAJON | C38: HUEVO | D38: 50000 | E38: =A38*D38 -> 50000 | I38: 38000 | J38: =I38*A38 -> 38000 | K38: =E38-J38 -> 12000
A39: 1 | B39: CAJA | C39: BANANA | D39: 40000 | E39: =A39*D39 -> 40000 | I39: 30000 | J39: =I39*A39 -> 30000 | K39: =E39-J39 -> 10000
A40: 2 | B40: KG | C40: CIRUELA | D40: 4000 | E40: =A40*D40 -> 8000 | J40: =I40*A40 -> 0 | K40: =E40-J40 -> 8000
A41: 3 | B41: KG | C41: DURAZNO | D41: 4000 | E41: =A41*D41 -> 12000 | J41: =I41*A41 -> 0 | K41: =E41-J41 -> 12000
A42: 0.5 | B42: KG | C42: KIWI | D42: 12000 | E42: =A42*D42 -> 6000 | J42: =I42*A42 -> 0 | K42: =E42-J42 -> 6000
A43: 3 | B43: KG | C43: LIMÓN | D43: 3000 | E43: =A43*D43 -> 9000 | I43: =35000/15 -> 2333.3333 | J43: =I43*A43 -> 7000 | K43: =E43-J43 -> 2000
A44: 4 | B44: KG | C44: MANZANA VERDE | D44: 5000 | E44: =A44*D44 -> 20000 | I44: =40000/18 -> 2222.2222 | J44: =I44*A44 -> 8888.8889 | K44: =E44-J44 -> 11111.111
A45: 7 | B45: KG | C45: NARANJA | D45: 1600 | E45: =A45*D45 -> 11200 | I45: =18000/15 -> 1200 | J45: =I45*A45 -> 8400 | K45: =E45-J45 -> 2800
A46: 2 | B46: UNIDAD | C46: MELON | D46: 4000 | E46: =A46*D46 -> 8000 | I46: 5000 | J46: =I46*A46 -> 10000 | K46: =E46-J46 -> -2000
A47: 12 | B47: KG | C47: SANDÍA | D47: 1200 | E47: =A47*D47 -> 14400 | I47: 600 | J47: =I47*A47 -> 7200 | K47: =E47-J47 -> 7200
A48: 2 | B48: KG | C48: UVA | D48: 3500 | E48: =A48*D48 -> 7000 | J48: =I48*A48 -> 0 | K48: =E48-J48 -> 7000
E50: =SUM(E18:E48) -> 320450 | K50: =SUM(K18:K48) -> 102421.59 | L50: =K50/E50 -> 0.319618
A54: AUPA | D54: rto: 3 | E54: 46035
A56: CANTIDAD | B56: UNIDAD | C56: PRODUCTO | D56: PRECIO | E56: TOTAL | I56: PRECIO | J56: TOTAL | K56: DIFERENCIA
A57: 5 | B57: MAPLE | C57: HUEVO | D57: 4500 | E57: =A57*D57 -> 22500 | I57: =38000/12 -> 3166.6667 | J57: =I57*A57 -> 15833.333 | K57: =E57-J57 -> 6666.6667
A58: 6 | B58: KG | C58: ZAPALLITO | D58: 1200 | E58: =A58*D58 -> 7200 | I58: =18000/15 -> 1200 | J58: =I58*A58 -> 7200 | K58: =E58-J58 -> 0
E60: =SUM(E57:E58) -> 29700 | K60: =SUM(K57:K58) -> 6666.6667 | L60: =K60/E60 -> 0.22446689
A64: TOTAL DIA | B64: =E60+E50+F12 -> 770050
A66: GANANCIA | B66: =K60+K50+K12 -> 324988.25
A68: % | B68: =B66/B64 -> 0.42203526
A70: BULTOS COMPRADOS | C70: 22
B75: EFECTIVO | C75: MERCADO PAGO | D75: BANCO GALCIA | E75: BANCO RIO | F75: CHEQUES
B76: ='13-01-2026 '!B146 -> 2924350 | C76: ='13-01-2026 '!C146 -> 65221.701 | D76: ='13-01-2026 '!D146 -> 732847.35 | E76: ='13-01-2026 '!E146 -> 0 | F76: ='13-01-2026 '!F146 -> 2642589.7
A78: INGRESOS
A79: COBR. CTA. CTE | B79: 0 | C79: 0 | D79: 0 | E79: 0 | F79: 0
A80: RENDIMIENTO MP | B80: 0 | C80: 76.53 | D80: 0 | E80: 0 | F80: 0
A81: CHE ACREDITADO | B81: 0 | C81: 0 | D81: 0 | E81: 0 | F81: 0
A82: COBR. VACIOS | B82: 0 | C82: 0 | D82: 0 | E82: 0 | F82: 0
A83: PRESTAMOS | B83: 0 | C83: 0 | D83: 0 | E83: 0 | F83: 0
A84: IMP. IIBB. 2% | B84: 0 | C84: =C79*2% -> 0 | D84: 0 | E84: 0 | F84: 0
A85: IMP. CRED. 0,6% | B85: 0 | C85: =C79*0.6%+C82*0.6% -> 0 | D85: =SUM(D79:D81)*0.6% -> 0 | E85: 0 | F85: 0
A87: TOTAL | B87: =SUM(B76:B85) -> 2924350 | C87: =C76+C79+C82+C83-C85+C80-C84 -> 65298.231 | D87: =D76+D79+D82+D83-D85+D81 -> 732847.35 | E87: =E76+E79+E82+E83-E85 -> 0 | F87: =F76+F79+F82+F83-F85-D81 -> 2642589.7
A89: GASTOS
A90: ING. MERCADO | B90: 1000 | C90: 0 | D90: 0 | E90: 0
A91: CARGA / VACIOS | C91: 0 | D91: 0 | E91: 0
A92: CHEQ DEBITADO | C92: 0 | D92: 0 | E92: 0
A93: PEAJE | B93: 2800 | C93: 0 | D93: 0 | E93: 0
A94: MERCADERIA | C94: =7350+132000 -> 139350 | D94: 0 | E94: 0
A95: COMBUSTIBLE | C95: 40000 | D95: 0 | E95: 0
A96: SUELDOS | B96: 0 | C96: 0 | D96: 0 | E96: 0
A97: DEV. PRESTAMOS | B97: 0 | C97: 0 | D97: 0 | E97: 0
A98: AGUA | B98: 0 | C98: 0 | D98: 0 | E98: 0
A99: FLETE JUAN | B99: 0 | C99: 0 | D99: 0 | E99: 0
A100: RETIRO JOAQUIN | B100: 0 | C100: 0 | D100: 0 | E100: 0
A101: RETIRO FEDERICO | B101: 0 | C101: 0 | D101: 0 | E101: 0
A102: ALQUILER LOCAL | B102: 0 | C102: 0 | D102: 0 | E102: 0
A103: CONTADOR | B103: 0 | C103: 0 | D103: 0 | E103: 0
A104: ACEITE/AGUA CHATA | B104: 0 | C104: 0 | D104: 0 | E104: 0
A105: REMIS | B105: 0 | C105: 0 | D105: 0 | E105: 0
A106: MECANICO | B106: 0 | C106: 0 | D106: 0 | E106: 0
A107: BOLSAS/LIMPIEZA | B107: 0 | C107: 0 | D107: 0 | E107: 0
... A115: MANT. CTA. | B115: 0 | C115: 0 | D115: 0 | E115: 0
A117: IMP. DEB. 0,6% | B117: 0 | C117: =SUM(C90:C114)*0.6% -> 1076.1 | D117: =SUM(D90:D114)*0.6%+(D118*0.6%) -> 900 | E117: =(E94*0.6%)+(E95*0.6%)+(E96*0.6%)+(E99*0.6%)+(E100*0.6%) -> 0
A118: PASE DE CUENTAS | B118: 0 | C118: =150000 -> 150000 | D118: 150000 | E118: =SUM(E91:E116)*0.6%+(E119*0.6%) -> 0
A120: TOTAL SALIDAS | B120: =SUM(B90:B119) -> 3800 | C120: =SUM(C90:C117) -> 180426.1 | D120: =SUM(D90:D118) -> 150900 | E120: =E101+E105+E117-E118 -> 0 | F120: =F94
A122: SALDOS | B122: =B87-B120 -> 2920550 | C122: =C87-C120+C118 -> 34872.131 | D122: =D87-D120 -> 581947.35 | E122: =E87-E120 -> 0 | F122: =F87-F120 -> 2642589.7
A124: fede | B124: =16000-B90-B93 -> 12200
A125: joaquin | B125: 2908350
B127: =SUM(B124:B125) -> 2920550

Sheet 15-01-2026 
A3: FV | E3: rto: 218 | F3: 46037 | I3: COMPRA
A5: CANTIDAD | B5: UNIDAD | C5: PRODUCTO | D5: PRECIO | E5: TOTAL | F5: TOTAL + IVA | I5: PRECIO | J5: TOTAL | K5: DIFERENCIA
A6: 2 | B6: CAJON | C6: TOM CHERRY | D6: 30000 | E6: =A6*D6 -> 60000 | F6: =E6*1.105 -> 66300 | I6: 30000 | J6: =I6*A6 -> 60000 | K6: =F6-J6 -> 6300
A7: 6 | B7: ATADO | C7: ALBAHACA | D7: 1000 | E7: =A7*D7 -> 6000 | F7: =E7*1.105 -> 6630 | I7: 500 | J7: =I7*A7 -> 3000 | K7: =F7-J7 -> 3630
A8: 2 | B8: CAJON | C8: TOMATE REDONDO | D8: 32000 | E8: =A8*D8 -> 64000 | F8: =E8*1.105 -> 70720 | I8: 25000 | J8: =I8*A8 -> 50000 | K8: =F8-J8 -> 20720
A9: 4 | B9: CAJA | C9: BANANA | D9: 38000 | E9: =A9*D9 -> 152000 | F9: =E9*1.105 -> 167960 | I9: 28000 | J9: =I9*A9 -> 112000 | K9: =F9-J9 -> 55960
A10: 4 | B10: CAJA | C10: DURAZNO | D10: 35000 | E10: =A10*D10 -> 140000 | F10: =E10*1.105 -> 154700 | I10: 30000 | J10: =I10*A10 -> 120000 | K10: =F10-J10 -> 34700
A11: 2 | B11: CAJA | C11: MANZANA GRANNY | D11: 70000 | E11: =A11*D11 -> 140000 | F11: =E11*1.105 -> 154700 | I11: 40000 | J11: =I11*A11 -> 80000 | K11: =F11-J11 -> 74700
A12: 1 | B12: CAJA | C12: UVA | D12: 32000 | E12: =A12*D12 -> 32000 | F12: =E12*1.105 -> 35360 | I12: 30000 | J12: =I12*A12 -> 30000 | K12: =F12-J12 -> 5360
A13: 1 | B13: CAJA | C13: CIRUELA | D13: 32000 | E13: =A13*D13 -> 32000 | F13: =E13*1.105 -> 35360 | I13: 35000 | J13: =I13*A13 -> 35000 | K13: =F13-J13 -> 360
A14: 1 | B14: CAJON | C14: TOMATE REDONDO | D14: 32000 | E14: =A14*D14 -> 32000 | F14: =E14*1.105 -> 35360 | G14: BOLSA | I14: 0 | J14: =I14*A14 -> 0 | K14: =F14-J14 -> 35360
A15: 1 | B15: CAJON | C15: CHERRY | D15: 30000 | E15: =A15*D15 -> 30000 | F15: =E15*1.105 -> 33150 | G15: BOLSA | I15: 0 | J15: =I15*A15 -> 0 | K15: =F15-J15 -> 33150
A16: 1 | B16: CAJA | C16: MANZANA GRANNY | D16: 70000 | E16: =A16*D16 -> 70000 | F16: =E16*1.105 -> 77350 | G16: BOLSA | I16: 0 | J16: =I16*A16 -> 0 | K16: =F16-J16 -> 77350
A17: 1 | B17: CAJA | C17: CIRUELA | D17: 32000 | E17: =A17*D17 -> 32000 | F17: =E17*1.105 -> 35360 | G17: BOLSA PROPIA | I17: 0 | J17: =I17*A17 -> 0 | K17: =F17-J17 -> 35360
E19: =SUM(E6:E17) -> 790000 | F19: =SUM(F6:F17) -> 872950 | K19: =SUM(K6:K17) -> 382950 | L19: =K19/F19 -> 0.43868492
A22: LA MARQUESA | D22: rto: 2 | E22: 46037
A24: CANTIDAD | B24: UNIDAD | C24: PRODUCTO | D24: PRECIO | E24: TOTAL | I24: PRECIO | J24: TOTAL | K24: DIFERENCIA
A25: 3 | B25: UNIDAD | C25: AJO | D25: 1000 | E25: =A25*D25 -> 3000 | I25: =560 -> 560 | J25: =I25*A25 -> 1680 | K25: =E25-J25 -> 1320
A26: 2 | B26: KG | C26: BANANA | D26: 3000 | E26: =A26*D26 -> 6000 | I26: 0 | J26: =I26*A26 -> 0 | K26: =E26-J26 -> 6000
A27: 4 | B27: CUBETA | C27: ARANDANO | D27: 2500 | E27: =A27*D27 -> 10000 | I27: =18000/12 -> 1500 | J27: =I27*A27 -> 6000 | K27: =E27-J27 -> 4000
A28: 0.5 | B28: KG | C28: CHAMPI | D28: 19000 | E28: =A28*D28 -> 9500 | I28: 16000 | J28: =I28*A28 -> 8000 | K28: =E28-J28 -> 1500
A29: 2 | B29: CAJON | C29: HUEVO | D29: 50000 | E29: =A29*D29 -> 100000 | I29: 38000 | J29: =I29*A29 -> 76000 | K29: =E29-J29 -> 24000
A30: 1 | B30: KG | C30: KIWI | D30: 13000 | E30: =A30*D30 -> 13000 | I30: 10000 | J30: =I30*A30 -> 10000 | K30: =E30-J30 -> 3000
A31: 2 | B31: KG | C31: LIMA | D31: 4000 | E31: =A31*D31 -> 8000 | I31: 3000 | J31: =I31*A31 -> 6000 | K31: =E31-J31 -> 2000
A32: 3 | B32: KG | C32: LIMON | D32: 3200 | E32: =A32*D32 -> 9600 | I32: =35000/15 -> 2333.3333 | J32: =I32*A32 -> 7000 | K32: =E32-J32 -> 2600
A33: 2 | B33: UNIDAD | C33: MANGO | D33: 2500 | E33: =A33*D33 -> 5000 | I33: =15000/9 -> 1666.6667 | J33: =I33*A33 -> 3333.3333 | K33: =E33-J33 -> 1666.6667
A34: 1 | B34: KG | C34: MANZANA GRANNY | D34: 3200 | E34: =A34*D34 -> 3200 | I34: =44000/18 -> 2444.4444 | J34: =I34*A34 -> 2444.4444 | K34: =E34-J34 -> 755.55556
A35: 15 | B35: UNIDAD | C35: PALTA | D35: 1200 | E35: =A35*D35 -> 18000 | I35: =65000/80 -> 812.5 | J35: =I35*A35 -> 12187.5 | K35: =E35-J35 -> 5812.5
A36: 1 | B36: KG | C36: TOM CHERRY | D36: 4000 | E36: =A36*D36 -> 4000 | I36: =30000/8 -> 3750 | J36: =I36*A36 -> 3750 | K36: =E36-J36 -> 250
A37: 1 | B37: CAJON | C37: TOMATE REDONDO | D37: 30000 | E37: =A37*D37 -> 30000 | I37: 22000 | J37: =I37*A37 -> 22000 | K37: =E37-J37 -> 8000
A38: 1 | B38: BOLSA | C38: ZANAHORIA | D38: 16000 | E38: =A38*D38 -> 16000 | I38: 13000 | J38: =I38*A38 -> 13000 | K38: =E38-J38 -> 3000
A39: 2 | B39: KG | C39: ZAP LARGO | D39: 2000 | E39: =A39*D39 -> 4000 | I39: =20000/14 -> 1428.5714 | J39: =I39*A39 -> 2857.1429 | K39: =E39-J39 -> 1142.8571
E41: =SUM(E25:E39) -> 239300 | K41: =SUM(K25:K39) -> 65047.579 | L41: =K41/E41 -> 0.2718244
A45: LA PIADINA | D45: rto: 6 | E45: 46035
A47: CANTIDAD | B47: UNIDAD | C47: PRODUCTO | D47: PRECIO | E47: TOTAL | I47: PRECIO | J47: TOTAL | K47: DIFERENCIA
A48: 4 | B48: ATADO | C48: ALBAHACA | D48: 1200 | E48: =A48*D48 -> 4800 | I48: 500 | J48: =I48*A48 -> 2000 | K48: =E48-J48 -> 2800
A49: 2 | B49: UNIDAD | C49: AJO | D49: 1200 | E49: =A49*D49 -> 2400 | I49: 560 | J49: =I49*A49 -> 1120 | K49: =E49-J49 -> 1280
A50: 1 | B50: KG | C50: LEC FRANCESA | D50: 3000 | E50: =A50*D50 -> 3000 | I50: 3000 | J50: =I50*A50 -> 3000 | K50: =E50-J50 -> 0
A51: 0.5 | B51: CAJON | C51: RUCULA | D51: 12000 | E51: =A51*D51 -> 6000 | I51: 6000 | J51: =I51*A51 -> 3000 | K51: =E51-J51 -> 3000
A52: 1.5 | B52: KG | C52: BANANA | D52: 3000 | E52: =A52*D52 -> 4500 | I52: 0 | J52: =I52*A52 -> 0 | K52: =E52-J52 -> 4500
A53: 1 | B53: KG | C53: MANZANA | D53: 3400 | E53: =A53*D53 -> 3400 | I53: =44000/18 -> 2444.4444 | J53: =I53*A53 -> 2444.4444 | K53: =E53-J53 -> 955.55556
A54: 2 | B54: KG | C54: NARANJA | D54: 1600 | E54: =A54*D54 -> 3200 | I54: =18000/15 -> 1200 | J54: =I54*A54 -> 2400 | K54: =E54-J54 -> 800
A55: 4 | B55: CUBETA | C55: ARANDANO | D55: 2500 | E55: =A55*D55 -> 10000 | I55: =18000/12 -> 1500 | J55: =I55*A55 -> 6000 | K55: =E55-J55 -> 4000
A56: 1 | B56: KG | C56: UVA | D56: 4500 | E56: =A56*D56 -> 4500 | I56: =30000/8 -> 3750 | J56: =I56*A56 -> 3750 | K56: =E56-J56 -> 750
A57: 0.5 | B57: KG | C57: KIWI | D57: 13000 | E57: =A57*D57 -> 6500 | I57: 10000 | J57: =I57*A57 -> 5000 | K57: =E57-J57 -> 1500
A58: 0.5 | B58: KG | C58: CIRUELA | D58: 4500 | E58: =A58*D58 -> 2250 | I58: =35000/12 -> 2916.6667 | J58: =I58*A58 -> 1458.3333 | K58: =E58-J58 -> 791.66667
E60: =SUM(E48:E58) -> 50550 | K60: =SUM(K48:K58) -> 20377.222 | L60: =K60/E60 -> 0.40311023
A64: TOTAL DIA | B64: =E60+E41+F19 -> 1162800
A66: GANANCIA | B66: =K60+K41+K19 -> 468374.8
A68: % | B68: =B66/B64 -> 0.40279911
A70: BULTOS COMPRADOS | C70: 26
B75: EFECTIVO | C75: MERCADO PAGO | D75: BANCO GALCIA | E75: BANCO RIO | F75: CHEQUES
B76: ='14-01-2026 '!B122 -> 2920550 | C76: ='14-01-2026 '!C122 -> 34872.131 | D76: ='14-01-2026 '!D122 -> 581947.35 | E76: ='14-01-2026 '!E122 -> 0 | F76: ='14-01-2026 '!F122 -> 2642589.7
A78: INGRESOS
A79: COBR. CTA. CTE | B79: 50550 | C79: 1575520.7 | D79: 0 | E79: 0 | F79: 0
A80: RENDIMIENTO MP | B80: 0 | C80: 26.82 | D80: 0 | E80: 0 | F80: 0
A81: CHE ACREDITADO | B81: 0 | C81: 0 | D81: 0 | E81: 0 | F81: 0
A82: COBR. VACIOS | B82: 0 | C82: 0 | D82: 0 | E82: 0 | F82: 0
A83: PRESTAMOS | B83: 0 | C83: 0 | D83: 0 | E83: 0 | F83: 0
A84: IMP. IIBB. 2% | B84: 0 | C84: =C79*2% -> 31510.415 | D84: =SUM(D78:D79)*2% -> 0 | E84: 0 | F84: 0
A85: IMP. CRED. 0,6% | B85: 0 | C85: =C79*0.6%+C82*0.6% -> 9453.1244 | D85: =SUM(D79:D81)*0.6% -> 0 | E85: 0 | F85: 0
A87: TOTAL | B87: =SUM(B76:B85) -> 2971100 | C87: =C76+C79+C82+C83-C85+C80-C84 -> 1569456.1 | D87: =D76+D79+D82+D83-D85+D81 -> 581947.35 | E87: =E76+E79+E82+E83-E85 -> 0 | F87: =F76+F79+F82+F83-F85-D81 -> 2642589.7
A89: GASTOS
A90: ING. MERCADO | B90: 1000 | C90: 0 | D90: 0 | E90: 0
A91: CARGA / VACIOS | B91: 0 | C91: 0 | D91: 0 | E91: 0
A92: CHEQ DEBITADO | B92: 0 | C92: 0 | D92: 0 | E92: 0
A93: PEAJE | B93: 2800 | C93: 0 | D93: 0 | E93: 0
A94: MERCADERIA | B94: 0 | C94: =84000+95000+93000 -> 272000 | D94: 0 | E94: 0
A95: COMBUSTIBLE | B95: 0 | C95: 0 | D95: 0 | E95: 0
A96: SUELDOS | B96: 0 | C96: 0 | D96: 0 | E96: 0
A97: DEV. PRESTAMOS | B97: 0 | C97: 0 | D97: 0 | E97: 0
A98: AGUA | B98: 0 | C98: 0 | D98: 0 | E98: 0
A99: FLETE JUAN | B99: 0 | C99: 0 | D99: 0 | E99: 0
A100: RETIRO JOAQUIN | B100: 0 | C100: 200000 | D100: 0 | E100: 0
A101: RETIRO FEDERICO | B101: 0 | C101: 0 | D101: 0 | E101: 0
A102: ALQUILER LOCAL | B102: 0 | C102: 0 | D102: 0 | E102: 0
A103: CONTADOR | B103: 0 | C103: 0 | D103: 0 | E103: 0
A104: ACEITE/AGUA CHATA | B104: 0 | C104: 0 | D104: 0 | E104: 0
A105: REMIS | B105: 0 | C105: 0 | D105: 0 | E105: 0
A106: MECANICO | B106: 0 | C106: 0 | D106: 0 | E106: 0
... A115: MANT. CTA. | B115: 0 | C115: 0 | D115: 0 | E115: 0
A117: IMP. DEB. 0,6% | B117: 0 | C117: =SUM(C90:C114)*0.6% -> 3621.2542 | D117: =SUM(D90:D114)*0.6%+(D118*0.6%) -> 2880 | E117: =(E94*0.6%)+(E95*0.6%)+(E96*0.6%)+(E99*0.6%)+(E100*0.6%) -> 0
A118: PASE DE CUENTAS | B118: 0 | C118: =200000+100000+180000 -> 480000 | D118: 480000 | E118: =SUM(E91:E116)*0.6%+(E119*0.6%) -> 0
A120: TOTAL SALIDAS | B120: =SUM(B90:B119) -> 3800 | C120: =SUM(C90:C117) -> 607163.62 | D120: =SUM(D90:D118) -> 482880 | E120: =E101+E105+E117-E118 -> 0 | F120: =F94
A122: SALDOS | B122: =B87-B120 -> 2967300 | C122: =C87-C120+C118 -> 1442292.5 | D122: =D87-D120 -> 99067.346 | E122: =E87-E120 -> 0 | F122: =F87-F120 -> 2642589.7
A124: fede | B124: =12200-B90-B93 -> 8400
A125: joaquin | B125: =2908350+B79 -> 2958900
B127: =SUM(B124:B125) -> 2967300

Sheet 16-01-2026 
A3: FV | E3: rto: 219 | F3: 46038 | I3: COMPRA
A5: CANTIDAD | B5: UNIDAD | C5: PRODUCTO | D5: PRECIO | E5: TOTAL | F5: TOTAL + IVA | I5: PRECIO | J5: TOTAL | K5: DIFERENCIA
A6: 4 | B6: CAJA | C6: BANANA | D6: 38000 | E6: =A6*D6 -> 152000 | F6: =E6*1.105 -> 167960 | I6: 30000 | J6: =I6*A6 -> 120000 | K6: =F6-J6 -> 47960
A7: 3 | B7: CAJA | C7: MANZANA GRNNY | D7: 70000 | E7: =A7*D7 -> 210000 | F7: =E7*1.105 -> 232050 | I7: 40000 | J7: =I7*A7 -> 120000 | K7: =F7-J7 -> 112050
A8: 2 | B8: CAJA | C8: NARANJA | D8: 22000 | E8: =A8*D8 -> 44000 | F8: =E8*1.105 -> 48620 | I8: 19000 | J8: =I8*A8 -> 38000 | K8: =F8-J8 -> 10620
A9: 1 | B9: CAJON | C9: UVA | D9: 32000 | E9: =A9*D9 -> 32000 | F9: =E9*1.105 -> 35360 | I9: 27000 | J9: =I9*A9 -> 27000 | K9: =F9-J9 -> 8360
A10: 23.8 | B10: KG | C10: SANDIA | D10: 1200 | E10: =A10*D10 -> 28560 | F10: =E10*1.105 -> 31558.8 | I10: 700 | J10: =I10*A10 -> 16660 | K10: =F10-J10 -> 14898.8
A11: 1 | B11: BOLSA | C11: CEBOLLA | D11: 14000 | E11: =A11*D11 -> 14000 | F11: =E11*1.105 -> 15470 | I11: 10000 | J11: =I11*A11 -> 10000 | K11: =F11-J11 -> 5470
A12: 1 | B12: CAJA | C12: BANANA | D12: 38000 | E12: =A12*D12 -> 38000 | F12: =E12*1.105 -> 41990 | G12: BOLSA | J12: =I12*A12 -> 0 | K12: =F12-J12 -> 41990
A13: 1 | B13: CAJA | C13: MANZANA | D13: 70000 | E13: =A13*D13 -> 70000 | F13: =E13*1.105 -> 77350 | G13: BOLSA | J13: =I13*A13 -> 0 | K13: =F13-J13 -> 77350
A14: 1 | B14: CAJA | C14: NARNAJA | D14: 22000 | E14: =A14*D14 -> 22000 | F14: =E14*1.105 -> 24310 | G14: BOLSA | J14: =I14*A14 -> 0 | K14: =F14-J14 -> 24310
E16: =SUM(E6:E14) -> 610560 | F16: =SUM(F6:F14) -> 674668.8 | K16: =SUM(K6:K14) -> 343008.8 | L16: =K16/F16 -> 0.50841065
A19: BRASOV | D19: rto: 5 | E19: 46038 | I19: COMPRA
A21: CANTIDAD | B21: UNIDAD | C21: PRODUCTO | D21: PRECIO | E21: TOTAL | I21: PRECIO | J21: TOTAL | K21: DIFERENCIA
A22: 2 | B22: CAJA | C22: LIMÓN | D22: 42000 | E22: =A22*D22 -> 84000 | I22: 32000 | J22: =I22*A22 -> 64000 | K22: =E22-J22 -> 20000
A23: 2 | B23: CAJÓN | C23: NARANJA | D23: 19000 | E23: =A23*D23 -> 38000 | I23: 15000 | J23: =I23*A23 -> 30000 | K23: =E23-J23 -> 8000
A24: 4 | B24: ATADO | C24: CEBOLLA DE VERDEO | D24: 5000 | E24: =A24*D24 -> 20000 | I24: 4000 | J24: =I24*A24 -> 16000 | K24: =E24-J24 -> 4000
A25: 1 | B25: CAJA | C25: PALTA | D25: 65000 | E25: =A25*D25 -> 65000 | I25: 57000 | J25: =I25*A25 -> 57000 | K25: =E25-J25 -> 8000
A26: 4 | B26: UNIDAD | C26: MANGO | D26: 2500 | E26: =A26*D26 -> 10000 | I26: =15000/9 -> 1666.6667 | J26: =I26*A26 -> 6666.6667 | K26: =E26-J26 -> 3333.3333
A27: 1 | B27: BANDEJA | C27: TOMATE CHERRY | D27: 22500 | E27: =A27*D27 -> 22500 | I27: =3750*5 -> 18750 | J27: =I27*A27 -> 18750 | K27: =E27-J27 -> 3750
E29: =SUM(E22:E27) -> 239500 | K29: =SUM(K22:K27) -> 47083.333 | L29: =K29/E29 -> 0.19659012
A32: COMO SIEMPRE LAGUNA | D32: rto: 21 | E32: 46038
A34: CANTIDAD | B34: UNIDAD | C34: PRODUCTO | D34: PRECIO | E34: TOTAL | I34: PRECIO | J34: TOTAL | K34: DIFERENCIA
A35: 2 | B35: BOLSA | C35: PAPA BLANCA | D35: 23000 | E35: =A35*D35 -> 46000 | I35: 19500 | J35: =I35*A35 -> 39000 | K35: =E35-J35 -> 7000
A36: 1 | B36: BOLSA | C36: CABUTIA | D36: 18000 | E36: =A36*D36 -> 18000 | I36: 15000 | J36: =I36*A36 -> 15000 | K36: =E36-J36 -> 3000
A37: 1 | B37: BOLSA | C37: ZANAHORIA | D37: 15000 | E37: =A37*D37 -> 15000 | I37: 13000 | J37: =I37*A37 -> 13000 | K37: =E37-J37 -> 2000
A38: 1 | B38: CAJÓN | C38: ESPINACA | D38: 22000 | E38: =A38*D38 -> 22000 | I38: 17000 | J38: =I38*A38 -> 17000 | K38: =E38-J38 -> 5000
A39: 1 | B39: CAJÓN | C39: HUEVOS | D39: 48000 | E39: =A39*D39 -> 48000 | I39: 38000 | J39: =I39*A39 -> 38000 | K39: =E39-J39 -> 10000
A40: 1 | B40: KG | C40: MANZANA VERDE | D40: 3500 | E40: =A40*D40 -> 3500 | I40: =40000/17 -> 2352.9412 | J40: =I40*A40 -> 2352.9412 | K40: =E40-J40 -> 1147.0588
A41: 5 | B41: UNIDAD | C41: AJO | D41: 1200 | E41: =A41*D41 -> 6000 | I41: 560 | J41: =I41*A41 -> 2800 | K41: =E41-J41 -> 3200
A42: 1 | B42: PAQ | C42: APIO | D42: 2000 | E42: =A42*D42 -> 2000 | I42: 1600 | J42: =I42*A42 -> 1600 | K42: =E42-J42 -> 400
A43: 6 | B43: KG | C43: CEBOLLA MORADA | D43: 1600 | E43: =A43*D43 -> 9600 | I43: =1000 -> 1000 | J43: =I43*A43 -> 6000 | K43: =E43-J43 -> 3600
A44: 2 | B44: CAJÓN | C44: COLIFLOR | D44: 15000 | E44: =A44*D44 -> 30000 | I44: 10000 | J44: =I44*A44 -> 20000 | K44: =E44-J44 -> 10000
A45: 6 | B45: KG | C45: TOMATE PERITA | D45: 3200 | E45: =A45*D45 -> 19200 | I45: =40000/15 -> 2666.6667 | J45: =I45*A45 -> 16000 | K45: =E45-J45 -> 3200
A46: 6 | B46: KG | C46: BONIATO | D46: 3200 | E46: =A46*D46 -> 19200 | I46: 2500 | J46: =I46*A46 -> 15000 | K46: =E46-J46 -> 4200
A47: 3 | B47: KG | C47: MORRÓN ROJO | D47: 3000 | E47: =A47*D47 -> 9000 | I47: =12000/8 -> 1500 | J47: =I47*A47 -> 4500 | K47: =E47-J47 -> 4500
A48: 1 | B48: KG | C48: MORRÓN AMARILLO | D48: 3500 | E48: =A48*D48 -> 3500 | I48: =16000/8 -> 2000 | J48: =I48*A48 -> 2000 | K48: =E48-J48 -> 1500
A49: 1 | B49: KG | C49: MORRÓN VERDE | D49: 2800 | E49: =A49*D49 -> 2800 | I49: 3000 | J49: =I49*A49 -> 3000 | K49: =E49-J49 -> -200
A50: 1 | B50: KG | C50: ZUCCINI | D50: 2000 | E50: =A50*D50 -> 2000 | I50: =20000/15 -> 1333.3333 | J50: =I50*A50 -> 1333.3333 | K50: =E50-J50 -> 666.66667
A51: 1 | B51: KG | C51: BERENJENA | D51: 1800 | E51: =A51*D51 -> 1800 | I51: =10000/8 -> 1250 | J51: =I51*A51 -> 1250 | K51: =E51-J51 -> 550
A52: 2 | B52: KG | C52: LIMA | D52: 4000 | E52: =A52*D52 -> 8000 | I52: 3000 | J52: =I52*A52 -> 6000 | K52: =E52-J52 -> 2000
A53: 12 | B53: UNIDAD | C53: PALTA | D53: 1400 | E53: =A53*D53 -> 16800 | I53: =65000/80 -> 812.5 | J53: =I53*A53 -> 9750 | K53: =E53-J53 -> 7050
A54: 1 | B54: PAQ | C54: CILANTRO | D54: 2000 | E54: =A54*D54 -> 2000 | I54: 1500 | J54: =I54*A54 -> 1500 | K54: =E54-J54 -> 500
A55: 1 | B55: PAQ | C55: CIBOULETTE | D55: 3000 | E55: =A55*D55 -> 3000 | I55: 2000 | J55: =I55*A55 -> 2000 | K55: =E55-J55 -> 1000
A56: 1 | B56: CAJÓN | C56: RÚCULA | D56: 9000 | E56: =A56*D56 -> 9000 | I56: 6000 | J56: =I56*A56 -> 6000 | K56: =E56-J56 -> 3000
A57: 1 | B57: CAJÓN | C57: LECHUGA FRANCESA | D57: 18000 | E57: =A57*D57 -> 18000 | I57: 15000 | J57: =I57*A57 -> 15000 | K57: =E57-J57 -> 3000
A58: 1 | B58: CAJÓN | C58: LECHUGA MORADA | D58: 18000 | E58: =A58*D58 -> 18000 | I58: 15000 | J58: =I58*A58 -> 15000 | K58: =E58-J58 -> 3000
A59: 2 | B59: UNIDAD | C59: PEPINO | D59: 2000 | E59: =A59*D59 -> 4000 | I59: 1500 | J59: =I59*A59 -> 3000 | K59: =E59-J59 -> 1000
A60: 1 | B60: CAJÓN | C60: TOMATE CHERRY | D60: 36000 | E60: =A60*D60 -> 36000 | I60: 30000 | J60: =I60*A60 -> 30000 | K60: =E60-J60 -> 6000
A61: 3 | B61: UNIDAD | C61: ROCOTO | D61: 6000 | E61: =A61*D61 -> 18000 | I61: 4000 | J61: =I61*A61 -> 12000 | K61: =E61-J61 -> 6000
A62: 2 | B62: KG | C62: PERA | D62: 3000 | E62: =A62*D62 -> 6000 | I62: =21000/9 -> 2333.3333 | J62: =I62*A62 -> 4666.6667 | K62: =E62-J62 -> 1333.3333
A63: 1 | B63: PAQ | C63: KALE | D63: 2000 | E63: =A63*D63 -> 2000 | I63: 1000 | J63: =I63*A63 -> 1000 | K63: =E63-J63 -> 1000
A64: 1 | B64: UNIDAD | C64: ANANÁ | D64: 5000 | E64: =A64*D64 -> 5000 | I64: 3000 | J64: =I64*A64 -> 3000 | K64: =E64-J64 -> 2000
A65: 1 | B65: UNIDAD | C65: MELÓN | D65: 6000 | E65: =A65*D65 -> 6000 | I65: 6000 | J65: =I65*A65 -> 6000 | K65: =E65-J65 -> 0
A66: 1 | B66: KG | C66: UVA | D66: 4500 | E66: =A66*D66 -> 4500 | I66: 0 | J66: =I66*A66 -> 0 | K66: =E66-J66 -> 4500
A67: 1 | B67: UNIDAD | C67: BROTE | D67: 2500 | E67: =A67*D67 -> 2500 | I67: 1500 | J67: =I67*A67 -> 1500 | K67: =E67-J67 -> 1000
A68: 0.5 | B68: CAJÓN | C68: POMELO | D68: 46000 | E68: =A68*D68 -> 23000 | I68: 40000 | J68: =I68*A68 -> 20000 | K68: =E68-J68 -> 3000
A69: 0.5 | B69: CAJÓN | C69: NARANJA | D69: 20000 | E69: =A69*D69 -> 10000 | I69: 15000 | J69: =I69*A69 -> 7500 | K69: =E69-J69 -> 2500
E71: =SUM(E35:E69) -> 449400 | K71: =SUM(K35:K69) -> 107647.06 | L71: =K71/E71 -> 0.23953507
A75: LA MARQUESA | D75: rto: 3 | E75: 46038
A77: CANTIDAD | B77: UNIDAD | C77: PRODUCTO | D77: PRECIO | E77: TOTAL | I77: PRECIO | J77: TOTAL | K77: DIFERENCIA
A78: 1 | B78: CAJA | C78: FRUTILLA TAMARA | D78: 34000 | E78: =A78*D78 -> 34000 | I78: 30000 | J78: =I78*A78 -> 30000 | K78: =E78-J78 -> 4000
A79: 1 | B79: ATADO | C79: PUERRO | D79: 6000 | E79: =A79*D79 -> 6000 | I79: 5000 | J79: =I79*A79 -> 5000 | K79: =E79-J79 -> 1000
E81: =SUM(E78:E79) -> 40000 | K81: =SUM(K78:K79) -> 5000 | L81: =K81/E81 -> 0.125
A85: LA PIADINA | D85: rto: 7 | E85: 46038
A87: CANTIDAD | B87: UNIDAD | C87: PRODUCTO | D87: PRECIO | E87: TOTAL | I87: PRECIO | J87: TOTAL | K87: DIFERENCIA
A88: 4 | B88: KG | C88: TOMATE | D88: 3500 | E88: =A88*D88 -> 14000 | I88: =42000/15 -> 2800 | J88: =I88*A88 -> 11200 | K88: =E88-J88 -> 2800
A89: 0.5 | B89: CAJÓN | C89: RÚCULA | D89: 10000 | E89: =A89*D89 -> 5000 | I89: 6000 | J89: =I89*A89 -> 3000 | K89: =E89-J89 -> 2000
A90: 0.5 | B90: KG | C90: LIMÓN | D90: 3500 | E90: =A90*D90 -> 1750 | I90: 2333 | J90: =I90*A90 -> 1166.5 | K90: =E90-J90 -> 583.5
A91: 1 | B91: KG | C91: LECHUGA FRANCESA | D91: 3500 | E91: =A91*D91 -> 3500 | I91: 0 | J91: =I91*A91 -> 0 | K91: =E91-J91 -> 3500
A92: 2 | B92: UNIDAD | C92: PALTA | D92: 1400 | E92: =A92*D92 -> 2800 | I92: =65000/80 -> 812.5 | J92: =I92*A92 -> 1625 | K92: =E92-J92 -> 1175
A93: 0.5 | B93: KG | C93: ZANAHORIA | D93: 2000 | E93: =A93*D93 -> 1000 | I93: =13000/8 -> 1625 | J93: =I93*A93 -> 812.5 | K93: =E93-J93 -> 187.5
E95: =SUM(E88:E93) -> 28050 | K95: =SUM(K88:K93) -> 10246 | L95: =K95/E95 -> 0.36527629
A99: MESTIZO | D99: rto: 4 | E99: 46038
A101: CANTIDAD | B101: UNIDAD | C101: PRODUCTO | D101: PRECIO | E101: TOTAL | I101: PRECIO | J101: TOTAL | K101: DIFERENCIA
A102: 1 | B102: CAJÓN | C102: TOMATE CHERRY | D102: 36000 | E102: =A102*D102 -> 36000 | I102: 30000 | J102: =I102*A102 -> 30000 | K102: =E102-J102 -> 6000
A103: 1 | B103: BOLSA | C103: PAPA BLANCA | D103: 23000 | E103: =A103*D103 -> 23000 | I103: 19500 | J103: =I103*A103 -> 19500 | K103: =E103-J103 -> 3500
A104: 2 | B104: KG | C104: PERA | D104: 3000 | E104: =A104*D104 -> 6000 | I104: =21000/9 -> 2333.3333 | J104: =I104*A104 -> 4666.6667 | K104: =E104-J104 -> 1333.3333
A105: 1 | B105: PAQ | C105: CEBOLLA DE VERDEO | D105: 5000 | E105: =A105*D105 -> 5000 | I105: 4000 | J105: =I105*A105 -> 4000 | K105: =E105-J105 -> 1000
A106: 1 | B106: PAQ | C106: TOMILLO | D106: 3000 | E106: =A106*D106 -> 3000 | I106: 2000 | J106: =I106*A106 -> 2000 | K106: =E106-J106 -> 1000
A107: 6 | B107: KG | C107: TOMATE PERITA | D107: 3200 | E107: =A107*D107 -> 19200 | I107: =40000/15 -> 2666.6667 | J107: =I107*A107 -> 16000 | K107: =E107-J107 -> 3200
A108: 4 | B108: UNIDAD | C108: AJO | D108: 1200 | E108: =A108*D108 -> 4800 | I108: 560 | J108: =I108*A108 -> 2240 | K108: =E108-J108 -> 2560
A109: 1 | B109: CAJÓN | C109: RÚCULA | D109: 9000 | E109: =A109*D109 -> 9000 | I109: 6000 | J109: =I109*A109 -> 6000 | K109: =E109-J109 -> 3000
A110: 1 | B110: CAJÓN | C110: ESPINACA | D110: 22000 | E110: =A110*D110 -> 22000 | I110: 17000 | J110: =I110*A110 -> 17000 | K110: =E110-J110 -> 5000
A111: 1 | B111: PAQ | C111: PEREJIL | D111: 3000 | E111: =A111*D111 -> 3000 | I111: 2000 | J111: =I111*A111 -> 2000 | K111: =E111-J111 -> 1000
A112: 1 | B112: PAQ | C112: ENELDO | D112: 3000 | E112: =A112*D112 -> 3000 | I112: 2000 | J112: =I112*A112 -> 2000 | K112: =E112-J112 -> 1000
A113: 1 | B113: UNIDAD | C113: BROTES DE REMOLACHA | D113: 2500 | E113: =A113*D113 -> 2500 | I113: 1500 | J113: =I113*A113 -> 1500 | K113: =E113-J113 -> 1000
A114: 1 | B114: CAJÓN | C114: LIMÓN | D114: 42000 | E114: =A114*D114 -> 42000 | I114: 32000 | J114: =I114*A114 -> 32000 | K114: =E114-J114 -> 10000
E116: =SUM(E102:E115) -> 178500 | K116: =SUM(K102:K114) -> 39593.333 | L116: =K116/E116 -> 0.22181139
A120: RAKUS | D120: rto: 15 | E120: 46038
A122: CANTIDAD | B122: UNIDAD | C122: PRODUCTO | D122: PRECIO | E122: TOTAL | I122: PRECIO | J122: TOTAL | K122: DIFERENCIA
A123: 7 | B123: ATADOS | C123: CILANTRO | D123: 2000 | E123: =A123*D123 -> 14000 | I123: 1500 | J123: =I123*A123 -> 10500 | K123: =E123-J123 -> 3500 | L123: =K123/E123 -> 0.25
A124: 2 | B124: ATADOS | C124: PEREJIL | D124: 4000 | E124: =A124*D124 -> 8000 | I124: 2000 | J124: =I124*A124 -> 4000 | K124: =E124-J124 -> 4000 | L124: =K124/E124 -> 0.5
A125: 5.3 | B125: KG | C125: FRUTILLA TAMARA | D125: 8500 | E125: =A125*D125 -> 45050 | I125: =30000/4 -> 7500 | J125: =I125*A125 -> 39750 | K125: =E125-J125 -> 5300 | L125: =K125/E125 -> 0.11764706
A126: 3 | B126: KG | C126: LECHUGA CRIOLLA | D126: 4000 | E126: =A126*D126 -> 12000 | I126: =17000/6 -> 2833.3333 | J126: =I126*A126 -> 8500 | K126: =E126-J126 -> 3500 | L126: =K126/E126 -> 0.29166667
A127: 13 | B127: ATADOS | C127: RÚCULA | D127: 400 | E127: =A127*D127 -> 5200 | I127: =6000/24 -> 250 | J127: =I127*A127 -> 3250 | K127: =E127-J127 -> 1950 | L127: =K127/E127 -> 0.375
A128: 4 | B128: KG | C128: MORRÓN ROJO | D128: 2800 | E128: =A128*D128 -> 11200 | I128: =12000/8 -> 1500 | J128: =I128*A128 -> 6000 | K128: =E128-J128 -> 5200 | L128: =K128/E128 -> 0.46428571
A129: 1 | B129: BANDEJA | C129: FLORES COMESTIBLES | D129: 5500 | E129: =A129*D129 -> 5500 | I129: 4000 | J129: =I129*A129 -> 4000 | K129: =E129-J129 -> 1500 | L129: =K129/E129 -> 0.27272727
A130: 1 | B130: CAJÓN | C130: NARANJA JUGO | D130: 22000 | E130: =A130*D130 -> 22000 | I130: 19000 | J130: =I130*A130 -> 19000 | K130: =E130-J130 -> 3000 | L130: =K130/E130 -> 0.13636364
A131: 1 | B131: CAJÓN | C131: LIMÓN | D131: 42000 | E131: =A131*D131 -> 42000 | I131: 32000 | J131: =I131*A131 -> 32000 | K131: =E131-J131 -> 10000
...

Sheet 19-01-2026 
A3: FV | E3: rto: 220 | F3: 46041 | I3: COMPRA
A5: CANTIDAD | B5: UNIDAD | C5: PRODUCTO | D5: PRECIO | E5: TOTAL | F5: TOTAL + IVA | I5: PRECIO | J5: TOTAL | K5: DIFERENCIA
A6: 2 | B6: CAJA | C6: MANZANA GRANNY | D6: 63000 | E6: =A6*D6 -> 126000 | F6: =E6*1.105 -> 139230 | I6: 40000 | J6: =I6*A6 -> 80000 | K6: =F6-J6 -> 59230
A7: 2 | B7: CAJON | C7: TOMATE REDONDO | D7: 53000 | E7: =A7*D7 -> 106000 | F7: =E7*1.105 -> 117130 | I7: 45000 | J7: =I7*A7 -> 90000 | K7: =F7-J7 -> 27130
A8: 2 | B8: CAJON | C8: TOMATE CHERRY | D8: 43000 | E8: =A8*D8 -> 86000 | F8: =E8*1.105 -> 95030 | I8: 35000 | J8: =I8*A8 -> 70000 | K8: =F8-J8 -> 25030
A9: 1 | B9: CAJON | C9: BERENJENA | D9: 13000 | E9: =A9*D9 -> 13000 | F9: =E9*1.105 -> 14365 | I9: 9000 | J9: =I9*A9 -> 9000 | K9: =F9-J9 -> 5365
A10: 6 | B10: ATADO | C10: ALBAHACA | D10: 1000 | E10: =A10*D10 -> 6000 | F10: =E10*1.105 -> 6630 | I10: 500 | J10: =I10*A10 -> 3000 | K10: =F10-J10 -> 3630
A11: 2 | B11: CAJA | C11: BANANA | D11: 38000 | E11: =A11*D11 -> 76000 | F11: =E11*1.105 -> 83980 | I11: 28000 | J11: =I11*A11 -> 56000 | K11: =F11-J11 -> 27980
A12: 2 | B12: CAJON | C12: UVA RED GLOBE OFER | D12: 25000 | E12: =A12*D12 -> 50000 | F12: =E12*1.105 -> 55250 | I12: =50000/3 -> 16666.667 | J12: =I12*A12 -> 33333.333 | K12: =F12-J12 -> 21916.667
A13: 4 | B13: CAJA | C13: CIRUELA | D13: 32000 | E13: =A13*D13 -> 128000 | F13: =E13*1.105 -> 141440 | I13: 27000 | J13: =I13*A13 -> 108000 | K13: =F13-J13 -> 33440
A14: 0.5 | B14: CAJON | C14: HUEVO | D14: 50000 | E14: =A14*D14 -> 25000 | F14: =E14*1.105 -> 27625 | I14: 38000 | J14: =I14*A14 -> 19000 | K14: =F14-J14 -> 8625
A15: 1 | B15: CAJA | C15: BANANA | D15: 38000 | E15: =A15*D15 -> 38000 | F15: =E15*1.105 -> 41990 | G15: BOLSA | J15: =I15*A15 -> 0 | K15: =F15-J15 -> 41990
A16: 1 | B16: CAJON | C16: TOMATE | D16: 53000 | E16: =A16*D16 -> 53000 | F16: =E16*1.105 -> 58565 | G16: BOLSA | J16: =I16*A16 -> 0 | K16: =F16-J16 -> 58565
A17: 1 | B17: CJAON | C17: TOM CHERRY | D17: 43000 | E17: =A17*D17 -> 43000 | F17: =E17*1.105 -> 47515 | G17: BOLSA | I17: 0 | J17: =I17*A17 -> 0 | K17: =F17-J17 -> 47515
A18: 1 | B18: CAJA | C18: MANZANA GRANNY | D18: 63000 | E18: =A18*D18 -> 63000 | F18: =E18*1.105 -> 69615 | G18: BOLSA | J18: =I18*A18 -> 0 | K18: =F18-J18 -> 69615
A19: 0.5 | B19: CAJON | C19: HUEVO | D19: 50000 | E19: =A19*D19 -> 25000 | F19: =E19*1.21 -> 30250 | G19: BOLSA | J19: =I19*A19 -> 0 | K19: =F19-J19 -> 30250
E21: =SUM(E6:E19) -> 838000 | F21: =SUM(F6:F19) -> 928615 | K21: =SUM(K6:K19) -> 460281.67
A24: COMO SIEMPRE LAGUNA | D24: rto: 22 | E24: 46041
A26: CANTIDAD | B26: UNIDAD | C26: PRODUCTO | D26: PRECIO | E26: TOTAL | I26: PRECIO | J26: TOTAL | K26: DIFERENCIA
A27: 0.5 | B27: CAJON | C27: NARANJA | D27: 20000 | E27: =A27*D27 -> 10000 | I27: 15000 | J27: =I27*A27 -> 7500 | K27: =E27-J27 -> 2500
A28: 1 | B28: CAJA | C28: LIMON | D28: 42000 | E28: =A28*D28 -> 42000 | I28: 32000 | J28: =I28*A28 -> 32000 | K28: =E28-J28 -> 10000
A29: 1 | B29: ATADO | C29: MENTA | D29: 3000 | E29: =A29*D29 -> 3000 | I29: 2000 | J29: =I29*A29 -> 2000 | K29: =E29-J29 -> 1000
A30: 2 | B30: BOLSA | C30: PAPA GARLIC | D30: 23000 | E30: =A30*D30 -> 46000 | I30: 19000 | J30: =I30*A30 -> 38000 | K30: =E30-J30 -> 8000
A31: 2 | B31: CAJON | C31: ESPINACA | D31: 22000 | E31: =A31*D31 -> 44000 | I31: 17000 | J31: =I31*A31 -> 34000 | K31: =E31-J31 -> 10000
A32: 0.5 | B32: KG | C32: CHAMPI | D32: 19000 | E32: =A32*D32 -> 9500 | I32: 16000 | J32: =I32*A32 -> 8000 | K32: =E32-J32 -> 1500
A33: 0.5 | B33: KG | C33: PORTO | D33: 20000 | E33: =A33*D33 -> 10000 | I33: 17000 | J33: =I33*A33 -> 8500 | K33: =E33-J33 -> 1500
A34: 3 | B34: UNIDAD | C34: AJO | D34: 1200 | E34: =A34*D34 -> 3600 | I34: 560 | J34: =I34*A34 -> 1680 | K34: =E34-J34 -> 1920
A35: 3 | B35: KG | C35: TOM PERITA | D35: 4000 | E35: =A35*D35 -> 12000 | I35: 4000 | J35: =I35*A35 -> 12000 | K35: =E35-J35 -> 0
A36: 3 | B36: KG | C36: MORRON ROJO | D36: 3000 | E36: =A36*D36 -> 9000 | I36: =10000/8 -> 1250 | J36: =I36*A36 -> 3750 | K36: =E36-J36 -> 5250
A37: 1 | B37: ATADO | C37: CILANTRO | D37: 2000 | E37: =A37*D37 -> 2000 | I37: 1000 | J37: =I37*A37 -> 1000 | K37: =E37-J37 -> 1000
A38: 1 | B38: ATADO | C38: CIBOULLETE | D38: 3000 | E38: =A38*D38 -> 3000 | I38: 2000 | J38: =I38*A38 -> 2000 | K38: =E38-J38 -> 1000
A39: 1 | B39: CAJON | C39: RUCULA | D39: 9000 | E39: =A39*D39 -> 9000 | I39: 5000 | J39: =I39*A39 -> 5000 | K39: =E39-J39 -> 4000
A40: 1 | B40: KG | C40: REMOLACHA | D40: 2000 | E40: =A40*D40 -> 2000 | I40: 1400 | J40: =I40*A40 -> 1400 | K40: =E40-J40 -> 600
E42: =SUM(E27:E40) -> 205100 | K42: =SUM(K27:K40) -> 48270 | L42: =K42/E42 -> 0.23534861
A45: LA PIADINA | D45: rto: 8 | E45: 46041
A47: CANTIDAD | B47: UNIDAD | C47: PRODUCTO | D47: PRECIO | E47: TOTAL | I47: PRECIO | J47: TOTAL | K47: DIFERENCIA
A48: 1 | B48: CAJON | C48: RUCULA | D48: 10000 | E48: =A48*D48 -> 10000 | I48: 5000 | J48: =I48*A48 -> 5000 | K48: =E48-J48 -> 5000
A49: 4 | B49: KG | C49: TOMATE | D49: 4000 | E49: =A49*D49 -> 16000 | I49: 0 | J49: =I49*A49 -> 0 | K49: =E49-J49 -> 16000
A50: 1.5 | B50: KG | C50: LECHUGA | D50: 4000 | E50: =A50*D50 -> 6000 | I50: 3500 | J50: =I50*A50 -> 5250 | K50: =E50-J50 -> 750
A51: 1 | B51: KG | C51: ZANAHORIA | D51: 2000 | E51: =A51*D51 -> 2000 | I51: 1200 | J51: =I51*A51 -> 1200 | K51: =E51-J51 -> 800
A52: 0.4 | B52: KG | C52: NARANJA | D52: 1400 | E52: =A52*D52 -> 560 | I52: =1000 -> 1000 | J52: =I52*A52 -> 400 | K52: =E52-J52 -> 160
I53: 0 | J53: =I53*A53 -> 0 | K53: =E53-J53 -> 0
E55: =SUM(E48:E53) -> 34560 | K55: =SUM(K48:K53) -> 22710 | L55: =K55/E55 -> 0.65711806
A59: MESTIZO | D59: rto: 5 | E59: 46041
A61: CANTIDAD | B61: UNIDAD | C61: PRODUCTO | D61: PRECIO | E61: TOTAL | I61: PRECIO | J61: TOTAL | K61: DIFERENCIA
A62: 1 | B62: BOLSA | C62: PAPA GARLIC | D62: 23000 | E62: =A62*D62 -> 23000 | I62: 19000 | J62: =I62*A62 -> 19000 | K62: =E62-J62 -> 4000
A63: 1 | B63: CAJON | C63: HUEVO | D63: 48000 | E63: =A63*D63 -> 48000 | I63: 38000 | J63: =I63*A63 -> 38000 | K63: =E63-J63 -> 10000
A64: 3 | B64: KG | C64: TOM PERITA | D64: 4000 | E64: =A64*D64 -> 12000 | I64: =30000/15 -> 2000 | J64: =I64*A64 -> 6000 | K64: =E64-J64 -> 6000
A65: 1 | B65: KG | C65: CEB MORADA | D65: 1600 | E65: =A65*D65 -> 1600 | I65: 1000 | J65: =I65*A65 -> 1000 | K65: =E65-J65 -> 600
A66: 1 | B66: CAJON | C66: MORRON ROJO | D66: 20000 | E66: =A66*D66 -> 20000 | I66: 10000 | J66: =I66*A66 -> 10000 | K66: =E66-J66 -> 10000
A67: 1 | B67: ATADO | C67: CEB VERDEO | D67: 5000 | E67: =A67*D67 -> 5000 | I67: 4500 | J67: =I67*A67 -> 4500 | K67: =E67-J67 -> 500
A68: 10 | B68: UNIDAD | C68: PALTA | D68: 1400 | E68: =A68*D68 -> 14000 | I68: =67000/70 -> 957.14286 | J68: =I68*A68 -> 9571.4286 | K68: =E68-J68 -> 4428.5714
A69: 1 | B69: ATADO | C69: CILANTRO | D69: 2000 | E69: =A69*D69 -> 2000 | I69: 1000 | J69: =I69*A69 -> 1000 | K69: =E69-J69 -> 1000
A70: 1 | B70: ATADO | C70: CIBOULLETE | D70: 3000 | E70: =A70*D70 -> 3000 | I70: 2000 | J70: =I70*A70 -> 2000 | K70: =E70-J70 -> 1000
A71: 1 | B71: CAJON | C71: RUCULA | D71: 9000 | E71: =A71*D71 -> 9000 | I71: 5000 | J71: =I71*A71 -> 5000 | K71: =E71-J71 -> 4000
A72: 0.5 | B72: CAJON | C72: LEC MORADA | D72: 13000 | E72: =A72*D72 -> 6500 | I72: 7000 | J72: =I72*A72 -> 3500 | K72: =E72-J72 -> 3000
E74: =SUM(E62:E73) -> 144100 | K74: =SUM(K62:K72) -> 44528.571 | L74: =K74/E74 -> 0.3090116
A78: PAULA | D78: rto: 4 | E78: 46041
A80: CANTIDAD | B80: UNIDAD | C80: PRODUCTO | D80: PRECIO | E80: TOTAL | I80: PRECIO | J80: TOTAL | K80: DIFERENCIA
A81: 1 | B81: BOLSA | C81: ANCO | D81: 18000 | E81: =A81*D81 -> 18000 | I81: 15000 | J81: =I81*A81 -> 15000 | K81: =E81-J81 -> 3000
A82: 2 | B82: KG | C82: BERENJENA | D82: 1700 | E82: =A82*D82 -> 3400 | I82: 0 | J82: =I82*A82 -> 0 | K82: =E82-J82 -> 3400
A83: 1 | B83: BOLSA | C83: CEBOLLA | D83: 13000 | E83: =A83*D83 -> 13000 | I83: 10000 | J83: =I83*A83 -> 10000 | K83: =E83-J83 -> 3000
A84: 2 | B84: KG | C84: LIMON | D84: 3200 | E84: =A84*D84 -> 6400 | I84: =35000/15 -> 2333.3333 | J84: =I84*A84 -> 4666.6667 | K84: =E84-J84 -> 1733.3333
A85: 1 | B85: BOLSA | C85: PAPA | D85: 20000 | E85: =A85*D85 -> 20000 | I85: 19000 | J85: =I85*A85 -> 19000 | K85: =E85-J85 -> 1000
A86: 2 | B86: KG | C86: ZAPALLITO REDONDO | D86: 2100 | E86: =A86*D86 -> 4200 | I86: 2100 | J86: =I86*A86 -> 4200 | K86: =E86-J86 -> 0
A87: 1 | B87: KG | C87: ZAPALLITO LARGO | D87: 2300 | E87: =A87*D87 -> 2300 | I87: =18000/14 -> 1285.7143 | J87: =I87*A87 -> 1285.7143 | K87: =E87-J87 -> 1014.2857
E89: =SUM(E81:E88) -> 67300 | K89: =SUM(K81:K87) -> 13147.619 | L89: =K89/E89 -> 0.19535838
A92: TOTAL DIA | B92: =E89+E74+E55+E42+F21 -> 1379675
A94: GANANCIA | B94: =K89+K74+K55+K42+K21 -> 588937.86
A96: % | B96: =B94/B92 -> 0.42686709
A98: BULTOS COMPRADOS
B103: EFECTIVO | C103: MERCADO PAGO | D103: BANCO GALCIA | E103: BANCO RIO | F103: CHEQUES
B104: ='16-01-2026 '!B218 -> 3236977.2 | C104: ='16-01-2026 '!C218 -> 1233073.4 | D104: ='16-01-2026 '!D218 -> 268569.7 | E104: ='16-01-2026 '!E218 -> 0 | F104: ='16-01-2026 '!F218 -> 3607546.4
A106: INGRESOS
A107: COBR. CTA. CTE | B107: 34560 | C107: =800000+94000 -> 894000 | D107: 0 | E107: 0 | F107: 0
A108: RENDIMIENTO MP | B108: 0 | C108: =3571-33.19 -> 3537.81 | D108: 0 | E108: 0 | F108: 0
A109: CHE ACREDITADO | B109: 0 | C109: 0 | D109: 1478207.8 | E109: 0 | F109: 1478207.8
A110: COBR. VACIOS | B110: 0 | C110: 0 | D110: 0 | E110: 0 | F110: 0
A111: PRESTAMOS | B111: 0 | C111: 0 | D111: 0 | E111: 0 | F111: 0
A112: VENTA DE CHEQUE | B112: 0 | C112: 0 | D112: 0 | E112: 0 | F112: 0
A113: IMP. IIBB. 2% | B113: 0 | C113: =C107*2% -> 17880 | D113: =SUM(D107:D109)*2% -> 29564.157 | E113: 0 | F113: 0
A114: IMP. CRED. 0,6% | B114: 0 | C114: =C107*0.6%+C110*0.6% -> 5364 | D114: =SUM(D107:D109)*0.6% -> 8869.247 | E114: 0 | F114: 0
A116: TOTAL | B116: =SUM(B104:B114) -> 3271537.2 | C116: =C104+C107+C110+C111-C114+C108-C113 -> 2107367.2 | D116: =D104+D107+D110+D111-D114+D109-D113-D112 -> 1708344.1 | E116: =E104+E107+E110+E111-E114 -> 0 | F116: =F104+F107+F110+F111-F114-D109 -> 2129338.5
A118: GASTOS
A119: ING. MERCADO | B119: 1000 | C119: 0 | D119: 0 | E119: 0
A120: CARGA / VACIOS | B120: 25000 | C120: =96000+45000 -> 141000 | D120: 0 | E120: 0
A121: CHEQ DEBITADO | B121: 0 | C121: 0 | D121: 0 | E121: 0
A122: PEAJE | B122: 2800 | C122: 0 | D122: 0 | E122: 0
A123: MERCADERIA | B123: 0 | C123: =52000+20740+101500+80000+57000+12000 -> 323240 | D123: 0 | E123: 0
A124: COMBUSTIBLE | B124: 0 | C124: 25000 | D124: 0 | E124: 0
A125: SUELDOS | B125: 34500 | C125: =215000+175000+163000 -> 553000 | D125: 0 | E125: 0
A126: DEV. PRESTAMOS | B126: 0 | C126: 0 | D126: 0 | E126: 0
A127: AGUA | B127: 0 | C127: 0 | D127: 0 | E127: 0
A128: FLETE JUAN | B128: 0 | C128: 0 | D128: 0 | E128: 0
A129: RETIRO JOAQUIN | B129: 0 | C129: 0 | D129: 0 | E129: 0
A130: RETIRO FEDERICO | B130: 0 | C130: 50000 | D130: 0 | E130: 0
A131: ALQUILER LOCAL | B131: 0 | C131: 0 | D131: 0 | E131: 0
A132: CONTADOR | B132: 0 | C132: 0 | D132: 0 | E132: 0
A133: ACEITE/AGUA CHATA | B133: 0 | C133: 0 | D133: 0 | E133: 0
A134: REMIS | B134: 0 | C134: 0 | D134: 0 | E134: 0
...

Sheet 20-01-2026 
A4: RAKUS | D4: rto: 16 | E4: 46042 | F4: **
A6: CANTIDAD | B6: UNIDAD | C6: PRODUCTO | D6: PRECIO | E6: TOTAL | I6: PRECIO | J6: TOTAL | K6: DIFERENCIA
A7: 1 | B7: KG | C7: TOMATE CHERRY | D7: 3800 | E7: =A7*D7 -> 3800 | I7: 0 | J7: =I7*A7 -> 0 | K7: =E7-J7 -> 3800
A8: 1 | B8: UNIDAD | C8: REP BLANCO | D8: 2000 | E8: =A8*D8 -> 2000 | I8: 1500 | J8: =I8*A8 -> 1500 | K8: =E8-J8 -> 500
A9: 1 | B9: UNIDAD | C9: REP ROJO | D9: 2000 | E9: =A9*D9 -> 2000 | I9: 1200 | J9: =I9*A9 -> 1200 | K9: =E9-J9 -> 800
A10: 4.1 | B10: KG | C10: TOMATE REDONDO | D10: 4000 | E10: =A10*D10 -> 16400 | I10: =40000/15 -> 2666.6667 | J10: =I10*A10 -> 10933.333 | K10: =E10-J10 -> 5466.6667
A11: 8 | B11: CUBETA | C11: ARANDANO | D11: 2500 | E11: =A11*D11 -> 20000 | I11: =22000/12 -> 1833.3333 | J11: =I11*A11 -> 14666.667 | K11: =E11-J11 -> 5333.3333
A12: 1 | B12: CAJON | C12: FRUTILLA | D12: 25000 | E12: =A12*D12 -> 25000 | I12: 20000 | J12: =I12*A12 -> 20000 | K12: =E12-J12 -> 5000
A13: 0.5 | B13: CAJON | C13: HUEVO | D13: 55000 | E13: =A13*D13 -> 27500 | I13: =43000 -> 43000 | J13: =I13*A13 -> 21500 | K13: =E13-J13 -> 6000
A14: 2 | B14: CAJON | C14: NARANJA SIN SEMILLA | D14: 22000 | E14: =A14*D14 -> 44000 | I14: 18000 | J14: =I14*A14 -> 36000 | K14: =E14-J14 -> 8000
A15: 1 | B15: CAJA | C15: LIMON | D15: 42000 | E15: =A15*D15 -> 42000 | I15: 30000 | J15: =I15*A15 -> 30000 | K15: =E15-J15 -> 12000
A16: 1 | B16: ATADO | C16: MENTA | D16: 3000 | E16: =A16*D16 -> 3000 | I16: 2000 | J16: =I16*A16 -> 2000 | K16: =E16-J16 -> 1000
A17: 2.2 | B17: KG | C17: LIMA | D17: 3500 | E17: =A17*D17 -> 7700 | I17: 2500 | J17: =I17*A17 -> 5500 | K17: =E17-J17 -> 2200
A18: 0.5 | B18: KG | C18: JENGIBRE | D18: 6500 | E18: =A18*D18 -> 3250 | I18: 4000 | J18: =I18*A18 -> 2000 | K18: =E18-J18 -> 1250
E20: =SUM(E7:E18) -> 196650 | K20: =SUM(K7:K18) -> 51350 | L20: =K20/E20 -> 0.26112382
A24: PAULA | D24: rto: 5 | E24: 46042 | F24: **
A26: CANTIDAD | B26: UNIDAD | C26: PRODUCTO | D26: PRECIO | E26: TOTAL | I26: PRECIO | J26: TOTAL | K26: DIFERENCIA
A27: 3 | B27: KG | C27: MORRON ROJO | D27: 2800 | E27: =A27*D27 -> 8400 | I27: =10000/8 -> 1250 | J27: =I27*A27 -> 3750 | K27: =E27-J27 -> 4650
A28: 0.5 | B28: ATADO | C28: CEB VERDEO | D28: 5000 | E28: =A28*D28 -> 2500 | I28: 4500 | J28: =I28*A28 -> 2250 | K28: =E28-J28 -> 250
A29: 0.5 | B29: ATADO | C29: PUERRO | D29: 6000 | E29: =A29*D29 -> 3000 | I29: 6000 | J29: =I29*A29 -> 3000 | K29: =E29-J29 -> 0
A30: 3 | B30: ATADO | C30: ALBAHACA | D30: 1000 | E30: =A30*D30 -> 3000 | I30: 500 | J30: =I30*A30 -> 1500 | K30: =E30-J30 -> 1500
A31: 1 | B31: KG | C31: TOM REDONDO | D31: 3600 | E31: =A31*D31 -> 3600 | I31: =40000/15 -> 2666.6667 | J31: =I31*A31 -> 2666.6667 | K31: =E31-J31 -> 933.33333
A32: 1 | B32: KG | C32: TOM CHERRY | D32: 4000 | E32: =A32*D32 -> 4000 | I32: 0 | J32: =I32*A32 -> 0 | K32: =E32-J32 -> 4000
E34: =SUM(E27:E32) -> 24500 | K34: =SUM(K27:K32) -> 11333.333 | L34: =K34/E34 -> 0.46258503
A38: BRASOV | D38: rto: 4 | E38: 46042
A40: CANTIDAD | B40: UNIDAD | C40: PRODUCTO | D40: PRECIO | E40: TOTAL | I40: PRECIO | J40: TOTAL | K40: DIFERENCIA
A41: 1 | B41: BOLSA | C41: PAPA | D41: 18000 | E41: =A41*D41 -> 18000 | I41: 18000 | J41: =I41*A41 -> 18000 | K41: =E41-J41 -> 0 | L41: =K41/E41 -> 0
A42: 1 | B42: BOLSA | C42: CEBOLLA | D42: 13000 | E42: =A42*D42 -> 13000 | I42: 9000 | J42: =I42*A42 -> 9000 | K42: =E42-J42 -> 4000 | L42: =K42/E42 -> 0.30769231
A43: 2 | B43: UNIDAD | C43: APIO | D43: 3000 | E43: =A43*D43 -> 6000 | I43: 2000 | J43: =I43*A43 -> 4000 | K43: =E43-J43 -> 2000 | L43: =K43/E43 -> 0.33333333
A44: 2 | B44: CAJON | C44: LIMON | D44: 35000 | E44: =A44*D44 -> 70000 | I44: 25000 | J44: =I44*A44 -> 50000 | K44: =E44-J44 -> 20000 | L44: =K44/E44 -> 0.28571429
A45: 2 | B45: CAJON | C45: NARANJA | D45: 19000 | E45: =A45*D45 -> 38000 | I45: 15000 | J45: =I45*A45 -> 30000 | K45: =E45-J45 -> 8000 | L45: =K45/E45 -> 0.21052632
A46: 1 | B46: CAJA | C46: PALTA | D46: 62000 | E46: =A46*D46 -> 62000 | I46: 50000 | J46: =I46*A46 -> 50000 | K46: =E46-J46 -> 12000 | L46: =K46/E46 -> 0.19354839
A47: 3 | B47: KG | C47: PEPINO | D47: 1800 | E47: =A47*D47 -> 5400 | I47: 1500 | J47: =I47*A47 -> 4500 | K47: =E47-J47 -> 900 | L47: =K47/E47 -> 0.16666667
A48: 4 | B48: UNIDAD | C48: MANGO | D48: 2500 | E48: =A48*D48 -> 10000 | I48: =22000/13 -> 1692.3077 | J48: =I48*A48 -> 6769.2308 | K48: =E48-J48 -> 3230.7692 | L48: =K48/E48 -> 0.32307692
A49: 1 | B49: BOLSA | C49: ANCO | D49: 14000 | E49: =A49*D49 -> 14000 | I49: 10000 | J49: =I49*A49 -> 10000 | K49: =E49-J49 -> 4000 | L49: =K49/E49 -> 0.28571429
A50: 3 | B50: ATADO | C50: MENTA | D50: 3000 | E50: =A50*D50 -> 9000 | I50: 2000 | J50: =I50*A50 -> 6000 | K50: =E50-J50 -> 3000 | L50: =K50/E50 -> 0.33333333
A51: 2 | B51: ATADO | C51: PEREJIL | D51: 3000 | E51: =A51*D51 -> 6000 | I51: 1500 | J51: =I51*A51 -> 3000 | K51: =E51-J51 -> 3000 | L51: =K51/E51 -> 0.5
A52: 1.5 | B52: ATADO | C52: PUERRO | D52: 7000 | E52: =A52*D52 -> 10500 | I52: 6000 | J52: =I52*A52 -> 9000 | K52: =E52-J52 -> 1500 | L52: =K52/E52 -> 0.14285714
E54: =SUM(E41:E52) -> 261900 | K54: =SUM(K41:K52) -> 61630.769 | L54: =K54/E54 -> 0.23532176
A56: LA PIADINA | D56: rto: 9 | E56: 46042 | F56: **
A58: CANTIDAD | B58: UNIDAD | C58: PRODUCTO | D58: PRECIO | E58: TOTAL | I58: PRECIO | J58: TOTAL | K58: DIFERENCIA
A59: 3 | B59: KG | C59: TOMATE REDONDO | D59: 4000 | E59: =A59*D59 -> 12000 | I59: 0 | J59: =I59*A59 -> 0 | K59: =E59-J59 -> 12000
A60: 8 | B60: ATADOS | C60: RUCULA AYER | D60: 0 | E60: =A60*D60 -> 0 | I60: 0 | J60: =I60*A60 -> 0 | K60: =E60-J60 -> 0
A61: 4 | B61: ATADOS | C61: RUCULA | D61: 450 | E61: =A61*D61 -> 1800 | I61: =1500/4 -> 375 | J61: =I61*A61 -> 1500 | K61: =E61-J61 -> 300
A62: 1 | B62: CAJON | C62: BERENJENA | D62: 14000 | E62: =A62*D62 -> 14000 | I62: 9000 | J62: =I62*A62 -> 9000 | K62: =E62-J62 -> 5000
E64: =SUM(E59:E62) -> 27800 | K64: =SUM(K59:K62) -> 17300 | L64: =K64/E64 -> 0.62230216
A66: LA MARQUESA | D66: rto: 4 | E66: 46042 | G66: **
A68: CANTIDAD | B68: UNIDAD | C68: PRODUCTO | D68: PRECIO | E68: TOTAL | I68: PRECIO | J68: TOTAL | K68: DIFERENCIA
A69: 1 | B69: CAJON | C69: ESPINACA | D69: 22000 | E69: =A69*D69 -> 22000 | I69: 16000 | J69: =I69*A69 -> 16000 | K69: =E69-J69 -> 6000
A70: 2 | B70: KG | C70: FRUTILLA | D70: 10000 | E70: =A70*D70 -> 20000 | I70: 10000 | J70: =I70*A70 -> 20000 | K70: =E70-J70 -> 0
A71: 2 | B71: KG | C71: LIMA | D71: 4000 | E71: =A71*D71 -> 8000 | I71: 2500 | J71: =I71*A71 -> 5000 | K71: =E71-J71 -> 3000
A72: 5 | B72: KG | C72: LIMON | D72: 3200 | E72: =A72*D72 -> 16000 | I72: =32000/15 -> 2133.3333 | J72: =I72*A72 -> 10666.667 | K72: =E72-J72 -> 5333.3333
A73: 9 | B73: UNIDAD | C73: MANGO - 5 KG - | D73: 2500 | E73: =A73*D73 -> 22500 | I73: 1692 | J73: =I73*A73 -> 15228 | K73: =E73-J73 -> 7272
A74: 15 | B74: UNIDAD | C74: PALTA | D74: 1400 | E74: =A74*D74 -> 21000 | I74: =67000/70 -> 957.14286 | J74: =I74*A74 -> 14357.143 | K74: =E74-J74 -> 6642.8571
A75: 1 | B75: KG | C75: PEPINO | D75: 2000 | E75: =A75*D75 -> 2000 | I75: 1500 | J75: =I75*A75 -> 1500 | K75: =E75-J75 -> 500
A76: 1 | B76: KG | C76: POMELO | D76: 3200 | E76: =A76*D76 -> 3200 | I76: =38000/15 -> 2533.3333 | J76: =I76*A76 -> 2533.3333 | K76: =E76-J76 -> 666.66667
A77: 4 | B77: ATADO | C77: PUERRO | D77: 7500 | E77: =A77*D77 -> 30000 | I77: 6000 | J77: =I77*A77 -> 24000 | K77: =E77-J77 -> 6000
A78: 3.9 | B78: KG | C78: ANCO | D78: 1200 | E78: =A78*D78 -> 4680 | I78: =10000/14 -> 714.28571 | J78: =I78*A78 -> 2785.7143 | K78: =E78-J78 -> 1894.2857
A79: 2 | B79: CAJON | C79: HUEVO | D79: 50000 | E79: =A79*D79 -> 100000 | I79: 43000 | J79: =I79*A79 -> 86000 | K79: =E79-J79 -> 14000
E81: =SUM(E69:E79) -> 249380 | K81: =SUM(K69:K79) -> 51309.143 | L81: =K81/E81 -> 0.20574682
A84: TOTAL DIA | B84: =E81+E64+E54+E34+E20 -> 760230
A86: GANANCIA | B86: =K81+K64+K54+K34+K20 -> 192923.25
A88: % | B88: =B86/B84 -> 0.25376958
A90: BULTOS COMPRADOS
B95: EFECTIVO | C95: MERCADO PAGO | D95: BANCO GALCIA | E95: BANCO RIO | F95: CHEQUES
B96: ='19-01-2026 '!B151 -> 329737.25 | C96: ='19-01-2026 '!C151 -> 1008573.8 | D96: ='19-01-2026 '!D151 -> 1706736.9 | F96: ='19-01-2026 '!F151 -> 2129338.5
A98: INGRESOS
A99: COBR. CTA. CTE | B99: 27800 | C99: 828700 | D99: 172966.87 | E99: 0 | F99: 0
A100: RENDIMIENTO MP | B100: 0 | C100: 728.97 | D100: 0 | E100: 0 | F100: 0
A101: CHE ACREDITADO | B101: 0 | C101: 0 | D101: 1491910.1 | E101: 0 | F101: 1486748.9
A102: COBR. VACIOS | B102: 0 | C102: 0 | D102: 0 | E102: 0 | F102: 0
A103: PRESTAMOS | B103: 0 | C103: 0 | D103: 0 | E103: 0 | F103: 0
A104: IMP. IIBB. 2% | B104: 0 | C104: =C99*2% -> 16574 | D104: =SUM(D98:D103)*2% -> 33297.54 | E104: 0 | F104: 0
A105: IMP. CRED. 0,6% | B105: 0 | C105: =C99*0.6%+C102*0.6% -> 4972.2 | D105: =SUM(D99:D101)*0.6% -> 9989.2619 | E105: 0 | F105: 0
A107: TOTAL | B107: =SUM(B96:B105) -> 357537.25 | C107: =C96+C99+C102+C103-C105+C100-C104 -> 1816456.6 | D107: =D96+D99+D102+D103-D105+D101-D104 -> 3328327.1 | E107: =E96+E99+E102+E103-E105 -> 0 | F107: =F96+F99+F102+F103-F105-D101 -> 637428.4
A109: GASTOS
A110: ING. MERCADO | B110: 4000 | C110: 0 | D110: 0 | E110: 0
A111: CARGA / VACIOS | B111: 0 | C111: 0 | D111: 0 | E111: 0
A112: CHEQ DEBITADO | B112: 0 | C112: 0 | D112: 750000 | E112: 0
A113: PEAJE | B113: 4200 | C113: 0 | D113: 0 | E113: 0
A114: MERCADERIA | B114: =41000+25000+66000 -> 132000 | C114: 123450 | D114: 0 | E114: 0
A115: COMBUSTIBLE | B115: 0 | C115: 0 | D115: 0 | E115: 0
A116: SUELDOS | B116: 0 | C116: 0 | D116: 0 | E116: 0
A117: DEV. PRESTAMOS | B117: 0 | C117: 0 | D117: 0 | E117: 0
A118: AGUA | B118: 0 | C118: 0 | D118: 0 | E118: 0
A119: FLETE JUAN | B119: 0 | C119: 0 | D119: 0 | E119: 0
A120: RETIRO JOAQUIN | B120: 0 | C120: 300000 | D120: 0 | E120: 0
A121: RETIRO FEDERICO | B121: 0 | C121: 0 | D121: 200000 | E121: 0
A122: ALQUILER LOCAL | B122: 0 | C122: 0 | D122: 0 | E122: 0
A123: CONTADOR | B123: 0 | C123: 0 | D123: 0 | E123: 0
A124: ACEITE/AGUA CHATA | B124: 0 | C124: 0 | D124: 0 | E124: 0
A125: REMIS | B125: 0 | C125: 0 | D125: 0 | E125: 0
A126: MECANICO | B126: 0 | C126: 0 | D126: 0 | E126: 0
... A135: MANT. CTA. | B135: 0 | C135: 0 | D135: 0 | E135: 0
A137: IMP. DEB. 0,6% | B137: 0 | C137: =SUM(C110:C134)*0.6% -> 2540.7 | D137: =SUM(D110:D135)*0.6% -> 5700 | E137: =(E114*0.6%)+(E115*0.6%)+(E116*0.6%)+(E119*0.6%)+(E120*0.6%) -> 0
A138: PASE DE CUENTAS | B138: 0 | C138: 0 | E138: =SUM(E111:E136)*0.6%+(E139*0.6%) -> 0
A140: TOTAL SALIDAS | B140: =SUM(B110:B139) -> 140200 | C140: =SUM(C110:C137) -> 425990.7 | D140: =SUM(D110:D138) -> 955700 | E140: =E121+E125+E137-E138 -> 0 | F140: =F114
A142: SALDOS | B142: =B107-B140 -> 217337.25 | C142: =C107-C140+C138 -> 1390465.9 | D142: =D107-D140+15816.83 -> 2388443.9 | E142: =E107-E140 -> 0 | F142: =F107-F140 -> 637428.4
A144: fede | B144: =214777.25-1000-2800-B114 -> 78977.25
A145: joaquin | B145: =114960+B99-3000-1400 -> 138360
...

Sheet 22-01-2026 
A3: FV | E3: rto: 221 | F3: 46044 | I3: COMPRA
A5: CANTIDAD | B5: UNIDAD | C5: PRODUCTO | D5: PRECIO | E5: TOTAL | F5: TOTAL + IVA | I5: PRECIO | J5: TOTAL | K5: DIFERENCIA
A6: 5 | B6: CAJA | C6: DURAZNO | D6: 35000 | E6: =A6*D6 -> 175000 | F6: =E6*1.105 -> 193375 | I6: =131000/5 -> 26200 | J6: =I6*A6 -> 131000 | K6: =F6-J6 -> 62375
A7: 1 | B7: CAJA | C7: UVA BLANCA | D7: 32000 | E7: =A7*D7 -> 32000 | F7: =E7*1.105 -> 35360 | I7: 25000 | J7: =I7*A7 -> 25000 | K7: =F7-J7 -> 10360
A8: 1 | B8: CAJA | C8: UVA RED GLOBE | D8: 25000 | E8: =A8*D8 -> 25000 | F8: =E8*1.105 -> 27625 | I8: 0 | J8: =I8*A8 -> 0 | K8: =F8-J8 -> 27625
A9: 2 | B9: CAJA | C9: MELON | D9: 28000 | E9: =A9*D9 -> 56000 | F9: =E9*1.105 -> 61880 | I9: 23000 | J9: =I9*A9 -> 46000 | K9: =F9-J9 -> 15880
E11: =SUM(E6:E9) -> 288000 | F11: =SUM(F6:F9) -> 318240 | K11: =SUM(K6:K9) -> 116240 | L11: =K11/F11 -> 0.36525892
A14: HOGAR | D14: rto: 3 | E14: 46044
A16: CANTIDAD | B16: UNIDAD | C16: PRODUCTO | D16: PRECIO | E16: TOTAL | I16: PRECIO | J16: TOTAL | K16: DIFERENCIA
A17: 4 | B17: ATADOS | C17: ACELGA | D17: 1200 | E17: =A17*D17 -> 4800 | I17: 1200 | J17: =I17*A17 -> 4800 | K17: =E17-J17 -> 0
A18: 1 | B18: UNIDAD | C18: APIO | D18: 2000 | E18: =A18*D18 -> 2000 | I18: 2000 | J18: =I18*A18 -> 2000 | K18: =E18-J18 -> 0
A19: 3 | B19: UNIDAD | C19: AJO | D19: 1200 | E19: =A19*D19 -> 3600 | I19: 560 | J19: =I19*A19 -> 1680 | K19: =E19-J19 -> 1920
A20: 4 | B20: KG | C20: BATATA | D20: 1500 | E20: =A20*D20 -> 6000 | I20: =11000/11 -> 1000 | J20: =I20*A20 -> 4000 | K20: =E20-J20 -> 2000
A21: 4 | B21: KG | C21: BONIATO | D21: 3800 | E21: =A21*D21 -> 15200 | I21: =23500/11 -> 2136.3636 | J21: =I21*A21 -> 8545.4545 | K21: =E21-J21 -> 6654.5455
A22: 2 | B22: KG | C22: CHAUCHA | D22: 5000 | E22: =A22*D22 -> 10000 | I22: 5000 | J22: =I22*A22 -> 10000 | K22: =E22-J22 -> 0
A23: 2 | B23: KG | C23: MORRON | D23: 3000 | E23: =A23*D23 -> 6000 | I23: =10000/8 -> 1250 | J23: =I23*A23 -> 2500 | K23: =E23-J23 -> 3500
A24: 1 | B24: KG | C24: LECHUGA | D24: 3500 | E24: =A24*D24 -> 3500 | I24: 3000 | J24: =I24*A24 -> 3000 | K24: =E24-J24 -> 500
A25: 2 | B25: UNIDAD | C25: PALTA | D25: 1300 | E25: =A25*D25 -> 2600 | I25: =67000/70 -> 957.14286 | J25: =I25*A25 -> 1914.2857 | K25: =E25-J25 -> 685.71429
A26: 0.5 | B26: ATADOS | C26: PEREJIL | D26: 3500 | E26: =A26*D26 -> 1750 | I26: 2000 | J26: =I26*A26 -> 1000 | K26: =E26-J26 -> 750
A27: 5 | B27: KG | C27: REMOLACHA | D27: 2000 | E27: =A27*D27 -> 10000 | I27: 1400 | J27: =I27*A27 -> 7000 | K27: =E27-J27 -> 3000
A28: 6 | B28: ATADOS | C28: RUCULA | D28: 500 | E28: =A28*D28 -> 3000 | I28: 300 | J28: =I28*A28 -> 1800 | K28: =E28-J28 -> 1200
A29: 6 | B29: KG | C29: TOMATE | D29: 3500 | E29: =A29*D29 -> 21000 | I29: =40000/15 -> 2666.6667 | J29: =I29*A29 -> 16000 | K29: =E29-J29 -> 5000
A30: 1 | B30: ATADOS | C30: VERDEO | D30: 5000 | E30: =A30*D30 -> 5000 | I30: 5000 | J30: =I30*A30 -> 5000 | K30: =E30-J30 -> 0
A31: 4 | B31: KG | C31: ZAPALLITO | D31: 2000 | E31: =A31*D31 -> 8000 | I31: 2000 | J31: =I31*A31 -> 8000 | K31: =E31-J31 -> 0
A32: 2 | B32: KG | C32: ZAPALLITO LARGO | D32: 2000 | E32: =A32*D32 -> 4000 | I32: =18000/14 -> 1285.7143 | J32: =I32*A32 -> 2571.4286 | K32: =E32-J32 -> 1428.5714
A33: 1 | B33: BOLSA | C33: ANCO | D33: 13000 | E33: =A33*D33 -> 13000 | I33: 10000 | J33: =I33*A33 -> 10000 | K33: =E33-J33 -> 3000
A34: 0.5 | B34: BOLSA | C34: CEBOLLA | D34: 13000 | E34: =A34*D34 -> 6500 | I34: 9000 | J34: =I34*A34 -> 4500 | K34: =E34-J34 -> 2000
A35: 1 | B35: BOLSA | C35: PAPA | D35: 14000 | E35: =A35*D35 -> 14000 | I35: 12000 | J35: =I35*A35 -> 12000 | K35: =E35-J35 -> 2000
A36: 1 | B36: BOLSA | C36: ZANAHORIA | D36: 13000 | E36: =A36*D36 -> 13000 | I36: 9000 | J36: =I36*A36 -> 9000 | K36: =E36-J36 -> 4000
A37: 0.5 | B37: CAJA | C37: BANANA | D37: 42000 | E37: =A37*D37 -> 21000 | I37: 38000 | J37: =I37*A37 -> 19000 | K37: =E37-J37 -> 2000
A38: 2 | B38: KG | C38: CIRUELA | D38: 4000 | E38: =A38*D38 -> 8000 | I38: 4000 | J38: =I38*A38 -> 8000 | K38: =E38-J38 -> 0
A39: 3 | B39: KG | C39: DURAZNO | D39: 4000 | E39: =A39*D39 -> 12000 | I39: 0 | J39: =I39*A39 -> 0 | K39: =E39-J39 -> 12000
A40: 3 | B40: KG | C40: LIMON | D40: 3000 | E40: =A40*D40 -> 9000 | I40: =32000/15 -> 2133.3333 | J40: =I40*A40 -> 6400 | K40: =E40-J40 -> 2600
A41: 1 | B41: MEDIA CAJA | C41: MANZANA | D41: 42000 | E41: =A41*D41 -> 42000 | I41: 37000 | J41: =I41*A41 -> 37000 | K41: =E41-J41 -> 5000
A42: 3 | B42: KG | C42: MANZANA GRANNY | D42: 5000 | E42: =A42*D42 -> 15000 | I42: =40000/18 -> 2222.2222 | J42: =I42*A42 -> 6666.6667 | K42: =E42-J42 -> 8333.3333
A43: 7 | B43: KG | C43: NARANJA | D43: 1600 | E43: =A43*D43 -> 11200 | I43: 1000 | J43: =I43*A43 -> 7000 | K43: =E43-J43 -> 4200
A44: 2 | B44: KG | C44: PERA | D44: 3300 | E44: =A44*D44 -> 6600 | I44: =21000/9 -> 2333.3333 | J44: =I44*A44 -> 4666.6667 | K44: =E44-J44 -> 1933.3333
A45: 2 | B45: UNIDAD | C45: MELON | D45: 4000 | E45: =A45*D45 -> 8000 | I45: 0 | J45: =I45*A45 -> 0 | K45: =E45-J45 -> 8000
A46: 2 | B46: KG | C46: UVA | D46: 3500 | E46: =A46*D46 -> 7000 | I46: =25000/8 -> 3125 | J46: =I46*A46 -> 6250 | K46: =E46-J46 -> 750
E48: =SUM(E17:E46) -> 292750 | K48: =SUM(K17:K46) -> 82455.498 | L48: =K48/E48 -> 0.2816584
A52: MUNCHIS | D52: rto: 2 | E52: 46044
A54: CANTIDAD | B54: UNIDAD | C54: PRODUCTO | D54: PRECIO | E54: TOTAL | F54: TOTAL + IVA | I54: PRECIO | J54: TOTAL | K54: DIFERENCIA
A55: 3 | B55: KG | C55: BANANA | D55: 3000 | E55: =A55*D55 -> 9000 | F55: =E55*1.105 -> 9945 | I55: =38000/17 -> 2235.2941 | J55: =I55*A55 -> 6705.8824 | K55: =F55-J55 -> 3239.1176
A56: 0.5 | B56: KG | C56: LEC CRIOLLA | D56: 4000 | E56: =A56*D56 -> 2000 | F56: =E56*1.105 -> 2210 | I56: 300 | J56: =I56*A56 -> 150 | K56: =F56-J56 -> 2060
A57: 2 | B57: KG | C57: TOM CHERRY | D57: 3500 | E57: =A57*D57 -> 7000 | F57: =E57*1.105 -> 7735 | I57: =20000/8 -> 2500 | J57: =I57*A57 -> 5000 | K57: =F57-J57 -> 2735
A58: 4 | B58: KG | C58: NARANJA | D58: 1600 | E58: =A58*D58 -> 6400 | F58: =E58*1.105 -> 7072 | I58: =15000/15 -> 1000 | J58: =I58*A58 -> 4000 | K58: =F58-J58 -> 3072
A59: 1 | B59: CAJON | C59: LIMON | D59: 32000 | E59: =A59*D59 -> 32000 | F59: =E59*1.105 -> 35360 | I59: 25000 | J59: =I59*A59 -> 25000 | K59: =F59-J59 -> 10360
A60: 1 | B60: ATADO | C60: MENTA | D60: 3000 | E60: =A60*D60 -> 3000 | F60: =E60*1.105 -> 3315 | I60: 2000 | J60: =I60*A60 -> 2000 | K60: =F60-J60 -> 1315
A61: 1 | B61: MAPLE | C61: HUEVO | D61: 4500 | E61: =A61*D61 -> 4500 | F61: =E61*1.21 -> 5445 | I61: =38000/12 -> 3166.6667 | J61: =I61*A61 -> 3166.6667 | K61: =F61-J61 -> 2278.3333
E63: =SUM(E55:E61) -> 63900 | F63: =SUM(F55:F61) -> 71082 | K63: =SUM(K55:K61) -> 25059.451 | L63: =K63/E63 -> 0.39216668
A68: TOTAL DIA | B68: =F63+E48+F11 -> 682072
A70: GANANCIA | B70: =K63+K48+K11 -> 223754.95
A72: % | B72: =B70/B68 -> 0.3280518
A74: BULTOS COMPRADOS
B79: EFECTIVO | C79: MERCADO PAGO | D79: BANCO GALCIA | E79: BANCO RIO | F79: CHEQUES
B80: ='20-01-2026 '!B142 -> 217337.25 | C80: ='20-01-2026 '!C142 -> 1390465.9 | D80: ='20-01-2026 '!D142 -> 2388443.9 | F80: ='20-01-2026 '!F142 -> 637428.4
A82: INGRESOS
A83: COBR. CTA. CTE | B83: 0 | C83: 0 | D83: 0 | E83: 0 | F83: 0
A84: RENDIMIENTO MP | B84: 0 | C84: =1010.75+1025.3 -> 2036.05 | D84: 0 | E84: 0 | F84: 0
A85: CHE ACREDITADO | B85: 0 | C85: 0 | D85: 0 | E85: 0 | F85: 0
A86: COBR. VACIOS | B86: 0 | C86: 0 | D86: 0 | E86: 0 | F86: 0
A87: PRESTAMOS | B87: 0 | C87: 0 | D87: 0 | E87: 0 | F87: 0
A88: IMP. IIBB. 2% | B88: 0 | C88: =C83*2% -> 0 | D88: =SUM(D82:D83)*2% -> 0 | E88: 0 | F88: 0
A89: IMP. CRED. 0,6% | B89: 0 | C89: =C83*0.6%+C86*0.6% -> 0 | D89: =SUM(D83:D85)*0.6% -> 0 | E89: 0 | F89: 0
A91: TOTAL | B91: =SUM(B80:B89) -> 217337.25 | C91: =C80+C83+C86+C87-C89+C84-C88 -> 1392501.9 | D91: =D80+D83+D86+D87-D89+D85-D88 -> 2388443.9 | E91: =E80+E83+E86+E87-E89 -> 0 | F91: =F80+F83+F86+F87-F89-D85 -> 637428.4
A93: GASTOS
A94: ING. MERCADO | B94: 1000 | C94: 0 | D94: 0 | E94: 0
A95: CARGA / VACIOS | B95: 0 | C95: 0 | D95: 0 | E95: 0
A96: CHEQ DEBITADO | B96: 0 | C96: 0 | D96: 0 | E96: 0
A97: PEAJE | B97: 2800 | C97: 0 | D97: 0 | E97: 0
A98: MERCADERIA | B98: 0 | C98: 28700 | D98: 0 | E98: 0
A99: COMBUSTIBLE | B99: 0 | C99: 25000 | D99: 0 | E99: 0
A100: SUELDOS | B100: 0 | C100: 0 | D100: 0 | E100: 0
A101: DEV. PRESTAMOS | B101: 0 | C101: 0 | D101: 0 | E101: 0
A102: AGUA | B102: 0 | C102: 0 | D102: 0 | E102: 0
A103: FLETE JUAN | B103: 0 | C103: 0 | D103: 0 | E103: 0
A104: RETIRO JOAQUIN | B104: 0 | C104: 0 | D104: 0 | E104: 0
A105: RETIRO FEDERICO | B105: 0 | C105: 0 | D105: 0 | E105: 0
... A119: MANT. CTA. | B119: 0 | C119: 0 | D119: 0 | E119: 0
A121: IMP. DEB. 0,6% | B121: 0 | C121: =SUM(C94:C118)*0.6% -> 322.2 | D121: 0 | E121: =(E98*0.6%)+(E99*0.6%)+(E100*0.6%)+(E103*0.6%)+(E104*0.6%) -> 0
A122: PASE DE CUENTAS | B122: 0 | C122: 0 | D122: 0 | E122: =SUM(E95:E120)*0.6%+(E123*0.6%) -> 0
A124: TOTAL SALIDAS | B124: =SUM(B94:B123) -> 3800 | C124: =SUM(C94:C121) -> 54022.2 | D124: =SUM(D94:D122) -> 0 | E124: =E105+E109+E121-E122 -> 0 | F124: =F98
A126: SALDOS | B126: =B91-B124 -> 213537.25 | C126: =C91-C124+C122 -> 1338479.7 | D126: =D91-D124 -> 2388443.9 | E126: =E91-E124 -> 0 | F126: =F91-F124 -> 637428.4
A128: fede | B128: =78977.25-B94-B97 -> 75177.25
A129: joaquin | B129: 138360
B131: =SUM(B127:B129) -> 213537.25

Sheet 23-01-2026 
A3: BRASOV | D3: rto: 6 | E3: 46045 | I3: COMPRA
A5: CANTIDAD | B5: UNIDAD | C5: PRODUCTO | D5: PRECIO | E5: TOTAL | I5: PRECIO | J5: TOTAL | K5: DIFERENCIA
A6: 0.5 | B6: CAJON | C6: TOMATE REDONDO | D6: 22000 | E6: =A6*D6 -> 11000 | I6: 15000 | J6: =I6*A6 -> 7500 | K6: =E6-J6 -> 3500
A7: 1 | B7: CAJON | C7: MORRON ROJO | D7: 16000 | E7: =A7*D7 -> 16000 | I7: 10000 | J7: =I7*A7 -> 10000 | K7: =E7-J7 -> 6000
A8: 2 | B8: ATADO | C8: CEB VERDEO | D8: 5000 | E8: =A8*D8 -> 10000 | I8: 4000 | J8: =I8*A8 -> 8000 | K8: =E8-J8 -> 2000
A9: 6 | B9: KG | C9: LIMA | D9: 4000 | E9: =A9*D9 -> 24000 | I9: 3000 | J9: =I9*A9 -> 18000 | K9: =E9-J9 -> 6000
A10: 2 | B10: CAJA | C10: LIMON | D10: 35000 | E10: =A10*D10 -> 70000 | I10: 25000 | J10: =I10*A10 -> 50000 | K10: =E10-J10 -> 20000
A11: 2 | B11: CAJON | C11: NARANJA | D11: 18000 | E11: =A11*D11 -> 36000 | I11: 10000 | J11: =I11*A11 -> 20000 | K11: =E11-J11 -> 16000
E13: =SUM(E6:E11) -> 167000 | K13: =SUM(K6:K11) -> 53500 | L13: =K13/E13 -> 0.32035928
A16: COMO SIEMPRE LAGUNA | D16: rto: 23 | E16: 46045
A18: CANTIDAD | B18: UNIDAD | C18: PRODUCTO | D18: PRECIO | E18: TOTAL | I18: PRECIO | J18: TOTAL | K18: DIFERENCIA
A19: 2 | B19: CAJON | C19: ESPINACA | D19: 20000 | E19: =A19*D19 -> 40000 | I19: 12000 | J19: =I19*A19 -> 24000 | K19: =E19-J19 -> 16000
A20: 1 | B20: BANDEJA | C20: BROTES | D20: 2500 | E20: =A20*D20 -> 2500 | I20: 1500 | J20: =I20*A20 -> 1500 | K20: =E20-J20 -> 1000
A21: 1 | B21: ATADO | C21: CEB VERDEO | D21: 5000 | E21: =A21*D21 -> 5000 | I21: 4000 | J21: =I21*A21 -> 4000 | K21: =E21-J21 -> 1000
A22: 3 | B22: UNIDAD | C22: AJO | D22: 1200 | E22: =A22*D22 -> 3600 | I22: 560 | J22: =I22*A22 -> 1680 | K22: =E22-J22 -> 1920
A23: 2 | B23: BOLSA | C23: PAPA | D23: 22000 | E23: =A23*D23 -> 44000 | I23: 16500 | J23: =I23*A23 -> 33000 | K23: =E23-J23 -> 11000
A24: 4 | B24: UNIDAD | C24: MANGO | D24: 3000 | E24: =A24*D24 -> 12000 | H24: S/COSTO | I24: 0 | J24: =I24*A24 -> 0 | K24: =E24-J24 -> 12000
A25: 1 | B25: KG | C25: BONIATO | D25: 3200 | E25: =A25*D25 -> 3200 | I25: =2400 -> 2400 | J25: =I25*A25 -> 2400 | K25: =E25-J25 -> 800
A26: 1 | B26: ATADO | C26: PEREJIL | D26: 4000 | E26: =A26*D26 -> 4000 | I26: 1500 | J26: =I26*A26 -> 1500 | K26: =E26-J26 -> 2500
A27: 1 | B27: CAJON | C27: LEC FRANCESA | D27: 14000 | E27: =A27*D27 -> 14000 | I27: 13000 | J27: =I27*A27 -> 13000 | K27: =E27-J27 -> 1000
A28: 1 | B28: CAJON | C28: LEC MORADA | D28: 12000 | E28: =A28*D28 -> 12000 | I28: 5000 | J28: =I28*A28 -> 5000 | K28: =E28-J28 -> 7000
A29: 1 | B29: CAJON | C29: RUCULA | D29: 10000 | E29: =A29*D29 -> 10000 | I29: 5000 | J29: =I29*A29 -> 5000 | K29: =E29-J29 -> 5000
A30: 1 | B30: CAJA | C30: LIMON | D30: 35000 | E30: =A30*D30 -> 35000 | I30: 25000 | J30: =I30*A30 -> 25000 | K30: =E30-J30 -> 10000
A31: 0.5 | B31: CAJON | C31: POMELO | D31: 35000 | E31: =A31*D31 -> 17500 | I31: 25000 | J31: =I31*A31 -> 12500 | K31: =E31-J31 -> 5000
A32: 0.5 | B32: CAJON | C32: NARANJA | D32: 18000 | E32: =A32*D32 -> 9000 | I32: 10000 | J32: =I32*A32 -> 5000 | K32: =E32-J32 -> 4000
A33: 0.25 | B33: KG | C33: JENGIBRE | D33: 5000 | E33: =A33*D33 -> 1250 | I33: 4000 | J33: =I33*A33 -> 1000 | K33: =E33-J33 -> 250
A34: 1 | B34: ATADO | C34: MENTA | D34: 3000 | E34: =A34*D34 -> 3000 | I34: 2000 | J34: =I34*A34 -> 2000 | K34: =E34-J34 -> 1000
E36: =SUM(E19:E34) -> 216050 | K36: =SUM(K19:K34) -> 79470 | L36: =K36/E36 -> 0.36783152
A40: LA MARQUESA | D40: rto: 5 | E40: 46045
A42: CANTIDAD | B42: UNIDAD | C42: PRODUCTO | D42: PRECIO | E42: TOTAL | I42: PRECIO | J42: TOTAL | K42: DIFERENCIA
A43: 1 | B43: CAJON | C43: NARANJA | D43: 16000 | E43: =A43*D43 -> 16000 | I43: 10000 | J43: =I43*A43 -> 10000 | K43: =E43-J43 -> 6000
A44: 1 | B44: CAJA | C44: LIMON | D44: 32000 | E44: =A44*D44 -> 32000 | I44: 25000 | J44: =I44*A44 -> 25000 | K44: =E44-J44 -> 7000
A45: 1 | B45: KG | C45: BANANA | D45: 2800 | E45: =A45*D45 -> 2800 | I45: 2000 | J45: =I45*A45 -> 2000 | K45: =E45-J45 -> 800
E47: =SUM(E43:E45) -> 50800 | K47: =SUM(K43:K45) -> 13800 | L47: =K47/E47 -> 0.27165354
A51: LA PIADINA | D51: rto: 10 | E51: 46045
A53: CANTIDAD | B53: UNIDAD | C53: PRODUCTO | D53: PRECIO | E53: TOTAL | I53: PRECIO | J53: TOTAL | K53: DIFERENCIA
A54: 1 | B54: CAJON | C54: RUCULA | D54: 9000 | E54: =A54*D54 -> 9000 | I54: 5000 | J54: =I54*A54 -> 5000 | K54: =E54-J54 -> 4000
A55: 3 | B55: ATADO | C55: ALBAHACA | D55: 1000 | E55: =A55*D55 -> 3000 | I55: =2500/6 -> 416.66667 | J55: =I55*A55 -> 1250 | K55: =E55-J55 -> 1750
A56: 1 | B56: KG | C56: LEC FRACNESA | D56: 3500 | E56: =A56*D56 -> 3500 | H56: S/COST | J56: =I56*A56 -> 0 | K56: =E56-J56 -> 3500
A57: 4 | B57: UNIDAD | C57: PALTA | D57: 1400 | E57: =A57*D57 -> 5600 | I57: =67000/70 -> 957.14286 | J57: =I57*A57 -> 3828.5714 | K57: =E57-J57 -> 1771.4286
A58: 3 | B58: ATADO | C58: ESPINACA | D58: 1500 | E58: =A58*D58 -> 4500 | H58: S/COST | J58: =I58*A58 -> 0 | K58: =E58-J58 -> 4500
A59: 1 | B59: KG | C59: LIMON | D59: 3200 | E59: =A59*D59 -> 3200 | I59: =35000/15 -> 2333.3333 | J59: =I59*A59 -> 2333.3333 | K59: =E59-J59 -> 866.66667
A60: 3 | B60: ATADO | C60: REMOLACHA | D60: 1800 | E60: =A60*D60 -> 5400 | I60: 1000 | J60: =I60*A60 -> 3000 | K60: =E60-J60 -> 2400
A61: 4 | B61: KG | C61: TOM REDONDO | D61: 1800 | E61: =A61*D61 -> 7200 | I61: =15000/15 -> 1000 | J61: =I61*A61 -> 4000 | K61: =E61-J61 -> 3200
A62: 1 | B62: KG | C62: MANZANA | D62: 5000 | E62: =A62*D62 -> 5000 | I62: 5000 | J62: =I62*A62 -> 5000 | K62: =E62-J62 -> 0
A63: 2 | B63: KG | C63: NARANJA | D63: 1500 | E63: =A63*D63 -> 3000 | I63: 1000 | J63: =I63*A63 -> 2000 | K63: =E63-J63 -> 1000
A64: 0.35 | B64: KG | C64: KIWI | D64: 12000 | E64: =A64*D64 -> 4200 | I64: =65000/7 -> 9285.7143 | J64: =I64*A64 -> 3250 | K64: =E64-J64 -> 950
A65: 2 | B65: CUBETA | C65: ARANDANO | D65: 3000 | E65: =A65*D65 -> 6000 | I65: =22000/12 -> 1833.3333 | J65: =I65*A65 -> 3666.6667 | K65: =E65-J65 -> 2333.3333
A66: 1 | B66: KG | C66: DURAZNO | D66: 4500 | E66: =A66*D66 -> 4500 | I66: 4000 | J66: =I66*A66 -> 4000 | K66: =E66-J66 -> 500
A67: 2 | B67: KG | C67: BANANA | D67: 3000 | E67: =A67*D67 -> 6000 | I67: 2000 | J67: =I67*A67 -> 4000 | K67: =E67-J67 -> 2000
A68: 0.5 | B68: KG | C68: UVA | D68: 4500 | E68: =A68*D68 -> 2250 | I68: =25000/8 -> 3125 | J68: =I68*A68 -> 1562.5 | K68: =E68-J68 -> 687.5
E70: =SUM(E54:E68) -> 72350 | K70: =SUM(K54:K68) -> 29458.929 | L70: =K70/E70 -> 0.40717248
A74: MESTIZO | D74: rto: 6 | E74: 46045
A76: CANTIDAD | B76: UNIDAD | C76: PRODUCTO | D76: PRECIO | E76: TOTAL | I76: PRECIO | J76: TOTAL | K76: DIFERENCIA
A77: 2 | B77: BOLSA | C77: PAPA BLANCA | D77: 22000 | E77: =A77*D77 -> 44000 | I77: 16500 | J77: =I77*A77 -> 33000 | K77: =E77-J77 -> 11000
A78: 2 | B78: ATADO | C78: ALBAHACA | D78: 1000 | E78: =A78*D78 -> 2000 | I78: =2500/6 -> 416.66667 | J78: =I78*A78 -> 833.33333 | K78: =E78-J78 -> 1166.6667
A79: 3.1 | B79: KG | C79: TOM PERITA | D79: 3500 | E79: =A79*D79 -> 10850 | I79: 2800 | J79: =I79*A79 -> 8680 | K79: =E79-J79 -> 2170
E81: =SUM(E77:E80) -> 56850 | K81: =SUM(K77:K79) -> 14336.667 | L81: =K81/E81 -> 0.25218411
A85: RAKUS | D85: rto: 16 | E85: 46045
A87: CANTIDAD | B87: UNIDAD | C87: PRODUCTO | D87: PRECIO | E87: TOTAL | I87: PRECIO | J87: TOTAL | K87: DIFERENCIA
A88: 5 | B88: KG | C88: BANANA ECUADOR | D88: 3000 | E88: =A88*D88 -> 15000 | I88: 2000 | J88: =I88*A88 -> 10000 | K88: =E88-J88 -> 5000
A89: 4 | B89: KG | C89: MORRON ROJO | D89: 2200 | E89: =A89*D89 -> 8800 | I89: =10000/8 -> 1250 | J89: =I89*A89 -> 5000 | K89: =E89-J89 -> 3800
A90: 2 | B90: ATADOS | C90: REMOLACHA | D90: 2000 | E90: =A90*D90 -> 4000 | I90: 1000 | J90: =I90*A90 -> 2000 | K90: =E90-J90 -> 2000
A91: 8 | B91: ATADO | C91: RUCULA | D91: 500 | E91: =A91*D91 -> 4000 | I91: =2000/6 -> 333.33333 | J91: =I91*A91 -> 2666.6667 | K91: =E91-J91 -> 1333.3333
A92: 1 | B92: KG | C92: KIWI | D92: 12000 | E92: =A92*D92 -> 12000 | I92: =65000/7 -> 9285.7143 | J92: =I92*A92 -> 9285.7143 | K92: =E92-J92 -> 2714.2857
A93: 1 | B93: KG | C93: CHAMPI | D93: 18500 | E93: =A93*D93 -> 18500 | I93: 16000 | J93: =I93*A93 -> 16000 | K93: =E93-J93 -> 2500
A94: 3 | B94: KG | C94: TOM CHERRY | D94: 3800 | E94: =A94*D94 -> 11400 | I94: =20000/8 -> 2500 | J94: =I94*A94 -> 7500 | K94: =E94-J94 -> 3900
A95: 1 | B95: CAJA | C95: MANZANA GRANNY | D95: 52000 | E95: =A95*D95 -> 52000 | I95: 40000 | J95: =I95*A95 -> 40000 | K95: =E95-J95 -> 12000
A96: 3 | B96: CAJON | C96: NARANJA S/SEMI | D96: 22000 | E96: =A96*D96 -> 66000 | I96: 18000 | J96: =I96*A96 -> 54000 | K96: =E96-J96 -> 12000
A97: 2 | B97: CAJA | C97: LIMON | D97: 38000 | E97: =A97*D97 -> 76000 | I97: 30000 | J97: =I97*A97 -> 60000 | K97: =E97-J97 -> 16000
A98: 1 | B98: ATADO | C98: MENTA | D98: 3000 | E98: =A98*D98 -> 3000 | I98: 2000 | J98: =I98*A98 -> 2000 | K98: =E98-J98 -> 1000
A99: 4 | B99: KG | C99: LIMA | D99: 4000 | E99: =A99*D99 -> 16000 | I99: 3000 | J99: =I99*A99 -> 12000 | K99: =E99-J99 -> 4000
E101: =SUM(E88:E100) -> 286700 | K101: =SUM(K88:K99) -> 66247.619 | L101: =K101/E101 -> 0.23106948
A103: FABRIC SUSHI - GORRITI | D103: rto: 1 | E103: 46045 | I103: COMPRA
A105: CANTIDAD | B105: UNIDAD | C105: PRODUCTO | D105: PRECIO | E105: TOTAL | F105: TOTAL + IVA | I105: PRECIO | J105: TOTAL | K105: DIFERENCIA
A106: 1 | B106: ATADO | C106: PUERRO | D106: 6000 | E106: =A106*D106 -> 6000 | F106: =E106*1.105 -> 6630 | I106: 6000 | J106: =I106*A106 -> 6000 | K106: =E106-J106 -> 0
A107: 0.5 | B107: KG | C107: TOMATE REDONDO | D107: 3500 | E107: =A107*D107 -> 1750 | F107: =E107*1.105 -> 1933.75 | I107: 1000 | J107: =I107*A107 -> 500 | K107: =E107-J107 -> 1250
A108: 3 | B108: KG | C108: BATATA | D108: 1400 | E108: =A108*D108 -> 4200 | F108: =E108*1.105 -> 4641 | I108: 1000 | J108: =I108*A108 -> 3000 | K108: =E108-J108 -> 1200
A109: 2 | B109: ATADO | C109: CILANTRO | D109: 2500 | E109: =A109*D109 -> 5000 | F109: =E109*1.105 -> 5525 | I109: 1000 | J109: =I109*A109 -> 2000 | K109: =E109-J109 -> 3000
A110: 2 | B110: ATADO | C110: CIBOULLETE | D110: 3500 | E110: =A110*D110 -> 7000 | F110: =E110*1.105 -> 7735 | I110: 2000 | J110: =I110*A110 -> 4000 | K110: =E110-J110 -> 3000
A111: 0.5 | B111: KG | C111: PEPINO | D111: 1500 | E111: =A111*D111 -> 750 | F111: =E111*1.105 -> 828.75 | I111: 1600 | J111: =I111*A111 -> 800 | K111: =E111-J111 -> -50
A112: 1 | B112: UNIDAD | C112: REP ROJO | D112: 1800 | E112: =A112*D112 -> 1800 | F112: =E112*1.105 -> 1989 | I112: 1500 | J112: =I112*A112 -> 1500 | K112: =E112-J112 -> 300
A113: 1 | B113: BANDEJA | C113: PORTOBELLO | D113: 6000 | E113: =A113*D113 -> 6000 | F113: =E113*1.105 -> 6630 | I113: 0 | J113: =I113*A113 -> 0 | K113: =E113-J113 -> 6000
E115: =SUM(E106:E113) -> 32500 | F115: =SUM(F106:F113) -> 35912.5 | K115: =SUM(K106:K113) -> 14700 | L115: =K115/E115 -> 0.45230769
A117: Comisión Juan | B117: 0.04 | E117: =E115*0.04 -> 1300
A121: CAFÉ MARTÍNEZ - MORENO | E121: rto: 1 | F121: 46045 | I121: COMPRA
A123: CANTIDAD | B123: UNIDAD | C123: PRODUCTO | D123: PRECIO | E123: TOTAL | I123: PRECIO | J123: TOTAL | K123: DIFERENCIA
A124: 1.5 | B124: KG | C124: LEC FRANCESA | D124: 3500 | E124: =A124*D124 -> 5250 | H124: S/COSTO | I124: 0 | J124: =I124*A124 -> 0 | K124: =E124-J124 -> 5250
A125: 0.5 | B125: KG | C125: LEC MORADA | D125: 3500 | E125: =A125*D125 -> 1750 | H125: S/COSTO | I125: 0 | J125: =I125*A125 -> 0 | K125: =E125-J125 -> 1750
A126: 2 | B126: ATADO | C126: RUCULA | D126: 450 | E126: =A126*D126 -> 900 | H126: S/COSTO | I126: 0 | J126: =I126*A126 -> 0 | K126: =E126-J126 -> 900
A127: 2 | B127: CAJON | C127: NARANJA | D127: 15000 | E127: =A127*D127 -> 30000 | I127: 10000 | J127: =I127*A127 -> 20000 | K127: =E127-J127 -> 10000
A128: 1 | B128: ATADO | C128: ALBAHACA | D128: 1000 | E128: =A128*D128 -> 1000 | I128: =2500/6 -> 416.66667 | J128: =I128*A128 -> 416.66667 | K128: =E128-J128 -> 583.33333
A129: 1 | B129: ATADO | C129: MENTA | D129: 3000 | E129: =A129*D129 -> 3000 | I129: 2000 | J129: =I129*A129 -> 2000 | K129: =E129-J129 -> 1000
A130: 1.5 | B130: KG | C130: TOM CHERRY | D130: 3500 | E130: =A130*D130 -> 5250 | I130: =20000/8 -> 2500 | J130: =I130*A130 -> 3750 | K130: =E130-J130 -> 1500
A131: 1 | B131: KG | C131: TOMATE REDONDO | D131: 3200 | E131: =A131*D131 -> 3200 | I131: 1000 | J131: =I131*A131 -> 1000 | K131: =E131-J131 -> 2200
A132: 12 | B132: UNIDAD | C132: PALTA | D132: 1000 | E132: =A132*D132 -> 12000 | I132: =53000/80 -> 662.5 | J132: =I132*A132 -> 7950 | K132: =E132-J132 -> 4050
A133: 1 | B133: KG | C133: KIWI | D133: 11500 | E133: =A133*D133 -> 11500 | I133: =65000/7 -> 9285.7143 | J133: =I133*A133 -> 9285.7143 | K133: =E133-J133 -> 2214.2857
A134: 1 | B134: KG | C134: BANANA | D134: 2600 | E134: =A134*D134 -> 2600 | I134: 2000 | J134: =I134*A134 -> 2000 | K134: =E134-J134 -> 600
A135: 2 | B135: KG | C135: FRUTILLA | D135: 6000 | E135: =A135*D135 -> 12000 | I135: 5000 | J135: =I135*A135 -> 10000 | K135: =E135-J135 -> 2000
E137: =SUM(E124:E135) -> 88450 | K137: =SUM(K124:K135) -> 32047.619 | L137: =K137/E137 -> 0.36232469
...

Sheet 26-01-2026 
A3: BRASOV | D3: rto: 7 | E3: 46048 | I3: COMPRA
A5: CANTIDAD | B5: UNIDAD | C5: PRODUCTO | D5: PRECIO | E5: TOTAL | I5: PRECIO | J5: TOTAL | K5: DIFERENCIA
A6: 4 | B6: UNIDAD | C6: MANGO | D6: 2500 | E6: =A6*D6 -> 10000 | I6: =15000/12 -> 1250 | J6: =I6*A6 -> 5000 | K6: =E6-J6 -> 5000
A7: 1 | B7: ATADO | C7: PUERRO | D7: 6500 | E7: =A7*D7 -> 6500 | I7: 5500 | J7: =I7*A7 -> 5500 | K7: =E7-J7 -> 1000
A8: 1 | B8: BANDEJA | C8: TOM CHERRY | D8: 17500 | E8: =A8*D8 -> 17500 | I8: =2500*5 -> 12500 | J8: =I8*A8 -> 12500 | K8: =E8-J8 -> 5000
A9: 1 | B9: CAJON | C9: TOMATE REDONDO | D9: 22000 | E9: =A9*D9 -> 22000 | I9: 11000 | J9: =I9*A9 -> 11000 | K9: =E9-J9 -> 11000
A10: 2 | B10: ATADO | C10: CIBOULLETE | D10: 3000 | E10: =A10*D10 -> 6000 | I10: 2000 | J10: =I10*A10 -> 4000 | K10: =E10-J10 -> 2000
A11: 0.5 | B11: KG | C11: JENGIBRE | D11: 6500 | E11: =A11*D11 -> 3250 | I11: 6000 | J11: =I11*A11 -> 3000 | K11: =E11-J11 -> 250
A12: 6 | B12: KG | C12: LIMA | D12: 3500 | E12: =A12*D12 -> 21000 | I12: 3000 | J12: =I12*A12 -> 18000 | K12: =E12-J12 -> 3000
A13: 1 | B13: CAJA | C13: LIMON | D13: 35000 | E13: =A13*D13 -> 35000 | I13: 28000 | J13: =I13*A13 -> 28000 | K13: =E13-J13 -> 7000
A14: 2 | B14: ATADO | C14: MENTA | D14: 3000 | E14: =A14*D14 -> 6000 | I14: 2000 | J14: =I14*A14 -> 4000 | K14: =E14-J14 -> 2000
A15: 4 | B15: ATADO | C15: PEREJIL | D15: 3000 | E15: =A15*D15 -> 12000 | I15: 2000 | J15: =I15*A15 -> 8000 | K15: =E15-J15 -> 4000
A16: 2 | B16: ATADO | C16: CEB VERDEO | D16: 5000 | E16: =A16*D16 -> 10000 | I16: 4000 | J16: =I16*A16 -> 8000 | K16: =E16-J16 -> 2000
A17: 1 | B17: BOLSA | C17: BONIATO | D17: 28500 | E17: =A17*D17 -> 28500 | I17: 25000 | J17: =I17*A17 -> 25000 | K17: =E17-J17 -> 3500
A18: 1 | B18: BOLSA | C18: ANCO | D18: 17000 | E18: =A18*D18 -> 17000 | I18: 14000 | J18: =I18*A18 -> 14000 | K18: =E18-J18 -> 3000
E20: =SUM(E6:E18) -> 194750 | K20: =SUM(K6:K18) -> 48750 | L20: =K20/E20 -> 0.25032092
A23: COMO SIEMPRE LAGUNA | D23: rto: 24 | E23: 46048
A25: CANTIDAD | B25: UNIDAD | C25: PRODUCTO | D25: PRECIO | E25: TOTAL | I25: PRECIO | J25: TOTAL | K25: DIFERENCIA
A26: 1 | B26: BOLSA | C26: ZANAHORIA | D26: 12000 | E26: =A26*D26 -> 12000 | I26: 9000 | J26: =I26*A26 -> 9000 | K26: =E26-J26 -> 3000
A27: 1 | B27: CAJON | C27: ESPINACA | D27: 16000 | E27: =A27*D27 -> 16000 | I27: 12000 | J27: =I27*A27 -> 12000 | K27: =E27-J27 -> 4000
A28: 0.5 | B28: CAJON | C28: HUEVO | D28: 50000 | E28: =A28*D28 -> 25000 | I28: 40000 | J28: =I28*A28 -> 20000 | K28: =E28-J28 -> 5000
A29: 1 | B29: KG | C29: CHAMPI | D29: 20000 | E29: =A29*D29 -> 20000 | I29: 17000 | J29: =I29*A29 -> 17000 | K29: =E29-J29 -> 3000
A30: 1 | B30: KG | C30: PORTO | D30: 22000 | E30: =A30*D30 -> 22000 | I30: 19000 | J30: =I30*A30 -> 19000 | K30: =E30-J30 -> 3000
A31: 1 | B31: UNIDAD | C31: APIO | D31: 1500 | E31: =A31*D31 -> 1500 | I31: 1000 | J31: =I31*A31 -> 1000 | K31: =E31-J31 -> 500
A32: 4 | B32: KG | C32: CEB MORADA | D32: 1600 | E32: =A32*D32 -> 6400 | I32: 1000 | J32: =I32*A32 -> 4000 | K32: =E32-J32 -> 2400
A33: 1 | B33: CAJON | C33: TOM PERITA | D33: 25000 | E33: =A33*D33 -> 25000 | I33: 15000 | J33: =I33*A33 -> 15000 | K33: =E33-J33 -> 10000
A34: 1 | B34: BOLSA | C34: CEBOLLA | D34: 13000 | E34: =A34*D34 -> 13000 | I34: 10000 | J34: =I34*A34 -> 10000 | K34: =E34-J34 -> 3000
A35: 3 | B35: KG | C35: PIM ROJO | D35: 2800 | E35: =A35*D35 -> 8400 | I35: =15000/8 -> 1875 | J35: =I35*A35 -> 5625 | K35: =E35-J35 -> 2775
A36: 1 | B36: KG | C36: PIM VERDE | D36: 3200 | E36: =A36*D36 -> 3200 | I36: 3000 | J36: =I36*A36 -> 3000 | K36: =E36-J36 -> 200
A37: 1 | B37: KG | C37: PIM AMARILLO | D37: 3200 | E37: =A37*D37 -> 3200 | I37: 2000 | J37: =I37*A37 -> 2000 | K37: =E37-J37 -> 1200
A38: 1 | B38: KG | C38: ZAP LARGO | D38: 2100 | E38: =A38*D38 -> 2100 | I38: 1500 | J38: =I38*A38 -> 1500 | K38: =E38-J38 -> 600
A39: 1 | B39: KG | C39: BERENJENA | D39: 1800 | E39: =A39*D39 -> 1800 | I39: =9000/8 -> 1125 | J39: =I39*A39 -> 1125 | K39: =E39-J39 -> 675
A40: 1 | B40: KG | C40: LIMA | D40: 4000 | E40: =A40*D40 -> 4000 | I40: 3000 | J40: =I40*A40 -> 3000 | K40: =E40-J40 -> 1000
A41: 2 | B41: ATADO | C41: ALBAHACA | D41: 1000 | E41: =A41*D41 -> 2000 | I41: =3000/6 -> 500 | J41: =I41*A41 -> 1000 | K41: =E41-J41 -> 1000
A42: 12 | B42: UNIDAD | C42: PALTA | D42: 1300 | E42: =A42*D42 -> 15600 | I42: 791 | J42: =I42*A42 -> 9492 | K42: =E42-J42 -> 6108
A43: 1 | B43: ATADO | C43: CILANTRO | D43: 3000 | E43: =A43*D43 -> 3000 | I43: 2000 | J43: =I43*A43 -> 2000 | K43: =E43-J43 -> 1000
A44: 1 | B44: ATADO | C44: CIBOULLETE | D44: 3000 | E44: =A44*D44 -> 3000 | I44: 2000 | J44: =I44*A44 -> 2000 | K44: =E44-J44 -> 1000
A45: 1 | B45: CAJON | C45: RUCULA | D45: 9000 | E45: =A45*D45 -> 9000 | I45: 5000 | J45: =I45*A45 -> 5000 | K45: =E45-J45 -> 4000
A46: 0.35 | B46: KG | C46: PEPINO | D46: 2500 | E46: =A46*D46 -> 875 | I46: 1500 | J46: =I46*A46 -> 525 | K46: =E46-J46 -> 350
A47: 1 | B47: ATADO | C47: ENELDO | D47: 3000 | E47: =A47*D47 -> 3000 | I47: 2000 | J47: =I47*A47 -> 2000 | K47: =E47-J47 -> 1000
A48: 4 | B48: UNIDAD | C48: MANGO | D48: 2500 | E48: =A48*D48 -> 10000 | I48: 1250 | J48: =I48*A48 -> 5000 | K48: =E48-J48 -> 5000
A49: 0.5 | B49: CAJA | C49: LIMON | D49: 35000 | E49: =A49*D49 -> 17500 | I49: 28000 | J49: =I49*A49 -> 14000 | K49: =E49-J49 -> 3500
A50: 0.5 | B50: CAJON | C50: NARANJA | D50: 19000 | E50: =A50*D50 -> 9500 | I50: 15000 | J50: =I50*A50 -> 7500 | K50: =E50-J50 -> 2000
A51: 0.5 | B51: CAJON | C51: POMELO | D51: 32000 | E51: =A51*D51 -> 16000 | I51: 25000 | J51: =I51*A51 -> 12500 | K51: =E51-J51 -> 3500
E53: =SUM(E26:E51) -> 253075 | K53: =SUM(K26:K51) -> 68808 | L53: =K53/E53 -> 0.27188778
A57: LA MARQUESA | D57: rto: 6 | E57: 46048
A59: CANTIDAD | B59: UNIDAD | C59: PRODUCTO | D59: PRECIO | E59: TOTAL | I59: PRECIO | J59: TOTAL | K59: DIFERENCIA
A60: 4 | B60: UNIDAD | C60: AJO | D60: 1200 | E60: =A60*D60 -> 4800 | I60: 560 | J60: =I60*A60 -> 2240 | K60: =E60-J60 -> 2560
A61: 1 | B61: KG | C61: BANANA | D61: 2400 | E61: =A61*D61 -> 2400 | I61: =30000/18 -> 1666.6667 | J61: =I61*A61 -> 1666.6667 | K61: =E61-J61 -> 733.33333
A62: 1 | B62: KG | C62: BERENJENA | D62: 1800 | E62: =A62*D62 -> 1800 | I62: =9000/8 -> 1125 | J62: =I62*A62 -> 1125 | K62: =E62-J62 -> 675
A63: 1 | B63: KG | C63: CHAMPI | D63: 20000 | E63: =A63*D63 -> 20000 | I63: 17000 | J63: =I63*A63 -> 17000 | K63: =E63-J63 -> 3000
A64: 1 | B64: CAJON | C64: ESPINACA | D64: 16000 | E64: =A64*D64 -> 16000 | I64: 12000 | J64: =I64*A64 -> 12000 | K64: =E64-J64 -> 4000
A65: 1 | B65: CAJA | C65: FRUTILLA | D65: 38000 | E65: =A65*D65 -> 38000 | I65: 34000 | J65: =I65*A65 -> 34000 | K65: =E65-J65 -> 4000
A66: 1 | B66: KG | C66: KIWI | D66: 12000 | E66: =A66*D66 -> 12000 | I66: =65000/7 -> 9285.7143 | J66: =I66*A66 -> 9285.7143 | K66: =E66-J66 -> 2714.2857
A67: 2 | B67: KG | C67: LIMA | D67: 4000 | E67: =A67*D67 -> 8000 | I67: 3000 | J67: =I67*A67 -> 6000 | K67: =E67-J67 -> 2000
A68: 1 | B68: CAJA | C68: LIMON | D68: 35000 | E68: =A68*D68 -> 35000 | I68: 28000 | J68: =I68*A68 -> 28000 | K68: =E68-J68 -> 7000
A69: 1 | B69: KG | C69: PIM ROJO | D69: 3200 | E69: =A69*D69 -> 3200 | I69: =15000/8 -> 1875 | J69: =I69*A69 -> 1875 | K69: =E69-J69 -> 1325
A70: 1 | B70: KG | C70: PIM VERDE | D70: 3200 | E70: =A70*D70 -> 3200 | I70: 3000 | J70: =I70*A70 -> 3000 | K70: =E70-J70 -> 200
A71: 1 | B71: CAJON | C71: NARANJA | D71: 18000 | E71: =A71*D71 -> 18000 | I71: 15000 | J71: =I71*A71 -> 15000 | K71: =E71-J71 -> 3000
A72: 10 | B72: UNIDAD | C72: PALTA | D72: 1300 | E72: =A72*D72 -> 13000 | I72: 791 | J72: =I72*A72 -> 7910 | K72: =E72-J72 -> 5090
A73: 0.7 | B73: KG | C73: PEPINO | D73: 2200 | E73: =A73*D73 -> 1540 | I73: 1500 | J73: =I73*A73 -> 1050 | K73: =E73-J73 -> 490
A74: 1 | B74: KG | C74: TOM CHERRY | D74: 3500 | E74: =A74*D74 -> 3500 | I74: =20000/8 -> 2500 | J74: =I74*A74 -> 2500 | K74: =E74-J74 -> 1000
A75: 5 | B75: KG | C75: TOM REDONDO | D75: 2000 | E75: =A75*D75 -> 10000 | I75: =11000/15 -> 733.33333 | J75: =I75*A75 -> 3666.6667 | K75: =E75-J75 -> 6333.3333
A76: 1 | B76: KG | C76: ANCO | D76: 1800 | E76: =A76*D76 -> 1800 | I76: =14000/15 -> 933.33333 | J76: =I76*A76 -> 933.33333 | K76: =E76-J76 -> 866.66667
A77: 1.2 | B77: KG | C77: ZAP LARGO | D77: 2100 | E77: =A77*D77 -> 2520 | I77: 1500 | J77: =I77*A77 -> 1800 | K77: =E77-J77 -> 720
A78: 3 | B78: CAJON | C78: HUEVO | D78: 50000 | E78: =A78*D78 -> 150000 | I78: 40000 | J78: =I78*A78 -> 120000 | K78: =E78-J78 -> 30000
E80: =SUM(E60:E78) -> 344760 | K80: =SUM(K60:K78) -> 75707.619 | L80: =K80/E80 -> 0.21959514
A84: PAULA CASERO | D84: rto: 6 | E84: 46048
A86: CANTIDAD | B86: UNIDAD | C86: PRODUCTO | D86: PRECIO | E86: TOTAL | I86: PRECIO | J86: TOTAL | K86: DIFERENCIA
A87: 1 | B87: BOLSA | C87: CEBOLLA | D87: 13000 | E87: =A87*D87 -> 13000 | I87: 10000 | J87: =I87*A87 -> 10000 | K87: =E87-J87 -> 3000
A88: 2 | B88: BOLSA | C88: PAPA | D88: 21000 | E88: =A88*D88 -> 42000 | I88: 17000 | J88: =I88*A88 -> 34000 | K88: =E88-J88 -> 8000
A89: 1 | B89: BOLSA | C89: ANCO | D89: 18000 | E89: =A89*D89 -> 18000 | I89: 14000 | J89: =I89*A89 -> 14000 | K89: =E89-J89 -> 4000
A90: 1 | B90: BOLSA | C90: ZANAHORIA | D90: 12000 | E90: =A90*D90 -> 12000 | I90: 9000 | J90: =I90*A90 -> 9000 | K90: =E90-J90 -> 3000
A91: 2 | B91: KG | C91: BERENJENA | D91: 1800 | E91: =A91*D91 -> 3600 | I91: =9000/8 -> 1125 | J91: =I91*A91 -> 2250 | K91: =E91-J91 -> 1350
A92: 5 | B92: KG | C92: TOMATE | D92: 2400 | E92: =A92*D92 -> 12000 | I92: =11000/15 -> 733.33333 | J92: =I92*A92 -> 3666.6667 | K92: =E92-J92 -> 8333.3333
A93: 1.2 | B93: KG | C93: LEC MANTECA | D93: 4000 | E93: =A93*D93 -> 4800 | I93: 3000 | J93: =I93*A93 -> 3600 | K93: =E93-J93 -> 1200
A94: 3 | B94: KG | C94: LIMON | D94: 2400 | E94: =A94*D94 -> 7200 | I94: =28000/15 -> 1866.6667 | J94: =I94*A94 -> 5600 | K94: =E94-J94 -> 1600
A95: 1 | B95: UNIDAD | C95: REP BLANCO | D95: 2000 | E95: =A95*D95 -> 2000 | I95: 1500 | J95: =I95*A95 -> 1500 | K95: =E95-J95 -> 500
A96: 1 | B96: UNIDAD | C96: REP ROJO | D96: 2000 | E96: =A96*D96 -> 2000 | I96: 1500 | J96: =I96*A96 -> 1500 | K96: =E96-J96 -> 500
A97: 3 | B97: ATADO | C97: RUCULA | D97: 500 | E97: =A97*D97 -> 1500 | I97: 0 | J97: =I97*A97 -> 0 | K97: =E97-J97 -> 1500
A98: 2 | B98: KG | C98: ZAPALLITO REDONDO | D98: 2100 | E98: =A98*D98 -> 4200 | I98: 1500 | J98: =I98*A98 -> 3000 | K98: =E98-J98 -> 1200
A99: 4 | B99: UNIDAD | C99: PALTA | D99: 1300 | E99: =A99*D99 -> 5200 | I99: 791 | J99: =I99*A99 -> 3164 | K99: =E99-J99 -> 2036
A100: 0.5 | B100: KG | C100: LEC MORADA | D100: 4000 | E100: =A100*D100 -> 2000 | I100: =7000/3 -> 2333.3333 | J100: =I100*A100 -> 1166.6667 | K100: =E100-J100 -> 833.33333
A101: 2 | B101: KG | C101: PIM ROJO | D101: 2400 | E101: =A101*D101 -> 4800 | I101: =15000/8 -> 1875 | J101: =I101*A101 -> 3750 | K101: =E101-J101 -> 1050
A102: 0.5 | B102: KG | C102: TOM CHERRY | D102: 3500 | E102: =A102*D102 -> 1750 | I102: =20000/8 -> 2500 | J102: =I102*A102 -> 1250 | K102: =E102-J102 -> 500
A103: 1.2 | B103: KG | C103: BANANA | D103: 2400 | E103: =A103*D103 -> 2880 | I103: =30000/18 -> 1666.6667 | J103: =I103*A103 -> 2000 | K103: =E103-J103 -> 880
E105: =SUM(E87:E103) -> 138930 | K105: =SUM(K87:K103) -> 39482.667 | L105: =K105/E105 -> 0.28419108
A109: MESTIZO | D109: rto: 7 | E109: 46048
A111: CANTIDAD | B111: UNIDAD | C111: PRODUCTO | D111: PRECIO | E111: TOTAL | I111: PRECIO | J111: TOTAL | K111: DIFERENCIA
A112: 1 | B112: BOLSA | C112: PAPA | D112: 22000 | E112: =A112*D112 -> 22000 | I112: 19000 | J112: =I112*A112 -> 19000 | K112: =E112-J112 -> 3000
A113: 0.5 | B113: CAJON | C113: RUCULA | D113: 9000 | E113: =A113*D113 -> 4500 | I113: 5000 | J113: =I113*A113 -> 2500 | K113: =E113-J113 -> 2000
A114: 0.5 | B114: CAJON | C114: LEC MORADA | D114: 11000 | E114: =A114*D114 -> 5500 | I114: 7000 | J114: =I114*A114 -> 3500 | K114: =E114-J114 -> 2000
A115: 0.5 | B115: CAJON | C115: LEC FRACNESA | D115: 14000 | E115: =A115*D115 -> 7000 | I115: 10000 | J115: =I115*A115 -> 5000 | K115: =E115-J115 -> 2000
A116: 1 | B116: ATADO | C116: ALBAHACA | D116: 1000 | E116: =A116*D116 -> 1000 | I116: 500 | J116: =I116*A116 -> 500 | K116: =E116-J116 -> 500
A117: 3 | B117: KG | C117: TOMATE | D117: 1800 | E117: =A117*D117 -> 5400 | I117: =11000/15 -> 733.33333 | J117: =I117*A117 -> 2200 | K117: =E117-J117 -> 3200
A118: 1 | B118: ATADO | C118: CIBOULLETE | D118: 3000 | E118: =A118*D118 -> 3000 | I118: 2000 | J118: =I118*A118 -> 2000 | K118: =E118-J118 -> 1000
A119: 3 | B119: UNIDAD | C119: AJO | D119: 1200 | E119: =A119*D119 -> 3600 | I119: 560 | J119: =I119*A119 -> 1680 | K119: =E119-J119 -> 1920
A120: 2 | B120: KG | C120: BERENJENA | D120: 1800 | E120: =A120*D120 -> 3600 | I120: =9000/8 -> 1125 | J120: =I120*A120 -> 2250 | K120: =E120-J120 -> 1350
A121: 2 | B121: KG | C121: ZAP LARGO | D121: 2100 | E121: =A121*D121 -> 4200 | I121: 1500 | J121: =I121*A121 -> 3000 | K121: =E121-J121 -> 1200
A122: 2 | B122: KG | C122: ZANAHORIA | D122: 1600 | E122: =A122*D122 -> 3200 | I122: =9000/8 -> 1125 | J122: =I122*A122 -> 2250 | K122: =E122-J122 -> 950
...

Sheet 27-01-2026 
A3: BRASOV | D3: rto: 8 | E3: 46049 | I3: COMPRA
A5: CANTIDAD | B5: UNIDAD | C5: PRODUCTO | D5: PRECIO | E5: TOTAL | I5: PRECIO | J5: TOTAL | K5: DIFERENCIA
A6: 1 | B6: CAJA | C6: PALTA | D6: 65000 | E6: =A6*D6 -> 65000 | I6: 50000 | J6: =I6*A6 -> 50000 | K6: =E6-J6 -> 15000
E8: =SUM(E6) -> 65000 | K8: =SUM(K6) -> 15000 | L8: =K8/E8 -> 0.23076923
A11: COLCAR | D11: rto: 1 | E11: 46049
A13: CANTIDAD | B13: UNIDAD | C13: PRODUCTO | D13: PRECIO | E13: TOTAL | I13: PRECIO | J13: TOTAL | K13: DIFERENCIA
A14: 5 | B14: BOLSA | C14: PAPA CEPILLADA | D14: 14000 | E14: =A14*D14 -> 70000 | F14: =E14*1.105 -> 77350 | I14: 12000 | J14: =I14*A14 -> 60000 | K14: =F14-J14 -> 17350
A15: 1 | B15: CAJON | C15: BANANA PARAGUAY | D15: 33000 | E15: =A15*D15 -> 33000 | F15: =E15*1.105 -> 36465 | I15: 22000 | J15: =I15*A15 -> 22000 | K15: =F15-J15 -> 14465
A16: 3 | B16: CAJON | C16: NARANJA S/SEMILLA | D16: 22000 | E16: =A16*D16 -> 66000 | F16: =E16*1.105 -> 72930 | I16: 12000 | J16: =I16*A16 -> 36000 | K16: =F16-J16 -> 36930
A17: 1 | B17: CAJON | C17: BROCOLI | D17: 15000 | E17: =A17*D17 -> 15000 | F17: =E17*1.105 -> 16575 | I17: 20000 | J17: =I17*A17 -> 20000 | K17: =F17-J17 -> -3425
A18: 2 | B18: BOLSA | C18: ZANAHORIA CUBITO | D18: 12000 | E18: =A18*D18 -> 24000 | F18: =E18*1.105 -> 26520 | I18: =19000/2 -> 9500 | J18: =I18*A18 -> 19000 | K18: =F18-J18 -> 7520
A19: 3 | B19: UNIDAD | C19: REPOLLO BLANCO | D19: 1800 | E19: =A19*D19 -> 5400 | F19: =E19*1.105 -> 5967 | I19: 0 | J19: =I19*A19 -> 0 | K19: =F19-J19 -> 5967
A20: 3 | B20: UNIDAD | C20: REPOLLO ROJO | D20: 1800 | E20: =A20*D20 -> 5400 | F20: =E20*1.105 -> 5967 | I20: 0 | J20: =I20*A20 -> 0 | K20: =F20-J20 -> 5967
E22: =SUM(E14:E20) -> 218800 | F22: =SUM(F14:F20) -> 241774 | K22: =SUM(K14:K20) -> 84774 | L22: =K22/E22 -> 0.38744973
A24: Comisión Juan | B24: 0.04 | E24: =E22*0.04 -> 8752
A27: RAKUS | D27: rto: 17 | E27: 46049
A29: CANTIDAD | B29: UNIDAD | C29: PRODUCTO | D29: PRECIO | E29: TOTAL | I29: PRECIO | J29: TOTAL | K29: DIFERENCIA
A30: 1 | B30: CAJON | C30: FRUTILLA | D30: 32000 | E30: =A30*D30 -> 32000 | I30: 28000 | J30: =I30*A30 -> 28000 | K30: =E30-J30 -> 4000
A31: 1 | B31: KG | C31: KIWI | D31: 12000 | E31: =A31*D31 -> 12000 | I31: =65000/7 -> 9285.7143 | J31: =I31*A31 -> 9285.7143 | K31: =E31-J31 -> 2714.2857
A32: 8 | B32: KG | C32: TOMATE REDONDO | D32: 1600 | E32: =A32*D32 -> 12800 | I32: =12000/15 -> 800 | J32: =I32*A32 -> 6400 | K32: =E32-J32 -> 6400
A33: 4 | B33: CUBETA | C33: ARANDANO | D33: 2500 | E33: =A33*D33 -> 10000 | I33: =23000/12 -> 1916.6667 | J33: =I33*A33 -> 7666.6667 | K33: =E33-J33 -> 2333.3333
A34: 1 | B34: KG | C34: TOM CHERRY | D34: 3800 | E34: =A34*D34 -> 3800 | I34: =20000/8 -> 2500 | J34: =I34*A34 -> 2500 | K34: =E34-J34 -> 1300
A35: 1 | B35: KG | C35: CHAMPI | D35: 20000 | E35: =A35*D35 -> 20000 | I35: 18000 | J35: =I35*A35 -> 18000 | K35: =E35-J35 -> 2000
E37: =SUM(E30:E35) -> 90600 | K37: =SUM(K30:K35) -> 18747.619 | L37: =K37/E37 -> 0.20692736
A41: PAULA CASERO | D41: rto: 7 | E41: 46048
A43: CANTIDAD | B43: UNIDAD | C43: PRODUCTO | D43: PRECIO | E43: TOTAL | I43: PRECIO | J43: TOTAL | K43: DIFERENCIA
A44: 1 | B44: BOLSA | C44: BATATA | D44: 14000 | E44: =A44*D44 -> 14000 | I44: 10000 | J44: =I44*A44 -> 10000 | K44: =E44-J44 -> 4000
E46: =SUM(E44) -> 14000 | K46: =SUM(K44) -> 4000 | L46: =K46/E46 -> 0.28571429
A50: LA PIADINA | D50: rto: 12 | E50: 46049
A52: CANTIDAD | B52: UNIDAD | C52: PRODUCTO | D52: PRECIO | E52: TOTAL | I52: PRECIO | J52: TOTAL | K52: DIFERENCIA
A53: 1 | B53: CAJON | C53: RUCULA | D53: 11000 | E53: =A53*D53 -> 11000 | I53: 6000 | J53: =I53*A53 -> 6000 | K53: =E53-J53 -> 5000
A54: 2 | B54: CAJON | C54: BERENJENA | D54: 14000 | E54: =A54*D54 -> 28000 | I54: 9000 | J54: =I54*A54 -> 18000 | K54: =E54-J54 -> 10000
A55: 1 | B55: UNIDAD | C55: REP ROJO | D55: 2000 | E55: =A55*D55 -> 2000 | I55: 1500 | J55: =I55*A55 -> 1500 | K55: =E55-J55 -> 500
A56: 1 | B56: UNIDAD | C56: APIO | D56: 2000 | E56: =A56*D56 -> 2000 | I56: 1500 | J56: =I56*A56 -> 1500 | K56: =E56-J56 -> 500
A57: 3 | B57: ATADO | C57: ALBAHACA | D57: 1000 | E57: =A57*D57 -> 3000 | I57: 500 | J57: =I57*A57 -> 1500 | K57: =E57-J57 -> 1500
A58: 3 | B58: KG | C58: TOMATE REDONDO | D58: 2000 | E58: =A58*D58 -> 6000 | I58: =12000/15 -> 800 | J58: =I58*A58 -> 2400 | K58: =E58-J58 -> 3600
A59: 2 | B59: UNIDAD | C59: AJO | D59: 1200 | E59: =A59*D59 -> 2400 | I59: 560 | J59: =I59*A59 -> 1120 | K59: =E59-J59 -> 1280
E61: =SUM(E53:E60) -> 54400 | K61: =SUM(K53:K59) -> 22380 | L61: =K61/E61 -> 0.41139706
A64: TOTAL DIA | B64: =E61+E46+E37+F22+E8 -> 465774
A66: GANANCIA | B66: =K61+K46+K37+K22+K8 -> 144901.62
A68: % | B68: =B66/B64 -> 0.31109856
A70: BULTOS COMPRADOS
B75: EFECTIVO | C75: MERCADO PAGO | D75: BANCO GALCIA | E75: BANCO RIO | F75: CHEQUES
B76: ='22-01-2026 '!B126 -> 213537.25 | C76: ='22-01-2026 '!C126 -> 1338479.7 | D76: ='22-01-2026 '!D126 -> 2388443.9 | E76: ='22-01-2026 '!E126 -> 0 | F76: ='22-01-2026 '!F126 -> 637428.4
A78: INGRESOS
A79: COBR. CTA. CTE | B79: 0 | C79: 0 | D79: 0 | E79: 0 | F79: 964956.69
A80: RENDIMIENTO MP | B80: 0 | C80: 1008.47 | D80: 0 | E80: 0 | F80: 0
A81: CHE ACREDITADO | B81: 0 | C81: 0 | D81: 0 | E81: 0 | F81: 0
A82: COBR. VACIOS | B82: 0 | C82: 0 | D82: 0 | E82: 0 | F82: 0
A83: PRESTAMOS | B83: 0 | C83: 0 | D83: 0 | E83: 0 | F83: 0
A84: VENTA DE CHEQUE | B84: 0 | C84: 0 | D84: 0 | E84: 0 | F84: 0
A85: IMP. IIBB. 2% | B85: 0 | C85: =C79*2% -> 0 | D85: =SUM(D79:D80)*2% -> 0 | E85: 0 | F85: 0
A86: IMP. CRED. 0,6% | B86: 0 | C86: =C79*0.6%+C82*0.6% -> 0 | D86: =SUM(D79:D81)*0.6% -> 0 | E86: 0 | F86: 0
A88: TOTAL | B88: =SUM(B76:B86) -> 213537.25 | C88: =C76+C79+C82+C83-C86+C80-C85 -> 1339488.2 | D88: =D76+D79+D82+D83-D86+D81-D85-D84 -> 2388443.9 | E88: =E76+E79+E82+E83-E86 -> 0 | F88: =F76+F79+F82+F83-F86-D81 -> 1602385.1
A90: GASTOS
A91: ING. MERCADO | B91: 1000 | C91: 0 | D91: 0 | E91: 0
A92: CARGA / VACIOS | B92: 0 | C92: 0 | D92: 0 | E92: 0
A93: CHEQ DEBITADO | B93: 0 | C93: 0 | D93: 900000 | E93: 0
A94: PEAJE | B94: 2800 | C94: 0 | D94: 0 | E94: 0
A95: MERCADERIA | B95: 0 | C95: 235800 | D95: 0 | E95: 0
A96: COMBUSTIBLE | B96: 0 | C96: 65000 | D96: 0 | E96: 0
A97: SUELDOS | B97: 0 | C97: 0 | D97: 0 | E97: 0
A98: DEV. PRESTAMOS | B98: 0 | C98: 0 | D98: 0 | E98: 0
A99: AGUA | B99: 0 | C99: 0 | D99: 0 | E99: 0
A100: FLETE JUAN | B100: 0 | C100: 0 | D100: 0 | E100: 0
A101: RETIRO JOAQUIN | B101: 0 | C101: 0 | D101: 0 | E101: 0
A102: RETIRO FEDERICO | B102: 0 | C102: 0 | D102: 0 | E102: 0
... A116: MANT. CTA. | B116: 0 | C116: 0 | D116: 0 | E116: 0
A118: IMP. DEB. 0,6% | B118: 0 | C118: =SUM(C91:C115)*0.6% -> 1804.8 | D118: =SUM(D91:D116)*0.6% -> 6086.154 | E118: =(E95*0.6%)+(E96*0.6%)+(E97*0.6%)+(E100*0.6%)+(E101*0.6%) -> 0
A119: PASE DE CUENTAS | B119: 0 | C119: 0 | D119: 0 | E119: =SUM(E92:E117)*0.6%+(E120*0.6%) -> 0
A121: TOTAL SALIDAS | B121: =SUM(B91:B120) -> 3800 | C121: =SUM(C91:C118) -> 302604.8 | D121: =SUM(D91:D119) -> 1020445.2 | E121: =E102+E106+E118-E119 -> 0 | F121: =F95
A123: SALDOS | B123: =B88-B121 -> 209737.25 | C123: =C88-C121+C119 -> 1036883.4 | D123: =D88-D121-29.2 -> 1367969.6 | E123: =E88-E121 -> 0 | F123: =F88-F121 -> 1602385.1
A125: fede | B125: =75177.25-B91-B94 -> 71377.25
A126: joaquin | B126: 138360
B128: =SUM(B125:B126) -> 209737.25

Sheet 28-01-2026 
A2: FV | D2: rto: 222 | E2: 46050
A4: CANTIDAD | B4: UNIDAD | C4: PRODUCTO | D4: PRECIO | E4: TOTAL | I4: PRECIO | J4: TOTAL | K4: DIFERENCIA
A5: 1 | B5: CAJON | C5: TOM CHERRY | D5: 30000 | E5: =A5*D5 -> 30000 | F5: =E5*1.105 -> 33150 | I5: 23000 | J5: =I5*A5 -> 23000 | K5: =F5-J5 -> 10150
A6: 2 | B6: CAJON | C6: TOMATE REDONDO | D6: 22000 | E6: =A6*D6 -> 44000 | F6: =E6*1.105 -> 48620 | I6: 15000 | J6: =I6*A6 -> 30000 | K6: =F6-J6 -> 18620
A7: 6 | B7: ATADO | C7: ALBAHACA | D7: 1000 | E7: =A7*D7 -> 6000 | F7: =E7*1.105 -> 6630 | I7: 500 | J7: =I7*A7 -> 3000 | K7: =F7-J7 -> 3630
A8: 1 | B8: CAJA | C8: BANANA | D8: 35000 | E8: =A8*D8 -> 35000 | F8: =E8*1.105 -> 38675 | I8: 26000 | J8: =I8*A8 -> 26000 | K8: =F8-J8 -> 12675
A9: 1 | B9: CAJA | C9: MELON BLANCO | D9: 25000 | E9: =A9*D9 -> 25000 | F9: =E9*1.105 -> 27625 | I9: 18000 | J9: =I9*A9 -> 18000 | K9: =F9-J9 -> 9625
A10: 26 | B10: KG | C10: SANDIA | D10: 1000 | E10: =A10*D10 -> 26000 | F10: =E10*1.105 -> 28730 | I10: 530 | J10: =I10*A10 -> 13780 | K10: =F10-J10 -> 14950
A11: 2 | B11: CAJON | C11: UVA | D11: 28000 | E11: =A11*D11 -> 56000 | F11: =E11*1.105 -> 61880 | I11: 20000 | J11: =I11*A11 -> 40000 | K11: =F11-J11 -> 21880
A12: 0.5 | B12: CAJON | C12: HUEVO | D12: 54000 | E12: =A12*D12 -> 27000 | F12: =E12*1.21 -> 32670 | I12: 46000 | J12: =I12*A12 -> 23000 | K12: =F12-J12 -> 9670
A13: 2 | B13: KG | C13: LIMON | D13: 2700 | E13: =A13*D13 -> 5400 | F13: =E13*1.105 -> 5967 | I13: =32000/15 -> 2133.3333 | J13: =I13*A13 -> 4266.6667 | K13: =F13-J13 -> 1700.3333
E15: =SUM(E5:E13) -> 254400 | F15: =SUM(F5:F13) -> 283947 | K15: =SUM(K5:K13) -> 102900.33 | L15: =K15/E15 -> 0.40448244
A18: HOGAR CARDALES | D18: rto: 4 | E18: 46050
A20: CANTIDAD | B20: UNIDAD | C20: PRODUCTO | D20: PRECIO | E20: TOTAL | I20: PRECIO | J20: TOTAL | K20: DIFERENCIA
A21: 1 | B21: UNIDAD | C21: APIO | D21: 2000 | E21: =A21*D21 -> 2000 | I21: 1500 | J21: =I21*A21 -> 1500 | K21: =E21-J21 -> 500
A22: 2 | B22: UNIDAD | C22: AJO | D22: 1200 | E22: =A22*D22 -> 2400 | I22: 560 | J22: =I22*A22 -> 1120 | K22: =E22-J22 -> 1280
A23: 2.2 | B23: KG | C23: BATATA | D23: 1500 | E23: =A23*D23 -> 3300 | I23: 1250 | J23: =I23*A23 -> 2750 | K23: =E23-J23 -> 550
A24: 4 | B24: KG | C24: BONIATO | D24: 3800 | E24: =A24*D24 -> 15200 | I24: =25000/11 -> 2272.7273 | J24: =I24*A24 -> 9090.9091 | K24: =E24-J24 -> 6109.0909
A25: 3 | B25: KG | C25: BERENJENA | D25: =1800 -> 1800 | E25: =A25*D25 -> 5400 | I25: =9000/8 -> 1125 | J25: =I25*A25 -> 3375 | K25: =E25-J25 -> 2025
A26: 4 | B26: UNIDAD | C26: BROCOLI | D26: 2000 | E26: =A26*D26 -> 8000 | I26: 1500 | J26: =I26*A26 -> 6000 | K26: =E26-J26 -> 2000
A27: 2 | B27: KG | C27: MORRON | D27: 2700 | E27: =A27*D27 -> 5400 | I27: =18000/8 -> 2250 | J27: =I27*A27 -> 4500 | K27: =E27-J27 -> 900
A28: 1 | B28: KG | C28: LECHUGA | D28: 3500 | E28: =A28*D28 -> 3500 | I28: =10000/4 -> 2500 | J28: =I28*A28 -> 2500 | K28: =E28-J28 -> 1000
A29: 2 | B29: UNIDAD | C29: PALTA | D29: 1300 | E29: =A29*D29 -> 2600 | I29: =57000/70 -> 814.28571 | J29: =I29*A29 -> 1628.5714 | K29: =E29-J29 -> 971.42857
A30: 6 | B30: ATADO | C30: REMOLACHA | D30: 1800 | E30: =A30*D30 -> 10800 | I30: 1000 | J30: =I30*A30 -> 6000 | K30: =E30-J30 -> 4800
A31: 1 | B31: UNIDAD | C31: REPOLLO | D31: 2000 | E31: =A31*D31 -> 2000 | I31: =15000/12 -> 1250 | J31: =I31*A31 -> 1250 | K31: =E31-J31 -> 750
A32: 6 | B32: ATADO | C32: RUCULA | D32: 500 | E32: =A32*D32 -> 3000 | I32: =1500/6 -> 250 | J32: =I32*A32 -> 1500 | K32: =E32-J32 -> 1500
A33: 6 | B33: KG | C33: TOMATE REDONDO | D33: 1600 | E33: =A33*D33 -> 9600 | I33: 0 | J33: =I33*A33 -> 0 | K33: =E33-J33 -> 9600
A34: 1 | B34: ATADO | C34: CEB VERDEO | D34: 5000 | E34: =A34*D34 -> 5000 | I34: 4000 | J34: =I34*A34 -> 4000 | K34: =E34-J34 -> 1000
A35: 2.2 | B35: KG | C35: ZAP LARGO | D35: 1800 | E35: =A35*D35 -> 3960 | I35: 1500 | J35: =I35*A35 -> 3300 | K35: =E35-J35 -> 660
A36: 1 | B36: BOLSA | C36: ANCO | D36: 18000 | E36: =A36*D36 -> 18000 | I36: 14000 | J36: =I36*A36 -> 14000 | K36: =E36-J36 -> 4000
A37: 0.5 | B37: BOLSA | C37: CEBOLLA | D37: 12500 | E37: =A37*D37 -> 6250 | I37: 8500 | J37: =I37*A37 -> 4250 | K37: =E37-J37 -> 2000
A38: 1 | B38: BOLSA | C38: PAPA | D38: 14000 | E38: =A38*D38 -> 14000 | I38: 12000 | J38: =I38*A38 -> 12000 | K38: =E38-J38 -> 2000
A39: 1 | B39: BOLSA | C39: ZANAHORIA | D39: 13000 | E39: =A39*D39 -> 13000 | I39: 9000 | J39: =I39*A39 -> 9000 | K39: =E39-J39 -> 4000
A40: 1 | B40: CAJON | C40: HUEVO NRO 1 | D40: 56000 | E40: =A40*D40 -> 56000 | I40: 52000 | J40: =I40*A40 -> 52000 | K40: =E40-J40 -> 4000
A41: 1 | B41: CAJA | C41: BANANA | D41: 38000 | E41: =A41*D41 -> 38000 | I41: 26000 | J41: =I41*A41 -> 26000 | K41: =E41-J41 -> 12000
A42: 4.1 | B42: KG | C42: CIRUELA | D42: 4000 | E42: =A42*D42 -> 16400 | I42: 4000 | J42: =I42*A42 -> 16400 | K42: =E42-J42 -> 0
A43: 4.2 | B43: KG | C43: DURAZNO | D43: 4000 | E43: =A43*D43 -> 16800 | I43: 4000 | J43: =I43*A43 -> 16800 | K43: =E43-J43 -> 0
A44: 2 | B44: KG | C44: LIMON | D44: 3000 | E44: =A44*D44 -> 6000 | I44: =32000/15 -> 2133.3333 | J44: =I44*A44 -> 4266.6667 | K44: =E44-J44 -> 1733.3333
A45: 0.5 | B45: CAJA | C45: MANZANA | D45: =62000 -> 62000 | E45: =A45*D45 -> 31000 | I45: 56000 | J45: =I45*A45 -> 28000 | K45: =E45-J45 -> 3000
A46: 6 | B46: KG | C46: NARANJA | D46: 1400 | E46: =A46*D46 -> 8400 | I46: 1000 | J46: =I46*A46 -> 6000 | K46: =E46-J46 -> 2400
A47: 8 | B47: KG | C47: SANDIA | D47: 1000 | E47: =A47*D47 -> 8000 | I47: 530 | J47: =I47*A47 -> 4240 | K47: =E47-J47 -> 3760
A48: 1 | B48: KG | C48: UVA | D48: 3500 | E48: =A48*D48 -> 3500 | I48: =25000/9 -> 2777.7778 | J48: =I48*A48 -> 2777.7778 | K48: =E48-J48 -> 722.22222
E50: =SUM(E21:E48) -> 317510 | K50: =SUM(K21:K48) -> 73261.075 | L50: =K50/E50 -> 0.23073628
A54: TOTAL DIA | B54: =E50+F15 -> 601457
A56: GANANCIA | B56: =K50+K15 -> 176161.41
A58: % | B58: =B56/B54 -> 0.29289111
A60: BULTOS COMPRADOS
B65: EFECTIVO | C65: MERCADO PAGO | D65: BANCO GALCIA | E65: BANCO RIO | F65: CHEQUES
B66: ='22-01-2026 '!B126 -> 213537.25 | C66: ='22-01-2026 '!C126 -> 1338479.7 | D66: ='22-01-2026 '!D126 -> 2388443.9 | E66: ='22-01-2026 '!E126 -> 0 | F66: ='22-01-2026 '!F126 -> 637428.4
A68: INGRESOS
A69: COBR. CTA. CTE | B69: 0 | C69: 0 | D69: 0 | E69: 0 | F69: 964956.69
A70: RENDIMIENTO MP | B70: 0 | C70: 1008.47 | D70: 0 | E70: 0 | F70: 0
A71: CHE ACREDITADO | B71: 0 | C71: 0 | D71: 0 | E71: 0 | F71: 0
A72: COBR. VACIOS | B72: 0 | C72: 0 | D72: 0 | E72: 0 | F72: 0
A73: PRESTAMOS | B73: 0 | C73: 0 | D73: 0 | E73: 0 | F73: 0
A74: VENTA DE CHEQUE | B74: 0 | C74: 0 | D74: 0 | E74: 0 | F74: 0
A75: IMP. IIBB. 2% | B75: 0 | C75: =C69*2% -> 0 | D75: =SUM(D69:D70)*2% -> 0 | E75: 0 | F75: 0
A76: IMP. CRED. 0,6% | B76: 0 | C76: =C69*0.6%+C72*0.6% -> 0 | D76: =SUM(D69:D71)*0.6% -> 0 | E76: 0 | F76: 0
A78: TOTAL | B78: =SUM(B66:B76) -> 213537.25 | C78: =C66+C69+C72+C73-C76+C70-C75 -> 1339488.2 | D78: =D66+D69+D72+D73-D76+D71-D75-D74 -> 2388443.9 | E78: =E66+E69+E72+E73-E76 -> 0 | F78: =F66+F69+F72+F73-F76-D71 -> 1602385.1
A80: GASTOS
A81: ING. MERCADO | B81: 1000 | C81: 0 | D81: 0 | E81: 0
A82: CARGA / VACIOS | B82: 0 | C82: 0 | D82: 0 | E82: 0
A83: CHEQ DEBITADO | B83: 0 | C83: 0 | D83: 900000 | E83: 0
A84: PEAJE | B84: 2800 | C84: 0 | D84: 0 | E84: 0
A85: MERCADERIA | B85: 0 | C85: 235800 | D85: 0 | E85: 0
A86: COMBUSTIBLE | B86: 0 | C86: 65000 | D86: 0 | E86: 0
A87: SUELDOS | B87: 0 | C87: 0 | D87: 0 | E87: 0
A88: DEV. PRESTAMOS | B88: 0 | C88: 0 | D88: 0 | E88: 0
A89: AGUA | B89: 0 | C89: 0 | D89: 0 | E89: 0
A90: FLETE JUAN | B90: 0 | C90: 0 | D90: 0 | E90: 0
A91: RETIRO JOAQUIN | B91: 0 | C91: 0 | D91: 0 | E91: 0
A92: RETIRO FEDERICO | B92: 0 | C92: 0 | D92: 0 | E92: 0
... A106: MANT. CTA. | B106: 0 | C106: 0 | D106: 0 | E106: 0
A108: IMP. DEB. 0,6% | B108: 0 | C108: =SUM(C81:C105)*0.6% -> 1804.8 | D108: =SUM(D81:D106)*0.6% -> 6086.154 | E108: =(E85*0.6%)+(E86*0.6%)+(E87*0.6%)+(E90*0.6%)+(E91*0.6%) -> 0
A109: PASE DE CUENTAS | B109: 0 | C109: 0 | D109: 0 | E109: =SUM(E82:E107)*0.6%+(E110*0.6%) -> 0
A111: TOTAL SALIDAS | B111: =SUM(B81:B110) -> 3800 | C111: =SUM(C81:C108) -> 302604.8 | D111: =SUM(D81:D109) -> 1020445.2 | E111: =E92+E96+E108-E109 -> 0 | F111: =F85
A113: SALDOS | B113: =B78-B111 -> 209737.25 | C113: =C78-C111+C109 -> 1036883.4 | D113: =D78-D111-29.2 -> 1367969.6 | E113: =E78-E111 -> 0 | F113: =F78-F111 -> 1602385.1
A115: fede | B115: =75177.25-B81-B84 -> 71377.25
A116: joaquin | B116: 138360
B118: =SUM(B115:B116) -> 209737.25

Sheet 29-01-2026 
A3: MARQUESA | D3: rto: 7 | E3: 46051
A5: CANTIDAD | B5: UNIDAD | C5: PRODUCTO | D5: PRECIO | E5: TOTAL | I5: PRECIO | J5: TOTAL | K5: DIFERENCIA
A6: 1 | B6: CAJON | C6: HUEVO | D6: 54000 | E6: =A6*D6 -> 54000 | I6: 50000 | J6: =I6*A6 -> 50000 | K6: =E6-J6 -> 4000
A7: 2 | B7: ATADOS | C7: ALBAHACA | D7: 1200 | E7: =A7*D7 -> 2400 | I7: =800 -> 800 | J7: =I7*A7 -> 1600 | K7: =E7-J7 -> 800
A8: 2 | B8: CUBETAS | C8: ARANDANO | D8: 2500 | E8: =A8*D8 -> 5000 | I8: =23000/12 -> 1916.6667 | J8: =I8*A8 -> 3833.3333 | K8: =E8-J8 -> 1166.6667
A9: 2 | B9: KG | C9: BANANA | D9: 3200 | E9: =A9*D9 -> 6400 | I9: =10500/4.2 -> 2500 | J9: =I9*A9 -> 5000 | K9: =E9-J9 -> 1400
A10: 4 | B10: KG | C10: LIMA | D10: 4000 | E10: =A10*D10 -> 16000 | I10: 3000 | J10: =I10*A10 -> 12000 | K10: =E10-J10 -> 4000
A11: 1 | B11: ATADOS | C11: MENTA | D11: 3000 | E11: =A11*D11 -> 3000 | I11: 2000 | J11: =I11*A11 -> 2000 | K11: =E11-J11 -> 1000
A12: 0.5 | B12: CAJON | C12: NARANJA | D12: 16000 | E12: =A12*D12 -> 8000 | I12: 11000 | J12: =I12*A12 -> 5500 | K12: =E12-J12 -> 2500
A13: 7 | B13: UNIDAD | C13: PALTA | D13: 1300 | E13: =A13*D13 -> 9100 | I13: =57000/70 -> 814.28571 | J13: =I13*A13 -> 5700 | K13: =E13-J13 -> 3400
A14: 1 | B14: KG | C14: POMELO | D14: 2500 | E14: =A14*D14 -> 2500 | I14: =25000/15 -> 1666.6667 | J14: =I14*A14 -> 1666.6667 | K14: =E14-J14 -> 833.33333
A15: 1.5 | B15: KG | C15: TOMATE | D15: 1800 | E15: =A15*D15 -> 2700 | H15: S/COSTO | I15: 0 | J15: =I15*A15 -> 0 | K15: =E15-J15 -> 2700
A16: 1 | B16: BOLSA | C16: ZANAHORIA | D16: 14000 | E16: =A16*D16 -> 14000 | I16: 11500 | J16: =I16*A16 -> 11500 | K16: =E16-J16 -> 2500
E18: =SUM(E6:E16) -> 123100 | K18: =SUM(K6:K16) -> 24300 | L18: =K18/E18 -> 0.19740049
A21: CAFE MARTINEZ - CAAMAÑO | D21: rto: 7 | E21: 46051
A23: CANTIDAD | B23: UNIDAD | C23: PRODUCTO | D23: PRECIO | E23: TOTAL | F23: TOTAL C/IVA | I23: PRECIO | J23: TOTAL | K23: DIFERENCIA
A24: 6 | B24: KG | C24: LIMON | D24: 3000 | E24: =A24*D24 -> 18000 | F24: =E24*1.105 -> 19890 | I24: =30000/15 -> 2000 | J24: =I24*A24 -> 12000 | K24: =E24-J24 -> 6000
A25: 1 | B25: KG | C25: MANZANA | D25: 3500 | E25: =A25*D25 -> 3500 | F25: =E25*1.105 -> 3867.5 | I25: =40000/18 -> 2222.2222 | J25: =I25*A25 -> 2222.2222 | K25: =E25-J25 -> 1277.7778
A26: 12 | B26: UNIDAD | C26: PALTA | D26: 1300 | E26: =A26*D26 -> 15600 | F26: =E26*1.105 -> 17238 | I26: =57000/70 -> 814.28571 | J26: =I26*A26 -> 9771.4286 | K26: =E26-J26 -> 5828.5714
A27: 1 | B27: KG | C27: CEBOLLA | D27: 900 | E27: =A27*D27 -> 900 | F27: =E27*1.105 -> 994.5 | I27: =8500/16 -> 531.25 | J27: =I27*A27 -> 531.25 | K27: =E27-J27 -> 368.75
A28: 2 | B28: KG | C28: BANANA | D28: 3200 | E28: =A28*D28 -> 6400 | F28: =E28*1.105 -> 7072 | I28: 2500 | J28: =I28*A28 -> 5000 | K28: =E28-J28 -> 1400
A29: 0.5 | B29: KG | C29: TOMATE REDONDO | D29: 1800 | E29: =A29*D29 -> 900 | F29: =E29*1.105 -> 994.5 | H29: S/COSTO | I29: 0 | J29: =I29*A29 -> 0 | K29: =E29-J29 -> 900
A30: 1 | B30: KG | C30: KIWI | D30: 12000 | E30: =A30*D30 -> 12000 | F30: =E30*1.105 -> 13260 | I30: =65000/7 -> 9285.7143 | J30: =I30*A30 -> 9285.7143 | K30: =E30-J30 -> 2714.2857
A31: 5 | B31: CAJON | C31: NARANJA | D31: 16000 | E31: =A31*D31 -> 80000 | F31: =E31*1.105 -> 88400 | I31: 11000 | J31: =I31*A31 -> 55000 | K31: =E31-J31 -> 25000
A32: 1 | B32: ATADO | C32: CIBOULLETE | D32: 3000 | E32: =A32*D32 -> 3000 | F32: =E32*1.105 -> 3315 | I32: 2000 | J32: =I32*A32 -> 2000 | K32: =E32-J32 -> 1000
A33: 2 | B33: KG | C33: TOM CHERRY | D33: 3500 | E33: =A33*D33 -> 7000 | F33: =E33*1.105 -> 7735 | I33: =23000/8 -> 2875 | J33: =I33*A33 -> 5750 | K33: =E33-J33 -> 1250
A34: 1 | B34: KG | C34: LECHUGA | D34: 3500 | E34: =A34*D34 -> 3500 | F34: =E34*1.105 -> 3867.5 | I34: =7000/4 -> 1750 | J34: =I34*A34 -> 1750 | K34: =E34-J34 -> 1750
A35: 4 | B35: ATADO | C35: RUCULA | D35: 500 | E35: =A35*D35 -> 2000 | F35: =E35*1.105 -> 2210 | I35: =2000/6 -> 333.33333 | J35: =I35*A35 -> 1333.3333 | K35: =E35-J35 -> 666.66667
A36: 2 | B36: KG | C36: FRUTILLA | D36: 6500 | E36: =A36*D36 -> 13000 | F36: =E36*1.105 -> 14365 | I36: =20000/4 -> 5000 | J36: =I36*A36 -> 10000 | K36: =E36-J36 -> 3000
E38: =SUM(E24:E36) -> 165800 | F38: =SUM(F24:F36) -> 183209 | K38: =SUM(K24:K36) -> 51156.052 | L38: =K38/E38 -> 0.30854072
A41: FABRIC SUSHI - GORRITI | D41: rto: 2 | E41: 46051 | I41: COMPRA
A43: CANTIDAD | B43: UNIDAD | C43: PRODUCTO | D43: PRECIO | E43: TOTAL | F43: TOTAL C/IVA | I43: PRECIO | J43: TOTAL | K43: DIFERENCIA
A44: 2 | B44: KG | C44: CEB MORADA | D44: 1600 | E44: =A44*D44 -> 3200 | F44: =E44*1.105 -> 3536 | I44: 1000 | J44: =I44*A44 -> 2000 | K44: =E44-J44 -> 1200
A45: 0.5 | B45: BOLSA | C45: PAPA | D45: 20000 | E45: =A45*D45 -> 10000 | F45: =E45*1.105 -> 11050 | I45: 18500 | J45: =I45*A45 -> 9250 | K45: =E45-J45 -> 750
A46: 5 | B46: KG | C46: BATATA | D46: 1400 | E46: =A46*D46 -> 7000 | F46: =E46*1.105 -> 7735 | I46: =1000 -> 1000 | J46: =I46*A46 -> 5000 | K46: =E46-J46 -> 2000
A47: 1 | B47: KG | C47: AJI PERUANO | D47: 26000 | E47: =A47*D47 -> 26000 | F47: =E47*1.105 -> 28730 | I47: 22000 | J47: =I47*A47 -> 22000 | K47: =E47-J47 -> 4000
A48: 2 | B48: KG | C48: ZAP LARGO | D48: 1500 | E48: =A48*D48 -> 3000 | F48: =E48*1.105 -> 3315 | I48: 1500 | J48: =I48*A48 -> 3000 | K48: =E48-J48 -> 0
A49: 1 | B49: KG | C49: JENGIBRE | D49: 6500 | E49: =A49*D49 -> 6500 | F49: =E49*1.105 -> 7182.5 | I49: 7000 | J49: =I49*A49 -> 7000 | K49: =E49-J49 -> -500
A50: 2 | B50: ATADO | C50: CEB VERDEO | D50: 5500 | E50: =A50*D50 -> 11000 | F50: =E50*1.105 -> 12155 | I50: 4000 | J50: =I50*A50 -> 8000 | K50: =E50-J50 -> 3000
A51: 3 | B51: ATADO | C51: CIBOULLETE | D51: 3000 | E51: =A51*D51 -> 9000 | F51: =E51*1.105 -> 9945 | I51: 2000 | J51: =I51*A51 -> 6000 | K51: =E51-J51 -> 3000
A52: 2 | B52: ATADO | C52: CILANTRO | D52: 3000 | E52: =A52*D52 -> 6000 | F52: =E52*1.105 -> 6630 | I52: 2000 | J52: =I52*A52 -> 4000 | K52: =E52-J52 -> 2000
A53: 1 | B53: ATADO | C53: ENELDO | D53: 3000 | E53: =A53*D53 -> 3000 | F53: =E53*1.105 -> 3315 | I53: 2000 | J53: =I53*A53 -> 2000 | K53: =E53-J53 -> 1000
A54: 0.25 | B54: KG | C54: AJI JALAPEÑO | D54: 9500 | E54: =A54*D54 -> 2375 | F54: =E54*1.105 -> 2624.375 | I54: 8000 | J54: =I54*A54 -> 2000 | K54: =E54-J54 -> 375
A55: 0.25 | B55: KG | C55: AJI ROCOTO | D55: 9500 | E55: =A55*D55 -> 2375 | F55: =E55*1.105 -> 2624.375 | I55: 8000 | J55: =I55*A55 -> 2000 | K55: =E55-J55 -> 375
A56: 2 | B56: KG | C56: PIM ROJO | D56: 2700 | E56: =A56*D56 -> 5400 | F56: =E56*1.105 -> 5967 | I56: =18000/8 -> 2250 | J56: =I56*A56 -> 4500 | K56: =E56-J56 -> 900
A57: 2 | B57: KG | C57: PIM AMARILLO | D57: 3000 | E57: =A57*D57 -> 6000 | F57: =E57*1.105 -> 6630 | I57: =15000/8 -> 1875 | J57: =I57*A57 -> 3750 | K57: =E57-J57 -> 2250
A58: 0.25 | B58: KG | C58: AJI LIMO | D58: 9500 | E58: =A58*D58 -> 2375 | F58: =E58*1.105 -> 2624.375 | I58: 8000 | J58: =I58*A58 -> 2000 | K58: =E58-J58 -> 375
A59: 5 | B59: UNIDAD | C59: AJO | D59: 900 | E59: =A59*D59 -> 4500 | F59: =E59*1.105 -> 4972.5 | I59: 560 | J59: =I59*A59 -> 2800 | K59: =E59-J59 -> 1700
A60: 5 | B60: KG | C60: LIMON | D60: 2700 | E60: =A60*D60 -> 13500 | F60: =E60*1.105 -> 14917.5 | I60: =30000/15 -> 2000 | J60: =I60*A60 -> 10000 | K60: =E60-J60 -> 3500
A61: 2 | B61: CAJA | C61: PALTA T.70 | D61: 75000 | E61: =A61*D61 -> 150000 | F61: =E61*1.105 -> 165750 | I61: 57000 | J61: =I61*A61 -> 114000 | K61: =E61-J61 -> 36000
E63: =SUM(E44:E61) -> 271225 | F63: =SUM(F44:F61) -> 299703.62 | K63: =SUM(K44:K61) -> 61925 | L63: =K63/E63 -> 0.22831597
A65: Comisión Juan | B65: 0.04 | E65: =E63*0.04 -> 10849
A69: CAFÉ MARTÍNEZ - MORENO | E69: rto: 2 | F69: 46051 | I69: COMPRA
A71: CANTIDAD | B71: UNIDAD | C71: PRODUCTO | D71: PRECIO | E71: TOTAL | I71: PRECIO | J71: TOTAL | K71: DIFERENCIA
A72: 1 | B72: KG | C72: LEC FRACNESA | D72: 3000 | E72: =A72*D72 -> 3000 | I72: =7000/4 -> 1750 | J72: =I72*A72 -> 1750 | K72: =E72-J72 -> 1250
A73: 3 | B73: ATADO | C73: RUCULA | D73: 350 | E73: =A73*D73 -> 1050 | I73: =2000/6 -> 333.33333 | J73: =I73*A73 -> 1000 | K73: =E73-J73 -> 50
A74: 12 | B74: UNIDAD | C74: PALTA | D74: 1200 | E74: =A74*D74 -> 14400 | I74: =57000/70 -> 814.28571 | J74: =I74*A74 -> 9771.4286 | K74: =E74-J74 -> 4628.5714
A75: 1.5 | B75: KG | C75: TOM CHERRY | D75: 3500 | E75: =A75*D75 -> 5250 | I75: =23000/8 -> 2875 | J75: =I75*A75 -> 4312.5 | K75: =E75-J75 -> 937.5
A76: 1 | B76: CAJON | C76: NARANJA | D76: 15000 | E76: =A76*D76 -> 15000 | I76: 11000 | J76: =I76*A76 -> 11000 | K76: =E76-J76 -> 4000
A77: 1 | B77: KG | C77: FRUTILLA | D77: 6000 | E77: =A77*D77 -> 6000 | I77: =20000/4 -> 5000 | J77: =I77*A77 -> 5000 | K77: =E77-J77 -> 1000
A78: 0.4 | B78: KG | C78: JENGIBRE | D78: 6500 | E78: =A78*D78 -> 2600 | I78: 7000 | J78: =I78*A78 -> 2800 | K78: =E78-J78 -> -200
A79: 3 | B79: KG | C79: LIMON | D79: 2700 | E79: =A79*D79 -> 8100 | I79: =30000/15 -> 2000 | J79: =I79*A79 -> 6000 | K79: =E79-J79 -> 2100
E81: =SUM(E72:E79) -> 55400 | K81: =SUM(K72:K79) -> 13766.071 | L81: =K81/E81 -> 0.24848504
A83: Comisión Juan | B83: 0.04 | E83: =E81*0.04 -> 2216
A86: HAVANA - MORENO | E86: rto: 1 | F86: 46051 | I86: COMPRA
A88: CANTIDAD | B88: UNIDAD | C88: PRODUCTO | D88: PRECIO | E88: TOTAL | I88: PRECIO | J88: TOTAL | K88: DIFERENCIA
A89: 1 | B89: CAJON | C89: NARANJA COMERCIAL | D89: 16000 | E89: =A89*D89 -> 16000 | I89: 11000 | J89: =I89*A89 -> 11000 | K89: =E89-J89 -> 5000
E91: =SUM(E89) -> 16000 | K91: =SUM(K89) -> 5000 | L91: =K91/E91 -> 0.3125
A93: Comisión Juan | B93: 0.04 | E93: =E91*0.04 -> 640
A97: TOTAL DIA | B97: =E91+E81+F63+F38+E18 -> 677412.62
A99: GANANCIA | B99: =K91+K81+K63+K38+K18 -> 156147.12
A101: % | B101: =B99/B97 -> 0.23050519
A103: BULTOS COMPRADOS
B108: EFECTIVO | C108: MERCADO PAGO | D108: BANCO GALCIA | E108: BANCO RIO | F108: CHEQUES
B109: ='22-01-2026 '!B126 -> 213537.25 | C109: ='22-01-2026 '!C126 -> 1338479.7 | D109: ='22-01-2026 '!D126 -> 2388443.9 | E109: ='22-01-2026 '!E126 -> 0 | F109: ='22-01-2026 '!F126 -> 637428.4
A111: INGRESOS
A112: COBR. CTA. CTE | B112: 0 | C112: 0 | D112: 0 | E112: 0 | F112: 964956.69
A113: RENDIMIENTO MP | B113: 0 | C113: 1008.47 | D113: 0 | E113: 0 | F113: 0
A114: CHE ACREDITADO | B114: 0 | C114: 0 | D114: 0 | E114: 0 | F114: 0
A115: COBR. VACIOS | B115: 0 | C115: 0 | D115: 0 | E115: 0 | F115: 0
A116: PRESTAMOS | B116: 0 | C116: 0 | D116: 0 | E116: 0 | F116: 0
A117: VENTA DE CHEQUE | B117: 0 | C117: 0 | D117: 0 | E117: 0 | F117: 0
A118: IMP. IIBB. 2% | B118: 0 | C118: =C112*2% -> 0 | D118: =SUM(D112:D113)*2% -> 0 | E118: 0 | F118: 0
A119: IMP. CRED. 0,6% | B119: 0 | C119: =C112*0.6%+C115*0.6% -> 0 | D119: =SUM(D112:D114)*0.6% -> 0 | E119: 0 | F119: 0
A121: TOTAL | B121: =SUM(B109:B119) -> 213537.25 | C121: =C109+C112+C115+C116-C119+C113-C118 -> 1339488.2 | D121: =D109+D112+D115+D116-D119+D114-D118-D117 -> 2388443.9 | E121: =E109+E112+E115+E116-E119 -> 0 | F121: =F109+F112+F115+F116-F119-D114 -> 1602385.1
A123: GASTOS
A124: ING. MERCADO | B124: 1000 | C124: 0 | D124: 0 | E124: 0
A125: CARGA / VACIOS | B125: 0 | C125: 0 | D125: 0 | E125: 0
A126: CHEQ DEBITADO | B126: 0 | C126: 0 | D126: 900000 | E126: 0
A127: PEAJE | B127: 2800 | C127: 0 | D127: 0 | E127: 0
A128: MERCADERIA | B128: 0 | C128: 235800 | D128: 0 | E128: 0
A129: COMBUSTIBLE | B129: 0 | C129: 65000 | D129: 0 | E129: 0
A130: SUELDOS | B130: 0 | C130: 0 | D130: 0 | E130: 0
A131: DEV. PRESTAMOS | B131: 0 | C131: 0 | D131: 0 | E131: 0
A132: AGUA | B132: 0 | C132: 0 | D132: 0 | E132: 0
A133: FLETE JUAN | B133: 0 | C133: 0 | D133: 0 | E133: 0
A134: RETIRO JOAQUIN | B134: 0 | C134: 0 | D134: 0 | E134: 0
A135: RETIRO FEDERICO | B135: 0 | C135: 0 | D135: 0 | E135: 0
... A149: MANT. CTA. | B149: 0 | C149: 0 | D149: 0 | E149: 0
A151: IMP. DEB. 0,6% | B151: 0 | C151: =SUM(C124:C148)*0.6% -> 1804.8 | D151: =SUM(D124:D149)*0.6% -> 6086.154 | E151: =(E128*0.6%)+(E129*0.6%)+(E130*0.6%)+(E133*0.6%)+(E134*0.6%) -> 0
...

Sheet 30-01-2026 
A3: BRASOV | D3: rto: 9 | E3: 46052 | I3: COMPRA
A5: CANTIDAD | B5: UNIDAD | C5: PRODUCTO | D5: PRECIO | E5: TOTAL | I5: PRECIO | J5: TOTAL | K5: DIFERENCIA
A6: 1 | B6: UNIDAD | C6: APIO | D6: 2000 | E6: =A6*D6 -> 2000 | I6: 1500 | J6: =I6*A6 -> 1500 | K6: =E6-J6 -> 500
A7: 1 | B7: CAJON | C7: TOMATE | D7: 22000 | E7: =A7*D7 -> 22000 | I7: 15000 | J7: =I7*A7 -> 15000 | K7: =E7-J7 -> 7000
A8: 1 | B8: BANDEJA | C8: TOM CHERRY | D8: 15000 | E8: =A8*D8 -> 15000 | I8: 10000 | J8: =I8*A8 -> 10000 | K8: =E8-J8 -> 5000
A9: 1 | B9: CAJA | C9: PALTA | D9: 65000 | E9: =A9*D9 -> 65000 | I9: 55000 | J9: =I9*A9 -> 55000 | K9: =E9-J9 -> 10000
A10: 4 | B10: ATADO | C10: CEB VERDEO | D10: 5000 | E10: =A10*D10 -> 20000 | I10: 4000 | J10: =I10*A10 -> 16000 | K10: =E10-J10 -> 4000
A11: 3 | B11: CAJA | C11: LIMON | D11: 26000 | E11: =A11*D11 -> 78000 | I11: 20000 | J11: =I11*A11 -> 60000 | K11: =E11-J11 -> 18000
A12: 2 | B12: BOLSA | C12: CEBOLLON | D12: 12000 | E12: =A12*D12 -> 24000 | I12: 8000 | J12: =I12*A12 -> 16000 | K12: =E12-J12 -> 8000
A13: 3 | B13: BOLSA | C13: PAPA | D13: 22000 | E13: =A13*D13 -> 66000 | I13: 18500 | J13: =I13*A13 -> 55500 | K13: =E13-J13 -> 10500
A14: 1 | B14: BOLSA | C14: BONIATO | D14: 26000 | E14: =A14*D14 -> 26000 | I14: 23000 | J14: =I14*A14 -> 23000 | K14: =E14-J14 -> 3000
A15: 1 | B15: BOLSA | C15: CEB MORADA | D15: 18000 | E15: =A15*D15 -> 18000 | I15: 14000 | J15: =I15*A15 -> 14000 | K15: =E15-J15 -> 4000
A16: 1 | B16: BOLSA | C16: ANCO | D16: 13000 | E16: =A16*D16 -> 13000 | I16: 10000 | J16: =I16*A16 -> 10000 | K16: =E16-J16 -> 3000
A17: 1 | B17: CAJON | C17: MORRON ROJO | D17: 26000 | E17: =A17*D17 -> 26000 | I17: 20000 | J17: =I17*A17 -> 20000 | K17: =E17-J17 -> 6000
E19: =SUM(E6:E17) -> 375000 | K19: =SUM(K6:K17) -> 79000 | L19: =K19/E19 -> 0.21066667
A22: COMO SIEMPRE LAGUNA | D22: rto: 25 | E22: 46052
A24: CANTIDAD | B24: UNIDAD | C24: PRODUCTO | D24: PRECIO | E24: TOTAL | I24: PRECIO | J24: TOTAL | K24: DIFERENCIA
A25: 2 | B25: BOLSA | C25: PAPA GARLIC | D25: 22000 | E25: =A25*D25 -> 44000 | I25: 18500 | J25: =I25*A25 -> 37000 | K25: =E25-J25 -> 7000
A26: 1 | B26: KG | C26: CHAMPI | D26: 20000 | E26: =A26*D26 -> 20000 | I26: 17000 | J26: =I26*A26 -> 17000 | K26: =E26-J26 -> 3000
A27: 1 | B27: KG | C27: PORTO | D27: 22000 | E27: =A27*D27 -> 22000 | I27: 19000 | J27: =I27*A27 -> 19000 | K27: =E27-J27 -> 3000
A28: 1 | B28: CAJON | C28: TOM CHERRY | D28: 28000 | E28: =A28*D28 -> 28000 | I28: 20000 | J28: =I28*A28 -> 20000 | K28: =E28-J28 -> 8000
A29: 1 | B29: ATADO | C29: CILANTRO | D29: 3000 | E29: =A29*D29 -> 3000 | I29: 2000 | J29: =I29*A29 -> 2000 | K29: =E29-J29 -> 1000
A30: 1 | B30: ATADO | C30: CIBOULLETE | D30: 3000 | E30: =A30*D30 -> 3000 | I30: 2000 | J30: =I30*A30 -> 2000 | K30: =E30-J30 -> 1000
A31: 2 | B31: KG | C31: LIMA | D31: 3500 | E31: =A31*D31 -> 7000 | I31: 2500 | J31: =I31*A31 -> 5000 | K31: =E31-J31 -> 2000
A32: 1 | B32: BANDEJA | C32: BROTE | D32: 2500 | E32: =A32*D32 -> 2500 | I32: 1500 | J32: =I32*A32 -> 1500 | K32: =E32-J32 -> 1000
A33: 1 | B33: KG | C33: BATATA | D33: 1600 | E33: =A33*D33 -> 1600 | I33: 1000 | J33: =I33*A33 -> 1000 | K33: =E33-J33 -> 600
A34: 1 | B34: CAJON | C34: RUCULA | D34: 10000 | E34: =A34*D34 -> 10000 | I34: 5000 | J34: =I34*A34 -> 5000 | K34: =E34-J34 -> 5000
A35: 0.5 | B35: CAJON | C35: LEC MORADA | D35: 10000 | E35: =A35*D35 -> 5000 | I35: 6000 | J35: =I35*A35 -> 3000 | K35: =E35-J35 -> 2000
A36: 0.5 | B36: CAJON | C36: LEC FRANCESA | D36: 14000 | E36: =A36*D36 -> 7000 | I36: 10000 | J36: =I36*A36 -> 5000 | K36: =E36-J36 -> 2000
... A40: 0.5 | B40: CAJON | C40: POMELO | D40: 32000 | E40: =A40*D40 -> 16000 | I40: 28000 | J40: =I40*A40 -> 14000 | K40: =E40-J40 -> 2000
E42: =SUM(E25:E40) -> 196700 | K42: =SUM(K25:K40) -> 43200 | L42: =K42/E42 -> 0.21962379
A46: ST CATERING | D46: rto: 1 | E46: 46052
A48: CANTIDAD | B48: UNIDAD | C48: PRODUCTO | D48: PRECIO | E48: TOTAL | I48: PRECIO | J48: TOTAL | K48: DIFERENCIA
A49: 10 | B49: CAJON | C49: ACELGA | D49: 11000 | E49: =A49*D49 -> 110000 | I49: =76000/10 -> 7600 | J49: =I49*A49 -> 76000 | K49: =E49-J49 -> 34000
A50: 4 | B50: BOLSA | C50: BATATA | D50: 14000 | E50: =A50*D50 -> 56000 | I50: 9000 | J50: =I50*A50 -> 36000 | K50: =E50-J50 -> 20000
A51: 4 | B51: BOLSA | C51: BONIATO | D51: 30000 | E51: =A51*D51 -> 120000 | I51: 23000 | J51: =I51*A51 -> 92000 | K51: =E51-J51 -> 28000
A52: 10 | B52: BOLSA | C52: CEBOLLON | D52: 13000 | E52: =A52*D52 -> 130000 | I52: 8000 | J52: =I52*A52 -> 80000 | K52: =E52-J52 -> 50000
A53: 1 | B53: CAJON | C53: TOM CHERRY | D53: 25000 | E53: =A53*D53 -> 25000 | I53: 20000 | J53: =I53*A53 -> 20000 | K53: =E53-J53 -> 5000
A54: 10 | B54: CAJON | C54: BROCOLI | D54: 15000 | E54: =A54*D54 -> 150000 | I54: 11000 | J54: =I54*A54 -> 110000 | K54: =E54-J54 -> 40000
