Workbook

Sheet 02-02-2026 
A3: FV | E3: rto: 223 | F3: 46055 | G3: ** | I3: COMPRA
A5: CANTIDAD | B5: UNIDAD | C5: PRODUCTO | D5: PRECIO | E5: TOTAL | F5: TOTAL + IVA | I5: PRECIO | J5: TOTAL | K5: DIFERENCIA
A6: 10 | B6: ATADOS | C6: TOMILLO | D6: 3500 | E6: =A6*D6 -> 35000 | F6: =E6*1.105 -> 38675 | I6: 2000 | J6: =I6*A6 -> 20000 | K6: =F6-J6 -> 18675
A7: 10 | B7: ATADOS | C7: ROMERO | D7: 3500 | E7: =A7*D7 -> 35000 | F7: =E7*1.105 -> 38675 | I7: 2000 | J7: =I7*A7 -> 20000 | K7: =F7-J7 -> 18675
A8: 10 | B8: ATADOS | C8: SALVIA | D8: 3500 | E8: =A8*D8 -> 35000 | F8: =E8*1.105 -> 38675 | I8: 2000 | J8: =I8*A8 -> 20000 | K8: =F8-J8 -> 18675
A9: 10 | B9: ATADOS | C9: ALBAHACA | D9: 1000 | E9: =A9*D9 -> 10000 | F9: =E9*1.105 -> 11050 | I9: =6000/12 -> 500 | J9: =I9*A9 -> 5000 | K9: =F9-J9 -> 6050
A10: 1 | B10: ATADOS | C10: CEB VERDEO | D10: 5500 | E10: =A10*D10 -> 5500 | F10: =E10*1.105 -> 6077.5 | I10: 4000 | J10: =I10*A10 -> 4000 | K10: =F10-J10 -> 2077.5
A11: 3 | B11: CAJON | C11: TOMATE REDONDO | D11: 18000 | E11: =A11*D11 -> 54000 | F11: =E11*1.105 -> 59670 | I11: 13000 | J11: =I11*A11 -> 39000 | K11: =F11-J11 -> 20670
A12: 3 | B12: CAJON | C12: TOMATE CHERRY | D12: 30000 | E12: =A12*D12 -> 90000 | F12: =E12*1.105 -> 99450 | I12: 20000 | J12: =I12*A12 -> 60000 | K12: =F12-J12 -> 39450
A13: 0.5 | B13: CAJON | C13: HUEVO | D13: 56000 | E13: =A13*D13 -> 28000 | F13: =E13*1.21 -> 33880 | I13: 46000 | J13: =I13*A13 -> 23000 | K13: =F13-J13 -> 10880
A14: 1 | B14: CAJON | C14: ZUCCINI | D14: 16000 | E14: =A14*D14 -> 16000 | F14: =E14*1.105 -> 17680 | I14: 8000 | J14: =I14*A14 -> 8000 | K14: =F14-J14 -> 9680
A15: 1 | B15: CAJON | C15: BERENJENA | D15: 15000 | E15: =A15*D15 -> 15000 | F15: =E15*1.105 -> 16575 | I15: 7000 | J15: =I15*A15 -> 7000 | K15: =F15-J15 -> 9575
A16: 1 | B16: CAJON | C16: MORRON ROJO | D16: 40000 | E16: =A16*D16 -> 40000 | F16: =E16*1.105 -> 44200 | I16: 30000 | J16: =I16*A16 -> 30000 | K16: =F16-J16 -> 14200
A17: 1 | B17: CAJON | C17: MORRON VERDE | D17: 25000 | E17: =A17*D17 -> 25000 | F17: =E17*1.105 -> 27625 | I17: 13000 | J17: =I17*A17 -> 13000 | K17: =F17-J17 -> 14625
A18: 1 | B18: CAJON | C18: MORRON AMARILLO | D18: 35000 | E18: =A18*D18 -> 35000 | F18: =E18*1.105 -> 38675 | I18: 25000 | J18: =I18*A18 -> 25000 | K18: =F18-J18 -> 13675
A19: 2 | B19: PAQUETES | C19: BROTE DE SOJA | D19: 3000 | E19: =A19*D19 -> 6000 | F19: =E19*1.105 -> 6630 | I19: 2000 | J19: =I19*A19 -> 4000 | K19: =F19-J19 -> 2630
A20: 2 | B20: CAJA | C20: MANZANA GRANNY | D20: 63000 | E20: =A20*D20 -> 126000 | F20: =E20*1.105 -> 139230 | I20: 40000 | J20: =I20*A20 -> 80000 | K20: =F20-J20 -> 59230
A21: 2 | B21: CAJA | C21: BANANA | D21: 35000 | E21: =A21*D21 -> 70000 | F21: =E21*1.105 -> 77350 | I21: 24000 | J21: =I21*A21 -> 48000 | K21: =F21-J21 -> 29350
A22: 3 | B22: CAJON | C22: NARANJA FRIO | D22: 22000 | E22: =A22*D22 -> 66000 | F22: =E22*1.105 -> 72930 | I22: 17000 | J22: =I22*A22 -> 51000 | K22: =F22-J22 -> 21930
A23: 28 | B23: KG | C23: SANDIA | D23: 1200 | E23: =A23*D23 -> 33600 | F23: =E23*1.105 -> 37128 | I23: 700 | J23: =I23*A23 -> 19600 | K23: =F23-J23 -> 17528
A24: 2 | B24: CAJON | C24: MELON BLANCO | D24: 22000 | E24: =A24*D24 -> 44000 | F24: =E24*1.105 -> 48620 | I24: 15000 | J24: =I24*A24 -> 30000 | K24: =F24-J24 -> 18620
A25: 2 | B25: CAJON | C25: UVA RED GLOBE | D25: 40000 | E25: =A25*D25 -> 80000 | F25: =E25*1.105 -> 88400 | I25: 25000 | J25: =I25*A25 -> 50000 | K25: =F25-J25 -> 38400
A26: 2 | B26: CAJA | C26: BANANA | D26: 35000 | E26: =A26*D26 -> 70000 | F26: =E26*1.105 -> 77350 | G26: BOLSA | J26: =I26*A26 -> 0 | K26: =F26-J26 -> 77350
A27: 2 | B27: CAJON | C27: NARANJA | D27: 22000 | E27: =A27*D27 -> 44000 | F27: =E27*1.105 -> 48620 | G27: BOLSA | J27: =I27*A27 -> 0 | K27: =F27-J27 -> 48620
A28: 0.5 | B28: CAJÓN | C28: HUEVO | D28: 56000 | E28: =A28*D28 -> 28000 | F28: =E28*1.21 -> 33880 | G28: BOLSA | J28: =I28*A28 -> 0 | K28: =F28-J28 -> 33880
A29: 1 | B29: CAJON | C29: BERENJENA | D29: 15000 | E29: =A29*D29 -> 15000 | F29: =E29*1.105 -> 16575 | G29: BOLSA PROPIA | J29: =I29*A29 -> 0 | K29: =F29-J29 -> 16575
A30: 1 | B30: CAJON | C30: ZUCCINI | D30: 16000 | E30: =A30*D30 -> 16000 | F30: =E30*1.105 -> 17680 | G30: BOLSA PROPIA | J30: =I30*A30 -> 0 | K30: =F30-J30 -> 17680
A31: 1 | B31: CAJÓN | C31: TOMATE REDONDO | D31: 18000 | E31: =A31*D31 -> 18000 | F31: =E31*1.105 -> 19890 | G31: BOLSA PROPIA | J31: =I31*A31 -> 0 | K31: =F31-J31 -> 19890
A32: 1 | B32: CAJON | C32: TOMATE CHERRY | D32: 30000 | E32: =A32*D32 -> 30000 | F32: =E32*1.105 -> 33150 | G32: BOLSA PROPIA | J32: =I32*A32 -> 0 | K32: =F32-J32 -> 33150
E34: =SUM(E6:E32) -> 1070100 | F34: =SUM(F6:F32) -> 1188340.5 | K34: =SUM(K6:K32) -> 631740.5 | L34: =K34/F34 -> 0.53161573
A37: LUSQTOFF | B37: SEDE: IRALA | E37: rto: 1 | F37: 46055 | G37: ** | I37: COMPRA
A39: CANTIDAD | B39: UNIDAD | C39: PRODUCTO | D39: PRECIO | E39: TOTAL | F39: TOTAL + IVA | I39: PRECIO | J39: TOTAL | K39: DIFERENCIA
A40: 5 | B40: KG | C40: BERENJENA | D40: 1700 | E40: =A40*D40 -> 8500 | F40: =E40*1.105 -> 9392.5 | I40: 1000 | J40: =I40*A40 -> 5000 | K40: =F40-J40 -> 4392.5
A41: 1 | B41: BOLSA | C41: ANCO | D41: 13000 | E41: =A41*D41 -> 13000 | F41: =E41*1.105 -> 14365 | I41: 8000 | J41: =I41*A41 -> 8000 | K41: =F41-J41 -> 6365
A42: 1 | B42: BOLSA | C42: PAPA | D42: 14000 | E42: =A42*D42 -> 14000 | F42: =E42*1.105 -> 15470 | I42: 11000 | J42: =I42*A42 -> 11000 | K42: =F42-J42 -> 4470
A43: 0.5 | B43: BOLSA | C43: ZANAHORIA | D43: 12000 | E43: =A43*D43 -> 6000 | F43: =E43*1.105 -> 6630 | I43: 8000 | J43: =I43*A43 -> 4000 | K43: =F43-J43 -> 2630
A44: 3 | B44: KG | C44: LECHUGA | D44: 3500 | E44: =A44*D44 -> 10500 | F44: =E44*1.105 -> 11602.5 | I44: =12000/4 -> 3000 | J44: =I44*A44 -> 9000 | K44: =F44-J44 -> 2602.5
A45: 3 | B45: KG | C45: TOMATE REDONDO | D45: 1500 | E45: =A45*D45 -> 4500 | F45: =E45*1.105 -> 4972.5 | I45: =1000 -> 1000 | J45: =I45*A45 -> 3000 | K45: =F45-J45 -> 1972.5
A46: 5 | B46: KG | C46: ZUCCINI | D46: 1500 | E46: =A46*D46 -> 7500 | F46: =E46*1.105 -> 8287.5 | I46: =8000/14 -> 571.42857 | J46: =I46*A46 -> 2857.1429 | K46: =F46-J46 -> 5430.3571
A47: 4 | B47: KG | C47: ZAPALLITOS | D47: 1300 | E47: =A47*D47 -> 5200 | F47: =E47*1.105 -> 5746 | I47: =10000/15 -> 666.66667 | J47: =I47*A47 -> 2666.6667 | K47: =F47-J47 -> 3079.3333
A48: 3 | B48: KG | C48: MORRON ROJO | D48: 3500 | E48: =A48*D48 -> 10500 | F48: =E48*1.105 -> 11602.5 | I48: =30000/8 -> 3750 | J48: =I48*A48 -> 11250 | K48: =F48-J48 -> 352.5
A49: 3 | B49: KG | C49: MORRON VERDE | D49: 2700 | E49: =A49*D49 -> 8100 | F49: =E49*1.105 -> 8950.5 | I49: =13000/8 -> 1625 | J49: =I49*A49 -> 4875 | K49: =F49-J49 -> 4075.5
A50: 2 | B50: ATADO | C50: RABANITOS | D50: 850 | E50: =A50*D50 -> 1700 | F50: =E50*1.105 -> 1878.5 | I50: =2000/3 -> 666.66667 | J50: =I50*A50 -> 1333.3333 | K50: =F50-J50 -> 545.16667
A51: 1.5 | B51: CAJON | C51: HUEVO N2 | D51: 52000 | E51: =A51*D51 -> 78000 | F51: =E51*1.21 -> 94380 | I51: 46000 | J51: =I51*A51 -> 69000 | K51: =F51-J51 -> 25380
A52: 2 | B52: KG | C52: KIWI | D52: 11500 | E52: =A52*D52 -> 23000 | F52: =E52*1.105 -> 25415 | I52: =65000/7 -> 9285.7143 | J52: =I52*A52 -> 18571.429 | K52: =F52-J52 -> 6843.5714
A53: 10 | B53: KG | C53: NARANJA DE JUGO | D53: 1200 | E53: =A53*D53 -> 12000 | F53: =E53*1.105 -> 13260 | I53: =12000/15 -> 800 | J53: =I53*A53 -> 8000 | K53: =F53-J53 -> 5260
A54: 1 | B54: CAJA | C54: BANANA ECUADOR | D54: 38000 | E54: =A54*D54 -> 38000 | F54: =E54*1.105 -> 41990 | I54: 24000 | J54: =I54*A54 -> 24000 | K54: =F54-J54 -> 17990
A55: 8 | B55: KG | C55: PERA | D55: 2800 | E55: =A55*D55 -> 22400 | F55: =E55*1.105 -> 24752 | I55: =18000/9 -> 2000 | J55: =I55*A55 -> 16000 | K55: =F55-J55 -> 8752
A56: 2 | B56: KG | C56: FRUTILLA | D56: 6000 | E56: =A56*D56 -> 12000 | F56: =E56*1.105 -> 13260 | I56: 5000 | J56: =I56*A56 -> 10000 | K56: =F56-J56 -> 3260
A57: 2 | B57: KG | C57: UVA NEGRA | D57: 4500 | E57: =A57*D57 -> 9000 | F57: =E57*1.105 -> 9945 | H57: S/COST | J57: =I57*A57 -> 0 | K57: =F57-J57 -> 9945
E59: =SUM(E40:E57) -> 283900 | F59: =SUM(F40:F57) -> 321899.5 | K59: =SUM(K40:K57) -> 113345.93 | L59: =K59/F59 -> 0.35211589
A61: Comisión Juan | B61: 0.04 | E61: =E59*0.04 -> 11356
A64: LUSQTOFF | B64: SEDE: IRALA | C64: EVENTO | E64: rto: 2 | F64: 46055 | G64: ** | I64: COMPRA
A66: CANTIDAD | B66: UNIDAD | C66: PRODUCTO | D66: PRECIO | E66: TOTAL | F66: TOTAL + IVA | I66: PRECIO | J66: TOTAL | K66: DIFERENCIA
A67: 6 | B67: KG | C67: LEC CRIOLLA | D67: 3500 | E67: =A67*D67 -> 21000 | F67: =E67*1.105 -> 23205 | I67: =12000/4 -> 3000 | J67: =I67*A67 -> 18000 | K67: =F67-J67 -> 5205
A68: 4.5 | B68: KG | C68: TOMATE PERITA | D68: 1500 | E68: =A68*D68 -> 6750 | F68: =E68*1.105 -> 7458.75 | I68: =10000/15 -> 666.66667 | J68: =I68*A68 -> 3000 | K68: =F68-J68 -> 4458.75
A69: 1 | B69: BOLSA | C69: PAPA | D69: 14000 | E69: =A69*D69 -> 14000 | F69: =E69*1.105 -> 15470 | I69: 11000 | J69: =I69*A69 -> 11000 | K69: =F69-J69 -> 4470
A70: 4 | B70: KG | C70: ZANAHORIA | D70: 1500 | E70: =A70*D70 -> 6000 | F70: =E70*1.105 -> 6630 | I70: =8000/8 -> 1000 | J70: =I70*A70 -> 4000 | K70: =F70-J70 -> 2630
A71: 6 | B71: ATADOS | C71: RUCULA | D71: 350 | E71: =A71*D71 -> 2100 | F71: =E71*1.105 -> 2320.5 | I71: =2500/12 -> 208.33333 | J71: =I71*A71 -> 1250 | K71: =F71-J71 -> 1070.5
E73: =SUM(E67:E71) -> 49850 | F73: =SUM(F67:F71) -> 55084.25 | K73: =SUM(K67:K71) -> 17834.25 | L73: =K73/F73 -> 0.32376314
A75: Comisión Juan | B75: 0.04 | E75: =E73*0.04 -> 1994
A78: LUSQTOFF | B78: SEDE: MORENO | E78: rto: 1 | F78: 46055 | G78: ** | I78: COMPRA
A80: CANTIDAD | B80: UNIDAD | C80: PRODUCTO | D80: PRECIO | E80: TOTAL | F80: TOTAL + IVA | I80: PRECIO | J80: TOTAL | K80: DIFERENCIA
A81: 4 | B81: KG | C81: BERENJENA | D81: 1700 | E81: =A81*D81 -> 6800 | F81: =E81*1.105 -> 7514 | I81: =1000 -> 1000 | J81: =I81*A81 -> 4000 | K81: =F81-J81 -> 3514
A82: 1 | B82: CAJON | C82: LEC CRIOLLA | D82: 16000 | E82: =A82*D82 -> 16000 | F82: =E82*1.105 -> 17680 | I82: 12000 | J82: =I82*A82 -> 12000 | K82: =F82-J82 -> 5680
A83: 0.5 | B83: CAJON | C83: TOMATE REDONDO | D83: 18000 | E83: =A83*D83 -> 9000 | F83: =E83*1.105 -> 9945 | I83: 15000 | J83: =I83*A83 -> 7500 | K83: =F83-J83 -> 2445
A84: 1 | B84: BOLSA | C84: ZANAHORIA | D84: 12000 | E84: =A84*D84 -> 12000 | F84: =E84*1.105 -> 13260 | I84: 8000 | J84: =I84*A84 -> 8000 | K84: =F84-J84 -> 5260
A85: 1 | B85: BOLSA | C85: CEBOLLA | D85: 13000 | E85: =A85*D85 -> 13000 | F85: =E85*1.105 -> 14365 | I85: 10000 | J85: =I85*A85 -> 10000 | K85: =F85-J85 -> 4365
A86: 1 | B86: CAJON | C86: HUEVO | D86: 52000 | E86: =A86*D86 -> 52000 | F86: =E86*1.21 -> 62920 | I86: 46000 | J86: =I86*A86 -> 46000 | K86: =F86-J86 -> 16920
A87: 0.5 | B87: BOLSA | C87: ANCO | D87: 13000 | E87: =A87*D87 -> 6500 | F87: =E87*1.105 -> 7182.5 | I87: 8000 | J87: =I87*A87 -> 4000 | K87: =F87-J87 -> 3182.5
A88: 1 | B88: ATADO | C88: PEREJIL | D88: 3500 | E88: =A88*D88 -> 3500 | F88: =E88*1.105 -> 3867.5 | I88: 2000 | J88: =I88*A88 -> 2000 | K88: =F88-J88 -> 1867.5
A89: 2 | B89: KG | C89: ZAPALLITOS | D89: 1300 | E89: =A89*D89 -> 2600 | F89: =E89*1.105 -> 2873 | I89: =10000/15 -> 666.66667 | J89: =I89*A89 -> 1333.3333 | K89: =F89-J89 -> 1539.6667
A90: 2 | B90: KG | C90: ZUCCINI | D90: 1500 | E90: =A90*D90 -> 3000 | F90: =E90*1.105 -> 3315 | I90: =8000/14 -> 571.42857 | J90: =I90*A90 -> 1142.8571 | K90: =F90-J90 -> 2172.1429
A91: 2 | B91: ATADO | C91: REMOLACHA | D91: 1600 | E91: =A91*D91 -> 3200 | F91: =E91*1.105 -> 3536 | I91: 1500 | J91: =I91*A91 -> 3000 | K91: =F91-J91 -> 536
A92: 1 | B92: ATADO | C92: RABANITO | D92: 850 | E92: =A92*D92 -> 850 | F92: =E92*1.105 -> 939.25 | I92: =2000/3 -> 666.66667 | J92: =I92*A92 -> 666.66667 | K92: =F92-J92 -> 272.58333
A93: 2 | B93: UNIDAD | C93: REP BLANCO | D93: 1800 | E93: =A93*D93 -> 3600 | F93: =E93*1.105 -> 3978 | I93: =15000/12 -> 1250 | J93: =I93*A93 -> 2500 | K93: =F93-J93 -> 1478
A94: 2 | B94: BOLSA | C94: PAPA | D94: 14000 | E94: =A94*D94 -> 28000 | F94: =E94*1.105 -> 30940 | I94: 11000 | J94: =I94*A94 -> 22000 | K94: =F94-J94 -> 8940
A95: 2 | B95: KG | C95: LIMON | D95: 2700 | E95: =A95*D95 -> 5400 | F95: =E95*1.105 -> 5967 | I95: =28000/15 -> 1866.6667 | J95: =I95*A95 -> 3733.3333 | K95: =F95-J95 -> 2233.6667
A96: 2 | B96: KG | C96: KIWI | D96: 11500 | E96: =A96*D96 -> 23000 | F96: =E96*1.105 -> 25415 | I96: =65000/7 -> 9285.7143 | J96: =I96*A96 -> 18571.429 | K96: =F96-J96 -> 6843.5714
A97: 8 | B97: KG | C97: PERA | D97: 2700 | E97: =A97*D97 -> 21600 | F97: =E97*1.105 -> 23868 | I97: =18000/8 -> 2250 | J97: =I97*A97 -> 18000 | K97: =F97-J97 -> 5868
A98: 1 | B98: CAJA | C98: BANANA ECUADOR | D98: 38000 | E98: =A98*D98 -> 38000 | F98: =E98*1.105 -> 41990 | I98: 24000 | J98: =I98*A98 -> 24000 | K98: =F98-J98 -> 17990
A99: 2 | B99: KG | C99: FRUTILLA | D99: 6000 | E99: =A99*D99 -> 12000 | F99: =E99*1.105 -> 13260 | I99: 5000 | J99: =I99*A99 -> 10000 | K99: =F99-J99 -> 3260
A100: 2 | B100: KG | C100: UVA NEGRA | D100: 4500 | E100: =A100*D100 -> 9000 | F100: =E100*1.105 -> 9945 | H100: S/COST | J100: =I100*A100 -> 0 | K100: =F100-J100 -> 9945
A101: 5 | B101: ATADO | C101: RUCULA | D101: 350 | E101: =A101*D101 -> 1750 | F101: =E101*1.105 -> 1933.75 | I101: =2500/12 -> 208.33333 | J101: =I101*A101 -> 1041.6667 | K101: =F101-J101 -> 892.08333
E103: =SUM(E81:E101) -> 270800 | F103: =SUM(F81:F101) -> 304694 | K103: =SUM(K81:K101) -> 105204.71 | L103: =K103/F103 -> 0.3452799
A105: Comisión Juan | B105: 0.04 | E105: =E103*0.04 -> 10832
A108: AUPA | D108: rto: 4 | E108: 46055 | F108: **
A110: CANTIDAD | B110: UNIDAD | C110: PRODUCTO | D110: PRECIO | E110: TOTAL | I110: PRECIO | J110: TOTAL | K110: DIFERENCIA
A111: 4 | B111: BOLSA | C111: PAPA | D111: 15000 | E111: =A111*D111 -> 60000 | I111: 11000 | J111: =I111*A111 -> 44000 | K111: =E111-J111 -> 16000
A112: 2 | B112: BOLSA | C112: CEBOLLA | D112: 14000 | E112: =A112*D112 -> 28000 | I112: 10000 | J112: =I112*A112 -> 20000 | K112: =E112-J112 -> 8000
A113: 4 | B113: ATADOS | C113: REMOLCHA | D113: 2200 | E113: =A113*D113 -> 8800 | I113: 1500 | J113: =I113*A113 -> 6000 | K113: =E113-J113 -> 2800
A114: 3 | B114: BOLSA | C114: ZANAHORIA | D114: 12000 | E114: =A114*D114 -> 36000 | I114: 8000 | J114: =I114*A114 -> 24000 | K114: =E114-J114 -> 12000
A115: 3 | B115: BOLSA | C115: ANCO | D115: 14000 | E115: =A115*D115 -> 42000 | I115: 8000 | J115: =I115*A115 -> 24000 | K115: =E115-J115 -> 18000
A116: 1.5 | B116: CAJON | C116: ZAPALLITO | D116: 14000 | E116: =A116*D116 -> 21000 | I116: 10000 | J116: =I116*A116 -> 15000 | K116: =E116-J116 -> 6000
A117: 1 | B117: CAJON | C117: ACELGA | D117: 14000 | E117: =A117*D117 -> 14000 | I117: 12000 | J117: =I117*A117 -> 12000 | K117: =E117-J117 -> 2000
A118: 1 | B118: KG | C118: LIMON | D118: 2500 | E118: =A118*D118 -> 2500 | I118: =28000/15 -> 1866.6667 | J118: =I118*A118 -> 1866.6667 | K118: =E118-J118 -> 633.33333
A119: 3 | B119: CAJA | C119: BANANA | D119: 37000 | E119: =A119*D119 -> 111000 | I119: 24000 | J119: =I119*A119 -> 72000 | K119: =E119-J119 -> 39000
A120: 2 | B120: CAJA | C120: MANZANA ROJA | D120: 40000 | E120: =A120*D120 -> 80000 | I120: 25000 | J120: =I120*A120 -> 50000 | K120: =E120-J120 -> 30000
A121: 2 | B121: CAJON | C121: NARANJA | D121: 16000 | E121: =A121*D121 -> 32000 | I121: 12000 | J121: =I121*A121 -> 24000 | K121: =E121-J121 -> 8000
A122: 1 | B122: UNIDAD | C122: REP COLOR | D122: 2000 | E122: =A122*D122 -> 2000 | I122: =15000/12 -> 1250 | J122: =I122*A122 -> 1250 | K122: =E122-J122 -> 750
...

Sheet 03-02-2026 
A3: FABRIC SUSHI - MORENO | E3: rto: 3 | F3: 46056 | I3: COMPRA
A5: CANTIDAD | B5: UNIDAD | C5: PRODUCTO | D5: PRECIO | E5: TOTAL | F5: TOTAL + IVA | I5: PRECIO | J5: TOTAL | K5: DIFERENCIA
A6: 1 | B6: UNIDAD | C6: APIO | D6: 1500 | E6: =A6*D6 -> 1500 | F6: =E6*1.105 -> 1657.5 | I6: 1000 | J6: =I6*A6 -> 1000 | K6: =F6-J6 -> 657.5
A7: 3 | B7: ATADOS | C7: CEB VERDEO | D7: 5500 | E7: =A7*D7 -> 16500 | F7: =E7*1.105 -> 18232.5 | I7: 4000 | J7: =I7*A7 -> 12000 | K7: =F7-J7 -> 6232.5
A8: 3 | B8: ATADOS | C8: CILANTRO | D8: 3000 | E8: =A8*D8 -> 9000 | F8: =E8*1.105 -> 9945 | I8: 2000 | J8: =I8*A8 -> 6000 | K8: =F8-J8 -> 3945
A9: 3 | B9: ATADOS | C9: CIBOULLETE | D9: 3000 | E9: =A9*D9 -> 9000 | F9: =E9*1.105 -> 9945 | I9: 2000 | J9: =I9*A9 -> 6000 | K9: =F9-J9 -> 3945
A10: 3 | B10: KG | C10: MORRON ROJO | D10: 4000 | E10: =A10*D10 -> 12000 | F10: =E10*1.105 -> 13260 | I10: =25000/8 -> 3125 | J10: =I10*A10 -> 9375 | K10: =F10-J10 -> 3885
A11: 2 | B11: KG | C11: MORRON VERDE | D11: 2700 | E11: =A11*D11 -> 5400 | F11: =E11*1.105 -> 5967 | I11: =13000/8 -> 1625 | J11: =I11*A11 -> 3250 | K11: =F11-J11 -> 2717
A12: 2 | B12: KG | C12: MORRON AMARILLO | D12: 4000 | E12: =A12*D12 -> 8000 | F12: =E12*1.105 -> 8840 | I12: =25000/8 -> 3125 | J12: =I12*A12 -> 6250 | K12: =F12-J12 -> 2590
A13: 2 | B13: KG | C13: ZAP LARGO | D13: 1500 | E13: =A13*D13 -> 3000 | F13: =E13*1.105 -> 3315 | I13: =8000/15 -> 533.33333 | J13: =I13*A13 -> 1066.6667 | K13: =F13-J13 -> 2248.3333
A14: 3 | B14: KG | C14: CEBOLLA MORADA | D14: 1600 | E14: =A14*D14 -> 4800 | F14: =E14*1.105 -> 5304 | I14: 1000 | J14: =I14*A14 -> 3000 | K14: =F14-J14 -> 2304
A15: 2 | B15: KG | C15: CEBOLLA | D15: 800 | E15: =A15*D15 -> 1600 | F15: =E15*1.105 -> 1768 | I15: =10000/17 -> 588.23529 | J15: =I15*A15 -> 1176.4706 | K15: =F15-J15 -> 591.52941
A16: 5 | B16: UNIDAD | C16: AJO | D16: 900 | E16: =A16*D16 -> 4500 | F16: =E16*1.105 -> 4972.5 | I16: 560 | J16: =I16*A16 -> 2800 | K16: =F16-J16 -> 2172.5
A17: 3 | B17: KG | C17: PEPINO | D17: 1300 | E17: =A17*D17 -> 3900 | F17: =E17*1.105 -> 4309.5 | I17: =12000/15 -> 800 | J17: =I17*A17 -> 2400 | K17: =F17-J17 -> 1909.5
A18: 2 | B18: KG | C18: TOMATE | D18: 1500 | E18: =A18*D18 -> 3000 | F18: =E18*1.105 -> 3315 | I18: =12000/15 -> 800 | J18: =I18*A18 -> 1600 | K18: =F18-J18 -> 1715
A19: 0.5 | B19: BOLSA | C19: PAPA LAVADA | D19: 20000 | E19: =A19*D19 -> 10000 | F19: =E19*1.105 -> 11050 | I19: 18500 | J19: =I19*A19 -> 9250 | K19: =F19-J19 -> 1800
A20: 5 | B20: KG | C20: BATATA | D20: 1400 | E20: =A20*D20 -> 7000 | F20: =E20*1.105 -> 7735 | I20: 1000 | J20: =I20*A20 -> 5000 | K20: =F20-J20 -> 2735
A21: 1 | B21: BANDEJAS | C21: GIRGOLAS | D21: 6000 | E21: =A21*D21 -> 6000 | F21: =E21*1.105 -> 6630 | I21: 4500 | J21: =I21*A21 -> 4500 | K21: =F21-J21 -> 2130
A22: 0.5 | B22: KG | C22: PORTOBELLO | D22: 22000 | E22: =A22*D22 -> 11000 | F22: =E22*1.105 -> 12155 | I22: 20000 | J22: =I22*A22 -> 10000 | K22: =F22-J22 -> 2155
A23: 1 | B23: KG | C23: AJI PERUANO | D23: 26000 | E23: =A23*D23 -> 26000 | F23: =E23*1.105 -> 28730 | I23: 22000 | J23: =I23*A23 -> 22000 | K23: =F23-J23 -> 6730
A24: 0.5 | B24: KG | C24: AJI ROCOTO | D24: 12000 | E24: =A24*D24 -> 6000 | F24: =E24*1.105 -> 6630 | I24: 8000 | J24: =I24*A24 -> 4000 | K24: =F24-J24 -> 2630
A25: 0.5 | B25: KG | C25: AJI LIMO | D25: 12000 | E25: =A25*D25 -> 6000 | F25: =E25*1.105 -> 6630 | I25: 7000 | J25: =I25*A25 -> 3500 | K25: =F25-J25 -> 3130
A26: 0.25 | B26: KG | C26: HONGOS DE PINO | D26: 50000 | E26: =A26*D26 -> 12500 | F26: =E26*1.105 -> 13812.5 | I26: 40000 | J26: =I26*A26 -> 10000 | K26: =F26-J26 -> 3812.5
A27: 1 | B27: BOLSA | C27: BROTES DE SOJA | D27: 3000 | E27: =A27*D27 -> 3000 | F27: =E27*1.105 -> 3315 | I27: 2000 | J27: =I27*A27 -> 2000 | K27: =F27-J27 -> 1315
A28: 0.6 | B28: KG | C28: AJI PANKA ROJO | D28: 23000 | E28: =A28*D28 -> 13800 | F28: =E28*1.105 -> 15249 | I28: 18000 | J28: =I28*A28 -> 10800 | K28: =F28-J28 -> 4449
A29: 4 | B29: ATADOS | C29: PUERRO | D29: 6000 | E29: =A29*D29 -> 24000 | F29: =E29*1.105 -> 26520 | I29: 4000 | J29: =I29*A29 -> 16000 | K29: =F29-J29 -> 10520
E31: =SUM(E6:E29) -> 207500 | F31: =SUM(F6:F29) -> 229287.5 | K31: =SUM(K6:K29) -> 76319.363 | L31: =K31/F31 -> 0.33285444
A33: Comisión Juan | B33: 0.04 | E33: =E31*0.04 -> 8300
A36: S&T CATERING | D36: rto: 2 | E36: 46056
A38: CANTIDAD | B38: UNIDAD | C38: PRODUCTO | D38: PRECIO | E38: TOTAL | I38: PRECIO | J38: TOTAL | K38: DIFERENCIA
A39: 2 | B39: CAJON | C39: ZAPALLITO LARGO | D39: 13000 | E39: =A39*D39 -> 26000 | I39: 8000 | J39: =I39*A39 -> 16000 | K39: =E39-J39 -> 10000
A40: 1 | B40: CAJON | C40: ZAPALLITO REDONDO | D40: 13000 | E40: =A40*D40 -> 13000 | H40: S/COSTO | I40: 0 | J40: =I40*A40 -> 0 | K40: =E40-J40 -> 13000
A41: 2 | B41: CAJON | C41: BERENJENA | D41: 13000 | E41: =A41*D41 -> 26000 | I41: 7000 | J41: =I41*A41 -> 14000 | K41: =E41-J41 -> 12000
A42: 2 | B42: CAJON | C42: LECHUGA FRANCESA | D42: 13000 | E42: =A42*D42 -> 26000 | I42: 10000 | J42: =I42*A42 -> 20000 | K42: =E42-J42 -> 6000
A43: 2 | B43: CAJON | C43: LECHUGA MORADA | D43: 10000 | E43: =A43*D43 -> 20000 | I43: 6000 | J43: =I43*A43 -> 12000 | K43: =E43-J43 -> 8000
A44: 2 | B44: CAJON | C44: RUCULA | D44: 7500 | E44: =A44*D44 -> 15000 | I44: 6000 | J44: =I44*A44 -> 12000 | K44: =E44-J44 -> 3000
A45: 1 | B45: CAJON | C45: CHERRY | D45: 23000 | E45: =A45*D45 -> 23000 | I45: 15000 | J45: =I45*A45 -> 15000 | K45: =E45-J45 -> 8000
E47: =SUM(E39:E45) -> 149000 | K47: =SUM(K39:K45) -> 60000 | L47: =K47/E47 -> 0.40268456
A51: RAKUS | D51: rto: 19 | E51: 46056
A53: CANTIDAD | B53: UNIDAD | C53: PRODUCTO | D53: PRECIO | E53: TOTAL | I53: PRECIO | J53: TOTAL | K53: DIFERENCIA
A54: 0.5 | B54: ATADO | C54: CEB VERDEO | D54: 5500 | E54: =A54*D54 -> 2750 | I54: 4000 | J54: =I54*A54 -> 2000 | K54: =E54-J54 -> 750
A55: 1 | B55: KG | C55: CHAMPI | D55: 20000 | E55: =A55*D55 -> 20000 | I55: 18000 | J55: =I55*A55 -> 18000 | K55: =E55-J55 -> 2000
A56: 1 | B56: CAJA | C56: ARANDANO | D56: 28000 | E56: =A56*D56 -> 28000 | I56: 24000 | J56: =I56*A56 -> 24000 | K56: =E56-J56 -> 4000
A57: 2 | B57: KG | C57: DURAZNO | D57: 4000 | E57: =A57*D57 -> 8000 | I57: =25000/12 -> 2083.3333 | J57: =I57*A57 -> 4166.6667 | K57: =E57-J57 -> 3833.3333
A58: 1 | B58: BOLSA | C58: CEBOLLA | D58: 13000 | E58: =A58*D58 -> 13000 | I58: 8000 | J58: =I58*A58 -> 8000 | K58: =E58-J58 -> 5000
A59: 2 | B59: KG | C59: TOM CHERRY | D59: 3500 | E59: =A59*D59 -> 7000 | I59: =15000/8 -> 1875 | J59: =I59*A59 -> 3750 | K59: =E59-J59 -> 3250
A60: 1 | B60: KG | C60: TOM CHERRY AMA | D60: 3500 | E60: =A60*D60 -> 3500 | I60: =23000/8 -> 2875 | J60: =I60*A60 -> 2875 | K60: =E60-J60 -> 625
A61: 2 | B61: CAJON | C61: NARANJA FRIO | D61: 22000 | E61: =A61*D61 -> 44000 | I61: 17000 | J61: =I61*A61 -> 34000 | K61: =E61-J61 -> 10000
A62: 0.5 | B62: CAJON | C62: POMELO IMPORTADO | D62: 45000 | E62: =A62*D62 -> 22500 | I62: 40000 | J62: =I62*A62 -> 20000 | K62: =E62-J62 -> 2500
A63: 1 | B63: ATADO | C63: MENTA | D63: 3000 | E63: =A63*D63 -> 3000 | I63: 2000 | J63: =I63*A63 -> 2000 | K63: =E63-J63 -> 1000
A64: 1 | B64: ATADO | C64: ALBAHACA | D64: 1000 | E64: =A64*D64 -> 1000 | I64: 500 | J64: =I64*A64 -> 500 | K64: =E64-J64 -> 500
A65: 2 | B65: KG | C65: LIMA | D65: 4000 | E65: =A65*D65 -> 8000 | I65: 2500 | J65: =I65*A65 -> 5000 | K65: =E65-J65 -> 3000
A66: 4.5 | B66: KG | C66: FRUTILLA | D66: 5500 | E66: =A66*D66 -> 24750 | I66: =20000/5 -> 4000 | J66: =I66*A66 -> 18000 | K66: =E66-J66 -> 6750
E68: =SUM(E54:E67) -> 185500 | K68: =SUM(K54:K66) -> 43208.333 | L68: =K68/E68 -> 0.23292902
A72: BRASOV | D72: rto: 10 | E72: 46056
A74: CANTIDAD | B74: UNIDAD | C74: PRODUCTO | D74: PRECIO | E74: TOTAL | I74: PRECIO | J74: TOTAL | K74: DIFERENCIA
A75: 1 | B75: BOLSA | C75: ANCO | D75: 13000 | E75: =A75*D75 -> 13000 | I75: 8000 | J75: =I75*A75 -> 8000 | K75: =E75-J75 -> 5000
A76: 3 | B76: UNIDAD | C76: APIO | D76: 2000 | E76: =A76*D76 -> 6000 | I76: 1000 | J76: =I76*A76 -> 3000 | K76: =E76-J76 -> 3000
A77: 1 | B77: BOLSA | C77: BATATA | D77: 12000 | E77: =A77*D77 -> 12000 | I77: 8500 | J77: =I77*A77 -> 8500 | K77: =E77-J77 -> 3500
A78: 1 | B78: BOLSA | C78: BONIATO | D78: 27000 | E78: =A78*D78 -> 27000 | I78: 23000 | J78: =I78*A78 -> 23000 | K78: =E78-J78 -> 4000
A79: 1 | B79: BANDEJA | C79: TOM CHERRY | D79: 12500 | E79: =A79*D79 -> 12500 | I79: =1875*5 -> 9375 | J79: =I79*A79 -> 9375 | K79: =E79-J79 -> 3125
A80: 1 | B80: ATADO | C80: CIBOULLETE | D80: 3000 | E80: =A80*D80 -> 3000 | I80: 2000 | J80: =I80*A80 -> 2000 | K80: =E80-J80 -> 1000
A81: 2 | B81: CAJA | C81: LIMON | D81: 26000 | E81: =A81*D81 -> 52000 | I81: 18000 | J81: =I81*A81 -> 36000 | K81: =E81-J81 -> 16000
A82: 2 | B82: ATADO | C82: MENTA | D82: 3000 | E82: =A82*D82 -> 6000 | I82: 2000 | J82: =I82*A82 -> 4000 | K82: =E82-J82 -> 2000
A83: 2 | B83: CAJON | C83: NARANJA | D83: 16000 | E83: =A83*D83 -> 32000 | I83: 13000 | J83: =I83*A83 -> 26000 | K83: =E83-J83 -> 6000
A84: 0.5 | B84: CAJON | C84: MORRON ROJO | D84: 30000 | E84: =A84*D84 -> 15000 | I84: 25000 | J84: =I84*A84 -> 12500 | K84: =E84-J84 -> 2500
A85: 1 | B85: CAJA | C85: PALTA | D85: 65000 | E85: =A85*D85 -> 65000 | I85: 53000 | J85: =I85*A85 -> 53000 | K85: =E85-J85 -> 12000
A86: 2 | B86: BOLSA | C86: PAPA | D86: 22000 | E86: =A86*D86 -> 44000 | I86: 18500 | J86: =I86*A86 -> 37000 | K86: =E86-J86 -> 7000
A87: 2 | B87: KG | C87: PEPINO | D87: 1400 | E87: =A87*D87 -> 2800 | I87: =12000/15 -> 800 | J87: =I87*A87 -> 1600 | K87: =E87-J87 -> 1200
A88: 2 | B88: ATADO | C88: PEREJIL | D88: 4000 | E88: =A88*D88 -> 8000 | I88: 2000 | J88: =I88*A88 -> 4000 | K88: =E88-J88 -> 4000
A89: 1 | B89: ATADO | C89: PUERRO | D89: 5000 | E89: =A89*D89 -> 5000 | I89: 4000 | J89: =I89*A89 -> 4000 | K89: =E89-J89 -> 1000
A90: 1 | B90: CAJON | C90: TOMATE REDONDO | D90: 18000 | E90: =A90*D90 -> 18000 | I90: 10000 | J90: =I90*A90 -> 10000 | K90: =E90-J90 -> 8000
A91: 2 | B91: ATADO | C91: CEB VERDEO | D91: 5000 | E91: =A91*D91 -> 10000 | I91: 4000 | J91: =I91*A91 -> 8000 | K91: =E91-J91 -> 2000
A92: 1 | B92: BOLSA | C92: ZANAHORIA | D92: 11000 | E92: =A92*D92 -> 11000 | I92: 8000 | J92: =I92*A92 -> 8000 | K92: =E92-J92 -> 3000
A93: 2 | B93: UNIDAD | C93: MANGO | D93: 2000 | E93: =A93*D93 -> 4000 | I93: =10000/12 -> 833.33333 | J93: =I93*A93 -> 1666.6667 | K93: =E93-J93 -> 2333.3333
E95: =SUM(E75:E94) -> 346300 | K95: =SUM(K75:K93) -> 86658.333 | L95: =K95/E95 -> 0.25024064
A98: HAVANNA | B98: MORENO | D98: rto: 3 | E98: 46056
A100: CANTIDAD | B100: UNIDAD | C100: PRODUCTO | D100: PRECIO | E100: TOTAL | I100: PRECIO | J100: TOTAL | K100: DIFERENCIA
A101: 2 | B101: KG | C101: BANANA | D101: 3000 | E101: =A101*D101 -> 6000 | I101: =24000/18 -> 1333.3333 | J101: =I101*A101 -> 2666.6667 | K101: =E101-J101 -> 3333.3333
A102: 2 | B102: CAJON | C102: NARANJA | D102: 16000 | E102: =A102*D102 -> 32000 | I102: 12000 | J102: =I102*A102 -> 24000 | K102: =E102-J102 -> 8000
E104: =SUM(E101:E103) -> 38000 | K104: =SUM(K101+K102) -> 11333.333 | L104: =K104/E104 -> 0.29824561
A106: Comisión Juan | B106: 0.04 | E106: =E104*0.04 -> 1520
A110: CAFE MARTINEZ | B110: MORENO - GORRITI | D110: rto: 3 | E110: 46056
A112: CANTIDAD | B112: UNIDAD | C112: PRODUCTO | D112: PRECIO | E112: TOTAL | I112: PRECIO | J112: TOTAL | K112: DIFERENCIA
A113: 0.5 | B113: KG | C113: FRUTILLA | D113: 6500 | E113: =A113*D113 -> 3250 | I113: =20000/5 -> 4000 | J113: =I113*A113 -> 2000 | K113: =E113-J113 -> 1250
A114: 1 | B114: KG | C114: LECHUGA FRANCESA | D114: 3000 | E114: =A114*D114 -> 3000 | H114: S/COSTO | I114: 0 | J114: =I114*A114 -> 0 | K114: =E114-J114 -> 3000
A115: 0.45 | B115: KG | C115: MANZANA | D115: 4000 | E115: =A115*D115 -> 1800 | I115: =40000/18 -> 2222.2222 | J115: =I115*A115 -> 1000 | K115: =E115-J115 -> 800
A116: 1 | B116: KG | C116: LIMON | D116: 3300 | E116: =A116*D116 -> 3300 | I116: =38000/15 -> 2533.3333 | J116: =I116*A116 -> 2533.3333 | K116: =E116-J116 -> 766.66667
E118: =SUM(E113:E117) -> 11350 | K118: =SUM(K113:K116) -> 5816.6667 | L118: =K118/E118 -> 0.51248164
A120: Comisión Juan | B120: 0.04 | E120: =E118*0.04 -> 454
A125: TOTAL DIA | B125: =E118+E104+E95+E68+E47+F31 -> 959437.5
A127: GANANCIA | B127: =K118+K104+K95+K68+K47+K31 -> 283336.03
A129: Comision Juan | B129: =E120+E106+E33 -> 10274
A131: % | B131: =B127/B125 -> 0.29531473
A133: BULTOS COMPRADOS | C133: 100
B138: EFECTIVO | C138: MERCADO PAGO | D138: BANCO GALCIA | E138: BANCO RIO | F138: CHEQUES
B139: 2528350 | C139: 308459.29 | D139: =2277828.28-500000-1000000+491000 -> 1268828.3 | F139: =8500000+1101582.8 -> 9601582.8
A141: INGRESOS
A142: COBR. CTA. CTE | B142: 319800 | C142: 0 | D142: 0 | E142: 0 | F142: 0
A143: RENDIMIENTO MP | B143: 0 | C143: 3625.2 | D143: 0 | E143: 0 | F143: 0
...

Sheet 04-02-2026 
A3: FV | E3: rto: 224 | F3: 46057 | I3: COMPRA
A5: CANTIDAD | B5: UNIDAD | C5: PRODUCTO | D5: PRECIO | E5: TOTAL | F5: TOTAL + IVA | I5: PRECIO | J5: TOTAL | K5: DIFERENCIA
A6: 3 | B6: CAJA | C6: BANANA | D6: 35000 | E6: =A6*D6 -> 105000 | F6: =E6*1.105 -> 116025 | I6: 25000 | J6: =I6*A6 -> 75000 | K6: =F6-J6 -> 41025
A7: 5 | B7: CAJA | C7: DURAZNO | D7: 34000 | E7: =A7*D7 -> 170000 | F7: =E7*1.105 -> 187850 | I7: 22000 | J7: =I7*A7 -> 110000 | K7: =F7-J7 -> 77850
A8: 3 | B8: CAJA | C8: CIRUELA | D8: 35000 | E8: =A8*D8 -> 105000 | F8: =E8*1.105 -> 116025 | I8: 27000 | J8: =I8*A8 -> 81000 | K8: =F8-J8 -> 35025
A9: 3 | B9: CAJA | C9: PELON | D9: 35000 | E9: =A9*D9 -> 105000 | F9: =E9*1.105 -> 116025 | I9: 20000 | J9: =I9*A9 -> 60000 | K9: =F9-J9 -> 56025
A10: 2 | B10: CAJON | C10: TOMATE REDONDO | D10: 18000 | E10: =A10*D10 -> 36000 | F10: =E10*1.105 -> 39780 | I10: 12000 | J10: =I10*A10 -> 24000 | K10: =F10-J10 -> 15780
A11: 1 | B11: CAJON | C11: HUEVO | D11: 56000 | E11: =A11*D11 -> 56000 | F11: =E11*1.21 -> 67760 | I11: 46000 | J11: =I11*A11 -> 46000 | K11: =F11-J11 -> 21760
A12: 2 | B12: CAJA | C12: MANZANA GRANNY | D12: 63000 | E12: =A12*D12 -> 126000 | F12: =E12*1.105 -> 139230 | I12: 22000 | J12: =I12*A12 -> 44000 | K12: =F12-J12 -> 95230
A13: 15 | B13: UNIDAD | C13: PALTA HASS | D13: 1300 | E13: =A13*D13 -> 19500 | F13: =E13*1.105 -> 21547.5 | I13: =53000/80 -> 662.5 | J13: =I13*A13 -> 9937.5 | K13: =F13-J13 -> 11610
A14: 2 | B14: CAJON | C14: NARANJA | D14: 22000 | E14: =A14*D14 -> 44000 | F14: =E14*1.105 -> 48620 | I14: 18000 | J14: =I14*A14 -> 36000 | K14: =F14-J14 -> 12620
A15: 19 | B15: KG | C15: SANDIA | D15: 1200 | E15: =A15*D15 -> 22800 | F15: =E15*1.105 -> 25194 | I15: 700 | J15: =I15*A15 -> 13300 | K15: =F15-J15 -> 11894
A16: 1 | B16: CAJON | C16: MELON | D16: 22000 | E16: =A16*D16 -> 22000 | F16: =E16*1.105 -> 24310 | I16: 15000 | J16: =I16*A16 -> 15000 | K16: =F16-J16 -> 9310
A17: 2 | B17: CAJON | C17: UVA blanca s/semilla | D17: 40000 | E17: =A17*D17 -> 80000 | F17: =E17*1.105 -> 88400 | I17: 35000 | J17: =I17*A17 -> 70000 | K17: =F17-J17 -> 18400
A18: 1 | B18: CAJA | C18: MANZANA GRANNY | D18: 63000 | E18: =A18*D18 -> 63000 | F18: =E18*1.105 -> 69615 | G18: bolsa | I18: 0 | J18: =I18*A18 -> 0 | K18: =F18-J18 -> 69615
A19: 1 | B19: CAJON | C19: NARANJA | D19: 22000 | E19: =A19*D19 -> 22000 | F19: =E19*1.105 -> 24310 | G19: bolsa | I19: 0 | J19: =I19*A19 -> 0 | K19: =F19-J19 -> 24310
A20: 1 | B20: CAJON | C20: TOMATE REDONDO | D20: 18000 | E20: =A20*D20 -> 18000 | F20: =E20*1.105 -> 19890 | G20: bolsa | I20: 0 | J20: =I20*A20 -> 0 | K20: =F20-J20 -> 19890
A21: 0.5 | B21: CAJON | C21: HUEVO | D21: 56000 | E21: =A21*D21 -> 28000 | F21: =E21*1.21 -> 33880 | G21: bolsa | I21: 0 | J21: =I21*A21 -> 0 | K21: =F21-J21 -> 33880
A22: 1 | B22: CAJON | C22: PELON | D22: 35000 | E22: =A22*D22 -> 35000 | F22: =E22*1.105 -> 38675 | G22: bolsa propia | I22: 0 | J22: =I22*A22 -> 0 | K22: =F22-J22 -> 38675
A23: 1 | B23: CAJON | C23: DURAZNO | D23: 34000 | E23: =A23*D23 -> 34000 | F23: =E23*1.105 -> 37570 | G23: bolsa propia | I23: 0 | J23: =I23*A23 -> 0 | K23: =F23-J23 -> 37570
A24: 3 | B24: CAJA | C24: BANANA | D24: 35000 | E24: =A24*D24 -> 105000 | F24: =E24*1.105 -> 116025 | G24: bolsa propia | I24: 0 | J24: =I24*A24 -> 0 | K24: =F24-J24 -> 116025
E26: =SUM(E6:E24) -> 1196300 | F26: =SUM(F6:F24) -> 1330731.5 | K26: =SUM(K6:K24) -> 746494 | L26: =K26/F26 -> 0.56096515
A29: LA PIADINA | D29: rto: 15 | E29: 46057
A31: CANTIDAD | B31: UNIDAD | C31: PRODUCTO | D31: PRECIO | E31: TOTAL | I31: PRECIO | J31: TOTAL | K31: DIFERENCIA
A32: 1 | B32: KG | C32: BANANA | D32: 2800 | E32: =A32*D32 -> 2800 | H32: S/COSTO | I32: 0 | J32: =I32*A32 -> 0 | K32: =E32-J32 -> 2800
A33: 1 | B33: KG | C33: NARANJA | D33: 1400 | E33: =A33*D33 -> 1400 | H33: S/COSTO | I33: 0 | J33: =I33*A33 -> 0 | K33: =E33-J33 -> 1400
A34: 0.5 | B34: KG | C34: MANZANA | D34: 3500 | E34: =A34*D34 -> 1750 | I34: =50000/18 -> 2777.7778 | J34: =I34*A34 -> 1388.8889 | K34: =E34-J34 -> 361.11111
A35: 1.5 | B35: KG | C35: FRUTILLA | D35: 6000 | E35: =A35*D35 -> 9000 | I35: =20000/5 -> 4000 | J35: =I35*A35 -> 6000 | K35: =E35-J35 -> 3000
A36: 0.35 | B36: KG | C36: DURAZNO | D36: 4500 | E36: =A36*D36 -> 1575 | H36: S/COSTO | I36: 0 | J36: =I36*A36 -> 0 | K36: =E36-J36 -> 1575
A37: 0.3 | B37: KG | C37: KIWI | D37: 12000 | E37: =A37*D37 -> 3600 | I37: =65000/7 -> 9285.7143 | J37: =I37*A37 -> 2785.7143 | K37: =E37-J37 -> 814.28571
A38: 3 | B38: CUBETA | C38: ARANDANO | D38: 2500 | E38: =A38*D38 -> 7500 | I38: =22000/12 -> 1833.3333 | J38: =I38*A38 -> 5500 | K38: =E38-J38 -> 2000
A39: 0.5 | B39: KG | C39: UVA | D39: 4500 | E39: =A39*D39 -> 2250 | H39: S/COSTO | I39: 0 | J39: =I39*A39 -> 0 | K39: =E39-J39 -> 2250
A40: 3 | B40: KG | C40: TOMATE | D40: 1500 | E40: =A40*D40 -> 4500 | I40: =13000/15 -> 866.66667 | J40: =I40*A40 -> 2600 | K40: =E40-J40 -> 1900
A41: 3 | B41: ATADO | C41: ALBAHACA | D41: 1000 | E41: =A41*D41 -> 3000 | I41: 500 | J41: =I41*A41 -> 1500 | K41: =E41-J41 -> 1500
A42: 1 | B42: KG | C42: LECHUGA | D42: 3500 | E42: =A42*D42 -> 3500 | H42: S/COSTO | I42: 0 | J42: =I42*A42 -> 0 | K42: =E42-J42 -> 3500
A43: 4 | B43: UNIDAD | C43: PALTA | D43: 1300 | E43: =A43*D43 -> 5200 | I43: =53000/80 -> 662.5 | J43: =I43*A43 -> 2650 | K43: =E43-J43 -> 2550
E45: =SUM(E32:E43) -> 46075 | K45: =SUM(K32:K42) -> 21100.397 | L45: =K45/E45 -> 0.45795761
A49: HOGAR CARDALES | D49: rto: 5 | E49: 46057
A51: CANTIDAD | B51: UNIDAD | C51: PRODUCTO | D51: PRECIO | E51: TOTAL | I51: PRECIO | J51: TOTAL | K51: DIFERENCIA
A52: 4 | B52: ATADOS | C52: ACELGA | D52: 1500 | E52: =A52*D52 -> 6000 | H52: VERDU | I52: 1500 | J52: =I52*A52 -> 6000 | K52: =E52-J52 -> 0
A53: 2 | B53: UNIDAD | C53: APIO | D53: 2000 | E53: =A53*D53 -> 4000 | I53: 1000 | J53: =I53*A53 -> 2000 | K53: =E53-J53 -> 2000
A54: 2 | B54: UNIDAD | C54: AJO | D54: 1200 | E54: =A54*D54 -> 2400 | I54: 560 | J54: =I54*A54 -> 1120 | K54: =E54-J54 -> 1280
A55: 2 | B55: UNIDAD | C55: BROCOLI | D55: 2000 | E55: =A55*D55 -> 4000 | H55: VERDU | I55: 1500 | J55: =I55*A55 -> 3000 | K55: =E55-J55 -> 1000
A56: 1 | B56: KG | C56: CHAUCHA | D56: 6000 | E56: =A56*D56 -> 6000 | H56: VERDU | I56: 5000 | J56: =I56*A56 -> 5000 | K56: =E56-J56 -> 1000
A57: 2 | B57: ATADOS | C57: ESPINACA | D57: 1800 | E57: =A57*D57 -> 3600 | H57: VERDU | I57: 1500 | J57: =I57*A57 -> 3000 | K57: =E57-J57 -> 600
A58: 1 | B58: KG | C58: MORRON ROJO | D58: 3500 | E58: =A58*D58 -> 3500 | I58: =25000/8 -> 3125 | J58: =I58*A58 -> 3125 | K58: =E58-J58 -> 375
A59: 3 | B59: KG | C59: LECHUGA | D59: 3000 | E59: =A59*D59 -> 9000 | H59: S/COSTO | I59: 0 | J59: =I59*A59 -> 0 | K59: =E59-J59 -> 9000
A60: 2 | B60: UNIDAD | C60: PALTA | D60: 1300 | E60: =A60*D60 -> 2600 | I60: =53000/80 -> 662.5 | J60: =I60*A60 -> 1325 | K60: =E60-J60 -> 1275
A61: 4 | B61: KG | C61: REMOLACHA | D61: 1800 | E61: =A61*D61 -> 7200 | I61: 1300 | J61: =I61*A61 -> 5200 | K61: =E61-J61 -> 2000
A62: 7 | B62: KG | C62: TOMATE | D62: 1400 | E62: =A62*D62 -> 9800 | I62: =13000/15 -> 866.66667 | J62: =I62*A62 -> 6066.6667 | K62: =E62-J62 -> 3733.3333
A63: 4 | B63: KG | C63: ZAPALLITO REDONDO | D63: 1500 | E63: =A63*D63 -> 6000 | I63: =8000/14 -> 571.42857 | J63: =I63*A63 -> 2285.7143 | K63: =E63-J63 -> 3714.2857
A64: 2 | B64: KG | C64: ZAP LARGO | D64: 1500 | E64: =A64*D64 -> 3000 | I64: =8000/14 -> 571.42857 | J64: =I64*A64 -> 1142.8571 | K64: =E64-J64 -> 1857.1429
A65: 0.5 | B65: BOLSA | C65: CEBOLLA | D65: 12500 | E65: =A65*D65 -> 6250 | I65: 9500 | J65: =I65*A65 -> 4750 | K65: =E65-J65 -> 1500
A66: 1 | B66: BOLSA | C66: PAPA CEPILLADA | D66: 15000 | E66: =A66*D66 -> 15000 | I66: 12000 | J66: =I66*A66 -> 12000 | K66: =E66-J66 -> 3000
A67: 0.5 | B67: CAJA | C67: BANANA | D67: 35000 | E67: =A67*D67 -> 17500 | I67: 25000 | J67: =I67*A67 -> 12500 | K67: =E67-J67 -> 5000
A68: 4 | B68: KG | C68: CIRUELA | D68: 4000 | E68: =A68*D68 -> 16000 | H68: S/COSTO | I68: 0 | J68: =I68*A68 -> 0 | K68: =E68-J68 -> 16000
A69: 4 | B69: KG | C69: DURAZNO | D69: 4000 | E69: =A69*D69 -> 16000 | H69: S/COSTO | I69: 0 | J69: =I69*A69 -> 0 | K69: =E69-J69 -> 16000
A70: 1 | B70: KG | C70: LIMON | D70: 3200 | E70: =A70*D70 -> 3200 | I70: =38000/15 -> 2533.3333 | J70: =I70*A70 -> 2533.3333 | K70: =E70-J70 -> 666.66667
A71: 1 | B71: KG | C71: NARANJA | D71: 1400 | E71: =A71*D71 -> 1400 | H71: S/COSTO | I71: 0 | J71: =I71*A71 -> 0 | K71: =E71-J71 -> 1400
A72: 2 | B72: UNIDAD | C72: MELON | D72: 5000 | E72: =A72*D72 -> 10000 | H72: S/COSTO | I72: 0 | J72: =I72*A72 -> 0 | K72: =E72-J72 -> 10000
A73: 8.8 | B73: KG | C73: SANDIA | D73: 1000 | E73: =A73*D73 -> 8800 | I73: 700 | J73: =I73*A73 -> 6160 | K73: =E73-J73 -> 2640
A74: 1 | B74: KG | C74: UVA | D74: 4000 | E74: =A74*D74 -> 4000 | H74: S/COSTO | I74: 0 | J74: =I74*A74 -> 0 | K74: =E74-J74 -> 4000
E76: =SUM(E52:E75) -> 165250 | K76: =SUM(K52:K74) -> 88041.429 | L76: =K76/E76 -> 0.53277718
A80: BRASOV | D80: rto: 11 | E80: 46057
A82: CANTIDAD | B82: UNIDAD | C82: PRODUCTO | D82: PRECIO | E82: TOTAL | I82: PRECIO | J82: TOTAL | K82: DIFERENCIA
A83: 1 | B83: CAJON | C83: LEC FRANCESA | D83: 14000 | E83: =A83*D83 -> 14000 | I83: 10000 | J83: =I83*A83 -> 10000 | K83: =E83-J83 -> 4000
A84: 1 | B84: CAJON | C84: LEC MORADA | D84: 10000 | E84: =A84*D84 -> 10000 | I84: 6000 | J84: =I84*A84 -> 6000 | K84: =E84-J84 -> 4000
E86: =SUM(E83:E85) -> 24000 | K86: =SUM(K83:K84) -> 8000 | L86: =K86/E86 -> 0.33333333
A90: MUNCHIS | E90: rto: 3 | F90: 46057 | I90: COMPRA
A92: CANTIDAD | B92: UNIDAD | C92: PRODUCTO | D92: PRECIO | E92: TOTAL | F92: TOTAL + IVA | I92: PRECIO | J92: TOTAL | K92: DIFERENCIA
A93: 2 | B93: KG | C93: BANANA | D93: 3000 | E93: =A93*D93 -> 6000 | F93: =E93*1.105 -> 6630 | H93: S/COSTO | I93: 0 | J93: =I93*A93 -> 0 | K93: =F93-J93 -> 6630
A94: 2 | B94: KG | C94: FRUTILLA | D94: 6500 | E94: =A94*D94 -> 13000 | F94: =E94*1.105 -> 14365 | I94: =25000/5 -> 5000 | J94: =I94*A94 -> 10000 | K94: =F94-J94 -> 4365
A95: 0.5 | B95: KG | C95: LEC CRIOLLA | D95: 3500 | E95: =A95*D95 -> 1750 | F95: =E95*1.105 -> 1933.75 | I95: 3000 | J95: =I95*A95 -> 1500 | K95: =F95-J95 -> 433.75
A96: 0.5 | B96: KG | C96: LEC MORADA | D96: 3500 | E96: =A96*D96 -> 1750 | F96: =E96*1.105 -> 1933.75 | H96: S/COSTO | I96: 0 | J96: =I96*A96 -> 0 | K96: =F96-J96 -> 1933.75
A97: 1 | B97: KG | C97: TOMATE CHERRY | D97: 3500 | E97: =A97*D97 -> 3500 | F97: =E97*1.105 -> 3867.5 | I97: =15000/6 -> 2500 | J97: =I97*A97 -> 2500 | K97: =F97-J97 -> 1367.5
A98: 1 | B98: ATADO | C98: MENTA | D98: 3000 | E98: =A98*D98 -> 3000 | F98: =E98*1.105 -> 3315 | I98: 2000 | J98: =I98*A98 -> 2000 | K98: =F98-J98 -> 1315
E100: =SUM(E93:E98) -> 29000 | F100: =SUM(F93:F98) -> 32045 | K100: =SUM(K93:K98) -> 16045 | L100: =K100/F100 -> 0.50070214
A104: TOTAL DIA | B104: =F100+E86+E76+E45+F26 -> 1598101.5
A106: GANANCIA | B106: =K100+K86+K76+K45+K26 -> 879680.83
A108: Comision Juan | B108: 0
A110: % | B110: =B106/B104 -> 0.55045366
A112: BULTOS COMPRADOS | C112: 100
B117: EFECTIVO | C117: MERCADO PAGO | D117: BANCO GALCIA | E117: BANCO RIO | F117: CHEQUES
B118: 2528350 | C118: 308459.29 | D118: =2277828.28-500000-1000000+491000 -> 1268828.3 | F118: =8500000+1101582.8 -> 9601582.8
A120: INGRESOS
A121: COBR. CTA. CTE | B121: 319800 | C121: 0 | D121: 0 | E121: 0 | F121: 0
A122: RENDIMIENTO MP | B122: 0 | C122: 3625.2 | D122: 0 | E122: 0 | F122: 0
A123: CHE ACREDITADO | B123: 0 | C123: 0 | D123: 1101582.8 | E123: 0 | F123: 0
A124: COBR. VACIOS | B124: 0 | C124: 0 | D124: 0 | E124: 0 | F124: 0
A125: PRESTAMOS | B125: 0 | C125: 0 | D125: 0 | E125: 0 | F125: 0
A126: IMP. CRED. 0,6% | B126: 0 | C126: =C121*0.6%+C124*0.6% -> 0 | D126: =SUM(D121:D123)*0.6% -> 6609.4968 | E126: 0 | F126: 0
A128: TOTAL | B128: =SUM(B118:B126) -> 2848150 | C128: =C118+C121+C124+C125-C126+C122 -> 312084.49 | D128: =D118+D121+D124+D125-D126+D123 -> 2363801.6 | E128: =E118+E121+E124+E125-E126 -> 0 | F128: =F118+F121+F124+F125-F126-D123 -> 8500000
A130: GASTOS
A131: ING. MERCADO | B131: 10000 | C131: 0 | D131: 0 | E131: 0
A132: CARGA / VACIOS | B132: 0 | C132: 0 | D132: 0 | E132: 0
A133: CHEQ DEBITADO | B133: 0 | C133: 0 | D133: 500000 | E133: 0
A134: PEAJE | B134: 0 | C134: 0 | D134: 0 | E134: 0
A135: MERCADERIA | B135: 0 | C135: 395000 | D135: 0 | E135: 0
A136: COMBUSTIBLE | B136: 40000 | C136: 0 | D136: 0 | E136: 0
A137: SUELDOS | B137: 0 | C137: 0 | D137: 0 | E137: 0
...

Sheet 05-02-2026 
A4: LA PIADINA | D4: rto: 16 | E4: 46058
A6: CANTIDAD | B6: UNIDAD | C6: PRODUCTO | D6: PRECIO | E6: TOTAL | I6: PRECIO | J6: TOTAL | K6: DIFERENCIA
A7: 1.5 | B7: CAJON | C7: RUCULA | D7: 10000 | E7: =A7*D7 -> 15000 | I7: 8000 | J7: =I7*A7 -> 12000 | K7: =E7-J7 -> 3000
A8: 1 | B8: KG | C8: LECHUGA | D8: 3500 | E8: =A8*D8 -> 3500 | I8: 3500 | J8: =I8*A8 -> 3500 | K8: =E8-J8 -> 0
A9: 4 | B9: KG | C9: TOMATE | D9: 1500 | E9: =A9*D9 -> 6000 | I9: 1500 | J9: =I9*A9 -> 6000 | K9: =E9-J9 -> 0
A10: 1 | B10: ATADO | C10: ESPINACA | D10: 2000 | E10: =A10*D10 -> 2000 | I10: 2000 | J10: =I10*A10 -> 2000 | K10: =E10-J10 -> 0
A11: 4 | B11: UNIDAD | C11: PALTA | D11: 1300 | E11: =A11*D11 -> 5200 | I11: 1300 | J11: =I11*A11 -> 5200 | K11: =E11-J11 -> 0
E13: =SUM(E7:E11) -> 31700 | K13: =SUM(K7:K11) -> 3000 | L13: =K13/E13 -> 0.094637224
A16: LUSQTOFF | B16: SEDE: IRALA | E16: rto: 3 | F16: 46058 | I16: COMPRA
A18: CANTIDAD | B18: UNIDAD | C18: PRODUCTO | D18: PRECIO | E18: TOTAL | F18: TOTAL + IVA | I18: PRECIO | J18: TOTAL | K18: DIFERENCIA
A19: 1 | B19: BOLSA | C19: CEBOLLA | D19: 13000 | E19: =A19*D19 -> 13000 | F19: =E19*1.105 -> 14365 | I19: 0 | J19: =I19*A19 -> 0 | K19: =F19-J19 -> 14365
A20: 1 | B20: CAJON | C20: LECHUGA | D20: 16000 | E20: =A20*D20 -> 16000 | F20: =E20*1.105 -> 17680 | I20: 0 | J20: =I20*A20 -> 0 | K20: =F20-J20 -> 17680
A21: 2 | B21: KG | C21: ZUCCINI | D21: 1500 | E21: =A21*D21 -> 3000 | F21: =E21*1.105 -> 3315 | I21: 0 | J21: =I21*A21 -> 0 | K21: =F21-J21 -> 3315
A22: 2 | B22: KG | C22: MORRON ROJO | D22: 3500 | E22: =A22*D22 -> 7000 | F22: =E22*1.105 -> 7735 | I22: 0 | J22: =I22*A22 -> 0 | K22: =F22-J22 -> 7735
E24: =SUM(E19:E22) -> 39000 | F24: =SUM(F19:F22) -> 43095 | K24: =SUM(K19:K22) -> 43095 | L24: =K24/F24 -> 1
A26: TOTAL DIA | B26: =F24+E13 -> 74795
A28: GANANCIA | B28: =K24+K13 -> 46095
A30: Comision Juan | B30: 0
A32: % | B32: =B28/B26 -> 0.61628451
A34: BULTOS COMPRADOS | C34: 100
B39: EFECTIVO | C39: MERCADO PAGO | D39: BANCO GALCIA | E39: BANCO RIO | F39: CHEQUES
B40: 2528350 | C40: 308459.29 | D40: =2277828.28-500000-1000000+491000 -> 1268828.3 | F40: =8500000+1101582.8 -> 9601582.8
A42: INGRESOS
A43: COBR. CTA. CTE | B43: 319800 | C43: 0 | D43: 0 | E43: 0 | F43: 0
A44: RENDIMIENTO MP | B44: 0 | C44: 3625.2 | D44: 0 | E44: 0 | F44: 0
A45: CHE ACREDITADO | B45: 0 | C45: 0 | D45: 1101582.8 | E45: 0 | F45: 0
A46: COBR. VACIOS | B46: 0 | C46: 0 | D46: 0 | E46: 0 | F46: 0
A47: PRESTAMOS | B47: 0 | C47: 0 | D47: 0 | E47: 0 | F47: 0
A48: IMP. CRED. 0,6% | B48: 0 | C48: =C43*0.6%+C46*0.6% -> 0 | D48: =SUM(D43:D45)*0.6% -> 6609.4968 | E48: 0 | F48: 0
A50: TOTAL | B50: =SUM(B40:B48) -> 2848150 | C50: =C40+C43+C46+C47-C48+C44 -> 312084.49 | D50: =D40+D43+D46+D47-D48+D45 -> 2363801.6 | E50: =E40+E43+E46+E47-E48 -> 0 | F50: =F40+F43+F46+F47-F48-D45 -> 8500000
A52: GASTOS
A53: ING. MERCADO | B53: 10000 | C53: 0 | D53: 0 | E53: 0
A54: CARGA / VACIOS | B54: 0 | C54: 0 | D54: 0 | E54: 0
A55: CHEQ DEBITADO | B55: 0 | C55: 0 | D55: 500000 | E55: 0
A56: PEAJE | B56: 0 | C56: 0 | D56: 0 | E56: 0
A57: MERCADERIA | B57: 0 | C57: 395000 | D57: 0 | E57: 0
A58: COMBUSTIBLE | B58: 40000 | C58: 0 | D58: 0 | E58: 0
A59: SUELDOS | B59: 0 | C59: 0 | D59: 0 | E59: 0
A60: DEV. PRESTAMOS | B60: 0 | C60: 0 | D60: 0 | E60: 0
A61: AGUA | B61: 0 | C61: 0 | D61: 0 | E61: 0
A62: FLETE JUAN | B62: 0 | C62: 0 | D62: 0 | E62: 0
A63: RETIRO JOAQUIN | B63: 0 | C63: 50000 | D63: 0 | E63: 0
A64: RETIRO FEDERICO | B64: 0 | C64: 50000 | D64: 0 | E64: 0
... A72: MONOTRIB. LEO | B72: 0 | C72: 0 | D72: 0 | E72: 0
A73: IIBB CHEQUE | B73: 0 | C73: 0 | D73: =SUM(D43:D45)*2% -> 22031.656 | E73: 0
A74: IIBB | B74: 0 | C74: 0 | D74: 0 | E74: 0
A75: IVA | B75: 0 | C75: 0 | D75: 0 | E75: 0
A76: GANANCIAS | B76: 0 | C76: 0 | D76: 0 | E76: 0
A77: MANT. CTA. | B77: 0 | C77: 0 | D77: 0 | E77: 0
A79: IMP. DEB. 0,6% | B79: 0 | C79: =SUM(C53:C76)*0.6% -> 2970 | D79: =SUM(D53:D76)*0.6%+(D80*0.6%) -> 5737.1923 | E79: =(E57*0.6%)+(E58*0.6%)+(E59*0.6%)+(E62*0.6%)+(E63*0.6%) -> 0
A80: PASE DE CUENTAS | B80: 0 | C80: =272000+150000 -> 422000 | D80: =272000+150000 -> 422000 | E80: =SUM(E54:E78)*0.6%+(E81*0.6%) -> 0
A82: TOTAL SALIDAS | B82: =SUM(B53:B81) -> 70000 | C82: =SUM(C53:C79) -> 497970 | D82: =SUM(D53:D80) -> 961935.91 | E82: =E64+E68+E79-E80 -> 0 | F82: =F57
A84: SALDOS | B84: =B50-B82 -> 2778150 | C84: =C50-C82+C80 -> 236114.49 | D84: =D50-D82 -> 1401865.7 | E84: =E50-E82 -> 0 | F84: =F50-F82 -> 8500000
A86: fede | B86: 249800
A87: joaquin | B87: 2528350
B89: =SUM(B86:B87) -> 2778150

Sheet 06-02-2026 
A2: COLEGIO SJCB - VIRREY DEL PINO 3299 | E2: rto: 1 | F2: 46059 | I2: COMPRA
A4: CANTIDAD | B4: UNIDAD | C4: PRODUCTO | D4: PRECIO | E4: TOTAL | F4: TOTAL + IVA | I4: PRECIO | J4: TOTAL | K4: DIFERENCIA
A5: 1 | B5: BOLSA | C5: PAPA | D5: 20000 | E5: =A5*D5 -> 20000 | F5: =E5*1.105 -> 22100 | I5: 17500 | J5: =I5*A5 -> 17500 | K5: =F5-J5 -> 4600
A6: 10 | B6: KG | C6: BATATA | D6: 1400 | E6: =A6*D6 -> 14000 | F6: =E6*1.105 -> 15470 | I6: =9000/11 -> 818.18182 | J6: =I6*A6 -> 8181.8182 | K6: =F6-J6 -> 7288.1818
A7: 12 | B7: KG | C7: ANCO | D7: 1000 | E7: =A7*D7 -> 12000 | F7: =E7*1.105 -> 13260 | I7: =8000/13 -> 615.38462 | J7: =I7*A7 -> 7384.6154 | K7: =F7-J7 -> 5875.3846
A8: 4 | B8: KG | C8: CEBOLLA MORADA | D8: 1600 | E8: =A8*D8 -> 6400 | F8: =E8*1.105 -> 7072 | I8: =1000 -> 1000 | J8: =I8*A8 -> 4000 | K8: =F8-J8 -> 3072
A9: 2 | B9: KG | C9: MORRON ROJO | D9: 3500 | E9: =A9*D9 -> 7000 | F9: =E9*1.105 -> 7735 | I9: =25000/8 -> 3125 | J9: =I9*A9 -> 6250 | K9: =F9-J9 -> 1485
A10: 1 | B10: KG | C10: MORRON VERDE | D10: 2300 | E10: =A10*D10 -> 2300 | F10: =E10*1.105 -> 2541.5 | I10: =12000/7 -> 1714.2857 | J10: =I10*A10 -> 1714.2857 | K10: =F10-J10 -> 827.21429
A11: 1 | B11: KG | C11: MORRON AMARILLO | D11: 3000 | E11: =A11*D11 -> 3000 | F11: =E11*1.105 -> 3315 | I11: =20000/8 -> 2500 | J11: =I11*A11 -> 2500 | K11: =F11-J11 -> 815
A12: 10 | B12: KG | C12: ZANAHORIA | D12: 1500 | E12: =A12*D12 -> 15000 | F12: =E12*1.105 -> 16575 | I12: =8000/8 -> 1000 | J12: =I12*A12 -> 10000 | K12: =F12-J12 -> 6575
A13: 1 | B13: KG | C13: BERENJENA | D13: 1600 | E13: =A13*D13 -> 1600 | F13: =E13*1.105 -> 1768 | I13: =1000 -> 1000 | J13: =I13*A13 -> 1000 | K13: =F13-J13 -> 768
A14: 2 | B14: MAPLE | C14: HUEVO | D14: 4500 | E14: =A14*D14 -> 9000 | F14: =E14*1.21 -> 10890 | I14: =52000/12 -> 4333.3333 | J14: =I14*A14 -> 8666.6667 | K14: =F14-J14 -> 2223.3333
A15: 3 | B15: KG | C15: BANANA | D15: 2500 | E15: =A15*D15 -> 7500 | F15: =E15*1.105 -> 8287.5 | I15: =25000/17 -> 1470.5882 | J15: =I15*A15 -> 4411.7647 | K15: =F15-J15 -> 3875.7353
A16: 5 | B16: KG | C16: MANZANA ROJA | D16: 4500 | E16: =A16*D16 -> 22500 | F16: =E16*1.105 -> 24862.5 | I16: =65000/18 -> 3611.1111 | J16: =I16*A16 -> 18055.556 | K16: =F16-J16 -> 6806.9444
A17: 5 | B17: KG | C17: MANZANA VERDE | D17: 3500 | E17: =A17*D17 -> 17500 | F17: =E17*1.105 -> 19337.5 | I17: =40000/18 -> 2222.2222 | J17: =I17*A17 -> 11111.111 | K17: =F17-J17 -> 8226.3889
A18: 8 | B18: KG | C18: NARANJA | D18: 1400 | E18: =A18*D18 -> 11200 | F18: =E18*1.105 -> 12376 | I18: =18000/16 -> 1125 | J18: =I18*A18 -> 9000 | K18: =F18-J18 -> 3376
A19: 0.2 | B19: KG | C19: PEREJIL | D19: 3500 | E19: =A19*D19 -> 700 | F19: =E19*1.105 -> 773.5 | I19: 1500 | J19: =I19*A19 -> 300 | K19: =F19-J19 -> 473.5
A20: 1 | B20: UNIDAD | C20: REPOLLO BLANCO | D20: 1500 | E20: =A20*D20 -> 1500 | F20: =E20*1.105 -> 1657.5 | I20: =13000/12 -> 1083.3333 | J20: =I20*A20 -> 1083.3333 | K20: =F20-J20 -> 574.16667
A21: 1 | B21: UNIDAD | C21: REPOLLO COLORADO | D21: 1500 | E21: =A21*D21 -> 1500 | F21: =E21*1.105 -> 1657.5 | I21: 1083.33 | J21: =I21*A21 -> 1083.33 | K21: =F21-J21 -> 574.17
A22: 5 | B22: KG | C22: TOMATE PERITA | D22: 1800 | E22: =A22*D22 -> 9000 | F22: =E22*1.105 -> 9945 | I22: =20000/15 -> 1333.3333 | J22: =I22*A22 -> 6666.6667 | K22: =F22-J22 -> 3278.3333
A23: 1 | B23: KG | C23: LECHUGA CRIOLLA | D23: 3000 | E23: =A23*D23 -> 3000 | F23: =E23*1.105 -> 3315 | I23: =10000/5 -> 2000 | J23: =I23*A23 -> 2000 | K23: =F23-J23 -> 1315
A24: 12 | B24: ATADOS | C24: RUCULA | D24: 350 | E24: =A24*D24 -> 4200 | F24: =E24*1.105 -> 4641 | I24: =6000/24 -> 250 | J24: =I24*A24 -> 3000 | K24: =F24-J24 -> 1641
E26: =SUM(E5:E24) -> 168900 | F26: =SUM(F5:F24) -> 187579.5 | K26: =SUM(K5:K24) -> 63670.353 | L26: =K26/F26 -> 0.3394313
A28: COLEGIO ST CATHERINES MOORLANDS - CARBAJAL 3250 | E28: rto: 1 | F28: 46059 | I28: COMPRA
A30: CANTIDAD | B30: UNIDAD | C30: PRODUCTO | D30: PRECIO | E30: TOTAL | F30: TOTAL + IVA | I30: PRECIO | J30: TOTAL | K30: DIFERENCIA
A31: 3 | B31: KG | C31: BANANA | D31: 2500 | E31: =A31*D31 -> 7500 | F31: =E31*1.105 -> 8287.5 | I31: =25000/17 -> 1470.5882 | J31: =I31*A31 -> 4411.7647 | K31: =F31-J31 -> 3875.7353
A32: 1 | B32: UNIDAD | C32: AJO | D32: 900 | E32: =A32*D32 -> 900 | F32: =E32*1.105 -> 994.5 | I32: =23000/50 -> 460 | J32: =I32*A32 -> 460 | K32: =F32-J32 -> 534.5
A33: 1 | B33: BOLSA | C33: BATATA | D33: 14000 | E33: =A33*D33 -> 14000 | F33: =E33*1.105 -> 15470 | I33: 9000 | J33: =I33*A33 -> 9000 | K33: =F33-J33 -> 6470
A34: 2 | B34: BOLSA | C34: ANCO | D34: 13000 | E34: =A34*D34 -> 26000 | F34: =E34*1.105 -> 28730 | I34: 8000 | J34: =I34*A34 -> 16000 | K34: =F34-J34 -> 12730
A35: 3 | B35: KG | C35: CEBOLLA | D35: 800 | E35: =A35*D35 -> 2400 | F35: =E35*1.105 -> 2652 | I35: =9500/18 -> 527.77778 | J35: =I35*A35 -> 1583.3333 | K35: =F35-J35 -> 1068.6667
A36: 6 | B36: KG | C36: CEBOLLA MORADA | D36: 1600 | E36: =A36*D36 -> 9600 | F36: =E36*1.105 -> 10608 | I36: 1000 | J36: =I36*A36 -> 6000 | K36: =F36-J36 -> 4608
A37: 1 | B37: ATADO | C37: CILANTRO | D37: 3000 | E37: =A37*D37 -> 3000 | F37: =E37*1.105 -> 3315 | I37: 2000 | J37: =I37*A37 -> 2000 | K37: =F37-J37 -> 1315
A38: 1 | B38: ATADO | C38: CIBOULETTE | D38: 3000 | E38: =A38*D38 -> 3000 | F38: =E38*1.105 -> 3315 | I38: 2000 | J38: =I38*A38 -> 2000 | K38: =F38-J38 -> 1315
A39: 2 | B39: ATADO | C39: CEBOLLA DE VERDEO | D39: 5500 | E39: =A39*D39 -> 11000 | F39: =E39*1.105 -> 12155 | I39: 3200 | J39: =I39*A39 -> 6400 | K39: =F39-J39 -> 5755
A40: 1 | B40: CAJON | C40: MANZANA ROJA | D40: 80000 | E40: =A40*D40 -> 80000 | F40: =E40*1.105 -> 88400 | I40: 65000 | J40: =I40*A40 -> 65000 | K40: =F40-J40 -> 23400
A41: 1 | B41: CAJON | C41: MANZANA VERDE | D41: 58000 | E41: =A41*D41 -> 58000 | F41: =E41*1.105 -> 64090 | I41: 40000 | J41: =I41*A41 -> 40000 | K41: =F41-J41 -> 24090
A42: 1 | B42: CAJON | C42: NARANJA JUGO | D42: 22000 | E42: =A42*D42 -> 22000 | F42: =E42*1.105 -> 24310 | I42: 18000 | J42: =I42*A42 -> 18000 | K42: =F42-J42 -> 6310
A43: 4 | B43: BOLSA | C43: PAPA LAVADA | D43: 20000 | E43: =A43*D43 -> 80000 | F43: =E43*1.105 -> 88400 | I43: 17500 | J43: =I43*A43 -> 70000 | K43: =F43-J43 -> 18400
A44: 0.5 | B44: ATADO | C44: PEREJIL | D44: 3500 | E44: =A44*D44 -> 1750 | F44: =E44*1.105 -> 1933.75 | I44: 1500 | J44: =I44*A44 -> 750 | K44: =F44-J44 -> 1183.75
A45: 5 | B45: KG | C45: MORRON ROJO | D45: 3500 | E45: =A45*D45 -> 17500 | F45: =E45*1.105 -> 19337.5 | I45: =25000/8 -> 3125 | J45: =I45*A45 -> 15625 | K45: =F45-J45 -> 3712.5
A46: 5 | B46: KG | C46: MORRON VERDE | D46: 2300 | E46: =A46*D46 -> 11500 | F46: =E46*1.105 -> 12707.5 | I46: =12000/7 -> 1714.2857 | J46: =I46*A46 -> 8571.4286 | K46: =F46-J46 -> 4136.0714
A47: 3 | B47: KG | C47: MORRON AMARILLO | D47: 3000 | E47: =A47*D47 -> 9000 | F47: =E47*1.105 -> 9945 | I47: =20000/8 -> 2500 | J47: =I47*A47 -> 7500 | K47: =F47-J47 -> 2445
A48: 3 | B48: UNIDAD | C48: REPOLLO BLANCO | D48: 1500 | E48: =A48*D48 -> 4500 | F48: =E48*1.105 -> 4972.5 | I48: =13000/12 -> 1083.3333 | J48: =I48*A48 -> 3250 | K48: =F48-J48 -> 1722.5
A49: 2 | B49: UNIDAD | C49: REPOLLO COLORADO | D49: 1500 | E49: =A49*D49 -> 3000 | F49: =E49*1.105 -> 3315 | I49: 1083.33 | J49: =I49*A49 -> 2166.66 | K49: =F49-J49 -> 1148.34
A50: 8 | B50: KG | C50: TOMATE PERITA | D50: 1800 | E50: =A50*D50 -> 14400 | F50: =E50*1.105 -> 15912 | I50: =20000/15 -> 1333.3333 | J50: =I50*A50 -> 10666.667 | K50: =F50-J50 -> 5245.3333
A51: 1 | B51: BOLSA | C51: ZANAHORIA | D51: 12000 | E51: =A51*D51 -> 12000 | F51: =E51*1.105 -> 13260 | I51: 8000 | J51: =I51*A51 -> 8000 | K51: =F51-J51 -> 5260
A52: 2 | B52: KG | C52: PERA | D52: 2500 | E52: =A52*D52 -> 5000 | F52: =E52*1.105 -> 5525 | I52: =30000/18 -> 1666.6667 | J52: =I52*A52 -> 3333.3333 | K52: =F52-J52 -> 2191.6667
A53: 0.6 | B53: KG | C53: BERENJENA | D53: 1600 | E53: =A53*D53 -> 960 | F53: =E53*1.105 -> 1060.8 | I53: 1000 | J53: =I53*A53 -> 600 | K53: =F53-J53 -> 460.8
A54: 1 | B54: KG | C54: ZUCCINI | D54: 1500 | E54: =A54*D54 -> 1500 | F54: =E54*1.105 -> 1657.5 | I54: =8000/15 -> 533.33333 | J54: =I54*A54 -> 533.33333 | K54: =F54-J54 -> 1124.1667
A55: 3 | B55: KG | C55: LECHUGA CRIOLLA | D55: 3000 | E55: =A55*D55 -> 9000 | F55: =E55*1.105 -> 9945 | I55: =10000/5 -> 2000 | J55: =I55*A55 -> 6000 | K55: =F55-J55 -> 3945
A56: 16 | B56: ATADO | C56: RUCULA | D56: 350 | E56: =A56*D56 -> 5600 | F56: =E56*1.105 -> 6188 | I56: =6000/24 -> 250 | J56: =I56*A56 -> 4000 | K56: =F56-J56 -> 2188
A57: 0.5 | B57: CAJON | C57: HUEVO | D57: 52000 | E57: =A57*D57 -> 26000 | F57: =E57*1.21 -> 31460 | I57: 52000 | J57: =I57*A57 -> 26000 | K57: =F57-J57 -> 5460
E59: =SUM(E31:E57) -> 439110 | F59: =SUM(F31:F57) -> 487946.55 | K59: =SUM(K31:K57) -> 150095.03 | L59: =K59/F59 -> 0.30760547
A61: COLEGIO VILLA DEVOTO SCHOOL - PEDRO MORAN 4441 | E61: rto: 1 | F61: 46059 | I61: COMPRA
A63: CANTIDAD | B63: UNIDAD | C63: PRODUCTO | D63: PRECIO | E63: TOTAL | F63: TOTAL + IVA | I63: PRECIO | J63: TOTAL | K63: DIFERENCIA
A64: 3 | B64: BOLSA | C64: PAPA LAVADA | D64: 20000 | E64: =A64*D64 -> 60000 | F64: =E64*1.105 -> 66300 | I64: 17500 | J64: =I64*A64 -> 52500 | K64: =F64-J64 -> 13800
A65: 1 | B65: BOLSA | C65: ANCO | D65: 13000 | E65: =A65*D65 -> 13000 | F65: =E65*1.105 -> 14365 | I65: 8000 | J65: =I65*A65 -> 8000 | K65: =F65-J65 -> 6365
A66: 2 | B66: KG | C66: CEBOLLA MORADA | D66: 1600 | E66: =A66*D66 -> 3200 | F66: =E66*1.105 -> 3536 | I66: 1000 | J66: =I66*A66 -> 2000 | K66: =F66-J66 -> 1536
A67: 2 | B67: KG | C67: CEBOLLA BLANCA | D67: 800 | E67: =A67*D67 -> 1600 | F67: =E67*1.105 -> 1768 | I67: =9500/18 -> 527.77778 | J67: =I67*A67 -> 1055.5556 | K67: =F67-J67 -> 712.44444
A68: 2 | B68: KG | C68: MORRON ROJO | D68: 3500 | E68: =A68*D68 -> 7000 | F68: =E68*1.105 -> 7735 | I68: =25000/8 -> 3125 | J68: =I68*A68 -> 6250 | K68: =F68-J68 -> 1485
A69: 2 | B69: KG | C69: MORRON AMARILLO | D69: 3000 | E69: =A69*D69 -> 6000 | F69: =E69*1.105 -> 6630 | I69: =20000/8 -> 2500 | J69: =I69*A69 -> 5000 | K69: =F69-J69 -> 1630
A70: 2 | B70: KG | C70: MORRON VERDE | D70: 2300 | E70: =A70*D70 -> 4600 | F70: =E70*1.105 -> 5083 | I70: =12000/7 -> 1714.2857 | J70: =I70*A70 -> 3428.5714 | K70: =F70-J70 -> 1654.4286
A71: 1 | B71: UNIDAD | C71: AJO | D71: 900 | E71: =A71*D71 -> 900 | F71: =E71*1.105 -> 994.5 | I71: =23000/50 -> 460 | J71: =I71*A71 -> 460 | K71: =F71-J71 -> 534.5
A72: 2 | B72: KG | C72: ZUCCINI | D72: 1500 | E72: =A72*D72 -> 3000 | F72: =E72*1.105 -> 3315 | I72: =8000/14 -> 571.42857 | J72: =I72*A72 -> 1142.8571 | K72: =F72-J72 -> 2172.1429
A73: 2 | B73: KG | C73: BERENJENA | D73: 1600 | E73: =A73*D73 -> 3200 | F73: =E73*1.105 -> 3536 | I73: 1000 | J73: =I73*A73 -> 2000 | K73: =F73-J73 -> 1536
A74: 1 | B74: BOLSA | C74: ZANAHORIA | D74: 12000 | E74: =A74*D74 -> 12000 | F74: =E74*1.105 -> 13260 | I74: 9000 | J74: =I74*A74 -> 9000 | K74: =F74-J74 -> 4260
A75: 1 | B75: KG | C75: LECHUGA CRIOLLA | D75: 3000 | E75: =A75*D75 -> 3000 | F75: =E75*1.105 -> 3315 | I75: 2000 | J75: =I75*A75 -> 2000 | K75: =F75-J75 -> 1315
A76: 7 | B76: KG | C76: TOMATE PERITA | D76: 1800 | E76: =A76*D76 -> 12600 | F76: =E76*1.105 -> 13923 | I76: =20000/18 -> 1111.1111 | J76: =I76*A76 -> 7777.7778 | K76: =F76-J76 -> 6145.2222
A77: 3 | B77: MAPLE | C77: HUEVO | D77: 4500 | E77: =A77*D77 -> 13500 | F77: =E77*1.21 -> 16335 | I77: =52000/12 -> 4333.3333 | J77: =I77*A77 -> 13000 | K77: =F77-J77 -> 3335
A78: 0.5 | B78: ATADO | C78: PEREJIL | D78: 3500 | E78: =A78*D78 -> 1750 | F78: =E78*1.105 -> 1933.75 | I78: 1500 | J78: =I78*A78 -> 750 | K78: =F78-J78 -> 1183.75
A79: 1 | B79: ATADO | C79: CILANTRO | D79: 3000 | E79: =A79*D79 -> 3000 | F79: =E79*1.105 -> 3315 | I79: 2000 | J79: =I79*A79 -> 2000 | K79: =F79-J79 -> 1315
A80: 12 | B80: ATADO | C80: RUCULA | D80: 350 | E80: =A80*D80 -> 4200 | F80: =E80*1.105 -> 4641 | I80: =6000/24 -> 250 | J80: =I80*A80 -> 3000 | K80: =F80-J80 -> 1641
A81: 1 | B81: KG | C81: REMOLACHA | D81: 1600 | E81: =A81*D81 -> 1600 | F81: =E81*1.105 -> 1768 | I81: 1500 | J81: =I81*A81 -> 1500 | K81: =F81-J81 -> 268
A82: 1 | B82: UNIDAD | C82: REPOLLO BLANCO | D82: 1500 | E82: =A82*D82 -> 1500 | F82: =E82*1.105 -> 1657.5 | I82: =13000/12 -> 1083.3333 | J82: =I82*A82 -> 1083.3333 | K82: =F82-J82 -> 574.16667
A83: 1 | B83: UNIDAD | C83: REPOLLO MORADO | D83: 1500 | E83: =A83*D83 -> 1500 | F83: =E83*1.105 -> 1657.5 | I83: 1083.33 | J83: =I83*A83 -> 1083.33 | K83: =F83-J83 -> 574.17
A84: 3 | B84: KG | C84: BANANA | D84: 2500 | E84: =A84*D84 -> 7500 | F84: =E84*1.105 -> 8287.5 | I84: =25000/18 -> 1388.8889 | J84: =I84*A84 -> 4166.6667 | K84: =F84-J84 -> 4120.8333
A85: 8 | B85: KG | C85: MANZANA VERDE | D85: 3500 | E85: =A85*D85 -> 28000 | F85: =E85*1.105 -> 30940 | I85: =40000/18 -> 2222.2222 | J85: =I85*A85 -> 17777.778 | K85: =F85-J85 -> 13162.222
A86: 8 | B86: KG | C86: MANZANA ROJA | D86: 4500 | E86: =A86*D86 -> 36000 | F86: =E86*1.105 -> 39780 | I86: =65000/18 -> 3611.1111 | J86: =I86*A86 -> 28888.889 | K86: =F86-J86 -> 10891.111
A87: 5 | B87: KG | C87: NARANJA | D87: 1400 | E87: =A87*D87 -> 7000 | F87: =E87*1.105 -> 7735 | I87: =18000/16 -> 1125 | J87: =I87*A87 -> 5625 | K87: =F87-J87 -> 2110
E89: =SUM(E64:E87) -> 235650 | F89: =SUM(F64:F87) -> 261810.75 | K89: =SUM(K64:K87) -> 82320.991 | L89: =K89/F89 -> 0.31442938
A92: COLCAR | E92: rto: 3 | F92: 46059 | I92: COMPRA
A94: CANTIDAD | B94: UNIDAD | C94: PRODUCTO | D94: PRECIO | E94: TOTAL | F94: TOTAL + IVA | I94: PRECIO | J94: TOTAL | K94: DIFERENCIA
A95: 2 | B95: BOLSA | C95: ZANAHORIA | D95: 12000 | E95: =A95*D95 -> 24000 | F95: =E95*1.105 -> 26520 | I95: 9000 | J95: =I95*A95 -> 18000 | K95: =F95-J95 -> 8520
A96: 2 | B96: BOLSA | C96: ANCO | D96: 13000 | E96: =A96*D96 -> 26000 | F96: =E96*1.105 -> 28730 | I96: 8000 | J96: =I96*A96 -> 16000 | K96: =F96-J96 -> 12730
A97: 1 | B97: CAJON | C97: CHOCLO | D97: 22000 | E97: =A97*D97 -> 22000 | F97: =E97*1.105 -> 24310 | I97: 12000 | J97: =I97*A97 -> 12000 | K97: =F97-J97 -> 12310
A98: 10 | B98: BOLSA | C98: PAPA | D98: 14000 | E98: =A98*D98 -> 140000 | F98: =E98*1.105 -> 154700 | I98: 12000 | J98: =I98*A98 -> 120000 | K98: =F98-J98 -> 34700
A99: 1 | B99: BOLSA | C99: CEBOLLA | D99: 13000 | E99: =A99*D99 -> 13000 | F99: =E99*1.105 -> 14365 | I99: 9500 | J99: =I99*A99 -> 9500 | K99: =F99-J99 -> 4865
A100: 1 | B100: CAJON | C100: MORRON ROJO | D100: 32000 | E100: =A100*D100 -> 32000 | F100: =E100*1.105 -> 35360 | I100: 25000 | J100: =I100*A100 -> 25000 | K100: =F100-J100 -> 10360
A101: 1 | B101: CAJON | C101: TOMATE REDONDO | D101: 20000 | E101: =A101*D101 -> 20000 | F101: =E101*1.105 -> 22100 | I101: 15000 | J101: =I101*A101 -> 15000 | K101: =F101-J101 -> 7100
A102: 2 | B102: BOLSA | C102: BATATA | D102: 14000 | E102: =A102*D102 -> 28000 | F102: =E102*1.105 -> 30940 | I102: 9000 | J102: =I102*A102 -> 18000 | K102: =F102-J102 -> 12940
A103: 2 | B103: CAJON | C103: NARANJA JUGO | D103: 22000 | E103: =A103*D103 -> 44000 | F103: =E103*1.105 -> 48620 | I103: =192000/3 -> 64000 | J103: =I103*A103 -> 128000 | K103: =F103-J103 -> -79380
A104: 2 | B104: CAJON | C104: BANANA PARAGUAY | D104: 26000 | E104: =A104*D104 -> 52000 | F104: =E104*1.105 -> 57460 | I104: 18000 | J104: =I104*A104 -> 36000 | K104: =F104-J104 -> 21460
A105: 2 | B105: BOLSA | C105: BROTE DE SOJA | D105: 3000 | E105: =A105*D105 -> 6000 | F105: =E105*1.105 -> 6630 | I105: 2000 | J105: =I105*A105 -> 4000 | K105: =F105-J105 -> 2630
A106: 2 | B106: CAJON | C106: ACELGA | D106: 12000 | E106: =A106*D106 -> 24000 | F106: =E106*1.105 -> 26520 | I106: =72000/8 -> 9000 | J106: =I106*A106 -> 18000 | K106: =F106-J106 -> 8520
E108: =SUM(E95:E106) -> 431000 | F108: =SUM(F95:F106) -> 476255 | K108: =SUM(K95:K106) -> 56755 | L108: =K108/F108 -> 0.11916935
A110: Comisión Juan | B110: 0.04 | E110: =E108*0.04 -> 17240
A113: FV | E113: rto: 225 | F113: 46059 | I113: COMPRA
A115: CANTIDAD | B115: UNIDAD | C115: PRODUCTO | D115: PRECIO | E115: TOTAL | F115: TOTAL + IVA | I115: PRECIO | J115: TOTAL | K115: DIFERENCIA
A116: 1 | B116: CAJA | C116: MANZANA GRANNY | D116: 63000 | E116: =A116*D116 -> 63000 | F116: =E116*1.105 -> 69615 | I116: 40000 | J116: =I116*A116 -> 40000 | K116: =F116-J116 -> 29615
A117: 2 | B117: CAJON | C117: CIRUELA | D117: 35000 | E117: =A117*D117 -> 70000 | F117: =E117*1.105 -> 77350 | I117: 0 | J117: =I117*A117 -> 0 | K117: =F117-J117 -> 77350
...

Sheet 09-02-2026 
A2: LUSQTOFF | B2: SEDE: MORENO | D2: rto: 2 | E2: 46062 | I2: COMPRA
A4: CANTIDAD | B4: UNIDAD | C4: PRODUCTO | D4: PRECIO | E4: TOTAL | F4: TOTAL + IVA | I4: COSTO | J4: TOTAL | K4: DIFERENCIA
A5: 2 | B5: UNIDAD | C5: ESPINACA | D5: 1800 | E5: =A5*D5 -> 3600 | F5: =E5*1.105 -> 3978 | I5: =7200/6 -> 1200 | J5: =I5*A5 -> 2400 | K5: =F5-J5 -> 1578
A6: 2 | B6: BOLSA | C6: PAPA CEPILLADA | D6: 14000 | E6: =A6*D6 -> 28000 | F6: =E6*1.105 -> 30940 | I6: 13000 | J6: =I6*A6 -> 26000 | K6: =F6-J6 -> 4940
A7: 2 | B7: BOLSA | C7: ANCO | D7: 13000 | E7: =A7*D7 -> 26000 | F7: =E7*1.105 -> 28730 | I7: 8000 | J7: =I7*A7 -> 16000 | K7: =F7-J7 -> 12730
A8: 1 | B8: CAJON | C8: ACELGA | D8: 15000 | E8: =A8*D8 -> 15000 | F8: =E8*1.105 -> 16575 | I8: 12000 | J8: =I8*A8 -> 12000 | K8: =F8-J8 -> 4575
A9: 1 | B9: ATADOS | C9: RABANITO | D9: 850 | E9: =A9*D9 -> 850 | F9: =E9*1.105 -> 939.25 | I9: 1600 | J9: =I9*A9 -> 1600 | K9: =F9-J9 -> -660.75
A10: 2 | B10: UNIDAD | C10: REMOLACHA | D10: 1800 | E10: =A10*D10 -> 3600 | F10: =E10*1.105 -> 3978 | I10: 1400 | J10: =I10*A10 -> 2800 | K10: =F10-J10 -> 1178
A11: 0.5 | B11: CAJON | C11: ZAPALLITO REDONDO | D11: 10000 | E11: =A11*D11 -> 5000 | F11: =E11*1.105 -> 5525 | I11: 6000 | J11: =I11*A11 -> 3000 | K11: =F11-J11 -> 2525
A12: 0.5 | B12: CAJON | C12: ZUCCINI | D12: 11000 | E12: =A12*D12 -> 5500 | F12: =E12*1.105 -> 6077.5 | I12: 7000 | J12: =I12*A12 -> 3500 | K12: =F12-J12 -> 2577.5
A13: 3 | B13: KG | C13: BERENJENA | D13: 1500 | E13: =A13*D13 -> 4500 | F13: =E13*1.105 -> 4972.5 | I13: 600 | J13: =I13*A13 -> 1800 | K13: =F13-J13 -> 3172.5
A14: 1 | B14: CAJON | C14: LECHUGA FRANCESA | D14: 14000 | E14: =A14*D14 -> 14000 | F14: =E14*1.105 -> 15470 | I14: 8000 | J14: =I14*A14 -> 8000 | K14: =F14-J14 -> 7470
A15: 0.5 | B15: CAJON | C15: TOMATE REDONDO | D15: 20000 | E15: =A15*D15 -> 10000 | F15: =E15*1.105 -> 11050 | I15: 12000 | J15: =I15*A15 -> 6000 | K15: =F15-J15 -> 5050
A16: 0.5 | B16: BOLSA | C16: ZANAHORIA CUBITO | D16: 12000 | E16: =A16*D16 -> 6000 | F16: =E16*1.105 -> 6630 | I16: 8000 | J16: =I16*A16 -> 4000 | K16: =F16-J16 -> 2630
A17: 1 | B17: BOLSA | C17: CEBOLLA | D17: 13000 | E17: =A17*D17 -> 13000 | F17: =E17*1.105 -> 14365 | I17: 9000 | J17: =I17*A17 -> 9000 | K17: =F17-J17 -> 5365
A18: 3 | B18: KG | C18: MORRÓN ROJO | D18: 3800 | E18: =A18*D18 -> 11400 | F18: =E18*1.105 -> 12597 | I18: =25000/8 -> 3125 | J18: =I18*A18 -> 9375 | K18: =F18-J18 -> 3222
A19: 2.7 | B19: KG | C19: MORRÓN VERDE | D19: 2800 | E19: =A19*D19 -> 7560 | F19: =E19*1.105 -> 8353.8 | I19: =12000/7 -> 1714.2857 | J19: =I19*A19 -> 4628.5714 | K19: =F19-J19 -> 3725.2286
A20: 2 | B20: KG | C20: LIMON | D20: 2700 | E20: =A20*D20 -> 5400 | F20: =E20*1.105 -> 5967 | I20: =28000/18 -> 1555.5556 | J20: =I20*A20 -> 3111.1111 | K20: =F20-J20 -> 2855.8889
A21: 2 | B21: UNIDAD | C21: REPOLLO BLANCO | D21: 1800 | E21: =A21*D21 -> 3600 | F21: =E21*1.105 -> 3978 | I21: 1600 | J21: =I21*A21 -> 3200 | K21: =F21-J21 -> 778
A22: 1 | B22: CAJON | C22: MANZANA ROJA | D22: 58000 | E22: =A22*D22 -> 58000 | F22: =E22*1.105 -> 64090 | I22: 50000 | J22: =I22*A22 -> 50000 | K22: =F22-J22 -> 14090
A23: 1 | B23: CAJON | C23: NARANJA DE JUGO | D23: 22000 | E23: =A23*D23 -> 22000 | F23: =E23*1.105 -> 24310 | I23: 18000 | J23: =I23*A23 -> 18000 | K23: =F23-J23 -> 6310
A24: 0.5 | B24: CAJON | C24: BANANA ECUADOR | D24: 35000 | E24: =A24*D24 -> 17500 | F24: =E24*1.105 -> 19337.5 | I24: 27000 | J24: =I24*A24 -> 13500 | K24: =F24-J24 -> 5837.5
A25: 2 | B25: KG | C25: FRUTILLA | D25: 12000 | E25: =A25*D25 -> 24000 | F25: =E25*1.105 -> 26520 | I25: 10000 | J25: =I25*A25 -> 20000 | K25: =F25-J25 -> 6520
A26: 2 | B26: KG | C26: KIWI | D26: 10500 | E26: =A26*D26 -> 21000 | F26: =E26*1.105 -> 23205 | I26: =60000/8 -> 7500 | J26: =I26*A26 -> 15000 | K26: =F26-J26 -> 8205
A27: 2 | B27: KG | C27: UVA | D27: 4500 | E27: =A27*D27 -> 9000 | F27: =E27*1.105 -> 9945 | I27: 3500 | J27: =I27*A27 -> 7000 | K27: =F27-J27 -> 2945
A28: 7 | B28: UNIDAD | C28: CHOCLO | D28: 800 | E28: =A28*D28 -> 5600 | F28: =E28*1.105 -> 6188 | I28: =4900/7 -> 700 | J28: =I28*A28 -> 4900 | K28: =F28-J28 -> 1288
E30: =SUM(E5:E28) -> 320110 | F30: =SUM(F5:F28) -> 353721.55 | K30: =SUM(K5:K28) -> 108906.87 | L30: =K30/F30 -> 0.3078887
A32: Comisión Juan | B32: 0.04 | E32: =E30*0.04 -> 12804.4
A34: LUSQTOFF | B34: SEDE: IRALA | E34: rto: 4 | F34: 46062 | I34: COMPRA
A36: CANTIDAD | B36: UNIDAD | C36: PRODUCTO | D36: PRECIO | E36: TOTAL | F36: TOTAL + IVA | I36: PRECIO | J36: TOTAL | K36: DIFERENCIA
A37: 1 | B37: BOLSA | C37: CEBOLLA | D37: 13000 | E37: =A37*D37 -> 13000 | F37: =E37*1.105 -> 14365 | I37: 9000 | J37: =I37*A37 -> 9000 | K37: =F37-J37 -> 5365
A38: 4 | B38: KG | C38: MORRON ROJO | D38: 3800 | E38: =A38*D38 -> 15200 | F38: =E38*1.105 -> 16796 | I38: =25000/8 -> 3125 | J38: =I38*A38 -> 12500 | K38: =F38-J38 -> 4296
A39: 4 | B39: KG | C39: MORRON VERDE | D39: 2800 | E39: =A39*D39 -> 11200 | F39: =E39*1.105 -> 12376 | I39: =12000/7 -> 1714.2857 | J39: =I39*A39 -> 6857.1429 | K39: =F39-J39 -> 5518.8571
A40: 3 | B40: ATADO | C40: ESPINACA | D40: 1800 | E40: =A40*D40 -> 5400 | F40: =E40*1.105 -> 5967 | I40: =7200/6 -> 1200 | J40: =I40*A40 -> 3600 | K40: =F40-J40 -> 2367
A41: 1 | B41: CAJON | C41: ZUCCINI | D41: 11000 | E41: =A41*D41 -> 11000 | F41: =E41*1.105 -> 12155 | I41: 7000 | J41: =I41*A41 -> 7000 | K41: =F41-J41 -> 5155
A42: 0.5 | B42: CAJON | C42: BERENJENA | D42: 13000 | E42: =A42*D42 -> 6500 | F42: =E42*1.105 -> 7182.5 | I42: 6000 | J42: =I42*A42 -> 3000 | K42: =F42-J42 -> 4182.5
A43: 1 | B43: BOLSA | C43: ZANAHORIA | D43: 12000 | E43: =A43*D43 -> 12000 | F43: =E43*1.105 -> 13260 | I43: 8000 | J43: =I43*A43 -> 8000 | K43: =F43-J43 -> 5260
A44: 2 | B44: BOLSA | C44: ANCO | D44: 13000 | E44: =A44*D44 -> 26000 | F44: =E44*1.105 -> 28730 | I44: 8000 | J44: =I44*A44 -> 16000 | K44: =F44-J44 -> 12730
A45: 5 | B45: KG | C45: BATATA | D45: 1500 | E45: =A45*D45 -> 7500 | F45: =E45*1.105 -> 8287.5 | I45: 1100 | J45: =I45*A45 -> 5500 | K45: =F45-J45 -> 2787.5
A46: 5 | B46: KG | C46: TOMATE REDONDO | D46: 1500 | E46: =A46*D46 -> 7500 | F46: =E46*1.105 -> 8287.5 | I46: =12000/18 -> 666.66667 | J46: =I46*A46 -> 3333.3333 | K46: =F46-J46 -> 4954.1667
A47: 2 | B47: ATADO | C47: ALBAHACA | D47: 800 | E47: =A47*D47 -> 1600 | F47: =E47*1.105 -> 1768 | I47: =9000/24 -> 375 | J47: =I47*A47 -> 750 | K47: =F47-J47 -> 1018
A48: 10 | B48: UNIDAD | C48: AJO | D48: 900 | E48: =A48*D48 -> 9000 | F48: =E48*1.105 -> 9945 | I48: =23000/50 -> 460 | J48: =I48*A48 -> 4600 | K48: =F48-J48 -> 5345
A49: 1 | B49: BOLSA | C49: PAPA CEPILLADA | D49: 14000 | E49: =A49*D49 -> 14000 | F49: =E49*1.105 -> 15470 | I49: 13000 | J49: =I49*A49 -> 13000 | K49: =F49-J49 -> 2470
A50: 0.5 | B50: CAJON | C50: ZAPALLITO REDONDO | D50: 10000 | E50: =A50*D50 -> 5000 | F50: =E50*1.105 -> 5525 | I50: 6000 | J50: =I50*A50 -> 3000 | K50: =F50-J50 -> 2525
A51: 4 | B51: ATADO | C51: REMOLACHA | D51: 1800 | E51: =A51*D51 -> 7200 | F51: =E51*1.105 -> 7956 | I51: 1400 | J51: =I51*A51 -> 5600 | K51: =F51-J51 -> 2356
A52: 1.5 | B52: CAJON | C52: ACELGA | D52: 15000 | E52: =A52*D52 -> 22500 | F52: =E52*1.105 -> 24862.5 | I52: 12000 | J52: =I52*A52 -> 18000 | K52: =F52-J52 -> 6862.5
A53: 1 | B53: ATADO | C53: CEBOLLA DE VERDEO | D53: 5500 | E53: =A53*D53 -> 5500 | F53: =E53*1.105 -> 6077.5 | I53: 4000 | J53: =I53*A53 -> 4000 | K53: =F53-J53 -> 2077.5
A54: 3 | B54: KG | C54: KIWI | D54: 10500 | E54: =A54*D54 -> 31500 | F54: =E54*1.105 -> 34807.5 | I54: =60000/8 -> 7500 | J54: =I54*A54 -> 22500 | K54: =F54-J54 -> 12307.5
A55: 2 | B55: KG | C55: FRUTILLA | D55: 12000 | E55: =A55*D55 -> 24000 | F55: =E55*1.105 -> 26520 | I55: 10000 | J55: =I55*A55 -> 20000 | K55: =F55-J55 -> 6520
A56: 1 | B56: CAJON | C56: BANANA ECUADOR | D56: 35000 | E56: =A56*D56 -> 35000 | F56: =E56*1.105 -> 38675 | I56: 27000 | J56: =I56*A56 -> 27000 | K56: =F56-J56 -> 11675
A57: 1 | B57: CAJON | C57: MANZANA ROJA | D57: 58000 | E57: =A57*D57 -> 58000 | F57: =E57*1.105 -> 64090 | I57: 50000 | J57: =I57*A57 -> 50000 | K57: =F57-J57 -> 14090
E59: =SUM(E37:E57) -> 328600 | F59: =SUM(F37:F57) -> 363103 | K59: =SUM(K37:K57) -> 119862.52 | L59: =K59/F59 -> 0.33010612
A61: Comisión Juan | B61: 0.04 | E61: =E59*0.04 -> 13144
A64: LUSQTOFF | B64: SEDE: IRALA | C64: EVENTO | E64: rto: 5 | F64: 46062 | I64: COMPRA
A66: CANTIDAD | B66: UNIDAD | C66: PRODUCTO | D66: PRECIO | E66: TOTAL | F66: TOTAL + IVA | I66: PRECIO | J66: TOTAL | K66: DIFERENCIA
A67: 20 | B67: ATADOS | C67: RUCULA | D67: 400 | E67: =A67*D67 -> 8000 | F67: =E67*1.105 -> 8840 | I67: =5000/24 -> 208.33333 | J67: =I67*A67 -> 4166.6667 | K67: =F67-J67 -> 4673.3333
A68: 10 | B68: KG | C68: PAPA CEPILLADA | D68: 1000 | E68: =A68*D68 -> 10000 | F68: =E68*1.105 -> 11050 | I68: =13000/18 -> 722.22222 | J68: =I68*A68 -> 7222.2222 | K68: =F68-J68 -> 3827.7778
A69: 3 | B69: KG | C69: ZANAHORIA | D69: 1400 | E69: =A69*D69 -> 4200 | F69: =E69*1.105 -> 4641 | I69: 900 | J69: =I69*A69 -> 2700 | K69: =F69-J69 -> 1941
A70: 3 | B70: KG | C70: LECHUGA FRANCESA | D70: 3500 | E70: =A70*D70 -> 10500 | F70: =E70*1.105 -> 11602.5 | I70: 1000 | J70: =I70*A70 -> 3000 | K70: =F70-J70 -> 8602.5
A71: 2.5 | B71: KG | C71: TOMATE PERITA | D71: 1800 | E71: =A71*D71 -> 4500 | F71: =E71*1.105 -> 4972.5 | I71: 1000 | J71: =I71*A71 -> 2500 | K71: =F71-J71 -> 2472.5
E73: =SUM(E67:E71) -> 37200 | F73: =SUM(F67:F71) -> 41106 | K73: =SUM(K67:K71) -> 21517.111 | L73: =K73/F73 -> 0.52345427
A75: Comisión Juan | B75: 0.04 | E75: =E73*0.04 -> 1488
A78: COLCAR | E78: rto: 4 | F78: 46062 | I78: COMPRA
A80: CANTIDAD | B80: UNIDAD | C80: PRODUCTO | D80: PRECIO | E80: TOTAL | F80: TOTAL + IVA | I80: PRECIO | J80: TOTAL | K80: DIFERENCIA
A81: 1 | B81: CAJON | C81: TOMATE CHERRY | D81: 22000 | E81: =A81*D81 -> 22000 | F81: =E81*1.105 -> 24310 | I81: 15000 | J81: =I81*A81 -> 15000 | K81: =F81-J81 -> 9310
A82: 6 | B82: ATADOS | C82: ALBAHACA | D82: 800 | E82: =A82*D82 -> 4800 | F82: =E82*1.105 -> 5304 | I82: =9000/24 -> 375 | J82: =I82*A82 -> 2250 | K82: =F82-J82 -> 3054
A83: 1 | B83: CAJON | C83: TOMATE REDONDO | D83: 20000 | E83: =A83*D83 -> 20000 | F83: =E83*1.105 -> 22100 | I83: 12000 | J83: =I83*A83 -> 12000 | K83: =F83-J83 -> 10100
A84: 1 | B84: CAJON | C84: LECHUGA MANTECA | D84: 14000 | E84: =A84*D84 -> 14000 | F84: =E84*1.105 -> 15470 | I84: 10000 | J84: =I84*A84 -> 10000 | K84: =F84-J84 -> 5470
A85: 2 | B85: BOLSA | C85: ZANAHORIA | D85: 12000 | E85: =A85*D85 -> 24000 | F85: =E85*1.105 -> 26520 | I85: 8000 | J85: =I85*A85 -> 16000 | K85: =F85-J85 -> 10520
A86: 6.2 | B86: KG | C86: BERENJENA | D86: 1400 | E86: =A86*D86 -> 8680 | F86: =E86*1.105 -> 9591.4 | I86: 600 | J86: =I86*A86 -> 3720 | K86: =F86-J86 -> 5871.4
A87: 1 | B87: BOLSA | C87: ANCO | D87: 13000 | E87: =A87*D87 -> 13000 | F87: =E87*1.105 -> 14365 | I87: 8000 | J87: =I87*A87 -> 8000 | K87: =F87-J87 -> 6365
A88: 1 | B88: CAJON | C88: HUEVO | D88: 54000 | E88: =A88*D88 -> 54000 | F88: =E88*1.21 -> 65340 | I88: 50000 | J88: =I88*A88 -> 50000 | K88: =F88-J88 -> 15340
E90: =SUM(E81:E88) -> 160480 | F90: =SUM(F81:F88) -> 183000.4 | K90: =SUM(K81:K88) -> 66030.4 | L90: =K90/F90 -> 0.36082107
A92: Comisión Juan | B92: 0.04 | E92: =E90*0.04 -> 6419.2
A94: FV | E94: rto: 226 | F94: 46062 | I94: COMPRA
A96: CANTIDAD | B96: UNIDAD | C96: PRODUCTO | D96: PRECIO | E96: TOTAL | F96: TOTAL + IVA | I96: PRECIO | J96: TOTAL | K96: DIFERENCIA
A97: 2 | B97: CAJON | C97: TOMATE REDONDO | D97: 23000 | E97: =A97*D97 -> 46000 | F97: =E97*1.105 -> 50830 | I97: 12000 | J97: =I97*A97 -> 24000 | K97: =F97-J97 -> 26830
A98: 2 | B98: CAJON | C98: TOMATE CHERRY | D98: 30000 | E98: =A98*D98 -> 60000 | F98: =E98*1.105 -> 66300 | I98: 15000 | J98: =I98*A98 -> 30000 | K98: =F98-J98 -> 36300
A99: 1 | B99: CAJON | C99: HUEVO | D99: 56000 | E99: =A99*D99 -> 56000 | F99: =E99*1.21 -> 67760 | I99: 50000 | J99: =I99*A99 -> 50000 | K99: =F99-J99 -> 17760
A100: 1 | B100: CAJON | C100: MORRON ROJO | D100: 40000 | E100: =A100*D100 -> 40000 | F100: =E100*1.105 -> 44200 | I100: 25000 | J100: =I100*A100 -> 25000 | K100: =F100-J100 -> 19200
A101: 1 | B101: ATADO | C101: PEREJIL | D101: 3000 | E101: =A101*D101 -> 3000 | F101: =E101*1.105 -> 3315 | I101: 2000 | J101: =I101*A101 -> 2000 | K101: =F101-J101 -> 1315
A102: 4 | B102: ATADO | C102: ALBAHACA | D102: 800 | E102: =A102*D102 -> 3200 | F102: =E102*1.105 -> 3536 | I102: =9000/24 -> 375 | J102: =I102*A102 -> 1500 | K102: =F102-J102 -> 2036
A103: 2 | B103: CAJA | C103: BANANA ECUADOR | D103: 35000 | E103: =A103*D103 -> 70000 | F103: =E103*1.105 -> 77350 | G103: BOLSA | J103: =I103*A103 -> 0 | K103: =F103-J103 -> 77350
A104: 2 | B104: CAJON | C104: DURAZNO | D104: 40000 | E104: =A104*D104 -> 80000 | F104: =E104*1.105 -> 88400 | I104: 25000 | J104: =I104*A104 -> 50000 | K104: =F104-J104 -> 38400
A105: 2 | B105: CAJON | C105: PELON | D105: 35000 | E105: =A105*D105 -> 70000 | F105: =E105*1.105 -> 77350 | I105: 24000 | J105: =I105*A105 -> 48000 | K105: =F105-J105 -> 29350
A106: 2 | B106: CAJON | C106: NARANJA JUGO | D106: 22000 | E106: =A106*D106 -> 44000 | F106: =E106*1.105 -> 48620 | I106: 18000 | J106: =I106*A106 -> 36000 | K106: =F106-J106 -> 12620
A107: 2 | B107: CAJON | C107: CIRUELA | D107: 42000 | E107: =A107*D107 -> 84000 | F107: =E107*1.105 -> 92820 | I107: 37000 | J107: =I107*A107 -> 74000 | K107: =F107-J107 -> 18820
A108: 2 | B108: CAJON | C108: MELON | D108: 22000 | E108: =A108*D108 -> 44000 | F108: =E108*1.105 -> 48620 | I108: 17000 | J108: =I108*A108 -> 34000 | K108: =F108-J108 -> 14620
A109: 42 | B109: KG | C109: SANDIA | D109: 1200 | E109: =A109*D109 -> 50400 | F109: =E109*1.105 -> 55692 | I109: 800 | J109: =I109*A109 -> 33600 | K109: =F109-J109 -> 22092
A110: 1 | B110: CAJA | C110: MANZANA GRANNY | D110: 63000 | E110: =A110*D110 -> 63000 | F110: =E110*1.105 -> 69615 | I110: 40000 | J110: =I110*A110 -> 40000 | K110: =F110-J110 -> 29615
A111: 1 | B111: CAJA | C111: MANZANA GRANNY | D111: 63000 | E111: =A111*D111 -> 63000 | F111: =E111*1.105 -> 69615 | G111: BOLSA | I111: 0 | J111: =I111*A111 -> 0 | K111: =F111-J111 -> 69615
A112: 1 | B112: CAJON | C112: CIRUELA | D112: 42000 | E112: =A112*D112 -> 42000 | F112: =E112*1.105 -> 46410 | G112: BOLSA | I112: 0 | J112: =I112*A112 -> 0 | K112: =F112-J112 -> 46410
A113: 1 | B113: CAJON | C113: NARANJA JUGO | D113: 22000 | E113: =A113*D113 -> 22000 | F113: =E113*1.105 -> 24310 | G113: BOLSA PROPIA | I113: 0 | J113: =I113*A113 -> 0 | K113: =F113-J113 -> 24310
A114: 3 | B114: CAJON | C114: DURAZNO | D114: 40000 | E114: =A114*D114 -> 120000 | F114: =E114*1.105 -> 132600 | G114: BOLSA PROPIA | I114: 0 | J114: =I114*A114 -> 0 | K114: =F114-J114 -> 132600
A115: 1 | B115: CAJA | C115: BANANA ECUADOR | D115: 35000 | E115: =A115*D115 -> 35000 | F115: =E115*1.105 -> 38675 | G115: BOLSA PROPIA | I115: 0 | J115: =I115*A115 -> 0 | K115: =F115-J115 -> 38675
A116: 1 | B116: CAJON | C116: MORRON ROJO | D116: 40000 | E116: =A116*D116 -> 40000 | F116: =E116*1.105 -> 44200 | G116: BOLSA | I116: 0 | J116: =I116*A116 -> 0 | K116: =F116-J116 -> 44200
A117: 1 | B117: CAJON | C117: TOMATE CHERRY | D117: 30000 | E117: =A117*D117 -> 30000 | F117: =E117*1.105 -> 33150 | G117: BOLSA | I117: 0 | J117: =I117*A117 -> 0 | K117: =F117-J117 -> 33150
A118: 1 | B118: CAJON | C118: TOMATE REDONDO | D118: 23000 | E118: =A118*D118 -> 23000 | F118: =E118*1.105 -> 25415 | G118: BOLSA | I118: 0 | J118: =I118*A118 -> 0 | K118: =F118-J118 -> 25415
A119: 0.5 | B119: CAJON | C119: HUEVO | D119: 56000 | E119: =A119*D119 -> 28000 | F119: =E119*1.21 -> 33880 | G119: BOLSA | I119: 0 | J119: =I119*A119 -> 0 | K119: =F119-J119 -> 33880
E121: =SUM(E97:E119) -> 1116600 | F121: =SUM(F97:F119) -> 1242663 | K121: =SUM(K97:K119) -> 794563 | L121: =K121/F121 -> 0.63940344
...

Sheet 10-02-2026 
A2: COLEGIO SJCB - VIRREY DEL PINO 3299 | E2: rto: 2 | F2: 46063 | I2: COMPRA
A4: CANTIDAD | B4: UNIDAD | C4: PRODUCTO | D4: PRECIO | E4: TOTAL | F4: TOTAL + IVA | I4: COSTO | J4: TOTAL | K4: DIFERENCIA
A5: 2 | B5: KG | C5: MORRON ROJO | D5: 4000 | E5: =A5*D5 -> 8000 | F5: =E5*1.105 -> 8840 | I5: =25000/7 -> 3571.4286 | J5: =I5*A5 -> 7142.8571 | K5: =F5-J5 -> 1697.1429
A6: 1 | B6: KG | C6: MORRON VERDE | D6: 3100 | E6: =A6*D6 -> 3100 | F6: =E6*1.105 -> 3425.5 | I6: =13000/7 -> 1857.1429 | J6: =I6*A6 -> 1857.1429 | K6: =F6-J6 -> 1568.3571
A7: 1 | B7: KG | C7: MORRON AMARILLO | D7: 4000 | E7: =A7*D7 -> 4000 | F7: =E7*1.105 -> 4420 | I7: =25000/7 -> 3571.4286 | J7: =I7*A7 -> 3571.4286 | K7: =F7-J7 -> 848.57143
A8: 5 | B8: KG | C8: CEBOLLA MORADA | D8: 1600 | E8: =A8*D8 -> 8000 | F8: =E8*1.105 -> 8840 | I8: 1000 | J8: =I8*A8 -> 5000 | K8: =F8-J8 -> 3840
A9: 1 | B9: BOLSA | C9: ZANAHORIA CUBITO | D9: 12000 | E9: =A9*D9 -> 12000 | F9: =E9*1.105 -> 13260 | I9: 9000 | J9: =I9*A9 -> 9000 | K9: =F9-J9 -> 4260
A10: 1 | B10: BOLSA | C10: PAPA LAVADA | D10: 21000 | E10: =A10*D10 -> 21000 | F10: =E10*1.105 -> 23205 | I10: 19000 | J10: =I10*A10 -> 19000 | K10: =F10-J10 -> 4205
A11: 1 | B11: UNIDAD | C11: CIBOULETTE | D11: 3000 | E11: =A11*D11 -> 3000 | F11: =E11*1.105 -> 3315 | I11: 2000 | J11: =I11*A11 -> 2000 | K11: =F11-J11 -> 1315
A12: 0.25 | B12: UNIDAD | C12: APIO | D12: 2500 | E12: =A12*D12 -> 625 | F12: =E12*1.105 -> 690.625 | I12: 2000 | J12: =I12*A12 -> 500 | K12: =F12-J12 -> 190.625
A13: 0.5 | B13: KG | C13: CEBOLLA | D13: 800 | E13: =A13*D13 -> 400 | F13: =E13*1.105 -> 442 | I13: 500 | J13: =I13*A13 -> 250 | K13: =F13-J13 -> 192
A14: 6 | B14: KG | C14: TOMATE PERITA | D14: 1600 | E14: =A14*D14 -> 9600 | F14: =E14*1.105 -> 10608 | I14: 1000 | J14: =I14*A14 -> 6000 | K14: =F14-J14 -> 4608
A15: 18 | B15: ATADOS | C15: RUCULA | D15: 500 | E15: =A15*D15 -> 9000 | F15: =E15*1.105 -> 9945 | I15: 416 | J15: =I15*A15 -> 7488 | K15: =F15-J15 -> 2457
A16: 1.25 | B16: KG | C16: LECHUGA CRIOLLA | D16: 3500 | E16: =A16*D16 -> 4375 | F16: =E16*1.105 -> 4834.375 | I16: 2500 | J16: =I16*A16 -> 3125 | K16: =F16-J16 -> 1709.375
A17: 4 | B17: KG | C17: NARANJA DE JUGO | D17: 1400 | E17: =A17*D17 -> 5600 | F17: =E17*1.105 -> 6188 | I17: 1000 | J17: =I17*A17 -> 4000 | K17: =F17-J17 -> 2188
A18: 4 | B18: KG | C18: MANZANA ROJA ELEGIDA | D18: 4500 | E18: =A18*D18 -> 18000 | F18: =E18*1.105 -> 19890 | I18: =60000/18 -> 3333.3333 | J18: =I18*A18 -> 13333.333 | K18: =F18-J18 -> 6556.6667
A19: 3 | B19: KG | C19: BANANA ECUADOR | D19: 2500 | E19: =A19*D19 -> 7500 | F19: =E19*1.105 -> 8287.5 | I19: =27000/18 -> 1500 | J19: =I19*A19 -> 4500 | K19: =F19-J19 -> 3787.5
A20: 2 | B20: MAPLE | C20: HUEVO N1 | D20: 4500 | E20: =A20*D20 -> 9000 | F20: =E20*1.21 -> 10890 | I20: =50000/12 -> 4166.6667 | J20: =I20*A20 -> 8333.3333 | K20: =F20-J20 -> 2556.6667
A21: 0.5 | B21: ATADOS | C21: CEBOLLA DE VERDEO | D21: 5000 | E21: =A21*D21 -> 2500 | F21: =E21*1.105 -> 2762.5 | I21: 4000 | J21: =I21*A21 -> 2000 | K21: =F21-J21 -> 762.5
A22: 4 | B22: KG | C22: MANDARINA | D22: 1600 | E22: =A22*D22 -> 6400 | F22: =E22*1.105 -> 7072 | I22: =40000/18 -> 2222.2222 | J22: =I22*A22 -> 8888.8889 | K22: =F22-J22 -> -1816.8889
A23: 0.5 | B23: KG | C23: BERENJENA | D23: 1600 | E23: =A23*D23 -> 800 | F23: =E23*1.105 -> 884 | I23: 600 | J23: =I23*A23 -> 300 | K23: =F23-J23 -> 584
E25: =SUM(E5:E23) -> 132900 | F25: =SUM(F5:F23) -> 147799.5 | K25: =SUM(K5:K23) -> 41509.516 | L25: =K25/F25 -> 0.28085018
A28: COLEGIO ST CATHERINES MOORLANDS - CARBAJAL 3250 | E28: rto: 2 | F28: 46063 | I28: COMPRA
A30: CANTIDAD | B30: UNIDAD | C30: PRODUCTO | D30: PRECIO | E30: TOTAL | F30: TOTAL + IVA | I30: PRECIO | J30: TOTAL | K30: DIFERENCIA
A31: 3 | B31: KG | C31: BANANA ECUADOR | D31: 2500 | E31: =A31*D31 -> 7500 | F31: =E31*1.105 -> 8287.5 | I31: 1500 | J31: =I31*A31 -> 4500 | K31: =F31-J31 -> 3787.5
A32: 2 | B32: KG | C32: MANDARINA | D32: 1600 | E32: =A32*D32 -> 3200 | F32: =E32*1.105 -> 3536 | I32: =40000/18 -> 2222.2222 | J32: =I32*A32 -> 4444.4444 | K32: =F32-J32 -> -908.44444
A33: 2 | B33: UNIDAD | C33: AJO | D33: 900 | E33: =A33*D33 -> 1800 | F33: =E33*1.105 -> 1989 | I33: 460 | J33: =I33*A33 -> 920 | K33: =F33-J33 -> 1069
A34: 1 | B34: BOLSA | C34: BATATA | D34: 14000 | E34: =A34*D34 -> 14000 | F34: =E34*1.105 -> 15470 | I34: 10000 | J34: =I34*A34 -> 10000 | K34: =F34-J34 -> 5470
A35: 6 | B35: KG | C35: CEBOLLA | D35: 800 | E35: =A35*D35 -> 4800 | F35: =E35*1.105 -> 5304 | I35: 500 | J35: =I35*A35 -> 3000 | K35: =F35-J35 -> 2304
A36: 6 | B36: KG | C36: CEBOLLA MORADA | D36: 1600 | E36: =A36*D36 -> 9600 | F36: =E36*1.105 -> 10608 | I36: 1000 | J36: =I36*A36 -> 6000 | K36: =F36-J36 -> 4608
A37: 1 | B37: UNIDAD | C37: CILANTRO | D37: 3000 | E37: =A37*D37 -> 3000 | F37: =E37*1.105 -> 3315 | I37: 1000 | J37: =I37*A37 -> 1000 | K37: =F37-J37 -> 2315
A38: 0.5 | B38: ATADO | C38: CEBOLLA DE VERDEO | D38: 5000 | E38: =A38*D38 -> 2500 | F38: =E38*1.105 -> 2762.5 | I38: 4000 | J38: =I38*A38 -> 2000 | K38: =F38-J38 -> 762.5
A39: 1.5 | B39: CAJON | C39: MANZANA ROJA ELEGIDA | D39: 80000 | E39: =A39*D39 -> 120000 | F39: =E39*1.105 -> 132600 | I39: 60000 | J39: =I39*A39 -> 90000 | K39: =F39-J39 -> 42600
A40: 1.5 | B40: CAJON | C40: MANZANA GRANNY | D40: 58000 | E40: =A40*D40 -> 87000 | F40: =E40*1.105 -> 96135 | I40: 45000 | J40: =I40*A40 -> 67500 | K40: =F40-J40 -> 28635
A41: 1 | B41: CAJON | C41: NARANJA JUGO | D41: 22000 | E41: =A41*D41 -> 22000 | F41: =E41*1.105 -> 24310 | I41: 18000 | J41: =I41*A41 -> 18000 | K41: =F41-J41 -> 6310
A42: 4 | B42: BOLSA | C42: PAPA LAVADA | D42: 21000 | E42: =A42*D42 -> 84000 | F42: =E42*1.105 -> 92820 | I42: 19000 | J42: =I42*A42 -> 76000 | K42: =F42-J42 -> 16820
A43: 1 | B43: ATADO | C43: PEREJIL | D43: 3500 | E43: =A43*D43 -> 3500 | F43: =E43*1.105 -> 3867.5 | I43: 2000 | J43: =I43*A43 -> 2000 | K43: =F43-J43 -> 1867.5
A44: 4 | B44: KG | C44: MORRON ROJO | D44: 4000 | E44: =A44*D44 -> 16000 | F44: =E44*1.105 -> 17680 | I44: =25000/7 -> 3571.4286 | J44: =I44*A44 -> 14285.714 | K44: =F44-J44 -> 3394.2857
A45: 3 | B45: KG | C45: MORRON VERDE | D45: 3100 | E45: =A45*D45 -> 9300 | F45: =E45*1.105 -> 10276.5 | I45: =13000/7 -> 1857.1429 | J45: =I45*A45 -> 5571.4286 | K45: =F45-J45 -> 4705.0714
A46: 6 | B46: KG | C46: REPOLLO BLANCO | D46: 1500 | E46: =A46*D46 -> 9000 | F46: =E46*1.105 -> 9945 | I46: 882 | J46: =I46*A46 -> 5292 | K46: =F46-J46 -> 4653
A47: 5 | B47: KG | C47: REPOLLO COLORADO | D47: 1500 | E47: =A47*D47 -> 7500 | F47: =E47*1.105 -> 8287.5 | I47: 882 | J47: =I47*A47 -> 4410 | K47: =F47-J47 -> 3877.5
A48: 18 | B48: KG | C48: TOMATE PERITA | D48: 1600 | E48: =A48*D48 -> 28800 | F48: =E48*1.105 -> 31824 | I48: 1000 | J48: =I48*A48 -> 18000 | K48: =F48-J48 -> 13824
A49: 3 | B49: BOLSA | C49: ZANAHORIA | D49: 12000 | E49: =A49*D49 -> 36000 | F49: =E49*1.105 -> 39780 | I49: 9000 | J49: =I49*A49 -> 27000 | K49: =F49-J49 -> 12780
A50: 1.5 | B50: KG | C50: LECHUGA CRIOLLA | D50: 3500 | E50: =A50*D50 -> 5250 | F50: =E50*1.105 -> 5801.25 | I50: 2500 | J50: =I50*A50 -> 3750 | K50: =F50-J50 -> 2051.25
A51: 35 | B51: ATADO | C51: RUCULA | D51: 500 | E51: =A51*D51 -> 17500 | F51: =E51*1.105 -> 19337.5 | I51: 416 | J51: =I51*A51 -> 14560 | K51: =F51-J51 -> 4777.5
A52: 4 | B52: KG | C52: CHAUCHA REDONDA | D52: 4000 | E52: =A52*D52 -> 16000 | F52: =E52*1.105 -> 17680 | I52: =15000/7 -> 2142.8571 | J52: =I52*A52 -> 8571.4286 | K52: =F52-J52 -> 9108.5714
A53: 0.5 | B53: CAJON | C53: HUEVO N1 | D53: 52000 | E53: =A53*D53 -> 26000 | F53: =E53*1.21 -> 31460 | I53: 50000 | J53: =I53*A53 -> 25000 | K53: =F53-J53 -> 6460
E55: =SUM(E31:E53) -> 534250 | F55: =SUM(F31:F53) -> 593076.25 | K55: =SUM(K31:K53) -> 181271.23 | L55: =K55/F55 -> 0.30564575
A59: COLEGIO VILLA DEVOTO SCHOOL - PEDRO MORAN 4441 | E59: rto: 2 | F59: 46063 | I59: COMPRA
A61: CANTIDAD | B61: UNIDAD | C61: PRODUCTO | D61: PRECIO | E61: TOTAL | F61: TOTAL + IVA | I61: PRECIO | J61: TOTAL | K61: DIFERENCIA
A62: 2 | B62: BOLSA | C62: PAPA LAVADA | D62: 21000 | E62: =A62*D62 -> 42000 | F62: =E62*1.105 -> 46410 | I62: 19000 | J62: =I62*A62 -> 38000 | K62: =F62-J62 -> 8410
A63: 1 | B63: BOLSA | C63: ANCO | D63: 13000 | E63: =A63*D63 -> 13000 | F63: =E63*1.105 -> 14365 | I63: 8000 | J63: =I63*A63 -> 8000 | K63: =F63-J63 -> 6365
A64: 3 | B64: KG | C64: CEBOLLA MORADA | D64: 1600 | E64: =A64*D64 -> 4800 | F64: =E64*1.105 -> 5304 | I64: 1000 | J64: =I64*A64 -> 3000 | K64: =F64-J64 -> 2304
A65: 2 | B65: KG | C65: CEBOLLA | D65: 800 | E65: =A65*D65 -> 1600 | F65: =E65*1.105 -> 1768 | I65: =9000/18 -> 500 | J65: =I65*A65 -> 1000 | K65: =F65-J65 -> 768
A66: 3 | B66: KG | C66: MORRON ROJO | D66: 4000 | E66: =A66*D66 -> 12000 | F66: =E66*1.105 -> 13260 | I66: =25000/7 -> 3571.4286 | J66: =I66*A66 -> 10714.286 | K66: =F66-J66 -> 2545.7143
A67: 3 | B67: KG | C67: MORRON AMARILLO | D67: 4000 | E67: =A67*D67 -> 12000 | F67: =E67*1.105 -> 13260 | I67: =25000/7 -> 3571.4286 | J67: =I67*A67 -> 10714.286 | K67: =F67-J67 -> 2545.7143
A68: 3 | B68: KG | C68: MORRON VERDE | D68: 3100 | E68: =A68*D68 -> 9300 | F68: =E68*1.105 -> 10276.5 | I68: =13000/7 -> 1857.1429 | J68: =I68*A68 -> 5571.4286 | K68: =F68-J68 -> 4705.0714
A69: 1 | B69: UNIDAD | C69: AJO | D69: 900 | E69: =A69*D69 -> 900 | F69: =E69*1.105 -> 994.5 | I69: =23000/50 -> 460 | J69: =I69*A69 -> 460 | K69: =F69-J69 -> 534.5
A70: 2 | B70: KG | C70: ZUCCINI | D70: 1500 | E70: =A70*D70 -> 3000 | F70: =E70*1.105 -> 3315 | I70: =7000/15 -> 466.66667 | J70: =I70*A70 -> 933.33333 | K70: =F70-J70 -> 2381.6667
A71: 2 | B71: BOLSA | C71: ZANAHORIA CUBITO | D71: 12000 | E71: =A71*D71 -> 24000 | F71: =E71*1.105 -> 26520 | I71: 9000 | J71: =I71*A71 -> 18000 | K71: =F71-J71 -> 8520
A72: 2 | B72: UNIDAD | C72: BROCOLI | D72: 2000 | E72: =A72*D72 -> 4000 | F72: =E72*1.105 -> 4420 | I72: 1500 | J72: =I72*A72 -> 3000 | K72: =F72-J72 -> 1420
A73: 2 | B73: KG | C73: LECHUGA CRIOLLA | D73: 3500 | E73: =A73*D73 -> 7000 | F73: =E73*1.105 -> 7735 | I73: 2500 | J73: =I73*A73 -> 5000 | K73: =F73-J73 -> 2735
A74: 10 | B74: KG | C74: TOMATE PERITA | D74: 1600 | E74: =A74*D74 -> 16000 | F74: =E74*1.105 -> 17680 | I74: 1000 | J74: =I74*A74 -> 10000 | K74: =F74-J74 -> 7680
A75: 10 | B75: ATADO | C75: RUCULA | D75: 500 | E75: =A75*D75 -> 5000 | F75: =E75*1.105 -> 5525 | I75: 416 | J75: =I75*A75 -> 4160 | K75: =F75-J75 -> 1365
A76: 2.2 | B76: KG | C76: REPOLLO BLANCO | D76: 1500 | E76: =A76*D76 -> 3300 | F76: =E76*1.105 -> 3646.5 | I76: 882 | J76: =I76*A76 -> 1940.4 | K76: =F76-J76 -> 1706.1
A77: 2.2 | B77: KG | C77: REPOLLO COLORADO | D77: 1500 | E77: =A77*D77 -> 3300 | F77: =E77*1.105 -> 3646.5 | I77: 882 | J77: =I77*A77 -> 1940.4 | K77: =F77-J77 -> 1706.1
A78: 3 | B78: MAPLE | C78: HUEVO N1 | D78: 4500 | E78: =A78*D78 -> 13500 | F78: =E78*1.21 -> 16335 | I78: =50000/12 -> 4166.6667 | J78: =I78*A78 -> 12500 | K78: =F78-J78 -> 3835
A79: 1 | B79: ATADO | C79: CEBOLLA DE VERDEO | D79: 5000 | E79: =A79*D79 -> 5000 | F79: =E79*1.105 -> 5525 | I79: 4000 | J79: =I79*A79 -> 4000 | K79: =F79-J79 -> 1525
A80: 1 | B80: UNIDAD | C80: PUERRO | D80: 6000 | E80: =A80*D80 -> 6000 | F80: =E80*1.105 -> 6630 | I80: 5000 | J80: =I80*A80 -> 5000 | K80: =F80-J80 -> 1630
A81: 5 | B81: KG | C81: BATATA | D81: 1400 | E81: =A81*D81 -> 7000 | F81: =E81*1.105 -> 7735 | I81: 1000 | J81: =I81*A81 -> 5000 | K81: =F81-J81 -> 2735
A82: 10 | B82: KG | C82: NARANJA JUGO | D82: 1400 | E82: =A82*D82 -> 14000 | F82: =E82*1.105 -> 15470 | I82: 1000 | J82: =I82*A82 -> 10000 | K82: =F82-J82 -> 5470
A83: 10 | B83: KG | C83: MANZANA GRANNY | D83: 3500 | E83: =A83*D83 -> 35000 | F83: =E83*1.105 -> 38675 | I83: =45000/18 -> 2500 | J83: =I83*A83 -> 25000 | K83: =F83-J83 -> 13675
A84: 10 | B84: KG | C84: MANZANA ROJA ELEGIDA | D84: 4500 | E84: =A84*D84 -> 45000 | F84: =E84*1.105 -> 49725 | I84: =60000/18 -> 3333.3333 | J84: =I84*A84 -> 33333.333 | K84: =F84-J84 -> 16391.667
A85: 4 | B85: KG | C85: BANANA | D85: 2500 | E85: =A85*D85 -> 10000 | F85: =E85*1.105 -> 11050 | I85: 1500 | J85: =I85*A85 -> 6000 | K85: =F85-J85 -> 5050
E87: =SUM(E62:E85) -> 296700 | F87: =SUM(F62:F85) -> 329271 | K87: =SUM(K62:K85) -> 106003.53 | L87: =K87/F87 -> 0.32193401
A90: FV | E90: rto: 227 | F90: 46063 | I90: COMPRA
A92: CANTIDAD | B92: UNIDAD | C92: PRODUCTO | D92: PRECIO | E92: TOTAL | F92: TOTAL + IVA | I92: PRECIO | J92: TOTAL | K92: DIFERENCIA
A93: 2 | B93: CAJA | C93: MANZANA GRANNY | D93: 63000 | E93: =A93*D93 -> 126000 | F93: =E93*1.105 -> 139230 | I93: 45000 | J93: =I93*A93 -> 90000 | K93: =F93-J93 -> 49230
A94: 2 | B94: CAJON | C94: CIRUELA | D94: 42000 | E94: =A94*D94 -> 84000 | F94: =E94*1.105 -> 92820 | I94: 37000 | J94: =I94*A94 -> 74000 | K94: =F94-J94 -> 18820
A95: 2 | B95: CAJON | C95: DURAZNO | D95: 40000 | E95: =A95*D95 -> 80000 | F95: =E95*1.105 -> 88400 | I95: 28000 | J95: =I95*A95 -> 56000 | K95: =F95-J95 -> 32400
A96: 2 | B96: CAJON | C96: PELON | D96: 35000 | E96: =A96*D96 -> 70000 | F96: =E96*1.105 -> 77350 | I96: 30000 | J96: =I96*A96 -> 60000 | K96: =F96-J96 -> 17350
A97: 2 | B97: CAJA | C97: BANANA ECUADOR | D97: 35000 | E97: =A97*D97 -> 70000 | F97: =E97*1.105 -> 77350 | I97: 27000 | J97: =I97*A97 -> 54000 | K97: =F97-J97 -> 23350
A98: 2 | B98: CAJON | C98: TOMATE REDONDO | D98: 23000 | E98: =A98*D98 -> 46000 | F98: =E98*1.105 -> 50830 | I98: 12000 | J98: =I98*A98 -> 24000 | K98: =F98-J98 -> 26830
A99: 0.5 | B99: CAJON | C99: HUEVO | D99: 56000 | E99: =A99*D99 -> 28000 | F99: =E99*1.21 -> 33880 | I99: 50000 | J99: =I99*A99 -> 25000 | K99: =F99-J99 -> 8880
A100: 1 | B100: CAJON | C100: BERENJENA | D100: 16000 | E100: =A100*D100 -> 16000 | F100: =E100*1.105 -> 17680 | I100: 6000 | J100: =I100*A100 -> 6000 | K100: =F100-J100 -> 11680
A101: 1 | B101: CAJON | C101: TOMATE CHERRY | D101: 30000 | E101: =A101*D101 -> 30000 | F101: =E101*1.105 -> 33150 | I101: 12000 | J101: =I101*A101 -> 12000 | K101: =F101-J101 -> 21150
A102: 1 | B102: CAJON | C102: NARANJA JUGO | D102: 22000 | E102: =A102*D102 -> 22000 | F102: =E102*1.105 -> 24310 | I102: 18000 | J102: =I102*A102 -> 18000 | K102: =F102-J102 -> 6310
A103: 1 | B103: CAJON | C103: NARANJA JUGO | D103: 22000 | E103: =A103*D103 -> 22000 | F103: =E103*1.105 -> 24310 | G103: BOLSA | I103: 0 | J103: =I103*A103 -> 0 | K103: =F103-J103 -> 24310
A104: 1 | B104: CAJON | C104: TOMATE CHERRY | D104: 30000 | E104: =A104*D104 -> 30000 | F104: =E104*1.105 -> 33150 | G104: BOLSA | I104: 0 | J104: =I104*A104 -> 0 | K104: =F104-J104 -> 33150
A105: 0.5 | B105: CAJON | C105: HUEVO | D105: 56000 | E105: =A105*D105 -> 28000 | F105: =E105*1.21 -> 33880 | G105: BOLSA | I105: 0 | J105: =I105*A105 -> 0 | K105: =F105-J105 -> 33880
A106: 1 | B106: CAJON | C106: TOMATE REDONDO | D106: 23000 | E106: =A106*D106 -> 23000 | F106: =E106*1.105 -> 25415 | G106: BOLSA | I106: 0 | J106: =I106*A106 -> 0 | K106: =F106-J106 -> 25415
A107: 1 | B107: CAJA | C107: BANANA ECUADOR | D107: 35000 | E107: =A107*D107 -> 35000 | F107: =E107*1.105 -> 38675 | G107: BOLSA | I107: 0 | J107: =I107*A107 -> 0 | K107: =F107-J107 -> 38675
A108: 1 | B108: CAJA | C108: MANZANA GRANNY | D108: 63000 | E108: =A108*D108 -> 63000 | F108: =E108*1.105 -> 69615 | G108: BOLSA | I108: 0 | J108: =I108*A108 -> 0 | K108: =F108-J108 -> 69615
A109: 3 | B109: CAJON | C109: DURAZNO | D109: 40000 | E109: =A109*D109 -> 120000 | F109: =E109*1.105 -> 132600 | G109: BOLSA PROPIA | I109: 0 | J109: =I109*A109 -> 0 | K109: =F109-J109 -> 132600
A110: 1 | B110: CAJON | C110: PELON | D110: 35000 | E110: =A110*D110 -> 35000 | F110: =E110*1.105 -> 38675 | G110: BOLSA PROPIA | I110: 0 | J110: =I110*A110 -> 0 | K110: =F110-J110 -> 38675
E112: =SUM(E93:E110) -> 928000 | F112: =SUM(F93:F110) -> 1031320 | K112: =SUM(K93:K110) -> 612320 | L112: =K112/F112 -> 0.59372455
A116: HAVANNA | B116: MORENO | D116: rto: 4 | E116: 46063
A118: CANTIDAD | B118: UNIDAD | C118: PRODUCTO | D118: PRECIO | E118: TOTAL | I118: PRECIO | J118: TOTAL | K118: DIFERENCIA
A119: 2 | B119: CAJON | C119: NARANJA JUGO COMERCIAL | D119: 17000 | E119: =A119*D119 -> 34000 | I119: =(11000+14000)/2 -> 12500 | J119: =I119*A119 -> 25000 | K119: =E119-J119 -> 9000
E121: =SUM(E119) -> 34000 | K121: =SUM(K119) -> 9000 | L121: =K121/E121 -> 0.26470588
...

Sheet 11-02-2026 
A2: FV | E2: rto: 228 | F2: 46064 | I2: COMPRA
A4: CANTIDAD | B4: UNIDAD | C4: PRODUCTO | D4: PRECIO | E4: TOTAL | F4: TOTAL + IVA | I4: PRECIO | J4: TOTAL | K4: DIFERENCIA
A5: 0.5 | B5: CAJON | C5: HUEVO | D5: 56000 | E5: =A5*D5 -> 28000 | F5: =E5*1.21 -> 33880 | I5: 50000 | J5: =I5*A5 -> 25000 | K5: =F5-J5 -> 8880
A6: 2 | B6: CAJON | C6: DURAZNO | D6: 40000 | E6: =A6*D6 -> 80000 | F6: =E6*1.105 -> 88400 | I6: 27000 | J6: =I6*A6 -> 54000 | K6: =F6-J6 -> 34400
A7: 2 | B7: CAJON | C7: CIRUELA | D7: 42000 | E7: =A7*D7 -> 84000 | F7: =E7*1.105 -> 92820 | I7: 26000 | J7: =I7*A7 -> 52000 | K7: =F7-J7 -> 40820
A8: 2 | B8: CAJON | C8: BANANA ECUADOR | D8: 35000 | E8: =A8*D8 -> 70000 | F8: =E8*1.105 -> 77350 | I8: 28000 | J8: =I8*A8 -> 56000 | K8: =F8-J8 -> 21350
A9: 2 | B9: CAJON | C9: NARANJA JUGO | D9: 22000 | E9: =A9*D9 -> 44000 | F9: =E9*1.105 -> 48620 | I9: 19000 | J9: =I9*A9 -> 38000 | K9: =F9-J9 -> 10620
A10: 2 | B10: CAJON | C10: MANZANA GRANNY | D10: 63000 | E10: =A10*D10 -> 126000 | F10: =E10*1.105 -> 139230 | I10: 21000 | J10: =I10*A10 -> 42000 | K10: =F10-J10 -> 97230
A11: 2 | B11: CAJON | C11: PELON | D11: 35000 | E11: =A11*D11 -> 70000 | F11: =E11*1.105 -> 77350 | I11: 25000 | J11: =I11*A11 -> 50000 | K11: =F11-J11 -> 27350
A12: 2 | B12: CAJON | C12: TOMATE REDONDO | D12: 23000 | E12: =A12*D12 -> 46000 | F12: =E12*1.105 -> 50830 | I12: 13000 | J12: =I12*A12 -> 26000 | K12: =F12-J12 -> 24830
A13: 2 | B13: CAJON | C13: TOMATE CHERRY | D13: 30000 | E13: =A13*D13 -> 60000 | F13: =E13*1.105 -> 66300 | I13: 15000 | J13: =I13*A13 -> 30000 | K13: =F13-J13 -> 36300
A14: 1 | B14: CAJON | C14: TOMATE CHERRY | D14: 30000 | E14: =A14*D14 -> 30000 | F14: =E14*1.105 -> 33150 | G14: BOLSA | I14: 0 | J14: =I14*A14 -> 0 | K14: =F14-J14 -> 33150
A15: 1 | B15: CAJON | C15: TOMATE REDONDO | D15: 23000 | E15: =A15*D15 -> 23000 | F15: =E15*1.105 -> 25415 | G15: BOLSA | I15: 0 | J15: =I15*A15 -> 0 | K15: =F15-J15 -> 25415
A16: 1 | B16: CAJON | C16: MANZANA GRANNY | D16: 63000 | E16: =A16*D16 -> 63000 | F16: =E16*1.105 -> 69615 | G16: BOLSA PROPIA | I16: 0 | J16: =I16*A16 -> 0 | K16: =F16-J16 -> 69615
A17: 1 | B17: CAJON | C17: BANANA ECUADOR | D17: 35000 | E17: =A17*D17 -> 35000 | F17: =E17*1.105 -> 38675 | G17: BOLSA | I17: 0 | J17: =I17*A17 -> 0 | K17: =F17-J17 -> 38675
A18: 1 | B18: CAJON | C18: CIRUELA | D18: 42000 | E18: =A18*D18 -> 42000 | F18: =E18*1.105 -> 46410 | G18: BOLSA | I18: 0 | J18: =I18*A18 -> 0 | K18: =F18-J18 -> 46410
A19: 1 | B19: CAJA | C19: DURAZNO | D19: 40000 | E19: =A19*D19 -> 40000 | F19: =E19*1.105 -> 44200 | G19: BOLSA | I19: 0 | J19: =I19*A19 -> 0 | K19: =F19-J19 -> 44200
A20: 0.5 | B20: CAJA | C20: HUEVO | D20: 56000 | E20: =A20*D20 -> 28000 | F20: =E20*1.21 -> 33880 | G20: BOLSA | J20: =I20*A20 -> 0 | K20: =F20-J20 -> 33880
E22: =SUM(E5:E20) -> 869000 | F22: =SUM(F5:F20) -> 966125 | K22: =SUM(K5:K20) -> 593125 | L22: =K22/F22 -> 0.61392159
A27: HOGAR CARDALES | D27: rto: 6 | E27: 46064
A29: CANTIDAD | B29: UNIDAD | C29: PRODUCTO | D29: PRECIO | E29: TOTAL | I29: PRECIO | J29: TOTAL | K29: DIFERENCIA
A30: 2 | B30: UNIDAD | C30: AJO | D30: 1200 | E30: =A30*D30 -> 2400 | I30: 460 | J30: =I30*A30 -> 920 | K30: =E30-J30 -> 1480
A31: 4 | B31: KG | C31: BONIATO | D31: 3200 | E31: =A31*D31 -> 12800 | I31: 2000 | J31: =I31*A31 -> 8000 | K31: =E31-J31 -> 4800
A32: 3 | B32: KG | C32: BERENJENA | D32: 1800 | E32: =A32*D32 -> 5400 | I32: 1500 | J32: =I32*A32 -> 4500 | K32: =E32-J32 -> 900
A33: 2 | B33: UNIDAD | C33: BROCOLI | D33: 2000 | E33: =A33*D33 -> 4000 | H33: S/C | I33: 0 | J33: =I33*A33 -> 0 | K33: =E33-J33 -> 4000
A34: 1 | B34: KG | C34: CHAUCHA | D34: 4500 | E34: =A34*D34 -> 4500 | I34: =15000/7 -> 2142.8571 | J34: =I34*A34 -> 2142.8571 | K34: =E34-J34 -> 2357.1429
A35: 2 | B35: KG | C35: TOMATE CHERRY | D35: 2800 | E35: =A35*D35 -> 5600 | I35: 1500 | J35: =I35*A35 -> 3000 | K35: =E35-J35 -> 2600
A36: 6 | B36: KG | C36: ESPINACA | D36: 1400 | E36: =A36*D36 -> 8400 | I36: =8000/12 -> 666.66667 | J36: =I36*A36 -> 4000 | K36: =E36-J36 -> 4400
A37: 3 | B37: ATADO | C37: MORRON ROJO | D37: 4500 | E37: =A37*D37 -> 13500 | I37: =25000/7 -> 3571.4286 | J37: =I37*A37 -> 10714.286 | K37: =E37-J37 -> 2785.7143
A38: 3 | B38: KG | C38: LECHUGA FRANCESA | D38: 3000 | E38: =A38*D38 -> 9000 | H38: S/C | I38: 0 | J38: =I38*A38 -> 0 | K38: =E38-J38 -> 9000
A39: 6 | B39: ATADO | C39: REMOLACHA | D39: 2200 | E39: =A39*D39 -> 13200 | I39: 1500 | J39: =I39*A39 -> 9000 | K39: =E39-J39 -> 4200
A40: 1.65 | B40: KG | C40: REPOLLO | D40: 1800 | E40: =A40*D40 -> 2970 | I40: 882 | J40: =I40*A40 -> 1455.3 | K40: =E40-J40 -> 1514.7
A41: 3 | B41: ATADO | C41: RUCULA | D41: 500 | E41: =A41*D41 -> 1500 | I41: 500 | J41: =I41*A41 -> 1500 | K41: =E41-J41 -> 0
A42: 6 | B42: KG | C42: TOMATE REDONDO | D42: 1700 | E42: =A42*D42 -> 10200 | I42: =13000/18 -> 722.22222 | J42: =I42*A42 -> 4333.3333 | K42: =E42-J42 -> 5866.6667
A43: 3 | B43: KG | C43: ZAPALLITO REDONDO | D43: 1500 | E43: =A43*D43 -> 4500 | I43: 1000 | J43: =I43*A43 -> 3000 | K43: =E43-J43 -> 1500
A44: 2 | B44: KG | C44: ZUCCINI | D44: 1500 | E44: =A44*D44 -> 3000 | I44: =8000/16 -> 500 | J44: =I44*A44 -> 1000 | K44: =E44-J44 -> 2000
A45: 1 | B45: BOLSA | C45: CABUTIA | D45: 12000 | E45: =A45*D45 -> 12000 | I45: 9000 | J45: =I45*A45 -> 9000 | K45: =E45-J45 -> 3000
A46: 0.5 | B46: BOLSA | C46: CEBOLLA | D46: 12500 | E46: =A46*D46 -> 6250 | I46: 9000 | J46: =I46*A46 -> 4500 | K46: =E46-J46 -> 1750
A47: 1 | B47: BOLSA | C47: PAPA | D47: 16000 | E47: =A47*D47 -> 16000 | I47: 13000 | J47: =I47*A47 -> 13000 | K47: =E47-J47 -> 3000
A48: 1 | B48: BOLSA | C48: ZANAHORIA | D48: 12000 | E48: =A48*D48 -> 12000 | I48: 9000 | J48: =I48*A48 -> 9000 | K48: =E48-J48 -> 3000
A49: 1 | B49: CAJON | C49: HUEVO | D49: 56000 | E49: =A49*D49 -> 56000 | I49: 50000 | J49: =I49*A49 -> 50000 | K49: =E49-J49 -> 6000
A50: 1 | B50: CAJA | C50: BANANA | D50: 35000 | E50: =A50*D50 -> 35000 | I50: 27000 | J50: =I50*A50 -> 27000 | K50: =E50-J50 -> 8000
A51: 1 | B51: KG | C51: CIRUELA | D51: 4000 | E51: =A51*D51 -> 4000 | H51: S/C | I51: 0 | J51: =I51*A51 -> 0 | K51: =E51-J51 -> 4000
A52: 3 | B52: KG | C52: DURAZNO | D52: 3500 | E52: =A52*D52 -> 10500 | I52: =27000/16 -> 1687.5 | J52: =I52*A52 -> 5062.5 | K52: =E52-J52 -> 5437.5
A53: 0.5 | B53: KG | C53: FRUTILLA | D53: 6000 | E53: =A53*D53 -> 3000 | H53: S/C | I53: 0 | J53: =I53*A53 -> 0 | K53: =E53-J53 -> 3000
A54: 0.5 | B54: KG | C54: KIWI | D54: 9500 | E54: =A54*D54 -> 4750 | I54: =60000/8 -> 7500 | J54: =I54*A54 -> 3750 | K54: =E54-J54 -> 1000
A55: 2 | B55: KG | C55: LIMON | D55: 2800 | E55: =A55*D55 -> 5600 | I55: =29000/18 -> 1611.1111 | J55: =I55*A55 -> 3222.2222 | K55: =E55-J55 -> 2377.7778
A56: 0.5 | B56: CAJA | C56: MANZANA ROJA | D56: 58000 | E56: =A56*D56 -> 29000 | I56: 50000 | J56: =I56*A56 -> 25000 | K56: =E56-J56 -> 4000
A57: 3 | B57: KG | C57: MANZANA VERDE | D57: 3500 | E57: =A57*D57 -> 10500 | I57: =45000/18 -> 2500 | J57: =I57*A57 -> 7500 | K57: =E57-J57 -> 3000
A58: 0.5 | B58: CAJA | C58: PERA | D58: 32000 | E58: =A58*D58 -> 16000 | I58: 25000 | J58: =I58*A58 -> 12500 | K58: =E58-J58 -> 3500
A59: 8.9 | B59: KG | C59: SANDIA | D59: 1200 | E59: =A59*D59 -> 10680 | I59: 800 | J59: =I59*A59 -> 7120 | K59: =E59-J59 -> 3560
A60: 1 | B60: KG | C60: UVA | D60: 5500 | E60: =A60*D60 -> 5500 | I60: 4800 | J60: =I60*A60 -> 4800 | K60: =E60-J60 -> 700
E62: =SUM(E30:E61) -> 337750 | K62: =SUM(K30:K60) -> 102729.5 | L62: =K62/E62 -> 0.30415841
A65: S&T CATERING | D65: rto: 5 | E65: 46064
A67: CANTIDAD | B67: UNIDAD | C67: PRODUCTO | D67: PRECIO | E67: TOTAL | I67: PRECIO | J67: TOTAL | K67: DIFERENCIA
A68: 0.5 | B68: CAJON | C68: TOMATE PERITA | D68: 20000 | E68: =A68*D68 -> 10000 | I68: 15000 | J68: =I68*A68 -> 7500 | K68: =E68-J68 -> 2500
A69: 0.5 | B69: CAJON | C69: TOMATE CHERRY | D69: 22000 | E69: =A69*D69 -> 11000 | I69: 12000 | J69: =I69*A69 -> 6000 | K69: =E69-J69 -> 5000
A70: 2 | B70: UNIDAD | C70: APIO | D70: 2500 | E70: =A70*D70 -> 5000 | I70: 2000 | J70: =I70*A70 -> 4000 | K70: =E70-J70 -> 1000
A71: 1 | B71: CAJON | C71: PUERRO | D71: 45000 | E71: =A71*D71 -> 45000 | I71: 38000 | J71: =I71*A71 -> 38000 | K71: =E71-J71 -> 7000
A72: 1 | B72: CAJON | C72: RUCULA | D72: 6500 | E72: =A72*D72 -> 6500 | I72: 5000 | J72: =I72*A72 -> 5000 | K72: =E72-J72 -> 1500
A73: 2 | B73: CAJON | C73: LECHUGA FRANCESA | D73: 14000 | E73: =A73*D73 -> 28000 | I73: 10000 | J73: =I73*A73 -> 20000 | K73: =E73-J73 -> 8000
A74: 1 | B74: CJAON | C74: LECHUGA MORADA | D74: 11000 | E74: =A74*D74 -> 11000 | I74: 9000 | J74: =I74*A74 -> 9000 | K74: =E74-J74 -> 2000
A75: 1.5 | B75: CAJON | C75: ESPINACA | D75: 13000 | E75: =A75*D75 -> 19500 | I75: 8000 | J75: =I75*A75 -> 12000 | K75: =E75-J75 -> 7500
A76: 0.5 | B76: CAJON | C76: PALTA | D76: 74000 | E76: =A76*D76 -> 37000 | I76: 64000 | J76: =I76*A76 -> 32000 | K76: =E76-J76 -> 5000
A77: 2 | B77: CAJON | C77: COLIFLOR | D77: 17000 | E77: =A77*D77 -> 34000 | I77: 14000 | J77: =I77*A77 -> 28000 | K77: =E77-J77 -> 6000
A78: 4 | B78: CAJON | C78: BROCOLI | D78: 18000 | E78: =A78*D78 -> 72000 | I78: 15000 | J78: =I78*A78 -> 60000 | K78: =E78-J78 -> 12000
E80: =SUM(E68:E78) -> 279000 | K80: =SUM(K68:K78) -> 57500 | L80: =K80/E80 -> 0.20609319
A82: LA PIADINA | D82: rto: 18 | E82: 46064
A84: CANTIDAD | B84: UNIDAD | C84: PRODUCTO | D84: PRECIO | E84: TOTAL | I84: PRECIO | J84: TOTAL | K84: DIFERENCIA
A85: 4 | B85: KG | C85: TOMATE REDONDO | D85: 1800 | E85: =A85*D85 -> 7200 | I85: =13000/18 -> 722.22222 | J85: =I85*A85 -> 2888.8889 | K85: =E85-J85 -> 4311.1111
A86: 5 | B86: UNIDAD | C86: PALTA | D86: 1400 | E86: =A86*D86 -> 7000 | I86: =64000/70 -> 914.28571 | J86: =I86*A86 -> 4571.4286 | K86: =E86-J86 -> 2428.5714
A87: 2 | B87: UNIDAD | C87: AJO | D87: 1100 | E87: =A87*D87 -> 2200 | I87: =23000/50 -> 460 | J87: =I87*A87 -> 920 | K87: =E87-J87 -> 1280
A88: 1 | B88: KG | C88: ZANAHORIA | D88: 1600 | E88: =A88*D88 -> 1600 | I88: 1000 | J88: =I88*A88 -> 1000 | K88: =E88-J88 -> 600
E90: =SUM(E85:E88) -> 18000 | K90: =SUM(K85:K88) -> 8619.6825 | L90: =K90/E90 -> 0.47887125
A94: RAKUS | D94: rto: 21 | E94: 46064
A96: CANTIDAD | B96: UNIDAD | C96: PRODUCTO | D96: PRECIO | E96: TOTAL | I96: PRECIO | J96: TOTAL | K96: DIFERENCIA
A97: 1 | B97: CAJON | C97: LIMA | D97: 42000 | E97: =A97*D97 -> 42000 | I97: 35000 | J97: =I97*A97 -> 35000 | K97: =E97-J97 -> 7000
A98: 5 | B98: ATADO | C98: CILANTRO | D98: 3000 | E98: =A98*D98 -> 15000 | I98: 2000 | J98: =I98*A98 -> 10000 | K98: =E98-J98 -> 5000
A99: 4 | B99: CUBETAS | C99: ARANDANOS | D99: 2500 | E99: =A99*D99 -> 10000 | I99: =20000/12 -> 1666.6667 | J99: =I99*A99 -> 6666.6667 | K99: =E99-J99 -> 3333.3333
A100: 1 | B100: KG | C100: CHAMPIGNON | D100: 20000 | E100: =A100*D100 -> 20000 | I100: 18000 | J100: =I100*A100 -> 18000 | K100: =E100-J100 -> 2000
A101: 1 | B101: CAJA | C101: MANZANA GRANNY | D101: 60000 | E101: =A101*D101 -> 60000 | I101: 45000 | J101: =I101*A101 -> 45000 | K101: =E101-J101 -> 15000
A102: 1 | B102: CAJON | C102: FRUTILLA GRANEL | D102: 30000 | E102: =A102*D102 -> 30000 | I102: 25000 | J102: =I102*A102 -> 25000 | K102: =E102-J102 -> 5000
A103: 4 | B103: KG | C103: DURAZNO | D103: 3500 | E103: =A103*D103 -> 14000 | I103: =27000/16 -> 1687.5 | J103: =I103*A103 -> 6750 | K103: =E103-J103 -> 7250
A104: 2 | B104: KG | C104: CIRUELA | D104: 4000 | E104: =A104*D104 -> 8000 | H104: S/C | I104: 0 | J104: =I104*A104 -> 0 | K104: =E104-J104 -> 8000
E106: =SUM(E97:E104) -> 199000 | K106: =SUM(K97:K104) -> 52583.333 | L106: =K106/E106 -> 0.26423786
A112: TOTAL DIA | B112: =E106+E90+E80+E62+F22 -> 1799875
A114: GANANCIA | B114: =K106+K90+K80+K62+K22 -> 814557.52
A116: Comision Juan | B116: 0
A118: % | B118: =B114/B112 -> 0.45256338
A120: BULTOS COMPRADOS | C120: 100
B125: EFECTIVO | C125: MERCADO PAGO | D125: BANCO GALCIA | E125: BANCO RIO | F125: CHEQUES
B126: 2528350 | C126: 308459.29 | D126: =2277828.28-500000-1000000+491000 -> 1268828.3 | F126: =8500000+1101582.8 -> 9601582.8
A128: INGRESOS
A129: COBR. CTA. CTE | B129: 319800 | C129: 0 | D129: 0 | E129: 0 | F129: 0
A130: RENDIMIENTO MP | B130: 0 | C130: 3625.2 | D130: 0 | E130: 0 | F130: 0
A131: CHE ACREDITADO | B131: 0 | C131: 0 | D131: 1101582.8 | E131: 0 | F131: 0
A132: COBR. VACIOS | B132: 0 | C132: 0 | D132: 0 | E132: 0 | F132: 0
A133: PRESTAMOS | B133: 0 | C133: 0 | D133: 0 | E133: 0 | F133: 0
A134: IMP. CRED. 0,6% | B134: 0 | C134: =C129*0.6%+C132*0.6% -> 0 | D134: =SUM(D129:D131)*0.6% -> 6609.4968 | E134: 0 | F134: 0
A136: TOTAL | B136: =SUM(B126:B134) -> 2848150 | C136: =C126+C129+C132+C133-C134+C130 -> 312084.49 | D136: =D126+D129+D132+D133-D134+D131 -> 2363801.6 | E136: =E126+E129+E132+E133-E134 -> 0 | F136: =F126+F129+F132+F133-F134-D131 -> 8500000
...

Sheet 12-02-2026 
A2: FV | E2: rto: 229 | F2: 46065 | I2: COMPRA
A4: CANTIDAD | B4: UNIDAD | C4: PRODUCTO | D4: PRECIO | E4: TOTAL | F4: TOTAL + IVA | I4: PRECIO | J4: TOTAL | K4: DIFERENCIA
A5: 4 | B5: CAJON | C5: CIRUELA | D5: 42000 | E5: =A5*D5 -> 168000 | F5: =E5*1.105 -> 185640 | I5: 26000 | J5: =I5*A5 -> 104000 | K5: =F5-J5 -> 81640
A6: 5 | B6: CAJON | C6: BANANA | D6: 35000 | E6: =A6*D6 -> 175000 | F6: =E6*1.105 -> 193375 | I6: 27000 | J6: =I6*A6 -> 135000 | K6: =F6-J6 -> 58375
A7: 5 | B7: CAJON | C7: DURAZNO | D7: 40000 | E7: =A7*D7 -> 200000 | F7: =E7*1.105 -> 221000 | I7: 27000 | J7: =I7*A7 -> 135000 | K7: =F7-J7 -> 86000
A8: 4 | B8: CAJON | C8: PELON | D8: 35000 | E8: =A8*D8 -> 140000 | F8: =E8*1.105 -> 154700 | I8: 20000 | J8: =I8*A8 -> 80000 | K8: =F8-J8 -> 74700
A9: 3 | B9: CAJON | C9: MANZANA GRANNY | D9: 63000 | E9: =A9*D9 -> 189000 | F9: =E9*1.105 -> 208845 | I9: 50000 | J9: =I9*A9 -> 150000 | K9: =F9-J9 -> 58845
A10: 1 | B10: CAJON | C10: HUEVO | D10: 56000 | E10: =A10*D10 -> 56000 | F10: =E10*1.21 -> 67760 | I10: 50000 | J10: =I10*A10 -> 50000 | K10: =F10-J10 -> 17760
A11: 0.5 | B11: CAJON | C11: HUEVO | D11: 56000 | E11: =A11*D11 -> 28000 | F11: =E11*1.21 -> 33880 | G11: BOLSA | I11: 0 | J11: =I11*A11 -> 0 | K11: =F11-J11 -> 33880
A12: 1 | B12: CAJON | C12: MANZANA GRANNY | D12: 63000 | E12: =A12*D12 -> 63000 | F12: =E12*1.105 -> 69615 | G12: BOLSA | I12: 0 | J12: =I12*A12 -> 0 | K12: =F12-J12 -> 69615
A13: 1 | B13: CAJON | C13: CIRUELA | D13: 42000 | E13: =A13*D13 -> 42000 | F13: =E13*1.105 -> 46410 | G13: BOLSA | I13: 0 | J13: =I13*A13 -> 0 | K13: =F13-J13 -> 46410
A14: 1 | B14: CAJON | C14: PELON | D14: 35000 | E14: =A14*D14 -> 35000 | F14: =E14*1.105 -> 38675 | G14: BOLSA | I14: 0 | J14: =I14*A14 -> 0 | K14: =F14-J14 -> 38675
A15: 1 | B15: CAJON | C15: BANANA | D15: 35000 | E15: =A15*D15 -> 35000 | F15: =E15*1.105 -> 38675 | G15: BOLSA | I15: 0 | J15: =I15*A15 -> 0 | K15: =F15-J15 -> 38675
E17: =SUM(E5:E15) -> 1131000 | F17: =SUM(F5:F15) -> 1258575 | K17: =SUM(K5:K15) -> 604575 | L17: =K17/F17 -> 0.4803647
A22: BRASOV | D22: rto: 13 | E22: 46065
A24: CANTIDAD | B24: UNIDAD | C24: PRODUCTO | D24: PRECIO | E24: TOTAL | I24: PRECIO | J24: TOTAL | K24: DIFERENCIA
A25: 2 | B25: BOLSA | C25: ANCO | D25: 13000 | E25: =A25*D25 -> 26000 | I25: 9000 | J25: =I25*A25 -> 18000 | K25: =E25-J25 -> 8000
A26: 4 | B26: BOLSA | C26: PAPA | D26: 21000 | E26: =A26*D26 -> 84000 | I26: 18000 | J26: =I26*A26 -> 72000 | K26: =E26-J26 -> 12000
A27: 1 | B27: BANDEJA | C27: TOM CHERRY | D27: 12500 | E27: =A27*D27 -> 12500 | I27: =1500*5 -> 7500 | J27: =I27*A27 -> 7500 | K27: =E27-J27 -> 5000
A28: 1 | B28: CAJA | C28: PALTA T.84 | D28: =64000+8000 -> 72000 | E28: =A28*D28 -> 72000 | I28: 64000 | J28: =I28*A28 -> 64000 | K28: =E28-J28 -> 8000
A29: 1 | B29: CAJA | C29: PALTA T.70 | D29: 75000 | E29: =A29*D29 -> 75000 | I29: 63000 | J29: =I29*A29 -> 63000 | K29: =E29-J29 -> 12000
A30: 4 | B30: CAJA | C30: LIMON | D30: 30000 | E30: =A30*D30 -> 120000 | I30: 25000 | J30: =I30*A30 -> 100000 | K30: =E30-J30 -> 20000
A31: 4 | B31: CAJON | C31: NARANJA FRIO | D31: 20000 | E31: =A31*D31 -> 80000 | I31: 17000 | J31: =I31*A31 -> 68000 | K31: =E31-J31 -> 12000
A32: 2 | B32: BOLSA | C32: BONIATO | D32: 27000 | E32: =A32*D32 -> 54000 | I32: 22000 | J32: =I32*A32 -> 44000 | K32: =E32-J32 -> 10000
A33: 1 | B33: CAJON | C33: TOMATE REDONDO | D33: 20000 | E33: =A33*D33 -> 20000 | I33: 16000 | J33: =I33*A33 -> 16000 | K33: =E33-J33 -> 4000
A34: 1 | B34: CAJON | C34: MORRON ROJO | D34: 32000 | E34: =A34*D34 -> 32000 | I34: 25000 | J34: =I34*A34 -> 25000 | K34: =E34-J34 -> 7000
A35: 6 | B35: ATADO | C35: CEB VERDEO | D35: 5000 | E35: =A35*D35 -> 30000 | I35: 4000 | J35: =I35*A35 -> 24000 | K35: =E35-J35 -> 6000
A36: 2 | B36: ATADO | C36: PEREJIL | D36: 3500 | E36: =A36*D36 -> 7000 | I36: 2000 | J36: =I36*A36 -> 4000 | K36: =E36-J36 -> 3000
A37: 2 | B37: BOLSA | C37: CEBOLLA | D37: 13000 | E37: =A37*D37 -> 26000 | I37: 9000 | J37: =I37*A37 -> 18000 | K37: =E37-J37 -> 8000
A38: 1 | B38: BOLSA | C38: BATATA | D38: 13000 | E38: =A38*D38 -> 13000 | I38: 10000 | J38: =I38*A38 -> 10000 | K38: =E38-J38 -> 3000
A39: 3 | B39: ATADO | C39: MENTA | D39: 3000 | E39: =A39*D39 -> 9000 | I39: 2000 | J39: =I39*A39 -> 6000 | K39: =E39-J39 -> 3000
A40: 2 | B40: ATADO | C40: CIBOULLETE | D40: 3500 | E40: =A40*D40 -> 7000 | I40: 2500 | J40: =I40*A40 -> 5000 | K40: =E40-J40 -> 2000
... A42: 4 | B42: UNIDAD | C42: MANGO | D42: 2200 | E42: =A42*D42 -> 8800 | I42: 2000 | J42: =I42*A42 -> 8000 | K42: =E42-J42 -> 800
E44: =SUM(E25:E43) -> 681800 | K44: =SUM(K25:K42) -> 129300 | L44: =K44/E44 -> 0.18964506
A47: LA PIADINA | D47: rto: 19 | E47: 46064
A49: CANTIDAD | B49: UNIDAD | C49: PRODUCTO | D49: PRECIO | E49: TOTAL | I49: PRECIO | J49: TOTAL | K49: DIFERENCIA
A50: 2 | B50: ATADO | C50: ESPINACA | D50: 1500 | E50: =A50*D50 -> 3000 | I50: 1200 | J50: =I50*A50 -> 2400 | K50: =E50-J50 -> 600
A51: 4 | B51: UNIDAD | C51: PALTA | D51: 1300 | E51: =A51*D51 -> 5200 | I51: 914 | J51: =I51*A51 -> 3656 | K51: =E51-J51 -> 1544
A52: 3 | B52: KG | C52: TOAMTE REDONDO | D52: 1500 | E52: =A52*D52 -> 4500 | I52: 722 | J52: =I52*A52 -> 2166 | K52: =E52-J52 -> 2334
A53: 1 | B53: CAJON | C53: RUCULA | D53: 10000 | E53: =A53*D53 -> 10000 | I53: 5000 | J53: =I53*A53 -> 5000 | K53: =E53-J53 -> 5000
A54: 1 | B54: KG | C54: ZANAHORIA | D54: 1500 | E54: =A54*D54 -> 1500 | I54: =9000/9 -> 1000 | J54: =I54*A54 -> 1000 | K54: =E54-J54 -> 500
A55: 0.5 | B55: KG | C55: BANANA | D55: 3000 | E55: =A55*D55 -> 1500 | H55: S/C | I55: 0 | J55: =I55*A55 -> 0 | K55: =E55-J55 -> 1500
A56: 0.5 | B56: KG | C56: NARANJA | D56: 1200 | E56: =A56*D56 -> 600 | H56: S/C | I56: 0 | J56: =I56*A56 -> 0 | K56: =E56-J56 -> 600
A57: 0.5 | B57: KG | C57: MANZANA | D57: 3500 | E57: =A57*D57 -> 1750 | I57: =50000/17 -> 2941.1765 | J57: =I57*A57 -> 1470.5882 | K57: =E57-J57 -> 279.41176
A58: 1 | B58: KG | C58: FRUTILLA | D58: 7500 | E58: =A58*D58 -> 7500 | I58: 6000 | J58: =I58*A58 -> 6000 | K58: =E58-J58 -> 1500
A59: 0.5 | B59: KG | C59: DURAZNO | D59: 3500 | E59: =A59*D59 -> 1750 | H59: S/C | I59: 0 | J59: =I59*A59 -> 0 | K59: =E59-J59 -> 1750
A60: 0.5 | B60: KG | C60: KIWI | D60: 11000 | E60: =A60*D60 -> 5500 | I60: 7500 | J60: =I60*A60 -> 3750 | K60: =E60-J60 -> 1750
A61: 3 | B61: CUBETA | C61: ARANDANO | D61: 2500 | E61: =A61*D61 -> 7500 | I61: =20000/12 -> 1666.6667 | J61: =I61*A61 -> 5000 | K61: =E61-J61 -> 2500
A62: 0.5 | B62: KG | C62: UVA | D62: 3500 | E62: =A62*D62 -> 1750 | I62: 3000 | J62: =I62*A62 -> 1500 | K62: =E62-J62 -> 250
E64: =SUM(E50:E62) -> 52050 | K64: =SUM(K50:K62) -> 20107.412 | L64: =K64/E64 -> 0.38630954
A66: PAULA | D66: rto: 12 | E66: 46065
A68: CANTIDAD | B68: UNIDAD | C68: PRODUCTO | D68: PRECIO | E68: TOTAL | I68: PRECIO | J68: TOTAL | K68: DIFERENCIA
A69: 1 | B69: KG | C69: TOM CHERRY | D69: 3000 | E69: =A69*D69 -> 3000 | I69: 1500 | J69: =I69*A69 -> 1500 | K69: =E69-J69 -> 1500
A70: 1 | B70: KG | C70: KIWI | D70: 11000 | E70: =A70*D70 -> 11000 | I70: 7500 | J70: =I70*A70 -> 7500 | K70: =E70-J70 -> 3500
E72: =SUM(E69:E70) -> 14000 | K72: =SUM(K69:K70) -> 5000 | L72: =K72/E72 -> 0.35714286
A74: HAVANNA MORENO | D74: rto: 5 | E74: 46065
A76: CANTIDAD | B76: UNIDAD | C76: PRODUCTO | D76: PRECIO | E76: TOTAL | I76: PRECIO | J76: TOTAL | K76: DIFERENCIA
A77: 2 | B77: CAJON | C77: NARANJA JUGO FRIO | D77: 23000 | E77: =A77*D77 -> 46000 | I77: 25000 | J77: =I77*A77 -> 50000 | K77: =E77-J77 -> -4000
E79: =SUM(E77) -> 46000 | K79: =SUM(K77:K78) -> -4000 | L79: =K79/E80 -> #DIV/0!
A81: Comisión Juan | B81: 0.04 | E81: =E79*0.04 -> 1840
A84: TOTAL DIA | B84: =E72+E64+E44+F17+E79 -> 2052425
A86: GANANCIA | B86: =K72+K64+K44+K17+K79 -> 754982.41
A88: Comision Juan | B88: =E81 -> 1840
A90: % | B90: =B86/B84 -> 0.36784896
A92: BULTOS COMPRADOS | C92: 100
B97: EFECTIVO | C97: MERCADO PAGO | D97: BANCO GALCIA | E97: BANCO RIO | F97: CHEQUES
B98: 2528350 | C98: 308459.29 | D98: =2277828.28-500000-1000000+491000 -> 1268828.3 | F98: =8500000+1101582.8 -> 9601582.8
A100: INGRESOS
A101: COBR. CTA. CTE | B101: 319800 | C101: 0 | D101: 0 | E101: 0 | F101: 0
A102: RENDIMIENTO MP | B102: 0 | C102: 3625.2 | D102: 0 | E102: 0 | F102: 0
A103: CHE ACREDITADO | B103: 0 | C103: 0 | D103: 1101582.8 | E103: 0 | F103: 0
A104: COBR. VACIOS | B104: 0 | C104: 0 | D104: 0 | E104: 0 | F104: 0
A105: PRESTAMOS | B105: 0 | C105: 0 | D105: 0 | E105: 0 | F105: 0
A106: IMP. CRED. 0,6% | B106: 0 | C106: =C101*0.6%+C104*0.6% -> 0 | D106: =SUM(D101:D103)*0.6% -> 6609.4968 | E106: 0 | F106: 0
A108: TOTAL | B108: =SUM(B98:B106) -> 2848150 | C108: =C98+C101+C104+C105-C106+C102 -> 312084.49 | D108: =D98+D101+D104+D105-D106+D103 -> 2363801.6 | E108: =E98+E101+E104+E105-E106 -> 0 | F108: =F98+F101+F104+F105-F106-D103 -> 8500000
A110: GASTOS
A111: ING. MERCADO | B111: 10000 | C111: 0 | D111: 0 | E111: 0
A112: CARGA / VACIOS | B112: 0 | C112: 0 | D112: 0 | E112: 0
A113: CHEQ DEBITADO | B113: 0 | C113: 0 | D113: 500000 | E113: 0
A114: PEAJE | B114: 0 | C114: 0 | D114: 0 | E114: 0
A115: MERCADERIA | B115: 0 | C115: 395000 | D115: 0 | E115: 0
A116: COMBUSTIBLE | B116: 40000 | C116: 0 | D116: 0 | E116: 0
A117: SUELDOS | B117: 0 | C117: 0 | D117: 0 | E117: 0
A118: DEV. PRESTAMOS | B118: 0 | C118: 0 | D118: 0 | E118: 0
A119: AGUA | B119: 0 | C119: 0 | D119: 0 | E119: 0
A120: FLETE JUAN | B120: 0 | C120: 0 | D120: 0 | E120: 0
A121: RETIRO JOAQUIN | B121: 0 | C121: 50000 | D121: 0 | E121: 0
A122: RETIRO FEDERICO | B122: 0 | C122: 50000 | D122: 0 | E122: 0
... A130: MONOTRIB. LEO | B130: 0 | C130: 0 | D130: 0 | E130: 0
A131: IIBB CHEQUE | B131: 0 | C131: 0 | D131: =SUM(D101:D103)*2% -> 22031.656 | E131: 0
A132: IIBB | B132: 0 | C132: 0 | D132: 0 | E132: 0
A133: IVA | B133: 0 | C133: 0 | D133: 0 | E133: 0
A134: GANANCIAS | B134: 0 | C134: 0 | D134: 0 | E134: 0
A135: MANT. CTA. | B135: 0 | C135: 0 | D135: 0 | E135: 0
A137: IMP. DEB. 0,6% | B137: 0 | C137: =SUM(C111:C134)*0.6% -> 2970 | D137: =SUM(D111:D134)*0.6%+(D138*0.6%) -> 5737.1923 | E137: =(E115*0.6%)+(E116*0.6%)+(E117*0.6%)+(E120*0.6%)+(E121*0.6%) -> 0
A138: PASE DE CUENTAS | B138: 0 | C138: =272000+150000 -> 422000 | D138: =272000+150000 -> 422000 | E138: =SUM(E112:E136)*0.6%+(E139*0.6%) -> 0
A140: TOTAL SALIDAS | B140: =SUM(B111:B139) -> 70000 | C140: =SUM(C111:C137) -> 497970 | D140: =SUM(D111:D138) -> 961935.91 | E140: =E122+E126+E137-E138 -> 0 | F140: =F115
A142: SALDOS | B142: =B108-B140 -> 2778150 | C142: =C108-C140+C138 -> 236114.49 | D142: =D108-D140 -> 1401865.7 | E142: =E108-E140 -> 0 | F142: =F108-F140 -> 8500000
A144: fede | B144: 249800
A145: joaquin | B145: 2528350
...

Sheet 13-02-2026 
A2: COLEGIO SJCB - VIRREY DEL PINO 3299 | E2: rto: 3 | F2: 46066 | I2: COMPRA
A4: CANTIDAD | B4: UNIDAD | C4: PRODUCTO | D4: PRECIO | E4: TOTAL | F4: TOTAL + IVA | I4: COSTO | J4: TOTAL | K4: DIFERENCIA
A5: 0.5 | B5: CAJON | C5: HUEVO N1 | D5: 52000 | E5: =A5*D5 -> 26000 | F5: =E5*1.21 -> 31460 | I5: 50000 | J5: =I5*A5 -> 25000 | K5: =F5-J5 -> 6460
A6: 1 | B6: UNIDAD | C6: AJO | D6: 900 | E6: =A6*D6 -> 900 | F6: =E6*1.105 -> 994.5 | I6: =23000/50 -> 460 | J6: =I6*A6 -> 460 | K6: =F6-J6 -> 534.5
A7: 1 | B7: UNIDAD | C7: APIO | D7: 2500 | E7: =A7*D7 -> 2500 | F7: =E7*1.105 -> 2762.5 | I7: 1200 | J7: =I7*A7 -> 1200 | K7: =F7-J7 -> 1562.5
A8: 1 | B8: BOLSA | C8: BATATA | D8: 16000 | E8: =A8*D8 -> 16000 | F8: =E8*1.105 -> 17680 | I8: 13000 | J8: =I8*A8 -> 13000 | K8: =F8-J8 -> 4680
A9: 2 | B9: UNIDAD | C9: BROCOLI | D9: 2500 | E9: =A9*D9 -> 5000 | F9: =E9*1.105 -> 5525 | I9: 1500 | J9: =I9*A9 -> 3000 | K9: =F9-J9 -> 2525
A10: 1 | B10: BOLSA | C10: ANCO | D10: 13000 | E10: =A10*D10 -> 13000 | F10: =E10*1.105 -> 14365 | I10: 8000 | J10: =I10*A10 -> 8000 | K10: =F10-J10 -> 6365
A11: 1.5 | B11: KG | C11: ANCO | D11: 1200 | E11: =A11*D11 -> 1800 | F11: =E11*1.105 -> 1989 | I11: =8000/15 -> 533.33333 | J11: =I11*A11 -> 800 | K11: =F11-J11 -> 1189
A12: 3 | B12: KG | C12: CEBOLLA MORADA | D12: 1600 | E12: =A12*D12 -> 4800 | F12: =E12*1.105 -> 5304 | I12: 1000 | J12: =I12*A12 -> 3000 | K12: =F12-J12 -> 2304
A13: 1 | B13: KG | C13: CEBOLLA COMUN | D13: 800 | E13: =A13*D13 -> 800 | F13: =E13*1.105 -> 884 | I13: =9000/16 -> 562.5 | J13: =I13*A13 -> 562.5 | K13: =F13-J13 -> 321.5
A14: 0.5 | B14: CAJON | C14: MANZANA ROJA ELEGIDA | D14: 80000 | E14: =A14*D14 -> 40000 | F14: =E14*1.105 -> 44200 | I14: 65000 | J14: =I14*A14 -> 32500 | K14: =F14-J14 -> 11700
A15: 0.5 | B15: CAJON | C15: MANZANA VERDE ELEGIDA | D15: 65000 | E15: =A15*D15 -> 32500 | F15: =E15*1.105 -> 35912.5 | I15: 55000 | J15: =I15*A15 -> 27500 | K15: =F15-J15 -> 8412.5
A16: 1 | B16: CAJON | C16: NARANJA JUGO ELEGIDA | D16: 22000 | E16: =A16*D16 -> 22000 | F16: =E16*1.105 -> 24310 | I16: 17000 | J16: =I16*A16 -> 17000 | K16: =F16-J16 -> 7310
A17: 3 | B17: BOLSA | C17: PAPA BLANCA | D17: 21000 | E17: =A17*D17 -> 63000 | F17: =E17*1.105 -> 69615 | I17: 18000 | J17: =I17*A17 -> 54000 | K17: =F17-J17 -> 15615
A18: 3 | B18: KG | C18: MORRÓN ROJO | D18: 4000 | E18: =A18*D18 -> 12000 | F18: =E18*1.105 -> 13260 | I18: =27000/8 -> 3375 | J18: =I18*A18 -> 10125 | K18: =F18-J18 -> 3135
A19: 2.5 | B19: KG | C19: MORRÓN VERDE | D19: 3100 | E19: =A19*D19 -> 7750 | F19: =E19*1.105 -> 8563.75 | I19: =12000/8 -> 1500 | J19: =I19*A19 -> 3750 | K19: =F19-J19 -> 4813.75
A20: 2 | B20: KG | C20: MORRÓN AMARILLO | D20: 4000 | E20: =A20*D20 -> 8000 | F20: =E20*1.105 -> 8840 | I20: =25000/8 -> 3125 | J20: =I20*A20 -> 6250 | K20: =F20-J20 -> 2590
A21: 0.5 | B21: ATADO | C21: PUERRO | D21: 6000 | E21: =A21*D21 -> 3000 | F21: =E21*1.105 -> 3315 | I21: 5000 | J21: =I21*A21 -> 2500 | K21: =F21-J21 -> 815
A22: 3 | B22: KG | C22: POMELO | D22: 4500 | E22: =A22*D22 -> 13500 | F22: =E22*1.105 -> 14917.5 | I22: =50000/14 -> 3571.4286 | J22: =I22*A22 -> 10714.286 | K22: =F22-J22 -> 4203.2143
A23: 1 | B23: UNIDAD | C23: REMOLACHA | D23: 1600 | E23: =A23*D23 -> 1600 | F23: =E23*1.105 -> 1768 | I23: =10000/9 -> 1111.1111 | J23: =I23*A23 -> 1111.1111 | K23: =F23-J23 -> 656.88889
A24: 0.7 | B24: KG | C24: REPOLLO BLANCO | D24: 1500 | E24: =A24*D24 -> 1050 | F24: =E24*1.105 -> 1160.25 | I24: 882 | J24: =I24*A24 -> 617.4 | K24: =F24-J24 -> 542.85
A25: 9 | B25: KG | C25: TOMATE PERITA | D25: 1600 | E25: =A25*D25 -> 14400 | F25: =E25*1.105 -> 15912 | I25: 1000 | J25: =I25*A25 -> 9000 | K25: =F25-J25 -> 6912
A26: 1 | B26: BOLSA | C26: ZANAHORIA CUBITO ELEGIDA | D26: 12000 | E26: =A26*D26 -> 12000 | F26: =E26*1.105 -> 13260 | I26: 8000 | J26: =I26*A26 -> 8000 | K26: =F26-J26 -> 5260
A27: 5 | B27: KG | C27: ZANAHORIA CUBITO ELEGIDA | D27: 1500 | E27: =A27*D27 -> 7500 | F27: =E27*1.105 -> 8287.5 | I27: =8000/9 -> 888.88889 | J27: =I27*A27 -> 4444.4444 | K27: =F27-J27 -> 3843.0556
A28: 3 | B28: KG | C28: ZAPALLITO REDONDO | D28: 1200 | E28: =A28*D28 -> 3600 | F28: =E28*1.105 -> 3978 | I28: =10000/15 -> 666.66667 | J28: =I28*A28 -> 2000 | K28: =F28-J28 -> 1978
A29: 6 | B29: UNIDAD | C29: PALTA | D29: 1300 | E29: =A29*D29 -> 7800 | F29: =E29*1.105 -> 8619 | I29: 914 | J29: =I29*A29 -> 5484 | K29: =F29-J29 -> 3135
A30: 1 | B30: UNIDAD | C30: KALE | D30: 2000 | E30: =A30*D30 -> 2000 | F30: =E30*1.105 -> 2210 | I30: 1000 | J30: =I30*A30 -> 1000 | K30: =F30-J30 -> 1210
A31: 1 | B31: KG | C31: BERENJENA | D31: 1600 | E31: =A31*D31 -> 1600 | F31: =E31*1.105 -> 1768 | I31: 1000 | J31: =I31*A31 -> 1000 | K31: =F31-J31 -> 768
A32: 0.3 | B32: KG | C32: TOMATE CHERRY | D32: 3500 | E32: =A32*D32 -> 1050 | F32: =E32*1.105 -> 1160.25 | I32: 3000 | J32: =I32*A32 -> 900 | K32: =F32-J32 -> 260.25
E34: =SUM(E5:E32) -> 325150 | F34: =SUM(F5:F32) -> 362020.75 | K34: =SUM(K5:K32) -> 109102.01 | L34: =IFERROR(K34/E34, 0) -> 0.33554362
A36: COLEGIO ST. MATTHEWS - MOLDES 1469, BELGRANO | E36: rto: 1 | F36: 46066 | I36: COMPRA
A38: CANTIDAD | B38: UNIDAD | C38: PRODUCTO | D38: PRECIO | E38: TOTAL | F38: TOTAL + IVA | I38: COSTO | J38: TOTAL | K38: DIFERENCIA
A39: 3 | B39: BOLSA | C39: PAPA BLANCA | D39: 21000 | E39: =A39*D39 -> 63000 | F39: =E39*1.105 -> 69615 | I39: 18000 | J39: =I39*A39 -> 54000 | K39: =F39-J39 -> 15615
A40: 1 | B40: BOLSA | C40: ANCO | D40: 13000 | E40: =A40*D40 -> 13000 | F40: =E40*1.105 -> 14365 | I40: 8000 | J40: =I40*A40 -> 8000 | K40: =F40-J40 -> 6365
A41: 1 | B41: BOLSA | C41: ZANAHORIA CUBITO ELEGIDA | D41: 12000 | E41: =A41*D41 -> 12000 | F41: =E41*1.105 -> 13260 | I41: 8000 | J41: =I41*A41 -> 8000 | K41: =F41-J41 -> 5260
A42: 8 | B42: KG | C42: TOMATE PERITA | D42: 1600 | E42: =A42*D42 -> 12800 | F42: =E42*1.105 -> 14144 | I42: 1000 | J42: =I42*A42 -> 8000 | K42: =F42-J42 -> 6144
A43: 3 | B43: KG | C43: BATATA | D43: 1800 | E43: =A43*D43 -> 5400 | F43: =E43*1.105 -> 5967 | I43: =13000/10 -> 1300 | J43: =I43*A43 -> 3900 | K43: =F43-J43 -> 2067
A44: 2 | B44: KG | C44: ZAPALLITO REDONDO | D44: 1200 | E44: =A44*D44 -> 2400 | F44: =E44*1.105 -> 2652 | I44: =10000/15 -> 666.66667 | J44: =I44*A44 -> 1333.3333 | K44: =F44-J44 -> 1318.6667
A45: 3 | B45: KG | C45: CEBOLLA MORADA | D45: 1600 | E45: =A45*D45 -> 4800 | F45: =E45*1.105 -> 5304 | I45: 1000 | J45: =I45*A45 -> 3000 | K45: =F45-J45 -> 2304
A46: 2 | B46: KG | C46: CEBOLLA | D46: 800 | E46: =A46*D46 -> 1600 | F46: =E46*1.105 -> 1768 | I46: =9000/16 -> 562.5 | J46: =I46*A46 -> 1125 | K46: =F46-J46 -> 643
A47: 3 | B47: KG | C47: MORRÓN ROJO | D47: 4000 | E47: =A47*D47 -> 12000 | F47: =E47*1.105 -> 13260 | I47: =27000/8 -> 3375 | J47: =I47*A47 -> 10125 | K47: =F47-J47 -> 3135
A48: 2.5 | B48: KG | C48: MORRÓN VERDE | D48: 3100 | E48: =A48*D48 -> 7750 | F48: =E48*1.105 -> 8563.75 | I48: =12000/8 -> 1500 | J48: =I48*A48 -> 3750 | K48: =F48-J48 -> 4813.75
A49: 2.5 | B49: KG | C49: MORRÓN AMARILLO | D49: 4000 | E49: =A49*D49 -> 10000 | F49: =E49*1.105 -> 11050 | I49: =25000/8 -> 3125 | J49: =I49*A49 -> 7812.5 | K49: =F49-J49 -> 3237.5
A50: 2 | B50: KG | C50: REPOLLO BLANCO | D50: 1500 | E50: =A50*D50 -> 3000 | F50: =E50*1.105 -> 3315 | I50: 882 | J50: =I50*A50 -> 1764 | K50: =F50-J50 -> 1551
A51: 1 | B51: KG | C51: ZUCCINI | D51: 1500 | E51: =A51*D51 -> 1500 | F51: =E51*1.105 -> 1657.5 | I51: =8000/15 -> 533.33333 | J51: =I51*A51 -> 533.33333 | K51: =F51-J51 -> 1124.1667
A52: 2 | B52: UNIDAD | C52: BRÓCOLI | D52: 2500 | E52: =A52*D52 -> 5000 | F52: =E52*1.105 -> 5525 | I52: 1500 | J52: =I52*A52 -> 3000 | K52: =F52-J52 -> 2525
A53: 0.7 | B53: KG | C53: TOMATE CHERRY | D53: 3500 | E53: =A53*D53 -> 2450 | F53: =E53*1.105 -> 2707.25 | I53: 3000 | J53: =I53*A53 -> 2100 | K53: =F53-J53 -> 607.25
A54: 0.6 | B54: KG | C54: REMOLACHA | D54: 1600 | E54: =A54*D54 -> 960 | F54: =E54*1.105 -> 1060.8 | I54: =10000/9 -> 1111.1111 | J54: =I54*A54 -> 666.66667 | K54: =F54-J54 -> 394.13333
A55: 1 | B55: UNIDAD | C55: APIO | D55: 2500 | E55: =A55*D55 -> 2500 | F55: =E55*1.105 -> 2762.5 | I55: 1200 | J55: =I55*A55 -> 1200 | K55: =F55-J55 -> 1562.5
A56: 1 | B56: CAJON | C56: NARANJA JUGO ELEGIDA | D56: 22000 | E56: =A56*D56 -> 22000 | F56: =E56*1.105 -> 24310 | I56: 17000 | J56: =I56*A56 -> 17000 | K56: =F56-J56 -> 7310
A57: 4 | B57: KG | C57: POMELO | D57: 4500 | E57: =A57*D57 -> 18000 | F57: =E57*1.105 -> 19890 | I57: =50000/14 -> 3571.4286 | J57: =I57*A57 -> 14285.714 | K57: =F57-J57 -> 5604.2857
A58: 3 | B58: KG | C58: MANZANA ROJA ELEGIDA | D58: 4500 | E58: =A58*D58 -> 13500 | F58: =E58*1.105 -> 14917.5 | I58: =65000/19 -> 3421.0526 | J58: =I58*A58 -> 10263.158 | K58: =F58-J58 -> 4654.3421
A59: 3 | B59: KG | C59: MANZANA VERDE ELEGIDA | D59: 4000 | E59: =A59*D59 -> 12000 | F59: =E59*1.105 -> 13260 | I59: =55000/18 -> 3055.5556 | J59: =I59*A59 -> 9166.6667 | K59: =F59-J59 -> 4093.3333
A60: 2 | B60: KG | C60: PERA | D60: 2500 | E60: =A60*D60 -> 5000 | F60: =E60*1.105 -> 5525 | I60: =25000/18 -> 1388.8889 | J60: =I60*A60 -> 2777.7778 | K60: =F60-J60 -> 2747.2222
A61: 0.5 | B61: CAJON | C61: HUEVO N1 | D61: 52000 | E61: =A61*D61 -> 26000 | F61: =E61*1.21 -> 31460 | I61: 50000 | J61: =I61*A61 -> 25000 | K61: =F61-J61 -> 6460
E63: =SUM(E39:E61) -> 256660 | F63: =SUM(F39:F61) -> 286339.3 | K63: =SUM(K39:K61) -> 89536.15 | L63: =IFERROR(K63/E63, 0) -> 0.3488512
A66: COLEGIO BRICK TOWERS | DEL VISO | E66: rto: 1 | F66: 46066 | I66: COMPRA
A68: CANTIDAD | B68: UNIDAD | C68: PRODUCTO | D68: PRECIO | E68: TOTAL | F68: TOTAL + IVA | I68: COSTO | J68: TOTAL | K68: DIFERENCIA
A69: 2 | B69: BOLSA | C69: PAPA BLANCA | D69: 21000 | E69: =A69*D69 -> 42000 | F69: =E69*1.105 -> 46410 | I69: 18000 | J69: =I69*A69 -> 36000 | K69: =F69-J69 -> 10410
A70: 1 | B70: BOLSA | C70: ZANAHORIA CUBITO ELEGIDA | D70: 12000 | E70: =A70*D70 -> 12000 | F70: =E70*1.105 -> 13260 | I70: 8000 | J70: =I70*A70 -> 8000 | K70: =F70-J70 -> 5260
A71: 1 | B71: BOLSA | C71: BATATA | D71: 16000 | E71: =A71*D71 -> 16000 | F71: =E71*1.105 -> 17680 | I71: 13000 | J71: =I71*A71 -> 13000 | K71: =F71-J71 -> 4680
A72: 3.96 | B72: KG | C72: ANCO | D72: 1200 | E72: =A72*D72 -> 4752 | F72: =E72*1.105 -> 5250.96 | I72: =8000/15 -> 533.33333 | J72: =I72*A72 -> 2112 | K72: =F72-J72 -> 3138.96
A73: 12 | B73: ATADO | C73: RUCULA | D73: 500 | E73: =A73*D73 -> 6000 | F73: =E73*1.105 -> 6630 | I73: =4000/24 -> 166.66667 | J73: =I73*A73 -> 2000 | K73: =F73-J73 -> 4630
A74: 2 | B74: KG | C74: LECHUGA FRANCESA | D74: 3500 | E74: =A74*D74 -> 7000 | F74: =E74*1.105 -> 7735 | I74: =10000/6 -> 1666.6667 | J74: =I74*A74 -> 3333.3333 | K74: =F74-J74 -> 4401.6667
A75: 8 | B75: KG | C75: TOMATE PERITA | D75: 1600 | E75: =A75*D75 -> 12800 | F75: =E75*1.105 -> 14144 | I75: 1000 | J75: =I75*A75 -> 8000 | K75: =F75-J75 -> 6144
A76: 2 | B76: KG | C76: MORRON ROJO | D76: 4000 | E76: =A76*D76 -> 8000 | F76: =E76*1.105 -> 8840 | I76: =27000/8 -> 3375 | J76: =I76*A76 -> 6750 | K76: =F76-J76 -> 2090
A77: 2 | B77: KG | C77: MORRON VERDE | D77: 3100 | E77: =A77*D77 -> 6200 | F77: =E77*1.105 -> 6851 | I77: =12000/8 -> 1500 | J77: =I77*A77 -> 3000 | K77: =F77-J77 -> 3851
A78: 2 | B78: KG | C78: MORRON AMARILLO | D78: 4000 | E78: =A78*D78 -> 8000 | F78: =E78*1.105 -> 8840 | I78: =25000/8 -> 3125 | J78: =I78*A78 -> 6250 | K78: =F78-J78 -> 2590
A79: 2 | B79: KG | C79: CHAUCHA REDONDA | D79: 4000 | E79: =A79*D79 -> 8000 | F79: =E79*1.105 -> 8840 | I79: =15000/7 -> 2142.8571 | J79: =I79*A79 -> 4285.7143 | K79: =F79-J79 -> 4554.2857
A80: 2 | B80: KG | C80: CEBOLLA | D80: 800 | E80: =A80*D80 -> 1600 | F80: =E80*1.105 -> 1768 | I80: =9000/16 -> 562.5 | J80: =I80*A80 -> 1125 | K80: =F80-J80 -> 643
A81: 1 | B81: KG | C81: CEBOLLA DE VERDEO | D81: 5000 | E81: =A81*D81 -> 5000 | F81: =E81*1.105 -> 5525 | I81: 4000 | J81: =I81*A81 -> 4000 | K81: =F81-J81 -> 1525
A82: 1 | B82: UNIDAD | C82: AJO | D82: 900 | E82: =A82*D82 -> 900 | F82: =E82*1.105 -> 994.5 | I82: =23000/50 -> 460 | J82: =I82*A82 -> 460 | K82: =F82-J82 -> 534.5
A83: 2 | B83: KG | C83: CEBOLLA MORADA | D83: 1600 | E83: =A83*D83 -> 3200 | F83: =E83*1.105 -> 3536 | I83: 1000 | J83: =I83*A83 -> 2000 | K83: =F83-J83 -> 1536
A84: 1 | B84: CAJON | C84: NARANJA JUGO ELEGIDA | D84: 22000 | E84: =A84*D84 -> 22000 | F84: =E84*1.105 -> 24310 | I84: 17000 | J84: =I84*A84 -> 17000 | K84: =F84-J84 -> 7310
A85: 1 | B85: CAJON | C85: MANZANA VERDE ELEGIDA | D85: 65000 | E85: =A85*D85 -> 65000 | F85: =E85*1.105 -> 71825 | I85: 55000 | J85: =I85*A85 -> 55000 | K85: =F85-J85 -> 16825
A86: 1 | B86: CAJON | C86: MANZANA ROJA ELEGIDA | D86: 80000 | E86: =A86*D86 -> 80000 | F86: =E86*1.105 -> 88400 | I86: 65000 | J86: =I86*A86 -> 65000 | K86: =F86-J86 -> 23400
A87: 3 | B87: KG | C87: BANANA ECUADOR | D87: 2500 | E87: =A87*D87 -> 7500 | F87: =E87*1.105 -> 8287.5 | I87: =28000/17 -> 1647.0588 | J87: =I87*A87 -> 4941.1765 | K87: =F87-J87 -> 3346.3235
A88: 2 | B88: KG | C88: PERA | D88: 2500 | E88: =A88*D88 -> 5000 | F88: =E88*1.105 -> 5525 | I88: =25000/18 -> 1388.8889 | J88: =I88*A88 -> 2777.7778 | K88: =F88-J88 -> 2747.2222
A89: 2 | B89: MAPLE | C89: HUEVO N1 | D89: 4500 | E89: =A89*D89 -> 9000 | F89: =E89*1.21 -> 10890 | I89: =50000/12 -> 4166.6667 | J89: =I89*A89 -> 8333.3333 | K89: =F89-J89 -> 2556.6667
E91: =SUM(E69:E89) -> 329952 | F91: =SUM(F69:F89) -> 365541.96 | K91: =SUM(K69:K89) -> 112173.62 | L91: =IFERROR(K91/F91, 0) -> 0.30686935
A94: COLEGIO VILLA DEVOTO SCHOOL - PEDRO MORAN 4441 | E94: rto: 3 | F94: 46066 | I94: COMPRA
A96: CANTIDAD | B96: UNIDAD | C96: PRODUCTO | D96: PRECIO | E96: TOTAL | F96: TOTAL + IVA | I96: COSTO | J96: TOTAL | K96: DIFERENCIA
A97: 4 | B97: KG | C97: MORRON ROJO | D97: 4000 | E97: =A97*D97 -> 16000 | F97: =E97*1.105 -> 17680 | I97: =27000/8 -> 3375 | J97: =I97*A97 -> 13500 | K97: =F97-J97 -> 4180
A98: 4 | B98: KG | C98: MORRON VERDE | D98: 3100 | E98: =A98*D98 -> 12400 | F98: =E98*1.105 -> 13702 | I98: =12000/8 -> 1500 | J98: =I98*A98 -> 6000 | K98: =F98-J98 -> 7702
A99: 4 | B99: KG | C99: MORRON AMARILLO | D99: 4000 | E99: =A99*D99 -> 16000 | F99: =E99*1.105 -> 17680 | I99: =25000/8 -> 3125 | J99: =I99*A99 -> 12500 | K99: =F99-J99 -> 5180
A100: 2 | B100: KG | C100: BERENJENA | D100: 1600 | E100: =A100*D100 -> 3200 | F100: =E100*1.105 -> 3536 | I100: 1000 | J100: =I100*A100 -> 2000 | K100: =F100-J100 -> 1536
A101: 3 | B101: KG | C101: ZUCCINI | D101: 1500 | E101: =A101*D101 -> 4500 | F101: =E101*1.105 -> 4972.5 | I101: =8000/15 -> 533.33333 | J101: =I101*A101 -> 1600 | K101: =F101-J101 -> 3372.5
A102: 2 | B102: ATADO | C102: CIBOULETTE | D102: 3000 | E102: =A102*D102 -> 6000 | F102: =E102*1.105 -> 6630 | I102: 2000 | J102: =I102*A102 -> 4000 | K102: =F102-J102 -> 2630
A103: 2 | B103: ATADO | C103: CILANTRO | D103: 3000 | E103: =A103*D103 -> 6000 | F103: =E103*1.105 -> 6630 | I103: 2000 | J103: =I103*A103 -> 4000 | K103: =F103-J103 -> 2630
A104: 1 | B104: ATADO | C104: PEREJIL | D104: 3500 | E104: =A104*D104 -> 3500 | F104: =E104*1.105 -> 3867.5 | I104: 1500 | J104: =I104*A104 -> 1500 | K104: =F104-J104 -> 2367.5
A105: 1.2 | B105: KG | C105: CEBOLLA DE VERDEO | D105: 5000 | E105: =A105*D105 -> 6000 | F105: =E105*1.105 -> 6630 | I105: 4000 | J105: =I105*A105 -> 4800 | K105: =F105-J105 -> 1830
A106: 1 | B106: ATADO | C106: APIO | D106: 2500 | E106: =A106*D106 -> 2500 | F106: =E106*1.105 -> 2762.5 | I106: 1200 | J106: =I106*A106 -> 1200 | K106: =F106-J106 -> 1562.5
A107: 1 | B107: BOLSA | C107: ANCO | D107: 13000 | E107: =A107*D107 -> 13000 | F107: =E107*1.105 -> 14365 | I107: 8000 | J107: =I107*A107 -> 8000 | K107: =F107-J107 -> 6365
A108: 2 | B108: KG | C108: BROCOLI | D108: 2500 | E108: =A108*D108 -> 5000 | F108: =E108*1.105 -> 5525 | I108: 1500 | J108: =I108*A108 -> 3000 | K108: =F108-J108 -> 2525
A109: 4 | B109: KG | C109: ZAPALLITO REDONDO | D109: 1200 | E109: =A109*D109 -> 4800 | F109: =E109*1.105 -> 5304 | I109: =10000/15 -> 666.66667 | J109: =I109*A109 -> 2666.6667 | K109: =F109-J109 -> 2637.3333
A110: 11 | B110: KG | C110: TOMATE PERITA | D110: 1600 | E110: =A110*D110 -> 17600 | F110: =E110*1.105 -> 19448 | I110: 1000 | J110: =I110*A110 -> 11000 | K110: =F110-J110 -> 8448
A111: 0.8 | B111: KG | C111: TOMATE CHERRY | D111: 3500 | E111: =A111*D111 -> 2800 | F111: =E111*1.105 -> 3094 | I111: 3000 | J111: =I111*A111 -> 2400 | K111: =F111-J111 -> 694
A112: 1 | B112: KG | C112: REMOLACHA | D112: 1600 | E112: =A112*D112 -> 1600 | F112: =E112*1.105 -> 1768 | I112: =10000/9 -> 1111.1111 | J112: =I112*A112 -> 1111.1111 | K112: =F112-J112 -> 656.88889
A113: 0.5 | B113: ATADO | C113: PUERRO | D113: 6000 | E113: =A113*D113 -> 3000 | F113: =E113*1.105 -> 3315 | I113: 5000 | J113: =I113*A113 -> 2500 | K113: =F113-J113 -> 815
...

Sheet 17-02-2026 
A2: COLCAR | E2: rto: 5 | F2: 46070 | I2: COMPRA
A4: CANTIDAD | B4: UNIDAD | C4: PRODUCTO | D4: PRECIO | E4: TOTAL | F4: TOTAL + IVA | I4: COSTO | J4: TOTAL | K4: DIFERENCIA
A5: 1 | B5: CAJON | C5: CHOCLO | D5: 18000 | E5: =A5*D5 -> 18000 | F5: =E5*1.105 -> 19890 | I5: 15000 | J5: =I5*A5 -> 15000 | K5: =F5-J5 -> 4890 | L5: =IFERROR(K5/E5, 0) -> 0.27166667
A6: 1 | B6: CAJON | C6: LECHUGA MANTECA | D6: 13000 | E6: =A6*D6 -> 13000 | F6: =E6*1.105 -> 14365 | I6: 9000 | J6: =I6*A6 -> 9000 | K6: =F6-J6 -> 5365 | L6: =IFERROR(K6/E6, 0) -> 0.41269231
A7: 2 | B7: CAJON | C7: TOMATE REDONDO | D7: 32000 | E7: =A7*D7 -> 64000 | F7: =E7*1.105 -> 70720 | I7: 28000 | J7: =I7*A7 -> 56000 | K7: =F7-J7 -> 14720 | L7: =IFERROR(K7/E7, 0) -> 0.23
A8: 3 | B8: CAJON | C8: ACELGA | D8: 16000 | E8: =A8*D8 -> 48000 | F8: =E8*1.105 -> 53040 | I8: 12000 | J8: =I8*A8 -> 36000 | K8: =F8-J8 -> 17040 | L8: =IFERROR(K8/E8, 0) -> 0.355
A9: 8 | B9: BOLSA | C9: PAPA | D9: 16000 | E9: =A9*D9 -> 128000 | F9: =E9*1.105 -> 141440 | I9: 13000 | J9: =I9*A9 -> 104000 | K9: =F9-J9 -> 37440 | L9: =IFERROR(K9/E9, 0) -> 0.2925
A10: 1 | B10: BOLSA | C10: ANCO | D10: 12000 | E10: =A10*D10 -> 12000 | F10: =E10*1.105 -> 13260 | I10: 8000 | J10: =I10*A10 -> 8000 | K10: =F10-J10 -> 5260 | L10: =IFERROR(K10/E10, 0) -> 0.43833333
A11: 1 | B11: BOLSA | C11: CEBOLLA | D11: 12000 | E11: =A11*D11 -> 12000 | F11: =E11*1.105 -> 13260 | I11: 8000 | J11: =I11*A11 -> 8000 | K11: =F11-J11 -> 5260 | L11: =IFERROR(K11/E11, 0) -> 0.43833333
E13: =SUM(E5:E11) -> 295000 | F13: =SUM(F5:F11) -> 325975 | K13: =SUM(K5:K11) -> 89975 | L13: =IFERROR(K13/E13, 0) -> 0.305
A15: Comisión Juan | B15: 0.04 | E15: =E13*0.04 -> 11800
A18: BRASOV | D18: rto: 14 | E18: 46070
A20: CANTIDAD | B20: UNIDAD | C20: PRODUCTO | D20: PRECIO | E20: TOTAL | I20: PRECIO | J20: TOTAL | K20: DIFERENCIA
A21: 1 | B21: BOLSA | C21: ANCO | D21: 13000 | E21: =A21*D21 -> 13000 | I21: 8000 | J21: =I21*A21 -> 8000 | K21: =E21-J21 -> 5000 | L21: =K21/E21 -> 0.38461538
A22: 1 | B22: BOLSA | C22: BONIATO | D22: 26000 | E22: =A22*D22 -> 26000 | I22: =105000/5 -> 21000 | J22: =I22*A22 -> 21000 | K22: =E22-J22 -> 5000 | L22: =K22/E22 -> 0.19230769
A23: 2 | B23: BOLSA | C23: PAPA LAVADA | D23: 22000 | E23: =A23*D23 -> 44000 | I23: =148000/8 -> 18500 | J23: =I23*A23 -> 37000 | K23: =E23-J23 -> 7000 | L23: =K23/E23 -> 0.15909091
A24: 2 | B24: KG | C24: PEPINO | D24: 1400 | E24: =A24*D24 -> 2800 | I24: 1000 | J24: =I24*A24 -> 2000 | K24: =E24-J24 -> 800 | L24: =K24/E24 -> 0.28571429
A25: 1 | B25: BANDEJA | C25: TOMATE CHERRY | D25: 14000 | E25: =A25*D25 -> 14000 | I25: =8000 -> 8000 | J25: =I25*A25 -> 8000 | K25: =E25-J25 -> 6000 | L25: =K25/E25 -> 0.42857143
A26: 2 | B26: CAJON | C26: NARANJA DE JUGO COMERCIAL | D26: 18000 | E26: =A26*D26 -> 36000 | I26: 15000 | J26: =I26*A26 -> 30000 | K26: =E26-J26 -> 6000 | L26: =K26/E26 -> 0.16666667
A27: 2 | B27: CAJA | C27: LIMON | D27: 32000 | E27: =A27*D27 -> 64000 | I27: 28000 | J27: =I27*A27 -> 56000 | K27: =E27-J27 -> 8000 | L27: =K27/E27 -> 0.125
A28: 1 | B28: KG | C28: JENGIBRE | D28: 12000 | E28: =A28*D28 -> 12000 | I28: 9000 | J28: =I28*A28 -> 9000 | K28: =E28-J28 -> 3000 | L28: =K28/E28 -> 0.25
A29: 3 | B29: ATADO | C29: CEBOLLA DE VERDEO | D29: 5000 | E29: =A29*D29 -> 15000 | I29: 3400 | J29: =I29*A29 -> 10200 | K29: =E29-J29 -> 4800 | L29: =K29/E29 -> 0.32
A30: 3 | B30: KG | C30: LIMA | D30: 4000 | E30: =A30*D30 -> 12000 | I30: 3000 | J30: =I30*A30 -> 9000 | K30: =E30-J30 -> 3000 | L30: =K30/E30 -> 0.25
E32: =SUM(E21:E31) -> 238800 | K32: =SUM(K21:K30) -> 48600 | L32: =K32/E32 -> 0.20351759
A37: RAKUS CAFE - PADUA | D37: rto: 23 | E37: 46070
A39: CANTIDAD | B39: UNIDAD | C39: PRODUCTO | D39: PRECIO | E39: TOTAL | J39: TOTAL | K39: DIFERENCIA
A40: 1.6 | B40: KG | C40: REPOLLO COLORADO | D40: 1800 | E40: =A40*D40 -> 2880 | I40: 1000 | J40: =I40*A40 -> 1600 | K40: =E40-J40 -> 1280
A41: 4 | B41: ATADO | C41: ALBAHACA | D41: 1000 | E41: =A41*D41 -> 4000 | I41: 600 | J41: =I41*A41 -> 2400 | K41: =E41-J41 -> 1600 | L41: =K41/E41 -> 0.4
A42: 12 | B42: UNIDAD | C42: AJO | D42: 900 | E42: =A42*D42 -> 10800 | I42: 560 | J42: =I42*A42 -> 6720 | K42: =E42-J42 -> 4080 | L42: =K42/E42 -> 0.37777778
A43: 0.5 | B43: KG | C43: CEBOLLA DE VERDEO | D43: 5000 | E43: =A43*D43 -> 2500 | I43: 3400 | J43: =I43*A43 -> 1700 | K43: =E43-J43 -> 800 | L43: =K43/E43 -> 0.32
A44: 9 | B44: CUBETAS | C44: ARANDANOS | D44: 2500 | E44: =A44*D44 -> 22500 | I44: 2000 | J44: =I44*A44 -> 18000 | K44: =E44-J44 -> 4500 | L44: =K44/E44 -> 0.2
A45: 3 | B45: KG | C45: MORRON ROJO | D45: 4500 | E45: =A45*D45 -> 13500 | I45: =26000/7 -> 3714.2857 | J45: =I45*A45 -> 11142.857 | K45: =E45-J45 -> 2357.1429 | L45: =K45/E45 -> 0.17460317
A46: 1 | B46: KG | C46: DURAZNO | D46: 4000 | E46: =A46*D46 -> 4000 | H46: s/c | J46: =I46*A46 -> 0 | K46: =E46-J46 -> 4000 | L46: =K46/E46 -> 1
A47: 5 | B47: ATADO | C47: RUCULA | D47: 400 | E47: =A47*D47 -> 2000 | I47: =4000/24 -> 166.66667 | J47: =I47*A47 -> 833.33333 | K47: =E47-J47 -> 1166.6667 | L47: =K47/E47 -> 0.58333333
A48: 3 | B48: KG | C48: TOMATE CHERRY | D48: 3500 | E48: =A48*D48 -> 10500 | I48: =16000/7 -> 2285.7143 | J48: =I48*A48 -> 6857.1429 | K48: =E48-J48 -> 3642.8571 | L48: =K48/E48 -> 0.34693878
A49: 2 | B49: KG | C49: FRUTILLA | D49: 5500 | E49: =A49*D49 -> 11000 | I49: =20000/5 -> 4000 | J49: =I49*A49 -> 8000 | K49: =E49-J49 -> 3000 | L49: =K49/E49 -> 0.27272727
A50: 3 | B50: CAJON | C50: NARANJA DE JUGO SIN SEMILLA | D50: 23000 | E50: =A50*D50 -> 69000 | I50: 20000 | J50: =I50*A50 -> 60000 | K50: =E50-J50 -> 9000 | L50: =K50/E50 -> 0.13043478
A51: 1 | B51: CAJA | C51: LIMON | D51: 32000 | E51: =A51*D51 -> 32000 | I51: 28000 | J51: =I51*A51 -> 28000 | K51: =E51-J51 -> 4000 | L51: =K51/E51 -> 0.125
A52: 1 | B52: ATADO | C52: MENTA | D52: 3000 | E52: =A52*D52 -> 3000 | I52: 2000 | J52: =I52*A52 -> 2000 | K52: =E52-J52 -> 1000 | L52: =K52/E52 -> 0.33333333
E54: =SUM(E40:E53) -> 187680 | K54: =SUM(K40:K52) -> 40426.667 | L54: =K54/E54 -> 0.2154021
A57: S&T CATERING | D57: rto: 6 | E57: 46070
A59: CANTIDAD | B59: CAJON | C59: PRODUCTO | D59: PRECIO | E59: TOTAL | I59: PRECIO | J59: TOTAL | K59: DIFERENCIA
A60: 1 | B60: CAJON | C60: LECHUGA | D60: 13000 | E60: =A60*D60 -> 13000 | I60: 8000 | J60: =I60*A60 -> 8000 | K60: =E60-J60 -> 5000 | L60: =K60/E60 -> 0.38461538
A61: 1 | B61: CAJON | C61: ESPIANCA | D61: 16000 | E61: =A61*D61 -> 16000 | I61: 13000 | J61: =I61*A61 -> 13000 | K61: =E61-J61 -> 3000 | L61: =K61/E61 -> 0.1875
A62: 1 | B62: CAJON | C62: TOMATE CHERRY | D62: 22000 | E62: =A62*D62 -> 22000 | I62: 16000 | J62: =I62*A62 -> 16000 | K62: =E62-J62 -> 6000 | L62: =K62/E62 -> 0.27272727
A63: 1 | B63: CAJON | C63: TOMATE PERITA | D63: 28000 | E63: =A63*D63 -> 28000 | I63: 24000 | J63: =I63*A63 -> 24000 | K63: =E63-J63 -> 4000 | L63: =K63/E63 -> 0.14285714
A64: 3 | B64: BOLSA | C64: BONIATO | D64: 27000 | E64: =A64*D64 -> 81000 | I64: 21000 | J64: =I64*A64 -> 63000 | K64: =E64-J64 -> 18000 | L64: =K64/E64 -> 0.22222222
A65: 3 | B65: BOLSA | C65: BATATA | D65: 13000 | E65: =A65*D65 -> 39000 | I65: 9000 | J65: =I65*A65 -> 27000 | K65: =E65-J65 -> 12000 | L65: =K65/E65 -> 0.30769231
A66: 1 | B66: CAJON | C66: CHAMPIGNON | D66: 90000 | E66: =A66*D66 -> 90000 | I66: 80000 | J66: =I66*A66 -> 80000 | K66: =E66-J66 -> 10000 | L66: =K66/E66 -> 0.11111111
A67: 10 | B67: BOLSA | C67: ANCO | D67: 12000 | E67: =A67*D67 -> 120000 | I67: 8000 | J67: =I67*A67 -> 80000 | K67: =E67-J67 -> 40000 | L67: =K67/E67 -> 0.33333333
A68: 2 | B68: ATADO | C68: PEREJIL | D68: 3000 | E68: =A68*D68 -> 6000 | I68: 2000 | J68: =I68*A68 -> 4000 | K68: =E68-J68 -> 2000 | L68: =K68/E68 -> 0.33333333
A69: 6 | B69: BOLSA | C69: ZANAHORIA INDUSTRIAL | D69: 16000 | E69: =A69*D69 -> 96000 | I69: 10000 | J69: =I69*A69 -> 60000 | K69: =E69-J69 -> 36000 | L69: =K69/E69 -> 0.375
A70: 5 | B70: BOLSA | C70: CEBOLLON | D70: 11000 | E70: =A70*D70 -> 55000 | I70: 8000 | J70: =I70*A70 -> 40000 | K70: =E70-J70 -> 15000 | L70: =K70/E70 -> 0.27272727
A71: 2 | B71: CAJON | C71: BERENJENA | D71: 10000 | E71: =A71*D71 -> 20000 | I71: 7000 | J71: =I71*A71 -> 14000 | K71: =E71-J71 -> 6000 | L71: =K71/E71 -> 0.3
... A82: 0.5 | B82: CAJON | C82: MANZANA ROJA | D82: 70000 | E82: =A82*D82 -> 35000 | I82: 65000 | J82: =I82*A82 -> 32500 | K82: =E82-J82 -> 2500 | L82: =K82/E82 -> 0.071428571
F83: =186+279+922 -> 1387
E84: =SUM(E60:E83) -> 922500 | K84: =SUM(K60:K82) -> 219200 | L84: =K84/E84 -> 0.23761518
A87: COMO SIEMPRE LAGUNA | D87: rto: 30 | E87: 46070
A89: CANTIDAD | B89: UNIDAD | C89: PRODUCTO | D89: PRECIO | E89: TOTAL | I89: PRECIO | J89: TOTAL | K89: DIFERENCIA
A90: 7 | B90: KG | C90: BONIATO | D90: 2800 | E90: =A90*D90 -> 19600 | I90: =21000/11 -> 1909.0909 | J90: =I90*A90 -> 13363.636 | K90: =E90-J90 -> 6236.3636 | L90: =K90/E90 -> 0.31818182
A91: 6 | B91: KG | C91: TOMATE PERITA | D91: 2200 | E91: =A91*D91 -> 13200 | I91: =24000/15 -> 1600 | J91: =I91*A91 -> 9600 | K91: =E91-J91 -> 3600 | L91: =K91/E91 -> 0.27272727
A92: 1 | B92: PAQUETE | C92: ENELDO | D92: 3000 | E92: =A92*D92 -> 3000 | I92: 2000 | J92: =I92*A92 -> 2000 | K92: =E92-J92 -> 1000 | L92: =K92/E92 -> 0.33333333
A93: 2 | B93: UNIDAD | C93: COLIFLOR | D93: 2000 | E93: =A93*D93 -> 4000 | H93: S/C | J93: =I93*A93 -> 0 | K93: =E93-J93 -> 4000 | L93: =K93/E93 -> 1
A94: 3 | B94: KG | C94: MANGO | D94: 2500 | E94: =A94*D94 -> 7500 | I94: =20000/12 -> 1666.6667 | J94: =I94*A94 -> 5000 | K94: =E94-J94 -> 2500 | L94: =K94/E94 -> 0.33333333
A95: 0.25 | B95: KG | C95: JENGIBRE | D95: 12000 | E95: =A95*D95 -> 3000 | I95: 9000 | J95: =I95*A95 -> 2250 | K95: =E95-J95 -> 750 | L95: =K95/E95 -> 0.25
A96: 2 | B96: KG | C96: CHAMPIGNON | D96: 21000 | E96: =A96*D96 -> 42000 | I96: 18000 | J96: =I96*A96 -> 36000 | K96: =E96-J96 -> 6000 | L96: =K96/E96 -> 0.14285714
A97: 2 | B97: CAJON | C97: PORTOBELLOS | D97: 23000 | E97: =A97*D97 -> 46000 | I97: 20000 | J97: =I97*A97 -> 40000 | K97: =E97-J97 -> 6000 | L97: =K97/E97 -> 0.13043478
A98: 1 | B98: CAJON | C98: LECHUGA FRANCESA | D98: 14000 | E98: =A98*D98 -> 14000 | I98: 8000 | J98: =I98*A98 -> 8000 | K98: =E98-J98 -> 6000 | L98: =K98/E98 -> 0.42857143
A99: 1 | B99: CAJON | C99: LECHUGA MORADA | D99: 13000 | E99: =A99*D99 -> 13000 | I99: =10500 -> 10500 | J99: =I99*A99 -> 10500 | K99: =E99-J99 -> 2500 | L99: =K99/E99 -> 0.19230769
A100: 1 | B100: CJAON | C100: RUCULA | D100: 9000 | E100: =A100*D100 -> 9000 | I100: 4000 | J100: =I100*A100 -> 4000 | K100: =E100-J100 -> 5000 | L100: =K100/E100 -> 0.55555556
A101: 5 | B101: CAJON | C101: ESPINACA | D101: 16000 | E101: =A101*D101 -> 80000 | I101: 13000 | J101: =I101*A101 -> 65000 | K101: =E101-J101 -> 15000 | L101: =K101/E101 -> 0.1875
A102: 2 | B102: BOLSA | C102: PAPA LAVADA | D102: 22000 | E102: =A102*D102 -> 44000 | I102: 18500 | J102: =I102*A102 -> 37000 | K102: =E102-J102 -> 7000 | L102: =K102/E102 -> 0.15909091
A103: 2 | B103: UNIDAD | C103: ALBAHACA | D103: 1000 | E103: =A103*D103 -> 2000 | I103: 600 | J103: =I103*A103 -> 1200 | K103: =E103-J103 -> 800 | L103: =K103/E103 -> 0.4
A104: 1 | B104: ATADO | C104: PUERRO | D104: 6000 | E104: =A104*D104 -> 6000 | I104: 3500 | J104: =I104*A104 -> 3500 | K104: =E104-J104 -> 2500 | L104: =K104/E104 -> 0.41666667
A105: 1 | B105: ATADO | C105: APIO | D105: 2500 | E105: =A105*D105 -> 2500 | I105: 1500 | J105: =I105*A105 -> 1500 | K105: =E105-J105 -> 1000 | L105: =K105/E105 -> 0.4
A106: 6 | B106: UNIDAD | C106: AJO | D106: 1200 | E106: =A106*D106 -> 7200 | I106: 560 | J106: =I106*A106 -> 3360 | K106: =E106-J106 -> 3840 | L106: =K106/E106 -> 0.53333333
A107: 4 | B107: KG | C107: MORRON ROJO | D107: 4500 | E107: =A107*D107 -> 18000 | I107: =26000/7 -> 3714.2857 | J107: =I107*A107 -> 14857.143 | K107: =E107-J107 -> 3142.8571 | L107: =K107/E107 -> 0.17460317
A108: 1 | B108: KG | C108: MORRON VERDE | D108: 3000 | E108: =A108*D108 -> 3000 | I108: =12000/8 -> 1500 | J108: =I108*A108 -> 1500 | K108: =E108-J108 -> 1500 | L108: =K108/E108 -> 0.5
A109: 1 | B109: KG | C109: MORRON AMARILLO | D109: 4000 | E109: =A109*D109 -> 4000 | I109: =20000/8 -> 2500 | J109: =I109*A109 -> 2500 | K109: =E109-J109 -> 1500 | L109: =K109/E109 -> 0.375
A110: 6 | B110: KG | C110: CEBOLLA MORADA | D110: 1600 | E110: =A110*D110 -> 9600 | I110: =13000/15 -> 866.66667 | J110: =I110*A110 -> 5200 | K110: =E110-J110 -> 4400 | L110: =K110/E110 -> 0.45833333
A111: 1 | B111: BOLSA | C111: CEBOLLA | D111: 800 | E111: =A111*D111 -> 800 | I111: =8000/17 -> 470.58824 | J111: =I111*A111 -> 470.58824 | K111: =E111-J111 -> 329.41176 | L111: =K111/E111 -> 0.41176471
A112: 1.5 | B112: KG | C112: LIMA | D112: 4000 | E112: =A112*D112 -> 6000 | I112: 3000 | J112: =I112*A112 -> 4500 | K112: =E112-J112 -> 1500 | L112: =K112/E112 -> 0.25
A113: 1 | B113: ATADO | C113: TOMILLO | D113: 3000 | E113: =A113*D113 -> 3000 | I113: 2000 | J113: =I113*A113 -> 2000 | K113: =E113-J113 -> 1000 | L113: =K113/E113 -> 0.33333333
A114: 12 | B114: UNIDAD | C114: PALTA | D114: 1400 | E114: =A114*D114 -> 16800 | I114: =65000/70 -> 928.57143 | J114: =I114*A114 -> 11142.857 | K114: =E114-J114 -> 5657.1429 | L114: =K114/E114 -> 0.33673469
A115: 1 | B115: ATADO | C115: CIBOULETTE | D115: 3500 | E115: =A115*D115 -> 3500 | I115: 2500 | J115: =I115*A115 -> 2500 | K115: =E115-J115 -> 1000 | L115: =K115/E115 -> 0.28571429
A116: 1 | B116: CAJON | C116: TOMATE CHERRY | D116: 28000 | E116: =A116*D116 -> 28000 | I116: 16000 | J116: =I116*A116 -> 16000 | K116: =E116-J116 -> 12000 | L116: =K116/E116 -> 0.42857143
A117: 0.5 | B117: CAJON | C117: NARANJA JUGO COMERCIAL | D117: 18000 | E117: =A117*D117 -> 9000 | I117: 15000 | J117: =I117*A117 -> 7500 | K117: =E117-J117 -> 1500 | L117: =K117/E117 -> 0.16666667
A118: 1 | B118: CAJON | C118: LIMON | D118: 32000 | E118: =A118*D118 -> 32000 | I118: 28000 | J118: =I118*A118 -> 28000 | K118: =E118-J118 -> 4000 | L118: =K118/E118 -> 0.125
A119: 0.5 | B119: KG | C119: PEPINO | D119: 1500 | E119: =A119*D119 -> 750 | I119: 1000 | J119: =I119*A119 -> 500 | K119: =E119-J119 -> 250 | L119: =K119/E119 -> 0.33333333
E121: =SUM(E90:E120) -> 450450 | K121: =SUM(K90:K119) -> 111505.78 | L121: =K121/E121 -> 0.24754307
A124: MESTIZO | D124: rto: 13 | E124: 46070
A126: CANTIDAD | B126: UNIDAD | C126: PRODUCTO | D126: PRECIO | E126: TOTAL | I126: PRECIO | J126: TOTAL | K126: DIFERENCIA
A127: 1 | B127: BOLSA | C127: CEBOLLA | D127: 13000 | E127: =A127*D127 -> 13000 | I127: 8000 | J127: =I127*A127 -> 8000 | K127: =E127-J127 -> 5000 | L127: =K127/E127 -> 0.38461538
A128: 6 | B128: KG | C128: MORRON ROJO | D128: 4500 | E128: =A128*D128 -> 27000 | I128: =26000/8 -> 3250 | J128: =I128*A128 -> 19500 | K128: =E128-J128 -> 7500 | L128: =K128/E128 -> 0.27777778
A129: 4 | B129: KG | C129: MORRON AMARILLO | D129: 4000 | E129: =A129*D129 -> 16000 | I129: =20000/7 -> 2857.1429 | J129: =I129*A129 -> 11428.571 | K129: =E129-J129 -> 4571.4286 | L129: =K129/E129 -> 0.28571429
A130: 4 | B130: KG | C130: MORRON VERDE | D130: 3000 | E130: =A130*D130 -> 12000 | I130: =12000/7 -> 1714.2857 | J130: =I130*A130 -> 6857.1429 | K130: =E130-J130 -> 5142.8571 | L130: =K130/E130 -> 0.42857143
A131: 2 | B131: KG | C131: ZUCCINI | D131: 1500 | E131: =A131*D131 -> 3000 | H131: S/C | I131: 0 | J131: =I131*A131 -> 0 | K131: =E131-J131 -> 3000 | L131: =K131/E131 -> 1
A132: 2 | B132: KG | C132: BERENJENA | D132: 1800 | E132: =A132*D132 -> 3600 | I132: =7000/8 -> 875 | J132: =I132*A132 -> 1750 | K132: =E132-J132 -> 1850 | L132: =K132/E132 -> 0.51388889
A133: 5 | B133: KG | C133: ZANAHORIA | D133: 1500 | E133: =A133*D133 -> 7500 | I133: =8000/9 -> 888.88889 | J133: =I133*A133 -> 4444.4444 | K133: =E133-J133 -> 3055.5556 | L133: =K133/E133 -> 0.40740741
A134: 1 | B134: CAJON | C134: RUCULA | D134: 9000 | E134: =A134*D134 -> 9000 | I134: 4000 | J134: =I134*A134 -> 4000 | K134: =E134-J134 -> 5000 | L134: =K134/E134 -> 0.55555556
...

Sheet 18-02-2026 
A2: COLEGIO WASHINGTON - LACROZE 1973 | E2: rto: 2 | F2: 46071 | G2: ** | I2: COMPRA
A4: CANTIDAD | B4: UNIDAD | C4: PRODUCTO | D4: PRECIO | E4: TOTAL | F4: TOTAL + IVA | I4: COSTO | J4: TOTAL | K4: DIFERENCIA
A5: 20 | B5: ATADO | C5: RUCULA | D5: 500 | E5: =A5*D5 -> 10000 | F5: =E5*1.105 -> 11050 | I5: =6000/24 -> 250 | J5: =I5*A5 -> 5000 | K5: =F5-J5 -> 6050 | L5: =IFERROR(K5/E5, 0) -> 0.605
A6: 2 | B6: KG | C6: LECHUGA CRIOLLA | D6: 3500 | E6: =A6*D6 -> 7000 | F6: =E6*1.105 -> 7735 | I6: =9000/5 -> 1800 | J6: =I6*A6 -> 3600 | K6: =F6-J6 -> 4135 | L6: =IFERROR(K6/E6, 0) -> 0.59071429
A7: 5 | B7: KG | C7: TOMATE PERITA | D7: 2600 | E7: =A7*D7 -> 13000 | F7: =E7*1.105 -> 14365 | I7: =28000/15 -> 1866.6667 | J7: =I7*A7 -> 9333.3333 | K7: =F7-J7 -> 5031.6667 | L7: =IFERROR(K7/E7, 0) -> 0.38705128
A8: 1 | B8: ATADO | C8: CEBOLLA DE VERDEO | D8: 5000 | E8: =A8*D8 -> 5000 | F8: =E8*1.105 -> 5525 | I8: 3000 | J8: =I8*A8 -> 3000 | K8: =F8-J8 -> 2525 | L8: =IFERROR(K8/E8, 0) -> 0.505
A9: 4 | B9: UNIDAD | C9: BROCOLI | D9: 2500 | E9: =A9*D9 -> 10000 | F9: =E9*1.105 -> 11050 | I9: =6400/4 -> 1600 | J9: =I9*A9 -> 6400 | K9: =F9-J9 -> 4650 | L9: =IFERROR(K9/E9, 0) -> 0.465
A10: 1 | B10: KG | C10: BANANA ECUADOR | D10: 2800 | E10: =A10*D10 -> 2800 | F10: =E10*1.105 -> 3094 | I10: =39000/18 -> 2166.6667 | J10: =I10*A10 -> 2166.6667 | K10: =F10-J10 -> 927.33333 | L10: =IFERROR(K10/E10, 0) -> 0.33119048
A11: 2 | B11: ATADO | C11: ALBAHACA | D11: 1000 | E11: =A11*D11 -> 2000 | F11: =E11*1.105 -> 2210 | I11: 600 | J11: =I11*A11 -> 1200 | K11: =F11-J11 -> 1010 | L11: =IFERROR(K11/E11, 0) -> 0.505
E13: =SUM(E5:E11) -> 49800 | F13: =SUM(F5:F11) -> 55029 | K13: =SUM(K5:K11) -> 24329 | L13: =IFERROR(K13/E13, 0) -> 0.48853414
A16: COLEGIO SAN JAVIER - JOSE A CABRERA 5901 | E16: rto: 2 | F16: 46071 | G16: ** | I16: COMPRA
A18: CANTIDAD | B18: UNIDAD | C18: PRODUCTO | D18: PRECIO | E18: TOTAL | F18: TOTAL + IVA | I18: COSTO | J18: TOTAL | K18: DIFERENCIA
A19: 2 | B19: ATADO | C19: ALBAHACA | D19: 1000 | E19: =A19*D19 -> 2000 | F19: =E19*1.105 -> 2210 | I19: 600 | J19: =I19*A19 -> 1200 | K19: =F19-J19 -> 1010 | L19: =IFERROR(K19/E19, 0) -> 0.505
A20: 3 | B20: KG | C20: BANANA ECUADOR | D20: 2800 | E20: =A20*D20 -> 8400 | F20: =E20*1.105 -> 9282 | I20: =39000/18 -> 2166.6667 | J20: =I20*A20 -> 6500 | K20: =F20-J20 -> 2782 | L20: =IFERROR(K20/E20, 0) -> 0.33119048
A21: 2 | B21: KG | C21: LECHUGA CRIOLLA | D21: 3500 | E21: =A21*D21 -> 7000 | F21: =E21*1.105 -> 7735 | I21: =9000/5 -> 1800 | J21: =I21*A21 -> 3600 | K21: =F21-J21 -> 4135 | L21: =IFERROR(K21/E21, 0) -> 0.59071429
A22: 15 | B22: ATADO | C22: RUCULA | D22: 500 | E22: =A22*D22 -> 7500 | F22: =E22*1.105 -> 8287.5 | I22: 250 | J22: =I22*A22 -> 3750 | K22: =F22-J22 -> 4537.5 | L22: =IFERROR(K22/E22, 0) -> 0.605
A23: 4.35 | B23: KG | C23: REPOLLO COLORADO | D23: 1800 | E23: =A23*D23 -> 7830 | F23: =E23*1.105 -> 8652.15 | I23: 1000 | J23: =I23*A23 -> 4350 | K23: =F23-J23 -> 4302.15 | L23: =IFERROR(K23/E23, 0) -> 0.54944444
A24: 1 | B24: ATADO | C24: CILANTRO | D24: 2000 | E24: =A24*D24 -> 2000 | F24: =E24*1.105 -> 2210 | I24: 2000 | J24: =I24*A24 -> 2000 | K24: =F24-J24 -> 210 | L24: =IFERROR(K24/E24, 0) -> 0.105
E26: =SUM(E19:E24) -> 34730 | F26: =SUM(F19:F24) -> 38376.65 | K26: =SUM(K19:K24) -> 16976.65 | L26: =IFERROR(K26/E26, 0) -> 0.48881802
A29: COLEGIO SJCB - VIRREY DEL PINO 3299 | E29: rto: 4 | F29: 46071 | I29: COMPRA
G30: **
A31: CANTIDAD | B31: UNIDAD | C31: PRODUCTO | D31: PRECIO | E31: TOTAL | F31: TOTAL + IVA | I31: COSTO | J31: TOTAL | K31: DIFERENCIA
A32: 0.75 | B32: ATADO | C32: CEBOLLA DE VERDEO | D32: 5000 | E32: =A32*D32 -> 3750 | F32: =E32*1.105 -> 4143.75 | I32: 3000 | J32: =I32*A32 -> 2250 | K32: =F32-J32 -> 1893.75 | L32: =IFERROR(K32/E32, 0) -> 0.505
A33: 2 | B33: ATADO | C33: ALBAHACA | D33: 1000 | E33: =A33*D33 -> 2000 | F33: =E33*1.105 -> 2210 | I33: 600 | J33: =I33*A33 -> 1200 | K33: =F33-J33 -> 1010 | L33: =IFERROR(K33/E33, 0) -> 0.505
A34: 3 | B34: KG | C34: BANANA ECUADOR | D34: 2800 | E34: =A34*D34 -> 8400 | F34: =E34*1.105 -> 9282 | I34: =39000/18 -> 2166.6667 | J34: =I34*A34 -> 6500 | K34: =F34-J34 -> 2782 | L34: =IFERROR(K34/E34, 0) -> 0.33119048
A35: 5 | B35: KG | C35: MANDARINA | D35: 3200 | E35: =A35*D35 -> 16000 | F35: =E35*1.105 -> 17680 | I35: =40000/15 -> 2666.6667 | J35: =I35*A35 -> 13333.333 | K35: =F35-J35 -> 4346.6667 | L35: =IFERROR(K35/E35, 0) -> 0.27166667
A36: 1 | B36: ATADO | C36: CILANTRO | D36: 2000 | E36: =A36*D36 -> 2000 | F36: =E36*1.105 -> 2210 | I36: 2000 | J36: =I36*A36 -> 2000 | K36: =F36-J36 -> 210 | L36: =IFERROR(K36/E36, 0) -> 0.105
A37: 0.25 | B37: KG | C37: PEREJIL | D37: 4000 | E37: =A37*D37 -> 1000 | F37: =E37*1.105 -> 1105 | I37: 1500 | J37: =I37*A37 -> 375 | K37: =F37-J37 -> 730 | L37: =IFERROR(K37/E37, 0) -> 0.73
A38: 1.7 | B38: KG | C38: REPOLLO COLORADO | D38: 1800 | E38: =A38*D38 -> 3060 | F38: =E38*1.105 -> 3381.3 | I38: 1000 | J38: =I38*A38 -> 1700 | K38: =F38-J38 -> 1681.3 | L38: =IFERROR(K38/E38, 0) -> 0.54944444
A39: 1.5 | B39: KG | C39: LECHUGA CRIOLLA | D39: 3500 | E39: =A39*D39 -> 5250 | F39: =E39*1.105 -> 5801.25 | I39: =9000/5 -> 1800 | J39: =I39*A39 -> 2700 | K39: =F39-J39 -> 3101.25 | L39: =IFERROR(K39/E39, 0) -> 0.59071429
A40: 14 | B40: ATADO | C40: RUCULA | D40: 500 | E40: =A40*D40 -> 7000 | F40: =E40*1.105 -> 7735 | I40: =6000/24 -> 250 | J40: =I40*A40 -> 3500 | K40: =F40-J40 -> 4235 | L40: =IFERROR(K40/E40, 0) -> 0.605
E42: =SUM(E32:E40) -> 48460 | F42: =SUM(F32:F40) -> 53548.3 | K42: =SUM(K32:K40) -> 19989.967 | L42: =IFERROR(K42/E42, 0) -> 0.41250447
A45: COLEGIO ST. MATTHEWS - MOLDES 1469, BELGRANO | E45: rto: 2 | F45: 46071 | G45: ** | I45: COMPRA
A47: CANTIDAD | B47: UNIDAD | C47: PRODUCTO | D47: PRECIO | E47: TOTAL | F47: TOTAL + IVA | I47: COSTO | J47: TOTAL | K47: DIFERENCIA
A48: 2 | B48: KG | C48: LECHUGA CRIOLLA | D48: 3500 | E48: =A48*D48 -> 7000 | F48: =E48*1.105 -> 7735 | I48: =9000/5 -> 1800 | J48: =I48*A48 -> 3600 | K48: =F48-J48 -> 4135 | L48: =IFERROR(K48/E48, 0) -> 0.59071429
A49: 8 | B49: ATADO | C49: RUCULA | D49: 500 | E49: =A49*D49 -> 4000 | F49: =E49*1.105 -> 4420 | I49: =6000/24 -> 250 | J49: =I49*A49 -> 2000 | K49: =F49-J49 -> 2420 | L49: =IFERROR(K49/E49, 0) -> 0.605
A50: 1 | B50: KG | C50: CEBOLLA DE VERDEO | D50: 5000 | E50: =A50*D50 -> 5000 | F50: =E50*1.105 -> 5525 | I50: 3000 | J50: =I50*A50 -> 3000 | K50: =F50-J50 -> 2525 | L50: =IFERROR(K50/E50, 0) -> 0.505
A51: 1 | B51: ATADO | C51: CIBOULETTE | D51: 3000 | E51: =A51*D51 -> 3000 | F51: =E51*1.105 -> 3315 | I51: 2500 | J51: =I51*A51 -> 2500 | K51: =F51-J51 -> 815 | L51: =IFERROR(K51/E51, 0) -> 0.27166667
A52: 0.5 | B52: ATADO | C52: PEREJIL | D52: 4000 | E52: =A52*D52 -> 2000 | F52: =E52*1.105 -> 2210 | I52: 1500 | J52: =I52*A52 -> 750 | K52: =F52-J52 -> 1460 | L52: =IFERROR(K52/E52, 0) -> 0.73
A53: 1 | B53: KG | C53: BANANA ECUADOR | D53: 2800 | E53: =A53*D53 -> 2800 | F53: =E53*1.105 -> 3094 | I53: =39000/18 -> 2166.6667 | J53: =I53*A53 -> 2166.6667 | K53: =F53-J53 -> 927.33333 | L53: =IFERROR(K53/E53, 0) -> 0.33119048
E55: =SUM(E48:E53) -> 23800 | F55: =SUM(F48:F53) -> 26299 | K55: =SUM(K48:K53) -> 12282.333 | L55: =IFERROR(K55/E55, 0) -> 0.51606443
A58: COLEGIO VILLA DEVOTO SCHOOL - PEDRO MORAN 4441 | E58: rto: 4 | F58: 46071 | G58: ** | I58: COMPRA
A60: CANTIDAD | B60: UNIDAD | C60: PRODUCTO | D60: PRECIO | E60: TOTAL | F60: TOTAL + IVA | I60: COSTO | J60: TOTAL | K60: DIFERENCIA
A61: 2 | B61: UNIDAD | C61: PALTA | D61: 1400 | E61: =A61*D61 -> 2800 | F61: =E61*1.105 -> 3094 | I61: =65000/70 -> 928.57143 | J61: =I61*A61 -> 1857.1429 | K61: =F61-J61 -> 1236.8571 | L61: =IFERROR(K61/E61, 0) -> 0.44173469
A62: 14 | B62: ATADO | C62: RUCULA | D62: 500 | E62: =A62*D62 -> 7000 | F62: =E62*1.105 -> 7735 | I62: =6000/24 -> 250 | J62: =I62*A62 -> 3500 | K62: =F62-J62 -> 4235 | L62: =IFERROR(K62/E62, 0) -> 0.605
A63: 2 | B63: KG | C63: LECHUGA CRIOLLA | D63: 3500 | E63: =A63*D63 -> 7000 | F63: =E63*1.105 -> 7735 | I63: =9000/5 -> 1800 | J63: =I63*A63 -> 3600 | K63: =F63-J63 -> 4135 | L63: =IFERROR(K63/E63, 0) -> 0.59071429
A64: 1.85 | B64: KG | C64: REPOLLO MORADO | D64: 1800 | E64: =A64*D64 -> 3330 | F64: =E64*1.105 -> 3679.65 | I64: 1000 | J64: =I64*A64 -> 1850 | K64: =F64-J64 -> 1829.65 | L64: =IFERROR(K64/E64, 0) -> 0.54944444
A65: 4 | B65: KG | C65: BANANA ECUADOR | D65: 2800 | E65: =A65*D65 -> 11200 | F65: =E65*1.105 -> 12376 | I65: =39000/18 -> 2166.6667 | J65: =I65*A65 -> 8666.6667 | K65: =F65-J65 -> 3709.3333 | L65: =IFERROR(K65/E65, 0) -> 0.33119048
E67: =SUM(E61:E65) -> 31330 | F67: =SUM(F61:F65) -> 34619.65 | K67: =SUM(K61:K65) -> 15145.84 | L67: =IFERROR(K67/E67, 0) -> 0.48342932
A70: MUNCHIS | E70: rto: 4 | F70: 46071 | G70: ** | I70: COMPRA
A72: CANTIDAD | B72: UNIDAD | C72: PRODUCTO | D72: PRECIO | E72: TOTAL | F72: TOTAL + IVA | I72: COSTO | J72: TOTAL | K72: DIFERENCIA
A73: 2 | B73: KG | C73: BANANA ECUADOR | D73: 3000 | E73: =A73*D73 -> 6000 | F73: =E73*1.105 -> 6630 | I73: =39000/18 -> 2166.6667 | J73: =I73*A73 -> 4333.3333 | K73: =F73-J73 -> 2296.6667 | L73: =IFERROR(K73/E73, 0) -> 0.38277778
A74: 0.5 | B74: KG | C74: LECHUGA MORADA | D74: 3500 | E74: =A74*D74 -> 1750 | F74: =E74*1.105 -> 1933.75 | H74: S/C | I74: 0 | J74: =I74*A74 -> 0 | K74: =F74-J74 -> 1933.75 | L74: =IFERROR(K74/E74, 0) -> 1.105
A75: 0.5 | B75: KG | C75: LECHUGA CRIOLLA | D75: 3500 | E75: =A75*D75 -> 1750 | F75: =E75*1.105 -> 1933.75 | I75: =9000/5 -> 1800 | J75: =I75*A75 -> 900 | K75: =F75-J75 -> 1033.75 | L75: =IFERROR(K75/E75, 0) -> 0.59071429
A76: 0.85 | B76: KG | C76: FRUTILLA | D76: 6500 | E76: =A76*D76 -> 5525 | F76: =E76*1.105 -> 6105.125 | I76: 5000 | J76: =I76*A76 -> 4250 | K76: =F76-J76 -> 1855.125 | L76: =IFERROR(K76/E76, 0) -> 0.33576923
A77: 1 | B77: KG | C77: TOMATE CHERRY | D77: 3500 | E77: =A77*D77 -> 3500 | F77: =E77*1.105 -> 3867.5 | H77: S/C | I77: 0 | J77: =I77*A77 -> 0 | K77: =F77-J77 -> 3867.5 | L77: =IFERROR(K77/E77, 0) -> 1.105
A78: 1 | B78: ATADO | C78: MENTA | D78: 4000 | E78: =A78*D78 -> 4000 | F78: =E78*1.105 -> 4420 | I78: 2000 | J78: =I78*A78 -> 2000 | K78: =F78-J78 -> 2420 | L78: =IFERROR(K78/E78, 0) -> 0.605
A79: 0.25 | B79: ATADO | C79: JENGIBRE | D79: 13000 | E79: =A79*D79 -> 3250 | F79: =E79*1.105 -> 3591.25 | I79: 9000 | J79: =I79*A79 -> 2250 | K79: =F79-J79 -> 1341.25 | L79: =IFERROR(K79/E79, 0) -> 0.41269231
A80: 0.5 | B80: CAJON | C80: LIMON | D80: 36000 | E80: =A80*D80 -> 18000 | F80: =E80*1.105 -> 19890 | I80: 30000 | J80: =I80*A80 -> 15000 | K80: =F80-J80 -> 4890 | L80: =IFERROR(K80/E80, 0) -> 0.27166667
A81: 2 | B81: KG | C81: NARANJA JUGO | D81: 1600 | E81: =A81*D81 -> 3200 | F81: =E81*1.105 -> 3536 | I81: =15000/15 -> 1000 | J81: =I81*A81 -> 2000 | K81: =F81-J81 -> 1536 | L81: =IFERROR(K81/E81, 0) -> 0.48
E83: =SUM(E73:E81) -> 46975 | F83: =SUM(F73:F81) -> 51907.375 | K83: =SUM(K73:K81) -> 21174.042 | L83: =IFERROR(K83/E83, 0) -> 0.45075129
A86: LUSQTOFF | B86: SEDE: MORENO | E86: rto: 3 | F86: 46071 | G86: ** | I86: COMPRA
A88: CANTIDAD | B88: UNIDAD | C88: PRODUCTO | D88: PRECIO | E88: TOTAL | F88: TOTAL + IVA | I88: COSTO | J88: TOTAL | K88: DIFERENCIA
A89: 1 | B89: BOLSA | C89: ANCO | D89: 12000 | E89: =A89*D89 -> 12000 | F89: =E89*1.105 -> 13260 | I89: 8000 | J89: =I89*A89 -> 8000 | K89: =F89-J89 -> 5260 | L89: =IFERROR(K89/E89, 0) -> 0.43833333
A90: 1 | B90: BOLSA | C90: CEBOLLA | D90: 12000 | E90: =A90*D90 -> 12000 | F90: =E90*1.105 -> 13260 | I90: 8000 | J90: =I90*A90 -> 8000 | K90: =F90-J90 -> 5260 | L90: =IFERROR(K90/E90, 0) -> 0.43833333
A91: 1 | B91: CAJON | C91: LECHUGA FRANCESA | D91: 11000 | E91: =A91*D91 -> 11000 | F91: =E91*1.105 -> 12155 | I91: 9000 | J91: =I91*A91 -> 9000 | K91: =F91-J91 -> 3155 | L91: =IFERROR(K91/E91, 0) -> 0.28681818
A92: 3 | B92: KG | C92: ZAPALLITO REDONDO | D92: 1400 | E92: =A92*D92 -> 4200 | F92: =E92*1.105 -> 4641 | I92: =12000/16 -> 750 | J92: =I92*A92 -> 2250 | K92: =F92-J92 -> 2391 | L92: =IFERROR(K92/E92, 0) -> 0.56928571
A93: 2 | B93: KG | C93: TOMATE REDONDO | D93: 2600 | E93: =A93*D93 -> 5200 | F93: =E93*1.105 -> 5746 | I93: =28000/15 -> 1866.6667 | J93: =I93*A93 -> 3733.3333 | K93: =F93-J93 -> 2012.6667 | L93: =IFERROR(K93/E93, 0) -> 0.38705128
A94: 2 | B94: KG | C94: REPOLLO BLANCO | D94: 1800 | E94: =A94*D94 -> 3600 | F94: =E94*1.105 -> 3978 | I94: 1000 | J94: =I94*A94 -> 2000 | K94: =F94-J94 -> 1978 | L94: =IFERROR(K94/E94, 0) -> 0.54944444
A95: 1 | B95: CAJON | C95: HUEVO | D95: 52000 | E95: =A95*D95 -> 52000 | F95: =E95*1.21 -> 62920 | I95: 48000 | J95: =I95*A95 -> 48000 | K95: =F95-J95 -> 14920 | L95: =IFERROR(K95/E95, 0) -> 0.28692308
A96: 3 | B96: KG | C96: ZANAHORIA | D96: 1400 | E96: =A96*D96 -> 4200 | F96: =E96*1.105 -> 4641 | I96: =8000/9 -> 888.88889 | J96: =I96*A96 -> 2666.6667 | K96: =F96-J96 -> 1974.3333 | L96: =IFERROR(K96/E96, 0) -> 0.47007937
A97: 4 | B97: CAJON | C97: ACELGA | D97: 16000 | E97: =A97*D97 -> 64000 | F97: =E97*1.105 -> 70720 | I97: 12000 | J97: =I97*A97 -> 48000 | K97: =F97-J97 -> 22720 | L97: =IFERROR(K97/E97, 0) -> 0.355
E99: =SUM(E89:E97) -> 168200 | F99: =SUM(F89:F97) -> 191321 | K99: =SUM(K89:K97) -> 59671 | L99: =IFERROR(K99/E99, 0) -> 0.35476219
A101: Comisión Juan | B101: 0.04 | E101: =E99*0.04 -> 6728
A104: LUSQTOFF | B104: SEDE: IRALA | E104: rto: 6 | F104: 46071 | G104: ** | I104: COMPRA
A106: CANTIDAD | B106: UNIDAD | C106: PRODUCTO | D106: PRECIO | E106: TOTAL | F106: TOTAL + IVA | I106: COSTO | J106: TOTAL | K106: DIFERENCIA
A107: 1 | B107: CAJON | C107: HUEVO | D107: 52000 | E107: =A107*D107 -> 52000 | F107: =E107*1.21 -> 62920 | I107: 48000 | J107: =I107*A107 -> 48000 | K107: =F107-J107 -> 14920 | L107: =IFERROR(K107/E107, 0) -> 0.28692308
A108: 1 | B108: BOLSA | C108: CEBOLLA | D108: 12000 | E108: =A108*D108 -> 12000 | F108: =E108*1.105 -> 13260 | I108: 8000 | J108: =I108*A108 -> 8000 | K108: =F108-J108 -> 5260 | L108: =IFERROR(K108/E108, 0) -> 0.43833333
A109: 1 | B109: BOLSA | C109: ZANAHORIA | D109: 12000 | E109: =A109*D109 -> 12000 | F109: =E109*1.105 -> 13260 | I109: 8000 | J109: =I109*A109 -> 8000 | K109: =F109-J109 -> 5260 | L109: =IFERROR(K109/E109, 0) -> 0.43833333
A110: 3 | B110: KG | C110: TOMATE REDONDO | D110: 2600 | E110: =A110*D110 -> 7800 | F110: =E110*1.105 -> 8619 | I110: =28000/15 -> 1866.6667 | J110: =I110*A110 -> 5600 | K110: =F110-J110 -> 3019 | L110: =IFERROR(K110/E110, 0) -> 0.38705128
A111: 2 | B111: KG | C111: MORRON VERDE | D111: 3000 | E111: =A111*D111 -> 6000 | F111: =E111*1.105 -> 6630 | I111: =12000/8 -> 1500 | J111: =I111*A111 -> 3000 | K111: =F111-J111 -> 3630 | L111: =IFERROR(K111/E111, 0) -> 0.605
A112: 2 | B112: KG | C112: MORRON ROJO | D112: 4500 | E112: =A112*D112 -> 9000 | F112: =E112*1.105 -> 9945 | I112: =30000/8 -> 3750 | J112: =I112*A112 -> 7500 | K112: =F112-J112 -> 2445 | L112: =IFERROR(K112/E112, 0) -> 0.27166667
A113: 6 | B113: ATADO | C113: ACELGA | D113: 2000 | E113: =A113*D113 -> 12000 | F113: =E113*1.105 -> 13260 | I113: 1600 | J113: =I113*A113 -> 9600 | K113: =F113-J113 -> 3660 | L113: =IFERROR(K113/E113, 0) -> 0.305
A114: 2 | B114: KG | C114: LECHUGA FRANCESA | D114: 3000 | E114: =A114*D114 -> 6000 | F114: =E114*1.105 -> 6630 | I114: =9000/8 -> 1125 | J114: =I114*A114 -> 2250 | K114: =F114-J114 -> 4380 | L114: =IFERROR(K114/E114, 0) -> 0.73
E116: =SUM(E107:E114) -> 116800 | F116: =SUM(F107:F114) -> 134524 | K116: =SUM(K107:K114) -> 42574 | L116: =IFERROR(K116/E116, 0) -> 0.36450342
A118: Comisión Juan | B118: 0.04 | E118: =E116*0.04 -> 4672
A120: LA PIADINA | D120: rto: 20 | E120: 46071 | G120: **
A122: CANTIDAD | B122: UNIDAD | C122: PRODUCTO | D122: PRECIO | E122: TOTAL | I122: PRECIO | J122: TOTAL | K122: DIFERENCIA | L122: =IFERROR(K122/E122, 0) -> 0
A123: 0.5 | B123: CAJON | C123: RUCULA | D123: 11000 | E123: =A123*D123 -> 5500 | I123: 6000 | J123: =I123*A123 -> 3000 | K123: =E123-J123 -> 2500 | L123: =IFERROR(K123/E123, 0) -> 0.45454545
A124: 2 | B124: ATADO | C124: ESPINACA | D124: 1700 | E124: =A124*D124 -> 3400 | I124: 1400 | J124: =I124*A124 -> 2800 | K124: =E124-J124 -> 600 | L124: =IFERROR(K124/E124, 0) -> 0.17647059
A125: 3 | B125: KG | C125: TOMATE REDONDO | D125: 3000 | E125: =A125*D125 -> 9000 | I125: =28000/15 -> 1866.6667 | J125: =I125*A125 -> 5600 | K125: =E125-J125 -> 3400 | L125: =IFERROR(K125/E125, 0) -> 0.37777778
A126: 1 | B126: KG | C126: BERENJENA | D126: 4000 | E126: =A126*D126 -> 4000 | I126: 1000 | J126: =I126*A126 -> 1000 | K126: =E126-J126 -> 3000 | L126: =IFERROR(K126/E126, 0) -> 0.75
A127: 1 | B127: UNIDAD | C127: AJO | D127: 1000 | E127: =A127*D127 -> 1000 | I127: 560 | J127: =I127*A127 -> 560 | K127: =E127-J127 -> 440 | L127: =IFERROR(K127/E127, 0) -> 0.44
E129: =SUM(E123:E128) -> 22900 | K129: =SUM(K123:K127) -> 9940 | L129: =IFERROR(K129/E129, 0) -> 0.43406114
A133: SAO MEDIALUNAS | B133: SEDE PILAR | D133: rto: 1 | E133: 46071 | G133: **
A135: CANTIDAD | B135: UNIDAD | C135: PRODUCTO | D135: PRECIO | E135: TOTAL | F135: TOTAL + IVA | I135: PRECIO | J135: TOTAL | K135: DIFERENCIA
A136: 1 | B136: CAJA | C136: BANANA ECUADOR | D136: 36000 | E136: =A136*D136 -> 36000 | F136: =E136*1.105 -> 39780 | I136: 28000 | J136: =I136*A136 -> 28000 | K136: =F136-J136 -> 11780 | L136: =IFERROR(K136/E136, 0) -> 0.32722222
E138: =SUM(E136:E137) -> 36000 | F138: =SUM(F136:F137) -> 39780 | K138: =SUM(K136) -> 11780 | L138: =IFERROR(K138/E138, 0) -> 0.32722222
A141: CAFE MARTINEZ | B141: MORENO - GORRITI | D141: rto: 4 | E141: 46071 | G141: **
A143: CANTIDAD | B143: UNIDAD | C143: PRODUCTO | D143: PRECIO | E143: TOTAL | I143: PRECIO | J143: TOTAL | K143: DIFERENCIA
...

Sheet 19-02-2026 
A2: COLCAR | E2: rto: 6 | F2: 46072 | I2: COMPRA
A4: CANTIDAD | B4: UNIDAD | C4: PRODUCTO | D4: PRECIO | E4: TOTAL | F4: TOTAL + IVA | I4: COSTO | J4: TOTAL | K4: DIFERENCIA
A5: 2 | B5: BOLSA | C5: ZANAHORIA | D5: 12000 | E5: =A5*D5 -> 24000 | F5: =E5*1.105 -> 26520 | I5: 8000 | J5: =I5*A5 -> 16000 | K5: =F5-J5 -> 10520 | L5: =IFERROR(K5/E5, 0) -> 0.43833333
A6: 1 | B6: CAJON | C6: MORRON ROJO | D6: 32000 | E6: =A6*D6 -> 32000 | F6: =E6*1.105 -> 35360 | I6: 24000 | J6: =I6*A6 -> 24000 | K6: =F6-J6 -> 11360 | L6: =IFERROR(K6/E6, 0) -> 0.355
A7: 4 | B7: KG | C7: BERENJENA | D7: 1500 | E7: =A7*D7 -> 6000 | F7: =E7*1.105 -> 6630 | I7: 1000 | J7: =I7*A7 -> 4000 | K7: =F7-J7 -> 2630 | L7: =IFERROR(K7/E7, 0) -> 0.43833333
A8: 4 | B8: KG | C8: ZUCCINI | D8: 1200 | E8: =A8*D8 -> 4800 | F8: =E8*1.105 -> 5304 | I8: =9000/15 -> 600 | J8: =I8*A8 -> 2400 | K8: =F8-J8 -> 2904 | L8: =IFERROR(K8/E8, 0) -> 0.605
A9: 8 | B9: BOLSA | C9: PAPA | D9: 15000 | E9: =A9*D9 -> 120000 | F9: =E9*1.105 -> 132600 | I9: 12000 | J9: =I9*A9 -> 96000 | K9: =F9-J9 -> 36600 | L9: =IFERROR(K9/E9, 0) -> 0.305
A10: 3 | B10: CAJA | C10: BANANA ECUADOR | D10: 32000 | E10: =A10*D10 -> 96000 | F10: =E10*1.105 -> 106080 | I10: 28000 | J10: =I10*A10 -> 84000 | K10: =F10-J10 -> 22080 | L10: =IFERROR(K10/E10, 0) -> 0.23
A11: 1 | B11: CAJON | C11: NARANJA JUGO COMERCIAL | D11: 18000 | E11: =A11*D11 -> 18000 | F11: =E11*1.105 -> 19890 | I11: 15000 | J11: =I11*A11 -> 15000 | K11: =F11-J11 -> 4890 | L11: =IFERROR(K11/E11, 0) -> 0.27166667
E13: =SUM(E5:E11) -> 300800 | F13: =SUM(F5:F11) -> 332384 | K13: =SUM(K5:K11) -> 90984 | L13: =IFERROR(K13/E13, 0) -> 0.3024734
A15: Comisión Juan | B15: 0.04 | E15: =E13*0.04 -> 12032
A18: COLEGIO ST CATHERINES MOORLANDS - CARBAJAL 3250 | E18: rto: 4 | F18: 46072 | I18: COMPRA
A20: CANTIDAD | B20: UNIDAD | C20: PRODUCTO | D20: PRECIO | E20: TOTAL | F20: TOTAL + IVA | I20: COSTO | J20: TOTAL | K20: DIFERENCIA
A21: 1 | B21: BOLSA | C21: BATATA | D21: 16000 | E21: =A21*D21 -> 16000 | F21: =E21*1.105 -> 17680 | I21: 11500 | J21: =I21*A21 -> 11500 | K21: =F21-J21 -> 6180 | L21: =IFERROR(K21/E21, 0) -> 0.38625
A22: 1 | B22: ATADO | C22: CILANTRO | D22: 3000 | E22: =A22*D22 -> 3000 | F22: =E22*1.105 -> 3315 | I22: =3500/6 -> 583.33333 | J22: =I22*A22 -> 583.33333 | K22: =F22-J22 -> 2731.6667 | L22: =IFERROR(K22/E22, 0) -> 0.91055556
A23: 1 | B23: ATADO | C23: PEREJIL | D23: 4000 | E23: =A23*D23 -> 4000 | F23: =E23*1.105 -> 4420 | I23: 2000 | J23: =I23*A23 -> 2000 | K23: =F23-J23 -> 2420 | L23: =IFERROR(K23/E23, 0) -> 0.605
A24: 4 | B24: KG | C24: REPOLLO BLANCO | D24: 1800 | E24: =A24*D24 -> 7200 | F24: =E24*1.105 -> 7956 | I24: 800 | J24: =I24*A24 -> 3200 | K24: =F24-J24 -> 4756 | L24: =IFERROR(K24/E24, 0) -> 0.66055556
A25: 3.5 | B25: KG | C25: REPOLLO COLORADO | D25: 1800 | E25: =A25*D25 -> 6300 | F25: =E25*1.105 -> 6961.5 | I25: 800 | J25: =I25*A25 -> 2800 | K25: =F25-J25 -> 4161.5 | L25: =IFERROR(K25/E25, 0) -> 0.66055556
A26: 15 | B26: KG | C26: TOMATE PERITA | D26: 2600 | E26: =A26*D26 -> 39000 | F26: =E26*1.105 -> 43095 | I26: =20000/15 -> 1333.3333 | J26: =I26*A26 -> 20000 | K26: =F26-J26 -> 23095 | L26: =IFERROR(K26/E26, 0) -> 0.59217949
A27: 3 | B27: KG | C27: MORRON AMARILLO | D27: 4000 | E27: =A27*D27 -> 12000 | F27: =E27*1.105 -> 13260 | I27: =25000/8 -> 3125 | J27: =I27*A27 -> 9375 | K27: =F27-J27 -> 3885 | L27: =IFERROR(K27/E27, 0) -> 0.32375
A28: 0.5 | B28: KG | C28: MORRON ROJO | D28: 4000 | E28: =A28*D28 -> 2000 | F28: =E28*1.105 -> 2210 | I28: =24000/8 -> 3000 | J28: =I28*A28 -> 1500 | K28: =F28-J28 -> 710 | L28: =IFERROR(K28/E28, 0) -> 0.355
A29: 4 | B29: KG | C29: CEBOLLA MORADA | D29: 1600 | E29: =A29*D29 -> 6400 | F29: =E29*1.105 -> 7072 | I29: =18000/16 -> 1125 | J29: =I29*A29 -> 4500 | K29: =F29-J29 -> 2572 | L29: =IFERROR(K29/E29, 0) -> 0.401875
A30: 3.5 | B30: KG | C30: CEBOLLA | D30: 800 | E30: =A30*D30 -> 2800 | F30: =E30*1.105 -> 3094 | I30: =8000/17 -> 470.58824 | J30: =I30*A30 -> 1647.0588 | K30: =F30-J30 -> 1446.9412 | L30: =IFERROR(K30/E30, 0) -> 0.51676471
A31: 8 | B31: ATADO | C31: ESPINACA | D31: 1600 | E31: =A31*D31 -> 12800 | F31: =E31*1.105 -> 14144 | I31: 1000 | J31: =I31*A31 -> 8000 | K31: =F31-J31 -> 6144 | L31: =IFERROR(K31/E31, 0) -> 0.48
A32: 3 | B32: KG | C32: BANANA ECUADOR | D32: 2800 | E32: =A32*D32 -> 8400 | F32: =E32*1.105 -> 9282 | I32: =28000/15 -> 1866.6667 | J32: =I32*A32 -> 5600 | K32: =F32-J32 -> 3682 | L32: =IFERROR(K32/E32, 0) -> 0.43833333
A33: 2 | B33: KG | C33: LECHUGA FRANCESA | D33: 2800 | E33: =A33*D33 -> 5600 | F33: =E33*1.105 -> 6188 | I33: =10000/8 -> 1250 | J33: =I33*A33 -> 2500 | K33: =F33-J33 -> 3688 | L33: =IFERROR(K33/E33, 0) -> 0.65857143
A34: 6 | B34: ATADO | C34: RUCULA | D34: 500 | E34: =A34*D34 -> 3000 | F34: =E34*1.105 -> 3315 | I34: =6000/24 -> 250 | J34: =I34*A34 -> 1500 | K34: =F34-J34 -> 1815 | L34: =IFERROR(K34/E34, 0) -> 0.605
E36: =SUM(E21:E34) -> 128500 | F36: =SUM(F21:F34) -> 141992.5 | K36: =SUM(K21:K34) -> 67287.108 | L36: =IFERROR(K36/E36, 0) -> 0.52363508
A39: COLEGIO SWORM JUNIOR COLLAGE | PACHECO | E39: rto: 1 | F39: 46072 | I39: COMPRA
A41: CANTIDAD | B41: UNIDAD | C41: PRODUCTO | D41: PRECIO | E41: TOTAL | F41: TOTAL + IVA | I41: COSTO | J41: TOTAL | K41: DIFERENCIA
A42: 10 | B42: KG | C42: TOMATE PERITA | D42: 2600 | E42: =A42*D42 -> 26000 | F42: =E42*1.105 -> 28730 | I42: 1333 | J42: =I42*A42 -> 13330 | K42: =F42-J42 -> 15400 | L42: =IFERROR(K42/E42, 0) -> 0.59230769
A43: 4.4 | B43: KG | C43: REPOLLO BLANCO | D43: 1800 | E43: =A43*D43 -> 7920 | F43: =E43*1.105 -> 8751.6 | I43: 800 | J43: =I43*A43 -> 3520 | K43: =F43-J43 -> 5231.6 | L43: =IFERROR(K43/E43, 0) -> 0.66055556
A44: 4.9 | B44: KG | C44: REPOLLO COLORADO | D44: 1800 | E44: =A44*D44 -> 8820 | F44: =E44*1.105 -> 9746.1 | I44: 800 | J44: =I44*A44 -> 3920 | K44: =F44-J44 -> 5826.1 | L44: =IFERROR(K44/E44, 0) -> 0.66055556
A45: 6 | B45: KG | C45: MORRON ROJO | D45: 4000 | E45: =A45*D45 -> 24000 | F45: =E45*1.105 -> 26520 | I45: 3000 | J45: =I45*A45 -> 18000 | K45: =F45-J45 -> 8520 | L45: =IFERROR(K45/E45, 0) -> 0.355
A46: 6 | B46: KG | C46: MORRON VERDE | D46: 3100 | E46: =A46*D46 -> 18600 | F46: =E46*1.105 -> 20553 | I46: =12000/8 -> 1500 | J46: =I46*A46 -> 9000 | K46: =F46-J46 -> 11553 | L46: =IFERROR(K46/E46, 0) -> 0.62112903
A47: 6 | B47: KG | C47: MORRON AMARILLO | D47: 4000 | E47: =A47*D47 -> 24000 | F47: =E47*1.105 -> 26520 | I47: 3125 | J47: =I47*A47 -> 18750 | K47: =F47-J47 -> 7770 | L47: =IFERROR(K47/E47, 0) -> 0.32375
A48: 1 | B48: KG | C48: ZUCCINI | D48: 1500 | E48: =A48*D48 -> 1500 | F48: =E48*1.105 -> 1657.5 | H48: S/C | I48: 0 | J48: =I48*A48 -> 0 | K48: =F48-J48 -> 1657.5 | L48: =IFERROR(K48/E48, 0) -> 1.105
A49: 2 | B49: KG | C49: CEBOLLA MORADA | D49: 1600 | E49: =A49*D49 -> 3200 | F49: =E49*1.105 -> 3536 | I49: 1125 | J49: =I49*A49 -> 2250 | K49: =F49-J49 -> 1286 | L49: =IFERROR(K49/E49, 0) -> 0.401875
A50: 1.5 | B50: KG | C50: CEBOLLA | D50: 800 | E50: =A50*D50 -> 1200 | F50: =E50*1.105 -> 1326 | I50: 470 | J50: =I50*A50 -> 705 | K50: =F50-J50 -> 621 | L50: =IFERROR(K50/E50, 0) -> 0.5175
A51: 2 | B51: ATADOS | C51: APIO | D51: 2500 | E51: =A51*D51 -> 5000 | F51: =E51*1.105 -> 5525 | I51: 1500 | J51: =I51*A51 -> 3000 | K51: =F51-J51 -> 2525 | L51: =IFERROR(K51/E51, 0) -> 0.505
A52: 1 | B52: ATADO | C52: PUERRO | D52: 6000 | E52: =A52*D52 -> 6000 | F52: =E52*1.105 -> 6630 | I52: 4000 | J52: =I52*A52 -> 4000 | K52: =F52-J52 -> 2630 | L52: =IFERROR(K52/E52, 0) -> 0.43833333
A53: 1 | B53: ATADO | C53: PEREJIL | D53: 4000 | E53: =A53*D53 -> 4000 | F53: =E53*1.105 -> 4420 | I53: 2000 | J53: =I53*A53 -> 2000 | K53: =F53-J53 -> 2420 | L53: =IFERROR(K53/E53, 0) -> 0.605
A54: 1 | B54: ATADO | C54: CILANTRO | D54: 3000 | E54: =A54*D54 -> 3000 | F54: =E54*1.105 -> 3315 | I54: 583 | J54: =I54*A54 -> 583 | K54: =F54-J54 -> 2732 | L54: =IFERROR(K54/E54, 0) -> 0.91066667
A55: 1 | B55: ATADO | C55: CIBOULETTE | D55: 3000 | E55: =A55*D55 -> 3000 | F55: =E55*1.105 -> 3315 | I55: 2000 | J55: =I55*A55 -> 2000 | K55: =F55-J55 -> 1315 | L55: =IFERROR(K55/E55, 0) -> 0.43833333
A56: 1 | B56: ATADO | C56: CEBOLLA DE VERDEO | D56: 5000 | E56: =A56*D56 -> 5000 | F56: =E56*1.105 -> 5525 | I56: 3500 | J56: =I56*A56 -> 3500 | K56: =F56-J56 -> 2025 | L56: =IFERROR(K56/E56, 0) -> 0.405
A57: 1 | B57: ATADO | C57: ALBAHACA | D57: 1000 | E57: =A57*D57 -> 1000 | F57: =E57*1.105 -> 1105 | I57: 800 | J57: =I57*A57 -> 800 | K57: =F57-J57 -> 305 | L57: =IFERROR(K57/E57, 0) -> 0.305
A58: 1 | B58: KG | C58: ZAPALLITO VERDE | D58: 1200 | E58: =A58*D58 -> 1200 | F58: =E58*1.105 -> 1326 | I58: 0 | J58: =I58*A58 -> 0 | K58: =F58-J58 -> 1326 | L58: =IFERROR(K58/E58, 0) -> 1.105
A59: 1 | B59: KG | C59: REMOLACHA | D59: 1600 | E59: =A59*D59 -> 1600 | F59: =E59*1.105 -> 1768 | I59: 1000 | J59: =I59*A59 -> 1000 | K59: =F59-J59 -> 768 | L59: =IFERROR(K59/E59, 0) -> 0.48
A60: 15 | B60: UNIDAD | C60: CHOCLO | D60: 1100 | E60: =A60*D60 -> 16500 | F60: =E60*1.105 -> 18232.5 | I60: =15000/40 -> 375 | J60: =I60*A60 -> 5625 | K60: =F60-J60 -> 12607.5 | L60: =IFERROR(K60/E60, 0) -> 0.76409091
A61: 3 | B61: UNIDAD | C61: AJO | D61: 900 | E61: =A61*D61 -> 2700 | F61: =E61*1.105 -> 2983.5 | I61: 560 | J61: =I61*A61 -> 1680 | K61: =F61-J61 -> 1303.5 | L61: =IFERROR(K61/E61, 0) -> 0.48277778
A62: 8 | B62: ATADO | C62: ESPINACA | D62: 1600 | E62: =A62*D62 -> 12800 | F62: =E62*1.105 -> 14144 | I62: 1000 | J62: =I62*A62 -> 8000 | K62: =F62-J62 -> 6144 | L62: =IFERROR(K62/E62, 0) -> 0.48
A63: 1.5 | B63: KG | C63: LECHUGA FRANCESA | D63: 2800 | E63: =A63*D63 -> 4200 | F63: =E63*1.105 -> 4641 | I63: =10000/8 -> 1250 | J63: =I63*A63 -> 1875 | K63: =F63-J63 -> 2766 | L63: =IFERROR(K63/E63, 0) -> 0.65857143
A64: 12 | B64: ATADO | C64: RUCULA | D64: 500 | E64: =A64*D64 -> 6000 | F64: =E64*1.105 -> 6630 | I64: =6000/24 -> 250 | J64: =I64*A64 -> 3000 | K64: =F64-J64 -> 3630 | L64: =IFERROR(K64/E64, 0) -> 0.605
A65: 0.5 | B65: KG | C65: TOMATE CHERRY | D65: 3500 | E65: =A65*D65 -> 1750 | F65: =E65*1.105 -> 1933.75 | H65: S/C | I65: 0 | J65: =I65*A65 -> 0 | K65: =F65-J65 -> 1933.75 | L65: =IFERROR(K65/E65, 0) -> 1.105
A66: 2 | B66: UNIDAD | C66: PALTA | D66: 1300 | E66: =A66*D66 -> 2600 | F66: =E66*1.105 -> 2873 | I66: 900 | J66: =I66*A66 -> 1800 | K66: =F66-J66 -> 1073 | L66: =IFERROR(K66/E66, 0) -> 0.41269231
A67: 2 | B67: KG | C67: CHAUCHA REDONDA | D67: 4000 | E67: =A67*D67 -> 8000 | F67: =E67*1.105 -> 8840 | I67: 4000 | J67: =I67*A67 -> 8000 | K67: =F67-J67 -> 840 | L67: =IFERROR(K67/E67, 0) -> 0.105
A68: 5 | B68: BOLSA | C68: PAPA LAVADA | D68: 21000 | E68: =A68*D68 -> 105000 | F68: =E68*1.105 -> 116025 | I68: 18000 | J68: =I68*A68 -> 90000 | K68: =F68-J68 -> 26025 | L68: =IFERROR(K68/E68, 0) -> 0.24785714
A69: 1 | B69: BOLSA | C69: BATATA | D69: 16000 | E69: =A69*D69 -> 16000 | F69: =E69*1.105 -> 17680 | I69: 11500 | J69: =I69*A69 -> 11500 | K69: =F69-J69 -> 6180 | L69: =IFERROR(K69/E69, 0) -> 0.38625
A70: 1 | B70: BOLSA | C70: ZANAHORIA | D70: 12000 | E70: =A70*D70 -> 12000 | F70: =E70*1.105 -> 13260 | I70: 8000 | J70: =I70*A70 -> 8000 | K70: =F70-J70 -> 5260 | L70: =IFERROR(K70/E70, 0) -> 0.43833333
A71: 1 | B71: BOLSA | C71: ANCO | D71: 13000 | E71: =A71*D71 -> 13000 | F71: =E71*1.105 -> 14365 | I71: 8000 | J71: =I71*A71 -> 8000 | K71: =F71-J71 -> 6365 | L71: =IFERROR(K71/E71, 0) -> 0.48961538
A72: 0.5 | B72: CAJON | C72: HUEVO N1 | D72: 52000 | E72: =A72*D72 -> 26000 | F72: =E72*1.21 -> 31460 | I72: 52000 | J72: =I72*A72 -> 26000 | K72: =F72-J72 -> 5460 | L72: =IFERROR(K72/E72, 0) -> 0.21
A73: 1 | B73: CAJON | C73: NARANJA JUGO DE FRIO | D73: 24000 | E73: =A73*D73 -> 24000 | F73: =E73*1.105 -> 26520 | I73: 20000 | J73: =I73*A73 -> 20000 | K73: =F73-J73 -> 6520 | L73: =IFERROR(K73/E73, 0) -> 0.27166667
A74: 4 | B74: KG | C74: BANANA ECUADOR | D74: 2800 | E74: =A74*D74 -> 11200 | F74: =E74*1.105 -> 12376 | I74: =28000/16 -> 1750 | J74: =I74*A74 -> 7000 | K74: =F74-J74 -> 5376 | L74: =IFERROR(K74/E74, 0) -> 0.48
A75: 1 | B75: KG | C75: UVA | D75: 4500 | E75: =A75*D75 -> 4500 | F75: =E75*1.105 -> 4972.5 | I75: 4000 | J75: =I75*A75 -> 4000 | K75: =F75-J75 -> 972.5 | L75: =IFERROR(K75/E75, 0) -> 0.21611111
A76: 3 | B76: KG | C76: MANZANA ROJA | D76: 4500 | E76: =A76*D76 -> 13500 | F76: =E76*1.105 -> 14917.5 | I76: =65000/20 -> 3250 | J76: =I76*A76 -> 9750 | K76: =F76-J76 -> 5167.5 | L76: =IFERROR(K76/E76, 0) -> 0.38277778
A77: 3 | B77: KG | C77: MANZANA VERDE | D77: 4000 | E77: =A77*D77 -> 12000 | F77: =E77*1.105 -> 13260 | I77: =55000/18 -> 3055.5556 | J77: =I77*A77 -> 9166.6667 | K77: =F77-J77 -> 4093.3333 | L77: =IFERROR(K77/E77, 0) -> 0.34111111
E79: =SUM(E42:E77) -> 436790 | F79: =SUM(F42:F77) -> 485382.95 | K79: =SUM(K42:K77) -> 175628.28 | L79: =IFERROR(K79/E79, 0) -> 0.40208861
A82: FV | E82: rto: 231 | F82: 46072 | I82: COMPRA
A84: CANTIDAD | B84: UNIDAD | C84: PRODUCTO | D84: PRECIO | E84: TOTAL | F84: TOTAL + IVA | I84: COSTO | J84: TOTAL | K84: DIFERENCIA
A85: 3 | B85: CAJON | C85: LECHUGA | D85: 12000 | E85: =A85*D85 -> 36000 | F85: =E85*1.105 -> 39780 | I85: =10000/3 -> 3333.3333 | J85: =I85*A85 -> 10000 | K85: =F85-J85 -> 29780 | L85: =IFERROR(K85/E85, 0) -> 0.82722222
A86: 10 | B86: DOCENA | C86: RUCULA | D86: 7500 | E86: =A86*D86 -> 75000 | F86: =E86*1.105 -> 82875 | I86: 3000 | J86: =I86*A86 -> 30000 | K86: =F86-J86 -> 52875 | L86: =IFERROR(K86/E86, 0) -> 0.705
A87: 3 | B87: CAJON | C87: TOMATE REDONDO | D87: 36000 | E87: =A87*D87 -> 108000 | F87: =E87*1.105 -> 119340 | I87: 25000 | J87: =I87*A87 -> 75000 | K87: =F87-J87 -> 44340 | L87: =IFERROR(K87/E87, 0) -> 0.41055556
A88: 2 | B88: CJAON | C88: TOMATE CHERRY | D88: 26000 | E88: =A88*D88 -> 52000 | F88: =E88*1.105 -> 57460 | H88: S/C | I88: 0 | J88: =I88*A88 -> 0 | K88: =F88-J88 -> 57460 | L88: =IFERROR(K88/E88, 0) -> 1.105
A89: 2 | B89: CAJON | C89: PEPINO | D89: 15000 | E89: =A89*D89 -> 30000 | F89: =E89*1.105 -> 33150 | I89: 7000 | J89: =I89*A89 -> 14000 | K89: =F89-J89 -> 19150 | L89: =IFERROR(K89/E89, 0) -> 0.63833333
A90: 2 | B90: CAJON | C90: BERENJENA | D90: 14000 | E90: =A90*D90 -> 28000 | F90: =E90*1.105 -> 30940 | I90: 10000 | J90: =I90*A90 -> 20000 | K90: =F90-J90 -> 10940 | L90: =IFERROR(K90/E90, 0) -> 0.39071429
A91: 1 | B91: CAJON | C91: REPOLLO BLANCO | D91: 15000 | E91: =A91*D91 -> 15000 | F91: =E91*1.105 -> 16575 | I91: 10000 | J91: =I91*A91 -> 10000 | K91: =F91-J91 -> 6575 | L91: =IFERROR(K91/E91, 0) -> 0.43833333
A92: 1 | B92: CAJON | C92: REPOLLO COLORADO | D92: 17000 | E92: =A92*D92 -> 17000 | F92: =E92*1.105 -> 18785 | I92: 12000 | J92: =I92*A92 -> 12000 | K92: =F92-J92 -> 6785 | L92: =IFERROR(K92/E92, 0) -> 0.39911765
A93: 2 | B93: CAJON | C93: REMOLACHA | D93: 14000 | E93: =A93*D93 -> 28000 | F93: =E93*1.105 -> 30940 | I93: 15000 | J93: =I93*A93 -> 30000 | K93: =F93-J93 -> 940 | L93: =IFERROR(K93/E93, 0) -> 0.033571429
A94: 2 | B94: CAJON | C94: ZUCCINI | D94: 14000 | E94: =A94*D94 -> 28000 | F94: =E94*1.21 -> 33880 | I94: 9000 | J94: =I94*A94 -> 18000 | K94: =F94-J94 -> 15880 | L94: =IFERROR(K94/E94, 0) -> 0.56714286
A95: 2 | B95: CAJON | C95: MORRON ROJO | D95: 35000 | E95: =A95*D95 -> 70000 | F95: =E95*1.105 -> 77350 | I95: 24000 | J95: =I95*A95 -> 48000 | K95: =F95-J95 -> 29350 | L95: =IFERROR(K95/E95, 0) -> 0.41928571
A96: 1 | B96: CAJON | C96: MORRON VERDE | D96: 18000 | E96: =A96*D96 -> 18000 | F96: =E96*1.105 -> 19890 | I96: 12000 | J96: =I96*A96 -> 12000 | K96: =F96-J96 -> 7890 | L96: =IFERROR(K96/E96, 0) -> 0.43833333
A97: 3 | B97: CAJA | C97: MANZANA GRANNY | D97: 63000 | E97: =A97*D97 -> 189000 | F97: =E97*1.105 -> 208845 | I97: 45000 | J97: =I97*A97 -> 135000 | K97: =F97-J97 -> 73845 | L97: =IFERROR(K97/E97, 0) -> 0.39071429
A98: 3 | B98: CAJON | C98: PELON | D98: 38000 | E98: =A98*D98 -> 114000 | F98: =E98*1.105 -> 125970 | I98: 22000 | J98: =I98*A98 -> 66000 | K98: =F98-J98 -> 59970 | L98: =IFERROR(K98/E98, 0) -> 0.52605263
A99: 38 | B99: KG | C99: SANDIA | D99: 1000 | E99: =A99*D99 -> 38000 | F99: =E99*1.105 -> 41990 | I99: =24000/38 -> 631.57895 | J99: =I99*A99 -> 24000 | K99: =F99-J99 -> 17990 | L99: =IFERROR(K99/E99, 0) -> 0.47342105
A100: 2 | B100: CAJON | C100: MELON | D100: 22000 | E100: =A100*D100 -> 44000 | F100: =E100*1.105 -> 48620 | I100: 12000 | J100: =I100*A100 -> 24000 | K100: =F100-J100 -> 24620 | L100: =IFERROR(K100/E100, 0) -> 0.55954545
A101: 2 | B101: CAJON | C101: BANANA ECUADOR | D101: 35000 | E101: =A101*D101 -> 70000 | F101: =E101*1.105 -> 77350 | I101: 28000 | J101: =I101*A101 -> 56000 | K101: =F101-J101 -> 21350 | L101: =IFERROR(K101/E101, 0) -> 0.305
A102: 4 | B102: CAJON | C102: NARANJA DE JUGO | D102: 25000 | E102: =A102*D102 -> 100000 | F102: =E102*1.105 -> 110500 | I102: 20000 | J102: =I102*A102 -> 80000 | K102: =F102-J102 -> 30500 | L102: =IFERROR(K102/E102, 0) -> 0.305
A103: 1 | B103: ATADO | C103: PEREJIL | D103: 4000 | E103: =A103*D103 -> 4000 | F103: =E103*1.21 -> 4840 | I103: 2000 | J103: =I103*A103 -> 2000 | K103: =F103-J103 -> 2840 | L103: =IFERROR(K103/E103, 0) -> 0.71
A104: 1 | B104: CAJON | C104: HUEVO | D104: 56000 | E104: =A104*D104 -> 56000 | F104: =E104*1.105 -> 61880 | I104: 48000 | J104: =I104*A104 -> 48000 | K104: =F104-J104 -> 13880 | L104: =IFERROR(K104/E104, 0) -> 0.24785714
A105: 1 | B105: CAJON | C105: BANANA ECUADOR | D105: 35000 | E105: =A105*D105 -> 35000 | F105: =E105*1.105 -> 38675 | G105: BOLSA | I105: 0 | J105: =I105*A105 -> 0 | K105: =F105-J105 -> 38675 | L105: =IFERROR(K105/E105, 0) -> 1.105
A106: 1 | B106: CAJON | C106: TOMATE REDONDO | D106: 36000 | E106: =A106*D106 -> 36000 | F106: =E106*1.105 -> 39780 | G106: BOLSA | I106: 0 | J106: =I106*A106 -> 0 | K106: =F106-J106 -> 39780 | L106: =IFERROR(K106/E106, 0) -> 1.105
A107: 1 | B107: CJAON | C107: TOMATE CHERRY | D107: 26000 | E107: =A107*D107 -> 26000 | F107: =E107*1.105 -> 28730 | G107: BOLSA | I107: 0 | J107: =I107*A107 -> 0 | K107: =F107-J107 -> 28730 | L107: =IFERROR(K107/E107, 0) -> 1.105
A108: 1 | B108: CAJON | C108: ZUCCINI | D108: 14000 | E108: =A108*D108 -> 14000 | F108: =E108*1.105 -> 15470 | G108: BOLSA | I108: 0 | J108: =I108*A108 -> 0 | K108: =F108-J108 -> 15470 | L108: =IFERROR(K108/E108, 0) -> 1.105
A109: 1 | B109: CAJON | C109: MORRON ROJO | D109: 35000 | E109: =A109*D109 -> 35000 | F109: =E109*1.105 -> 38675 | G109: BOLSA PROPIA | I109: 0 | J109: =I109*A109 -> 0 | K109: =F109-J109 -> 38675 | L109: =IFERROR(K109/E109, 0) -> 1.105
A110: 1 | B110: CAJA | C110: MANZANA GRANNY | D110: 63000 | E110: =A110*D110 -> 63000 | F110: =E110*1.105 -> 69615 | G110: BOLSA PROPIA | I110: 0 | J110: =I110*A110 -> 0 | K110: =F110-J110 -> 69615 | L110: =IFERROR(K110/E110, 0) -> 1.105
A111: 1 | B111: CAJON | C111: MORRON VERDE | D111: 18000 | E111: =A111*D111 -> 18000 | F111: =E111*1.21 -> 21780 | G111: BOLSA PROPIA | I111: 0 | J111: =I111*A111 -> 0 | K111: =F111-J111 -> 21780 | L111: =IFERROR(K111/E111, 0) -> 1.21
E113: =SUM(E85:E111) -> 1347000 | F113: =SUM(F85:F111) -> 1493685 | K113: =SUM(K85:K111) -> 779685 | L113: =IFERROR(K113/E113, 0) -> 0.57883074
A118: TOTAL DIA | B118: =F113+F79+F36+F13 -> 2453444.5
A120: GANANCIA | B120: =K113+K79+K36+K13 -> 1113584.4
A122: Comision Juan | B122: =E15 -> 12032
...

Sheet 20-02-2026 
A3: COLEGIO ST CATHERINES MOORLANDS - CARBAJAL 3250 | E3: rto: 5 | F3: 46073 | I3: COMPRA
A5: CANTIDAD | B5: UNIDAD | C5: PRODUCTO | D5: PRECIO | E5: TOTAL | F5: TOTAL + IVA | I5: COSTO | J5: TOTAL | K5: DIFERENCIA
A6: 1 | B6: ATADO | C6: CILANTRO | D6: 3000 | E6: =A6*D6 -> 3000 | F6: =E6*1.105 -> 3315 | I6: 2000 | J6: =I6*A6 -> 2000 | K6: =F6-J6 -> 1315 | L6: =IFERROR(K6/E6, 0) -> 0.43833333
A7: 1 | B7: ATADO | C7: PEREJIL | D7: 4000 | E7: =A7*D7 -> 4000 | F7: =E7*1.105 -> 4420 | I7: 1000 | J7: =I7*A7 -> 1000 | K7: =F7-J7 -> 3420 | L7: =IFERROR(K7/E7, 0) -> 0.855
A8: 4 | B8: KG | C8: REPOLLO BLANCO | D8: 1800 | E8: =A8*D8 -> 7200 | F8: =E8*1.105 -> 7956 | I8: 1000 | J8: =I8*A8 -> 4000 | K8: =F8-J8 -> 3956 | L8: =IFERROR(K8/E8, 0) -> 0.54944444
A9: 3 | B9: KG | C9: REPOLLO COLORADO | D9: 1800 | E9: =A9*D9 -> 5400 | F9: =E9*1.105 -> 5967 | I9: 1000 | J9: =I9*A9 -> 3000 | K9: =F9-J9 -> 2967 | L9: =IFERROR(K9/E9, 0) -> 0.54944444
A10: 15 | B10: KG | C10: TOMATE PERITA | D10: 2300 | E10: =A10*D10 -> 34500 | F10: =E10*1.105 -> 38122.5 | I10: =20000/15 -> 1333.3333 | J10: =I10*A10 -> 20000 | K10: =F10-J10 -> 18122.5 | L10: =IFERROR(K10/E10, 0) -> 0.52528986
A11: 2 | B11: KG | C11: MORRON AMARILLO | D11: 4000 | E11: =A11*D11 -> 8000 | F11: =E11*1.105 -> 8840 | I11: =22000/8 -> 2750 | J11: =I11*A11 -> 5500 | K11: =F11-J11 -> 3340 | L11: =IFERROR(K11/E11, 0) -> 0.4175
A12: 3 | B12: KG | C12: MORRON VERDE | D12: 3100 | E12: =A12*D12 -> 9300 | F12: =E12*1.105 -> 10276.5 | I12: =12000/8 -> 1500 | J12: =I12*A12 -> 4500 | K12: =F12-J12 -> 5776.5 | L12: =IFERROR(K12/E12, 0) -> 0.62112903
A13: 4 | B13: KG | C13: MORRON ROJO | D13: 4000 | E13: =A13*D13 -> 16000 | F13: =E13*1.105 -> 17680 | I13: =28000/8 -> 3500 | J13: =I13*A13 -> 14000 | K13: =F13-J13 -> 3680 | L13: =IFERROR(K13/E13, 0) -> 0.23
A14: 4 | B14: KG | C14: CEBOLLA MORADA | D14: 1600 | E14: =A14*D14 -> 6400 | F14: =E14*1.105 -> 7072 | I14: =18000/17 -> 1058.8235 | J14: =I14*A14 -> 4235.2941 | K14: =F14-J14 -> 2836.7059 | L14: =IFERROR(K14/E14, 0) -> 0.44323529
A15: 3.5 | B15: KG | C15: CEBOLLA | D15: 800 | E15: =A15*D15 -> 2800 | F15: =E15*1.105 -> 3094 | I15: =9000/17 -> 529.41176 | J15: =I15*A15 -> 1852.9412 | K15: =F15-J15 -> 1241.0588 | L15: =IFERROR(K15/E15, 0) -> 0.44323529
A16: 14 | B16: ATADO | C16: ESPINACA | D16: 1600 | E16: =A16*D16 -> 22400 | F16: =E16*1.105 -> 24752 | I16: =1000 -> 1000 | J16: =I16*A16 -> 14000 | K16: =F16-J16 -> 10752 | L16: =IFERROR(K16/E16, 0) -> 0.48
A17: 4 | B17: KG | C17: BANANA ECUADOR | D17: 2800 | E17: =A17*D17 -> 11200 | F17: =E17*1.105 -> 12376 | I17: =15000/18 -> 833.33333 | J17: =I17*A17 -> 3333.3333 | K17: =F17-J17 -> 9042.6667 | L17: =IFERROR(K17/E17, 0) -> 0.80738095
A18: 5 | B18: KG | C18: LECHUGA CRIOLLA | D18: 2800 | E18: =A18*D18 -> 14000 | F18: =E18*1.105 -> 15470 | I18: =8000/7 -> 1142.8571 | J18: =I18*A18 -> 5714.2857 | K18: =F18-J18 -> 9755.7143 | L18: =IFERROR(K18/E18, 0) -> 0.69683673
A19: 20 | B19: ATADO | C19: RUCULA | D19: 500 | E19: =A19*D19 -> 10000 | F19: =E19*1.105 -> 11050 | I19: =6000/24 -> 250 | J19: =I19*A19 -> 5000 | K19: =F19-J19 -> 6050 | L19: =IFERROR(K19/E19, 0) -> 0.605
A20: 20 | B20: UNIDAD | C20: CHOCLO | D20: 800 | E20: =A20*D20 -> 16000 | F20: =E20*1.105 -> 17680 | I20: =9000/20 -> 450 | J20: =I20*A20 -> 9000 | K20: =F20-J20 -> 8680 | L20: =IFERROR(K20/E20, 0) -> 0.5425
A21: 1 | B21: BOLSA | C21: ANCO | D21: 13000 | E21: =A21*D21 -> 13000 | F21: =E21*1.105 -> 14365 | I21: 10000 | J21: =I21*A21 -> 10000 | K21: =F21-J21 -> 4365 | L21: =IFERROR(K21/E21, 0) -> 0.33576923
A22: 4 | B22: KG | C22: COLIFLOR | D22: 2200 | E22: =A22*D22 -> 8800 | F22: =E22*1.105 -> 9724 | I22: =12000/10 -> 1200 | J22: =I22*A22 -> 4800 | K22: =F22-J22 -> 4924 | L22: =IFERROR(K22/E22, 0) -> 0.55954545
A23: 1.5 | B23: KG | C23: CHAUCHA PLANA | D23: 4000 | E23: =A23*D23 -> 6000 | F23: =E23*1.105 -> 6630 | I23: =22000/7 -> 3142.8571 | J23: =I23*A23 -> 4714.2857 | K23: =F23-J23 -> 1915.7143 | L23: =IFERROR(K23/E23, 0) -> 0.31928571
A24: 1 | B24: KG | C24: PEPINO | D24: 1000 | E24: =A24*D24 -> 1000 | F24: =E24*1.105 -> 1105 | I24: =7000/15 -> 466.66667 | J24: =I24*A24 -> 466.66667 | K24: =F24-J24 -> 638.33333 | L24: =IFERROR(K24/E24, 0) -> 0.63833333
A25: 1 | B25: BOLSA | C25: ZANAHORIA | D25: 13000 | E25: =A25*D25 -> 13000 | F25: =E25*1.105 -> 14365 | I25: 8000 | J25: =I25*A25 -> 8000 | K25: =F25-J25 -> 6365 | L25: =IFERROR(K25/E25, 0) -> 0.48961538
A26: 1 | B26: ATADO | C26: PUERRO | D26: 6000 | E26: =A26*D26 -> 6000 | F26: =E26*1.105 -> 6630 | I26: =45000/11 -> 4090.9091 | J26: =I26*A26 -> 4090.9091 | K26: =F26-J26 -> 2539.0909 | L26: =IFERROR(K26/E26, 0) -> 0.42318182
A27: 2 | B27: KG | C27: FRUTILLA | D27: 8500 | E27: =A27*D27 -> 17000 | F27: =E27*1.105 -> 18785 | I27: =30000/4 -> 7500 | J27: =I27*A27 -> 15000 | K27: =F27-J27 -> 3785 | L27: =IFERROR(K27/E27, 0) -> 0.22264706
A28: 2 | B28: UNIDAD | C28: AJO | D28: 900 | E28: =A28*D28 -> 1800 | F28: =E28*1.105 -> 1989 | I28: 560 | J28: =I28*A28 -> 1120 | K28: =F28-J28 -> 869 | L28: =IFERROR(K28/E28, 0) -> 0.48277778
A29: 0.6 | B29: KG | C29: BERENJENA | D29: 1400 | E29: =A29*D29 -> 840 | F29: =E29*1.105 -> 928.2 | I29: =1000 -> 1000 | J29: =I29*A29 -> 600 | K29: =F29-J29 -> 328.2 | L29: =IFERROR(K29/E29, 0) -> 0.39071429
A30: 1 | B30: KG | C30: ZUCCINI | D30: 1000 | E30: =A30*D30 -> 1000 | F30: =E30*1.105 -> 1105 | I30: =7000/15 -> 466.66667 | J30: =I30*A30 -> 466.66667 | K30: =F30-J30 -> 638.33333 | L30: =IFERROR(K30/E30, 0) -> 0.63833333
A31: 2 | B31: UNIDAD | C31: BROCOLI | D31: 2500 | E31: =A31*D31 -> 5000 | F31: =E31*1.105 -> 5525 | I31: =13000/8 -> 1625 | J31: =I31*A31 -> 3250 | K31: =F31-J31 -> 2275 | L31: =IFERROR(K31/E31, 0) -> 0.455
A32: 3 | B32: KG | C32: REMOLACHA | D32: 2000 | E32: =A32*D32 -> 6000 | F32: =E32*1.105 -> 6630 | I32: =15000/9 -> 1666.6667 | J32: =I32*A32 -> 5000 | K32: =F32-J32 -> 1630 | L32: =IFERROR(K32/E32, 0) -> 0.27166667
A33: 3 | B33: KG | C33: MANDARINA | D33: 3200 | E33: =A33*D33 -> 9600 | F33: =E33*1.105 -> 10608 | I33: =38000/14 -> 2714.2857 | J33: =I33*A33 -> 8142.8571 | K33: =F33-J33 -> 2465.1429 | L33: =IFERROR(K33/E33, 0) -> 0.25678571
A34: 2 | B34: KG | C34: PERA | D34: 2200 | E34: =A34*D34 -> 4400 | F34: =E34*1.105 -> 4862 | I34: =28000/17 -> 1647.0588 | J34: =I34*A34 -> 3294.1176 | K34: =F34-J34 -> 1567.8824 | L34: =IFERROR(K34/E34, 0) -> 0.3563369
A35: 2 | B35: ATADO | C35: CIBOULETTE | D35: 3000 | E35: =A35*D35 -> 6000 | F35: =E35*1.105 -> 6630 | I35: 2000 | J35: =I35*A35 -> 4000 | K35: =F35-J35 -> 2630 | L35: =IFERROR(K35/E35, 0) -> 0.43833333
A36: 2 | B36: CAJON | C36: NARANJA DE JUGO | D36: 24000 | E36: =A36*D36 -> 48000 | F36: =E36*1.105 -> 53040 | I36: 20000 | J36: =I36*A36 -> 40000 | K36: =F36-J36 -> 13040 | L36: =IFERROR(K36/E36, 0) -> 0.27166667
A37: 0.5 | B37: CAJON | C37: MANZANA ROJA | D37: 70000 | E37: =A37*D37 -> 35000 | F37: =E37*1.105 -> 38675 | I37: 65000 | J37: =I37*A37 -> 32500 | K37: =F37-J37 -> 6175 | L37: =IFERROR(K37/E37, 0) -> 0.17642857
A38: 0.5 | B38: CAJON | C38: MANZANA VERDE | D38: 65000 | E38: =A38*D38 -> 32500 | F38: =E38*1.105 -> 35912.5 | I38: =60000 -> 60000 | J38: =I38*A38 -> 30000 | K38: =F38-J38 -> 5912.5 | L38: =IFERROR(K38/E38, 0) -> 0.18192308
E40: =SUM(E6:E38) -> 385140 | F40: =SUM(F6:F38) -> 425579.7 | K40: =SUM(K6:K38) -> 152998.34 | L40: =IFERROR(K40/E40, 0) -> 0.39725384
A43: MASTER COLLAGE (OHHIGINS) | E43: rto: 1 | F43: 46073 | I43: COMPRA
A45: CANTIDAD | B45: UNIDAD | C45: PRODUCTO | D45: PRECIO | E45: TOTAL | F45: TOTAL + IVA | I45: COSTO | J45: TOTAL | K45: DIFERENCIA
A46: 1 | B46: BOLSA | C46: PAPA LAVADA | D46: 21000 | E46: =A46*D46 -> 21000 | F46: =E46*1.105 -> 23205 | I46: 18000 | J46: =I46*A46 -> 18000 | K46: =F46-J46 -> 5205 | L46: =IFERROR(K46/E46, 0) -> 0.24785714
A47: 7 | B47: KG | C47: ANCO | D47: 1000 | E47: =A47*D47 -> 7000 | F47: =E47*1.105 -> 7735 | I47: =10000/16 -> 625 | J47: =I47*A47 -> 4375 | K47: =F47-J47 -> 3360 | L47: =IFERROR(K47/E47, 0) -> 0.48
A48: 0.9 | B48: KG | C48: MORRON ROJO | D48: 4000 | E48: =A48*D48 -> 3600 | F48: =E48*1.105 -> 3978 | I48: =28000/8 -> 3500 | J48: =I48*A48 -> 3150 | K48: =F48-J48 -> 828 | L48: =IFERROR(K48/E48, 0) -> 0.23
A49: 4 | B49: KG | C49: CEBOLLA | D49: 800 | E49: =A49*D49 -> 3200 | F49: =E49*1.105 -> 3536 | I49: =9000/17 -> 529.41176 | J49: =I49*A49 -> 2117.6471 | K49: =F49-J49 -> 1418.3529 | L49: =IFERROR(K49/E49, 0) -> 0.44323529
A50: 5 | B50: KG | C50: TOMATE PERITA | D50: 2300 | E50: =A50*D50 -> 11500 | F50: =E50*1.105 -> 12707.5 | I50: =20000/15 -> 1333.3333 | J50: =I50*A50 -> 6666.6667 | K50: =F50-J50 -> 6040.8333 | L50: =IFERROR(K50/E50, 0) -> 0.52528986
A51: 1 | B51: ATADO | C51: RUCULA | D51: 500 | E51: =A51*D51 -> 500 | F51: =E51*1.105 -> 552.5 | I51: =6000/24 -> 250 | J51: =I51*A51 -> 250 | K51: =F51-J51 -> 302.5 | L51: =IFERROR(K51/E51, 0) -> 0.605
A52: 1 | B52: ATADO | C52: PUERRO | D52: 6000 | E52: =A52*D52 -> 6000 | F52: =E52*1.105 -> 6630 | I52: 4100 | J52: =I52*A52 -> 4100 | K52: =F52-J52 -> 2530 | L52: =IFERROR(K52/E52, 0) -> 0.42166667
A53: 1 | B53: KG | C53: BATATA | D53: 1600 | E53: =A53*D53 -> 1600 | F53: =E53*1.105 -> 1768 | I53: =10500/12 -> 875 | J53: =I53*A53 -> 875 | K53: =F53-J53 -> 893 | L53: =IFERROR(K53/E53, 0) -> 0.558125
A54: 1 | B54: KG | C54: ZAPALLITO VERDE | D54: 1000 | E54: =A54*D54 -> 1000 | F54: =E54*1.105 -> 1105 | I54: =10000/15 -> 666.66667 | J54: =I54*A54 -> 666.66667 | K54: =F54-J54 -> 438.33333 | L54: =IFERROR(K54/E54, 0) -> 0.43833333
A55: 1 | B55: KG | C55: LIMON | D55: 2600 | E55: =A55*D55 -> 2600 | F55: =E55*1.105 -> 2873 | I55: =30000/15 -> 2000 | J55: =I55*A55 -> 2000 | K55: =F55-J55 -> 873 | L55: =IFERROR(K55/E55, 0) -> 0.33576923
A56: 2 | B56: KG | C56: ZANAHORIA | D56: 1400 | E56: =A56*D56 -> 2800 | F56: =E56*1.105 -> 3094 | I56: =8000/8 -> 1000 | J56: =I56*A56 -> 2000 | K56: =F56-J56 -> 1094 | L56: =IFERROR(K56/E56, 0) -> 0.39071429
A57: 1 | B57: KG | C57: BERENJENA | D57: 1400 | E57: =A57*D57 -> 1400 | F57: =E57*1.105 -> 1547 | I57: 1000 | J57: =I57*A57 -> 1000 | K57: =F57-J57 -> 547 | L57: =IFERROR(K57/E57, 0) -> 0.39071429
A58: 1 | B58: ATADO | C58: ALBAHACA | D58: 1000 | E58: =A58*D58 -> 1000 | F58: =E58*1.105 -> 1105 | I58: =5000/12 -> 416.66667 | J58: =I58*A58 -> 416.66667 | K58: =F58-J58 -> 688.33333 | L58: =IFERROR(K58/E58, 0) -> 0.68833333
A59: 0.45 | B59: KG | C59: PEPINO | D59: 1000 | E59: =A59*D59 -> 450 | F59: =E59*1.105 -> 497.25 | I59: =7000/15 -> 466.66667 | J59: =I59*A59 -> 210 | K59: =F59-J59 -> 287.25 | L59: =IFERROR(K59/E59, 0) -> 0.63833333
A60: 1 | B60: KG | C60: BANANA ECUADOR | D60: 2800 | E60: =A60*D60 -> 2800 | F60: =E60*1.105 -> 3094 | I60: =15000/18 -> 833.33333 | J60: =I60*A60 -> 833.33333 | K60: =F60-J60 -> 2260.6667 | L60: =IFERROR(K60/E60, 0) -> 0.80738095
A61: 4 | B61: KG | C61: NARANJA DE JUGO | D61: 1600 | E61: =A61*D61 -> 6400 | F61: =E61*1.105 -> 7072 | I61: =20000/15 -> 1333.3333 | J61: =I61*A61 -> 5333.3333 | K61: =F61-J61 -> 1738.6667 | L61: =IFERROR(K61/E61, 0) -> 0.27166667
A62: 1 | B62: KG | C62: MANZANA VERDE | D62: 4000 | E62: =A62*D62 -> 4000 | F62: =E62*1.105 -> 4420 | I62: =60000/18 -> 3333.3333 | J62: =I62*A62 -> 3333.3333 | K62: =F62-J62 -> 1086.6667 | L62: =IFERROR(K62/E62, 0) -> 0.27166667
A63: 2 | B63: KG | C63: MANZANA ROJA | D63: 4500 | E63: =A63*D63 -> 9000 | F63: =E63*1.105 -> 9945 | I63: =65000/18 -> 3611.1111 | J63: =I63*A63 -> 7222.2222 | K63: =F63-J63 -> 2722.7778 | L63: =IFERROR(K63/E63, 0) -> 0.30253086
A64: 1 | B64: KG | C64: POMELO | D64: 3000 | E64: =A64*D64 -> 3000 | F64: =E64*1.105 -> 3315 | I64: =40000/15 -> 2666.6667 | J64: =I64*A64 -> 2666.6667 | K64: =F64-J64 -> 648.33333 | L64: =IFERROR(K64/E64, 0) -> 0.21611111
A65: 1 | B65: KG | C65: PERA | D65: 2200 | E65: =A65*D65 -> 2200 | F65: =E65*1.105 -> 2431 | I65: =28000/17 -> 1647.0588 | J65: =I65*A65 -> 1647.0588 | K65: =F65-J65 -> 783.94118 | L65: =IFERROR(K65/E65, 0) -> 0.3563369
A66: 1 | B66: KG | C66: UVA | D66: 4000 | E66: =A66*D66 -> 4000 | F66: =E66*1.105 -> 4420 | I66: 3850 | J66: =I66*A66 -> 3850 | K66: =F66-J66 -> 570 | L66: =IFERROR(K66/E66, 0) -> 0.1425
A67: 1 | B67: KG | C67: CIRUELA | D67: 4000 | E67: =A67*D67 -> 4000 | F67: =E67*1.105 -> 4420 | I67: =10500/3 -> 3500 | J67: =I67*A67 -> 3500 | K67: =F67-J67 -> 920 | L67: =IFERROR(K67/E67, 0) -> 0.23
A68: 1 | B68: KG | C68: FRUTILLA | D68: 8500 | E68: =A68*D68 -> 8500 | F68: =E68*1.105 -> 9392.5 | I68: =30000/4 -> 7500 | J68: =I68*A68 -> 7500 | K68: =F68-J68 -> 1892.5 | L68: =IFERROR(K68/E68, 0) -> 0.22264706
A69: 6 | B69: MAPLE | C69: HUEVO | D69: 4500 | E69: =A69*D69 -> 27000 | F69: =E69*1.21 -> 32670 | I69: =52000/12 -> 4333.3333 | J69: =I69*A69 -> 26000 | K69: =F69-J69 -> 6670 | L69: =IFERROR(K69/E69, 0) -> 0.24703704
E71: =SUM(E46:E69) -> 134550 | F71: =SUM(F46:F69) -> 151512.75 | K71: =SUM(K46:K69) -> 43799.155 | L71: =IFERROR(K71/E71, 0) -> 0.32552326
A74: COLEGIO SAN MARCOS | SAN ISIDRO | E74: rto: 1 | F74: 46073 | I74: COMPRA
A76: CANTIDAD | B76: UNIDAD | C76: PRODUCTO | D76: PRECIO | E76: TOTAL | F76: TOTAL + IVA | I76: COSTO | J76: TOTAL | K76: DIFERENCIA
A77: 1 | B77: CAJON | C77: TOMATE PERITA | D77: 32000 | E77: =A77*D77 -> 32000 | F77: =E77*1.105 -> 35360 | I77: 20000 | J77: =I77*A77 -> 20000 | K77: =F77-J77 -> 15360 | L77: =IFERROR(K77/E77, 0) -> 0.48
A78: 1 | B78: CAJON | C78: LECHUGA CRIOLLA | D78: 15000 | E78: =A78*D78 -> 15000 | F78: =E78*1.105 -> 16575 | I78: =8000 -> 8000 | J78: =I78*A78 -> 8000 | K78: =F78-J78 -> 8575 | L78: =IFERROR(K78/E78, 0) -> 0.57166667
A79: 1 | B79: CAJON | C79: RUCULA | D79: 10000 | E79: =A79*D79 -> 10000 | F79: =E79*1.105 -> 11050 | I79: 6000 | J79: =I79*A79 -> 6000 | K79: =F79-J79 -> 5050 | L79: =IFERROR(K79/E79, 0) -> 0.505
A80: 1 | B80: CAJON | C80: HUEVO N1 | D80: 52000 | E80: =A80*D80 -> 52000 | F80: =E80*1.21 -> 62920 | I80: 52000 | J80: =I80*A80 -> 52000 | K80: =F80-J80 -> 10920 | L80: =IFERROR(K80/E80, 0) -> 0.21
A81: 1 | B81: KG | C81: REMOLACHA | D81: 2000 | E81: =A81*D81 -> 2000 | F81: =E81*1.105 -> 2210 | I81: =15000/9 -> 1666.6667 | J81: =I81*A81 -> 1666.6667 | K81: =F81-J81 -> 543.33333 | L81: =IFERROR(K81/E81, 0) -> 0.27166667
A82: 1 | B82: CAJON | C82: ESPINACA | D82: 16000 | E82: =A82*D82 -> 16000 | F82: =E82*1.105 -> 17680 | I82: 12000 | J82: =I82*A82 -> 12000 | K82: =F82-J82 -> 5680 | L82: =IFERROR(K82/E82, 0) -> 0.355
