Workbook

Sheet COMPRAS
B1: FECHA | C1: PRODUCTO | D1: COSTO | E1: CANTIDAD | F1: KILOS / UNIDADES | G1: PROVEEDOR | H1: METODO DE PAGO | I1: VACIO | J1: UNIDAD
A2: d536df47 | B2: 46065 | C2: ACELGA | D2: 12000 | E2: 2 | F2: 10 | G2: JCB | I2: 4000 | J2: CAJON

Sheet PRECIOS
A1: PRODUCTO | B1: UNIDAD | C1: COSTO ACTUAL | D1: MARGEN (%) | E1: PRECIO VENTA | F1: KG / UNIDAD POR CAJON | G1: TOTAL VACIOS | H1: STOCK ACTUAL X UNIDADES | I1: COSTO UNITARIO | J1: VENTA UNITARIO
A2: ACELGA | B2: CAJON | C2: =IFERROR(AVERAGEIFS(COMPRAS!$D:$D, COMPRAS!$C:$C, $A2, COMPRAS!$J:$J, $B2), 0) -> 12000 | D2: 1.3 | E2: =ROUNDUP(C2 * D2, -3) -> 16000 | F2: =IFERROR(AVERAGEIFS(COMPRAS!$F:$F, COMPRAS!$C:$C, $A2, COMPRAS!$J:$J, $B2), 1) -> 10 | G2: =IFERROR(SUMIFS(COMPRAS!I:I, COMPRAS!C:C, A2) * SUMIFS(COMPRAS!E:E, COMPRAS!C:C, A2) / COUNTIF(COMPRAS!C:C, A2), 0) -> 8000 | H2: =IFERROR( ((SUMIFS(COMPRAS!$E:$E, COMPRAS!$C:$C, $A2, COMPRAS!$J:$J, "CAJON") + SUMIFS(COMPRAS!$E:$E, COMPRAS!$C:$C, $A2, COMPRAS!$J:$J, "BOLSA")) * $F2) - ((SUMIFS(prueba!$A:$A, prueba!$C:$C, $A2, prueba!$B:$B, "CAJON") + SUMIFS(prueba!$A:$A, prueba!$C:$C, $A2, prueba!$B:$B, "BOLSA")) * $F2) - MAX(0, (SUMIFS(prueba!$A:$A, prueba!$C:$C, $A2, prueba!$B:$B, "UNIDAD") + SUMIFS(prueba!$A:$A, prueba!$C:$C, $A2, prueba!$B:$B, "KG")) - (SUMIFS(COMPRAS!$E:$E, COMPRAS!$C:$C, $A2, COMPRAS!$J:$J, "UNIDAD") + SUMIFS(COMPRAS!$E:$E, COMPRAS!$C:$C, $A2, COMPRAS!$J:$J, "KG"))), 0) -> 20 | I2: =IFERROR(C2 / F2, 0) -> 1200 | J2: =IFERROR(ROUNDUP((E2 / F2) * 1.2, -2),0) -> 2000 | K2: =A2&B2 -> ACELGACAJON
A3: ACELGA | B3: UNIDAD | C3: =IFERROR(AVERAGEIFS(COMPRAS!$D:$D, COMPRAS!$C:$C, $A3, COMPRAS!$J:$J, $B3), 0) -> 0 | D3: 1.1 | E3: =ROUNDUP(C3 * D3, -2) -> 0 | F3: =IFERROR(AVERAGEIFS(COMPRAS!$F:$F, COMPRAS!$C:$C, $A3, COMPRAS!$J:$J, $B3), 1) -> 1 | G3: =IFERROR(SUMIFS(COMPRAS!I:I, COMPRAS!C:C, A3) * SUMIFS(COMPRAS!E:E, COMPRAS!C:C, A3) / COUNTIF(COMPRAS!C:C, A3), 0) -> 8000 | H3: =MAX(0, (SUMIFS(COMPRAS!$E:$E, COMPRAS!$C:$C, $A3, COMPRAS!$J:$J, "UNIDAD") + SUMIFS(COMPRAS!$E:$E, COMPRAS!$C:$C, $A3, COMPRAS!$J:$J, "KG")) - (SUMIFS(prueba!$A:$A, prueba!$C:$C, $A3, prueba!$B:$B, "UNIDAD") + SUMIFS(prueba!$A:$A, prueba!$C:$C, $A3, prueba!$B:$B, "KG")) ) -> 0 | I3: =IFERROR(C3 / F3, 0) -> 0 | J3: =IFERROR(ROUNDUP((E3 / F3) , -2),0) -> 0 | K3: =A3&B3 -> ACELGAUNIDAD
A4: ALBAHACA | B4: CAJON | C4: =IFERROR(AVERAGEIFS(COMPRAS!$D:$D, COMPRAS!$C:$C, $A4, COMPRAS!$J:$J, $B4), 0) -> 0 | D4: 1.3 | E4: =ROUNDUP(C4 *D4, -3) -> 0 | F4: =IFERROR(AVERAGEIFS(COMPRAS!$F:$F, COMPRAS!$C:$C, $A4, COMPRAS!$J:$J, $B4), 1) -> 1 | G4: =IFERROR(SUMIFS(COMPRAS!I:I, COMPRAS!C:C, A4) * SUMIFS(COMPRAS!E:E, COMPRAS!C:C, A4) / COUNTIF(COMPRAS!C:C, A4), 0) -> 0 | H4: =IFERROR( ((SUMIFS(COMPRAS!$E:$E, COMPRAS!$C:$C, $A4, COMPRAS!$J:$J, "CAJON") + SUMIFS(COMPRAS!$E:$E, COMPRAS!$C:$C, $A4, COMPRAS!$J:$J, "BOLSA")) * $F4) - ((SUMIFS(prueba!$A:$A, prueba!$C:$C, $A4, prueba!$B:$B, "CAJON") + SUMIFS(prueba!$A:$A, prueba!$C:$C, $A4, prueba!$B:$B, "BOLSA")) * $F4) - MAX(0, (SUMIFS(prueba!$A:$A, prueba!$C:$C, $A4, prueba!$B:$B, "UNIDAD") + SUMIFS(prueba!$A:$A, prueba!$C:$C, $A4, prueba!$B:$B, "KG")) - (SUMIFS(COMPRAS!$E:$E, COMPRAS!$C:$C, $A4, COMPRAS!$J:$J, "UNIDAD") + SUMIFS(COMPRAS!$E:$E, COMPRAS!$C:$C, $A4, COMPRAS!$J:$J, "KG"))), 0) -> 0 | I4: =IFERROR(C4 / F4, 0) -> 0 | J4: =IFERROR(ROUNDUP((E4 / F4) * 1.1, -2),0) -> 0 | K4: =A4&B4 -> ALBAHACACAJON
A5: ALBAHACA | B5: UNIDAD | C5: =IFERROR(AVERAGEIFS(COMPRAS!$D:$D, COMPRAS!$C:$C, $A5, COMPRAS!$J:$J, $B5), 0) -> 0 | D5: 1.3 | E5: =ROUNDUP(C5 *D5, -2) -> 0 | F5: =IFERROR(AVERAGEIFS(COMPRAS!$F:$F, COMPRAS!$C:$C, $A5, COMPRAS!$J:$J, $B5), 1) -> 1 | G5: =IFERROR(SUMIFS(COMPRAS!I:I, COMPRAS!C:C, A5) * SUMIFS(COMPRAS!E:E, COMPRAS!C:C, A5) / COUNTIF(COMPRAS!C:C, A5), 0) -> 0 | H5: =MAX(0, (SUMIFS(COMPRAS!$E:$E, COMPRAS!$C:$C, $A5, COMPRAS!$J:$J, "UNIDAD") + SUMIFS(COMPRAS!$E:$E, COMPRAS!$C:$C, $A5, COMPRAS!$J:$J, "KG")) - (SUMIFS(prueba!$A:$A, prueba!$C:$C, $A5, prueba!$B:$B, "UNIDAD") + SUMIFS(prueba!$A:$A, prueba!$C:$C, $A5, prueba!$B:$B, "KG")) ) -> 0 | I5: =IFERROR(C5 / F5, 0) -> 0 | J5: =IFERROR(ROUNDUP((E5 / F5) * 1.1, -2),0) -> 0 | K5: =A5&B5 -> ALBAHACAUNIDAD
A6: APIO | B6: CAJON | C6: =IFERROR(AVERAGEIFS(COMPRAS!$D:$D, COMPRAS!$C:$C, $A6, COMPRAS!$J:$J, $B6), 0) -> 0 | D6: 1.3 | E6: =ROUNDUP(C6 *D6, -3) -> 0 | F6: =IFERROR(AVERAGEIFS(COMPRAS!$F:$F, COMPRAS!$C:$C, $A6, COMPRAS!$J:$J, $B6), 1) -> 1 | G6: =IFERROR(SUMIFS(COMPRAS!I:I, COMPRAS!C:C, A6) * SUMIFS(COMPRAS!E:E, COMPRAS!C:C, A6) / COUNTIF(COMPRAS!C:C, A6), 0) -> 0 | H6: =IFERROR( ((SUMIFS(COMPRAS!$E:$E, COMPRAS!$C:$C, $A6, COMPRAS!$J:$J, "CAJON") + SUMIFS(COMPRAS!$E:$E, COMPRAS!$C:$C, $A6, COMPRAS!$J:$J, "BOLSA")) * $F6) - ((SUMIFS(prueba!$A:$A, prueba!$C:$C, $A6, prueba!$B:$B, "CAJON") + SUMIFS(prueba!$A:$A, prueba!$C:$C, $A6, prueba!$B:$B, "BOLSA")) * $F6) - MAX(0, (SUMIFS(prueba!$A:$A, prueba!$C:$C, $A6, prueba!$B:$B, "UNIDAD") + SUMIFS(prueba!$A:$A, prueba!$C:$C, $A6, prueba!$B:$B, "KG")) - (SUMIFS(COMPRAS!$E:$E, COMPRAS!$C:$C, $A6, COMPRAS!$J:$J, "UNIDAD") + SUMIFS(COMPRAS!$E:$E, COMPRAS!$C:$C, $A6, COMPRAS!$J:$J, "KG"))), 0) -> -2 | I6: =IFERROR(C6 / F6, 0) -> 0 | J6: =IFERROR(ROUNDUP((E6 / F6) * 1.1, -2),0) -> 0 | K6: =A6&B6 -> APIOCAJON
A7: APIO | B7: UNIDAD | C7: =IFERROR(AVERAGEIFS(COMPRAS!$D:$D, COMPRAS!$C:$C, $A7, COMPRAS!$J:$J, $B7), 0) -> 0 | D7: 1.3 | E7: =ROUNDUP(C7 *D7, -2) -> 0 | F7: =IFERROR(AVERAGEIFS(COMPRAS!$F:$F, COMPRAS!$C:$C, $A7, COMPRAS!$J:$J, $B7), 1) -> 1 | G7: =IFERROR(SUMIFS(COMPRAS!I:I, COMPRAS!C:C, A7) * SUMIFS(COMPRAS!E:E, COMPRAS!C:C, A7) / COUNTIF(COMPRAS!C:C, A7), 0) -> 0 | H7: =MAX(0, (SUMIFS(COMPRAS!$E:$E, COMPRAS!$C:$C, $A7, COMPRAS!$J:$J, "UNIDAD") + SUMIFS(COMPRAS!$E:$E, COMPRAS!$C:$C, $A7, COMPRAS!$J:$J, "KG")) - (SUMIFS(prueba!$A:$A, prueba!$C:$C, $A7, prueba!$B:$B, "UNIDAD") + SUMIFS(prueba!$A:$A, prueba!$C:$C, $A7, prueba!$B:$B, "KG")) ) -> 0 | I7: =IFERROR(C7 / F7, 0) -> 0 | J7: =IFERROR(ROUNDUP((E7 / F7) * 1.1, -2),0) -> 0 | K7: =A7&B7 -> APIOUNIDAD
A8: BROCOLI | B8: CAJON | C8: =IFERROR(AVERAGEIFS(COMPRAS!$D:$D, COMPRAS!$C:$C, $A8, COMPRAS!$J:$J, $B8), 0) -> 0 | D8: 1.3 | E8: =ROUNDUP(C8 *D8, -3) -> 0 | F8: =IFERROR(AVERAGEIFS(COMPRAS!$F:$F, COMPRAS!$C:$C, $A8, COMPRAS!$J:$J, $B8), 1) -> 1 | G8: =IFERROR(SUMIFS(COMPRAS!I:I, COMPRAS!C:C, A8) * SUMIFS(COMPRAS!E:E, COMPRAS!C:C, A8) / COUNTIF(COMPRAS!C:C, A8), 0) -> 0 | H8: =IFERROR( ((SUMIFS(COMPRAS!$E:$E, COMPRAS!$C:$C, $A8, COMPRAS!$J:$J, "CAJON") + SUMIFS(COMPRAS!$E:$E, COMPRAS!$C:$C, $A8, COMPRAS!$J:$J, "BOLSA")) * $F8) - ((SUMIFS(prueba!$A:$A, prueba!$C:$C, $A8, prueba!$B:$B, "CAJON") + SUMIFS(prueba!$A:$A, prueba!$C:$C, $A8, prueba!$B:$B, "BOLSA")) * $F8) - MAX(0, (SUMIFS(prueba!$A:$A, prueba!$C:$C, $A8, prueba!$B:$B, "UNIDAD") + SUMIFS(prueba!$A:$A, prueba!$C:$C, $A8, prueba!$B:$B, "KG")) - (SUMIFS(COMPRAS!$E:$E, COMPRAS!$C:$C, $A8, COMPRAS!$J:$J, "UNIDAD") + SUMIFS(COMPRAS!$E:$E, COMPRAS!$C:$C, $A8, COMPRAS!$J:$J, "KG"))), 0) -> 0 | I8: =IFERROR(C8 / F8, 0) -> 0 | J8: =IFERROR(ROUNDUP((E8 / F8) * 1.1, -2),0) -> 0 | K8: =A8&B8 -> BROCOLICAJON
A9: BROCOLI | B9: UNIDAD | C9: =IFERROR(AVERAGEIFS(COMPRAS!$D:$D, COMPRAS!$C:$C, $A9, COMPRAS!$J:$J, $B9), 0) -> 0 | D9: 1.3 | E9: =ROUNDUP(C9 *D9, -2) -> 0 | F9: =IFERROR(AVERAGEIFS(COMPRAS!$F:$F, COMPRAS!$C:$C, $A9, COMPRAS!$J:$J, $B9), 1) -> 1 | G9: =IFERROR(SUMIFS(COMPRAS!I:I, COMPRAS!C:C, A9) * SUMIFS(COMPRAS!E:E, COMPRAS!C:C, A9) / COUNTIF(COMPRAS!C:C, A9), 0) -> 0 | H9: =MAX(0, (SUMIFS(COMPRAS!$E:$E, COMPRAS!$C:$C, $A9, COMPRAS!$J:$J, "UNIDAD") + SUMIFS(COMPRAS!$E:$E, COMPRAS!$C:$C, $A9, COMPRAS!$J:$J, "KG")) - (SUMIFS(prueba!$A:$A, prueba!$C:$C, $A9, prueba!$B:$B, "UNIDAD") + SUMIFS(prueba!$A:$A, prueba!$C:$C, $A9, prueba!$B:$B, "KG")) ) -> 0 | I9: =IFERROR(C9 / F9, 0) -> 0 | J9: =IFERROR(ROUNDUP((E9 / F9) * 1.1, -2),0) -> 0 | K9: =A9&B9 -> BROCOLIUNIDAD
A10: REPOLLITOS DE BRUSELAS | B10: CAJON | C10: =IFERROR(AVERAGEIFS(COMPRAS!$D:$D, COMPRAS!$C:$C, $A10, COMPRAS!$J:$J, $B10), 0) -> 0 | D10: 1.3 | E10: =ROUNDUP(C10 *D10, -3) -> 0 | F10: =IFERROR(AVERAGEIFS(COMPRAS!$F:$F, COMPRAS!$C:$C, $A10, COMPRAS!$J:$J, $B10), 1) -> 1 | G10: =IFERROR(SUMIFS(COMPRAS!I:I, COMPRAS!C:C, A10) * SUMIFS(COMPRAS!E:E, COMPRAS!C:C, A10) / COUNTIF(COMPRAS!C:C, A10), 0) -> 0 | H10: =IFERROR( ((SUMIFS(COMPRAS!$E:$E, COMPRAS!$C:$C, $A10, COMPRAS!$J:$J, "CAJON") + SUMIFS(COMPRAS!$E:$E, COMPRAS!$C:$C, $A10, COMPRAS!$J:$J, "BOLSA")) * $F10) - ((SUMIFS(prueba!$A:$A, prueba!$C:$C, $A10, prueba!$B:$B, "CAJON") + SUMIFS(prueba!$A:$A, prueba!$C:$C, $A10, prueba!$B:$B, "BOLSA")) * $F10) - MAX(0, (SUMIFS(prueba!$A:$A, prueba!$C:$C, $A10, prueba!$B:$B, "UNIDAD") + SUMIFS(prueba!$A:$A, prueba!$C:$C, $A10, prueba!$B:$B, "KG")) - (SUMIFS(COMPRAS!$E:$E, COMPRAS!$C:$C, $A10, COMPRAS!$J:$J, "UNIDAD") + SUMIFS(COMPRAS!$E:$E, COMPRAS!$C:$C, $A10, COMPRAS!$J:$J, "KG"))), 0) -> 0 | I10: =IFERROR(C10 / F10, 0) -> 0 | J10: =IFERROR(ROUNDUP((E10 / F10) * 1.1, -2),0) -> 0 | K10: =A10&B10 -> REPOLLITOS DE BRUSELASCAJON
A11: REPOLLITOS DE BRUSELAS | B11: UNIDAD | C11: =IFERROR(AVERAGEIFS(COMPRAS!$D:$D, COMPRAS!$C:$C, $A11, COMPRAS!$J:$J, $B11), 0) -> 0 | D11: 1.3 | E11: =ROUNDUP(C11 *D11, -2) -> 0 | F11: =IFERROR(AVERAGEIFS(COMPRAS!$F:$F, COMPRAS!$C:$C, $A11, COMPRAS!$J:$J, $B11), 1) -> 1 | G11: =IFERROR(SUMIFS(COMPRAS!I:I, COMPRAS!C:C, A11) * SUMIFS(COMPRAS!E:E, COMPRAS!C:C, A11) / COUNTIF(COMPRAS!C:C, A11), 0) -> 0 | H11: =MAX(0, (SUMIFS(COMPRAS!$E:$E, COMPRAS!$C:$C, $A11, COMPRAS!$J:$J, "UNIDAD") + SUMIFS(COMPRAS!$E:$E, COMPRAS!$C:$C, $A11, COMPRAS!$J:$J, "KG")) - (SUMIFS(prueba!$A:$A, prueba!$C:$C, $A11, prueba!$B:$B, "UNIDAD") + SUMIFS(prueba!$A:$A, prueba!$C:$C, $A11, prueba!$B:$B, "KG")) ) -> 0 | I11: =IFERROR(C11 / F11, 0) -> 0 | J11: =IFERROR(ROUNDUP((E11 / F11) * 1.1, -2),0) -> 0 | K11: =A11&B11 -> REPOLLITOS DE BRUSELASUNIDAD
A12: CEBOLLA DE VERDEO | B12: CAJON | C12: =IFERROR(AVERAGEIFS(COMPRAS!$D:$D, COMPRAS!$C:$C, $A12, COMPRAS!$J:$J, $B12), 0) -> 0 | D12: 1.3 | E12: =ROUNDUP(C12 *D12, -3) -> 0 | F12: =IFERROR(AVERAGEIFS(COMPRAS!$F:$F, COMPRAS!$C:$C, $A12, COMPRAS!$J:$J, $B12), 1) -> 1 | G12: =IFERROR(SUMIFS(COMPRAS!I:I, COMPRAS!C:C, A12) * SUMIFS(COMPRAS!E:E, COMPRAS!C:C, A12) / COUNTIF(COMPRAS!C:C, A12), 0) -> 0 | H12: =IFERROR( ((SUMIFS(COMPRAS!$E:$E, COMPRAS!$C:$C, $A12, COMPRAS!$J:$J, "CAJON") + SUMIFS(COMPRAS!$E:$E, COMPRAS!$C:$C, $A12, COMPRAS!$J:$J, "BOLSA")) * $F12) - ((SUMIFS(prueba!$A:$A, prueba!$C:$C, $A12, prueba!$B:$B, "CAJON") + SUMIFS(prueba!$A:$A, prueba!$C:$C, $A12, prueba!$B:$B, "BOLSA")) * $F12) - MAX(0, (SUMIFS(prueba!$A:$A, prueba!$C:$C, $A12, prueba!$B:$B, "UNIDAD") + SUMIFS(prueba!$A:$A, prueba!$C:$C, $A12, prueba!$B:$B, "KG")) - (SUMIFS(COMPRAS!$E:$E, COMPRAS!$C:$C, $A12, COMPRAS!$J:$J, "UNIDAD") + SUMIFS(COMPRAS!$E:$E, COMPRAS!$C:$C, $A12, COMPRAS!$J:$J, "KG"))), 0) -> 0 | I12: =IFERROR(C12 / F12, 0) -> 0 | J12: =IFERROR(ROUNDUP((E12 / F12) * 1.1, -2),0) -> 0 | K12: =A12&B12 -> CEBOLLA DE VERDEOCAJON
A13: CEBOLLA DE VERDEO | B13: UNIDAD | C13: =IFERROR(AVERAGEIFS(COMPRAS!$D:$D, COMPRAS!$C:$C, $A13, COMPRAS!$J:$J, $B13), 0) -> 0 | D13: 1.3 | E13: =ROUNDUP(C13 *D13, -2) -> 0 | F13: =IFERROR(AVERAGEIFS(COMPRAS!$F:$F, COMPRAS!$C:$C, $A13, COMPRAS!$J:$J, $B13), 1) -> 1 | G13: =IFERROR(SUMIFS(COMPRAS!I:I, COMPRAS!C:C, A13) * SUMIFS(COMPRAS!E:E, COMPRAS!C:C, A13) / COUNTIF(COMPRAS!C:C, A13), 0) -> 0 | H13: =MAX(0, (SUMIFS(COMPRAS!$E:$E, COMPRAS!$C:$C, $A13, COMPRAS!$J:$J, "UNIDAD") + SUMIFS(COMPRAS!$E:$E, COMPRAS!$C:$C, $A13, COMPRAS!$J:$J, "KG")) - (SUMIFS(prueba!$A:$A, prueba!$C:$C, $A13, prueba!$B:$B, "UNIDAD") + SUMIFS(prueba!$A:$A, prueba!$C:$C, $A13, prueba!$B:$B, "KG")) ) -> 0 | I13: =IFERROR(C13 / F13, 0) -> 0 | J13: =IFERROR(ROUNDUP((E13 / F13) * 1.1, -2),0) -> 0 | K13: =A13&B13 -> CEBOLLA DE VERDEOUNIDAD
A14: COLIFLOR | B14: CAJON | C14: =IFERROR(AVERAGEIFS(COMPRAS!$D:$D, COMPRAS!$C:$C, $A14, COMPRAS!$J:$J, $B14), 0) -> 0 | D14: 1.3 | E14: =ROUNDUP(C14 * D14, -3) -> 0 | F14: =IFERROR(AVERAGEIFS(COMPRAS!$F:$F, COMPRAS!$C:$C, $A14, COMPRAS!$J:$J, $B14), 1) -> 1 | G14: =IFERROR(SUMIFS(COMPRAS!I:I, COMPRAS!C:C, A14) * SUMIFS(COMPRAS!E:E, COMPRAS!C:C, A14) / COUNTIF(COMPRAS!C:C, A14), 0) -> 0 | H14: =IFERROR( ((SUMIFS(COMPRAS!$E:$E, COMPRAS!$C:$C, $A14, COMPRAS!$J:$J, "CAJON") + SUMIFS(COMPRAS!$E:$E, COMPRAS!$C:$C, $A14, COMPRAS!$J:$J, "BOLSA")) * $F14) - ((SUMIFS(prueba!$A:$A, prueba!$C:$C, $A14, prueba!$B:$B, "CAJON") + SUMIFS(prueba!$A:$A, prueba!$C:$C, $A14, prueba!$B:$B, "BOLSA")) * $F14) - MAX(0, (SUMIFS(prueba!$A:$A, prueba!$C:$C, $A14, prueba!$B:$B, "UNIDAD") + SUMIFS(prueba!$A:$A, prueba!$C:$C, $A14, prueba!$B:$B, "KG")) - (SUMIFS(COMPRAS!$E:$E, COMPRAS!$C:$C, $A14, COMPRAS!$J:$J, "UNIDAD") + SUMIFS(COMPRAS!$E:$E, COMPRAS!$C:$C, $A14, COMPRAS!$J:$J, "KG"))), 0) -> 0 | I14: =IFERROR(C14 / F14, 0) -> 0 | J14: =IFERROR(ROUNDUP((E14 / F14) * 1.1, -2),0) -> 0 | K14: =A14&B14 -> COLIFLORCAJON
A15: COLIFLOR | B15: UNIDAD | C15: =IFERROR(AVERAGEIFS(COMPRAS!$D:$D, COMPRAS!$C:$C, $A15, COMPRAS!$J:$J, $B15), 0) -> 0 | D15: 1.3 | E15: =ROUNDUP(C15 * D15, -2) -> 0 | F15: =IFERROR(AVERAGEIFS(COMPRAS!$F:$F, COMPRAS!$C:$C, $A15, COMPRAS!$J:$J, $B15), 1) -> 1 | G15: =IFERROR(SUMIFS(COMPRAS!I:I, COMPRAS!C:C, A15) * SUMIFS(COMPRAS!E:E, COMPRAS!C:C, A15) / COUNTIF(COMPRAS!C:C, A15), 0) -> 0 | H15: =MAX(0, (SUMIFS(COMPRAS!$E:$E, COMPRAS!$C:$C, $A15, COMPRAS!$J:$J, "UNIDAD") + SUMIFS(COMPRAS!$E:$E, COMPRAS!$C:$C, $A15, COMPRAS!$J:$J, "KG")) - (SUMIFS(prueba!$A:$A, prueba!$C:$C, $A15, prueba!$B:$B, "UNIDAD") + SUMIFS(prueba!$A:$A, prueba!$C:$C, $A15, prueba!$B:$B, "KG")) ) -> 0 | I15: =IFERROR(C15 / F15, 0) -> 0 | J15: =IFERROR(ROUNDUP((E15 / F15) * 1.1, -2),0) -> 0 | K15: =A15&B15 -> COLIFLORUNIDAD
A16: ESPINACA | B16: CAJON | C16: =IFERROR(AVERAGEIFS(COMPRAS!$D:$D, COMPRAS!$C:$C, $A16, COMPRAS!$J:$J, $B16), 0) -> 0 | D16: 1.3 | E16: =ROUNDUP(C16 *D16, -3) -> 0 | F16: =IFERROR(AVERAGEIFS(COMPRAS!$F:$F, COMPRAS!$C:$C, $A16, COMPRAS!$J:$J, $B16), 1) -> 1 | G16: =IFERROR(SUMIFS(COMPRAS!I:I, COMPRAS!C:C, A16) * SUMIFS(COMPRAS!E:E, COMPRAS!C:C, A16) / COUNTIF(COMPRAS!C:C, A16), 0) -> 0 | H16: =IFERROR( ((SUMIFS(COMPRAS!$E:$E, COMPRAS!$C:$C, $A16, COMPRAS!$J:$J, "CAJON") + SUMIFS(COMPRAS!$E:$E, COMPRAS!$C:$C, $A16, COMPRAS!$J:$J, "BOLSA")) * $F16) - ((SUMIFS(prueba!$A:$A, prueba!$C:$C, $A16, prueba!$B:$B, "CAJON") + SUMIFS(prueba!$A:$A, prueba!$C:$C, $A16, prueba!$B:$B, "BOLSA")) * $F16) - MAX(0, (SUMIFS(prueba!$A:$A, prueba!$C:$C, $A16, prueba!$B:$B, "UNIDAD") + SUMIFS(prueba!$A:$A, prueba!$C:$C, $A16, prueba!$B:$B, "KG")) - (SUMIFS(COMPRAS!$E:$E, COMPRAS!$C:$C, $A16, COMPRAS!$J:$J, "UNIDAD") + SUMIFS(COMPRAS!$E:$E, COMPRAS!$C:$C, $A16, COMPRAS!$J:$J, "KG"))), 0) -> 0 | I16: =IFERROR(C16 / F16, 0) -> 0 | J16: =IFERROR(ROUNDUP((E16 / F16) * 1.1, -2),0) -> 0 | K16: =A16&B16 -> ESPINACACAJON
A17: ESPINACA | B17: UNIDAD | C17: =IFERROR(AVERAGEIFS(COMPRAS!$D:$D, COMPRAS!$C:$C, $A17, COMPRAS!$J:$J, $B17), 0) -> 0 | D17: 1.3 | E17: =ROUNDUP(C17 *D17, -2) -> 0 | F17: =IFERROR(AVERAGEIFS(COMPRAS!$F:$F, COMPRAS!$C:$C, $A17, COMPRAS!$J:$J, $B17), 1) -> 1 | G17: =IFERROR(SUMIFS(COMPRAS!I:I, COMPRAS!C:C, A17) * SUMIFS(COMPRAS!E:E, COMPRAS!C:C, A17) / COUNTIF(COMPRAS!C:C, A17), 0) -> 0 | H17: =MAX(0, (SUMIFS(COMPRAS!$E:$E, COMPRAS!$C:$C, $A17, COMPRAS!$J:$J, "UNIDAD") + SUMIFS(COMPRAS!$E:$E, COMPRAS!$C:$C, $A17, COMPRAS!$J:$J, "KG")) - (SUMIFS(prueba!$A:$A, prueba!$C:$C, $A17, prueba!$B:$B, "UNIDAD") + SUMIFS(prueba!$A:$A, prueba!$C:$C, $A17, prueba!$B:$B, "KG")) ) -> 0 | I17: =IFERROR(C17 / F17, 0) -> 0 | J17: =IFERROR(ROUNDUP((E17 / F17) * 1.1, -2),0) -> 0 | K17: =A17&B17 -> ESPINACAUNIDAD
A18: LECHUGA CAPUCCINA | B18: CAJON | C18: =IFERROR(AVERAGEIFS(COMPRAS!$D:$D, COMPRAS!$C:$C, $A18, COMPRAS!$J:$J, $B18), 0) -> 0 | D18: 1.3 | E18: =ROUNDUP(C18 *D18, -3) -> 0 | F18: =IFERROR(AVERAGEIFS(COMPRAS!$F:$F, COMPRAS!$C:$C, $A18, COMPRAS!$J:$J, $B18), 1) -> 1 | G18: =IFERROR(SUMIFS(COMPRAS!I:I, COMPRAS!C:C, A18) * SUMIFS(COMPRAS!E:E, COMPRAS!C:C, A18) / COUNTIF(COMPRAS!C:C, A18), 0) -> 0 | H18: =IFERROR( ((SUMIFS(COMPRAS!$E:$E, COMPRAS!$C:$C, $A18, COMPRAS!$J:$J, "CAJON") + SUMIFS(COMPRAS!$E:$E, COMPRAS!$C:$C, $A18, COMPRAS!$J:$J, "BOLSA")) * $F18) - ((SUMIFS(prueba!$A:$A, prueba!$C:$C, $A18, prueba!$B:$B, "CAJON") + SUMIFS(prueba!$A:$A, prueba!$C:$C, $A18, prueba!$B:$B, "BOLSA")) * $F18) - MAX(0, (SUMIFS(prueba!$A:$A, prueba!$C:$C, $A18, prueba!$B:$B, "UNIDAD") + SUMIFS(prueba!$A:$A, prueba!$C:$C, $A18, prueba!$B:$B, "KG")) - (SUMIFS(COMPRAS!$E:$E, COMPRAS!$C:$C, $A18, COMPRAS!$J:$J, "UNIDAD") + SUMIFS(COMPRAS!$E:$E, COMPRAS!$C:$C, $A18, COMPRAS!$J:$J, "KG"))), 0) -> 0 | I18: =IFERROR(C18 / F18, 0) -> 0 | J18: =IFERROR(ROUNDUP((E18 / F18) * 1.1, -2),0) -> 0 | K18: =A18&B18 -> LECHUGA CAPUCCINACAJON
A19: LECHUGA CAPUCCINA | B19: KG | C19: =IFERROR(AVERAGEIFS(COMPRAS!$D:$D, COMPRAS!$C:$C, $A19, COMPRAS!$J:$J, $B19), 0) -> 0 | D19: 1.3 | E19: =ROUNDUP(C19 *D19, -2) -> 0 | F19: =IFERROR(AVERAGEIFS(COMPRAS!$F:$F, COMPRAS!$C:$C, $A19, COMPRAS!$J:$J, $B19), 1) -> 1 | G19: =IFERROR(SUMIFS(COMPRAS!I:I, COMPRAS!C:C, A19) * SUMIFS(COMPRAS!E:E, COMPRAS!C:C, A19) / COUNTIF(COMPRAS!C:C, A19), 0) -> 0 | H19: =MAX(0, (SUMIFS(COMPRAS!$E:$E, COMPRAS!$C:$C, $A19, COMPRAS!$J:$J, "UNIDAD") + SUMIFS(COMPRAS!$E:$E, COMPRAS!$C:$C, $A19, COMPRAS!$J:$J, "KG")) - (SUMIFS(prueba!$A:$A, prueba!$C:$C, $A19, prueba!$B:$B, "UNIDAD") + SUMIFS(prueba!$A:$A, prueba!$C:$C, $A19, prueba!$B:$B, "KG")) ) -> 0 | I19: =IFERROR(C19 / F19, 0) -> 0 | J19: =IFERROR(ROUNDUP((E19 / F19) * 1.1, -2),0) -> 0 | K19: =A19&B19 -> LECHUGA CAPUCCINAKG
A20: LECHUGA MORADA | B20: CAJON | C20: =IFERROR(AVERAGEIFS(COMPRAS!$D:$D, COMPRAS!$C:$C, $A20, COMPRAS!$J:$J, $B20), 0) -> 0 | D20: 1.3 | E20: =ROUNDUP(C20 *D20, -3) -> 0 | F20: =IFERROR(AVERAGEIFS(COMPRAS!$F:$F, COMPRAS!$C:$C, $A20, COMPRAS!$J:$J, $B20), 1) -> 1 | G20: =IFERROR(SUMIFS(COMPRAS!I:I, COMPRAS!C:C, A20) * SUMIFS(COMPRAS!E:E, COMPRAS!C:C, A20) / COUNTIF(COMPRAS!C:C, A20), 0) -> 0 | H20: =IFERROR( ((SUMIFS(COMPRAS!$E:$E, COMPRAS!$C:$C, $A20, COMPRAS!$J:$J, "CAJON") + SUMIFS(COMPRAS!$E:$E, COMPRAS!$C:$C, $A20, COMPRAS!$J:$J, "BOLSA")) * $F20) - ((SUMIFS(prueba!$A:$A, prueba!$C:$C, $A20, prueba!$B:$B, "CAJON") + SUMIFS(prueba!$A:$A, prueba!$C:$C, $A20, prueba!$B:$B, "BOLSA")) * $F20) - MAX(0, (SUMIFS(prueba!$A:$A, prueba!$C:$C, $A20, prueba!$B:$B, "UNIDAD") + SUMIFS(prueba!$A:$A, prueba!$C:$C, $A20, prueba!$B:$B, "KG")) - (SUMIFS(COMPRAS!$E:$E, COMPRAS!$C:$C, $A20, COMPRAS!$J:$J, "UNIDAD") + SUMIFS(COMPRAS!$E:$E, COMPRAS!$C:$C, $A20, COMPRAS!$J:$J, "KG"))), 0) -> 0 | I20: =IFERROR(C20 / F20, 0) -> 0 | J20: =IFERROR(ROUNDUP((E20 / F20) * 1.1, -2),0) -> 0 | K20: =A20&B20 -> LECHUGA MORADACAJON
A21: LECHUGA MORADA | B21: KG | C21: =IFERROR(AVERAGEIFS(COMPRAS!$D:$D, COMPRAS!$C:$C, $A21, COMPRAS!$J:$J, $B21), 0) -> 0 | D21: 1.3 | E21: =ROUNDUP(C21 *D21, -2) -> 0 | F21: =IFERROR(AVERAGEIFS(COMPRAS!$F:$F, COMPRAS!$C:$C, $A21, COMPRAS!$J:$J, $B21), 1) -> 1 | G21: =IFERROR(SUMIFS(COMPRAS!I:I, COMPRAS!C:C, A21) * SUMIFS(COMPRAS!E:E, COMPRAS!C:C, A21) / COUNTIF(COMPRAS!C:C, A21), 0) -> 0 | H21: =MAX(0, (SUMIFS(COMPRAS!$E:$E, COMPRAS!$C:$C, $A21, COMPRAS!$J:$J, "UNIDAD") + SUMIFS(COMPRAS!$E:$E, COMPRAS!$C:$C, $A21, COMPRAS!$J:$J, "KG")) - (SUMIFS(prueba!$A:$A, prueba!$C:$C, $A21, prueba!$B:$B, "UNIDAD") + SUMIFS(prueba!$A:$A, prueba!$C:$C, $A21, prueba!$B:$B, "KG")) ) -> 0 | I21: =IFERROR(C21 / F21, 0) -> 0 | J21: =IFERROR(ROUNDUP((E21 / F21) * 1.1, -2),0) -> 0 | K21: =A21&B21 -> LECHUGA MORADAKG
A22: LECHUGA CRIOLLA | B22: CAJON | C22: =IFERROR(AVERAGEIFS(COMPRAS!$D:$D, COMPRAS!$C:$C, $A22, COMPRAS!$J:$J, $B22), 0) -> 0 | D22: 1.3 | E22: =ROUNDUP(C22 *D22, -3) -> 0 | F22: =IFERROR(AVERAGEIFS(COMPRAS!$F:$F, COMPRAS!$C:$C, $A22, COMPRAS!$J:$J, $B22), 1) -> 1 | G22: =IFERROR(SUMIFS(COMPRAS!I:I, COMPRAS!C:C, A22) * SUMIFS(COMPRAS!E:E, COMPRAS!C:C, A22) / COUNTIF(COMPRAS!C:C, A22), 0) -> 0 | H22: =IFERROR( ((SUMIFS(COMPRAS!$E:$E, COMPRAS!$C:$C, $A22, COMPRAS!$J:$J, "CAJON") + SUMIFS(COMPRAS!$E:$E, COMPRAS!$C:$C, $A22, COMPRAS!$J:$J, "BOLSA")) * $F22) - ((SUMIFS(prueba!$A:$A, prueba!$C:$C, $A22, prueba!$B:$B, "CAJON") + SUMIFS(prueba!$A:$A, prueba!$C:$C, $A22, prueba!$B:$B, "BOLSA")) * $F22) - MAX(0, (SUMIFS(prueba!$A:$A, prueba!$C:$C, $A22, prueba!$B:$B, "UNIDAD") + SUMIFS(prueba!$A:$A, prueba!$C:$C, $A22, prueba!$B:$B, "KG")) - (SUMIFS(COMPRAS!$E:$E, COMPRAS!$C:$C, $A22, COMPRAS!$J:$J, "UNIDAD") + SUMIFS(COMPRAS!$E:$E, COMPRAS!$C:$C, $A22, COMPRAS!$J:$J, "KG"))), 0) -> 0 | I22: =IFERROR(C22 / F22, 0) -> 0 | J22: =IFERROR(ROUNDUP((E22 / F22) * 1.1, -2),0) -> 0 | K22: =A22&B22 -> LECHUGA CRIOLLACAJON
A23: LECHUGA CRIOLLA | B23: KG | C23: =IFERROR(AVERAGEIFS(COMPRAS!$D:$D, COMPRAS!$C:$C, $A23, COMPRAS!$J:$J, $B23), 0) -> 0 | D23: 1.3 | E23: =ROUNDUP(C23 *D23, -2) -> 0 | F23: =IFERROR(AVERAGEIFS(COMPRAS!$F:$F, COMPRAS!$C:$C, $A23, COMPRAS!$J:$J, $B23), 1) -> 1 | G23: =IFERROR(SUMIFS(COMPRAS!I:I, COMPRAS!C:C, A23) * SUMIFS(COMPRAS!E:E, COMPRAS!C:C, A23) / COUNTIF(COMPRAS!C:C, A23), 0) -> 0 | H23: =MAX(0, (SUMIFS(COMPRAS!$E:$E, COMPRAS!$C:$C, $A23, COMPRAS!$J:$J, "UNIDAD") + SUMIFS(COMPRAS!$E:$E, COMPRAS!$C:$C, $A23, COMPRAS!$J:$J, "KG")) - (SUMIFS(prueba!$A:$A, prueba!$C:$C, $A23, prueba!$B:$B, "UNIDAD") + SUMIFS(prueba!$A:$A, prueba!$C:$C, $A23, prueba!$B:$B, "KG")) ) -> 0 | I23: =IFERROR(C23 / F23, 0) -> 0 | J23: =IFERROR(ROUNDUP((E23 / F23) * 1.1, -2),0) -> 0 | K23: =A23&B23 -> LECHUGA CRIOLLAKG
A24: LECHUGA FRANCESA | B24: CAJON | C24: =IFERROR(AVERAGEIFS(COMPRAS!$D:$D, COMPRAS!$C:$C, $A24, COMPRAS!$J:$J, $B24), 0) -> 0 | D24: 1.3 | E24: =ROUNDUP(C24 *D24, -3) -> 0 | F24: =IFERROR(AVERAGEIFS(COMPRAS!$F:$F, COMPRAS!$C:$C, $A24, COMPRAS!$J:$J, $B24), 1) -> 1 | G24: =IFERROR(SUMIFS(COMPRAS!I:I, COMPRAS!C:C, A24) * SUMIFS(COMPRAS!E:E, COMPRAS!C:C, A24) / COUNTIF(COMPRAS!C:C, A24), 0) -> 0 | H24: =IFERROR( ((SUMIFS(COMPRAS!$E:$E, COMPRAS!$C:$C, $A24, COMPRAS!$J:$J, "CAJON") + SUMIFS(COMPRAS!$E:$E, COMPRAS!$C:$C, $A24, COMPRAS!$J:$J, "BOLSA")) * $F24) - ((SUMIFS(prueba!$A:$A, prueba!$C:$C, $A24, prueba!$B:$B, "CAJON") + SUMIFS(prueba!$A:$A, prueba!$C:$C, $A24, prueba!$B:$B, "BOLSA")) * $F24) - MAX(0, (SUMIFS(prueba!$A:$A, prueba!$C:$C, $A24, prueba!$B:$B, "UNIDAD") + SUMIFS(prueba!$A:$A, prueba!$C:$C, $A24, prueba!$B:$B, "KG")) - (SUMIFS(COMPRAS!$E:$E, COMPRAS!$C:$C, $A24, COMPRAS!$J:$J, "UNIDAD") + SUMIFS(COMPRAS!$E:$E, COMPRAS!$C:$C, $A24, COMPRAS!$J:$J, "KG"))), 0) -> 0 | I24: =IFERROR(C24 / F24, 0) -> 0 | J24: =IFERROR(ROUNDUP((E24 / F24) * 1.1, -2),0) -> 0 | K24: =A24&B24 -> LECHUGA FRANCESACAJON
A25: LECHUGA FRANCESA | B25: KG | C25: =IFERROR(AVERAGEIFS(COMPRAS!$D:$D, COMPRAS!$C:$C, $A25, COMPRAS!$J:$J, $B25), 0) -> 0 | D25: 1.3 | E25: =ROUNDUP(C25 *D25, -2) -> 0 | F25: =IFERROR(AVERAGEIFS(COMPRAS!$F:$F, COMPRAS!$C:$C, $A25, COMPRAS!$J:$J, $B25), 1) -> 1 | G25: =IFERROR(SUMIFS(COMPRAS!I:I, COMPRAS!C:C, A25) * SUMIFS(COMPRAS!E:E, COMPRAS!C:C, A25) / COUNTIF(COMPRAS!C:C, A25), 0) -> 0 | H25: =MAX(0, (SUMIFS(COMPRAS!$E:$E, COMPRAS!$C:$C, $A25, COMPRAS!$J:$J, "UNIDAD") + SUMIFS(COMPRAS!$E:$E, COMPRAS!$C:$C, $A25, COMPRAS!$J:$J, "KG")) - (SUMIFS(prueba!$A:$A, prueba!$C:$C, $A25, prueba!$B:$B, "UNIDAD") + SUMIFS(prueba!$A:$A, prueba!$C:$C, $A25, prueba!$B:$B, "KG")) ) -> 0 | I25: =IFERROR(C25 / F25, 0) -> 0 | J25: =IFERROR(ROUNDUP((E25 / F25) * 1.1, -2),0) -> 0 | K25: =A25&B25 -> LECHUGA FRANCESAKG
A26: LECHUGA MANTECA | B26: CAJON | C26: =IFERROR(AVERAGEIFS(COMPRAS!$D:$D, COMPRAS!$C:$C, $A26, COMPRAS!$J:$J, $B26), 0) -> 0 | D26: 1.3 | E26: =ROUNDUP(C26 * D26, -3) -> 0 | F26: =IFERROR(AVERAGEIFS(COMPRAS!$F:$F, COMPRAS!$C:$C, $A26, COMPRAS!$J:$J, $B26), 1) -> 1 | G26: =IFERROR(SUMIFS(COMPRAS!I:I, COMPRAS!C:C, A26) * SUMIFS(COMPRAS!E:E, COMPRAS!C:C, A26) / COUNTIF(COMPRAS!C:C, A26), 0) -> 0 | H26: =IFERROR( ((SUMIFS(COMPRAS!$E:$E, COMPRAS!$C:$C, $A26, COMPRAS!$J:$J, "CAJON") + SUMIFS(COMPRAS!$E:$E, COMPRAS!$C:$C, $A26, COMPRAS!$J:$J, "BOLSA")) * $F26) - ((SUMIFS(prueba!$A:$A, prueba!$C:$C, $A26, prueba!$B:$B, "CAJON") + SUMIFS(prueba!$A:$A, prueba!$C:$C, $A26, prueba!$B:$B, "BOLSA")) * $F26) - MAX(0, (SUMIFS(prueba!$A:$A, prueba!$C:$C, $A26, prueba!$B:$B, "UNIDAD") + SUMIFS(prueba!$A:$A, prueba!$C:$C, $A26, prueba!$B:$B, "KG")) - (SUMIFS(COMPRAS!$E:$E, COMPRAS!$C:$C, $A26, COMPRAS!$J:$J, "UNIDAD") + SUMIFS(COMPRAS!$E:$E, COMPRAS!$C:$C, $A26, COMPRAS!$J:$J, "KG"))), 0) -> 0 | I26: =IFERROR(C26 / F26, 0) -> 0 | J26: =IFERROR(ROUNDUP((E26 / F26) * 1.1, -2),0) -> 0 | K26: =A26&B26 -> LECHUGA MANTECACAJON
A27: LECHUGA MANTECA | B27: KG | C27: =IFERROR(AVERAGEIFS(COMPRAS!$D:$D, COMPRAS!$C:$C, $A27, COMPRAS!$J:$J, $B27), 0) -> 0 | D27: 1.3 | E27: =ROUNDUP(C27 * D27, -2) -> 0 | F27: =IFERROR(AVERAGEIFS(COMPRAS!$F:$F, COMPRAS!$C:$C, $A27, COMPRAS!$J:$J, $B27), 1) -> 1 | G27: =IFERROR(SUMIFS(COMPRAS!I:I, COMPRAS!C:C, A27) * SUMIFS(COMPRAS!E:E, COMPRAS!C:C, A27) / COUNTIF(COMPRAS!C:C, A27), 0) -> 0 | H27: =MAX(0, (SUMIFS(COMPRAS!$E:$E, COMPRAS!$C:$C, $A27, COMPRAS!$J:$J, "UNIDAD") + SUMIFS(COMPRAS!$E:$E, COMPRAS!$C:$C, $A27, COMPRAS!$J:$J, "KG")) - (SUMIFS(prueba!$A:$A, prueba!$C:$C, $A27, prueba!$B:$B, "UNIDAD") + SUMIFS(prueba!$A:$A, prueba!$C:$C, $A27, prueba!$B:$B, "KG")) ) -> 0 | I27: =IFERROR(C27 / F27, 0) -> 0 | J27: =IFERROR(ROUNDUP((E27 / F27) * 1.1, -2),0) -> 0 | K27: =A27&B27 -> LECHUGA MANTECAKG
A28: PEREJIL | B28: CAJON | C28: =IFERROR(AVERAGEIFS(COMPRAS!$D:$D, COMPRAS!$C:$C, $A28, COMPRAS!$J:$J, $B28), 0) -> 0 | D28: 1.3 | E28: =ROUNDUP(C28 *D28, -3) -> 0 | F28: =IFERROR(AVERAGEIFS(COMPRAS!$F:$F, COMPRAS!$C:$C, $A28, COMPRAS!$J:$J, $B28), 1) -> 1 | G28: =IFERROR(SUMIFS(COMPRAS!I:I, COMPRAS!C:C, A28) * SUMIFS(COMPRAS!E:E, COMPRAS!C:C, A28) / COUNTIF(COMPRAS!C:C, A28), 0) -> 0 | H28: =IFERROR( ((SUMIFS(COMPRAS!$E:$E, COMPRAS!$C:$C, $A28, COMPRAS!$J:$J, "CAJON") + SUMIFS(COMPRAS!$E:$E, COMPRAS!$C:$C, $A28, COMPRAS!$J:$J, "BOLSA")) * $F28) - ((SUMIFS(prueba!$A:$A, prueba!$C:$C, $A28, prueba!$B:$B, "CAJON") + SUMIFS(prueba!$A:$A, prueba!$C:$C, $A28, prueba!$B:$B, "BOLSA")) * $F28) - MAX(0, (SUMIFS(prueba!$A:$A, prueba!$C:$C, $A28, prueba!$B:$B, "UNIDAD") + SUMIFS(prueba!$A:$A, prueba!$C:$C, $A28, prueba!$B:$B, "KG")) - (SUMIFS(COMPRAS!$E:$E, COMPRAS!$C:$C, $A28, COMPRAS!$J:$J, "UNIDAD") + SUMIFS(COMPRAS!$E:$E, COMPRAS!$C:$C, $A28, COMPRAS!$J:$J, "KG"))), 0) -> 0 | I28: =IFERROR(C28 / F28, 0) -> 0 | J28: =IFERROR(ROUNDUP((E28 / F28) * 1.1, -2),0) -> 0 | K28: =A28&B28 -> PEREJILCAJON
A29: PEREJIL | B29: UNIDAD | C29: =IFERROR(AVERAGEIFS(COMPRAS!$D:$D, COMPRAS!$C:$C, $A29, COMPRAS!$J:$J, $B29), 0) -> 0 | D29: 1.3 | E29: =ROUNDUP(C29 *D29, -2) -> 0 | F29: =IFERROR(AVERAGEIFS(COMPRAS!$F:$F, COMPRAS!$C:$C, $A29, COMPRAS!$J:$J, $B29), 1) -> 1 | G29: =IFERROR(SUMIFS(COMPRAS!I:I, COMPRAS!C:C, A29) * SUMIFS(COMPRAS!E:E, COMPRAS!C:C, A29) / COUNTIF(COMPRAS!C:C, A29), 0) -> 0 | H29: =MAX(0, (SUMIFS(COMPRAS!$E:$E, COMPRAS!$C:$C, $A29, COMPRAS!$J:$J, "UNIDAD") + SUMIFS(COMPRAS!$E:$E, COMPRAS!$C:$C, $A29, COMPRAS!$J:$J, "KG")) - (SUMIFS(prueba!$A:$A, prueba!$C:$C, $A29, prueba!$B:$B, "UNIDAD") + SUMIFS(prueba!$A:$A, prueba!$C:$C, $A29, prueba!$B:$B, "KG")) ) -> 0 | I29: =IFERROR(C29 / F29, 0) -> 0 | J29: =IFERROR(ROUNDUP((E29 / F29) * 1.1, -2),0) -> 0 | K29: =A29&B29 -> PEREJILUNIDAD
A30: PUERRO | B30: CAJON | C30: =IFERROR(AVERAGEIFS(COMPRAS!$D:$D, COMPRAS!$C:$C, $A30, COMPRAS!$J:$J, $B30), 0) -> 0 | D30: 1.3 | E30: =ROUNDUP(C30 *D30, -3) -> 0 | F30: =IFERROR(AVERAGEIFS(COMPRAS!$F:$F, COMPRAS!$C:$C, $A30, COMPRAS!$J:$J, $B30), 1) -> 1 | G30: =IFERROR(SUMIFS(COMPRAS!I:I, COMPRAS!C:C, A30) * SUMIFS(COMPRAS!E:E, COMPRAS!C:C, A30) / COUNTIF(COMPRAS!C:C, A30), 0) -> 0 | H30: =IFERROR( ((SUMIFS(COMPRAS!$E:$E, COMPRAS!$C:$C, $A30, COMPRAS!$J:$J, "CAJON") + SUMIFS(COMPRAS!$E:$E, COMPRAS!$C:$C, $A30, COMPRAS!$J:$J, "BOLSA")) * $F30) - ((SUMIFS(prueba!$A:$A, prueba!$C:$C, $A30, prueba!$B:$B, "CAJON") + SUMIFS(prueba!$A:$A, prueba!$C:$C, $A30, prueba!$B:$B, "BOLSA")) * $F30) - MAX(0, (SUMIFS(prueba!$A:$A, prueba!$C:$C, $A30, prueba!$B:$B, "UNIDAD") + SUMIFS(prueba!$A:$A, prueba!$C:$C, $A30, prueba!$B:$B, "KG")) - (SUMIFS(COMPRAS!$E:$E, COMPRAS!$C:$C, $A30, COMPRAS!$J:$J, "UNIDAD") + SUMIFS(COMPRAS!$E:$E, COMPRAS!$C:$C, $A30, COMPRAS!$J:$J, "KG"))), 0) -> 0 | I30: =IFERROR(C30 / F30, 0) -> 0 | J30: =IFERROR(ROUNDUP((E30 / F30) * 1.1, -2),0) -> 0 | K30: =A30&B30 -> PUERROCAJON
A31: PUERRO | B31: UNIDAD | C31: =IFERROR(AVERAGEIFS(COMPRAS!$D:$D, COMPRAS!$C:$C, $A31, COMPRAS!$J:$J, $B31), 0) -> 0 | D31: 1.3 | E31: =ROUNDUP(C31 *D31, -2) -> 0 | F31: =IFERROR(AVERAGEIFS(COMPRAS!$F:$F, COMPRAS!$C:$C, $A31, COMPRAS!$J:$J, $B31), 1) -> 1 | G31: =IFERROR(SUMIFS(COMPRAS!I:I, COMPRAS!C:C, A31) * SUMIFS(COMPRAS!E:E, COMPRAS!C:C, A31) / COUNTIF(COMPRAS!C:C, A31), 0) -> 0 | H31: =MAX(0, (SUMIFS(COMPRAS!$E:$E, COMPRAS!$C:$C, $A31, COMPRAS!$J:$J, "UNIDAD") + SUMIFS(COMPRAS!$E:$E, COMPRAS!$C:$C, $A31, COMPRAS!$J:$J, "KG")) - (SUMIFS(prueba!$A:$A, prueba!$C:$C, $A31, prueba!$B:$B, "UNIDAD") + SUMIFS(prueba!$A:$A, prueba!$C:$C, $A31, prueba!$B:$B, "KG")) ) -> 0 | I31: =IFERROR(C31 / F31, 0) -> 0 | J31: =IFERROR(ROUNDUP((E31 / F31) * 1.1, -2),0) -> 0 | K31: =A31&B31 -> PUERROUNIDAD
A32: RABANITO | B32: CAJON | C32: =IFERROR(AVERAGEIFS(COMPRAS!$D:$D, COMPRAS!$C:$C, $A32, COMPRAS!$J:$J, $B32), 0) -> 0 | D32: 1.3 | E32: =ROUNDUP(C32 *D32, -3) -> 0 | F32: =IFERROR(AVERAGEIFS(COMPRAS!$F:$F, COMPRAS!$C:$C, $A32, COMPRAS!$J:$J, $B32), 1) -> 1 | G32: =IFERROR(SUMIFS(COMPRAS!I:I, COMPRAS!C:C, A32) * SUMIFS(COMPRAS!E:E, COMPRAS!C:C, A32) / COUNTIF(COMPRAS!C:C, A32), 0) -> 0 | H32: =IFERROR( ((SUMIFS(COMPRAS!$E:$E, COMPRAS!$C:$C, $A32, COMPRAS!$J:$J, "CAJON") + SUMIFS(COMPRAS!$E:$E, COMPRAS!$C:$C, $A32, COMPRAS!$J:$J, "BOLSA")) * $F32) - ((SUMIFS(prueba!$A:$A, prueba!$C:$C, $A32, prueba!$B:$B, "CAJON") + SUMIFS(prueba!$A:$A, prueba!$C:$C, $A32, prueba!$B:$B, "BOLSA")) * $F32) - MAX(0, (SUMIFS(prueba!$A:$A, prueba!$C:$C, $A32, prueba!$B:$B, "UNIDAD") + SUMIFS(prueba!$A:$A, prueba!$C:$C, $A32, prueba!$B:$B, "KG")) - (SUMIFS(COMPRAS!$E:$E, COMPRAS!$C:$C, $A32, COMPRAS!$J:$J, "UNIDAD") + SUMIFS(COMPRAS!$E:$E, COMPRAS!$C:$C, $A32, COMPRAS!$J:$J, "KG"))), 0) -> 0 | I32: =IFERROR(C32 / F32, 0) -> 0 | J32: =IFERROR(ROUNDUP((E32 / F32) * 1.1, -2),0) -> 0 | K32: =A32&B32 -> RABANITOCAJON
A33: RABANITO | B33: UNIDAD | C33: =IFERROR(AVERAGEIFS(COMPRAS!$D:$D, COMPRAS!$C:$C, $A33, COMPRAS!$J:$J, $B33), 0) -> 0 | D33: 1.3 | E33: =ROUNDUP(C33 *D33, -2) -> 0 | F33: =IFERROR(AVERAGEIFS(COMPRAS!$F:$F, COMPRAS!$C:$C, $A33, COMPRAS!$J:$J, $B33), 1) -> 1 | G33: =IFERROR(SUMIFS(COMPRAS!I:I, COMPRAS!C:C, A33) * SUMIFS(COMPRAS!E:E, COMPRAS!C:C, A33) / COUNTIF(COMPRAS!C:C, A33), 0) -> 0 | H33: =MAX(0, (SUMIFS(COMPRAS!$E:$E, COMPRAS!$C:$C, $A33, COMPRAS!$J:$J, "UNIDAD") + SUMIFS(COMPRAS!$E:$E, COMPRAS!$C:$C, $A33, COMPRAS!$J:$J, "KG")) - (SUMIFS(prueba!$A:$A, prueba!$C:$C, $A33, prueba!$B:$B, "UNIDAD") + SUMIFS(prueba!$A:$A, prueba!$C:$C, $A33, prueba!$B:$B, "KG")) ) -> 0 | I33: =IFERROR(C33 / F33, 0) -> 0 | J33: =IFERROR(ROUNDUP((E33 / F33) * 1.1, -2),0) -> 0 | K33: =A33&B33 -> RABANITOUNIDAD
A34: REPOLLO BLANCO | B34: CAJON | C34: =IFERROR(AVERAGEIFS(COMPRAS!$D:$D, COMPRAS!$C:$C, $A34, COMPRAS!$J:$J, $B34), 0) -> 0 | D34: 1.3 | E34: =ROUNDUP(C34 *D34, -3) -> 0 | F34: =IFERROR(AVERAGEIFS(COMPRAS!$F:$F, COMPRAS!$C:$C, $A34, COMPRAS!$J:$J, $B34), 1) -> 1 | G34: =IFERROR(SUMIFS(COMPRAS!I:I, COMPRAS!C:C, A34) * SUMIFS(COMPRAS!E:E, COMPRAS!C:C, A34) / COUNTIF(COMPRAS!C:C, A34), 0) -> 0 | H34: =IFERROR( ((SUMIFS(COMPRAS!$E:$E, COMPRAS!$C:$C, $A34, COMPRAS!$J:$J, "CAJON") + SUMIFS(COMPRAS!$E:$E, COMPRAS!$C:$C, $A34, COMPRAS!$J:$J, "BOLSA")) * $F34) - ((SUMIFS(prueba!$A:$A, prueba!$C:$C, $A34, prueba!$B:$B, "CAJON") + SUMIFS(prueba!$A:$A, prueba!$C:$C, $A34, prueba!$B:$B, "BOLSA")) * $F34) - MAX(0, (SUMIFS(prueba!$A:$A, prueba!$C:$C, $A34, prueba!$B:$B, "UNIDAD") + SUMIFS(prueba!$A:$A, prueba!$C:$C, $A34, prueba!$B:$B, "KG")) - (SUMIFS(COMPRAS!$E:$E, COMPRAS!$C:$C, $A34, COMPRAS!$J:$J, "UNIDAD") + SUMIFS(COMPRAS!$E:$E, COMPRAS!$C:$C, $A34, COMPRAS!$J:$J, "KG"))), 0) -> 0 | I34: =IFERROR(C34 / F34, 0) -> 0 | J34: =IFERROR(ROUNDUP((E34 / F34) * 1.1, -2),0) -> 0 | K34: =A34&B34 -> REPOLLO BLANCOCAJON
A35: REPOLLO BLANCO | B35: UNIDAD | C35: =IFERROR(AVERAGEIFS(COMPRAS!$D:$D, COMPRAS!$C:$C, $A35, COMPRAS!$J:$J, $B35), 0) -> 0 | D35: 1.3 | E35: =ROUNDUP(C35 *D35, -2) -> 0 | F35: =IFERROR(AVERAGEIFS(COMPRAS!$F:$F, COMPRAS!$C:$C, $A35, COMPRAS!$J:$J, $B35), 1) -> 1 | G35: =IFERROR(SUMIFS(COMPRAS!I:I, COMPRAS!C:C, A35) * SUMIFS(COMPRAS!E:E, COMPRAS!C:C, A35) / COUNTIF(COMPRAS!C:C, A35), 0) -> 0 | H35: =MAX(0, (SUMIFS(COMPRAS!$E:$E, COMPRAS!$C:$C, $A35, COMPRAS!$J:$J, "UNIDAD") + SUMIFS(COMPRAS!$E:$E, COMPRAS!$C:$C, $A35, COMPRAS!$J:$J, "KG")) - (SUMIFS(prueba!$A:$A, prueba!$C:$C, $A35, prueba!$B:$B, "UNIDAD") + SUMIFS(prueba!$A:$A, prueba!$C:$C, $A35, prueba!$B:$B, "KG")) ) -> 0 | I35: =IFERROR(C35 / F35, 0) -> 0 | J35: =IFERROR(ROUNDUP((E35 / F35) * 1.1, -2),0) -> 0 | K35: =A35&B35 -> REPOLLO BLANCOUNIDAD
A36: REPOLLO ROJO | B36: CAJON | C36: =IFERROR(AVERAGEIFS(COMPRAS!$D:$D, COMPRAS!$C:$C, $A36, COMPRAS!$J:$J, $B36), 0) -> 0 | D36: 1.3 | E36: =ROUNDUP(C36 *D36, -3) -> 0 | F36: =IFERROR(AVERAGEIFS(COMPRAS!$F:$F, COMPRAS!$C:$C, $A36, COMPRAS!$J:$J, $B36), 1) -> 1 | G36: =IFERROR(SUMIFS(COMPRAS!I:I, COMPRAS!C:C, A36) * SUMIFS(COMPRAS!E:E, COMPRAS!C:C, A36) / COUNTIF(COMPRAS!C:C, A36), 0) -> 0 | H36: =IFERROR( ((SUMIFS(COMPRAS!$E:$E, COMPRAS!$C:$C, $A36, COMPRAS!$J:$J, "CAJON") + SUMIFS(COMPRAS!$E:$E, COMPRAS!$C:$C, $A36, COMPRAS!$J:$J, "BOLSA")) * $F36) - ((SUMIFS(prueba!$A:$A, prueba!$C:$C, $A36, prueba!$B:$B, "CAJON") + SUMIFS(prueba!$A:$A, prueba!$C:$C, $A36, prueba!$B:$B, "BOLSA")) * $F36) - MAX(0, (SUMIFS(prueba!$A:$A, prueba!$C:$C, $A36, prueba!$B:$B, "UNIDAD") + SUMIFS(prueba!$A:$A, prueba!$C:$C, $A36, prueba!$B:$B, "KG")) - (SUMIFS(COMPRAS!$E:$E, COMPRAS!$C:$C, $A36, COMPRAS!$J:$J, "UNIDAD") + SUMIFS(COMPRAS!$E:$E, COMPRAS!$C:$C, $A36, COMPRAS!$J:$J, "KG"))), 0) -> 0 | I36: =IFERROR(C36 / F36, 0) -> 0 | J36: =IFERROR(ROUNDUP((E36 / F36) * 1.1, -2),0) -> 0 | K36: =A36&B36 -> REPOLLO ROJOCAJON
A37: REPOLLO ROJO | B37: UNIDAD | C37: =IFERROR(AVERAGEIFS(COMPRAS!$D:$D, COMPRAS!$C:$C, $A37, COMPRAS!$J:$J, $B37), 0) -> 0 | D37: 1.3 | E37: =ROUNDUP(C37 *D37, -2) -> 0 | F37: =IFERROR(AVERAGEIFS(COMPRAS!$F:$F, COMPRAS!$C:$C, $A37, COMPRAS!$J:$J, $B37), 1) -> 1 | G37: =IFERROR(SUMIFS(COMPRAS!I:I, COMPRAS!C:C, A37) * SUMIFS(COMPRAS!E:E, COMPRAS!C:C, A37) / COUNTIF(COMPRAS!C:C, A37), 0) -> 0 | H37: =MAX(0, (SUMIFS(COMPRAS!$E:$E, COMPRAS!$C:$C, $A37, COMPRAS!$J:$J, "UNIDAD") + SUMIFS(COMPRAS!$E:$E, COMPRAS!$C:$C, $A37, COMPRAS!$J:$J, "KG")) - (SUMIFS(prueba!$A:$A, prueba!$C:$C, $A37, prueba!$B:$B, "UNIDAD") + SUMIFS(prueba!$A:$A, prueba!$C:$C, $A37, prueba!$B:$B, "KG")) ) -> 0 | I37: =IFERROR(C37 / F37, 0) -> 0 | J37: =IFERROR(ROUNDUP((E37 / F37) * 1.1, -2),0) -> 0 | K37: =A37&B37 -> REPOLLO ROJOUNIDAD
A38: RUCULA | B38: CAJON | C38: =IFERROR(AVERAGEIFS(COMPRAS!$D:$D, COMPRAS!$C:$C, $A38, COMPRAS!$J:$J, $B38), 0) -> 0 | D38: 1.3 | E38: =ROUNDUP(C38 * D38, -3) -> 0 | F38: =IFERROR(AVERAGEIFS(COMPRAS!$F:$F, COMPRAS!$C:$C, $A38, COMPRAS!$J:$J, $B38), 1) -> 1 | G38: =IFERROR(SUMIFS(COMPRAS!I:I, COMPRAS!C:C, A38) * SUMIFS(COMPRAS!E:E, COMPRAS!C:C, A38) / COUNTIF(COMPRAS!C:C, A38), 0) -> 0 | H38: =IFERROR( ((SUMIFS(COMPRAS!$E:$E, COMPRAS!$C:$C, $A38, COMPRAS!$J:$J, "CAJON") + SUMIFS(COMPRAS!$E:$E, COMPRAS!$C:$C, $A38, COMPRAS!$J:$J, "BOLSA")) * $F38) - ((SUMIFS(prueba!$A:$A, prueba!$C:$C, $A38, prueba!$B:$B, "CAJON") + SUMIFS(prueba!$A:$A, prueba!$C:$C, $A38, prueba!$B:$B, "BOLSA")) * $F38) - MAX(0, (SUMIFS(prueba!$A:$A, prueba!$C:$C, $A38, prueba!$B:$B, "UNIDAD") + SUMIFS(prueba!$A:$A, prueba!$C:$C, $A38, prueba!$B:$B, "KG")) - (SUMIFS(COMPRAS!$E:$E, COMPRAS!$C:$C, $A38, COMPRAS!$J:$J, "UNIDAD") + SUMIFS(COMPRAS!$E:$E, COMPRAS!$C:$C, $A38, COMPRAS!$J:$J, "KG"))), 0) -> 0 | I38: =IFERROR(C38 / F38, 0) -> 0 | J38: =IFERROR(ROUNDUP((E38 / F38) * 1.1, -2),0) -> 0 | K38: =A38&B38 -> RUCULACAJON
A39: RUCULA | B39: UNIDAD | C39: =IFERROR(AVERAGEIFS(COMPRAS!$D:$D, COMPRAS!$C:$C, $A39, COMPRAS!$J:$J, $B39), 0) -> 0 | D39: 1.3 | E39: =ROUNDUP(C39 * D39, -2) -> 0 | F39: =IFERROR(AVERAGEIFS(COMPRAS!$F:$F, COMPRAS!$C:$C, $A39, COMPRAS!$J:$J, $B39), 1) -> 1 | G39: =IFERROR(SUMIFS(COMPRAS!I:I, COMPRAS!C:C, A39) * SUMIFS(COMPRAS!E:E, COMPRAS!C:C, A39) / COUNTIF(COMPRAS!C:C, A39), 0) -> 0 | H39: =MAX(0, (SUMIFS(COMPRAS!$E:$E, COMPRAS!$C:$C, $A39, COMPRAS!$J:$J, "UNIDAD") + SUMIFS(COMPRAS!$E:$E, COMPRAS!$C:$C, $A39, COMPRAS!$J:$J, "KG")) - (SUMIFS(prueba!$A:$A, prueba!$C:$C, $A39, prueba!$B:$B, "UNIDAD") + SUMIFS(prueba!$A:$A, prueba!$C:$C, $A39, prueba!$B:$B, "KG")) ) -> 0 | I39: =IFERROR(C39 / F39, 0) -> 0 | J39: =IFERROR(ROUNDUP((E39 / F39) * 1.1, -2),0) -> 0 | K39: =A39&B39 -> RUCULAUNIDAD
A40: BANANA ECUADOR | B40: CAJON | C40: =IFERROR(AVERAGEIFS(COMPRAS!$D:$D, COMPRAS!$C:$C, $A40, COMPRAS!$J:$J, $B40), 0) -> 0 | D40: 1.3 | E40: =ROUNDUP(C40 *D40, -3) -> 0 | F40: =IFERROR(AVERAGEIFS(COMPRAS!$F:$F, COMPRAS!$C:$C, $A40, COMPRAS!$J:$J, $B40), 1) -> 1 | G40: =IFERROR(SUMIFS(COMPRAS!I:I, COMPRAS!C:C, A40) * SUMIFS(COMPRAS!E:E, COMPRAS!C:C, A40) / COUNTIF(COMPRAS!C:C, A40), 0) -> 0 | H40: =IFERROR( ((SUMIFS(COMPRAS!$E:$E, COMPRAS!$C:$C, $A40, COMPRAS!$J:$J, "CAJON") + SUMIFS(COMPRAS!$E:$E, COMPRAS!$C:$C, $A40, COMPRAS!$J:$J, "BOLSA")) * $F40) - ((SUMIFS(prueba!$A:$A, prueba!$C:$C, $A40, prueba!$B:$B, "CAJON") + SUMIFS(prueba!$A:$A, prueba!$C:$C, $A40, prueba!$B:$B, "BOLSA")) * $F40) - MAX(0, (SUMIFS(prueba!$A:$A, prueba!$C:$C, $A40, prueba!$B:$B, "UNIDAD") + SUMIFS(prueba!$A:$A, prueba!$C:$C, $A40, prueba!$B:$B, "KG")) - (SUMIFS(COMPRAS!$E:$E, COMPRAS!$C:$C, $A40, COMPRAS!$J:$J, "UNIDAD") + SUMIFS(COMPRAS!$E:$E, COMPRAS!$C:$C, $A40, COMPRAS!$J:$J, "KG"))), 0) -> 0 | I40: =IFERROR(C40 / F40, 0) -> 0 | J40: =IFERROR(ROUNDUP((E40 / F40) * 1.1, -2),0) -> 0 | K40: =A40&B40 -> BANANA ECUADORCAJON
A41: BANANA ECUADOR | B41: KG | C41: =IFERROR(AVERAGEIFS(COMPRAS!$D:$D, COMPRAS!$C:$C, $A41, COMPRAS!$J:$J, $B41), 0) -> 0 | D41: 1.3 | E41: =ROUNDUP(C41 *D41, -2) -> 0 | F41: =IFERROR(AVERAGEIFS(COMPRAS!$F:$F, COMPRAS!$C:$C, $A41, COMPRAS!$J:$J, $B41), 1) -> 1 | G41: =IFERROR(SUMIFS(COMPRAS!I:I, COMPRAS!C:C, A41) * SUMIFS(COMPRAS!E:E, COMPRAS!C:C, A41) / COUNTIF(COMPRAS!C:C, A41), 0) -> 0 | H41: =MAX(0, (SUMIFS(COMPRAS!$E:$E, COMPRAS!$C:$C, $A41, COMPRAS!$J:$J, "UNIDAD") + SUMIFS(COMPRAS!$E:$E, COMPRAS!$C:$C, $A41, COMPRAS!$J:$J, "KG")) - (SUMIFS(prueba!$A:$A, prueba!$C:$C, $A41, prueba!$B:$B, "UNIDAD") + SUMIFS(prueba!$A:$A, prueba!$C:$C, $A41, prueba!$B:$B, "KG")) ) -> 0 | I41: =IFERROR(C41 / F41, 0) -> 0 | J41: =IFERROR(ROUNDUP((E41 / F41) * 1.1, -2),0) -> 0 | K41: =A41&B41 -> BANANA ECUADORKG
A42: BANANA BOLIVIA | B42: CAJON | C42: =IFERROR(AVERAGEIFS(COMPRAS!$D:$D, COMPRAS!$C:$C, $A42, COMPRAS!$J:$J, $B42), 0) -> 0 | D42: 1.3 | E42: =ROUNDUP(C42 *D42, -3) -> 0 | F42: =IFERROR(AVERAGEIFS(COMPRAS!$F:$F, COMPRAS!$C:$C, $A42, COMPRAS!$J:$J, $B42), 1) -> 1 | G42: =IFERROR(SUMIFS(COMPRAS!I:I, COMPRAS!C:C, A42) * SUMIFS(COMPRAS!E:E, COMPRAS!C:C, A42) / COUNTIF(COMPRAS!C:C, A42), 0) -> 0 | H42: =IFERROR( ((SUMIFS(COMPRAS!$E:$E, COMPRAS!$C:$C, $A42, COMPRAS!$J:$J, "CAJON") + SUMIFS(COMPRAS!$E:$E, COMPRAS!$C:$C, $A42, COMPRAS!$J:$J, "BOLSA")) * $F42) - ((SUMIFS(prueba!$A:$A, prueba!$C:$C, $A42, prueba!$B:$B, "CAJON") + SUMIFS(prueba!$A:$A, prueba!$C:$C, $A42, prueba!$B:$B, "BOLSA")) * $F42) - MAX(0, (SUMIFS(prueba!$A:$A, prueba!$C:$C, $A42, prueba!$B:$B, "UNIDAD") + SUMIFS(prueba!$A:$A, prueba!$C:$C, $A42, prueba!$B:$B, "KG")) - (SUMIFS(COMPRAS!$E:$E, COMPRAS!$C:$C, $A42, COMPRAS!$J:$J, "UNIDAD") + SUMIFS(COMPRAS!$E:$E, COMPRAS!$C:$C, $A42, COMPRAS!$J:$J, "KG"))), 0) -> 0 | I42: =IFERROR(C42 / F42, 0) -> 0 | J42: =IFERROR(ROUNDUP((E42 / F42) * 1.1, -2),0) -> 0 | K42: =A42&B42 -> BANANA BOLIVIACAJON
A43: BANANA BOLIVIA | B43: KG | C43: =IFERROR(AVERAGEIFS(COMPRAS!$D:$D, COMPRAS!$C:$C, $A43, COMPRAS!$J:$J, $B43), 0) -> 0 | D43: 1.3 | E43: =ROUNDUP(C43 *D43, -2) -> 0 | F43: =IFERROR(AVERAGEIFS(COMPRAS!$F:$F, COMPRAS!$C:$C, $A43, COMPRAS!$J:$J, $B43), 1) -> 1 | G43: =IFERROR(SUMIFS(COMPRAS!I:I, COMPRAS!C:C, A43) * SUMIFS(COMPRAS!E:E, COMPRAS!C:C, A43) / COUNTIF(COMPRAS!C:C, A43), 0) -> 0 | H43: =MAX(0, (SUMIFS(COMPRAS!$E:$E, COMPRAS!$C:$C, $A43, COMPRAS!$J:$J, "UNIDAD") + SUMIFS(COMPRAS!$E:$E, COMPRAS!$C:$C, $A43, COMPRAS!$J:$J, "KG")) - (SUMIFS(prueba!$A:$A, prueba!$C:$C, $A43, prueba!$B:$B, "UNIDAD") + SUMIFS(prueba!$A:$A, prueba!$C:$C, $A43, prueba!$B:$B, "KG")) ) -> 0 | I43: =IFERROR(C43 / F43, 0) -> 0 | J43: =IFERROR(ROUNDUP((E43 / F43) * 1.1, -2),0) -> 0 | K43: =A43&B43 -> BANANA BOLIVIAKG
A44: BANANA PARAGUAY | B44: CAJON | C44: =IFERROR(AVERAGEIFS(COMPRAS!$D:$D, COMPRAS!$C:$C, $A44, COMPRAS!$J:$J, $B44), 0) -> 0 | D44: 1.3 | E44: =ROUNDUP(C44 *D44, -3) -> 0 | F44: =IFERROR(AVERAGEIFS(COMPRAS!$F:$F, COMPRAS!$C:$C, $A44, COMPRAS!$J:$J, $B44), 1) -> 1 | G44: =IFERROR(SUMIFS(COMPRAS!I:I, COMPRAS!C:C, A44) * SUMIFS(COMPRAS!E:E, COMPRAS!C:C, A44) / COUNTIF(COMPRAS!C:C, A44), 0) -> 0 | H44: =IFERROR( ((SUMIFS(COMPRAS!$E:$E, COMPRAS!$C:$C, $A44, COMPRAS!$J:$J, "CAJON") + SUMIFS(COMPRAS!$E:$E, COMPRAS!$C:$C, $A44, COMPRAS!$J:$J, "BOLSA")) * $F44) - ((SUMIFS(prueba!$A:$A, prueba!$C:$C, $A44, prueba!$B:$B, "CAJON") + SUMIFS(prueba!$A:$A, prueba!$C:$C, $A44, prueba!$B:$B, "BOLSA")) * $F44) - MAX(0, (SUMIFS(prueba!$A:$A, prueba!$C:$C, $A44, prueba!$B:$B, "UNIDAD") + SUMIFS(prueba!$A:$A, prueba!$C:$C, $A44, prueba!$B:$B, "KG")) - (SUMIFS(COMPRAS!$E:$E, COMPRAS!$C:$C, $A44, COMPRAS!$J:$J, "UNIDAD") + SUMIFS(COMPRAS!$E:$E, COMPRAS!$C:$C, $A44, COMPRAS!$J:$J, "KG"))), 0) -> 0 | I44: =IFERROR(C44 / F44, 0) -> 0 | J44: =IFERROR(ROUNDUP((E44 / F44) * 1.1, -2),0) -> 0 | K44: =A44&B44 -> BANANA PARAGUAYCAJON
A45: BANANA PARAGUAY | B45: KG | C45: =IFERROR(AVERAGEIFS(COMPRAS!$D:$D, COMPRAS!$C:$C, $A45, COMPRAS!$J:$J, $B45), 0) -> 0 | D45: 1.3 | E45: =ROUNDUP(C45 *D45, -2) -> 0 | F45: =IFERROR(AVERAGEIFS(COMPRAS!$F:$F, COMPRAS!$C:$C, $A45, COMPRAS!$J:$J, $B45), 1) -> 1 | G45: =IFERROR(SUMIFS(COMPRAS!I:I, COMPRAS!C:C, A45) * SUMIFS(COMPRAS!E:E, COMPRAS!C:C, A45) / COUNTIF(COMPRAS!C:C, A45), 0) -> 0 | H45: =MAX(0, (SUMIFS(COMPRAS!$E:$E, COMPRAS!$C:$C, $A45, COMPRAS!$J:$J, "UNIDAD") + SUMIFS(COMPRAS!$E:$E, COMPRAS!$C:$C, $A45, COMPRAS!$J:$J, "KG")) - (SUMIFS(prueba!$A:$A, prueba!$C:$C, $A45, prueba!$B:$B, "UNIDAD") + SUMIFS(prueba!$A:$A, prueba!$C:$C, $A45, prueba!$B:$B, "KG")) ) -> 0 | I45: =IFERROR(C45 / F45, 0) -> 0 | J45: =IFERROR(ROUNDUP((E45 / F45) * 1.1, -2),0) -> 0 | K45: =A45&B45 -> BANANA PARAGUAYKG
A46: FRUTILLA TAMARA | B46: CAJON | C46: =IFERROR(AVERAGEIFS(COMPRAS!$D:$D, COMPRAS!$C:$C, $A46, COMPRAS!$J:$J, $B46), 0) -> 0 | D46: 1.3 | E46: =ROUNDUP(C46 *D46, -3) -> 0 | F46: =IFERROR(AVERAGEIFS(COMPRAS!$F:$F, COMPRAS!$C:$C, $A46, COMPRAS!$J:$J, $B46), 1) -> 1 | G46: =IFERROR(SUMIFS(COMPRAS!I:I, COMPRAS!C:C, A46) * SUMIFS(COMPRAS!E:E, COMPRAS!C:C, A46) / COUNTIF(COMPRAS!C:C, A46), 0) -> 0 | H46: =IFERROR( ((SUMIFS(COMPRAS!$E:$E, COMPRAS!$C:$C, $A46, COMPRAS!$J:$J, "CAJON") + SUMIFS(COMPRAS!$E:$E, COMPRAS!$C:$C, $A46, COMPRAS!$J:$J, "BOLSA")) * $F46) - ((SUMIFS(prueba!$A:$A, prueba!$C:$C, $A46, prueba!$B:$B, "CAJON") + SUMIFS(prueba!$A:$A, prueba!$C:$C, $A46, prueba!$B:$B, "BOLSA")) * $F46) - MAX(0, (SUMIFS(prueba!$A:$A, prueba!$C:$C, $A46, prueba!$B:$B, "UNIDAD") + SUMIFS(prueba!$A:$A, prueba!$C:$C, $A46, prueba!$B:$B, "KG")) - (SUMIFS(COMPRAS!$E:$E, COMPRAS!$C:$C, $A46, COMPRAS!$J:$J, "UNIDAD") + SUMIFS(COMPRAS!$E:$E, COMPRAS!$C:$C, $A46, COMPRAS!$J:$J, "KG"))), 0) -> 0 | I46: =IFERROR(C46 / F46, 0) -> 0 | J46: =IFERROR(ROUNDUP((E46 / F46) * 1.1, -2),0) -> 0 | K46: =A46&B46 -> FRUTILLA TAMARACAJON
A47: FRUTILLA TAMARA | B47: KG | C47: =IFERROR(AVERAGEIFS(COMPRAS!$D:$D, COMPRAS!$C:$C, $A47, COMPRAS!$J:$J, $B47), 0) -> 0 | D47: 1.3 | E47: =ROUNDUP(C47 *D47, -2) -> 0 | F47: =IFERROR(AVERAGEIFS(COMPRAS!$F:$F, COMPRAS!$C:$C, $A47, COMPRAS!$J:$J, $B47), 1) -> 1 | G47: =IFERROR(SUMIFS(COMPRAS!I:I, COMPRAS!C:C, A47) * SUMIFS(COMPRAS!E:E, COMPRAS!C:C, A47) / COUNTIF(COMPRAS!C:C, A47), 0) -> 0 | H47: =MAX(0, (SUMIFS(COMPRAS!$E:$E, COMPRAS!$C:$C, $A47, COMPRAS!$J:$J, "UNIDAD") + SUMIFS(COMPRAS!$E:$E, COMPRAS!$C:$C, $A47, COMPRAS!$J:$J, "KG")) - (SUMIFS(prueba!$A:$A, prueba!$C:$C, $A47, prueba!$B:$B, "UNIDAD") + SUMIFS(prueba!$A:$A, prueba!$C:$C, $A47, prueba!$B:$B, "KG")) ) -> 0 | I47: =IFERROR(C47 / F47, 0) -> 0 | J47: =IFERROR(ROUNDUP((E47 / F47) * 1.1, -2),0) -> 0 | K47: =A47&B47 -> FRUTILLA TAMARAKG
A48: FRUTILLA | B48: CAJON | C48: =IFERROR(AVERAGEIFS(COMPRAS!$D:$D, COMPRAS!$C:$C, $A48, COMPRAS!$J:$J, $B48), 0) -> 0 | D48: 1.3 | E48: =ROUNDUP(C48 *D48, -3) -> 0 | F48: =IFERROR(AVERAGEIFS(COMPRAS!$F:$F, COMPRAS!$C:$C, $A48, COMPRAS!$J:$J, $B48), 1) -> 1 | G48: =IFERROR(SUMIFS(COMPRAS!I:I, COMPRAS!C:C, A48) * SUMIFS(COMPRAS!E:E, COMPRAS!C:C, A48) / COUNTIF(COMPRAS!C:C, A48), 0) -> 0 | H48: =IFERROR( ((SUMIFS(COMPRAS!$E:$E, COMPRAS!$C:$C, $A48, COMPRAS!$J:$J, "CAJON") + SUMIFS(COMPRAS!$E:$E, COMPRAS!$C:$C, $A48, COMPRAS!$J:$J, "BOLSA")) * $F48) - ((SUMIFS(prueba!$A:$A, prueba!$C:$C, $A48, prueba!$B:$B, "CAJON") + SUMIFS(prueba!$A:$A, prueba!$C:$C, $A48, prueba!$B:$B, "BOLSA")) * $F48) - MAX(0, (SUMIFS(prueba!$A:$A, prueba!$C:$C, $A48, prueba!$B:$B, "UNIDAD") + SUMIFS(prueba!$A:$A, prueba!$C:$C, $A48, prueba!$B:$B, "KG")) - (SUMIFS(COMPRAS!$E:$E, COMPRAS!$C:$C, $A48, COMPRAS!$J:$J, "UNIDAD") + SUMIFS(COMPRAS!$E:$E, COMPRAS!$C:$C, $A48, COMPRAS!$J:$J, "KG"))), 0) -> 0 | I48: =IFERROR(C48 / F48, 0) -> 0 | J48: =IFERROR(ROUNDUP((E48 / F48) * 1.1, -2),0) -> 0 | K48: =A48&B48 -> FRUTILLACAJON
A49: FRUTILLA | B49: KG | C49: =IFERROR(AVERAGEIFS(COMPRAS!$D:$D, COMPRAS!$C:$C, $A49, COMPRAS!$J:$J, $B49), 0) -> 0 | D49: 1.3 | E49: =ROUNDUP(C49 *D49, -2) -> 0 | F49: =IFERROR(AVERAGEIFS(COMPRAS!$F:$F, COMPRAS!$C:$C, $A49, COMPRAS!$J:$J, $B49), 1) -> 1 | G49: =IFERROR(SUMIFS(COMPRAS!I:I, COMPRAS!C:C, A49) * SUMIFS(COMPRAS!E:E, COMPRAS!C:C, A49) / COUNTIF(COMPRAS!C:C, A49), 0) -> 0 | H49: =MAX(0, (SUMIFS(COMPRAS!$E:$E, COMPRAS!$C:$C, $A49, COMPRAS!$J:$J, "UNIDAD") + SUMIFS(COMPRAS!$E:$E, COMPRAS!$C:$C, $A49, COMPRAS!$J:$J, "KG")) - (SUMIFS(prueba!$A:$A, prueba!$C:$C, $A49, prueba!$B:$B, "UNIDAD") + SUMIFS(prueba!$A:$A, prueba!$C:$C, $A49, prueba!$B:$B, "KG")) ) -> 0 | I49: =IFERROR(C49 / F49, 0) -> 0 | J49: =IFERROR(ROUNDUP((E49 / F49) * 1.1, -2),0) -> 0 | K49: =A49&B49 -> FRUTILLAKG
A50: KIWI | B50: CAJON | C50: =IFERROR(AVERAGEIFS(COMPRAS!$D:$D, COMPRAS!$C:$C, $A50, COMPRAS!$J:$J, $B50), 0) -> 0 | D50: 1.3 | E50: =ROUNDUP(C50 * D50, -3) -> 0 | F50: =IFERROR(AVERAGEIFS(COMPRAS!$F:$F, COMPRAS!$C:$C, $A50, COMPRAS!$J:$J, $B50), 1) -> 1 | G50: =IFERROR(SUMIFS(COMPRAS!I:I, COMPRAS!C:C, A50) * SUMIFS(COMPRAS!E:E, COMPRAS!C:C, A50) / COUNTIF(COMPRAS!C:C, A50), 0) -> 0 | H50: =IFERROR( ((SUMIFS(COMPRAS!$E:$E, COMPRAS!$C:$C, $A50, COMPRAS!$J:$J, "CAJON") + SUMIFS(COMPRAS!$E:$E, COMPRAS!$C:$C, $A50, COMPRAS!$J:$J, "BOLSA")) * $F50) - ((SUMIFS(prueba!$A:$A, prueba!$C:$C, $A50, prueba!$B:$B, "CAJON") + SUMIFS(prueba!$A:$A, prueba!$C:$C, $A50, prueba!$B:$B, "BOLSA")) * $F50) - MAX(0, (SUMIFS(prueba!$A:$A, prueba!$C:$C, $A50, prueba!$B:$B, "UNIDAD") + SUMIFS(prueba!$A:$A, prueba!$C:$C, $A50, prueba!$B:$B, "KG")) - (SUMIFS(COMPRAS!$E:$E, COMPRAS!$C:$C, $A50, COMPRAS!$J:$J, "UNIDAD") + SUMIFS(COMPRAS!$E:$E, COMPRAS!$C:$C, $A50, COMPRAS!$J:$J, "KG"))), 0) -> 0 | I50: =IFERROR(C50 / F50, 0) -> 0 | J50: =IFERROR(ROUNDUP((E50 / F50) * 1.1, -2),0) -> 0 | K50: =A50&B50 -> KIWICAJON
A51: KIWI | B51: KG | C51: =IFERROR(AVERAGEIFS(COMPRAS!$D:$D, COMPRAS!$C:$C, $A51, COMPRAS!$J:$J, $B51), 0) -> 0 | D51: 1.3 | E51: =ROUNDUP(C51 * D51, -2) -> 0 | F51: =IFERROR(AVERAGEIFS(COMPRAS!$F:$F, COMPRAS!$C:$C, $A51, COMPRAS!$J:$J, $B51), 1) -> 1 | G51: =IFERROR(SUMIFS(COMPRAS!I:I, COMPRAS!C:C, A51) * SUMIFS(COMPRAS!E:E, COMPRAS!C:C, A51) / COUNTIF(COMPRAS!C:C, A51), 0) -> 0 | H51: =MAX(0, (SUMIFS(COMPRAS!$E:$E, COMPRAS!$C:$C, $A51, COMPRAS!$J:$J, "UNIDAD") + SUMIFS(COMPRAS!$E:$E, COMPRAS!$C:$C, $A51, COMPRAS!$J:$J, "KG")) - (SUMIFS(prueba!$A:$A, prueba!$C:$C, $A51, prueba!$B:$B, "UNIDAD") + SUMIFS(prueba!$A:$A, prueba!$C:$C, $A51, prueba!$B:$B, "KG")) ) -> 0 | I51: =IFERROR(C51 / F51, 0) -> 0 | J51: =IFERROR(ROUNDUP((E51 / F51) * 1.1, -2),0) -> 0 | K51: =A51&B51 -> KIWIKG
A52: LIMA | B52: CAJON | C52: =IFERROR(AVERAGEIFS(COMPRAS!$D:$D, COMPRAS!$C:$C, $A52, COMPRAS!$J:$J, $B52), 0) -> 0 | D52: 1.3 | E52: =ROUNDUP(C52 *D52, -3) -> 0 | F52: =IFERROR(AVERAGEIFS(COMPRAS!$F:$F, COMPRAS!$C:$C, $A52, COMPRAS!$J:$J, $B52), 1) -> 1 | G52: =IFERROR(SUMIFS(COMPRAS!I:I, COMPRAS!C:C, A52) * SUMIFS(COMPRAS!E:E, COMPRAS!C:C, A52) / COUNTIF(COMPRAS!C:C, A52), 0) -> 0 | H52: =IFERROR( ((SUMIFS(COMPRAS!$E:$E, COMPRAS!$C:$C, $A52, COMPRAS!$J:$J, "CAJON") + SUMIFS(COMPRAS!$E:$E, COMPRAS!$C:$C, $A52, COMPRAS!$J:$J, "BOLSA")) * $F52) - ((SUMIFS(prueba!$A:$A, prueba!$C:$C, $A52, prueba!$B:$B, "CAJON") + SUMIFS(prueba!$A:$A, prueba!$C:$C, $A52, prueba!$B:$B, "BOLSA")) * $F52) - MAX(0, (SUMIFS(prueba!$A:$A, prueba!$C:$C, $A52, prueba!$B:$B, "UNIDAD") + SUMIFS(prueba!$A:$A, prueba!$C:$C, $A52, prueba!$B:$B, "KG")) - (SUMIFS(COMPRAS!$E:$E, COMPRAS!$C:$C, $A52, COMPRAS!$J:$J, "UNIDAD") + SUMIFS(COMPRAS!$E:$E, COMPRAS!$C:$C, $A52, COMPRAS!$J:$J, "KG"))), 0) -> 0 | I52: =IFERROR(C52 / F52, 0) -> 0 | J52: =IFERROR(ROUNDUP((E52 / F52) * 1.1, -2),0) -> 0 | K52: =A52&B52 -> LIMACAJON
A53: LIMA | B53: KG | C53: =IFERROR(AVERAGEIFS(COMPRAS!$D:$D, COMPRAS!$C:$C, $A53, COMPRAS!$J:$J, $B53), 0) -> 0 | D53: 1.3 | E53: =ROUNDUP(C53 *D53, -2) -> 0 | F53: =IFERROR(AVERAGEIFS(COMPRAS!$F:$F, COMPRAS!$C:$C, $A53, COMPRAS!$J:$J, $B53), 1) -> 1 | G53: =IFERROR(SUMIFS(COMPRAS!I:I, COMPRAS!C:C, A53) * SUMIFS(COMPRAS!E:E, COMPRAS!C:C, A53) / COUNTIF(COMPRAS!C:C, A53), 0) -> 0 | H53: =MAX(0, (SUMIFS(COMPRAS!$E:$E, COMPRAS!$C:$C, $A53, COMPRAS!$J:$J, "UNIDAD") + SUMIFS(COMPRAS!$E:$E, COMPRAS!$C:$C, $A53, COMPRAS!$J:$J, "KG")) - (SUMIFS(prueba!$A:$A, prueba!$C:$C, $A53, prueba!$B:$B, "UNIDAD") + SUMIFS(prueba!$A:$A, prueba!$C:$C, $A53, prueba!$B:$B, "KG")) ) -> 0 | I53: =IFERROR(C53 / F53, 0) -> 0 | J53: =IFERROR(ROUNDUP((E53 / F53) * 1.1, -2),0) -> 0 | K53: =A53&B53 -> LIMAKG
A54: LIMON | B54: CAJON | C54: =IFERROR(AVERAGEIFS(COMPRAS!$D:$D, COMPRAS!$C:$C, $A54, COMPRAS!$J:$J, $B54), 0) -> 0 | D54: 1.3 | E54: =ROUNDUP(C54 *D54, -3) -> 0 | F54: =IFERROR(AVERAGEIFS(COMPRAS!$F:$F, COMPRAS!$C:$C, $A54, COMPRAS!$J:$J, $B54), 1) -> 1 | G54: =IFERROR(SUMIFS(COMPRAS!I:I, COMPRAS!C:C, A54) * SUMIFS(COMPRAS!E:E, COMPRAS!C:C, A54) / COUNTIF(COMPRAS!C:C, A54), 0) -> 0 | H54: =IFERROR( ((SUMIFS(COMPRAS!$E:$E, COMPRAS!$C:$C, $A54, COMPRAS!$J:$J, "CAJON") + SUMIFS(COMPRAS!$E:$E, COMPRAS!$C:$C, $A54, COMPRAS!$J:$J, "BOLSA")) * $F54) - ((SUMIFS(prueba!$A:$A, prueba!$C:$C, $A54, prueba!$B:$B, "CAJON") + SUMIFS(prueba!$A:$A, prueba!$C:$C, $A54, prueba!$B:$B, "BOLSA")) * $F54) - MAX(0, (SUMIFS(prueba!$A:$A, prueba!$C:$C, $A54, prueba!$B:$B, "UNIDAD") + SUMIFS(prueba!$A:$A, prueba!$C:$C, $A54, prueba!$B:$B, "KG")) - (SUMIFS(COMPRAS!$E:$E, COMPRAS!$C:$C, $A54, COMPRAS!$J:$J, "UNIDAD") + SUMIFS(COMPRAS!$E:$E, COMPRAS!$C:$C, $A54, COMPRAS!$J:$J, "KG"))), 0) -> 0 | I54: =IFERROR(C54 / F54, 0) -> 0 | J54: =IFERROR(ROUNDUP((E54 / F54) * 1.1, -2),0) -> 0 | K54: =A54&B54 -> LIMONCAJON
A55: LIMON | B55: KG | C55: =IFERROR(AVERAGEIFS(COMPRAS!$D:$D, COMPRAS!$C:$C, $A55, COMPRAS!$J:$J, $B55), 0) -> 0 | D55: 1.3 | E55: =ROUNDUP(C55 *D55, -2) -> 0 | F55: =IFERROR(AVERAGEIFS(COMPRAS!$F:$F, COMPRAS!$C:$C, $A55, COMPRAS!$J:$J, $B55), 1) -> 1 | G55: =IFERROR(SUMIFS(COMPRAS!I:I, COMPRAS!C:C, A55) * SUMIFS(COMPRAS!E:E, COMPRAS!C:C, A55) / COUNTIF(COMPRAS!C:C, A55), 0) -> 0 | H55: =MAX(0, (SUMIFS(COMPRAS!$E:$E, COMPRAS!$C:$C, $A55, COMPRAS!$J:$J, "UNIDAD") + SUMIFS(COMPRAS!$E:$E, COMPRAS!$C:$C, $A55, COMPRAS!$J:$J, "KG")) - (SUMIFS(prueba!$A:$A, prueba!$C:$C, $A55, prueba!$B:$B, "UNIDAD") + SUMIFS(prueba!$A:$A, prueba!$C:$C, $A55, prueba!$B:$B, "KG")) ) -> 0 | I55: =IFERROR(C55 / F55, 0) -> 0 | J55: =IFERROR(ROUNDUP((E55 / F55) * 1.1, -2),0) -> 0 | K55: =A55&B55 -> LIMONKG
A56: MANDARINA | B56: CAJON | C56: =IFERROR(AVERAGEIFS(COMPRAS!$D:$D, COMPRAS!$C:$C, $A56, COMPRAS!$J:$J, $B56), 0) -> 0 | D56: 1.3 | E56: =ROUNDUP(C56 *D56, -3) -> 0 | F56: =IFERROR(AVERAGEIFS(COMPRAS!$F:$F, COMPRAS!$C:$C, $A56, COMPRAS!$J:$J, $B56), 1) -> 1 | G56: =IFERROR(SUMIFS(COMPRAS!I:I, COMPRAS!C:C, A56) * SUMIFS(COMPRAS!E:E, COMPRAS!C:C, A56) / COUNTIF(COMPRAS!C:C, A56), 0) -> 0 | H56: =IFERROR( ((SUMIFS(COMPRAS!$E:$E, COMPRAS!$C:$C, $A56, COMPRAS!$J:$J, "CAJON") + SUMIFS(COMPRAS!$E:$E, COMPRAS!$C:$C, $A56, COMPRAS!$J:$J, "BOLSA")) * $F56) - ((SUMIFS(prueba!$A:$A, prueba!$C:$C, $A56, prueba!$B:$B, "CAJON") + SUMIFS(prueba!$A:$A, prueba!$C:$C, $A56, prueba!$B:$B, "BOLSA")) * $F56) - MAX(0, (SUMIFS(prueba!$A:$A, prueba!$C:$C, $A56, prueba!$B:$B, "UNIDAD") + SUMIFS(prueba!$A:$A, prueba!$C:$C, $A56, prueba!$B:$B, "KG")) - (SUMIFS(COMPRAS!$E:$E, COMPRAS!$C:$C, $A56, COMPRAS!$J:$J, "UNIDAD") + SUMIFS(COMPRAS!$E:$E, COMPRAS!$C:$C, $A56, COMPRAS!$J:$J, "KG"))), 0) -> 0 | I56: =IFERROR(C56 / F56, 0) -> 0 | J56: =IFERROR(ROUNDUP((E56 / F56) * 1.1, -2),0) -> 0 | K56: =A56&B56 -> MANDARINACAJON
A57: MANDARINA | B57: KG | C57: =IFERROR(AVERAGEIFS(COMPRAS!$D:$D, COMPRAS!$C:$C, $A57, COMPRAS!$J:$J, $B57), 0) -> 0 | D57: 1.3 | E57: =ROUNDUP(C57 *D57, -2) -> 0 | F57: =IFERROR(AVERAGEIFS(COMPRAS!$F:$F, COMPRAS!$C:$C, $A57, COMPRAS!$J:$J, $B57), 1) -> 1 | G57: =IFERROR(SUMIFS(COMPRAS!I:I, COMPRAS!C:C, A57) * SUMIFS(COMPRAS!E:E, COMPRAS!C:C, A57) / COUNTIF(COMPRAS!C:C, A57), 0) -> 0 | H57: =MAX(0, (SUMIFS(COMPRAS!$E:$E, COMPRAS!$C:$C, $A57, COMPRAS!$J:$J, "UNIDAD") + SUMIFS(COMPRAS!$E:$E, COMPRAS!$C:$C, $A57, COMPRAS!$J:$J, "KG")) - (SUMIFS(prueba!$A:$A, prueba!$C:$C, $A57, prueba!$B:$B, "UNIDAD") + SUMIFS(prueba!$A:$A, prueba!$C:$C, $A57, prueba!$B:$B, "KG")) ) -> 0 | I57: =IFERROR(C57 / F57, 0) -> 0 | J57: =IFERROR(ROUNDUP((E57 / F57) * 1.1, -2),0) -> 0 | K57: =A57&B57 -> MANDARINAKG
A58: MANGO | B58: CAJON | C58: =IFERROR(AVERAGEIFS(COMPRAS!$D:$D, COMPRAS!$C:$C, $A58, COMPRAS!$J:$J, $B58), 0) -> 0 | D58: 1.3 | E58: =ROUNDUP(C58 *D58, -3) -> 0 | F58: =IFERROR(AVERAGEIFS(COMPRAS!$F:$F, COMPRAS!$C:$C, $A58, COMPRAS!$J:$J, $B58), 1) -> 1 | G58: =IFERROR(SUMIFS(COMPRAS!I:I, COMPRAS!C:C, A58) * SUMIFS(COMPRAS!E:E, COMPRAS!C:C, A58) / COUNTIF(COMPRAS!C:C, A58), 0) -> 0 | H58: =IFERROR( ((SUMIFS(COMPRAS!$E:$E, COMPRAS!$C:$C, $A58, COMPRAS!$J:$J, "CAJON") + SUMIFS(COMPRAS!$E:$E, COMPRAS!$C:$C, $A58, COMPRAS!$J:$J, "BOLSA")) * $F58) - ((SUMIFS(prueba!$A:$A, prueba!$C:$C, $A58, prueba!$B:$B, "CAJON") + SUMIFS(prueba!$A:$A, prueba!$C:$C, $A58, prueba!$B:$B, "BOLSA")) * $F58) - MAX(0, (SUMIFS(prueba!$A:$A, prueba!$C:$C, $A58, prueba!$B:$B, "UNIDAD") + SUMIFS(prueba!$A:$A, prueba!$C:$C, $A58, prueba!$B:$B, "KG")) - (SUMIFS(COMPRAS!$E:$E, COMPRAS!$C:$C, $A58, COMPRAS!$J:$J, "UNIDAD") + SUMIFS(COMPRAS!$E:$E, COMPRAS!$C:$C, $A58, COMPRAS!$J:$J, "KG"))), 0) -> 0 | I58: =IFERROR(C58 / F58, 0) -> 0 | J58: =IFERROR(ROUNDUP((E58 / F58) * 1.1, -2),0) -> 0 | K58: =A58&B58 -> MANGOCAJON
A59: MANGO | B59: UNIDAD | C59: =IFERROR(AVERAGEIFS(COMPRAS!$D:$D, COMPRAS!$C:$C, $A59, COMPRAS!$J:$J, $B59), 0) -> 0 | D59: 1.3 | E59: =ROUNDUP(C59 *D59, -2) -> 0 | F59: =IFERROR(AVERAGEIFS(COMPRAS!$F:$F, COMPRAS!$C:$C, $A59, COMPRAS!$J:$J, $B59), 1) -> 1 | G59: =IFERROR(SUMIFS(COMPRAS!I:I, COMPRAS!C:C, A59) * SUMIFS(COMPRAS!E:E, COMPRAS!C:C, A59) / COUNTIF(COMPRAS!C:C, A59), 0) -> 0 | H59: =MAX(0, (SUMIFS(COMPRAS!$E:$E, COMPRAS!$C:$C, $A59, COMPRAS!$J:$J, "UNIDAD") + SUMIFS(COMPRAS!$E:$E, COMPRAS!$C:$C, $A59, COMPRAS!$J:$J, "KG")) - (SUMIFS(prueba!$A:$A, prueba!$C:$C, $A59, prueba!$B:$B, "UNIDAD") + SUMIFS(prueba!$A:$A, prueba!$C:$C, $A59, prueba!$B:$B, "KG")) ) -> 0 | I59: =IFERROR(C59 / F59, 0) -> 0 | J59: =IFERROR(ROUNDUP((E59 / F59) * 1.1, -2),0) -> 0 | K59: =A59&B59 -> MANGOUNIDAD
A60: MANZANA ROJA ELEGIDA | B60: CAJON | C60: =IFERROR(AVERAGEIFS(COMPRAS!$D:$D, COMPRAS!$C:$C, $A60, COMPRAS!$J:$J, $B60), 0) -> 0 | D60: 1.3 | E60: =ROUNDUP(C60 *D60, -3) -> 0 | F60: =IFERROR(AVERAGEIFS(COMPRAS!$F:$F, COMPRAS!$C:$C, $A60, COMPRAS!$J:$J, $B60), 1) -> 1 | G60: =IFERROR(SUMIFS(COMPRAS!I:I, COMPRAS!C:C, A60) * SUMIFS(COMPRAS!E:E, COMPRAS!C:C, A60) / COUNTIF(COMPRAS!C:C, A60), 0) -> 0 | H60: =IFERROR( ((SUMIFS(COMPRAS!$E:$E, COMPRAS!$C:$C, $A60, COMPRAS!$J:$J, "CAJON") + SUMIFS(COMPRAS!$E:$E, COMPRAS!$C:$C, $A60, COMPRAS!$J:$J, "BOLSA")) * $F60) - ((SUMIFS(prueba!$A:$A, prueba!$C:$C, $A60, prueba!$B:$B, "CAJON") + SUMIFS(prueba!$A:$A, prueba!$C:$C, $A60, prueba!$B:$B, "BOLSA")) * $F60) - MAX(0, (SUMIFS(prueba!$A:$A, prueba!$C:$C, $A60, prueba!$B:$B, "UNIDAD") + SUMIFS(prueba!$A:$A, prueba!$C:$C, $A60, prueba!$B:$B, "KG")) - (SUMIFS(COMPRAS!$E:$E, COMPRAS!$C:$C, $A60, COMPRAS!$J:$J, "UNIDAD") + SUMIFS(COMPRAS!$E:$E, COMPRAS!$C:$C, $A60, COMPRAS!$J:$J, "KG"))), 0) -> 0 | I60: =IFERROR(C60 / F60, 0) -> 0 | J60: =IFERROR(ROUNDUP((E60 / F60) * 1.1, -2),0) -> 0 | K60: =A60&B60 -> MANZANA ROJA ELEGIDACAJON
A61: MANZANA ROJA ELEGIDA | B61: KG | C61: =IFERROR(AVERAGEIFS(COMPRAS!$D:$D, COMPRAS!$C:$C, $A61, COMPRAS!$J:$J, $B61), 0) -> 0 | D61: 1.3 | E61: =ROUNDUP(C61 *D61, -2) -> 0 | F61: =IFERROR(AVERAGEIFS(COMPRAS!$F:$F, COMPRAS!$C:$C, $A61, COMPRAS!$J:$J, $B61), 1) -> 1 | G61: =IFERROR(SUMIFS(COMPRAS!I:I, COMPRAS!C:C, A61) * SUMIFS(COMPRAS!E:E, COMPRAS!C:C, A61) / COUNTIF(COMPRAS!C:C, A61), 0) -> 0 | H61: =MAX(0, (SUMIFS(COMPRAS!$E:$E, COMPRAS!$C:$C, $A61, COMPRAS!$J:$J, "UNIDAD") + SUMIFS(COMPRAS!$E:$E, COMPRAS!$C:$C, $A61, COMPRAS!$J:$J, "KG")) - (SUMIFS(prueba!$A:$A, prueba!$C:$C, $A61, prueba!$B:$B, "UNIDAD") + SUMIFS(prueba!$A:$A, prueba!$C:$C, $A61, prueba!$B:$B, "KG")) ) -> 0 | I61: =IFERROR(C61 / F61, 0) -> 0 | J61: =IFERROR(ROUNDUP((E61 / F61) * 1.1, -2),0) -> 0 | K61: =A61&B61 -> MANZANA ROJA ELEGIDAKG
A62: MANZANA ROJA COMERCIAL | B62: CAJON | C62: =IFERROR(AVERAGEIFS(COMPRAS!$D:$D, COMPRAS!$C:$C, $A62, COMPRAS!$J:$J, $B62), 0) -> 0 | D62: 1.3 | E62: =ROUNDUP(C62 * D62, -3) -> 0 | F62: =IFERROR(AVERAGEIFS(COMPRAS!$F:$F, COMPRAS!$C:$C, $A62, COMPRAS!$J:$J, $B62), 1) -> 1 | G62: =IFERROR(SUMIFS(COMPRAS!I:I, COMPRAS!C:C, A62) * SUMIFS(COMPRAS!E:E, COMPRAS!C:C, A62) / COUNTIF(COMPRAS!C:C, A62), 0) -> 0 | H62: =IFERROR( ((SUMIFS(COMPRAS!$E:$E, COMPRAS!$C:$C, $A62, COMPRAS!$J:$J, "CAJON") + SUMIFS(COMPRAS!$E:$E, COMPRAS!$C:$C, $A62, COMPRAS!$J:$J, "BOLSA")) * $F62) - ((SUMIFS(prueba!$A:$A, prueba!$C:$C, $A62, prueba!$B:$B, "CAJON") + SUMIFS(prueba!$A:$A, prueba!$C:$C, $A62, prueba!$B:$B, "BOLSA")) * $F62) - MAX(0, (SUMIFS(prueba!$A:$A, prueba!$C:$C, $A62, prueba!$B:$B, "UNIDAD") + SUMIFS(prueba!$A:$A, prueba!$C:$C, $A62, prueba!$B:$B, "KG")) - (SUMIFS(COMPRAS!$E:$E, COMPRAS!$C:$C, $A62, COMPRAS!$J:$J, "UNIDAD") + SUMIFS(COMPRAS!$E:$E, COMPRAS!$C:$C, $A62, COMPRAS!$J:$J, "KG"))), 0) -> 0 | I62: =IFERROR(C62 / F62, 0) -> 0 | J62: =IFERROR(ROUNDUP((E62 / F62) * 1.1, -2),0) -> 0 | K62: =A62&B62 -> MANZANA ROJA COMERCIALCAJON
A63: MANZANA ROJA COMERCIAL | B63: KG | C63: =IFERROR(AVERAGEIFS(COMPRAS!$D:$D, COMPRAS!$C:$C, $A63, COMPRAS!$J:$J, $B63), 0) -> 0 | D63: 1.3 | E63: =ROUNDUP(C63 * D63, -2) -> 0 | F63: =IFERROR(AVERAGEIFS(COMPRAS!$F:$F, COMPRAS!$C:$C, $A63, COMPRAS!$J:$J, $B63), 1) -> 1 | G63: =IFERROR(SUMIFS(COMPRAS!I:I, COMPRAS!C:C, A63) * SUMIFS(COMPRAS!E:E, COMPRAS!C:C, A63) / COUNTIF(COMPRAS!C:C, A63), 0) -> 0 | H63: =MAX(0, (SUMIFS(COMPRAS!$E:$E, COMPRAS!$C:$C, $A63, COMPRAS!$J:$J, "UNIDAD") + SUMIFS(COMPRAS!$E:$E, COMPRAS!$C:$C, $A63, COMPRAS!$J:$J, "KG")) - (SUMIFS(prueba!$A:$A, prueba!$C:$C, $A63, prueba!$B:$B, "UNIDAD") + SUMIFS(prueba!$A:$A, prueba!$C:$C, $A63, prueba!$B:$B, "KG")) ) -> 0 | I63: =IFERROR(C63 / F63, 0) -> 0 | J63: =IFERROR(ROUNDUP((E63 / F63) * 1.1, -2),0) -> 0 | K63: =A63&B63 -> MANZANA ROJA COMERCIALKG
A64: MANZANA GRANNY ELEGIDA | B64: CAJON | C64: =IFERROR(AVERAGEIFS(COMPRAS!$D:$D, COMPRAS!$C:$C, $A64, COMPRAS!$J:$J, $B64), 0) -> 0 | D64: 1.3 | E64: =ROUNDUP(C64 *D64, -3) -> 0 | F64: =IFERROR(AVERAGEIFS(COMPRAS!$F:$F, COMPRAS!$C:$C, $A64, COMPRAS!$J:$J, $B64), 1) -> 1 | G64: =IFERROR(SUMIFS(COMPRAS!I:I, COMPRAS!C:C, A64) * SUMIFS(COMPRAS!E:E, COMPRAS!C:C, A64) / COUNTIF(COMPRAS!C:C, A64), 0) -> 0 | H64: =IFERROR( ((SUMIFS(COMPRAS!$E:$E, COMPRAS!$C:$C, $A64, COMPRAS!$J:$J, "CAJON") + SUMIFS(COMPRAS!$E:$E, COMPRAS!$C:$C, $A64, COMPRAS!$J:$J, "BOLSA")) * $F64) - ((SUMIFS(prueba!$A:$A, prueba!$C:$C, $A64, prueba!$B:$B, "CAJON") + SUMIFS(prueba!$A:$A, prueba!$C:$C, $A64, prueba!$B:$B, "BOLSA")) * $F64) - MAX(0, (SUMIFS(prueba!$A:$A, prueba!$C:$C, $A64, prueba!$B:$B, "UNIDAD") + SUMIFS(prueba!$A:$A, prueba!$C:$C, $A64, prueba!$B:$B, "KG")) - (SUMIFS(COMPRAS!$E:$E, COMPRAS!$C:$C, $A64, COMPRAS!$J:$J, "UNIDAD") + SUMIFS(COMPRAS!$E:$E, COMPRAS!$C:$C, $A64, COMPRAS!$J:$J, "KG"))), 0) -> 0 | I64: =IFERROR(C64 / F64, 0) -> 0 | J64: =IFERROR(ROUNDUP((E64 / F64) * 1.1, -2),0) -> 0 | K64: =A64&B64 -> MANZANA GRANNY ELEGIDACAJON
A65: MANZANA GRANNY ELEGIDA | B65: KG | C65: =IFERROR(AVERAGEIFS(COMPRAS!$D:$D, COMPRAS!$C:$C, $A65, COMPRAS!$J:$J, $B65), 0) -> 0 | D65: 1.3 | E65: =ROUNDUP(C65 *D65, -2) -> 0 | F65: =IFERROR(AVERAGEIFS(COMPRAS!$F:$F, COMPRAS!$C:$C, $A65, COMPRAS!$J:$J, $B65), 1) -> 1 | G65: =IFERROR(SUMIFS(COMPRAS!I:I, COMPRAS!C:C, A65) * SUMIFS(COMPRAS!E:E, COMPRAS!C:C, A65) / COUNTIF(COMPRAS!C:C, A65), 0) -> 0 | H65: =MAX(0, (SUMIFS(COMPRAS!$E:$E, COMPRAS!$C:$C, $A65, COMPRAS!$J:$J, "UNIDAD") + SUMIFS(COMPRAS!$E:$E, COMPRAS!$C:$C, $A65, COMPRAS!$J:$J, "KG")) - (SUMIFS(prueba!$A:$A, prueba!$C:$C, $A65, prueba!$B:$B, "UNIDAD") + SUMIFS(prueba!$A:$A, prueba!$C:$C, $A65, prueba!$B:$B, "KG")) ) -> 0 | I65: =IFERROR(C65 / F65, 0) -> 0 | J65: =IFERROR(ROUNDUP((E65 / F65) * 1.1, -2),0) -> 0 | K65: =A65&B65 -> MANZANA GRANNY ELEGIDAKG
A66: MANZANA GRANNY COMERCIAL | B66: CAJON | C66: =IFERROR(AVERAGEIFS(COMPRAS!$D:$D, COMPRAS!$C:$C, $A66, COMPRAS!$J:$J, $B66), 0) -> 0 | D66: 1.3 | E66: =ROUNDUP(C66 *D66, -3) -> 0 | F66: =IFERROR(AVERAGEIFS(COMPRAS!$F:$F, COMPRAS!$C:$C, $A66, COMPRAS!$J:$J, $B66), 1) -> 1 | G66: =IFERROR(SUMIFS(COMPRAS!I:I, COMPRAS!C:C, A66) * SUMIFS(COMPRAS!E:E, COMPRAS!C:C, A66) / COUNTIF(COMPRAS!C:C, A66), 0) -> 0 | H66: =IFERROR( ((SUMIFS(COMPRAS!$E:$E, COMPRAS!$C:$C, $A66, COMPRAS!$J:$J, "CAJON") + SUMIFS(COMPRAS!$E:$E, COMPRAS!$C:$C, $A66, COMPRAS!$J:$J, "BOLSA")) * $F66) - ((SUMIFS(prueba!$A:$A, prueba!$C:$C, $A66, prueba!$B:$B, "CAJON") + SUMIFS(prueba!$A:$A, prueba!$C:$C, $A66, prueba!$B:$B, "BOLSA")) * $F66) - MAX(0, (SUMIFS(prueba!$A:$A, prueba!$C:$C, $A66, prueba!$B:$B, "UNIDAD") + SUMIFS(prueba!$A:$A, prueba!$C:$C, $A66, prueba!$B:$B, "KG")) - (SUMIFS(COMPRAS!$E:$E, COMPRAS!$C:$C, $A66, COMPRAS!$J:$J, "UNIDAD") + SUMIFS(COMPRAS!$E:$E, COMPRAS!$C:$C, $A66, COMPRAS!$J:$J, "KG"))), 0) -> 0 | I66: =IFERROR(C66 / F66, 0) -> 0 | J66: =IFERROR(ROUNDUP((E66 / F66) * 1.1, -2),0) -> 0 | K66: =A66&B66 -> MANZANA GRANNY COMERCIALCAJON
A67: MANZANA GRANNY COMERCIAL | B67: KG | C67: =IFERROR(AVERAGEIFS(COMPRAS!$D:$D, COMPRAS!$C:$C, $A67, COMPRAS!$J:$J, $B67), 0) -> 0 | D67: 1.3 | E67: =ROUNDUP(C67 *D67, -2) -> 0 | F67: =IFERROR(AVERAGEIFS(COMPRAS!$F:$F, COMPRAS!$C:$C, $A67, COMPRAS!$J:$J, $B67), 1) -> 1 | G67: =IFERROR(SUMIFS(COMPRAS!I:I, COMPRAS!C:C, A67) * SUMIFS(COMPRAS!E:E, COMPRAS!C:C, A67) / COUNTIF(COMPRAS!C:C, A67), 0) -> 0 | H67: =MAX(0, (SUMIFS(COMPRAS!$E:$E, COMPRAS!$C:$C, $A67, COMPRAS!$J:$J, "UNIDAD") + SUMIFS(COMPRAS!$E:$E, COMPRAS!$C:$C, $A67, COMPRAS!$J:$J, "KG")) - (SUMIFS(prueba!$A:$A, prueba!$C:$C, $A67, prueba!$B:$B, "UNIDAD") + SUMIFS(prueba!$A:$A, prueba!$C:$C, $A67, prueba!$B:$B, "KG")) ) -> 0 | I67: =IFERROR(C67 / F67, 0) -> 0 | J67: =IFERROR(ROUNDUP((E67 / F67) * 1.1, -2),0) -> 0 | K67: =A67&B67 -> MANZANA GRANNY COMERCIALKG
A68: MELON AMARILLO | B68: CAJON | C68: =IFERROR(AVERAGEIFS(COMPRAS!$D:$D, COMPRAS!$C:$C, $A68, COMPRAS!$J:$J, $B68), 0) -> 0 | D68: 1.3 | E68: =ROUNDUP(C68 *D68, -3) -> 0 | F68: =IFERROR(AVERAGEIFS(COMPRAS!$F:$F, COMPRAS!$C:$C, $A68, COMPRAS!$J:$J, $B68), 1) -> 1 | G68: =IFERROR(SUMIFS(COMPRAS!I:I, COMPRAS!C:C, A68) * SUMIFS(COMPRAS!E:E, COMPRAS!C:C, A68) / COUNTIF(COMPRAS!C:C, A68), 0) -> 0 | H68: =IFERROR( ((SUMIFS(COMPRAS!$E:$E, COMPRAS!$C:$C, $A68, COMPRAS!$J:$J, "CAJON") + SUMIFS(COMPRAS!$E:$E, COMPRAS!$C:$C, $A68, COMPRAS!$J:$J, "BOLSA")) * $F68) - ((SUMIFS(prueba!$A:$A, prueba!$C:$C, $A68, prueba!$B:$B, "CAJON") + SUMIFS(prueba!$A:$A, prueba!$C:$C, $A68, prueba!$B:$B, "BOLSA")) * $F68) - MAX(0, (SUMIFS(prueba!$A:$A, prueba!$C:$C, $A68, prueba!$B:$B, "UNIDAD") + SUMIFS(prueba!$A:$A, prueba!$C:$C, $A68, prueba!$B:$B, "KG")) - (SUMIFS(COMPRAS!$E:$E, COMPRAS!$C:$C, $A68, COMPRAS!$J:$J, "UNIDAD") + SUMIFS(COMPRAS!$E:$E, COMPRAS!$C:$C, $A68, COMPRAS!$J:$J, "KG"))), 0) -> 0 | I68: =IFERROR(C68 / F68, 0) -> 0 | J68: =IFERROR(ROUNDUP((E68 / F68) * 1.1, -2),0) -> 0 | K68: =A68&B68 -> MELON AMARILLOCAJON
A69: MELON AMARILLO | B69: UNIDAD | C69: =IFERROR(AVERAGEIFS(COMPRAS!$D:$D, COMPRAS!$C:$C, $A69, COMPRAS!$J:$J, $B69), 0) -> 0 | D69: 1.3 | E69: =ROUNDUP(C69 *D69, -2) -> 0 | F69: =IFERROR(AVERAGEIFS(COMPRAS!$F:$F, COMPRAS!$C:$C, $A69, COMPRAS!$J:$J, $B69), 1) -> 1 | G69: =IFERROR(SUMIFS(COMPRAS!I:I, COMPRAS!C:C, A69) * SUMIFS(COMPRAS!E:E, COMPRAS!C:C, A69) / COUNTIF(COMPRAS!C:C, A69), 0) -> 0 | H69: =MAX(0, (SUMIFS(COMPRAS!$E:$E, COMPRAS!$C:$C, $A69, COMPRAS!$J:$J, "UNIDAD") + SUMIFS(COMPRAS!$E:$E, COMPRAS!$C:$C, $A69, COMPRAS!$J:$J, "KG")) - (SUMIFS(prueba!$A:$A, prueba!$C:$C, $A69, prueba!$B:$B, "UNIDAD") + SUMIFS(prueba!$A:$A, prueba!$C:$C, $A69, prueba!$B:$B, "KG")) ) -> 0 | I69: =IFERROR(C69 / F69, 0) -> 0 | J69: =IFERROR(ROUNDUP((E69 / F69) * 1.1, -2),0) -> 0 | K69: =A69&B69 -> MELON AMARILLOUNIDAD
A70: MELON BLANCO | B70: CAJON | C70: =IFERROR(AVERAGEIFS(COMPRAS!$D:$D, COMPRAS!$C:$C, $A70, COMPRAS!$J:$J, $B70), 0) -> 0 | D70: 1.3 | E70: =ROUNDUP(C70 *D70, -3) -> 0 | F70: =IFERROR(AVERAGEIFS(COMPRAS!$F:$F, COMPRAS!$C:$C, $A70, COMPRAS!$J:$J, $B70), 1) -> 1 | G70: =IFERROR(SUMIFS(COMPRAS!I:I, COMPRAS!C:C, A70) * SUMIFS(COMPRAS!E:E, COMPRAS!C:C, A70) / COUNTIF(COMPRAS!C:C, A70), 0) -> 0 | H70: =IFERROR( ((SUMIFS(COMPRAS!$E:$E, COMPRAS!$C:$C, $A70, COMPRAS!$J:$J, "CAJON") + SUMIFS(COMPRAS!$E:$E, COMPRAS!$C:$C, $A70, COMPRAS!$J:$J, "BOLSA")) * $F70) - ((SUMIFS(prueba!$A:$A, prueba!$C:$C, $A70, prueba!$B:$B, "CAJON") + SUMIFS(prueba!$A:$A, prueba!$C:$C, $A70, prueba!$B:$B, "BOLSA")) * $F70) - MAX(0, (SUMIFS(prueba!$A:$A, prueba!$C:$C, $A70, prueba!$B:$B, "UNIDAD") + SUMIFS(prueba!$A:$A, prueba!$C:$C, $A70, prueba!$B:$B, "KG")) - (SUMIFS(COMPRAS!$E:$E, COMPRAS!$C:$C, $A70, COMPRAS!$J:$J, "UNIDAD") + SUMIFS(COMPRAS!$E:$E, COMPRAS!$C:$C, $A70, COMPRAS!$J:$J, "KG"))), 0) -> 0 | I70: =IFERROR(C70 / F70, 0) -> 0 | J70: =IFERROR(ROUNDUP((E70 / F70) * 1.1, -2),0) -> 0 | K70: =A70&B70 -> MELON BLANCOCAJON
A71: MELON BLANCO | B71: UNIDAD | C71: =IFERROR(AVERAGEIFS(COMPRAS!$D:$D, COMPRAS!$C:$C, $A71, COMPRAS!$J:$J, $B71), 0) -> 0 | D71: 1.3 | E71: =ROUNDUP(C71 *D71, -2) -> 0 | F71: =IFERROR(AVERAGEIFS(COMPRAS!$F:$F, COMPRAS!$C:$C, $A71, COMPRAS!$J:$J, $B71), 1) -> 1 | G71: =IFERROR(SUMIFS(COMPRAS!I:I, COMPRAS!C:C, A71) * SUMIFS(COMPRAS!E:E, COMPRAS!C:C, A71) / COUNTIF(COMPRAS!C:C, A71), 0) -> 0 | H71: =MAX(0, (SUMIFS(COMPRAS!$E:$E, COMPRAS!$C:$C, $A71, COMPRAS!$J:$J, "UNIDAD") + SUMIFS(COMPRAS!$E:$E, COMPRAS!$C:$C, $A71, COMPRAS!$J:$J, "KG")) - (SUMIFS(prueba!$A:$A, prueba!$C:$C, $A71, prueba!$B:$B, "UNIDAD") + SUMIFS(prueba!$A:$A, prueba!$C:$C, $A71, prueba!$B:$B, "KG")) ) -> 0 | I71: =IFERROR(C71 / F71, 0) -> 0 | J71: =IFERROR(ROUNDUP((E71 / F71) * 1.1, -2),0) -> 0 | K71: =A71&B71 -> MELON BLANCOUNIDAD
A72: NARANJA JUGO ELEGIDA | B72: CAJON | C72: =IFERROR(AVERAGEIFS(COMPRAS!$D:$D, COMPRAS!$C:$C, $A72, COMPRAS!$J:$J, $B72), 0) -> 0 | D72: 1.3 | E72: =ROUNDUP(C72 *D72, -3) -> 0 | F72: =IFERROR(AVERAGEIFS(COMPRAS!$F:$F, COMPRAS!$C:$C, $A72, COMPRAS!$J:$J, $B72), 1) -> 1 | G72: =IFERROR(SUMIFS(COMPRAS!I:I, COMPRAS!C:C, A72) * SUMIFS(COMPRAS!E:E, COMPRAS!C:C, A72) / COUNTIF(COMPRAS!C:C, A72), 0) -> 0 | H72: =IFERROR( ((SUMIFS(COMPRAS!$E:$E, COMPRAS!$C:$C, $A72, COMPRAS!$J:$J, "CAJON") + SUMIFS(COMPRAS!$E:$E, COMPRAS!$C:$C, $A72, COMPRAS!$J:$J, "BOLSA")) * $F72) - ((SUMIFS(prueba!$A:$A, prueba!$C:$C, $A72, prueba!$B:$B, "CAJON") + SUMIFS(prueba!$A:$A, prueba!$C:$C, $A72, prueba!$B:$B, "BOLSA")) * $F72) - MAX(0, (SUMIFS(prueba!$A:$A, prueba!$C:$C, $A72, prueba!$B:$B, "UNIDAD") + SUMIFS(prueba!$A:$A, prueba!$C:$C, $A72, prueba!$B:$B, "KG")) - (SUMIFS(COMPRAS!$E:$E, COMPRAS!$C:$C, $A72, COMPRAS!$J:$J, "UNIDAD") + SUMIFS(COMPRAS!$E:$E, COMPRAS!$C:$C, $A72, COMPRAS!$J:$J, "KG"))), 0) -> 0 | I72: =IFERROR(C72 / F72, 0) -> 0 | J72: =IFERROR(ROUNDUP((E72 / F72) * 1.1, -2),0) -> 0 | K72: =A72&B72 -> NARANJA JUGO ELEGIDACAJON
A73: NARANJA JUGO ELEGIDA | B73: KG | C73: =IFERROR(AVERAGEIFS(COMPRAS!$D:$D, COMPRAS!$C:$C, $A73, COMPRAS!$J:$J, $B73), 0) -> 0 | D73: 1.3 | E73: =ROUNDUP(C73 *D73, -2) -> 0 | F73: =IFERROR(AVERAGEIFS(COMPRAS!$F:$F, COMPRAS!$C:$C, $A73, COMPRAS!$J:$J, $B73), 1) -> 1 | G73: =IFERROR(SUMIFS(COMPRAS!I:I, COMPRAS!C:C, A73) * SUMIFS(COMPRAS!E:E, COMPRAS!C:C, A73) / COUNTIF(COMPRAS!C:C, A73), 0) -> 0 | H73: =MAX(0, (SUMIFS(COMPRAS!$E:$E, COMPRAS!$C:$C, $A73, COMPRAS!$J:$J, "UNIDAD") + SUMIFS(COMPRAS!$E:$E, COMPRAS!$C:$C, $A73, COMPRAS!$J:$J, "KG")) - (SUMIFS(prueba!$A:$A, prueba!$C:$C, $A73, prueba!$B:$B, "UNIDAD") + SUMIFS(prueba!$A:$A, prueba!$C:$C, $A73, prueba!$B:$B, "KG")) ) -> 0 | I73: =IFERROR(C73 / F73, 0) -> 0 | J73: =IFERROR(ROUNDUP((E73 / F73) * 1.1, -2),0) -> 0 | K73: =A73&B73 -> NARANJA JUGO ELEGIDAKG
A74: NARANJA JUGO COMERCIAL | B74: CAJON | C74: =IFERROR(AVERAGEIFS(COMPRAS!$D:$D, COMPRAS!$C:$C, $A74, COMPRAS!$J:$J, $B74), 0) -> 0 | D74: 1.3 | E74: =ROUNDUP(C74 * D74, -3) -> 0 | F74: =IFERROR(AVERAGEIFS(COMPRAS!$F:$F, COMPRAS!$C:$C, $A74, COMPRAS!$J:$J, $B74), 1) -> 1 | G74: =IFERROR(SUMIFS(COMPRAS!I:I, COMPRAS!C:C, A74) * SUMIFS(COMPRAS!E:E, COMPRAS!C:C, A74) / COUNTIF(COMPRAS!C:C, A74), 0) -> 0 | H74: =IFERROR( ((SUMIFS(COMPRAS!$E:$E, COMPRAS!$C:$C, $A74, COMPRAS!$J:$J, "CAJON") + SUMIFS(COMPRAS!$E:$E, COMPRAS!$C:$C, $A74, COMPRAS!$J:$J, "BOLSA")) * $F74) - ((SUMIFS(prueba!$A:$A, prueba!$C:$C, $A74, prueba!$B:$B, "CAJON") + SUMIFS(prueba!$A:$A, prueba!$C:$C, $A74, prueba!$B:$B, "BOLSA")) * $F74) - MAX(0, (SUMIFS(prueba!$A:$A, prueba!$C:$C, $A74, prueba!$B:$B, "UNIDAD") + SUMIFS(prueba!$A:$A, prueba!$C:$C, $A74, prueba!$B:$B, "KG")) - (SUMIFS(COMPRAS!$E:$E, COMPRAS!$C:$C, $A74, COMPRAS!$J:$J, "UNIDAD") + SUMIFS(COMPRAS!$E:$E, COMPRAS!$C:$C, $A74, COMPRAS!$J:$J, "KG"))), 0) -> -1 | I74: =IFERROR(C74 / F74, 0) -> 0 | J74: =IFERROR(ROUNDUP((E74 / F74) * 1.1, -2),0) -> 0 | K74: =A74&B74 -> NARANJA JUGO COMERCIALCAJON
A75: NARANJA JUGO COMERCIAL | B75: KG | C75: =IFERROR(AVERAGEIFS(COMPRAS!$D:$D, COMPRAS!$C:$C, $A75, COMPRAS!$J:$J, $B75), 0) -> 0 | D75: 1.3 | E75: =ROUNDUP(C75 * D75, -2) -> 0 | F75: =IFERROR(AVERAGEIFS(COMPRAS!$F:$F, COMPRAS!$C:$C, $A75, COMPRAS!$J:$J, $B75), 1) -> 1 | G75: =IFERROR(SUMIFS(COMPRAS!I:I, COMPRAS!C:C, A75) * SUMIFS(COMPRAS!E:E, COMPRAS!C:C, A75) / COUNTIF(COMPRAS!C:C, A75), 0) -> 0 | H75: =MAX(0, (SUMIFS(COMPRAS!$E:$E, COMPRAS!$C:$C, $A75, COMPRAS!$J:$J, "UNIDAD") + SUMIFS(COMPRAS!$E:$E, COMPRAS!$C:$C, $A75, COMPRAS!$J:$J, "KG")) - (SUMIFS(prueba!$A:$A, prueba!$C:$C, $A75, prueba!$B:$B, "UNIDAD") + SUMIFS(prueba!$A:$A, prueba!$C:$C, $A75, prueba!$B:$B, "KG")) ) -> 0 | I75: =IFERROR(C75 / F75, 0) -> 0 | J75: =IFERROR(ROUNDUP((E75 / F75) * 1.1, -2),0) -> 0 | K75: =A75&B75 -> NARANJA JUGO COMERCIALKG
A76: NARANJA JUGO COMERIAL | B76: CAJON | C76: =IFERROR(AVERAGEIFS(COMPRAS!$D:$D, COMPRAS!$C:$C, $A76, COMPRAS!$J:$J, $B76), 0) -> 0 | D76: 1.3 | E76: =ROUNDUP(C76 *D76, -3) -> 0 | F76: =IFERROR(AVERAGEIFS(COMPRAS!$F:$F, COMPRAS!$C:$C, $A76, COMPRAS!$J:$J, $B76), 1) -> 1 | G76: =IFERROR(SUMIFS(COMPRAS!I:I, COMPRAS!C:C, A76) * SUMIFS(COMPRAS!E:E, COMPRAS!C:C, A76) / COUNTIF(COMPRAS!C:C, A76), 0) -> 0 | H76: =IFERROR( ((SUMIFS(COMPRAS!$E:$E, COMPRAS!$C:$C, $A76, COMPRAS!$J:$J, "CAJON") + SUMIFS(COMPRAS!$E:$E, COMPRAS!$C:$C, $A76, COMPRAS!$J:$J, "BOLSA")) * $F76) - ((SUMIFS(prueba!$A:$A, prueba!$C:$C, $A76, prueba!$B:$B, "CAJON") + SUMIFS(prueba!$A:$A, prueba!$C:$C, $A76, prueba!$B:$B, "BOLSA")) * $F76) - MAX(0, (SUMIFS(prueba!$A:$A, prueba!$C:$C, $A76, prueba!$B:$B, "UNIDAD") + SUMIFS(prueba!$A:$A, prueba!$C:$C, $A76, prueba!$B:$B, "KG")) - (SUMIFS(COMPRAS!$E:$E, COMPRAS!$C:$C, $A76, COMPRAS!$J:$J, "UNIDAD") + SUMIFS(COMPRAS!$E:$E, COMPRAS!$C:$C, $A76, COMPRAS!$J:$J, "KG"))), 0) -> 0 | I76: =IFERROR(C76 / F76, 0) -> 0 | J76: =IFERROR(ROUNDUP((E76 / F76) * 1.1, -2),0) -> 0 | K76: =A76&B76 -> NARANJA JUGO COMERIALCAJON
A77: NARANJA JUGO COMERIAL | B77: KG | C77: =IFERROR(AVERAGEIFS(COMPRAS!$D:$D, COMPRAS!$C:$C, $A77, COMPRAS!$J:$J, $B77), 0) -> 0 | D77: 1.3 | E77: =ROUNDUP(C77 *D77, -2) -> 0 | F77: =IFERROR(AVERAGEIFS(COMPRAS!$F:$F, COMPRAS!$C:$C, $A77, COMPRAS!$J:$J, $B77), 1) -> 1 | G77: =IFERROR(SUMIFS(COMPRAS!I:I, COMPRAS!C:C, A77) * SUMIFS(COMPRAS!E:E, COMPRAS!C:C, A77) / COUNTIF(COMPRAS!C:C, A77), 0) -> 0 | H77: =MAX(0, (SUMIFS(COMPRAS!$E:$E, COMPRAS!$C:$C, $A77, COMPRAS!$J:$J, "UNIDAD") + SUMIFS(COMPRAS!$E:$E, COMPRAS!$C:$C, $A77, COMPRAS!$J:$J, "KG")) - (SUMIFS(prueba!$A:$A, prueba!$C:$C, $A77, prueba!$B:$B, "UNIDAD") + SUMIFS(prueba!$A:$A, prueba!$C:$C, $A77, prueba!$B:$B, "KG")) ) -> 0 | I77: =IFERROR(C77 / F77, 0) -> 0 | J77: =IFERROR(ROUNDUP((E77 / F77) * 1.1, -2),0) -> 0 | K77: =A77&B77 -> NARANJA JUGO COMERIALKG
A78: NARANJA OMBLIGO | B78: CAJON | C78: =IFERROR(AVERAGEIFS(COMPRAS!$D:$D, COMPRAS!$C:$C, $A78, COMPRAS!$J:$J, $B78), 0) -> 0 | D78: 1.3 | E78: =ROUNDUP(C78 *D78, -3) -> 0 | F78: =IFERROR(AVERAGEIFS(COMPRAS!$F:$F, COMPRAS!$C:$C, $A78, COMPRAS!$J:$J, $B78), 1) -> 1 | G78: =IFERROR(SUMIFS(COMPRAS!I:I, COMPRAS!C:C, A78) * SUMIFS(COMPRAS!E:E, COMPRAS!C:C, A78) / COUNTIF(COMPRAS!C:C, A78), 0) -> 0 | H78: =IFERROR( ((SUMIFS(COMPRAS!$E:$E, COMPRAS!$C:$C, $A78, COMPRAS!$J:$J, "CAJON") + SUMIFS(COMPRAS!$E:$E, COMPRAS!$C:$C, $A78, COMPRAS!$J:$J, "BOLSA")) * $F78) - ((SUMIFS(prueba!$A:$A, prueba!$C:$C, $A78, prueba!$B:$B, "CAJON") + SUMIFS(prueba!$A:$A, prueba!$C:$C, $A78, prueba!$B:$B, "BOLSA")) * $F78) - MAX(0, (SUMIFS(prueba!$A:$A, prueba!$C:$C, $A78, prueba!$B:$B, "UNIDAD") + SUMIFS(prueba!$A:$A, prueba!$C:$C, $A78, prueba!$B:$B, "KG")) - (SUMIFS(COMPRAS!$E:$E, COMPRAS!$C:$C, $A78, COMPRAS!$J:$J, "UNIDAD") + SUMIFS(COMPRAS!$E:$E, COMPRAS!$C:$C, $A78, COMPRAS!$J:$J, "KG"))), 0) -> 0 | I78: =IFERROR(C78 / F78, 0) -> 0 | J78: =IFERROR(ROUNDUP((E78 / F78) * 1.1, -2),0) -> 0 | K78: =A78&B78 -> NARANJA OMBLIGOCAJON
A79: NARANJA OMBLIGO | B79: KG | C79: =IFERROR(AVERAGEIFS(COMPRAS!$D:$D, COMPRAS!$C:$C, $A79, COMPRAS!$J:$J, $B79), 0) -> 0 | D79: 1.3 | E79: =ROUNDUP(C79 *D79, -2) -> 0 | F79: =IFERROR(AVERAGEIFS(COMPRAS!$F:$F, COMPRAS!$C:$C, $A79, COMPRAS!$J:$J, $B79), 1) -> 1 | G79: =IFERROR(SUMIFS(COMPRAS!I:I, COMPRAS!C:C, A79) * SUMIFS(COMPRAS!E:E, COMPRAS!C:C, A79) / COUNTIF(COMPRAS!C:C, A79), 0) -> 0 | H79: =MAX(0, (SUMIFS(COMPRAS!$E:$E, COMPRAS!$C:$C, $A79, COMPRAS!$J:$J, "UNIDAD") + SUMIFS(COMPRAS!$E:$E, COMPRAS!$C:$C, $A79, COMPRAS!$J:$J, "KG")) - (SUMIFS(prueba!$A:$A, prueba!$C:$C, $A79, prueba!$B:$B, "UNIDAD") + SUMIFS(prueba!$A:$A, prueba!$C:$C, $A79, prueba!$B:$B, "KG")) ) -> 0 | I79: =IFERROR(C79 / F79, 0) -> 0 | J79: =IFERROR(ROUNDUP((E79 / F79) * 1.1, -2),0) -> 0 | K79: =A79&B79 -> NARANJA OMBLIGOKG
A80: PALTA | B80: CAJON | C80: =IFERROR(AVERAGEIFS(COMPRAS!$D:$D, COMPRAS!$C:$C, $A80, COMPRAS!$J:$J, $B80), 0) -> 0 | D80: 1.3 | E80: =ROUNDUP(C80 *D80, -3) -> 0 | F80: =IFERROR(AVERAGEIFS(COMPRAS!$F:$F, COMPRAS!$C:$C, $A80, COMPRAS!$J:$J, $B80), 1) -> 1 | G80: =IFERROR(SUMIFS(COMPRAS!I:I, COMPRAS!C:C, A80) * SUMIFS(COMPRAS!E:E, COMPRAS!C:C, A80) / COUNTIF(COMPRAS!C:C, A80), 0) -> 0 | H80: =IFERROR( ((SUMIFS(COMPRAS!$E:$E, COMPRAS!$C:$C, $A80, COMPRAS!$J:$J, "CAJON") + SUMIFS(COMPRAS!$E:$E, COMPRAS!$C:$C, $A80, COMPRAS!$J:$J, "BOLSA")) * $F80) - ((SUMIFS(prueba!$A:$A, prueba!$C:$C, $A80, prueba!$B:$B, "CAJON") + SUMIFS(prueba!$A:$A, prueba!$C:$C, $A80, prueba!$B:$B, "BOLSA")) * $F80) - MAX(0, (SUMIFS(prueba!$A:$A, prueba!$C:$C, $A80, prueba!$B:$B, "UNIDAD") + SUMIFS(prueba!$A:$A, prueba!$C:$C, $A80, prueba!$B:$B, "KG")) - (SUMIFS(COMPRAS!$E:$E, COMPRAS!$C:$C, $A80, COMPRAS!$J:$J, "UNIDAD") + SUMIFS(COMPRAS!$E:$E, COMPRAS!$C:$C, $A80, COMPRAS!$J:$J, "KG"))), 0) -> 0 | I80: =IFERROR(C80 / F80, 0) -> 0 | J80: =IFERROR(ROUNDUP((E80 / F80) * 1.1, -2),0) -> 0 | K80: =A80&B80 -> PALTACAJON
A81: PALTA | B81: UNIDAD | C81: =IFERROR(AVERAGEIFS(COMPRAS!$D:$D, COMPRAS!$C:$C, $A81, COMPRAS!$J:$J, $B81), 0) -> 0 | D81: 1.3 | E81: =ROUNDUP(C81 *D81, -2) -> 0 | F81: =IFERROR(AVERAGEIFS(COMPRAS!$F:$F, COMPRAS!$C:$C, $A81, COMPRAS!$J:$J, $B81), 1) -> 1 | G81: =IFERROR(SUMIFS(COMPRAS!I:I, COMPRAS!C:C, A81) * SUMIFS(COMPRAS!E:E, COMPRAS!C:C, A81) / COUNTIF(COMPRAS!C:C, A81), 0) -> 0 | H81: =MAX(0, (SUMIFS(COMPRAS!$E:$E, COMPRAS!$C:$C, $A81, COMPRAS!$J:$J, "UNIDAD") + SUMIFS(COMPRAS!$E:$E, COMPRAS!$C:$C, $A81, COMPRAS!$J:$J, "KG")) - (SUMIFS(prueba!$A:$A, prueba!$C:$C, $A81, prueba!$B:$B, "UNIDAD") + SUMIFS(prueba!$A:$A, prueba!$C:$C, $A81, prueba!$B:$B, "KG")) ) -> 0 | I81: =IFERROR(C81 / F81, 0) -> 0 | J81: =IFERROR(ROUNDUP((E81 / F81) * 1.1, -2),0) -> 0 | K81: =A81&B81 -> PALTAUNIDAD
A82: POMELO IMPORTADO | B82: CAJON | C82: =IFERROR(AVERAGEIFS(COMPRAS!$D:$D, COMPRAS!$C:$C, $A82, COMPRAS!$J:$J, $B82), 0) -> 0 | D82: 1.3 | E82: =ROUNDUP(C82 *D82, -3) -> 0 | F82: =IFERROR(AVERAGEIFS(COMPRAS!$F:$F, COMPRAS!$C:$C, $A82, COMPRAS!$J:$J, $B82), 1) -> 1 | G82: =IFERROR(SUMIFS(COMPRAS!I:I, COMPRAS!C:C, A82) * SUMIFS(COMPRAS!E:E, COMPRAS!C:C, A82) / COUNTIF(COMPRAS!C:C, A82), 0) -> 0 | H82: =IFERROR( ((SUMIFS(COMPRAS!$E:$E, COMPRAS!$C:$C, $A82, COMPRAS!$J:$J, "CAJON") + SUMIFS(COMPRAS!$E:$E, COMPRAS!$C:$C, $A82, COMPRAS!$J:$J, "BOLSA")) * $F82) - ((SUMIFS(prueba!$A:$A, prueba!$C:$C, $A82, prueba!$B:$B, "CAJON") + SUMIFS(prueba!$A:$A, prueba!$C:$C, $A82, prueba!$B:$B, "BOLSA")) * $F82) - MAX(0, (SUMIFS(prueba!$A:$A, prueba!$C:$C, $A82, prueba!$B:$B, "UNIDAD") + SUMIFS(prueba!$A:$A, prueba!$C:$C, $A82, prueba!$B:$B, "KG")) - (SUMIFS(COMPRAS!$E:$E, COMPRAS!$C:$C, $A82, COMPRAS!$J:$J, "UNIDAD") + SUMIFS(COMPRAS!$E:$E, COMPRAS!$C:$C, $A82, COMPRAS!$J:$J, "KG"))), 0) -> 0 | I82: =IFERROR(C82 / F82, 0) -> 0 | J82: =IFERROR(ROUNDUP((E82 / F82) * 1.1, -2),0) -> 0 | K82: =A82&B82 -> POMELO IMPORTADOCAJON
A83: POMELO IMPORTADO | B83: KG | C83: =IFERROR(AVERAGEIFS(COMPRAS!$D:$D, COMPRAS!$C:$C, $A83, COMPRAS!$J:$J, $B83), 0) -> 0 | D83: 1.3 | E83: =ROUNDUP(C83 *D83, -2) -> 0 | F83: =IFERROR(AVERAGEIFS(COMPRAS!$F:$F, COMPRAS!$C:$C, $A83, COMPRAS!$J:$J, $B83), 1) -> 1 | G83: =IFERROR(SUMIFS(COMPRAS!I:I, COMPRAS!C:C, A83) * SUMIFS(COMPRAS!E:E, COMPRAS!C:C, A83) / COUNTIF(COMPRAS!C:C, A83), 0) -> 0 | H83: =MAX(0, (SUMIFS(COMPRAS!$E:$E, COMPRAS!$C:$C, $A83, COMPRAS!$J:$J, "UNIDAD") + SUMIFS(COMPRAS!$E:$E, COMPRAS!$C:$C, $A83, COMPRAS!$J:$J, "KG")) - (SUMIFS(prueba!$A:$A, prueba!$C:$C, $A83, prueba!$B:$B, "UNIDAD") + SUMIFS(prueba!$A:$A, prueba!$C:$C, $A83, prueba!$B:$B, "KG")) ) -> 0 | I83: =IFERROR(C83 / F83, 0) -> 0 | J83: =IFERROR(ROUNDUP((E83 / F83) * 1.1, -2),0) -> 0 | K83: =A83&B83 -> POMELO IMPORTADOKG
A84: POMELO NACIONAL | B84: CAJON | C84: =IFERROR(AVERAGEIFS(COMPRAS!$D:$D, COMPRAS!$C:$C, $A84, COMPRAS!$J:$J, $B84), 0) -> 0 | D84: 1.3 | E84: =ROUNDUP(C84 *D84, -3) -> 0 | F84: =IFERROR(AVERAGEIFS(COMPRAS!$F:$F, COMPRAS!$C:$C, $A84, COMPRAS!$J:$J, $B84), 1) -> 1 | G84: =IFERROR(SUMIFS(COMPRAS!I:I, COMPRAS!C:C, A84) * SUMIFS(COMPRAS!E:E, COMPRAS!C:C, A84) / COUNTIF(COMPRAS!C:C, A84), 0) -> 0 | H84: =IFERROR( ((SUMIFS(COMPRAS!$E:$E, COMPRAS!$C:$C, $A84, COMPRAS!$J:$J, "CAJON") + SUMIFS(COMPRAS!$E:$E, COMPRAS!$C:$C, $A84, COMPRAS!$J:$J, "BOLSA")) * $F84) - ((SUMIFS(prueba!$A:$A, prueba!$C:$C, $A84, prueba!$B:$B, "CAJON") + SUMIFS(prueba!$A:$A, prueba!$C:$C, $A84, prueba!$B:$B, "BOLSA")) * $F84) - MAX(0, (SUMIFS(prueba!$A:$A, prueba!$C:$C, $A84, prueba!$B:$B, "UNIDAD") + SUMIFS(prueba!$A:$A, prueba!$C:$C, $A84, prueba!$B:$B, "KG")) - (SUMIFS(COMPRAS!$E:$E, COMPRAS!$C:$C, $A84, COMPRAS!$J:$J, "UNIDAD") + SUMIFS(COMPRAS!$E:$E, COMPRAS!$C:$C, $A84, COMPRAS!$J:$J, "KG"))), 0) -> 0 | I84: =IFERROR(C84 / F84, 0) -> 0 | J84: =IFERROR(ROUNDUP((E84 / F84) * 1.1, -2),0) -> 0 | K84: =A84&B84 -> POMELO NACIONALCAJON
A85: POMELO NACIONAL | B85: KG | C85: =IFERROR(AVERAGEIFS(COMPRAS!$D:$D, COMPRAS!$C:$C, $A85, COMPRAS!$J:$J, $B85), 0) -> 0 | D85: 1.3 | E85: =ROUNDUP(C85 *D85, -2) -> 0 | F85: =IFERROR(AVERAGEIFS(COMPRAS!$F:$F, COMPRAS!$C:$C, $A85, COMPRAS!$J:$J, $B85), 1) -> 1 | G85: =IFERROR(SUMIFS(COMPRAS!I:I, COMPRAS!C:C, A85) * SUMIFS(COMPRAS!E:E, COMPRAS!C:C, A85) / COUNTIF(COMPRAS!C:C, A85), 0) -> 0 | H85: =MAX(0, (SUMIFS(COMPRAS!$E:$E, COMPRAS!$C:$C, $A85, COMPRAS!$J:$J, "UNIDAD") + SUMIFS(COMPRAS!$E:$E, COMPRAS!$C:$C, $A85, COMPRAS!$J:$J, "KG")) - (SUMIFS(prueba!$A:$A, prueba!$C:$C, $A85, prueba!$B:$B, "UNIDAD") + SUMIFS(prueba!$A:$A, prueba!$C:$C, $A85, prueba!$B:$B, "KG")) ) -> 0 | I85: =IFERROR(C85 / F85, 0) -> 0 | J85: =IFERROR(ROUNDUP((E85 / F85) * 1.1, -2),0) -> 0 | K85: =A85&B85 -> POMELO NACIONALKG
A86: UVA BLANCA | B86: CAJON | C86: =IFERROR(AVERAGEIFS(COMPRAS!$D:$D, COMPRAS!$C:$C, $A86, COMPRAS!$J:$J, $B86), 0) -> 0 | D86: 1.3 | E86: =ROUNDUP(C86 * D86, -3) -> 0 | F86: =IFERROR(AVERAGEIFS(COMPRAS!$F:$F, COMPRAS!$C:$C, $A86, COMPRAS!$J:$J, $B86), 1) -> 1 | G86: =IFERROR(SUMIFS(COMPRAS!I:I, COMPRAS!C:C, A86) * SUMIFS(COMPRAS!E:E, COMPRAS!C:C, A86) / COUNTIF(COMPRAS!C:C, A86), 0) -> 0 | H86: =IFERROR( ((SUMIFS(COMPRAS!$E:$E, COMPRAS!$C:$C, $A86, COMPRAS!$J:$J, "CAJON") + SUMIFS(COMPRAS!$E:$E, COMPRAS!$C:$C, $A86, COMPRAS!$J:$J, "BOLSA")) * $F86) - ((SUMIFS(prueba!$A:$A, prueba!$C:$C, $A86, prueba!$B:$B, "CAJON") + SUMIFS(prueba!$A:$A, prueba!$C:$C, $A86, prueba!$B:$B, "BOLSA")) * $F86) - MAX(0, (SUMIFS(prueba!$A:$A, prueba!$C:$C, $A86, prueba!$B:$B, "UNIDAD") + SUMIFS(prueba!$A:$A, prueba!$C:$C, $A86, prueba!$B:$B, "KG")) - (SUMIFS(COMPRAS!$E:$E, COMPRAS!$C:$C, $A86, COMPRAS!$J:$J, "UNIDAD") + SUMIFS(COMPRAS!$E:$E, COMPRAS!$C:$C, $A86, COMPRAS!$J:$J, "KG"))), 0) -> 0 | I86: =IFERROR(C86 / F86, 0) -> 0 | J86: =IFERROR(ROUNDUP((E86 / F86) * 1.1, -2),0) -> 0 | K86: =A86&B86 -> UVA BLANCACAJON
A87: UVA BLANCA | B87: KG | C87: =IFERROR(AVERAGEIFS(COMPRAS!$D:$D, COMPRAS!$C:$C, $A87, COMPRAS!$J:$J, $B87), 0) -> 0 | D87: 1.3 | E87: =ROUNDUP(C87 * D87, -2) -> 0 | F87: =IFERROR(AVERAGEIFS(COMPRAS!$F:$F, COMPRAS!$C:$C, $A87, COMPRAS!$J:$J, $B87), 1) -> 1 | G87: =IFERROR(SUMIFS(COMPRAS!I:I, COMPRAS!C:C, A87) * SUMIFS(COMPRAS!E:E, COMPRAS!C:C, A87) / COUNTIF(COMPRAS!C:C, A87), 0) -> 0 | H87: =MAX(0, (SUMIFS(COMPRAS!$E:$E, COMPRAS!$C:$C, $A87, COMPRAS!$J:$J, "UNIDAD") + SUMIFS(COMPRAS!$E:$E, COMPRAS!$C:$C, $A87, COMPRAS!$J:$J, "KG")) - (SUMIFS(prueba!$A:$A, prueba!$C:$C, $A87, prueba!$B:$B, "UNIDAD") + SUMIFS(prueba!$A:$A, prueba!$C:$C, $A87, prueba!$B:$B, "KG")) ) -> 0 | I87: =IFERROR(C87 / F87, 0) -> 0 | J87: =IFERROR(ROUNDUP((E87 / F87) * 1.1, -2),0) -> 0 | K87: =A87&B87 -> UVA BLANCAKG
A88: UVA ROSADA | B88: CAJON | C88: =IFERROR(AVERAGEIFS(COMPRAS!$D:$D, COMPRAS!$C:$C, $A88, COMPRAS!$J:$J, $B88), 0) -> 0 | D88: 1.3 | E88: =ROUNDUP(C88 *D88, -3) -> 0 | F88: =IFERROR(AVERAGEIFS(COMPRAS!$F:$F, COMPRAS!$C:$C, $A88, COMPRAS!$J:$J, $B88), 1) -> 1 | G88: =IFERROR(SUMIFS(COMPRAS!I:I, COMPRAS!C:C, A88) * SUMIFS(COMPRAS!E:E, COMPRAS!C:C, A88) / COUNTIF(COMPRAS!C:C, A88), 0) -> 0 | H88: =IFERROR( ((SUMIFS(COMPRAS!$E:$E, COMPRAS!$C:$C, $A88, COMPRAS!$J:$J, "CAJON") + SUMIFS(COMPRAS!$E:$E, COMPRAS!$C:$C, $A88, COMPRAS!$J:$J, "BOLSA")) * $F88) - ((SUMIFS(prueba!$A:$A, prueba!$C:$C, $A88, prueba!$B:$B, "CAJON") + SUMIFS(prueba!$A:$A, prueba!$C:$C, $A88, prueba!$B:$B, "BOLSA")) * $F88) - MAX(0, (SUMIFS(prueba!$A:$A, prueba!$C:$C, $A88, prueba!$B:$B, "UNIDAD") + SUMIFS(prueba!$A:$A, prueba!$C:$C, $A88, prueba!$B:$B, "KG")) - (SUMIFS(COMPRAS!$E:$E, COMPRAS!$C:$C, $A88, COMPRAS!$J:$J, "UNIDAD") + SUMIFS(COMPRAS!$E:$E, COMPRAS!$C:$C, $A88, COMPRAS!$J:$J, "KG"))), 0) -> 0 | I88: =IFERROR(C88 / F88, 0) -> 0 | J88: =IFERROR(ROUNDUP((E88 / F88) * 1.1, -2),0) -> 0 | K88: =A88&B88 -> UVA ROSADACAJON
A89: UVA ROSADA | B89: KG | C89: =IFERROR(AVERAGEIFS(COMPRAS!$D:$D, COMPRAS!$C:$C, $A89, COMPRAS!$J:$J, $B89), 0) -> 0 | D89: 1.3 | E89: =ROUNDUP(C89 *D89, -2) -> 0 | F89: =IFERROR(AVERAGEIFS(COMPRAS!$F:$F, COMPRAS!$C:$C, $A89, COMPRAS!$J:$J, $B89), 1) -> 1 | G89: =IFERROR(SUMIFS(COMPRAS!I:I, COMPRAS!C:C, A89) * SUMIFS(COMPRAS!E:E, COMPRAS!C:C, A89) / COUNTIF(COMPRAS!C:C, A89), 0) -> 0 | H89: =MAX(0, (SUMIFS(COMPRAS!$E:$E, COMPRAS!$C:$C, $A89, COMPRAS!$J:$J, "UNIDAD") + SUMIFS(COMPRAS!$E:$E, COMPRAS!$C:$C, $A89, COMPRAS!$J:$J, "KG")) - (SUMIFS(prueba!$A:$A, prueba!$C:$C, $A89, prueba!$B:$B, "UNIDAD") + SUMIFS(prueba!$A:$A, prueba!$C:$C, $A89, prueba!$B:$B, "KG")) ) -> 0 | I89: =IFERROR(C89 / F89, 0) -> 0 | J89: =IFERROR(ROUNDUP((E89 / F89) * 1.1, -2),0) -> 0 | K89: =A89&B89 -> UVA ROSADAKG
A90: UVA NEGRA | B90: CAJON | C90: =IFERROR(AVERAGEIFS(COMPRAS!$D:$D, COMPRAS!$C:$C, $A90, COMPRAS!$J:$J, $B90), 0) -> 0 | D90: 1.3 | E90: =ROUNDUP(C90 *D90, -3) -> 0 | F90: =IFERROR(AVERAGEIFS(COMPRAS!$F:$F, COMPRAS!$C:$C, $A90, COMPRAS!$J:$J, $B90), 1) -> 1 | G90: =IFERROR(SUMIFS(COMPRAS!I:I, COMPRAS!C:C, A90) * SUMIFS(COMPRAS!E:E, COMPRAS!C:C, A90) / COUNTIF(COMPRAS!C:C, A90), 0) -> 0 | H90: =IFERROR( ((SUMIFS(COMPRAS!$E:$E, COMPRAS!$C:$C, $A90, COMPRAS!$J:$J, "CAJON") + SUMIFS(COMPRAS!$E:$E, COMPRAS!$C:$C, $A90, COMPRAS!$J:$J, "BOLSA")) * $F90) - ((SUMIFS(prueba!$A:$A, prueba!$C:$C, $A90, prueba!$B:$B, "CAJON") + SUMIFS(prueba!$A:$A, prueba!$C:$C, $A90, prueba!$B:$B, "BOLSA")) * $F90) - MAX(0, (SUMIFS(prueba!$A:$A, prueba!$C:$C, $A90, prueba!$B:$B, "UNIDAD") + SUMIFS(prueba!$A:$A, prueba!$C:$C, $A90, prueba!$B:$B, "KG")) - (SUMIFS(COMPRAS!$E:$E, COMPRAS!$C:$C, $A90, COMPRAS!$J:$J, "UNIDAD") + SUMIFS(COMPRAS!$E:$E, COMPRAS!$C:$C, $A90, COMPRAS!$J:$J, "KG"))), 0) -> 0 | I90: =IFERROR(C90 / F90, 0) -> 0 | J90: =IFERROR(ROUNDUP((E90 / F90) * 1.1, -2),0) -> 0 | K90: =A90&B90 -> UVA NEGRACAJON
A91: UVA NEGRA | B91: KG | C91: =IFERROR(AVERAGEIFS(COMPRAS!$D:$D, COMPRAS!$C:$C, $A91, COMPRAS!$J:$J, $B91), 0) -> 0 | D91: 1.3 | E91: =ROUNDUP(C91 *D91, -2) -> 0 | F91: =IFERROR(AVERAGEIFS(COMPRAS!$F:$F, COMPRAS!$C:$C, $A91, COMPRAS!$J:$J, $B91), 1) -> 1 | G91: =IFERROR(SUMIFS(COMPRAS!I:I, COMPRAS!C:C, A91) * SUMIFS(COMPRAS!E:E, COMPRAS!C:C, A91) / COUNTIF(COMPRAS!C:C, A91), 0) -> 0 | H91: =MAX(0, (SUMIFS(COMPRAS!$E:$E, COMPRAS!$C:$C, $A91, COMPRAS!$J:$J, "UNIDAD") + SUMIFS(COMPRAS!$E:$E, COMPRAS!$C:$C, $A91, COMPRAS!$J:$J, "KG")) - (SUMIFS(prueba!$A:$A, prueba!$C:$C, $A91, prueba!$B:$B, "UNIDAD") + SUMIFS(prueba!$A:$A, prueba!$C:$C, $A91, prueba!$B:$B, "KG")) ) -> 0 | I91: =IFERROR(C91 / F91, 0) -> 0 | J91: =IFERROR(ROUNDUP((E91 / F91) * 1.1, -2),0) -> 0 | K91: =A91&B91 -> UVA NEGRAKG
A92: PERA | B92: CAJON | C92: =IFERROR(AVERAGEIFS(COMPRAS!$D:$D, COMPRAS!$C:$C, $A92, COMPRAS!$J:$J, $B92), 0) -> 0 | D92: 1.3 | E92: =ROUNDUP(C92 *D92, -3) -> 0 | F92: =IFERROR(AVERAGEIFS(COMPRAS!$F:$F, COMPRAS!$C:$C, $A92, COMPRAS!$J:$J, $B92), 1) -> 1 | G92: =IFERROR(SUMIFS(COMPRAS!I:I, COMPRAS!C:C, A92) * SUMIFS(COMPRAS!E:E, COMPRAS!C:C, A92) / COUNTIF(COMPRAS!C:C, A92), 0) -> 0 | H92: =IFERROR( ((SUMIFS(COMPRAS!$E:$E, COMPRAS!$C:$C, $A92, COMPRAS!$J:$J, "CAJON") + SUMIFS(COMPRAS!$E:$E, COMPRAS!$C:$C, $A92, COMPRAS!$J:$J, "BOLSA")) * $F92) - ((SUMIFS(prueba!$A:$A, prueba!$C:$C, $A92, prueba!$B:$B, "CAJON") + SUMIFS(prueba!$A:$A, prueba!$C:$C, $A92, prueba!$B:$B, "BOLSA")) * $F92) - MAX(0, (SUMIFS(prueba!$A:$A, prueba!$C:$C, $A92, prueba!$B:$B, "UNIDAD") + SUMIFS(prueba!$A:$A, prueba!$C:$C, $A92, prueba!$B:$B, "KG")) - (SUMIFS(COMPRAS!$E:$E, COMPRAS!$C:$C, $A92, COMPRAS!$J:$J, "UNIDAD") + SUMIFS(COMPRAS!$E:$E, COMPRAS!$C:$C, $A92, COMPRAS!$J:$J, "KG"))), 0) -> 0 | I92: =IFERROR(C92 / F92, 0) -> 0 | J92: =IFERROR(ROUNDUP((E92 / F92) * 1.1, -2),0) -> 0 | K92: =A92&B92 -> PERACAJON
A93: PERA | B93: KG | C93: =IFERROR(AVERAGEIFS(COMPRAS!$D:$D, COMPRAS!$C:$C, $A93, COMPRAS!$J:$J, $B93), 0) -> 0 | D93: 1.3 | E93: =ROUNDUP(C93 *D93, -2) -> 0 | F93: =IFERROR(AVERAGEIFS(COMPRAS!$F:$F, COMPRAS!$C:$C, $A93, COMPRAS!$J:$J, $B93), 1) -> 1 | G93: =IFERROR(SUMIFS(COMPRAS!I:I, COMPRAS!C:C, A93) * SUMIFS(COMPRAS!E:E, COMPRAS!C:C, A93) / COUNTIF(COMPRAS!C:C, A93), 0) -> 0 | H93: =MAX(0, (SUMIFS(COMPRAS!$E:$E, COMPRAS!$C:$C, $A93, COMPRAS!$J:$J, "UNIDAD") + SUMIFS(COMPRAS!$E:$E, COMPRAS!$C:$C, $A93, COMPRAS!$J:$J, "KG")) - (SUMIFS(prueba!$A:$A, prueba!$C:$C, $A93, prueba!$B:$B, "UNIDAD") + SUMIFS(prueba!$A:$A, prueba!$C:$C, $A93, prueba!$B:$B, "KG")) ) -> 0 | I93: =IFERROR(C93 / F93, 0) -> 0 | J93: =IFERROR(ROUNDUP((E93 / F93) * 1.1, -2),0) -> 0 | K93: =A93&B93 -> PERAKG
A94: BERENJENA | B94: CAJON | C94: =IFERROR(AVERAGEIFS(COMPRAS!$D:$D, COMPRAS!$C:$C, $A94, COMPRAS!$J:$J, $B94), 0) -> 0 | D94: 1.3 | E94: =ROUNDUP(C94 *D94, -3) -> 0 | F94: =IFERROR(AVERAGEIFS(COMPRAS!$F:$F, COMPRAS!$C:$C, $A94, COMPRAS!$J:$J, $B94), 1) -> 1 | G94: =IFERROR(SUMIFS(COMPRAS!I:I, COMPRAS!C:C, A94) * SUMIFS(COMPRAS!E:E, COMPRAS!C:C, A94) / COUNTIF(COMPRAS!C:C, A94), 0) -> 0 | H94: =IFERROR( ((SUMIFS(COMPRAS!$E:$E, COMPRAS!$C:$C, $A94, COMPRAS!$J:$J, "CAJON") + SUMIFS(COMPRAS!$E:$E, COMPRAS!$C:$C, $A94, COMPRAS!$J:$J, "BOLSA")) * $F94) - ((SUMIFS(prueba!$A:$A, prueba!$C:$C, $A94, prueba!$B:$B, "CAJON") + SUMIFS(prueba!$A:$A, prueba!$C:$C, $A94, prueba!$B:$B, "BOLSA")) * $F94) - MAX(0, (SUMIFS(prueba!$A:$A, prueba!$C:$C, $A94, prueba!$B:$B, "UNIDAD") + SUMIFS(prueba!$A:$A, prueba!$C:$C, $A94, prueba!$B:$B, "KG")) - (SUMIFS(COMPRAS!$E:$E, COMPRAS!$C:$C, $A94, COMPRAS!$J:$J, "UNIDAD") + SUMIFS(COMPRAS!$E:$E, COMPRAS!$C:$C, $A94, COMPRAS!$J:$J, "KG"))), 0) -> 0 | I94: =IFERROR(C94 / F94, 0) -> 0 | J94: =IFERROR(ROUNDUP((E94 / F94) * 1.1, -2),0) -> 0 | K94: =A94&B94 -> BERENJENACAJON
A95: BERENJENA | B95: KG | C95: =IFERROR(AVERAGEIFS(COMPRAS!$D:$D, COMPRAS!$C:$C, $A95, COMPRAS!$J:$J, $B95), 0) -> 0 | D95: 1.3 | E95: =ROUNDUP(C95 *D95, -2) -> 0 | F95: =IFERROR(AVERAGEIFS(COMPRAS!$F:$F, COMPRAS!$C:$C, $A95, COMPRAS!$J:$J, $B95), 1) -> 1 | G95: =IFERROR(SUMIFS(COMPRAS!I:I, COMPRAS!C:C, A95) * SUMIFS(COMPRAS!E:E, COMPRAS!C:C, A95) / COUNTIF(COMPRAS!C:C, A95), 0) -> 0 | H95: =MAX(0, (SUMIFS(COMPRAS!$E:$E, COMPRAS!$C:$C, $A95, COMPRAS!$J:$J, "UNIDAD") + SUMIFS(COMPRAS!$E:$E, COMPRAS!$C:$C, $A95, COMPRAS!$J:$J, "KG")) - (SUMIFS(prueba!$A:$A, prueba!$C:$C, $A95, prueba!$B:$B, "UNIDAD") + SUMIFS(prueba!$A:$A, prueba!$C:$C, $A95, prueba!$B:$B, "KG")) ) -> 0 | I95: =IFERROR(C95 / F95, 0) -> 0 | J95: =IFERROR(ROUNDUP((E95 / F95) * 1.1, -2),0) -> 0 | K95: =A95&B95 -> BERENJENAKG
A96: CHAUCHA ROLLIZA | B96: CAJON | C96: =IFERROR(AVERAGEIFS(COMPRAS!$D:$D, COMPRAS!$C:$C, $A96, COMPRAS!$J:$J, $B96), 0) -> 0 | D96: 1.3 | E96: =ROUNDUP(C96 *D96, -3) -> 0 | F96: =IFERROR(AVERAGEIFS(COMPRAS!$F:$F, COMPRAS!$C:$C, $A96, COMPRAS!$J:$J, $B96), 1) -> 1 | G96: =IFERROR(SUMIFS(COMPRAS!I:I, COMPRAS!C:C, A96) * SUMIFS(COMPRAS!E:E, COMPRAS!C:C, A96) / COUNTIF(COMPRAS!C:C, A96), 0) -> 0 | H96: =IFERROR( ((SUMIFS(COMPRAS!$E:$E, COMPRAS!$C:$C, $A96, COMPRAS!$J:$J, "CAJON") + SUMIFS(COMPRAS!$E:$E, COMPRAS!$C:$C, $A96, COMPRAS!$J:$J, "BOLSA")) * $F96) - ((SUMIFS(prueba!$A:$A, prueba!$C:$C, $A96, prueba!$B:$B, "CAJON") + SUMIFS(prueba!$A:$A, prueba!$C:$C, $A96, prueba!$B:$B, "BOLSA")) * $F96) - MAX(0, (SUMIFS(prueba!$A:$A, prueba!$C:$C, $A96, prueba!$B:$B, "UNIDAD") + SUMIFS(prueba!$A:$A, prueba!$C:$C, $A96, prueba!$B:$B, "KG")) - (SUMIFS(COMPRAS!$E:$E, COMPRAS!$C:$C, $A96, COMPRAS!$J:$J, "UNIDAD") + SUMIFS(COMPRAS!$E:$E, COMPRAS!$C:$C, $A96, COMPRAS!$J:$J, "KG"))), 0) -> 0 | I96: =IFERROR(C96 / F96, 0) -> 0 | J96: =IFERROR(ROUNDUP((E96 / F96) * 1.1, -2),0) -> 0 | K96: =A96&B96 -> CHAUCHA ROLLIZACAJON
A97: CHAUCHA ROLLIZA | B97: KG | C97: =IFERROR(AVERAGEIFS(COMPRAS!$D:$D, COMPRAS!$C:$C, $A97, COMPRAS!$J:$J, $B97), 0) -> 0 | D97: 1.3 | E97: =ROUNDUP(C97 *D97, -2) -> 0 | F97: =IFERROR(AVERAGEIFS(COMPRAS!$F:$F, COMPRAS!$C:$C, $A97, COMPRAS!$J:$J, $B97), 1) -> 1 | G97: =IFERROR(SUMIFS(COMPRAS!I:I, COMPRAS!C:C, A97) * SUMIFS(COMPRAS!E:E, COMPRAS!C:C, A97) / COUNTIF(COMPRAS!C:C, A97), 0) -> 0 | H97: =MAX(0, (SUMIFS(COMPRAS!$E:$E, COMPRAS!$C:$C, $A97, COMPRAS!$J:$J, "UNIDAD") + SUMIFS(COMPRAS!$E:$E, COMPRAS!$C:$C, $A97, COMPRAS!$J:$J, "KG")) - (SUMIFS(prueba!$A:$A, prueba!$C:$C, $A97, prueba!$B:$B, "UNIDAD") + SUMIFS(prueba!$A:$A, prueba!$C:$C, $A97, prueba!$B:$B, "KG")) ) -> 0 | I97: =IFERROR(C97 / F97, 0) -> 0 | J97: =IFERROR(ROUNDUP((E97 / F97) * 1.1, -2),0) -> 0 | K97: =A97&B97 -> CHAUCHA ROLLIZAKG
A98: CHAUCHA PLANA | B98: CAJON | C98: =IFERROR(AVERAGEIFS(COMPRAS!$D:$D, COMPRAS!$C:$C, $A98, COMPRAS!$J:$J, $B98), 0) -> 0 | D98: 1.3 | E98: =ROUNDUP(C98 * D98, -3) -> 0 | F98: =IFERROR(AVERAGEIFS(COMPRAS!$F:$F, COMPRAS!$C:$C, $A98, COMPRAS!$J:$J, $B98), 1) -> 1 | G98: =IFERROR(SUMIFS(COMPRAS!I:I, COMPRAS!C:C, A98) * SUMIFS(COMPRAS!E:E, COMPRAS!C:C, A98) / COUNTIF(COMPRAS!C:C, A98), 0) -> 0 | H98: =IFERROR( ((SUMIFS(COMPRAS!$E:$E, COMPRAS!$C:$C, $A98, COMPRAS!$J:$J, "CAJON") + SUMIFS(COMPRAS!$E:$E, COMPRAS!$C:$C, $A98, COMPRAS!$J:$J, "BOLSA")) * $F98) - ((SUMIFS(prueba!$A:$A, prueba!$C:$C, $A98, prueba!$B:$B, "CAJON") + SUMIFS(prueba!$A:$A, prueba!$C:$C, $A98, prueba!$B:$B, "BOLSA")) * $F98) - MAX(0, (SUMIFS(prueba!$A:$A, prueba!$C:$C, $A98, prueba!$B:$B, "UNIDAD") + SUMIFS(prueba!$A:$A, prueba!$C:$C, $A98, prueba!$B:$B, "KG")) - (SUMIFS(COMPRAS!$E:$E, COMPRAS!$C:$C, $A98, COMPRAS!$J:$J, "UNIDAD") + SUMIFS(COMPRAS!$E:$E, COMPRAS!$C:$C, $A98, COMPRAS!$J:$J, "KG"))), 0) -> 0 | I98: =IFERROR(C98 / F98, 0) -> 0 | J98: =IFERROR(ROUNDUP((E98 / F98) * 1.1, -2),0) -> 0 | K98: =A98&B98 -> CHAUCHA PLANACAJON
A99: CHAUCHA PLANA | B99: KG | C99: =IFERROR(AVERAGEIFS(COMPRAS!$D:$D, COMPRAS!$C:$C, $A99, COMPRAS!$J:$J, $B99), 0) -> 0 | D99: 1.3 | E99: =ROUNDUP(C99 * D99, -2) -> 0 | F99: =IFERROR(AVERAGEIFS(COMPRAS!$F:$F, COMPRAS!$C:$C, $A99, COMPRAS!$J:$J, $B99), 1) -> 1 | G99: =IFERROR(SUMIFS(COMPRAS!I:I, COMPRAS!C:C, A99) * SUMIFS(COMPRAS!E:E, COMPRAS!C:C, A99) / COUNTIF(COMPRAS!C:C, A99), 0) -> 0 | H99: =MAX(0, (SUMIFS(COMPRAS!$E:$E, COMPRAS!$C:$C, $A99, COMPRAS!$J:$J, "UNIDAD") + SUMIFS(COMPRAS!$E:$E, COMPRAS!$C:$C, $A99, COMPRAS!$J:$J, "KG")) - (SUMIFS(prueba!$A:$A, prueba!$C:$C, $A99, prueba!$B:$B, "UNIDAD") + SUMIFS(prueba!$A:$A, prueba!$C:$C, $A99, prueba!$B:$B, "KG")) ) -> 0 | I99: =IFERROR(C99 / F99, 0) -> 0 | J99: =IFERROR(ROUNDUP((E99 / F99) * 1.1, -2),0) -> 0 | K99: =A99&B99 -> CHAUCHA PLANAKG
A100: CHOCLO | B100: CAJON | C100: =IFERROR(AVERAGEIFS(COMPRAS!$D:$D, COMPRAS!$C:$C, $A100, COMPRAS!$J:$J, $B100), 0) -> 0 | D100: 1.3 | E100: =ROUNDUP(C100 *D100, -3) -> 0 | F100: =IFERROR(AVERAGEIFS(COMPRAS!$F:$F, COMPRAS!$C:$C, $A100, COMPRAS!$J:$J, $B100), 1) -> 1 | G100: =IFERROR(SUMIFS(COMPRAS!I:I, COMPRAS!C:C, A100) * SUMIFS(COMPRAS!E:E, COMPRAS!C:C, A100) / COUNTIF(COMPRAS!C:C, A100), 0) -> 0 | H100: =IFERROR( ((SUMIFS(COMPRAS!$E:$E, COMPRAS!$C:$C, $A100, COMPRAS!$J:$J, "CAJON") + SUMIFS(COMPRAS!$E:$E, COMPRAS!$C:$C, $A100, COMPRAS!$J:$J, "BOLSA")) * $F100) - ((SUMIFS(prueba!$A:$A, prueba!$C:$C, $A100, prueba!$B:$B, "CAJON") + SUMIFS(prueba!$A:$A, prueba!$C:$C, $A100, prueba!$B:$B, "BOLSA")) * $F100) - MAX(0, (SUMIFS(prueba!$A:$A, prueba!$C:$C, $A100, prueba!$B:$B, "UNIDAD") + SUMIFS(prueba!$A:$A, prueba!$C:$C, $A100, prueba!$B:$B, "KG")) - (SUMIFS(COMPRAS!$E:$E, COMPRAS!$C:$C, $A100, COMPRAS!$J:$J, "UNIDAD") + SUMIFS(COMPRAS!$E:$E, COMPRAS!$C:$C, $A100, COMPRAS!$J:$J, "KG"))), 0) -> 0 | I100: =IFERROR(C100 / F100, 0) -> 0 | J100: =IFERROR(ROUNDUP((E100 / F100) * 1.1, -2),0) -> 0 | K100: =A100&B100 -> CHOCLOCAJON
...

Sheet STOCK
B1: COPIAR MENSAJE ABAJO (B2)
C4: STOCK | J4: MERMA
C5: CANTIDAD | D5: UNIDAD | E5: PRODUCTO | F5: KG/UN BULTO | G5: PRECIO | H5: TOTAL | J5: CANTIDAD | K5: UNIDAD | L5: PRODCUTO | M5: VALOR
C6: 1 | D6: CAJON | E6: BANANA ECUADOR | F6: =IFERROR(VLOOKUP(E6, PRECIOS!$A$40:$I$500, 6, FALSE), 1) -> 1 | G6: =IFERROR(VLOOKUP(E6, PRECIOS!$A$40:$I$500, 9, FALSE), 0) -> 0 | H6: =C6 * IFERROR(VLOOKUP(E6, PRECIOS!$A$40:$I$500, 3, FALSE), 0) -> 0 | J6: =(C6 * F6) - IFERROR(VLOOKUP(E6, PRECIOS!$A$40:$I$500, 8, FALSE), 0) -> 1 | K6: KG | L6: BANANA ECUADOR | M6: =J6 * G6 -> 0
C7: 8 | D7: KG | E7: TOMATE REDONDO | F7: =1 -> 1 | G7: =IFERROR(VLOOKUP(E7, PRECIOS!$A$40:$I$500, 9, FALSE), 0) -> 0 | H7: =C7 * IFERROR(VLOOKUP(E7, PRECIOS!$A$40:$I$500, 3, FALSE), 0) -> 0 | J7: =(C7 * F7) - IFERROR(VLOOKUP(E7, PRECIOS!$A$40:$I$500, 8, FALSE), 0) -> 10 | K7: KG | L7: TOMATE REDONDO | M7: =J7 * G7 -> 0
C8: 2 | D8: KG | E8: CEBOLLA MAQUINADA | F8: =1 -> 1 | G8: =IFERROR(VLOOKUP(E8, PRECIOS!$A$40:$I$500, 9, FALSE), 0) -> 0 | H8: =C8 * IFERROR(VLOOKUP(E8, PRECIOS!$A$40:$I$500, 3, FALSE), 0) -> 0 | J8: =(C8 * F8) - IFERROR(VLOOKUP(E8, PRECIOS!$A$40:$I$500, 8, FALSE), 0) -> 2 | K8: KG | L8: CEBOLLA MAQUINADA | M8: =J8 * G8 -> 0

Sheet ARMADO DE COMPRA
B1: COPIAR MENSAJE ABAJO (B2)
B4: CLIENTES YA PROCESADOS | C4: GRUPO | D4: CANTIDAD | E4: UNIDAD | F4: PRODUCTO
B5: FV | C5: FRUTA | D5: 2 | E5: CAJON | F5: NARANJA JUGO COMERCIAL
B6: BRASOV | C6: HORTALIZA LIVIANA | D6: 3 | E6: CAJON | F6: TOMATE REDONDO
C7: VERDURA | D7: 12 | E7: UNIDAD | F7: APIO

Sheet CARGA DE PEDIDOS
B1: COPIAR MENSAJE ABAJO (B2)
C4: ¿LLEVA IVA? | D4: SI
C6: FV | F6: rto: | G6: =TODAY() -> 46079 | K6: COMPRA
C8: CANTIDAD | D8: UNIDAD | E8: PRODUCTO | F8: PRECIO | G8: TOTAL | H8: TOTAL + IVA | K8: COSTO | L8: TOTAL | M8: DIFERENCIA
C9: 2 | D9: CAJON | E9: TOMATE REDONDO | F9: =LET( precio_exacto, SUMIFS(PRECIOS!$E:$E, PRECIOS!$A:$A, E9, PRECIOS!$B:$B, D9), precio_unitario_cajon, SUMIFS(PRECIOS!$J:$J, PRECIOS!$A:$A, E9, PRECIOS!$B:$B, "CAJON"), precio_unitario_bolsa, SUMIFS(PRECIOS!$J:$J, PRECIOS!$A:$A, E9, PRECIOS!$B:$B, "BOLSA"), IF(precio_exacto > 0, precio_exacto, IF(precio_unitario_cajon > 0, precio_unitario_cajon, IF(precio_unitario_bolsa > 0, precio_unitario_bolsa, 0) ) ) ) -> 0 | G9: =C9*F9 -> 0 | H9: =G9*1.105 -> 0 | K9: =IFERROR( IF(OR(D9="CAJON", D9="BOLSA"), SUMIFS(PRECIOS!$C:$C, PRECIOS!$A:$A, E9, PRECIOS!$B:$B, D9), LET( stock_suelto_inicial, SUMIFS(COMPRAS!$E:$E, COMPRAS!$C:$C, E9, COMPRAS!$J:$J, "UNIDAD") + SUMIFS(COMPRAS!$E:$E, COMPRAS!$C:$C, E9, COMPRAS!$J:$J, "KG"), acumulado_anterior, SUMIFS($M8:O$9, $C8:E$9, E9), unidades_esta_venta, C9, costo_unidad_base, SUMIFS(PRECIOS!$I:$I, PRECIOS!$A:$A, E9, PRECIOS!$B:$B, "UNIDAD") + SUMIFS(PRECIOS!$I:$I, PRECIOS!$A:$A, E9, PRECIOS!$B:$B, "KG"), costo_cajon, SUMIFS(PRECIOS!$I:$I, PRECIOS!$A:$A, E9, PRECIOS!$B:$B, "CAJON"), costo_bolsa, SUMIFS(PRECIOS!$I:$I, PRECIOS!$A:$A, E9, PRECIOS!$B:$B, "BOLSA"), costo_bulto_ref, IF(costo_cajon > 0, costo_cajon, costo_bolsa), unidades_con_costo_suelto, MAX(0, MIN(unidades_esta_venta, stock_suelto_inicial - acumulado_anterior)), unidades_con_costo_bulto, unidades_esta_venta - unidades_con_costo_suelto, IF(unidades_esta_venta = 0, 0, ((unidades_con_costo_suelto * costo_unidad_base) + (unidades_con_costo_bulto * costo_bulto_ref)) / unidades_esta_venta ) ) ), 0) -> 0 | L9: =K9*C9 -> 0 | M9: =H9-L9 -> 0
C10: 2 | D10: UNIDAD | E10: APIO | F10: =LET( precio_exacto, SUMIFS(PRECIOS!$E:$E, PRECIOS!$A:$A, E10, PRECIOS!$B:$B, D10), precio_unitario_cajon, SUMIFS(PRECIOS!$J:$J, PRECIOS!$A:$A, E10, PRECIOS!$B:$B, "CAJON"), precio_unitario_bolsa, SUMIFS(PRECIOS!$J:$J, PRECIOS!$A:$A, E10, PRECIOS!$B:$B, "BOLSA"), IF(precio_exacto > 0, precio_exacto, IF(precio_unitario_cajon > 0, precio_unitario_cajon, IF(precio_unitario_bolsa > 0, precio_unitario_bolsa, 0) ) ) ) -> 0 | G10: =C10*F10 -> 0 | H10: =G10*1.105 -> 0 | K10: =IFERROR( IF(OR(D10="CAJON", D10="BOLSA"), SUMIFS(PRECIOS!$C:$C, PRECIOS!$A:$A, E10, PRECIOS!$B:$B, D10), LET( stock_suelto_inicial, SUMIFS(COMPRAS!$E:$E, COMPRAS!$C:$C, E10, COMPRAS!$J:$J, "UNIDAD") + SUMIFS(COMPRAS!$E:$E, COMPRAS!$C:$C, E10, COMPRAS!$J:$J, "KG"), acumulado_anterior, SUMIFS($M$9:O9, $C$9:E9, E10), unidades_esta_venta, C10, costo_unidad_base, SUMIFS(PRECIOS!$I:$I, PRECIOS!$A:$A, E10, PRECIOS!$B:$B, "UNIDAD") + SUMIFS(PRECIOS!$I:$I, PRECIOS!$A:$A, E10, PRECIOS!$B:$B, "KG"), costo_cajon, SUMIFS(PRECIOS!$I:$I, PRECIOS!$A:$A, E10, PRECIOS!$B:$B, "CAJON"), costo_bolsa, SUMIFS(PRECIOS!$I:$I, PRECIOS!$A:$A, E10, PRECIOS!$B:$B, "BOLSA"), costo_bulto_ref, IF(costo_cajon > 0, costo_cajon, costo_bolsa), unidades_con_costo_suelto, MAX(0, MIN(unidades_esta_venta, stock_suelto_inicial - acumulado_anterior)), unidades_con_costo_bulto, unidades_esta_venta - unidades_con_costo_suelto, IF(unidades_esta_venta = 0, 0, ((unidades_con_costo_suelto * costo_unidad_base) + (unidades_con_costo_bulto * costo_bulto_ref)) / unidades_esta_venta ) ) ), 0) -> 0 | L10: =K10*C10 -> 0 | M10: =H10-L10 -> 0
C11: 1 | D11: CAJON | E11: NARANJA JUGO COMERCIAL | F11: =LET( precio_exacto, SUMIFS(PRECIOS!$E:$E, PRECIOS!$A:$A, E11, PRECIOS!$B:$B, D11), precio_unitario_cajon, SUMIFS(PRECIOS!$J:$J, PRECIOS!$A:$A, E11, PRECIOS!$B:$B, "CAJON"), precio_unitario_bolsa, SUMIFS(PRECIOS!$J:$J, PRECIOS!$A:$A, E11, PRECIOS!$B:$B, "BOLSA"), IF(precio_exacto > 0, precio_exacto, IF(precio_unitario_cajon > 0, precio_unitario_cajon, IF(precio_unitario_bolsa > 0, precio_unitario_bolsa, 0) ) ) ) -> 0 | G11: =C11*F11 -> 0 | H11: =G11*1.105 -> 0 | K11: =IFERROR( IF(OR(D11="CAJON", D11="BOLSA"), SUMIFS(PRECIOS!$C:$C, PRECIOS!$A:$A, E11, PRECIOS!$B:$B, D11), LET( stock_suelto_inicial, SUMIFS(COMPRAS!$E:$E, COMPRAS!$C:$C, E11, COMPRAS!$J:$J, "UNIDAD") + SUMIFS(COMPRAS!$E:$E, COMPRAS!$C:$C, E11, COMPRAS!$J:$J, "KG"), acumulado_anterior, SUMIFS($M$9:O10, $C$9:E10, E11), unidades_esta_venta, C11, costo_unidad_base, SUMIFS(PRECIOS!$I:$I, PRECIOS!$A:$A, E11, PRECIOS!$B:$B, "UNIDAD") + SUMIFS(PRECIOS!$I:$I, PRECIOS!$A:$A, E11, PRECIOS!$B:$B, "KG"), costo_cajon, SUMIFS(PRECIOS!$I:$I, PRECIOS!$A:$A, E11, PRECIOS!$B:$B, "CAJON"), costo_bolsa, SUMIFS(PRECIOS!$I:$I, PRECIOS!$A:$A, E11, PRECIOS!$B:$B, "BOLSA"), costo_bulto_ref, IF(costo_cajon > 0, costo_cajon, costo_bolsa), unidades_con_costo_suelto, MAX(0, MIN(unidades_esta_venta, stock_suelto_inicial - acumulado_anterior)), unidades_con_costo_bulto, unidades_esta_venta - unidades_con_costo_suelto, IF(unidades_esta_venta = 0, 0, ((unidades_con_costo_suelto * costo_unidad_base) + (unidades_con_costo_bulto * costo_bulto_ref)) / unidades_esta_venta ) ) ), 0) -> 0 | L11: =K11*C11 -> 0 | M11: =H11-L11 -> 0
G13: =SUM(G9:G11) -> 0 | H13: =SUM(H9:H11) -> 0 | M13: =SUM(M9:M11) -> 0 | N13: =IFERROR(M13/G13, 0) -> 0
F500: =LET( precio_exacto, SUMIFS(PRECIOS!$E:$E, PRECIOS!$A:$A, E500, PRECIOS!$B:$B, D500), precio_unitario_cajon, SUMIFS(PRECIOS!$J:$J, PRECIOS!$A:$A, E500, PRECIOS!$B:$B, "CAJON"), precio_unitario_bolsa, SUMIFS(PRECIOS!$J:$J, PRECIOS!$A:$A, E500, PRECIOS!$B:$B, "BOLSA"), IF(precio_exacto > 0, precio_exacto, IF(precio_unitario_cajon > 0, precio_unitario_cajon, IF(precio_unitario_bolsa > 0, precio_unitario_bolsa, 0) ) ) ) -> 0 | G500: =C500*F500 -> 0 | H500: =G500*1.105 -> 0 | K500: =IFERROR( IF(OR(D500="CAJON", D500="BOLSA"), SUMIFS(PRECIOS!$C:$C, PRECIOS!$A:$A, E500, PRECIOS!$B:$B, D500), LET( stock_suelto_inicial, SUMIFS(COMPRAS!$E:$E, COMPRAS!$C:$C, E500, COMPRAS!$J:$J, "UNIDAD") + SUMIFS(COMPRAS!$E:$E, COMPRAS!$C:$C, E500, COMPRAS!$J:$J, "KG"), acumulado_anterior, SUMIFS($M$9:O499, $C$9:E499, E500), unidades_esta_venta, C500, costo_unidad_base, SUMIFS(PRECIOS!$I:$I, PRECIOS!$A:$A, E500, PRECIOS!$B:$B, "UNIDAD") + SUMIFS(PRECIOS!$I:$I, PRECIOS!$A:$A, E500, PRECIOS!$B:$B, "KG"), costo_cajon, SUMIFS(PRECIOS!$I:$I, PRECIOS!$A:$A, E500, PRECIOS!$B:$B, "CAJON"), costo_bolsa, SUMIFS(PRECIOS!$I:$I, PRECIOS!$A:$A, E500, PRECIOS!$B:$B, "BOLSA"), costo_bulto_ref, IF(costo_cajon > 0, costo_cajon, costo_bolsa), unidades_con_costo_suelto, MAX(0, MIN(unidades_esta_venta, stock_suelto_inicial - acumulado_anterior)), unidades_con_costo_bulto, unidades_esta_venta - unidades_con_costo_suelto, IF(unidades_esta_venta = 0, 0, ((unidades_con_costo_suelto * costo_unidad_base) + (unidades_con_costo_bulto * costo_bulto_ref)) / unidades_esta_venta ) ) ), 0) -> 0 | L500: =K500*C500 -> 0 | M500: =H500-L500 -> 0

Sheet prueba
A1: FECHA | B1: =TODAY() -> 46079
A3: FV | D3: rto: | E3: =TODAY() -> 46079 | I3: COMPRA
A5: CANTIDAD | B5: UNIDAD | C5: PRODUCTO | D5: PRECIO | E5: TOTAL | F5: TOTAL + IVA | I5: COSTO | J5: TOTAL | K5: DIFERENCIA | M5: UN/KG X PRODUCTO
A6: 2 | B6: CAJON | C6: TOMATE REDONDO | D6: =LET( precio_exacto, SUMIFS(PRECIOS!$E:$E, PRECIOS!$A:$A, C6, PRECIOS!$B:$B, B6), precio_unitario_cajon, SUMIFS(PRECIOS!$J:$J, PRECIOS!$A:$A, C6, PRECIOS!$B:$B, "CAJON"), precio_unitario_bolsa, SUMIFS(PRECIOS!$J:$J, PRECIOS!$A:$A, C6, PRECIOS!$B:$B, "BOLSA"), IF(precio_exacto > 0, precio_exacto, IF(precio_unitario_cajon > 0, precio_unitario_cajon, IF(precio_unitario_bolsa > 0, precio_unitario_bolsa, 0) ) ) ) -> 0 | E6: =A6*D6 -> 0 | F6: =E6*1.105 -> 0 | I6: =IFERROR( IF(OR(B6="CAJON", B6="BOLSA"), SUMIFS(PRECIOS!$C:$C, PRECIOS!$A:$A, C6, PRECIOS!$B:$B, B6), LET( stock_suelto_inicial, SUMIFS(COMPRAS!$E:$E, COMPRAS!$C:$C, C6, COMPRAS!$J:$J, "UNIDAD") + SUMIFS(COMPRAS!$E:$E, COMPRAS!$C:$C, C6, COMPRAS!$J:$J, "KG"), acumulado_anterior, SUMIFS($M5:M$9, $C5:C$9, C6), unidades_esta_venta, A6, costo_unidad_base, SUMIFS(PRECIOS!$I:$I, PRECIOS!$A:$A, C6, PRECIOS!$B:$B, "UNIDAD") + SUMIFS(PRECIOS!$I:$I, PRECIOS!$A:$A, C6, PRECIOS!$B:$B, "KG"), costo_cajon, SUMIFS(PRECIOS!$I:$I, PRECIOS!$A:$A, C6, PRECIOS!$B:$B, "CAJON"), costo_bolsa, SUMIFS(PRECIOS!$I:$I, PRECIOS!$A:$A, C6, PRECIOS!$B:$B, "BOLSA"), costo_bulto_ref, IF(costo_cajon > 0, costo_cajon, costo_bolsa), unidades_con_costo_suelto, MAX(0, MIN(unidades_esta_venta, stock_suelto_inicial - acumulado_anterior)), unidades_con_costo_bulto, unidades_esta_venta - unidades_con_costo_suelto, IF(unidades_esta_venta = 0, 0, ((unidades_con_costo_suelto * costo_unidad_base) + (unidades_con_costo_bulto * costo_bulto_ref)) / unidades_esta_venta ) ) ), 0) -> 0 | J6: =I6*A6 -> 0 | K6: =F6-J6 -> 0 | M6: =IF(C6="", 0, SUMIFS($M$5:M5, $C$5:C5, C6) + IF(OR(B6="UNIDAD", B6="KG"), A6, 0) ) -> 0
A7: 2 | B7: UNIDAD | C7: APIO | D7: =LET( precio_exacto, SUMIFS(PRECIOS!$E:$E, PRECIOS!$A:$A, C7, PRECIOS!$B:$B, B7), precio_unitario_cajon, SUMIFS(PRECIOS!$J:$J, PRECIOS!$A:$A, C7, PRECIOS!$B:$B, "CAJON"), precio_unitario_bolsa, SUMIFS(PRECIOS!$J:$J, PRECIOS!$A:$A, C7, PRECIOS!$B:$B, "BOLSA"), IF(precio_exacto > 0, precio_exacto, IF(precio_unitario_cajon > 0, precio_unitario_cajon, IF(precio_unitario_bolsa > 0, precio_unitario_bolsa, 0) ) ) ) -> 0 | E7: =A7*D7 -> 0 | F7: =E7*1.105 -> 0 | I7: =IFERROR( IF(OR(B7="CAJON", B7="BOLSA"), SUMIFS(PRECIOS!$C:$C, PRECIOS!$A:$A, C7, PRECIOS!$B:$B, B7), LET( stock_suelto_inicial, SUMIFS(COMPRAS!$E:$E, COMPRAS!$C:$C, C7, COMPRAS!$J:$J, "UNIDAD") + SUMIFS(COMPRAS!$E:$E, COMPRAS!$C:$C, C7, COMPRAS!$J:$J, "KG"), acumulado_anterior, SUMIFS($M6:M$9, $C6:C$9, C7), unidades_esta_venta, A7, costo_unidad_base, SUMIFS(PRECIOS!$I:$I, PRECIOS!$A:$A, C7, PRECIOS!$B:$B, "UNIDAD") + SUMIFS(PRECIOS!$I:$I, PRECIOS!$A:$A, C7, PRECIOS!$B:$B, "KG"), costo_cajon, SUMIFS(PRECIOS!$I:$I, PRECIOS!$A:$A, C7, PRECIOS!$B:$B, "CAJON"), costo_bolsa, SUMIFS(PRECIOS!$I:$I, PRECIOS!$A:$A, C7, PRECIOS!$B:$B, "BOLSA"), costo_bulto_ref, IF(costo_cajon > 0, costo_cajon, costo_bolsa), unidades_con_costo_suelto, MAX(0, MIN(unidades_esta_venta, stock_suelto_inicial - acumulado_anterior)), unidades_con_costo_bulto, unidades_esta_venta - unidades_con_costo_suelto, IF(unidades_esta_venta = 0, 0, ((unidades_con_costo_suelto * costo_unidad_base) + (unidades_con_costo_bulto * costo_bulto_ref)) / unidades_esta_venta ) ) ), 0) -> 0 | J7: =I7*A7 -> 0 | K7: =F7-J7 -> 0 | M7: =IF(C7="", 0, SUMIFS($M$5:M6, $C$5:C6, C7) + IF(OR(B7="UNIDAD", B7="KG"), A7, 0) ) -> 2
A8: 1 | B8: CAJON | C8: NARANJA JUGO COMERCIAL | D8: =LET( precio_exacto, SUMIFS(PRECIOS!$E:$E, PRECIOS!$A:$A, C8, PRECIOS!$B:$B, B8), precio_unitario_cajon, SUMIFS(PRECIOS!$J:$J, PRECIOS!$A:$A, C8, PRECIOS!$B:$B, "CAJON"), precio_unitario_bolsa, SUMIFS(PRECIOS!$J:$J, PRECIOS!$A:$A, C8, PRECIOS!$B:$B, "BOLSA"), IF(precio_exacto > 0, precio_exacto, IF(precio_unitario_cajon > 0, precio_unitario_cajon, IF(precio_unitario_bolsa > 0, precio_unitario_bolsa, 0) ) ) ) -> 0 | E8: =A8*D8 -> 0 | F8: =E8*1.105 -> 0 | I8: =IFERROR( IF(OR(B8="CAJON", B8="BOLSA"), SUMIFS(PRECIOS!$C:$C, PRECIOS!$A:$A, C8, PRECIOS!$B:$B, B8), LET( stock_suelto_inicial, SUMIFS(COMPRAS!$E:$E, COMPRAS!$C:$C, C8, COMPRAS!$J:$J, "UNIDAD") + SUMIFS(COMPRAS!$E:$E, COMPRAS!$C:$C, C8, COMPRAS!$J:$J, "KG"), acumulado_anterior, SUMIFS($M7:M$9, $C7:C$9, C8), unidades_esta_venta, A8, costo_unidad_base, SUMIFS(PRECIOS!$I:$I, PRECIOS!$A:$A, C8, PRECIOS!$B:$B, "UNIDAD") + SUMIFS(PRECIOS!$I:$I, PRECIOS!$A:$A, C8, PRECIOS!$B:$B, "KG"), costo_cajon, SUMIFS(PRECIOS!$I:$I, PRECIOS!$A:$A, C8, PRECIOS!$B:$B, "CAJON"), costo_bolsa, SUMIFS(PRECIOS!$I:$I, PRECIOS!$A:$A, C8, PRECIOS!$B:$B, "BOLSA"), costo_bulto_ref, IF(costo_cajon > 0, costo_cajon, costo_bolsa), unidades_con_costo_suelto, MAX(0, MIN(unidades_esta_venta, stock_suelto_inicial - acumulado_anterior)), unidades_con_costo_bulto, unidades_esta_venta - unidades_con_costo_suelto, IF(unidades_esta_venta = 0, 0, ((unidades_con_costo_suelto * costo_unidad_base) + (unidades_con_costo_bulto * costo_bulto_ref)) / unidades_esta_venta ) ) ), 0) -> 0 | J8: =I8*A8 -> 0 | K8: =F8-J8 -> 0 | M8: =IF(C8="", 0, SUMIFS($M$5:M7, $C$5:C7, C8) + IF(OR(B8="UNIDAD", B8="KG"), A8, 0) ) -> 0
M9: =IF(C9="", 0, SUMIFS($M$5:M8, $C$5:C8, C9) + IF(OR(B9="UNIDAD", B9="KG"), A9, 0) ) -> 0
E10: =SUM(E6:E8) -> 0 | F10: =SUM(F6:F8) -> 0 | K10: =SUM(K6:K8) -> 0 | L10: =IFERROR(K10/E10, 0) -> 0 | M10: =IF(C10="", 0, SUMIFS($M$5:M9, $C$5:C9, C10) + IF(OR(B10="UNIDAD", B10="KG"), A10, 0) ) -> 0
M11: =IF(C11="", 0, SUMIFS($M$5:M10, $C$5:C10, C11) + IF(OR(B11="UNIDAD", B11="KG"), A11, 0) ) -> 0
M12: =IF(C12="", 0, SUMIFS($M$5:M11, $C$5:C11, C12) + IF(OR(B12="UNIDAD", B12="KG"), A12, 0) ) -> 0
M13: =IF(C13="", 0, SUMIFS($M$5:M12, $C$5:C12, C13) + IF(OR(B13="UNIDAD", B13="KG"), A13, 0) ) -> 0
M14: =IF(C14="", 0, SUMIFS($M$5:M13, $C$5:C13, C14) + IF(OR(B14="UNIDAD", B14="KG"), A14, 0) ) -> 0
M15: =IF(C15="", 0, SUMIFS($M$5:M14, $C$5:C14, C15) + IF(OR(B15="UNIDAD", B15="KG"), A15, 0) ) -> 0
M16: =IF(C16="", 0, SUMIFS($M$5:M15, $C$5:C15, C16) + IF(OR(B16="UNIDAD", B16="KG"), A16, 0) ) -> 0
M17: =IF(C17="", 0, SUMIFS($M$5:M16, $C$5:C16, C17) + IF(OR(B17="UNIDAD", B17="KG"), A17, 0) ) -> 0
M18: =IF(C18="", 0, SUMIFS($M$5:M17, $C$5:C17, C18) + IF(OR(B18="UNIDAD", B18="KG"), A18, 0) ) -> 0
M19: =IF(C19="", 0, SUMIFS($M$5:M18, $C$5:C18, C19) + IF(OR(B19="UNIDAD", B19="KG"), A19, 0) ) -> 0
M20: =IF(C20="", 0, SUMIFS($M$5:M19, $C$5:C19, C20) + IF(OR(B20="UNIDAD", B20="KG"), A20, 0) ) -> 0
M21: =IF(C21="", 0, SUMIFS($M$5:M20, $C$5:C20, C21) + IF(OR(B21="UNIDAD", B21="KG"), A21, 0) ) -> 0
M22: =IF(C22="", 0, SUMIFS($M$5:M21, $C$5:C21, C22) + IF(OR(B22="UNIDAD", B22="KG"), A22, 0) ) -> 0
... M248: =IF(C248="", 0, SUMIFS($M$5:M247, $C$5:C247, C248) + IF(OR(B248="UNIDAD", B248="KG"), A248, 0) ) -> 0
