Workbook

Sheet 01-04-2026 
A3: COLEGIO SJCB - VIRREY DEL PINO 3299 | E3: rto: 15 | F3: 46113 | I3: COMPRA
A5: CANTIDAD | B5: UNIDAD | C5: PRODUCTO | D5: PRECIO | E5: TOTAL | F5: TOTAL + IVA | I5: COSTO | J5: TOTAL | K5: DIFERENCIA
A6: 4 | B6: MAPLE | C6: HUEVO N1 | D6: 4500 | E6: =A6*D6 -> 18000 | F6: =E6*1.21 -> 21780 | I6: =54000/12 -> 4500 | J6: =I6*A6 -> 18000 | K6: =F6-J6 -> 3780 | L6: =IFERROR(K6/E6, 0) -> 0.21
A7: 1 | B7: UNIDAD | C7: AJO | D7: 900 | E7: =A7*D7 -> 900 | F7: =E7*1.105 -> 994.5 | I7: 460 | J7: =I7*A7 -> 460 | K7: =F7-J7 -> 534.5 | L7: =IFERROR(K7/E7, 0) -> 0.59388889
A8: 1 | B8: UNIDAD | C8: BROCOLI | D8: 2600 | E8: =A8*D8 -> 2600 | F8: =E8*1.105 -> 2873 | I8: =18000/13 -> 1384.6154 | J8: =I8*A8 -> 1384.6154 | K8: =F8-J8 -> 1488.3846 | L8: =IFERROR(K8/E8, 0) -> 0.57245562
A9: 1 | B9: BOLSA | C9: ANCO | D9: 13000 | E9: =A9*D9 -> 13000 | F9: =E9*1.105 -> 14365 | I9: 9000 | J9: =I9*A9 -> 9000 | K9: =F9-J9 -> 5365 | L9: =IFERROR(K9/E9, 0) -> 0.41269231
A10: 2.5 | B10: KG | C10: CEBOLLA MORADA | D10: 1600 | E10: =A10*D10 -> 4000 | F10: =E10*1.105 -> 4420 | I10: =12000/15 -> 800 | J10: =I10*A10 -> 2000 | K10: =F10-J10 -> 2420 | L10: =IFERROR(K10/E10, 0) -> 0.605
A11: 0.8 | B11: KG | C11: CHAUCHA PLANA | D11: 4000 | E11: =A11*D11 -> 3200 | F11: =E11*1.105 -> 3536 | I11: =13000/8 -> 1625 | J11: =I11*A11 -> 1300 | K11: =F11-J11 -> 2236 | L11: =IFERROR(K11/E11, 0) -> 0.69875
A12: 25 | B12: UNIDAD | C12: CHOCLO | D12: 800 | E12: =A12*D12 -> 20000 | F12: =E12*1.105 -> 22100 | I12: =30000/94 -> 319.14894 | J12: =I12*A12 -> 7978.7234 | K12: =F12-J12 -> 14121.277 | L12: =IFERROR(K12/E12, 0) -> 0.70606383
A13: 2 | B13: ATADO | C13: ESPINACA | D13: 1700 | E13: =A13*D13 -> 3400 | F13: =E13*1.105 -> 3757 | I13: =12000/10 -> 1200 | J13: =I13*A13 -> 2400 | K13: =F13-J13 -> 1357 | L13: =IFERROR(K13/E13, 0) -> 0.39911765
A14: 0.5 | B14: CAJON | C14: MANZANA ROJA | D14: 58000 | E14: =A14*D14 -> 29000 | F14: =E14*1.105 -> 32045 | I14: 53000 | J14: =I14*A14 -> 26500 | K14: =F14-J14 -> 5545 | L14: =IFERROR(K14/E14, 0) -> 0.1912069
A15: 0.5 | B15: CAJON | C15: MANZANA VERDE | D15: 70000 | E15: =A15*D15 -> 35000 | F15: =E15*1.105 -> 38675 | I15: 65000 | J15: =I15*A15 -> 32500 | K15: =F15-J15 -> 6175 | L15: =IFERROR(K15/E15, 0) -> 0.17642857
A16: 1 | B16: CAJON | C16: NARANJA | D16: 25000 | E16: =A16*D16 -> 25000 | F16: =E16*1.105 -> 27625 | I16: 22000 | J16: =I16*A16 -> 22000 | K16: =F16-J16 -> 5625 | L16: =IFERROR(K16/E16, 0) -> 0.225
A17: 1 | B17: BOLSA | C17: PAPA BLANCA | D17: 23000 | E17: =A17*D17 -> 23000 | F17: =E17*1.105 -> 25415 | I17: 19000 | J17: =I17*A17 -> 19000 | K17: =F17-J17 -> 6415 | L17: =IFERROR(K17/E17, 0) -> 0.27891304
A18: 1 | B18: ATADO | C18: CIBOULETTE | D18: 3000 | E18: =A18*D18 -> 3000 | F18: =E18*1.105 -> 3315 | I18: 2000 | J18: =I18*A18 -> 2000 | K18: =F18-J18 -> 1315 | L18: =IFERROR(K18/E18, 0) -> 0.43833333
A19: 0.1 | B19: KG | C19: PEREJIL | D19: 3500 | E19: =A19*D19 -> 350 | F19: =E19*1.105 -> 386.75 | I19: 1000 | J19: =I19*A19 -> 100 | K19: =F19-J19 -> 286.75 | L19: =IFERROR(K19/E19, 0) -> 0.81928571
A20: 0.75 | B20: KG | C20: PEPINO | D20: 1500 | E20: =A20*D20 -> 1125 | F20: =E20*1.105 -> 1243.125 | I20: 1500 | J20: =I20*A20 -> 1125 | K20: =F20-J20 -> 118.125 | L20: =IFERROR(K20/E20, 0) -> 0.105
A21: 1.3 | B21: KG | C21: MORRON ROJO | D21: 3200 | E21: =A21*D21 -> 4160 | F21: =E21*1.105 -> 4596.8 | I21: 1000 | J21: =I21*A21 -> 1300 | K21: =F21-J21 -> 3296.8 | L21: =IFERROR(K21/E21, 0) -> 0.7925
A22: 0.5 | B22: KG | C22: MORRON VERDE | D22: 2400 | E22: =A22*D22 -> 1200 | F22: =E22*1.105 -> 1326 | I22: 1000 | J22: =I22*A22 -> 500 | K22: =F22-J22 -> 826 | L22: =IFERROR(K22/E22, 0) -> 0.68833333
A23: 0.5 | B23: KG | C23: MORRON AMARILLO | D23: 2800 | E23: =A23*D23 -> 1400 | F23: =E23*1.105 -> 1547 | I23: =12000/7 -> 1714.2857 | J23: =I23*A23 -> 857.14286 | K23: =F23-J23 -> 689.85714 | L23: =IFERROR(K23/E23, 0) -> 0.4927551
A24: 1.2 | B24: KG | C24: PUERRO | D24: 5000 | E24: =A24*D24 -> 6000 | F24: =E24*1.105 -> 6630 | I24: 2000 | J24: =I24*A24 -> 2400 | K24: =F24-J24 -> 4230 | L24: =IFERROR(K24/E24, 0) -> 0.705
A25: 0.6 | B25: KG | C25: REMOLACHA | D25: 2500 | E25: =A25*D25 -> 1500 | F25: =E25*1.105 -> 1657.5 | I25: =14000/11 -> 1272.7273 | J25: =I25*A25 -> 763.63636 | K25: =F25-J25 -> 893.86364 | L25: =IFERROR(K25/E25, 0) -> 0.59590909
A26: 2 | B26: KG | C26: REPOLLO BLANCO | D26: 1800 | E26: =A26*D26 -> 3600 | F26: =E26*1.105 -> 3978 | I26: 1000 | J26: =I26*A26 -> 2000 | K26: =F26-J26 -> 1978 | L26: =IFERROR(K26/E26, 0) -> 0.54944444
A27: 1.2 | B27: KG | C27: REPOLLO COLORADO | D27: 1800 | E27: =A27*D27 -> 2160 | F27: =E27*1.105 -> 2386.8 | I27: 1000 | J27: =I27*A27 -> 1200 | K27: =F27-J27 -> 1186.8 | L27: =IFERROR(K27/E27, 0) -> 0.54944444
A28: 9 | B28: KG | C28: TOMATE PERITA | D28: 2400 | E28: =A28*D28 -> 21600 | F28: =E28*1.105 -> 23868 | I28: =15000/15 -> 1000 | J28: =I28*A28 -> 9000 | K28: =F28-J28 -> 14868 | L28: =IFERROR(K28/E28, 0) -> 0.68833333
A29: 6 | B29: KG | C29: ZANAHORIA | D29: 1300 | E29: =A29*D29 -> 7800 | F29: =E29*1.105 -> 8619 | I29: 1000 | J29: =I29*A29 -> 6000 | K29: =F29-J29 -> 2619 | L29: =IFERROR(K29/E29, 0) -> 0.33576923
A30: 2 | B30: UNIDAD | C30: COLIFLOR | D30: 2800 | E30: =A30*D30 -> 5600 | F30: =E30*1.105 -> 6188 | I30: =18000/10 -> 1800 | J30: =I30*A30 -> 3600 | K30: =F30-J30 -> 2588 | L30: =IFERROR(K30/E30, 0) -> 0.46214286
A31: 0.5 | B31: ATADO | C31: CEBOLLA DE VERDEO | D31: 4500 | E31: =A31*D31 -> 2250 | F31: =E31*1.105 -> 2486.25 | I31: 1200 | J31: =I31*A31 -> 600 | K31: =F31-J31 -> 1886.25 | L31: =IFERROR(K31/E31, 0) -> 0.83833333
A32: 0.5 | B32: KG | C32: LECHUGA CRIOLLA | D32: 3200 | E32: =A32*D32 -> 1600 | F32: =E32*1.105 -> 1768 | I32: 2000 | J32: =I32*A32 -> 1000 | K32: =F32-J32 -> 768 | L32: =IFERROR(K32/E32, 0) -> 0.48
E34: =SUM(E6:E32) -> 240445 | F34: =SUM(F6:F32) -> 267581.72 | K34: =SUM(K6:K32) -> 92612.607 | L34: =K34/F34 -> 0.34610961
A37: COLEGIO WASHINGTON - LACROZE 1973 | E37: rto: 14 | F37: 46113 | I37: COMPRA
A39: CANTIDAD | B39: UNIDAD | C39: PRODUCTO | D39: PRECIO | E39: TOTAL | F39: TOTAL + IVA | I39: COSTO | J39: TOTAL | K39: DIFERENCIA
A40: 1.5 | B40: KG | C40: REMOLACHA | D40: 2500 | E40: =A40*D40 -> 3750 | F40: =E40*1.105 -> 4143.75 | I40: =14000/11 -> 1272.7273 | J40: =I40*A40 -> 1909.0909 | K40: =F40-J40 -> 2234.6591 | L40: =IFERROR(K40/E40, 0) -> 0.59590909
A41: 1 | B41: BOLSA | C41: ZANAHORIA | D41: 12000 | E41: =A41*D41 -> 12000 | F41: =E41*1.105 -> 13260 | I41: 7000 | J41: =I41*A41 -> 7000 | K41: =F41-J41 -> 6260 | L41: =IFERROR(K41/E41, 0) -> 0.52166667
A42: 1 | B42: KG | C42: MORRON ROJO | D42: 3200 | E42: =A42*D42 -> 3200 | F42: =E42*1.105 -> 3536 | I42: 1000 | J42: =I42*A42 -> 1000 | K42: =F42-J42 -> 2536 | L42: =IFERROR(K42/E42, 0) -> 0.7925
A43: 3 | B43: KG | C43: CEBOLLA MORADA | D43: 1600 | E43: =A43*D43 -> 4800 | F43: =E43*1.105 -> 5304 | I43: =12000/15 -> 800 | J43: =I43*A43 -> 2400 | K43: =F43-J43 -> 2904 | L43: =IFERROR(K43/E43, 0) -> 0.605
A44: 1.5 | B44: KG | C44: PUERRO | D44: 5000 | E44: =A44*D44 -> 7500 | F44: =E44*1.105 -> 8287.5 | I44: 2000 | J44: =I44*A44 -> 3000 | K44: =F44-J44 -> 5287.5 | L44: =IFERROR(K44/E44, 0) -> 0.705
A45: 0.5 | B45: ATADO | C45: CEBOLLA DE VERDEO | D45: 4500 | E45: =A45*D45 -> 2250 | F45: =E45*1.105 -> 2486.25 | I45: 1200 | J45: =I45*A45 -> 600 | K45: =F45-J45 -> 1886.25 | L45: =IFERROR(K45/E45, 0) -> 0.83833333
A46: 0.5 | B46: ATADO | C46: PEREJIL | D46: 3500 | E46: =A46*D46 -> 1750 | F46: =E46*1.105 -> 1933.75 | I46: 1000 | J46: =I46*A46 -> 500 | K46: =F46-J46 -> 1433.75 | L46: =IFERROR(K46/E46, 0) -> 0.81928571
A47: 5 | B47: KG | C47: TOMATE PERITA | D47: 2400 | E47: =A47*D47 -> 12000 | F47: =E47*1.105 -> 13260 | I47: =15000/15 -> 1000 | J47: =I47*A47 -> 5000 | K47: =F47-J47 -> 8260 | L47: =IFERROR(K47/E47, 0) -> 0.68833333
A48: 0.5 | B48: KG | C48: PEPINO | D48: 1500 | E48: =A48*D48 -> 750 | F48: =E48*1.105 -> 828.75 | I48: 1500 | J48: =I48*A48 -> 750 | K48: =F48-J48 -> 78.75 | L48: =IFERROR(K48/E48, 0) -> 0.105
A49: 3.8 | B49: KG | C49: REPOLLO BLANCO | D49: 1800 | E49: =A49*D49 -> 6840 | F49: =E49*1.105 -> 7558.2 | I49: 1000 | J49: =I49*A49 -> 3800 | K49: =F49-J49 -> 3758.2 | L49: =IFERROR(K49/E49, 0) -> 0.54944444
A50: 1.65 | B50: KG | C50: REPOLLO COLORADO | D50: 1800 | E50: =A50*D50 -> 2970 | F50: =E50*1.105 -> 3281.85 | I50: 1000 | J50: =I50*A50 -> 1650 | K50: =F50-J50 -> 1631.85 | L50: =IFERROR(K50/E50, 0) -> 0.54944444
A51: 0.5 | B51: CAJON | C51: HUEVO N1 | D51: 54000 | E51: =A51*D51 -> 27000 | F51: =E51*1.21 -> 32670 | I51: 54000 | J51: =I51*A51 -> 27000 | K51: =F51-J51 -> 5670 | L51: =IFERROR(K51/E51, 0) -> 0.21
A52: 2.5 | B52: KG | C52: LECHUGA CRIOLLA | D52: 3200 | E52: =A52*D52 -> 8000 | F52: =E52*1.105 -> 8840 | I52: 2000 | J52: =I52*A52 -> 5000 | K52: =F52-J52 -> 3840 | L52: =IFERROR(K52/E52, 0) -> 0.48
A53: 15 | B53: ATADO | C53: RUCULA | D53: 600 | E53: =A53*D53 -> 9000 | F53: =E53*1.105 -> 9945 | I53: =7000/24 -> 291.66667 | J53: =I53*A53 -> 4375 | K53: =F53-J53 -> 5570 | L53: =IFERROR(K53/E53, 0) -> 0.61888889
A54: 4 | B54: ATADO | C54: ESPINACA | D54: 1700 | E54: =A54*D54 -> 6800 | F54: =E54*1.105 -> 7514 | I54: =12000/10 -> 1200 | J54: =I54*A54 -> 4800 | K54: =F54-J54 -> 2714 | L54: =IFERROR(K54/E54, 0) -> 0.39911765
A55: 1 | B55: UNIDAD | C55: BROCOLI | D55: 2600 | E55: =A55*D55 -> 2600 | F55: =E55*1.105 -> 2873 | I55: =18000/13 -> 1384.6154 | J55: =I55*A55 -> 1384.6154 | K55: =F55-J55 -> 1488.3846 | L55: =IFERROR(K55/E55, 0) -> 0.57245562
A56: 1.5 | B56: CAJON | C56: NARANJA | D56: 25000 | E56: =A56*D56 -> 37500 | F56: =E56*1.105 -> 41437.5 | I56: 22000 | J56: =I56*A56 -> 33000 | K56: =F56-J56 -> 8437.5 | L56: =IFERROR(K56/E56, 0) -> 0.225
A57: 4 | B57: KG | C57: MANZANA VERDE | D57: 4200 | E57: =A57*D57 -> 16800 | F57: =E57*1.105 -> 18564 | I57: =65000/17 -> 3823.5294 | J57: =I57*A57 -> 15294.118 | K57: =F57-J57 -> 3269.8824 | L57: =IFERROR(K57/E57, 0) -> 0.19463585
A58: 5 | B58: KG | C58: MANZANA ROJA | D58: 3400 | E58: =A58*D58 -> 17000 | F58: =E58*1.105 -> 18785 | I58: =53000/18 -> 2944.4444 | J58: =I58*A58 -> 14722.222 | K58: =F58-J58 -> 4062.7778 | L58: =IFERROR(K58/E58, 0) -> 0.23898693
E60: =SUM(E40:E58) -> 182510 | F60: =SUM(F40:F58) -> 204508.55 | K60: =SUM(K40:K58) -> 71323.504 | L60: =K60/F60 -> 0.34875561
A64: COLEGIO ST. MATTHEWS - MOLDES 1469, BELGRANO | E64: rto: 15 | F64: 46113 | I64: COMPRA
A66: CANTIDAD | B66: UNIDAD | C66: PRODUCTO | D66: PRECIO | E66: TOTAL | F66: TOTAL + IVA | I66: COSTO | J66: TOTAL | K66: DIFERENCIA
A67: 1 | B67: BOLSA | C67: PAPA BLANCA | D67: 23000 | E67: =A67*D67 -> 23000 | F67: =E67*1.105 -> 25415 | I67: 19000 | J67: =I67*A67 -> 19000 | K67: =F67-J67 -> 6415 | L67: =IFERROR(K67/E67, 0) -> 0.27891304
A68: 1 | B68: BOLSA | C68: CALABAZA | D68: 13000 | E68: =A68*D68 -> 13000 | F68: =E68*1.105 -> 14365 | I68: 9000 | J68: =I68*A68 -> 9000 | K68: =F68-J68 -> 5365 | L68: =IFERROR(K68/E68, 0) -> 0.41269231
A69: 7 | B69: KG | C69: TOMATE PERITA | D69: 2400 | E69: =A69*D69 -> 16800 | F69: =E69*1.105 -> 18564 | I69: =15000/15 -> 1000 | J69: =I69*A69 -> 7000 | K69: =F69-J69 -> 11564 | L69: =IFERROR(K69/E69, 0) -> 0.68833333
A70: 5 | B70: KG | C70: ZANAHORIA | D70: 1300 | E70: =A70*D70 -> 6500 | F70: =E70*1.105 -> 7182.5 | I70: 1000 | J70: =I70*A70 -> 5000 | K70: =F70-J70 -> 2182.5 | L70: =IFERROR(K70/E70, 0) -> 0.33576923
A71: 5 | B71: UNIDAD | C71: COLIFLOR | D71: 2800 | E71: =A71*D71 -> 14000 | F71: =E71*1.105 -> 15470 | I71: =18000/10 -> 1800 | J71: =I71*A71 -> 9000 | K71: =F71-J71 -> 6470 | L71: =IFERROR(K71/E71, 0) -> 0.46214286
A72: 2 | B72: KG | C72: REMOLACHA | D72: 2500 | E72: =A72*D72 -> 5000 | F72: =E72*1.105 -> 5525 | I72: =14000/11 -> 1272.7273 | J72: =I72*A72 -> 2545.4545 | K72: =F72-J72 -> 2979.5455 | L72: =IFERROR(K72/E72, 0) -> 0.59590909
A73: 2 | B73: KG | C73: PUERRO | D73: 5000 | E73: =A73*D73 -> 10000 | F73: =E73*1.105 -> 11050 | I73: 2000 | J73: =I73*A73 -> 4000 | K73: =F73-J73 -> 7050 | L73: =IFERROR(K73/E73, 0) -> 0.705
A74: 24 | B74: UNIDAD | C74: CHOCLO | D74: 800 | E74: =A74*D74 -> 19200 | F74: =E74*1.105 -> 21216 | I74: =30000/94 -> 319.14894 | J74: =I74*A74 -> 7659.5745 | K74: =F74-J74 -> 13556.426 | L74: =IFERROR(K74/E74, 0) -> 0.70606383
A75: 1 | B75: KG | C75: REPOLLO BLANCO | D75: 1800 | E75: =A75*D75 -> 1800 | F75: =E75*1.105 -> 1989 | I75: 1000 | J75: =I75*A75 -> 1000 | K75: =F75-J75 -> 989 | L75: =IFERROR(K75/E75, 0) -> 0.54944444
A76: 1 | B76: KG | C76: CEBOLLA MORADA | D76: 1600 | E76: =A76*D76 -> 1600 | F76: =E76*1.105 -> 1768 | I76: =12000/15 -> 800 | J76: =I76*A76 -> 800 | K76: =F76-J76 -> 968 | L76: =IFERROR(K76/E76, 0) -> 0.605
A77: 3 | B77: KG | C77: MANZANA ROJA | D77: 3400 | E77: =A77*D77 -> 10200 | F77: =E77*1.105 -> 11271 | I77: =53000/18 -> 2944.4444 | J77: =I77*A77 -> 8833.3333 | K77: =F77-J77 -> 2437.6667 | L77: =IFERROR(K77/E77, 0) -> 0.23898693
A78: 3 | B78: KG | C78: MANZANA VERDE | D78: 4200 | E78: =A78*D78 -> 12600 | F78: =E78*1.105 -> 13923 | I78: =65000/17 -> 3823.5294 | J78: =I78*A78 -> 11470.588 | K78: =F78-J78 -> 2452.4118 | L78: =IFERROR(K78/E78, 0) -> 0.19463585
A79: 2 | B79: KG | C79: PERA | D79: 3000 | E79: =A79*D79 -> 6000 | F79: =E79*1.105 -> 6630 | I79: =30000/18 -> 1666.6667 | J79: =I79*A79 -> 3333.3333 | K79: =F79-J79 -> 3296.6667 | L79: =IFERROR(K79/E79, 0) -> 0.54944444
E81: =SUM(E67:E79) -> 139700 | F81: =SUM(F67:F79) -> 154368.5 | K81: =SUM(K67:K79) -> 65726.216 | L81: =K81/F81 -> 0.42577479
A84: COLEGIO SAN JAVIER - JOSE A CABRERA 5901 | E84: rto: 15 | F84: 46113 | I84: COMPRA
A86: CANTIDAD | B86: UNIDAD | C86: PRODUCTO | D86: PRECIO | E86: TOTAL | F86: TOTAL + IVA | I86: COSTO | J86: TOTAL | K86: DIFERENCIA
A87: 2 | B87: UNIDAD | C87: AJO | D87: 900 | E87: =A87*D87 -> 1800 | F87: =E87*1.105 -> 1989 | I87: 460 | J87: =I87*A87 -> 920 | K87: =F87-J87 -> 1069 | L87: =IFERROR(K87/E87, 0) -> 0.59388889
A88: 1 | B88: ATADO | C88: ALBAHACA | D88: 1500 | E88: =A88*D88 -> 1500 | F88: =E88*1.105 -> 1657.5 | I88: 1200 | J88: =I88*A88 -> 1200 | K88: =F88-J88 -> 457.5 | L88: =IFERROR(K88/E88, 0) -> 0.305
A89: 1 | B89: BOLSA | C89: PAPA BLANCA | D89: 23000 | E89: =A89*D89 -> 23000 | F89: =E89*1.105 -> 25415 | I89: 19000 | J89: =I89*A89 -> 19000 | K89: =F89-J89 -> 6415 | L89: =IFERROR(K89/E89, 0) -> 0.27891304
A90: 4 | B90: KG | C90: CALABAZA | D90: 1000 | E90: =A90*D90 -> 4000 | F90: =E90*1.105 -> 4420 | I90: =9000/18 -> 500 | J90: =I90*A90 -> 2000 | K90: =F90-J90 -> 2420 | L90: =IFERROR(K90/E90, 0) -> 0.605
A91: 15 | B91: UNIDAD | C91: CHOCLO | D91: 800 | E91: =A91*D91 -> 12000 | F91: =E91*1.105 -> 13260 | I91: =30000/94 -> 319.14894 | J91: =I91*A91 -> 4787.234 | K91: =F91-J91 -> 8472.766 | L91: =IFERROR(K91/E91, 0) -> 0.70606383
A92: 1 | B92: KG | C92: REMOLACHA | D92: 2500 | E92: =A92*D92 -> 2500 | F92: =E92*1.105 -> 2762.5 | I92: =14000/11 -> 1272.7273 | J92: =I92*A92 -> 1272.7273 | K92: =F92-J92 -> 1489.7727 | L92: =IFERROR(K92/E92, 0) -> 0.59590909
A93: 6 | B93: KG | C93: ZANAHORIA | D93: 1300 | E93: =A93*D93 -> 7800 | F93: =E93*1.105 -> 8619 | I93: 1000 | J93: =I93*A93 -> 6000 | K93: =F93-J93 -> 2619 | L93: =IFERROR(K93/E93, 0) -> 0.33576923
A94: 2 | B94: KG | C94: PUERRO | D94: 5000 | E94: =A94*D94 -> 10000 | F94: =E94*1.105 -> 11050 | I94: 2000 | J94: =I94*A94 -> 4000 | K94: =F94-J94 -> 7050 | L94: =IFERROR(K94/E94, 0) -> 0.705
A95: 1.25 | B95: KG | C95: REPOLLO COLORADO | D95: 1800 | E95: =A95*D95 -> 2250 | F95: =E95*1.105 -> 2486.25 | I95: 1000 | J95: =I95*A95 -> 1250 | K95: =F95-J95 -> 1236.25 | L95: =IFERROR(K95/E95, 0) -> 0.54944444
A96: 1.2 | B96: KG | C96: CHAUCHA PLANA | D96: 4000 | E96: =A96*D96 -> 4800 | F96: =E96*1.105 -> 5304 | I96: =13000/8 -> 1625 | J96: =I96*A96 -> 1950 | K96: =F96-J96 -> 3354 | L96: =IFERROR(K96/E96, 0) -> 0.69875
A97: 3 | B97: UNIDAD | C97: COLIFLOR | D97: 2800 | E97: =A97*D97 -> 8400 | F97: =E97*1.105 -> 9282 | I97: =18000/10 -> 1800 | J97: =I97*A97 -> 5400 | K97: =F97-J97 -> 3882 | L97: =IFERROR(K97/E97, 0) -> 0.46214286
A98: 5 | B98: KG | C98: MANZANA VERDE | D98: 4200 | E98: =A98*D98 -> 21000 | F98: =E98*1.105 -> 23205 | I98: =65000/17 -> 3823.5294 | J98: =I98*A98 -> 19117.647 | K98: =F98-J98 -> 4087.3529 | L98: =IFERROR(K98/E98, 0) -> 0.19463585
A99: 3 | B99: KG | C99: MANZANA ROJA | D99: 3400 | E99: =A99*D99 -> 10200 | F99: =E99*1.105 -> 11271 | I99: =53000/18 -> 2944.4444 | J99: =I99*A99 -> 8833.3333 | K99: =F99-J99 -> 2437.6667 | L99: =IFERROR(K99/E99, 0) -> 0.23898693
A100: 1 | B100: ATADO | C100: KALE | D100: 2000 | E100: =A100*D100 -> 2000 | F100: =E100*1.105 -> 2210 | I100: 1000 | J100: =I100*A100 -> 1000 | K100: =F100-J100 -> 1210 | L100: =IFERROR(K100/E100, 0) -> 0.605
E102: =SUM(E87:E100) -> 111250 | F102: =SUM(F87:F100) -> 122931.25 | K102: =SUM(K87:K100) -> 46200.308 | L102: =K102/F102 -> 0.37582233
A105: COLEGIO SAN MARCOS | SAN ISIDRO | E105: rto: 11 | F105: 46113 | I105: COMPRA
A107: CANTIDAD | B107: UNIDAD | C107: PRODUCTO | D107: PRECIO | E107: TOTAL | F107: TOTAL + IVA | I107: COSTO | J107: TOTAL | K107: DIFERENCIA
A108: 0.5 | B108: CAJON | C108: TOMATE PERITA | D108: 30000 | E108: =A108*D108 -> 15000 | F108: =E108*1.105 -> 16575 | I108: 15000 | J108: =I108*A108 -> 7500 | K108: =F108-J108 -> 9075 | L108: =IFERROR(K108/E108, 0) -> 0.605
A109: 15 | B109: ATADO | C109: RUCULA | D109: 600 | E109: =A109*D109 -> 9000 | F109: =E109*1.105 -> 9945 | I109: =7000/24 -> 291.66667 | J109: =I109*A109 -> 4375 | K109: =F109-J109 -> 5570 | L109: =IFERROR(K109/E109, 0) -> 0.61888889
A110: 2 | B110: BOLSA | C110: PAPA BLANCA | D110: 23000 | E110: =A110*D110 -> 46000 | F110: =E110*1.105 -> 50830 | I110: 19000 | J110: =I110*A110 -> 38000 | K110: =F110-J110 -> 12830 | L110: =IFERROR(K110/E110, 0) -> 0.27891304
A111: 4 | B111: KG | C111: REPOLLO BLANCO | D111: 1800 | E111: =A111*D111 -> 7200 | F111: =E111*1.105 -> 7956 | I111: 1000 | J111: =I111*A111 -> 4000 | K111: =F111-J111 -> 3956 | L111: =IFERROR(K111/E111, 0) -> 0.54944444
A112: 1 | B112: KG | C112: REPOLLO COLORADO | D112: 1800 | E112: =A112*D112 -> 1800 | F112: =E112*1.105 -> 1989 | I112: 1000 | J112: =I112*A112 -> 1000 | K112: =F112-J112 -> 989 | L112: =IFERROR(K112/E112, 0) -> 0.54944444
A113: 1.55 | B113: KG | C113: MORRON ROJO | D113: 3200 | E113: =A113*D113 -> 4960 | F113: =E113*1.105 -> 5480.8 | I113: 1000 | J113: =I113*A113 -> 1550 | K113: =F113-J113 -> 3930.8 | L113: =IFERROR(K113/E113, 0) -> 0.7925
A114: 1 | B114: KG | C114: CHAMPIGNON | D114: 21000 | E114: =A114*D114 -> 21000 | F114: =E114*1.105 -> 23205 | I114: 17000 | J114: =I114*A114 -> 17000 | K114: =F114-J114 -> 6205 | L114: =IFERROR(K114/E114, 0) -> 0.29547619
A115: 2 | B115: ATADO | C115: PUERRO | D115: 5000 | E115: =A115*D115 -> 10000 | F115: =E115*1.105 -> 11050 | I115: 2000 | J115: =I115*A115 -> 4000 | K115: =F115-J115 -> 7050 | L115: =IFERROR(K115/E115, 0) -> 0.705
A116: 1 | B116: ATADO | C116: CEBOLLA DE VERDEO | D116: 4500 | E116: =A116*D116 -> 4500 | F116: =E116*1.105 -> 4972.5 | I116: 1200 | J116: =I116*A116 -> 1200 | K116: =F116-J116 -> 3772.5 | L116: =IFERROR(K116/E116, 0) -> 0.83833333
A117: 1 | B117: ATADO | C117: PEREJIL | D117: 3500 | E117: =A117*D117 -> 3500 | F117: =E117*1.105 -> 3867.5 | I117: 1000 | J117: =I117*A117 -> 1000 | K117: =F117-J117 -> 2867.5 | L117: =IFERROR(K117/E117, 0) -> 0.81928571
A118: 2 | B118: UNIDAD | C118: AJO | D118: 900 | E118: =A118*D118 -> 1800 | F118: =E118*1.105 -> 1989 | I118: 460 | J118: =I118*A118 -> 920 | K118: =F118-J118 -> 1069 | L118: =IFERROR(K118/E118, 0) -> 0.59388889
A119: 1 | B119: KG | C119: CEBOLLA | D119: 800 | E119: =A119*D119 -> 800 | F119: =E119*1.105 -> 884 | I119: =10000/16 -> 625 | J119: =I119*A119 -> 625 | K119: =F119-J119 -> 259 | L119: =IFERROR(K119/E119, 0) -> 0.32375
A120: 1 | B120: KG | C120: CEBOLLA MORADA | D120: 1600 | E120: =A120*D120 -> 1600 | F120: =E120*1.105 -> 1768 | I120: =12000/15 -> 800 | J120: =I120*A120 -> 800 | K120: =F120-J120 -> 968 | L120: =IFERROR(K120/E120, 0) -> 0.605
...

Sheet 02-04-2026 
A3: LA PIADINA | D3: rto: 32 | E3: 46114 | F3: **
A5: CANTIDAD | B5: UNIDAD | C5: PRODUCTO | D5: PRECIO | E5: TOTAL | I5: PRECIO | J5: TOTAL | K5: DIFERENCIA
A6: 1 | B6: CAJON | C6: RUCULA | D6: 13000 | E6: =A6*D6 -> 13000 | I6: 8000 | J6: =I6*A6 -> 8000 | K6: =E6-J6 -> 5000 | L6: =K6/E6 -> 0.38461538
A7: 3 | B7: ATADO | C7: ALBAHACA | D7: 1500 | E7: =A7*D7 -> 4500 | I7: 1500 | J7: =I7*A7 -> 4500 | K7: =E7-J7 -> 0 | L7: =K7/E7 -> 0
A8: 5 | B8: KG | C8: TOMATE | D8: 2200 | E8: =A8*D8 -> 11000 | I8: =14000/15 -> 933.33333 | J8: =I8*A8 -> 4666.6667 | K8: =E8-J8 -> 6333.3333 | L8: =K8/E8 -> 0.57575758
A9: 0.5 | B9: KG | C9: TOMATE CHERRY | D9: 3000 | E9: =A9*D9 -> 1500 | I9: 1000 | J9: =I9*A9 -> 500 | K9: =E9-J9 -> 1000 | L9: =K9/E9 -> 0.66666667
A10: 1 | B10: KG | C10: LECHUGA | D10: 3500 | E10: =A10*D10 -> 3500 | H10: S/C | I10: 0 | J10: =I10*A10 -> 0 | K10: =E10-J10 -> 3500 | L10: =K10/E10 -> 1
E12: =SUM(E6:E11) -> 33500 | K12: =SUM(K6:K10) -> 15833.333 | L12: =K12/E12 -> 0.47263682
A16: BRASOV | D16: rto: 27 | E16: 46114 | F16: **
A18: CANTIDAD | B18: UNIDAD | C18: PRODUCTO | D18: PRECIO | E18: TOTAL | I18: PRECIO | J18: TOTAL | K18: DIFERENCIA
A19: 4 | B19: CAJON | C19: LECHUGA FRANCESA | D19: 9000 | E19: =A19*D19 -> 36000 | I19: =18000/4 -> 4500 | J19: =I19*A19 -> 18000 | K19: =E19-J19 -> 18000 | L19: =K19/E19 -> 0.5
A20: 1 | B20: KG | C20: JENGIBRE | D20: 10000 | E20: =A20*D20 -> 10000 | I20: 8000 | J20: =I20*A20 -> 8000 | K20: =E20-J20 -> 2000 | L20: =K20/E20 -> 0.2
A21: 4 | B21: ATADO | C21: MENTA | D21: 3000 | E21: =A21*D21 -> 12000 | I21: 2000 | J21: =I21*A21 -> 8000 | K21: =E21-J21 -> 4000 | L21: =K21/E21 -> 0.33333333
A22: 3 | B22: KG | C22: LIMA | D22: 4000 | E22: =A22*D22 -> 12000 | I22: 3000 | J22: =I22*A22 -> 9000 | K22: =E22-J22 -> 3000 | L22: =K22/E22 -> 0.25
A23: 4 | B23: CAJON | C23: LIMON | D23: 28000 | E23: =A23*D23 -> 112000 | I23: 12000 | J23: =I23*A23 -> 48000 | K23: =E23-J23 -> 64000 | L23: =K23/E23 -> 0.57142857
A24: 3 | B24: CAJON | C24: NARANJA | D24: 26000 | E24: =A24*D24 -> 78000 | I24: 22000 | J24: =I24*A24 -> 66000 | K24: =E24-J24 -> 12000 | L24: =K24/E24 -> 0.15384615
A25: 2 | B25: ATADO | C25: PEREJIL | D25: 3500 | E25: =A25*D25 -> 7000 | I25: 1000 | J25: =I25*A25 -> 2000 | K25: =E25-J25 -> 5000 | L25: =K25/E25 -> 0.71428571
A26: 4 | B26: ATADO | C26: CEBOLLA DE VERDEO | D26: 4500 | E26: =A26*D26 -> 18000 | I26: 1200 | J26: =I26*A26 -> 4800 | K26: =E26-J26 -> 13200 | L26: =K26/E26 -> 0.73333333
A27: 4 | B27: UNIDAD | C27: MANGO | D27: 3000 | E27: =A27*D27 -> 12000 | I27: =20000/9 -> 2222.2222 | J27: =I27*A27 -> 8888.8889 | K27: =E27-J27 -> 3111.1111 | L27: =K27/E27 -> 0.25925926
A28: 2 | B28: ATADO | C28: PUERRO | D28: 4000 | E28: =A28*D28 -> 8000 | I28: 2000 | J28: =I28*A28 -> 4000 | K28: =E28-J28 -> 4000 | L28: =K28/E28 -> 0.5
A29: 1 | B29: CAJON | C29: TOMATE PERITA | D29: 20000 | E29: =A29*D29 -> 20000 | I29: 15000 | J29: =I29*A29 -> 15000 | K29: =E29-J29 -> 5000 | L29: =K29/E29 -> 0.25
A30: 2 | B30: KG | C30: PEPINO | D30: 1500 | E30: =A30*D30 -> 3000 | I30: 1500 | J30: =I30*A30 -> 3000 | K30: =E30-J30 -> 0 | L30: =K30/E30 -> 0
A31: 0.5 | B31: CAJA | C31: PALTA (50u) | D31: 85000 | E31: =A31*D31 -> 42500 | I31: 82000 | J31: =I31*A31 -> 41000 | K31: =E31-J31 -> 1500 | L31: =K31/E31 -> 0.035294118
E33: =SUM(E19:E31) -> 370500 | K33: =SUM(K19:K31) -> 134811.11 | L33: =K33/E33 -> 0.36386265
A36: COMO SIEMPRE LAGUNA | D36: rto: 43 | E36: 46114 | F36: **
A38: CANTIDAD | B38: UNIDAD | C38: PRODUCTO | D38: PRECIO | E38: TOTAL | I38: PRECIO | J38: TOTAL | K38: DIFERENCIA
A39: 1 | B39: ATADO | C39: APIO | D39: 2500 | E39: =A39*D39 -> 2500 | I39: 1000 | J39: =I39*A39 -> 1000 | K39: =E39-J39 -> 1500 | L39: =K39/E39 -> 0.6
A40: 1 | B40: ATADO | C40: PUERRO | D40: 5000 | E40: =A40*D40 -> 5000 | I40: 2000 | J40: =I40*A40 -> 2000 | K40: =E40-J40 -> 3000 | L40: =K40/E40 -> 0.6
A41: 2 | B41: KG | C41: CEBOLLA MORADA | D41: 1600 | E41: =A41*D41 -> 3200 | I41: 1000 | J41: =I41*A41 -> 2000 | K41: =E41-J41 -> 1200 | L41: =K41/E41 -> 0.375
A42: 8 | B42: KG | C42: TOMATE PERITA | D42: 2200 | E42: =A42*D42 -> 17600 | I42: 1000 | J42: =I42*A42 -> 8000 | K42: =E42-J42 -> 9600 | L42: =K42/E42 -> 0.54545455
A43: 1 | B43: ATADO | C43: CIBOULETTE | D43: 3000 | E43: =A43*D43 -> 3000 | I43: 2000 | J43: =I43*A43 -> 2000 | K43: =E43-J43 -> 1000 | L43: =K43/E43 -> 0.33333333
A44: 2 | B44: ATADO | C44: ALBAHACA | D44: 1500 | E44: =A44*D44 -> 3000 | I44: 1500 | J44: =I44*A44 -> 3000 | K44: =E44-J44 -> 0 | L44: =K44/E44 -> 0
A45: 3 | B45: UNIDAD | C45: MANGO | D45: 3000 | E45: =A45*D45 -> 9000 | I45: 2222 | J45: =I45*A45 -> 6666 | K45: =E45-J45 -> 2334 | L45: =K45/E45 -> 0.25933333
A46: 2 | B46: ATADO | C46: MENTA | D46: 3000 | E46: =A46*D46 -> 6000 | I46: 2000 | J46: =I46*A46 -> 4000 | K46: =E46-J46 -> 2000 | L46: =K46/E46 -> 0.33333333
A47: 6 | B47: KG | C47: LIMON | D47: 2400 | E47: =A47*D47 -> 14400 | I47: =12000/14 -> 857.14286 | J47: =I47*A47 -> 5142.8571 | K47: =E47-J47 -> 9257.1429 | L47: =K47/E47 -> 0.64285714
A48: 6 | B48: KG | C48: NARANJA | D48: 1800 | E48: =A48*D48 -> 10800 | I48: =22000/15 -> 1466.6667 | J48: =I48*A48 -> 8800 | K48: =E48-J48 -> 2000 | L48: =K48/E48 -> 0.18518519
A49: 2 | B49: UNIDAD | C49: COLIFLOR | D49: 2800 | E49: =A49*D49 -> 5600 | I49: =18000/10 -> 1800 | J49: =I49*A49 -> 3600 | K49: =E49-J49 -> 2000 | L49: =K49/E49 -> 0.35714286
A50: 1 | B50: CAJON | C50: LECHUGA MORADA | D50: 11000 | E50: =A50*D50 -> 11000 | I50: 6000 | J50: =I50*A50 -> 6000 | K50: =E50-J50 -> 5000 | L50: =K50/E50 -> 0.45454545
A51: 0.5 | B51: CAJON | C51: RUCULA | D51: 12000 | E51: =A51*D51 -> 6000 | I51: 8000 | J51: =I51*A51 -> 4000 | K51: =E51-J51 -> 2000 | L51: =K51/E51 -> 0.33333333
E53: =SUM(E39:E51) -> 97100 | K53: =SUM(K39:K52) -> 40891.143 | L53: =K53/E53 -> 0.42112403
A56: LA MARQUESA | D56: rto: 24 | E56: 46114
A58: CANTIDAD | B58: UNIDAD | C58: PRODUCTO | D58: PRECIO | E58: TOTAL | I58: PRECIO | J58: TOTAL | K58: DIFERENCIA
A59: 0.5 | B59: KG | C59: KIWI | D59: 8500 | E59: =A59*D59 -> 4250 | I59: =45000/7 -> 6428.5714 | J59: =I59*A59 -> 3214.2857 | K59: =E59-J59 -> 1035.7143 | L59: =K59/E59 -> 0.24369748
A60: 1 | B60: KG | C60: BANANA ECUADOR | D60: 3000 | E60: =A60*D60 -> 3000 | I60: =30000/18 -> 1666.6667 | J60: =I60*A60 -> 1666.6667 | K60: =E60-J60 -> 1333.3333 | L60: =K60/E60 -> 0.44444444
A61: 15 | B61: UNIDAD | C61: PALTA | D61: 1400 | E61: =A61*D61 -> 21000 | I61: 1078 | J61: =I61*A61 -> 16170 | K61: =E61-J61 -> 4830 | L61: =K61/E61 -> 0.23
A62: 1 | B62: ATADO | C62: ALBAHACA | D62: 1500 | E62: =A62*D62 -> 1500 | I62: 1500 | J62: =I62*A62 -> 1500 | K62: =E62-J62 -> 0 | L62: =K62/E62 -> 0
A63: 1 | B63: CAJON | C63: NARANJA | D63: 26000 | E63: =A63*D63 -> 26000 | I63: 22000 | J63: =I63*A63 -> 22000 | K63: =E63-J63 -> 4000 | L63: =K63/E63 -> 0.15384615
E65: =SUM(E59:E63) -> 55750 | K65: =SUM(K59:K63) -> 11199.048 | L65: =K65/E65 -> 0.20087978
A69: QUINQUELA | D69: rto: 9 | E69: 46114 | F69: **
A71: CANTIDAD | B71: UNIDAD | C71: PRODUCTO | D71: PRECIO | E71: TOTAL | I71: PRECIO | J71: TOTAL | K71: DIFERENCIA
A72: 1 | B72: CAJON | C72: NARANJA | D72: 26000 | E72: =A72*D72 -> 26000 | I72: 22000 | J72: =I72*A72 -> 22000 | K72: =E72-J72 -> 4000 | L72: =K72/E72 -> 0.15384615
A73: 1 | B73: ATADO | C73: ALBAHACA | D73: 1500 | E73: =A73*D73 -> 1500 | I73: 1500 | J73: =I73*A73 -> 1500 | K73: =E73-J73 -> 0 | L73: =K73/E73 -> 0
A74: 12 | B74: UNIDAD | C74: PALTA | D74: 1400 | E74: =A74*D74 -> 16800 | I74: 1078 | J74: =I74*A74 -> 12936 | K74: =E74-J74 -> 3864 | L74: =K74/E74 -> 0.23
A75: 2 | B75: KG | C75: TOMATE REDONDO | D75: 1800 | E75: =A75*D75 -> 3600 | I75: =14000/15 -> 933.33333 | J75: =I75*A75 -> 1866.6667 | K75: =E75-J75 -> 1733.3333 | L75: =K75/E75 -> 0.48148148
A76: 2 | B76: KG | C76: POMELO | D76: 3200 | E76: =A76*D76 -> 6400 | I76: 800 | J76: =I76*A76 -> 1600 | K76: =E76-J76 -> 4800 | L76: =K76/E76 -> 0.75
E78: =SUM(E72:E76) -> 54300 | K78: =SUM(K72:K76) -> 14397.333 | L78: =K78/E78 -> 0.26514426
A81: RAKUS CAFE - PADUA | D81: rto: 33 | E81: 46114
A83: CANTIDAD | B83: UNIDAD | C83: PRODUCTO | D83: PRECIO | E83: TOTAL | F83: ** | I83: PRECIO | J83: TOTAL | K83: DIFERENCIA
A84: 4 | B84: KG | C84: LECHUGA CRIOLLA | D84: 3500 | E84: =A84*D84 -> 14000 | I84: 2000 | J84: =I84*A84 -> 8000 | K84: =E84-J84 -> 6000 | L84: =K84/E84 -> 0.42857143
A85: 31 | B85: ATADOS | C85: RUCULA | D85: 500 | E85: =A85*D85 -> 15500 | I85: =8000/24 -> 333.33333 | J85: =I85*A85 -> 10333.333 | K85: =E85-J85 -> 5166.6667 | L85: =K85/E85 -> 0.33333333
A86: 1.7 | B86: KG | C86: REPOLLO COLORADO | D86: 1800 | E86: =A86*D86 -> 3060 | I86: 1000 | J86: =I86*A86 -> 1700 | K86: =E86-J86 -> 1360 | L86: =K86/E86 -> 0.44444444
A87: 12 | B87: UNIDAD | C87: AJO | D87: 900 | E87: =A87*D87 -> 10800 | I87: 460 | J87: =I87*A87 -> 5520 | K87: =E87-J87 -> 5280 | L87: =K87/E87 -> 0.48888889
A88: 3 | B88: CAJON | C88: NARANJA DE JUGO | D88: 25000 | E88: =A88*D88 -> 75000 | I88: 22000 | J88: =I88*A88 -> 66000 | K88: =E88-J88 -> 9000 | L88: =K88/E88 -> 0.12
A89: 1 | B89: CAJON | C89: LIMON | D89: 28000 | E89: =A89*D89 -> 28000 | I89: 12000 | J89: =I89*A89 -> 12000 | K89: =E89-J89 -> 16000 | L89: =K89/E89 -> 0.57142857
A90: 1 | B90: ATADO | C90: MENTA | D90: 3000 | E90: =A90*D90 -> 3000 | I90: 2000 | J90: =I90*A90 -> 2000 | K90: =E90-J90 -> 1000 | L90: =K90/E90 -> 0.33333333
A91: 4 | B91: KG | C91: LIMA | D91: 4000 | E91: =A91*D91 -> 16000 | I91: 3000 | J91: =I91*A91 -> 12000 | K91: =E91-J91 -> 4000 | L91: =K91/E91 -> 0.25
E93: =SUM(E84:E91) -> 165360 | K93: =SUM(K84:K91) -> 47806.667 | L93: =K93/E93 -> 0.2891066
A96: COLCAR | E96: rto: 15 | F96: 46114 | G96: ** | I96: COMPRA
A98: CANTIDAD | B98: UNIDAD | C98: PRODUCTO | D98: PRECIO | E98: TOTAL | F98: TOTAL + IVA | I98: COSTO | J98: TOTAL | K98: DIFERENCIA
A99: 1 | B99: CAJON | C99: CHOCLO | D99: 12000 | E99: =A99*D99 -> 12000 | F99: =E99*1.105 -> 13260 | I99: 8000 | J99: =I99*A99 -> 8000 | K99: =F99-J99 -> 5260 | L99: =IFERROR(K99/E99, 0) -> 0.43833333
A100: 5 | B100: BOLSA | C100: PAPA | D100: 14000 | E100: =A100*D100 -> 70000 | F100: =E100*1.105 -> 77350 | I100: 10000 | J100: =I100*A100 -> 50000 | K100: =F100-J100 -> 27350 | L100: =IFERROR(K100/E100, 0) -> 0.39071429
A101: 1 | B101: BOLSA | C101: BATATA | D101: 15000 | E101: =A101*D101 -> 15000 | F101: =E101*1.105 -> 16575 | I101: 12000 | J101: =I101*A101 -> 12000 | K101: =F101-J101 -> 4575 | L101: =IFERROR(K101/E101, 0) -> 0.305
A102: 1 | B102: BOLSA | C102: CALABAZA | D102: 13000 | E102: =A102*D102 -> 13000 | F102: =E102*1.105 -> 14365 | I102: 9000 | J102: =I102*A102 -> 9000 | K102: =F102-J102 -> 5365 | L102: =IFERROR(K102/E102, 0) -> 0.41269231
A103: 4 | B103: CAJON | C103: ACELGA | D103: 11000 | E103: =A103*D103 -> 44000 | F103: =E103*1.105 -> 48620 | I103: 8000 | J103: =I103*A103 -> 32000 | K103: =F103-J103 -> 16620 | L103: =IFERROR(K103/E103, 0) -> 0.37772727
E105: =SUM(E99:E103) -> 154000 | F105: =SUM(F99:F103) -> 170170 | K105: =SUM(K99:K103) -> 59170 | L105: =K105/F105 -> 0.34771111
A109: FABRIC SUSHI | D109: RTO: 17 | E109: 46114
A111: CANTIDAD | B111: UNIDAD | C111: PRODUCTO | D111: PRECIO | E111: TOTAL | I111: PRECIO | J111: TOTAL | K111: DIFERENCIA
A112: 1 | B112: ATADO | C112: PUERRO | D112: 5000 | E112: =A112*D112 -> 5000 | I112: 2000 | J112: =I112*A112 -> 2000 | K112: =E112-J112 -> 3000 | L112: =K112/E112 -> 0.6
A113: 0.65 | B113: KG | C113: TOMATE | D113: 2200 | E113: =A113*D113 -> 1430 | I113: =14000/15 -> 933.33333 | J113: =I113*A113 -> 606.66667 | K113: =E113-J113 -> 823.33333 | L113: =K113/E113 -> 0.57575758
A114: 4 | B114: ATADO | C114: CIBOULETTE | D114: 3000 | E114: =A114*D114 -> 12000 | I114: 2000 | J114: =I114*A114 -> 8000 | K114: =E114-J114 -> 4000 | L114: =K114/E114 -> 0.33333333
A115: 3 | B115: ATADO | C115: CILANTRO | D115: 2000 | E115: =A115*D115 -> 6000 | I115: 500 | J115: =I115*A115 -> 1500 | K115: =E115-J115 -> 4500 | L115: =K115/E115 -> 0.75
A116: 1 | B116: ATADO | C116: CEBOLLA DE VERDEO | D116: 4500 | E116: =A116*D116 -> 4500 | I116: 1200 | J116: =I116*A116 -> 1200 | K116: =E116-J116 -> 3300 | L116: =K116/E116 -> 0.73333333
A117: 2 | B117: BANDEJA | C117: PORTOBELLO | D117: 6000 | E117: =A117*D117 -> 12000 | I117: 4500 | J117: =I117*A117 -> 9000 | K117: =E117-J117 -> 3000 | L117: =K117/E117 -> 0.25
A118: 4 | B118: KG | C118: PEPINO | D118: 1500 | E118: =A118*D118 -> 6000 | I118: 1500 | J118: =I118*A118 -> 6000 | K118: =E118-J118 -> 0 | L118: =K118/E118 -> 0
A119: 0.5 | B119: BOLSA | C119: PAPA CEPILLADA | D119: 18000 | E119: =A119*D119 -> 9000 | I119: 10000 | J119: =I119*A119 -> 5000 | K119: =E119-J119 -> 4000 | L119: =K119/E119 -> 0.44444444
A120: 3 | B120: KG | C120: CEBOLLA MORADA | D120: 1600 | E120: =A120*D120 -> 4800 | I120: 1000 | J120: =I120*A120 -> 3000 | K120: =E120-J120 -> 1800 | L120: =K120/E120 -> 0.375
A121: 2 | B121: KG | C121: MORRON | D121: 2800 | E121: =A121*D121 -> 5600 | I121: 1000 | J121: =I121*A121 -> 2000 | K121: =E121-J121 -> 3600 | L121: =K121/E121 -> 0.64285714
A122: 1 | B122: KG | C122: MORRON VERDE | D122: 2500 | E122: =A122*D122 -> 2500 | I122: 1000 | J122: =I122*A122 -> 1000 | K122: =E122-J122 -> 1500 | L122: =K122/E122 -> 0.6
A123: 2 | B123: KG | C123: ZUCCINI | D123: 1400 | E123: =A123*D123 -> 2800 | I123: 1000 | J123: =I123*A123 -> 2000 | K123: =E123-J123 -> 800 | L123: =K123/E123 -> 0.28571429
A124: 4 | B124: UNIDAD | C124: AJO | D124: 900 | E124: =A124*D124 -> 3600 | I124: 460 | J124: =I124*A124 -> 1840 | K124: =E124-J124 -> 1760 | L124: =K124/E124 -> 0.48888889
A125: 0.5 | B125: KG | C125: LOCOTO | D125: 12000 | E125: =A125*D125 -> 6000 | I125: 8000 | J125: =I125*A125 -> 4000 | K125: =E125-J125 -> 2000 | L125: =K125/E125 -> 0.33333333
... A129: 1 | B129: CAJA | C129: LIMON | D129: 28000 | E129: =A129*D129 -> 28000 | I129: 12000 | J129: =I129*A129 -> 12000 | K129: =E129-J129 -> 16000 | L129: =K129/E129 -> 0.57142857
E131: =SUM(E112:E130) -> 133230 | K131: =SUM(K112:K129) -> 56583.333 | L131: =K131/E131 -> 0.42470415
A134: SAN ANTONIO | D134: rto: 2 | E134: 46114 | F134: **
A136: CANTIDAD | B136: UNIDAD | C136: PRODUCTO | D136: PRECIO | E136: TOTAL | F136: TOTAL + IVA | I136: PRECIO | J136: TOTAL | K136: DIFERENCIA
A137: 1 | B137: CAJON | C137: ACELGA | D137: 11000 | E137: =A137*D137 -> 11000 | F137: =E137*1.105 -> 12155 | I137: 8000 | J137: =I137*A137 -> 8000 | K137: =E137-J137 -> 3000 | L137: =K137/E137 -> 0.27272727
A138: 3 | B138: BOLSA | C138: CEBOLLON | D138: 14000 | E138: =A138*D138 -> 42000 | F138: =E138*1.105 -> 46410 | I138: 9000 | J138: =I138*A138 -> 27000 | K138: =E138-J138 -> 15000 | L138: =K138/E138 -> 0.35714286
A139: 3 | B139: BOLSA | C139: CEBOLLON CAMBIO | D139: 0 | E139: =A139*D139 -> 0 | F139: =E139*1.105 -> 0 | J139: =I139*A139 -> 0 | K139: =E139-J139 -> 0 | L139: =K139/E139 -> #DIV/0!
A140: 1 | B140: CAJON | C140: TOMATE | D140: 20000 | E140: =A140*D140 -> 20000 | F140: =E140*1.105 -> 22100 | I140: 15000 | J140: =I140*A140 -> 15000 | K140: =E140-J140 -> 5000 | L140: =K140/E140 -> 0.25
E142: =SUM(E137:E141) -> 73000 | F142: =SUM(F137:F140) -> 80665 | K142: =SUM(K137:K140) -> 23000 | L142: =K142/E142 -> 0.31506849
...

Sheet 06-04-2026 
A3: COLEGIO SJCB - VIRREY DEL PINO 3299 | E3: rto: 16 | F3: 46118 | I3: COMPRA
A5: CANTIDAD | B5: UNIDAD | C5: PRODUCTO | D5: PRECIO | E5: TOTAL | F5: TOTAL + IVA | I5: COSTO | J5: TOTAL | K5: DIFERENCIA
A6: 1 | B6: ATADO | C6: ALBAHACA | D6: 1500 | E6: =A6*D6 -> 1500 | F6: =E6*1.21 -> 1815 | I6: 1500 | J6: =I6*A6 -> 1500 | K6: =F6-J6 -> 315 | L6: =IFERROR(K6/E6, 0) -> 0.21
A7: 1 | B7: KG | C7: FRUTILLA | D7: 11000 | E7: =A7*D7 -> 11000 | F7: =E7*1.21 -> 13310 | I7: =38000/4 -> 9500 | J7: =I7*A7 -> 9500 | K7: =F7-J7 -> 3810 | L7: =IFERROR(K7/E7, 0) -> 0.34636364
A8: 1 | B8: ATADO | C8: CILANTRO | D8: 3000 | E8: =A8*D8 -> 3000 | F8: =E8*1.21 -> 3630 | I8: 500 | J8: =I8*A8 -> 500 | K8: =F8-J8 -> 3130 | L8: =IFERROR(K8/E8, 0) -> 1.0433333
A9: 1.5 | B9: KG | C9: LECHUGA CRIOLLA | D9: 3200 | E9: =A9*D9 -> 4800 | F9: =E9*1.21 -> 5808 | I9: =10000/4 -> 2500 | J9: =I9*A9 -> 3750 | K9: =F9-J9 -> 2058 | L9: =IFERROR(K9/E9, 0) -> 0.42875
A10: 5 | B10: ATADO | C10: RUCULA | D10: 600 | E10: =A10*D10 -> 3000 | F10: =E10*1.21 -> 3630 | I10: =5000/24 -> 208.33333 | J10: =I10*A10 -> 1041.6667 | K10: =F10-J10 -> 2588.3333 | L10: =IFERROR(K10/E10, 0) -> 0.86277778
A11: 5 | B11: KG | C11: BANANA | D11: 3000 | E11: =A11*D11 -> 15000 | F11: =E11*1.21 -> 18150 | I11: =32000/18 -> 1777.7778 | J11: =I11*A11 -> 8888.8889 | K11: =F11-J11 -> 9261.1111 | L11: =IFERROR(K11/E11, 0) -> 0.61740741
E13: =SUM(E6:E11) -> 38300 | F13: =SUM(F6:F11) -> 46343 | K13: =SUM(K6:K11) -> 21162.444 | L13: =K13/F13 -> 0.45664813
A18: COLEGIO ST. MATTHEWS - MOLDES 1469, BELGRANO | E18: rto: 16 | F18: 46118 | I18: COMPRA
A20: CANTIDAD | B20: UNIDAD | C20: PRODUCTO | D20: PRECIO | E20: TOTAL | F20: TOTAL + IVA | I20: COSTO | J20: TOTAL | K20: DIFERENCIA
A21: 3 | B21: BOLSA | C21: PAPA BLANCA | D21: 23000 | E21: =A21*D21 -> 69000 | F21: =E21*1.105 -> 76245 | I21: 18000 | J21: =I21*A21 -> 54000 | K21: =F21-J21 -> 22245 | L21: =IFERROR(K21/E21, 0) -> 0.3223913
A22: 1 | B22: BOLSA | C22: BATATA | D22: 16000 | E22: =A22*D22 -> 16000 | F22: =E22*1.105 -> 17680 | I22: 12000 | J22: =I22*A22 -> 12000 | K22: =F22-J22 -> 5680 | L22: =IFERROR(K22/E22, 0) -> 0.355
A23: 1 | B23: BOLSA | C23: ZANAHORIA | D23: 12000 | E23: =A23*D23 -> 12000 | F23: =E23*1.105 -> 13260 | I23: 7000 | J23: =I23*A23 -> 7000 | K23: =F23-J23 -> 6260 | L23: =IFERROR(K23/E23, 0) -> 0.52166667
A24: 8 | B24: KG | C24: TOMATE PERITA | D24: 2400 | E24: =A24*D24 -> 19200 | F24: =E24*1.105 -> 21216 | I24: 1666 | J24: =I24*A24 -> 13328 | K24: =F24-J24 -> 7888 | L24: =IFERROR(K24/E24, 0) -> 0.41083333
A25: 3 | B25: KG | C25: CEBOLLA MORADA | D25: 1600 | E25: =A25*D25 -> 4800 | F25: =E25*1.105 -> 5304 | I25: 1000 | J25: =I25*A25 -> 3000 | K25: =F25-J25 -> 2304 | L25: =IFERROR(K25/E25, 0) -> 0.48
A26: 2 | B26: KG | C26: CEBOLLA | D26: 800 | E26: =A26*D26 -> 1600 | F26: =E26*1.105 -> 1768 | I26: =10000/15 -> 666.66667 | J26: =I26*A26 -> 1333.3333 | K26: =F26-J26 -> 434.66667 | L26: =IFERROR(K26/E26, 0) -> 0.27166667
A27: 2 | B27: KG | C27: CHAUCHA | D27: 4000 | E27: =A27*D27 -> 8000 | F27: =E27*1.105 -> 8840 | I27: =18000/8 -> 2250 | J27: =I27*A27 -> 4500 | K27: =F27-J27 -> 4340 | L27: =IFERROR(K27/E27, 0) -> 0.5425
A28: 2 | B28: KG | C28: ZUCCINI | D28: 1400 | E28: =A28*D28 -> 2800 | F28: =E28*1.105 -> 3094 | I28: 1000 | J28: =I28*A28 -> 2000 | K28: =F28-J28 -> 1094 | L28: =IFERROR(K28/E28, 0) -> 0.39071429
A29: 1 | B29: KG | C29: REMOLACHA | D29: 2500 | E29: =A29*D29 -> 2500 | F29: =E29*1.105 -> 2762.5 | I29: 1400 | J29: =I29*A29 -> 1400 | K29: =F29-J29 -> 1362.5 | L29: =IFERROR(K29/E29, 0) -> 0.545
A30: 3 | B30: UNIDAD | C30: BROCOLI | D30: 2600 | E30: =A30*D30 -> 7800 | F30: =E30*1.105 -> 8619 | I30: =15000/8 -> 1875 | J30: =I30*A30 -> 5625 | K30: =F30-J30 -> 2994 | L30: =IFERROR(K30/E30, 0) -> 0.38384615
A31: 2 | B31: KG | C31: ZAPALLITO REDONDO | D31: 1400 | E31: =A31*D31 -> 2800 | F31: =E31*1.105 -> 3094 | I31: =16000/15 -> 1066.6667 | J31: =I31*A31 -> 2133.3333 | K31: =F31-J31 -> 960.66667 | L31: =IFERROR(K31/E31, 0) -> 0.34309524
A32: 2 | B32: KG | C32: MORRON ROJO | D32: 3200 | E32: =A32*D32 -> 6400 | F32: =E32*1.105 -> 7072 | I32: =15000/7 -> 2142.8571 | J32: =I32*A32 -> 4285.7143 | K32: =F32-J32 -> 2786.2857 | L32: =IFERROR(K32/E32, 0) -> 0.43535714
A33: 1 | B33: KG | C33: MORRON VERDE | D33: 2400 | E33: =A33*D33 -> 2400 | F33: =E33*1.105 -> 2652 | I33: =15000/7 -> 2142.8571 | J33: =I33*A33 -> 2142.8571 | K33: =F33-J33 -> 509.14286 | L33: =IFERROR(K33/E33, 0) -> 0.21214286
A34: 1 | B34: KG | C34: REPOLLO COLORADO | D34: 1800 | E34: =A34*D34 -> 1800 | F34: =E34*1.105 -> 1989 | I34: 1000 | J34: =I34*A34 -> 1000 | K34: =F34-J34 -> 989 | L34: =IFERROR(K34/E34, 0) -> 0.54944444
A35: 1.8 | B35: KG | C35: REPOLLO BLANCO | D35: 1800 | E35: =A35*D35 -> 3240 | F35: =E35*1.105 -> 3580.2 | I35: 1000 | J35: =I35*A35 -> 1800 | K35: =F35-J35 -> 1780.2 | L35: =IFERROR(K35/E35, 0) -> 0.54944444
A36: 1 | B36: KG | C36: PEPINO | D36: 1500 | E36: =A36*D36 -> 1500 | F36: =E36*1.105 -> 1657.5 | I36: 1500 | J36: =I36*A36 -> 1500 | K36: =F36-J36 -> 157.5 | L36: =IFERROR(K36/E36, 0) -> 0.105
A37: 20 | B37: ATADO | C37: RUCULA | D37: 600 | E37: =A37*D37 -> 12000 | F37: =E37*1.105 -> 13260 | I37: 208 | J37: =I37*A37 -> 4160 | K37: =F37-J37 -> 9100 | L37: =IFERROR(K37/E37, 0) -> 0.75833333
A38: 2 | B38: KG | C38: LECHUGA CRIOLLA | D38: 3200 | E38: =A38*D38 -> 6400 | F38: =E38*1.105 -> 7072 | I38: =10000/4 -> 2500 | J38: =I38*A38 -> 5000 | K38: =F38-J38 -> 2072 | L38: =IFERROR(K38/E38, 0) -> 0.32375
A39: 10 | B39: ATADO | C39: ESPINACA | D39: 1700 | E39: =A39*D39 -> 17000 | F39: =E39*1.105 -> 18785 | I39: 1200 | J39: =I39*A39 -> 12000 | K39: =F39-J39 -> 6785 | L39: =IFERROR(K39/E39, 0) -> 0.39911765
A40: 1 | B40: ATADO | C40: CILANTRO | D40: 3000 | E40: =A40*D40 -> 3000 | F40: =E40*1.105 -> 3315 | I40: 500 | J40: =I40*A40 -> 500 | K40: =F40-J40 -> 2815 | L40: =IFERROR(K40/E40, 0) -> 0.93833333
A41: 1 | B41: ATADO | C41: CIBOULETTE | D41: 3000 | E41: =A41*D41 -> 3000 | F41: =E41*1.105 -> 3315 | I41: 2000 | J41: =I41*A41 -> 2000 | K41: =F41-J41 -> 1315 | L41: =IFERROR(K41/E41, 0) -> 0.43833333
A42: 2 | B42: ATADO | C42: ALBAHACA | D42: 1500 | E42: =A42*D42 -> 3000 | F42: =E42*1.105 -> 3315 | I42: 1500 | J42: =I42*A42 -> 3000 | K42: =F42-J42 -> 315 | L42: =IFERROR(K42/E42, 0) -> 0.105
A43: 3 | B43: UNIDAD | C43: PALTA | D43: 1600 | E43: =A43*D43 -> 4800 | F43: =E43*1.105 -> 5304 | I43: 1078 | J43: =I43*A43 -> 3234 | K43: =F43-J43 -> 2070 | L43: =IFERROR(K43/E43, 0) -> 0.43125
A44: 0.8 | B44: KG | C44: TOMATE CHERRY | D44: 3000 | E44: =A44*D44 -> 2400 | F44: =E44*1.105 -> 2652 | I44: =13000/7 -> 1857.1429 | J44: =I44*A44 -> 1485.7143 | K44: =F44-J44 -> 1166.2857 | L44: =IFERROR(K44/E44, 0) -> 0.48595238
A45: 0.5 | B45: ATADO | C45: PEREJIL | D45: 3500 | E45: =A45*D45 -> 1750 | F45: =E45*1.105 -> 1933.75 | I45: 1500 | J45: =I45*A45 -> 750 | K45: =F45-J45 -> 1183.75 | L45: =IFERROR(K45/E45, 0) -> 0.67642857
A46: 0.5 | B46: ATADO | C46: CEBOLLA DE VERDEO | D46: 4500 | E46: =A46*D46 -> 2250 | F46: =E46*1.105 -> 2486.25 | I46: 1200 | J46: =I46*A46 -> 600 | K46: =F46-J46 -> 1886.25 | L46: =IFERROR(K46/E46, 0) -> 0.83833333
A47: 1 | B47: ATADO | C47: APIO | D47: 2500 | E47: =A47*D47 -> 2500 | F47: =E47*1.105 -> 2762.5 | I47: 1000 | J47: =I47*A47 -> 1000 | K47: =F47-J47 -> 1762.5 | L47: =IFERROR(K47/E47, 0) -> 0.705
A48: 3 | B48: CAJON | C48: NARANJA | D48: 26000 | E48: =A48*D48 -> 78000 | F48: =E48*1.105 -> 86190 | I48: 22000 | J48: =I48*A48 -> 66000 | K48: =F48-J48 -> 20190 | L48: =IFERROR(K48/E48, 0) -> 0.25884615
A49: 7 | B49: KG | C49: POMELO | D49: 3200 | E49: =A49*D49 -> 22400 | F49: =E49*1.105 -> 24752 | I49: =32000/15 -> 2133.3333 | J49: =I49*A49 -> 14933.333 | K49: =F49-J49 -> 9818.6667 | L49: =IFERROR(K49/E49, 0) -> 0.43833333
A50: 4 | B50: KG | C50: MANZANA ROJA | D50: 3600 | E50: =A50*D50 -> 14400 | F50: =E50*1.105 -> 15912 | I50: =52000/17 -> 3058.8235 | J50: =I50*A50 -> 12235.294 | K50: =F50-J50 -> 3676.7059 | L50: =IFERROR(K50/E50, 0) -> 0.2553268
A51: 4 | B51: KG | C51: MANZANA VERDE | D51: 4500 | E51: =A51*D51 -> 18000 | F51: =E51*1.105 -> 19890 | I51: =65000/17 -> 3823.5294 | J51: =I51*A51 -> 15294.118 | K51: =F51-J51 -> 4595.8824 | L51: =IFERROR(K51/E51, 0) -> 0.2553268
A52: 3 | B52: KG | C52: PERA | D52: 3000 | E52: =A52*D52 -> 9000 | F52: =E52*1.105 -> 9945 | I52: =20000/9 -> 2222.2222 | J52: =I52*A52 -> 6666.6667 | K52: =F52-J52 -> 3278.3333 | L52: =IFERROR(K52/E52, 0) -> 0.36425926
A53: 2 | B53: KG | C53: MANDARINA | D53: 3200 | E53: =A53*D53 -> 6400 | F53: =E53*1.105 -> 7072 | I53: 1000 | J53: =I53*A53 -> 2000 | K53: =F53-J53 -> 5072 | L53: =IFERROR(K53/E53, 0) -> 0.7925
A54: 0.5 | B54: KG | C54: FRUTILLA | D54: 11000 | E54: =A54*D54 -> 5500 | F54: =E54*1.105 -> 6077.5 | I54: 9500 | J54: =I54*A54 -> 4750 | K54: =F54-J54 -> 1327.5 | L54: =IFERROR(K54/E54, 0) -> 0.24136364
A55: 2 | B55: KG | C55: BANANA | D55: 3000 | E55: =A55*D55 -> 6000 | F55: =E55*1.105 -> 6630 | I55: =32000/18 -> 1777.7778 | J55: =I55*A55 -> 3555.5556 | K55: =F55-J55 -> 3074.4444 | L55: =IFERROR(K55/E55, 0) -> 0.51240741
A56: 0.5 | B56: CAJON | C56: HUEVO N1 | D56: 54000 | E56: =A56*D56 -> 27000 | F56: =E56*1.21 -> 32670 | I56: 54000 | J56: =I56*A56 -> 27000 | K56: =F56-J56 -> 5670 | L56: =IFERROR(K56/E56, 0) -> 0.21
E58: =SUM(E21:E56) -> 406640 | F58: =SUM(F21:F56) -> 452172.2 | K58: =SUM(K21:K56) -> 148959.28 | L58: =K58/F58 -> 0.32943043
A61: COLEGIO SAN JAVIER - JOSE A CABRERA 5901 | E61: rto: 16 | F61: 46118 | I61: COMPRA
A63: CANTIDAD | B63: UNIDAD | C63: PRODUCTO | D63: PRECIO | E63: TOTAL | F63: TOTAL + IVA | I63: COSTO | J63: TOTAL | K63: DIFERENCIA
A64: 4 | B64: KG | C64: LECHUGA CRIOLLA | D64: 3200 | E64: =A64*D64 -> 12800 | F64: =E64*1.105 -> 14144 | I64: =10000/4 -> 2500 | J64: =I64*A64 -> 10000 | K64: =F64-J64 -> 4144 | L64: =IFERROR(K64/E64, 0) -> 0.32375
A65: 15 | B65: ATADO | C65: RUCULA | D65: 600 | E65: =A65*D65 -> 9000 | F65: =E65*1.105 -> 9945 | I65: 208 | J65: =I65*A65 -> 3120 | K65: =F65-J65 -> 6825 | L65: =IFERROR(K65/E65, 0) -> 0.75833333
A66: 5 | B66: KG | C66: BANANA | D66: 3000 | E66: =A66*D66 -> 15000 | F66: =E66*1.105 -> 16575 | I66: =32000/18 -> 1777.7778 | J66: =I66*A66 -> 8888.8889 | K66: =F66-J66 -> 7686.1111 | L66: =IFERROR(K66/E66, 0) -> 0.51240741
A67: 1 | B67: CAJON | C67: NARANJA | D67: 26000 | E67: =A67*D67 -> 26000 | F67: =E67*1.105 -> 28730 | I67: 22000 | J67: =I67*A67 -> 22000 | K67: =F67-J67 -> 6730 | L67: =IFERROR(K67/E67, 0) -> 0.25884615
A68: 13 | B68: ATADO | C68: ESPINACA | D68: 1700 | E68: =A68*D68 -> 22100 | F68: =E68*1.105 -> 24420.5 | I68: 1200 | J68: =I68*A68 -> 15600 | K68: =F68-J68 -> 8820.5 | L68: =IFERROR(K68/E68, 0) -> 0.39911765
A69: 2 | B69: ATADO | C69: CIBOULETTE | D69: 3000 | E69: =A69*D69 -> 6000 | F69: =E69*1.105 -> 6630 | I69: 2000 | J69: =I69*A69 -> 4000 | K69: =F69-J69 -> 2630 | L69: =IFERROR(K69/E69, 0) -> 0.43833333
A70: 0.5 | B70: ATADO | C70: PEREJIL | D70: 3500 | E70: =A70*D70 -> 1750 | F70: =E70*1.105 -> 1933.75 | I70: 1500 | J70: =I70*A70 -> 750 | K70: =F70-J70 -> 1183.75 | L70: =IFERROR(K70/E70, 0) -> 0.67642857
A71: 8 | B71: KG | C71: TOMATE PERITA | D71: 2400 | E71: =A71*D71 -> 19200 | F71: =E71*1.105 -> 21216 | I71: 1666 | J71: =I71*A71 -> 13328 | K71: =F71-J71 -> 7888 | L71: =IFERROR(K71/E71, 0) -> 0.41083333
A72: 4.5 | B72: KG | C72: CHAUCHA | D72: 4000 | E72: =A72*D72 -> 18000 | F72: =E72*1.105 -> 19890 | I72: =18000/8 -> 2250 | J72: =I72*A72 -> 10125 | K72: =F72-J72 -> 9765 | L72: =IFERROR(K72/E72, 0) -> 0.5425
A73: 2 | B73: UNIDAD | C73: PALTA | D73: 1600 | E73: =A73*D73 -> 3200 | F73: =E73*1.105 -> 3536 | I73: 1078 | J73: =I73*A73 -> 2156 | K73: =F73-J73 -> 1380 | L73: =IFERROR(K73/E73, 0) -> 0.43125
A74: 5 | B74: KG | C74: BATATA | D74: 1600 | E74: =A74*D74 -> 8000 | F74: =E74*1.105 -> 8840 | I74: 1200 | J74: =I74*A74 -> 6000 | K74: =F74-J74 -> 2840 | L74: =IFERROR(K74/E74, 0) -> 0.355
A75: 10 | B75: KG | C75: CALABAZA | D75: 1000 | E75: =A75*D75 -> 10000 | F75: =E75*1.105 -> 11050 | I75: 500 | J75: =I75*A75 -> 5000 | K75: =F75-J75 -> 6050 | L75: =IFERROR(K75/E75, 0) -> 0.605
A76: 4 | B76: BOLSA | C76: PAPA BLANCA | D76: 23000 | E76: =A76*D76 -> 92000 | F76: =E76*1.105 -> 101660 | I76: 18000 | J76: =I76*A76 -> 72000 | K76: =F76-J76 -> 29660 | L76: =IFERROR(K76/E76, 0) -> 0.3223913
A77: 2 | B77: KG | C77: ZAPALLITO REDONDO | D77: 1400 | E77: =A77*D77 -> 2800 | F77: =E77*1.105 -> 3094 | I77: =16000/15 -> 1066.6667 | J77: =I77*A77 -> 2133.3333 | K77: =F77-J77 -> 960.66667 | L77: =IFERROR(K77/E77, 0) -> 0.34309524
A78: 2 | B78: UNIDAD | C78: BROCOLI | D78: 2600 | E78: =A78*D78 -> 5200 | F78: =E78*1.105 -> 5746 | I78: =15000/8 -> 1875 | J78: =I78*A78 -> 3750 | K78: =F78-J78 -> 1996 | L78: =IFERROR(K78/E78, 0) -> 0.38384615
A79: 1 | B79: KG | C79: REMOLACHA | D79: 2500 | E79: =A79*D79 -> 2500 | F79: =E79*1.105 -> 2762.5 | I79: 1400 | J79: =I79*A79 -> 1400 | K79: =F79-J79 -> 1362.5 | L79: =IFERROR(K79/E79, 0) -> 0.545
A80: 1 | B80: BOLSA | C80: ZANAHORIA | D80: 12000 | E80: =A80*D80 -> 12000 | F80: =E80*1.105 -> 13260 | I80: 7000 | J80: =I80*A80 -> 7000 | K80: =F80-J80 -> 6260 | L80: =IFERROR(K80/E80, 0) -> 0.52166667
A81: 3 | B81: KG | C81: ZANAHORIA | D81: 1300 | E81: =A81*D81 -> 3900 | F81: =E81*1.105 -> 4309.5 | I81: =7000/9 -> 777.77778 | J81: =I81*A81 -> 2333.3333 | K81: =F81-J81 -> 1976.1667 | L81: =IFERROR(K81/E81, 0) -> 0.5067094
A82: 1 | B82: CAJON | C82: MANZANA VERDE | D82: 72000 | E82: =A82*D82 -> 72000 | F82: =E82*1.105 -> 79560 | I82: 65000 | J82: =I82*A82 -> 65000 | K82: =F82-J82 -> 14560 | L82: =IFERROR(K82/E82, 0) -> 0.20222222
A83: 1 | B83: CAJON | C83: MANZANA ROJA | D83: 60000 | E83: =A83*D83 -> 60000 | F83: =E83*1.105 -> 66300 | I83: 52000 | J83: =I83*A83 -> 52000 | K83: =F83-J83 -> 14300 | L83: =IFERROR(K83/E83, 0) -> 0.23833333
A84: 0.5 | B84: CAJON | C84: HUEVO N1 | D84: 54000 | E84: =A84*D84 -> 27000 | F84: =E84*1.21 -> 32670 | I84: 54000 | J84: =I84*A84 -> 27000 | K84: =F84-J84 -> 5670 | L84: =IFERROR(K84/E84, 0) -> 0.21
A85: 1.65 | B85: KG | C85: REPOLLO BLANCO | D85: 1800 | E85: =A85*D85 -> 2970 | F85: =E85*1.105 -> 3281.85 | I85: 1000 | J85: =I85*A85 -> 1650 | K85: =F85-J85 -> 1631.85 | L85: =IFERROR(K85/E85, 0) -> 0.54944444
A86: 1.4 | B86: KG | C86: REPOLLO COLORADO | D86: 1800 | E86: =A86*D86 -> 2520 | F86: =E86*1.105 -> 2784.6 | I86: 1000 | J86: =I86*A86 -> 1400 | K86: =F86-J86 -> 1384.6 | L86: =IFERROR(K86/E86, 0) -> 0.54944444
A87: 1 | B87: KG | C87: FRUTILLA | D87: 11000 | E87: =A87*D87 -> 11000 | F87: =E87*1.105 -> 12155 | I87: =38000/4 -> 9500 | J87: =I87*A87 -> 9500 | K87: =F87-J87 -> 2655 | L87: =IFERROR(K87/E87, 0) -> 0.24136364
A88: 4 | B88: KG | C88: POMELO | D88: 3200 | E88: =A88*D88 -> 12800 | F88: =E88*1.105 -> 14144 | I88: =32000/15 -> 2133.3333 | J88: =I88*A88 -> 8533.3333 | K88: =F88-J88 -> 5610.6667 | L88: =IFERROR(K88/E88, 0) -> 0.43833333
A89: 2 | B89: KG | C89: MORRON ROJO | D89: 3200 | E89: =A89*D89 -> 6400 | F89: =E89*1.105 -> 7072 | I89: =15000/7 -> 2142.8571 | J89: =I89*A89 -> 4285.7143 | K89: =F89-J89 -> 2786.2857 | L89: =IFERROR(K89/E89, 0) -> 0.43535714
A90: 1 | B90: KG | C90: MORRON VERDE | D90: 2400 | E90: =A90*D90 -> 2400 | F90: =E90*1.105 -> 2652 | I90: =15000/7 -> 2142.8571 | J90: =I90*A90 -> 2142.8571 | K90: =F90-J90 -> 509.14286 | L90: =IFERROR(K90/E90, 0) -> 0.21214286
A91: 2 | B91: KG | C91: PUERRO | D91: 5000 | E91: =A91*D91 -> 10000 | F91: =E91*1.105 -> 11050 | I91: 2500 | J91: =I91*A91 -> 5000 | K91: =F91-J91 -> 6050 | L91: =IFERROR(K91/E91, 0) -> 0.605
A92: 1 | B92: KG | C92: APIO | D92: 2500 | E92: =A92*D92 -> 2500 | F92: =E92*1.105 -> 2762.5 | I92: 1000 | J92: =I92*A92 -> 1000 | K92: =F92-J92 -> 1762.5 | L92: =IFERROR(K92/E92, 0) -> 0.705
E94: =SUM(E64:E92) -> 479040 | F94: =SUM(F64:F92) -> 532174.2 | K94: =SUM(K64:K92) -> 165077.74 | L94: =K94/F94 -> 0.31019493
A97: COLEGIO SAN MARCOS | SAN ISIDRO | E97: rto: 12 | F97: 46118 | I97: COMPRA
A99: CANTIDAD | B99: UNIDAD | C99: PRODUCTO | D99: PRECIO | E99: TOTAL | F99: TOTAL + IVA | I99: COSTO | J99: TOTAL | K99: DIFERENCIA
A100: 2 | B100: CAJON | C100: TOMATE PERITA | D100: 36000 | E100: =A100*D100 -> 72000 | F100: =E100*1.105 -> 79560 | I100: 25000 | J100: =I100*A100 -> 50000 | K100: =F100-J100 -> 29560 | L100: =IFERROR(K100/E100, 0) -> 0.41055556
A101: 1 | B101: CAJON | C101: LECHUGA CRIOLLA | D101: 21000 | E101: =A101*D101 -> 21000 | F101: =E101*1.105 -> 23205 | I101: 17000 | J101: =I101*A101 -> 17000 | K101: =F101-J101 -> 6205 | L101: =IFERROR(K101/E101, 0) -> 0.29547619
A102: 1 | B102: CAJON | C102: RUCULA | D102: 9000 | E102: =A102*D102 -> 9000 | F102: =E102*1.105 -> 9945 | I102: 5000 | J102: =I102*A102 -> 5000 | K102: =F102-J102 -> 4945 | L102: =IFERROR(K102/E102, 0) -> 0.54944444
A103: 4 | B103: BOLSA | C103: ZANAHORIA | D103: 12000 | E103: =A103*D103 -> 48000 | F103: =E103*1.105 -> 53040 | I103: 7000 | J103: =I103*A103 -> 28000 | K103: =F103-J103 -> 25040 | L103: =IFERROR(K103/E103, 0) -> 0.52166667
A104: 5 | B104: BOLSA | C104: PAPA BLANCA | D104: 23000 | E104: =A104*D104 -> 115000 | F104: =E104*1.105 -> 127075 | I104: 18000 | J104: =I104*A104 -> 90000 | K104: =F104-J104 -> 37075 | L104: =IFERROR(K104/E104, 0) -> 0.3223913
A105: 2 | B105: BOLSA | C105: ANCO | D105: 13000 | E105: =A105*D105 -> 26000 | F105: =E105*1.105 -> 28730 | I105: 8000 | J105: =I105*A105 -> 16000 | K105: =F105-J105 -> 12730 | L105: =IFERROR(K105/E105, 0) -> 0.48961538
A106: 1 | B106: BOLSA | C106: BATATA | D106: 15000 | E106: =A106*D106 -> 15000 | F106: =E106*1.105 -> 16575 | I106: 12000 | J106: =I106*A106 -> 12000 | K106: =F106-J106 -> 4575 | L106: =IFERROR(K106/E106, 0) -> 0.305
A107: 6.2 | B107: KG | C107: REPOLLO BLANCO | D107: 1800 | E107: =A107*D107 -> 11160 | F107: =E107*1.105 -> 12331.8 | I107: 1000 | J107: =I107*A107 -> 6200 | K107: =F107-J107 -> 6131.8 | L107: =IFERROR(K107/E107, 0) -> 0.54944444
A108: 7.4 | B108: KG | C108: REPOLLO COLORADO | D108: 1800 | E108: =A108*D108 -> 13320 | F108: =E108*1.105 -> 14718.6 | I108: 1000 | J108: =I108*A108 -> 7400 | K108: =F108-J108 -> 7318.6 | L108: =IFERROR(K108/E108, 0) -> 0.54944444
A109: 6 | B109: KG | C109: ZAPALLITO REDONDO | D109: 1400 | E109: =A109*D109 -> 8400 | F109: =E109*1.105 -> 9282 | I109: =16000/15 -> 1066.6667 | J109: =I109*A109 -> 6400 | K109: =F109-J109 -> 2882 | L109: =IFERROR(K109/E109, 0) -> 0.34309524
A110: 3 | B110: KG | C110: MORRON ROJO | D110: 3200 | E110: =A110*D110 -> 9600 | F110: =E110*1.105 -> 10608 | I110: =15000/7 -> 2142.8571 | J110: =I110*A110 -> 6428.5714 | K110: =F110-J110 -> 4179.4286 | L110: =IFERROR(K110/E110, 0) -> 0.43535714
A111: 2 | B111: KG | C111: MORRON VERDE | D111: 2400 | E111: =A111*D111 -> 4800 | F111: =E111*1.105 -> 5304 | I111: =15000/7 -> 2142.8571 | J111: =I111*A111 -> 4285.7143 | K111: =F111-J111 -> 1018.2857 | L111: =IFERROR(K111/E111, 0) -> 0.21214286
A112: 2 | B112: KG | C112: MORRON AMARILLO | D112: 2800 | E112: =A112*D112 -> 5600 | F112: =E112*1.105 -> 6188 | I112: =15000/7 -> 2142.8571 | J112: =I112*A112 -> 4285.7143 | K112: =F112-J112 -> 1902.2857 | L112: =IFERROR(K112/E112, 0) -> 0.33969388
A113: 1 | B113: KG | C113: CHAUCHA PLANA | D113: 4000 | E113: =A113*D113 -> 4000 | F113: =E113*1.105 -> 4420 | I113: =18000/8 -> 2250 | J113: =I113*A113 -> 2250 | K113: =F113-J113 -> 2170 | L113: =IFERROR(K113/E113, 0) -> 0.5425
A114: 5 | B114: KG | C114: CHAUCHA | D114: 4000 | E114: =A114*D114 -> 20000 | F114: =E114*1.105 -> 22100 | I114: =13000/8 -> 1625 | J114: =I114*A114 -> 8125 | K114: =F114-J114 -> 13975 | L114: =IFERROR(K114/E114, 0) -> 0.69875
A115: 1 | B115: ATADO | C115: CEBOLLA DE VERDEO | D115: 4500 | E115: =A115*D115 -> 4500 | F115: =E115*1.105 -> 4972.5 | I115: 1200 | J115: =I115*A115 -> 1200 | K115: =F115-J115 -> 3772.5 | L115: =IFERROR(K115/E115, 0) -> 0.83833333
A116: 1 | B116: UNIDAD | C116: APIO | D116: 2500 | E116: =A116*D116 -> 2500 | F116: =E116*1.105 -> 2762.5 | I116: 1000 | J116: =I116*A116 -> 1000 | K116: =F116-J116 -> 1762.5 | L116: =IFERROR(K116/E116, 0) -> 0.705
A117: 4 | B117: UNIDAD | C117: PALTA | D117: 1600 | E117: =A117*D117 -> 6400 | F117: =E117*1.105 -> 7072 | I117: 1078 | J117: =I117*A117 -> 4312 | K117: =F117-J117 -> 2760 | L117: =IFERROR(K117/E117, 0) -> 0.43125
...

Sheet 07-04-2026 
A3: COLEGIO WASHINGTON - LACROZE 1973 | E3: rto: 15 | F3: 46119 | I3: COMPRA
A5: CANTIDAD | B5: UNIDAD | C5: PRODUCTO | D5: PRECIO | E5: TOTAL | F5: TOTAL + IVA | I5: COSTO | J5: TOTAL | K5: DIFERENCIA
A6: 1 | B6: BOLSA | C6: ANCO | D6: 13000 | E6: =A6*D6 -> 13000 | F6: =E6*1.105 -> 14365 | I6: 7000 | J6: =I6*A6 -> 7000 | K6: =F6-J6 -> 7365 | L6: =IFERROR(K6/E6, 0) -> 0.56653846
A7: 2 | B7: KG | C7: ANCO | D7: 1000 | E7: =A7*D7 -> 2000 | F7: =E7*1.105 -> 2210 | I7: =7000/15 -> 466.66667 | J7: =I7*A7 -> 933.33333 | K7: =F7-J7 -> 1276.6667 | L7: =IFERROR(K7/E7, 0) -> 0.63833333
A8: 1 | B8: BOLSA | C8: BATATA | D8: 16000 | E8: =A8*D8 -> 16000 | F8: =E8*1.105 -> 17680 | I8: 12000 | J8: =I8*A8 -> 12000 | K8: =F8-J8 -> 5680 | L8: =IFERROR(K8/E8, 0) -> 0.355
A9: 5 | B9: BOLSA | C9: PAPA BLANCA | D9: 23000 | E9: =A9*D9 -> 115000 | F9: =E9*1.105 -> 127075 | I9: 17500 | J9: =I9*A9 -> 87500 | K9: =F9-J9 -> 39575 | L9: =IFERROR(K9/E9, 0) -> 0.34413043
A10: 1.5 | B10: BOLSA | C10: ZANAHORIA | D10: 12000 | E10: =A10*D10 -> 18000 | F10: =E10*1.105 -> 19890 | I10: 7000 | J10: =I10*A10 -> 10500 | K10: =F10-J10 -> 9390 | L10: =IFERROR(K10/E10, 0) -> 0.52166667
A11: 3 | B11: UNIDAD | C11: COLIFLOR | D11: 2800 | E11: =A11*D11 -> 8400 | F11: =E11*1.105 -> 9282 | I11: =16000/10 -> 1600 | J11: =I11*A11 -> 4800 | K11: =F11-J11 -> 4482 | L11: =IFERROR(K11/E11, 0) -> 0.53357143
A12: 3.5 | B12: KG | C12: CEBOLLA MORADA | D12: 1600 | E12: =A12*D12 -> 5600 | F12: =E12*1.105 -> 6188 | I12: 1000 | J12: =I12*A12 -> 3500 | K12: =F12-J12 -> 2688 | L12: =IFERROR(K12/E12, 0) -> 0.48
A13: 1 | B13: KG | C13: CEBOLLA | D13: 800 | E13: =A13*D13 -> 800 | F13: =E13*1.105 -> 884 | I13: =10000/15 -> 666.66667 | J13: =I13*A13 -> 666.66667 | K13: =F13-J13 -> 217.33333 | L13: =IFERROR(K13/E13, 0) -> 0.27166667
A14: 2 | B14: UNIDAD | C14: AJO | D14: 900 | E14: =A14*D14 -> 1800 | F14: =E14*1.105 -> 1989 | I14: 460 | J14: =I14*A14 -> 920 | K14: =F14-J14 -> 1069 | L14: =IFERROR(K14/E14, 0) -> 0.59388889
A15: 3.75 | B15: KG | C15: REPOLLO BLANCO | D15: 1800 | E15: =A15*D15 -> 6750 | F15: =E15*1.105 -> 7458.75 | I15: 1000 | J15: =I15*A15 -> 3750 | K15: =F15-J15 -> 3708.75 | L15: =IFERROR(K15/E15, 0) -> 0.54944444
A16: 3 | B16: KG | C16: REPOLLO COLORADO | D16: 1800 | E16: =A16*D16 -> 5400 | F16: =E16*1.105 -> 5967 | I16: 1000 | J16: =I16*A16 -> 3000 | K16: =F16-J16 -> 2967 | L16: =IFERROR(K16/E16, 0) -> 0.54944444
A17: 1 | B17: KG | C17: ZUCCINI | D17: 1400 | E17: =A17*D17 -> 1400 | F17: =E17*1.105 -> 1547 | I17: =12000/14 -> 857.14286 | J17: =I17*A17 -> 857.14286 | K17: =F17-J17 -> 689.85714 | L17: =IFERROR(K17/E17, 0) -> 0.4927551
A18: 0.5 | B18: KG | C18: BERENJENA | D18: 1500 | E18: =A18*D18 -> 750 | F18: =E18*1.105 -> 828.75 | I18: =10000/8 -> 1250 | J18: =I18*A18 -> 625 | K18: =F18-J18 -> 203.75 | L18: =IFERROR(K18/E18, 0) -> 0.27166667
A19: 0.5 | B19: KG | C19: APIO | D19: 2500 | E19: =A19*D19 -> 1250 | F19: =E19*1.105 -> 1381.25 | I19: =9000/8 -> 1125 | J19: =I19*A19 -> 562.5 | K19: =F19-J19 -> 818.75 | L19: =IFERROR(K19/E19, 0) -> 0.655
A20: 1 | B20: ATADO | C20: PEREJIL | D20: 3500 | E20: =A20*D20 -> 3500 | F20: =E20*1.105 -> 3867.5 | I20: 1500 | J20: =I20*A20 -> 1500 | K20: =F20-J20 -> 2367.5 | L20: =IFERROR(K20/E20, 0) -> 0.67642857
A21: 1 | B21: ATADO | C21: CIBOULETTE | D21: 3000 | E21: =A21*D21 -> 3000 | F21: =E21*1.105 -> 3315 | I21: 2000 | J21: =I21*A21 -> 2000 | K21: =F21-J21 -> 1315 | L21: =IFERROR(K21/E21, 0) -> 0.43833333
A22: 1 | B22: ATADO | C22: CILANTRO | D22: 3000 | E22: =A22*D22 -> 3000 | F22: =E22*1.105 -> 3315 | I22: 2000 | J22: =I22*A22 -> 2000 | K22: =F22-J22 -> 1315 | L22: =IFERROR(K22/E22, 0) -> 0.43833333
A23: 0.5 | B23: KG | C23: CEBOLLA DE VERDEO | D23: 4500 | E23: =A23*D23 -> 2250 | F23: =E23*1.105 -> 2486.25 | I23: 2000 | J23: =I23*A23 -> 1000 | K23: =F23-J23 -> 1486.25 | L23: =IFERROR(K23/E23, 0) -> 0.66055556
A24: 2 | B24: ATADO | C24: ALBAHACA | D24: 1500 | E24: =A24*D24 -> 3000 | F24: =E24*1.105 -> 3315 | I24: 1000 | J24: =I24*A24 -> 2000 | K24: =F24-J24 -> 1315 | L24: =IFERROR(K24/E24, 0) -> 0.43833333
A25: 1 | B25: KG | C25: REMOLACHA | D25: 2500 | E25: =A25*D25 -> 2500 | F25: =E25*1.105 -> 2762.5 | I25: =14000/9 -> 1555.5556 | J25: =I25*A25 -> 1555.5556 | K25: =F25-J25 -> 1206.9444 | L25: =IFERROR(K25/E25, 0) -> 0.48277778
A26: 1 | B26: UNIDAD | C26: BROCOLI | D26: 2600 | E26: =A26*D26 -> 2600 | F26: =E26*1.105 -> 2873 | I26: =15000/8 -> 1875 | J26: =I26*A26 -> 1875 | K26: =F26-J26 -> 998 | L26: =IFERROR(K26/E26, 0) -> 0.38384615
A27: 0.7 | B27: KG | C27: TOMATE CHERRY | D27: 3000 | E27: =A27*D27 -> 2100 | F27: =E27*1.105 -> 2320.5 | I27: =7000/6 -> 1166.6667 | J27: =I27*A27 -> 816.66667 | K27: =F27-J27 -> 1503.8333 | L27: =IFERROR(K27/E27, 0) -> 0.71611111
A28: 16 | B28: KG | C28: TOMATE PERITA | D28: 2400 | E28: =A28*D28 -> 38400 | F28: =E28*1.105 -> 42432 | I28: =25000/15 -> 1666.6667 | J28: =I28*A28 -> 26666.667 | K28: =F28-J28 -> 15765.333 | L28: =IFERROR(K28/E28, 0) -> 0.41055556
A29: 4 | B29: KG | C29: LECHUGA CRIOLLA | D29: 4000 | E29: =A29*D29 -> 16000 | F29: =E29*1.105 -> 17680 | I29: =18000/4 -> 4500 | J29: =I29*A29 -> 18000 | K29: =F29-J29 -> -320 | L29: =IFERROR(K29/E29, 0) -> -0.02
A30: 25 | B30: ATADO | C30: RUCULA | D30: 600 | E30: =A30*D30 -> 15000 | F30: =E30*1.105 -> 16575 | I30: =8000/24 -> 333.33333 | J30: =I30*A30 -> 8333.3333 | K30: =F30-J30 -> 8241.6667 | L30: =IFERROR(K30/E30, 0) -> 0.54944444
A31: 9 | B31: ATADO | C31: ESPINACA | D31: 1700 | E31: =A31*D31 -> 15300 | F31: =E31*1.105 -> 16906.5 | I31: =13000/12 -> 1083.3333 | J31: =I31*A31 -> 9750 | K31: =F31-J31 -> 7156.5 | L31: =IFERROR(K31/E31, 0) -> 0.4677451
A32: 0.1 | B32: KG | C32: LIMON | D32: 2400 | E32: =A32*D32 -> 240 | F32: =E32*1.105 -> 265.2 | I32: =20000/15 -> 1333.3333 | J32: =I32*A32 -> 133.33333 | K32: =F32-J32 -> 131.86667 | L32: =IFERROR(K32/E32, 0) -> 0.54944444
A33: 5 | B33: KG | C33: POMELO | D33: 3200 | E33: =A33*D33 -> 16000 | F33: =E33*1.105 -> 17680 | I33: =32000/15 -> 2133.3333 | J33: =I33*A33 -> 10666.667 | K33: =F33-J33 -> 7013.3333 | L33: =IFERROR(K33/E33, 0) -> 0.43833333
A34: 5 | B34: KG | C34: ZAPALLITO REDONDO | D34: 1400 | E34: =A34*D34 -> 7000 | F34: =E34*1.105 -> 7735 | I34: =15000/14 -> 1071.4286 | J34: =I34*A34 -> 5357.1429 | K34: =F34-J34 -> 2377.8571 | L34: =IFERROR(K34/E34, 0) -> 0.33969388
A35: 2 | B35: CAJON | C35: NARANJA | D35: 26000 | E35: =A35*D35 -> 52000 | F35: =E35*1.105 -> 57460 | I35: 25000 | J35: =I35*A35 -> 50000 | K35: =F35-J35 -> 7460 | L35: =IFERROR(K35/E35, 0) -> 0.14346154
A36: 1 | B36: CAJON | C36: MANZANA ROJA | D36: 60000 | E36: =A36*D36 -> 60000 | F36: =E36*1.105 -> 66300 | I36: 50000 | J36: =I36*A36 -> 50000 | K36: =F36-J36 -> 16300 | L36: =IFERROR(K36/E36, 0) -> 0.27166667
A37: 4 | B37: KG | C37: MANZANA VERDE | D37: 4500 | E37: =A37*D37 -> 18000 | F37: =E37*1.105 -> 19890 | I37: =65000/17 -> 3823.5294 | J37: =I37*A37 -> 15294.118 | K37: =F37-J37 -> 4595.8824 | L37: =IFERROR(K37/E37, 0) -> 0.2553268
A38: 5 | B38: KG | C38: CHAUCHA | D38: 4000 | E38: =A38*D38 -> 20000 | F38: =E38*1.105 -> 22100 | I38: =18000/8 -> 2250 | J38: =I38*A38 -> 11250 | K38: =F38-J38 -> 10850 | L38: =IFERROR(K38/E38, 0) -> 0.5425
A39: 1.8 | B39: KG | C39: CHAUCHA PLANA | D39: 4000 | E39: =A39*D39 -> 7200 | F39: =E39*1.105 -> 7956 | I39: 2250 | J39: =I39*A39 -> 4050 | K39: =F39-J39 -> 3906 | L39: =IFERROR(K39/E39, 0) -> 0.5425
A40: 4 | B40: KG | C40: MORRON ROJO | D40: 3200 | E40: =A40*D40 -> 12800 | F40: =E40*1.105 -> 14144 | I40: =20000/7 -> 2857.1429 | J40: =I40*A40 -> 11428.571 | K40: =F40-J40 -> 2715.4286 | L40: =IFERROR(K40/E40, 0) -> 0.21214286
A41: 2 | B41: KG | C41: MORRON AMARILLO | D41: 2800 | E41: =A41*D41 -> 5600 | F41: =E41*1.105 -> 6188 | I41: =15000/7 -> 2142.8571 | J41: =I41*A41 -> 4285.7143 | K41: =F41-J41 -> 1902.2857 | L41: =IFERROR(K41/E41, 0) -> 0.33969388
A42: 2 | B42: KG | C42: MORRON VERDE | D42: 2400 | E42: =A42*D42 -> 4800 | F42: =E42*1.105 -> 5304 | I42: =12000/7 -> 1714.2857 | J42: =I42*A42 -> 3428.5714 | K42: =F42-J42 -> 1875.4286 | L42: =IFERROR(K42/E42, 0) -> 0.39071429
A43: 0.5 | B43: CAJON | C43: HUEVO N1 | D43: 54000 | E43: =A43*D43 -> 27000 | F43: =E43*1.21 -> 32670 | I43: 50000 | J43: =I43*A43 -> 25000 | K43: =F43-J43 -> 7670 | L43: =IFERROR(K43/E43, 0) -> 0.28407407
E45: =SUM(E6:E43) -> 533440 | F45: =SUM(F6:F43) -> 592286.2 | K45: =SUM(K6:K43) -> 189280.22 | L45: =K45/F45 -> 0.3195756
A48: COLEGIO SJCB - VIRREY DEL PINO 3299 | E48: rto: 17 | F48: 46119 | I48: COMPRA
A50: CANTIDAD | B50: UNIDAD | C50: PRODUCTO | D50: PRECIO | E50: TOTAL | F50: TOTAL + IVA | I50: COSTO | J50: TOTAL | K50: DIFERENCIA
A51: 0.5 | B51: KG | C51: CEBOLLA DE VERDEO | D51: 4500 | E51: =A51*D51 -> 2250 | F51: =E51*1.105 -> 2486.25 | I51: 2000 | J51: =I51*A51 -> 1000 | K51: =F51-J51 -> 1486.25 | L51: =IFERROR(K51/E51, 0) -> 0.66055556
A52: 2 | B52: UNIDAD | C52: AJO | D52: 900 | E52: =A52*D52 -> 1800 | F52: =E52*1.105 -> 1989 | I52: 460 | J52: =I52*A52 -> 920 | K52: =F52-J52 -> 1069 | L52: =IFERROR(K52/E52, 0) -> 0.59388889
A53: 1 | B53: ATADO | C53: ALBAHACA | D53: 1500 | E53: =A53*D53 -> 1500 | F53: =E53*1.105 -> 1657.5 | I53: 1000 | J53: =I53*A53 -> 1000 | K53: =F53-J53 -> 657.5 | L53: =IFERROR(K53/E53, 0) -> 0.43833333
A54: 0.25 | B54: KG | C54: APIO | D54: 2500 | E54: =A54*D54 -> 625 | F54: =E54*1.105 -> 690.625 | I54: =9000/8 -> 1125 | J54: =I54*A54 -> 281.25 | K54: =F54-J54 -> 409.375 | L54: =IFERROR(K54/E54, 0) -> 0.655
A55: 3 | B55: KG | C55: BANANA | D55: 3000 | E55: =A55*D55 -> 9000 | F55: =E55*1.105 -> 9945 | I55: =32000/17 -> 1882.3529 | J55: =I55*A55 -> 5647.0588 | K55: =F55-J55 -> 4297.9412 | L55: =IFERROR(K55/E55, 0) -> 0.47754902
A56: 1 | B56: BOLSA | C56: BATATA | D56: 16000 | E56: =A56*D56 -> 16000 | F56: =E56*1.105 -> 17680 | I56: 12000 | J56: =I56*A56 -> 12000 | K56: =F56-J56 -> 5680 | L56: =IFERROR(K56/E56, 0) -> 0.355
A57: 3 | B57: KG | C57: BATATA | D57: 1600 | E57: =A57*D57 -> 4800 | F57: =E57*1.105 -> 5304 | I57: =12000/11 -> 1090.9091 | J57: =I57*A57 -> 3272.7273 | K57: =F57-J57 -> 2031.2727 | L57: =IFERROR(K57/E57, 0) -> 0.42318182
A58: 2 | B58: UNIDAD | C58: BROCOLI | D58: 2600 | E58: =A58*D58 -> 5200 | F58: =E58*1.105 -> 5746 | I58: =15000/8 -> 1875 | J58: =I58*A58 -> 3750 | K58: =F58-J58 -> 1996 | L58: =IFERROR(K58/E58, 0) -> 0.38384615
A59: 1 | B59: BOLSA | C59: CALABAZA | D59: 13000 | E59: =A59*D59 -> 13000 | F59: =E59*1.105 -> 14365 | I59: 7000 | J59: =I59*A59 -> 7000 | K59: =F59-J59 -> 7365 | L59: =IFERROR(K59/E59, 0) -> 0.56653846
A60: 3.5 | B60: KG | C60: CEBOLLA MORADA | D60: 1600 | E60: =A60*D60 -> 5600 | F60: =E60*1.105 -> 6188 | I60: 1000 | J60: =I60*A60 -> 3500 | K60: =F60-J60 -> 2688 | L60: =IFERROR(K60/E60, 0) -> 0.48
A61: 3 | B61: KG | C61: CEBOLLA | D61: 800 | E61: =A61*D61 -> 2400 | F61: =E61*1.105 -> 2652 | I61: =10000/15 -> 666.66667 | J61: =I61*A61 -> 2000 | K61: =F61-J61 -> 652 | L61: =IFERROR(K61/E61, 0) -> 0.27166667
A62: 3 | B62: KG | C62: CHAUCHA | D62: 4000 | E62: =A62*D62 -> 12000 | F62: =E62*1.105 -> 13260 | I62: =18000/8 -> 2250 | J62: =I62*A62 -> 6750 | K62: =F62-J62 -> 6510 | L62: =IFERROR(K62/E62, 0) -> 0.5425
A63: 6 | B63: ATADO | C63: ESPINACA | D63: 1700 | E63: =A63*D63 -> 10200 | F63: =E63*1.105 -> 11271 | I63: =1070 -> 1070 | J63: =I63*A63 -> 6420 | K63: =F63-J63 -> 4851 | L63: =IFERROR(K63/E63, 0) -> 0.47558824
A64: 0.5 | B64: CAJON | C64: MANZANA ROJA | D64: 60000 | E64: =A64*D64 -> 30000 | F64: =E64*1.105 -> 33150 | I64: 50000 | J64: =I64*A64 -> 25000 | K64: =F64-J64 -> 8150 | L64: =IFERROR(K64/E64, 0) -> 0.27166667
A65: 0.5 | B65: CAJON | C65: MANZANA VERDE | D65: 72000 | E65: =A65*D65 -> 36000 | F65: =E65*1.105 -> 39780 | I65: 65000 | J65: =I65*A65 -> 32500 | K65: =F65-J65 -> 7280 | L65: =IFERROR(K65/E65, 0) -> 0.20222222
A66: 1.5 | B66: CAJON | C66: NARANJA | D66: 26000 | E66: =A66*D66 -> 39000 | F66: =E66*1.105 -> 43095 | I66: 25000 | J66: =I66*A66 -> 37500 | K66: =F66-J66 -> 5595 | L66: =IFERROR(K66/E66, 0) -> 0.14346154
A67: 3 | B67: BOLSA | C67: PAPA BLANCA | D67: 23000 | E67: =A67*D67 -> 69000 | F67: =E67*1.105 -> 76245 | I67: 17000 | J67: =I67*A67 -> 51000 | K67: =F67-J67 -> 25245 | L67: =IFERROR(K67/E67, 0) -> 0.36586957
A68: 1 | B68: ATADO | C68: CILANTRO | D68: 3000 | E68: =A68*D68 -> 3000 | F68: =E68*1.105 -> 3315 | I68: 2000 | J68: =I68*A68 -> 2000 | K68: =F68-J68 -> 1315 | L68: =IFERROR(K68/E68, 0) -> 0.43833333
A69: 0.3 | B69: KG | C69: PEREJIL | D69: 3500 | E69: =A69*D69 -> 1050 | F69: =E69*1.105 -> 1160.25 | I69: 1500 | J69: =I69*A69 -> 450 | K69: =F69-J69 -> 710.25 | L69: =IFERROR(K69/E69, 0) -> 0.67642857
A70: 0.5 | B70: KG | C70: PEPINO | D70: 1500 | E70: =A70*D70 -> 750 | F70: =E70*1.105 -> 828.75 | I70: =8000/14 -> 571.42857 | J70: =I70*A70 -> 285.71429 | K70: =F70-J70 -> 543.03571 | L70: =IFERROR(K70/E70, 0) -> 0.72404762
A71: 3.5 | B71: KG | C71: MORRON ROJO | D71: 3200 | E71: =A71*D71 -> 11200 | F71: =E71*1.105 -> 12376 | I71: =20000/7 -> 2857.1429 | J71: =I71*A71 -> 10000 | K71: =F71-J71 -> 2376 | L71: =IFERROR(K71/E71, 0) -> 0.21214286
A72: 0.5 | B72: KG | C72: MORRON VERDE | D72: 2400 | E72: =A72*D72 -> 1200 | F72: =E72*1.105 -> 1326 | I72: =12000/7 -> 1714.2857 | J72: =I72*A72 -> 857.14286 | K72: =F72-J72 -> 468.85714 | L72: =IFERROR(K72/E72, 0) -> 0.39071429
A73: 0.5 | B73: KG | C73: MORRON AMARILLO | D73: 2800 | E73: =A73*D73 -> 1400 | F73: =E73*1.105 -> 1547 | I73: =15000/7 -> 2142.8571 | J73: =I73*A73 -> 1071.4286 | K73: =F73-J73 -> 475.57143 | L73: =IFERROR(K73/E73, 0) -> 0.33969388
A74: 5 | B74: KG | C74: POMELO | D74: 3200 | E74: =A74*D74 -> 16000 | F74: =E74*1.105 -> 17680 | I74: =32000/15 -> 2133.3333 | J74: =I74*A74 -> 10666.667 | K74: =F74-J74 -> 7013.3333 | L74: =IFERROR(K74/E74, 0) -> 0.43833333
A75: 1 | B75: KG | C75: REMOLACHA | D75: 2500 | E75: =A75*D75 -> 2500 | F75: =E75*1.105 -> 2762.5 | I75: =14000/9 -> 1555.5556 | J75: =I75*A75 -> 1555.5556 | K75: =F75-J75 -> 1206.9444 | L75: =IFERROR(K75/E75, 0) -> 0.48277778
A76: 2 | B76: KG | C76: REPOLLO BLANCO | D76: 1800 | E76: =A76*D76 -> 3600 | F76: =E76*1.105 -> 3978 | I76: 1000 | J76: =I76*A76 -> 2000 | K76: =F76-J76 -> 1978 | L76: =IFERROR(K76/E76, 0) -> 0.54944444
A77: 1.5 | B77: KG | C77: REPOLLO COLORADO | D77: 1800 | E77: =A77*D77 -> 2700 | F77: =E77*1.105 -> 2983.5 | I77: 1000 | J77: =I77*A77 -> 1500 | K77: =F77-J77 -> 1483.5 | L77: =IFERROR(K77/E77, 0) -> 0.54944444
A78: 11 | B78: KG | C78: TOMATE PERITA | D78: 2400 | E78: =A78*D78 -> 26400 | F78: =E78*1.105 -> 29172 | I78: =25000/15 -> 1666.6667 | J78: =I78*A78 -> 18333.333 | K78: =F78-J78 -> 10838.667 | L78: =IFERROR(K78/E78, 0) -> 0.41055556
A79: 0.8 | B79: KG | C79: TOMATE CHERRY | D79: 3000 | E79: =A79*D79 -> 2400 | F79: =E79*1.105 -> 2652 | I79: =7000/6 -> 1166.6667 | J79: =I79*A79 -> 933.33333 | K79: =F79-J79 -> 1718.6667 | L79: =IFERROR(K79/E79, 0) -> 0.71611111
A80: 1 | B80: BOLSA | C80: ZANAHORIA | D80: 12000 | E80: =A80*D80 -> 12000 | F80: =E80*1.105 -> 13260 | I80: 7000 | J80: =I80*A80 -> 7000 | K80: =F80-J80 -> 6260 | L80: =IFERROR(K80/E80, 0) -> 0.52166667
A81: 4.5 | B81: KG | C81: ZANAHORIA | D81: 1300 | E81: =A81*D81 -> 5850 | F81: =E81*1.105 -> 6464.25 | I81: 1000 | J81: =I81*A81 -> 4500 | K81: =F81-J81 -> 1964.25 | L81: =IFERROR(K81/E81, 0) -> 0.33576923
A82: 3.5 | B82: KG | C82: ZAPALLITO REDONDO | D82: 1400 | E82: =A82*D82 -> 4900 | F82: =E82*1.105 -> 5414.5 | I82: =15000/14 -> 1071.4286 | J82: =I82*A82 -> 3750 | K82: =F82-J82 -> 1664.5 | L82: =IFERROR(K82/E82, 0) -> 0.33969388
A83: 0.5 | B83: KG | C83: BERENJENA | D83: 1500 | E83: =A83*D83 -> 750 | F83: =E83*1.105 -> 828.75 | I83: =32000/17 -> 1882.3529 | J83: =I83*A83 -> 941.17647 | K83: =F83-J83 -> -112.42647 | L83: =IFERROR(K83/E83, 0) -> -0.14990196
A84: 2 | B84: KG | C84: LECHUGA CRIOLLA | D84: 4000 | E84: =A84*D84 -> 8000 | F84: =E84*1.105 -> 8840 | I84: =18000/4 -> 4500 | J84: =I84*A84 -> 9000 | K84: =F84-J84 -> -160 | L84: =IFERROR(K84/E84, 0) -> -0.02
A85: 15 | B85: ATADO | C85: RUCULA | D85: 600 | E85: =A85*D85 -> 9000 | F85: =E85*1.105 -> 9945 | I85: =8000/24 -> 333.33333 | J85: =I85*A85 -> 5000 | K85: =F85-J85 -> 4945 | L85: =IFERROR(K85/E85, 0) -> 0.54944444
A86: 1.5 | B86: KG | C86: ZUCCINI | D86: 1400 | E86: =A86*D86 -> 2100 | F86: =E86*1.105 -> 2320.5 | I86: =12000/14 -> 857.14286 | J86: =I86*A86 -> 1285.7143 | K86: =F86-J86 -> 1034.7857 | L86: =IFERROR(K86/E86, 0) -> 0.4927551
A87: 0.5 | B87: CAJON | C87: HUEVO N1 | D87: 54000 | E87: =A87*D87 -> 27000 | F87: =E87*1.21 -> 32670 | I87: 50000 | J87: =I87*A87 -> 25000 | K87: =F87-J87 -> 7670 | L87: =IFERROR(K87/E87, 0) -> 0.28407407
E89: =SUM(E51:E87) -> 400175 | F89: =SUM(F51:F87) -> 445028.38 | K89: =SUM(K51:K87) -> 139357.27 | L89: =K89/F89 -> 0.31314245
A94: COLEGIO VILLA DEVOTO SCHOOL - PEDRO MORAN 4441 | E94: rto: 18 | F94: 46119 | I94: COMPRA
A96: CANTIDAD | B96: UNIDAD | C96: PRODUCTO | D96: PRECIO | E96: TOTAL | F96: TOTAL + IVA | I96: COSTO | J96: TOTAL | K96: DIFERENCIA
A97: 10.2 | B97: KG | C97: POMELO | D97: 3200 | E97: =A97*D97 -> 32640 | F97: =E97*1.105 -> 36067.2 | I97: =32000/15 -> 2133.3333 | J97: =I97*A97 -> 21760 | K97: =F97-J97 -> 14307.2 | L97: =IFERROR(K97/E97, 0) -> 0.43833333
A98: 2 | B98: CAJON | C98: NARANJA | D98: 26000 | E98: =A98*D98 -> 52000 | F98: =E98*1.105 -> 57460 | I98: 25000 | J98: =I98*A98 -> 50000 | K98: =F98-J98 -> 7460 | L98: =IFERROR(K98/E98, 0) -> 0.14346154
A99: 3 | B99: KG | C99: BANANA | D99: 3000 | E99: =A99*D99 -> 9000 | F99: =E99*1.105 -> 9945 | I99: =32000/17 -> 1882.3529 | J99: =I99*A99 -> 5647.0588 | K99: =F99-J99 -> 4297.9412 | L99: =IFERROR(K99/E99, 0) -> 0.47754902
A100: 10 | B100: KG | C100: MANZANA ROJA | D100: 3600 | E100: =A100*D100 -> 36000 | F100: =E100*1.105 -> 39780 | I100: =50000/17 -> 2941.1765 | J100: =I100*A100 -> 29411.765 | K100: =F100-J100 -> 10368.235 | L100: =IFERROR(K100/E100, 0) -> 0.28800654
A101: 7 | B101: ATADO | C101: ESPINACA | D101: 1700 | E101: =A101*D101 -> 11900 | F101: =E101*1.105 -> 13149.5 | I101: 1070 | J101: =I101*A101 -> 7490 | K101: =F101-J101 -> 5659.5 | L101: =IFERROR(K101/E101, 0) -> 0.47558824
A102: 0.8 | B102: KG | C102: TOMATE CHERRY | D102: 3000 | E102: =A102*D102 -> 2400 | F102: =E102*1.105 -> 2652 | I102: =7000/6 -> 1166.6667 | J102: =I102*A102 -> 933.33333 | K102: =F102-J102 -> 1718.6667 | L102: =IFERROR(K102/E102, 0) -> 0.71611111
A103: 1 | B103: KG | C103: CEBOLLA MORADA | D103: 1600 | E103: =A103*D103 -> 1600 | F103: =E103*1.105 -> 1768 | I103: 1000 | J103: =I103*A103 -> 1000 | K103: =F103-J103 -> 768 | L103: =IFERROR(K103/E103, 0) -> 0.48
A104: 1 | B104: KG | C104: CEBOLLA | D104: 800 | E104: =A104*D104 -> 800 | F104: =E104*1.105 -> 884 | I104: =10000/15 -> 666.66667 | J104: =I104*A104 -> 666.66667 | K104: =F104-J104 -> 217.33333 | L104: =IFERROR(K104/E104, 0) -> 0.27166667
A105: 2 | B105: BOLSA | C105: ZANAHORIA | D105: 12000 | E105: =A105*D105 -> 24000 | F105: =E105*1.105 -> 26520 | I105: 7000 | J105: =I105*A105 -> 14000 | K105: =F105-J105 -> 12520 | L105: =IFERROR(K105/E105, 0) -> 0.52166667
A106: 4 | B106: KG | C106: ZAPALLITO REDONDO | D106: 1400 | E106: =A106*D106 -> 5600 | F106: =E106*1.105 -> 6188 | I106: =15000/14 -> 1071.4286 | J106: =I106*A106 -> 4285.7143 | K106: =F106-J106 -> 1902.2857 | L106: =IFERROR(K106/E106, 0) -> 0.33969388
A107: 2 | B107: KG | C107: ZUCCINI | D107: 1400 | E107: =A107*D107 -> 2800 | F107: =E107*1.105 -> 3094 | I107: =12000/14 -> 857.14286 | J107: =I107*A107 -> 1714.2857 | K107: =F107-J107 -> 1379.7143 | L107: =IFERROR(K107/E107, 0) -> 0.4927551
A108: 2 | B108: KG | C108: BERENJENA | D108: 1500 | E108: =A108*D108 -> 3000 | F108: =E108*1.105 -> 3315 | I108: =10000/8 -> 1250 | J108: =I108*A108 -> 2500 | K108: =F108-J108 -> 815 | L108: =IFERROR(K108/E108, 0) -> 0.27166667
A109: 14 | B109: KG | C109: TOMATE PERITA | D109: 2400 | E109: =A109*D109 -> 33600 | F109: =E109*1.105 -> 37128 | I109: =25000/15 -> 1666.6667 | J109: =I109*A109 -> 23333.333 | K109: =F109-J109 -> 13794.667 | L109: =IFERROR(K109/E109, 0) -> 0.41055556
A110: 0.2 | B110: KG | C110: APIO | D110: 2500 | E110: =A110*D110 -> 500 | F110: =E110*1.105 -> 552.5 | I110: =9000/8 -> 1125 | J110: =I110*A110 -> 225 | K110: =F110-J110 -> 327.5 | L110: =IFERROR(K110/E110, 0) -> 0.655
A111: 2 | B111: KG | C111: REPOLLO BLANCO | D111: 1800 | E111: =A111*D111 -> 3600 | F111: =E111*1.105 -> 3978 | I111: 1000 | J111: =I111*A111 -> 2000 | K111: =F111-J111 -> 1978 | L111: =IFERROR(K111/E111, 0) -> 0.54944444
A112: 2.2 | B112: KG | C112: REPOLLO COLORADO | D112: 1800 | E112: =A112*D112 -> 3960 | F112: =E112*1.105 -> 4375.8 | I112: 1000 | J112: =I112*A112 -> 2200 | K112: =F112-J112 -> 2175.8 | L112: =IFERROR(K112/E112, 0) -> 0.54944444
A113: 1 | B113: ATADO | C113: CIBOULETTE | D113: 3000 | E113: =A113*D113 -> 3000 | F113: =E113*1.105 -> 3315 | I113: 2000 | J113: =I113*A113 -> 2000 | K113: =F113-J113 -> 1315 | L113: =IFERROR(K113/E113, 0) -> 0.43833333
...

Sheet 08-04-2026 
A3: COLEGIO SAN MARCOS | SAN ISIDRO | E3: rto: 13 | F3: 46120 | I3: COMPRA
A5: CANTIDAD | B5: UNIDAD | C5: PRODUCTO | D5: PRECIO | E5: TOTAL | F5: TOTAL + IVA | I5: COSTO | J5: TOTAL | K5: DIFERENCIA
A6: 1 | B6: CAJON | C6: TOMATE PERITA | D6: 36000 | E6: =A6*D6 -> 36000 | F6: =E6*1.105 -> 39780 | I6: 22000 | J6: =I6*A6 -> 22000 | K6: =F6-J6 -> 17780 | L6: =IFERROR(K6/E6, 0) -> 0.49388889
A7: 1 | B7: CAJON | C7: LECHUGA CRIOLLA | D7: 20000 | E7: =A7*D7 -> 20000 | F7: =E7*1.105 -> 22100 | I7: 17000 | J7: =I7*A7 -> 17000 | K7: =F7-J7 -> 5100 | L7: =IFERROR(K7/E7, 0) -> 0.255
A8: 1 | B8: CAJON | C8: RUCULA | D8: 13000 | E8: =A8*D8 -> 13000 | F8: =E8*1.105 -> 14365 | I8: 10000 | J8: =I8*A8 -> 10000 | K8: =F8-J8 -> 4365 | L8: =IFERROR(K8/E8, 0) -> 0.33576923
A9: 3 | B9: BOLSA | C9: PAPA BLANCA | D9: 25000 | E9: =A9*D9 -> 75000 | F9: =E9*1.105 -> 82875 | I9: 20000 | J9: =I9*A9 -> 60000 | K9: =F9-J9 -> 22875 | L9: =IFERROR(K9/E9, 0) -> 0.305
A10: 4.2 | B10: KG | C10: REPOLLO BLANCO | D10: 1800 | E10: =A10*D10 -> 7560 | F10: =E10*1.105 -> 8353.8 | I10: 1000 | J10: =I10*A10 -> 4200 | K10: =F10-J10 -> 4153.8 | L10: =IFERROR(K10/E10, 0) -> 0.54944444
A11: 3.45 | B11: KG | C11: REPOLLO COLORADO | D11: 1800 | E11: =A11*D11 -> 6210 | F11: =E11*1.105 -> 6862.05 | I11: 1000 | J11: =I11*A11 -> 3450 | K11: =F11-J11 -> 3412.05 | L11: =IFERROR(K11/E11, 0) -> 0.54944444
A12: 2 | B12: KG | C12: ZAPALLITO REDONDO | D12: 1400 | E12: =A12*D12 -> 2800 | F12: =E12*1.105 -> 3094 | I12: =15000/14 -> 1071.4286 | J12: =I12*A12 -> 2142.8571 | K12: =F12-J12 -> 951.14286 | L12: =IFERROR(K12/E12, 0) -> 0.33969388
A13: 3 | B13: KG | C13: MORRON ROJO | D13: 3200 | E13: =A13*D13 -> 9600 | F13: =E13*1.105 -> 10608 | I13: =14000/7 -> 2000 | J13: =I13*A13 -> 6000 | K13: =F13-J13 -> 4608 | L13: =IFERROR(K13/E13, 0) -> 0.48
A14: 2 | B14: KG | C14: MORRON VERDE | D14: 2400 | E14: =A14*D14 -> 4800 | F14: =E14*1.105 -> 5304 | I14: =13000/7 -> 1857.1429 | J14: =I14*A14 -> 3714.2857 | K14: =F14-J14 -> 1589.7143 | L14: =IFERROR(K14/E14, 0) -> 0.33119048
A15: 2 | B15: KG | C15: MORRON AMARILLO | D15: 2800 | E15: =A15*D15 -> 5600 | F15: =E15*1.105 -> 6188 | I15: =15000/7 -> 2142.8571 | J15: =I15*A15 -> 4285.7143 | K15: =F15-J15 -> 1902.2857 | L15: =IFERROR(K15/E15, 0) -> 0.33969388
A16: 1 | B16: KG | C16: BERENJENA | D16: 2000 | E16: =A16*D16 -> 2000 | F16: =E16*1.105 -> 2210 | I16: =10000/7 -> 1428.5714 | J16: =I16*A16 -> 1428.5714 | K16: =F16-J16 -> 781.42857 | L16: =IFERROR(K16/E16, 0) -> 0.39071429
A17: 1 | B17: ATADO | C17: CEBOLLA DE VERDEO | D17: 4500 | E17: =A17*D17 -> 4500 | F17: =E17*1.105 -> 4972.5 | I17: 2000 | J17: =I17*A17 -> 2000 | K17: =F17-J17 -> 2972.5 | L17: =IFERROR(K17/E17, 0) -> 0.66055556
A18: 3 | B18: UNIDAD | C18: PALTA | D18: 1600 | E18: =A18*D18 -> 4800 | F18: =E18*1.105 -> 5304 | I18: =85000/70 -> 1214.2857 | J18: =I18*A18 -> 3642.8571 | K18: =F18-J18 -> 1661.1429 | L18: =IFERROR(K18/E18, 0) -> 0.34607143
A19: 1 | B19: ATADO | C19: CILANTRO | D19: 3000 | E19: =A19*D19 -> 3000 | F19: =E19*1.105 -> 3315 | I19: 2000 | J19: =I19*A19 -> 2000 | K19: =F19-J19 -> 1315 | L19: =IFERROR(K19/E19, 0) -> 0.43833333
A20: 2 | B20: ATADO | C20: PEREJIL | D20: 3500 | E20: =A20*D20 -> 7000 | F20: =E20*1.105 -> 7735 | I20: 1500 | J20: =I20*A20 -> 3000 | K20: =F20-J20 -> 4735 | L20: =IFERROR(K20/E20, 0) -> 0.67642857
A21: 2 | B21: UNIDAD | C21: AJO | D21: 900 | E21: =A21*D21 -> 1800 | F21: =E21*1.105 -> 1989 | I21: 460 | J21: =I21*A21 -> 920 | K21: =F21-J21 -> 1069 | L21: =IFERROR(K21/E21, 0) -> 0.59388889
A22: 0.5 | B22: KG | C22: PEPINO | D22: 1500 | E22: =A22*D22 -> 750 | F22: =E22*1.105 -> 828.75 | I22: =8000/14 -> 571.42857 | J22: =I22*A22 -> 285.71429 | K22: =F22-J22 -> 543.03571 | L22: =IFERROR(K22/E22, 0) -> 0.72404762
A23: 2 | B23: KG | C23: ZUCCINI | D23: 1400 | E23: =A23*D23 -> 2800 | F23: =E23*1.105 -> 3094 | I23: =12000/14 -> 857.14286 | J23: =I23*A23 -> 1714.2857 | K23: =F23-J23 -> 1379.7143 | L23: =IFERROR(K23/E23, 0) -> 0.4927551
A24: 6 | B24: KG | C24: CEBOLLA | D24: 1200 | E24: =A24*D24 -> 7200 | F24: =E24*1.105 -> 7956 | I24: =12000/15 -> 800 | J24: =I24*A24 -> 4800 | K24: =F24-J24 -> 3156 | L24: =IFERROR(K24/E24, 0) -> 0.43833333
A25: 3 | B25: KG | C25: CEBOLLA MORADA | D25: 1600 | E25: =A25*D25 -> 4800 | F25: =E25*1.105 -> 5304 | I25: 1000 | J25: =I25*A25 -> 3000 | K25: =F25-J25 -> 2304 | L25: =IFERROR(K25/E25, 0) -> 0.48
A26: 1 | B26: ATADO | C26: ALBAHACA | D26: 1500 | E26: =A26*D26 -> 1500 | F26: =E26*1.105 -> 1657.5 | I26: 1000 | J26: =I26*A26 -> 1000 | K26: =F26-J26 -> 657.5 | L26: =IFERROR(K26/E26, 0) -> 0.43833333
A27: 5 | B27: UNIDAD | C27: BROCOLI | D27: 3000 | E27: =A27*D27 -> 15000 | F27: =E27*1.105 -> 16575 | I27: =18000/8 -> 2250 | J27: =I27*A27 -> 11250 | K27: =F27-J27 -> 5325 | L27: =IFERROR(K27/E27, 0) -> 0.355
A28: 1 | B28: CAJON | C28: MANZANA ROJA | D28: 60000 | E28: =A28*D28 -> 60000 | F28: =E28*1.105 -> 66300 | I28: 50000 | J28: =I28*A28 -> 50000 | K28: =F28-J28 -> 16300 | L28: =IFERROR(K28/E28, 0) -> 0.27166667
A29: 1 | B29: CAJON | C29: MANZANA VERDE | D29: 72000 | E29: =A29*D29 -> 72000 | F29: =E29*1.105 -> 79560 | I29: 65000 | J29: =I29*A29 -> 65000 | K29: =F29-J29 -> 14560 | L29: =IFERROR(K29/E29, 0) -> 0.20222222
A30: 2 | B30: CAJON | C30: NARANJA | D30: 28000 | E30: =A30*D30 -> 56000 | F30: =E30*1.105 -> 61880 | I30: 24000 | J30: =I30*A30 -> 48000 | K30: =F30-J30 -> 13880 | L30: =IFERROR(K30/E30, 0) -> 0.24785714
A31: 10 | B31: KG | C31: PERA | D31: 3000 | E31: =A31*D31 -> 30000 | F31: =E31*1.105 -> 33150 | I31: =20000/9 -> 2222.2222 | J31: =I31*A31 -> 22222.222 | K31: =F31-J31 -> 10927.778 | L31: =IFERROR(K31/E31, 0) -> 0.36425926
A32: 15.4 | B32: KG | C32: BANANA | D32: 3000 | E32: =A32*D32 -> 46200 | F32: =E32*1.105 -> 51051 | I32: =36000/17 -> 2117.6471 | J32: =I32*A32 -> 32611.765 | K32: =F32-J32 -> 18439.235 | L32: =IFERROR(K32/E32, 0) -> 0.39911765
A33: 4 | B33: KG | C33: POMELO | D33: 3200 | E33: =A33*D33 -> 12800 | F33: =E33*1.105 -> 14144 | I33: =32000/15 -> 2133.3333 | J33: =I33*A33 -> 8533.3333 | K33: =F33-J33 -> 5610.6667 | L33: =IFERROR(K33/E33, 0) -> 0.43833333
A34: 0.5 | B34: CAJON | C34: HUEVO N1 | D34: 54000 | E34: =A34*D34 -> 27000 | F34: =E34*1.21 -> 32670 | I34: 50000 | J34: =I34*A34 -> 25000 | K34: =F34-J34 -> 7670 | L34: =IFERROR(K34/E34, 0) -> 0.28407407
E36: =SUM(E6:E34) -> 539720 | F36: =SUM(F6:F34) -> 599225.6 | K36: =SUM(K6:K34) -> 180023.99 | L36: =K36/F36 -> 0.30042774
A42: COLEGIO SWORM JUNIOR COLLAGE | PACHECO | E42: rto: 12 | F42: 46120 | I42: COMPRA
A44: CANTIDAD | B44: UNIDAD | C44: PRODUCTO | D44: PRECIO | E44: TOTAL | F44: TOTAL + IVA | I44: COSTO | J44: TOTAL | K44: DIFERENCIA
A45: 10 | B45: KG | C45: TOMATE PERITA | D45: 2400 | E45: =A45*D45 -> 24000 | F45: =E45*1.105 -> 26520 | I45: =22000/15 -> 1466.6667 | J45: =I45*A45 -> 14666.667 | K45: =F45-J45 -> 11853.333 | L45: =IFERROR(K45/E45, 0) -> 0.49388889
A46: 6 | B46: ATADO | C46: ESPINACA | D46: 1700 | E46: =A46*D46 -> 10200 | F46: =E46*1.105 -> 11271 | I46: =13000/12 -> 1083.3333 | J46: =I46*A46 -> 6500 | K46: =F46-J46 -> 4771 | L46: =IFERROR(K46/E46, 0) -> 0.4677451
A47: 2 | B47: UNIDAD | C47: BROCOLI | D47: 3000 | E47: =A47*D47 -> 6000 | F47: =E47*1.105 -> 6630 | I47: =18000/8 -> 2250 | J47: =I47*A47 -> 4500 | K47: =F47-J47 -> 2130 | L47: =IFERROR(K47/E47, 0) -> 0.355
A48: 1.5 | B48: KG | C48: MORRON ROJO | D48: 3200 | E48: =A48*D48 -> 4800 | F48: =E48*1.105 -> 5304 | I48: =14000/7 -> 2000 | J48: =I48*A48 -> 3000 | K48: =F48-J48 -> 2304 | L48: =IFERROR(K48/E48, 0) -> 0.48
A49: 10 | B49: ATADO | C49: RUCULA | D49: 600 | E49: =A49*D49 -> 6000 | F49: =E49*1.105 -> 6630 | I49: =10000/24 -> 416.66667 | J49: =I49*A49 -> 4166.6667 | K49: =F49-J49 -> 2463.3333 | L49: =IFERROR(K49/E49, 0) -> 0.41055556
A50: 3 | B50: KG | C50: ZAPALLITO REDONDO | D50: 1400 | E50: =A50*D50 -> 4200 | F50: =E50*1.105 -> 4641 | I50: =15000/14 -> 1071.4286 | J50: =I50*A50 -> 3214.2857 | K50: =F50-J50 -> 1426.7143 | L50: =IFERROR(K50/E50, 0) -> 0.33969388
A51: 1 | B51: KG | C51: ZUCCINI | D51: 1400 | E51: =A51*D51 -> 1400 | F51: =E51*1.105 -> 1547 | I51: =12000/14 -> 857.14286 | J51: =I51*A51 -> 857.14286 | K51: =F51-J51 -> 689.85714 | L51: =IFERROR(K51/E51, 0) -> 0.4927551
A52: 3 | B52: KG | C52: CEBOLLA MORADA | D52: 1600 | E52: =A52*D52 -> 4800 | F52: =E52*1.105 -> 5304 | I52: 1000 | J52: =I52*A52 -> 3000 | K52: =F52-J52 -> 2304 | L52: =IFERROR(K52/E52, 0) -> 0.48
A53: 1 | B53: KG | C53: CEBOLLA | D53: 1200 | E53: =A53*D53 -> 1200 | F53: =E53*1.105 -> 1326 | I53: 800 | J53: =I53*A53 -> 800 | K53: =F53-J53 -> 526 | L53: =IFERROR(K53/E53, 0) -> 0.43833333
A54: 2 | B54: UNIDAD | C54: APIO | D54: 2500 | E54: =A54*D54 -> 5000 | F54: =E54*1.105 -> 5525 | I54: =9000/8 -> 1125 | J54: =I54*A54 -> 2250 | K54: =F54-J54 -> 3275 | L54: =IFERROR(K54/E54, 0) -> 0.655
A55: 1 | B55: KG | C55: BERENJENA | D55: 2000 | E55: =A55*D55 -> 2000 | F55: =E55*1.105 -> 2210 | I55: =10000/7 -> 1428.5714 | J55: =I55*A55 -> 1428.5714 | K55: =F55-J55 -> 781.42857 | L55: =IFERROR(K55/E55, 0) -> 0.39071429
A56: 3 | B56: BOLSA | C56: PAPA BLANCA | D56: 25000 | E56: =A56*D56 -> 75000 | F56: =E56*1.105 -> 82875 | I56: 20000 | J56: =I56*A56 -> 60000 | K56: =F56-J56 -> 22875 | L56: =IFERROR(K56/E56, 0) -> 0.305
A57: 3 | B57: KG | C57: BANANA | D57: 3000 | E57: =A57*D57 -> 9000 | F57: =E57*1.105 -> 9945 | I57: =36000/17 -> 2117.6471 | J57: =I57*A57 -> 6352.9412 | K57: =F57-J57 -> 3592.0588 | L57: =IFERROR(K57/E57, 0) -> 0.39911765
A58: 3 | B58: KG | C58: MANZANA VERDE | D58: 4500 | E58: =A58*D58 -> 13500 | F58: =E58*1.105 -> 14917.5 | I58: =65000/17 -> 3823.5294 | J58: =I58*A58 -> 11470.588 | K58: =F58-J58 -> 3446.9118 | L58: =IFERROR(K58/E58, 0) -> 0.2553268
A59: 3 | B59: KG | C59: MANZANA ROJA | D59: 3600 | E59: =A59*D59 -> 10800 | F59: =E59*1.105 -> 11934 | I59: =50000/17 -> 2941.1765 | J59: =I59*A59 -> 8823.5294 | K59: =F59-J59 -> 3110.4706 | L59: =IFERROR(K59/E59, 0) -> 0.28800654
E61: =SUM(E45:E59) -> 177900 | F61: =SUM(F45:F59) -> 196579.5 | K61: =SUM(K45:K59) -> 65549.108 | L61: =K61/F61 -> 0.33344834
A66: COLEGIO ST. MATTHEWS | CAAMAÑO | E66: rto: 13 | F66: 46120 | I66: COMPRA
A68: CANTIDAD | B68: UNIDAD | C68: PRODUCTO | D68: PRECIO | E68: TOTAL | F68: TOTAL + IVA | I68: COSTO | J68: TOTAL | K68: DIFERENCIA
A69: 6 | B69: KG | C69: TOMATE PERITA | D69: 2400 | E69: =A69*D69 -> 14400 | F69: =E69*1.105 -> 15912 | I69: =22000/14 -> 1571.4286 | J69: =I69*A69 -> 9428.5714 | K69: =F69-J69 -> 6483.4286 | L69: =IFERROR(K69/E69, 0) -> 0.4502381
A70: 0.5 | B70: ATADO | C70: PEREJIL | D70: 3500 | E70: =A70*D70 -> 1750 | F70: =E70*1.105 -> 1933.75 | I70: 1500 | J70: =I70*A70 -> 750 | K70: =F70-J70 -> 1183.75 | L70: =IFERROR(K70/E70, 0) -> 0.67642857
A71: 1.3 | B71: UNIDAD | C71: REPOLLO BLANCO | D71: 1800 | E71: =A71*D71 -> 2340 | F71: =E71*1.105 -> 2585.7 | I71: 1000 | J71: =I71*A71 -> 1300 | K71: =F71-J71 -> 1285.7 | L71: =IFERROR(K71/E71, 0) -> 0.54944444
A72: 1.2 | B72: UNIDAD | C72: REPOLLO COLORADO | D72: 1800 | E72: =A72*D72 -> 2160 | F72: =E72*1.105 -> 2386.8 | I72: 1000 | J72: =I72*A72 -> 1200 | K72: =F72-J72 -> 1186.8 | L72: =IFERROR(K72/E72, 0) -> 0.54944444
A73: 1 | B73: BOLSA | C73: ZANAHORIA | D73: 12000 | E73: =A73*D73 -> 12000 | F73: =E73*1.105 -> 13260 | I73: 7000 | J73: =I73*A73 -> 7000 | K73: =F73-J73 -> 6260 | L73: =IFERROR(K73/E73, 0) -> 0.52166667
A74: 4 | B74: KG | C74: LECHUGA CRIOLLA | D74: 5000 | E74: =A74*D74 -> 20000 | F74: =E74*1.105 -> 22100 | I74: =17000/4 -> 4250 | J74: =I74*A74 -> 17000 | K74: =F74-J74 -> 5100 | L74: =IFERROR(K74/E74, 0) -> 0.255
A75: 16 | B75: ATADO | C75: RUCULA | D75: 600 | E75: =A75*D75 -> 9600 | F75: =E75*1.105 -> 10608 | I75: =10000/24 -> 416.66667 | J75: =I75*A75 -> 6666.6667 | K75: =F75-J75 -> 3941.3333 | L75: =IFERROR(K75/E75, 0) -> 0.41055556
A76: 0.5 | B76: KG | C76: REMOLACHA | D76: 2500 | E76: =A76*D76 -> 1250 | F76: =E76*1.105 -> 1381.25 | I76: =14000/9 -> 1555.5556 | J76: =I76*A76 -> 777.77778 | K76: =F76-J76 -> 603.47222 | L76: =IFERROR(K76/E76, 0) -> 0.48277778
A77: 1 | B77: BOLSA | C77: CALABAZA | D77: 13000 | E77: =A77*D77 -> 13000 | F77: =E77*1.105 -> 14365 | I77: 8000 | J77: =I77*A77 -> 8000 | K77: =F77-J77 -> 6365 | L77: =IFERROR(K77/E77, 0) -> 0.48961538
A78: 4 | B78: BOLSA | C78: PAPA BLANCA | D78: 25000 | E78: =A78*D78 -> 100000 | F78: =E78*1.105 -> 110500 | I78: 20000 | J78: =I78*A78 -> 80000 | K78: =F78-J78 -> 30500 | L78: =IFERROR(K78/E78, 0) -> 0.305
A79: 5 | B79: KG | C79: MANZANA VERDE | D79: 4500 | E79: =A79*D79 -> 22500 | F79: =E79*1.105 -> 24862.5 | I79: =65000/17 -> 3823.5294 | J79: =I79*A79 -> 19117.647 | K79: =F79-J79 -> 5744.8529 | L79: =IFERROR(K79/E79, 0) -> 0.2553268
A80: 8 | B80: KG | C80: MANZANA ROJA | D80: 3600 | E80: =A80*D80 -> 28800 | F80: =E80*1.105 -> 31824 | I80: =50000/17 -> 2941.1765 | J80: =I80*A80 -> 23529.412 | K80: =F80-J80 -> 8294.5882 | L80: =IFERROR(K80/E80, 0) -> 0.28800654
A81: 1 | B81: CAJON | C81: NARANJA | D81: 28000 | E81: =A81*D81 -> 28000 | F81: =E81*1.105 -> 30940 | I81: 24000 | J81: =I81*A81 -> 24000 | K81: =F81-J81 -> 6940 | L81: =IFERROR(K81/E81, 0) -> 0.24785714
A82: 3 | B82: KG | C82: BANANA | D82: 3000 | E82: =A82*D82 -> 9000 | F82: =E82*1.105 -> 9945 | I82: =36000/17 -> 2117.6471 | J82: =I82*A82 -> 6352.9412 | K82: =F82-J82 -> 3592.0588 | L82: =IFERROR(K82/E82, 0) -> 0.39911765
A83: 3 | B83: KG | C83: POMELO | D83: 3200 | E83: =A83*D83 -> 9600 | F83: =E83*1.105 -> 10608 | I83: =32000/15 -> 2133.3333 | J83: =I83*A83 -> 6400 | K83: =F83-J83 -> 4208 | L83: =IFERROR(K83/E83, 0) -> 0.43833333
A84: 2 | B84: KG | C84: MORRON ROJO | D84: 3200 | E84: =A84*D84 -> 6400 | F84: =E84*1.105 -> 7072 | I84: =14000/7 -> 2000 | J84: =I84*A84 -> 4000 | K84: =F84-J84 -> 3072 | L84: =IFERROR(K84/E84, 0) -> 0.48
A85: 1 | B85: KG | C85: MORRON AMARILLO | D85: 2800 | E85: =A85*D85 -> 2800 | F85: =E85*1.105 -> 3094 | I85: =15000/7 -> 2142.8571 | J85: =I85*A85 -> 2142.8571 | K85: =F85-J85 -> 951.14286 | L85: =IFERROR(K85/E85, 0) -> 0.33969388
A86: 1 | B86: KG | C86: MORRON VERDE | D86: 2400 | E86: =A86*D86 -> 2400 | F86: =E86*1.105 -> 2652 | I86: =13000/7 -> 1857.1429 | J86: =I86*A86 -> 1857.1429 | K86: =F86-J86 -> 794.85714 | L86: =IFERROR(K86/E86, 0) -> 0.33119048
A87: 1 | B87: KG | C87: CEBOLLA | D87: 1200 | E87: =A87*D87 -> 1200 | F87: =E87*1.105 -> 1326 | I87: 800 | J87: =I87*A87 -> 800 | K87: =F87-J87 -> 526 | L87: =IFERROR(K87/E87, 0) -> 0.43833333
A88: 1 | B88: KG | C88: CEBOLLA MORADA | D88: 1600 | E88: =A88*D88 -> 1600 | F88: =E88*1.105 -> 1768 | I88: 1000 | J88: =I88*A88 -> 1000 | K88: =F88-J88 -> 768 | L88: =IFERROR(K88/E88, 0) -> 0.48
A89: 0.5 | B89: KG | C89: PEPINO | D89: 1500 | E89: =A89*D89 -> 750 | F89: =E89*1.105 -> 828.75 | I89: =8000/14 -> 571.42857 | J89: =I89*A89 -> 285.71429 | K89: =F89-J89 -> 543.03571 | L89: =IFERROR(K89/E89, 0) -> 0.72404762
A90: 1 | B90: KG | C90: ZUCCINI | D90: 1400 | E90: =A90*D90 -> 1400 | F90: =E90*1.105 -> 1547 | I90: =12000/14 -> 857.14286 | J90: =I90*A90 -> 857.14286 | K90: =F90-J90 -> 689.85714 | L90: =IFERROR(K90/E90, 0) -> 0.4927551
A91: 1 | B91: UNIDAD | C91: BROCOLI | D91: 3000 | E91: =A91*D91 -> 3000 | F91: =E91*1.105 -> 3315 | I91: =18000/8 -> 2250 | J91: =I91*A91 -> 2250 | K91: =F91-J91 -> 1065 | L91: =IFERROR(K91/E91, 0) -> 0.355
A92: 2 | B92: KG | C92: ZAPALLITO REDONDO | D92: 1400 | E92: =A92*D92 -> 2800 | F92: =E92*1.105 -> 3094 | I92: =15000/14 -> 1071.4286 | J92: =I92*A92 -> 2142.8571 | K92: =F92-J92 -> 951.14286 | L92: =IFERROR(K92/E92, 0) -> 0.33969388
A93: 0.5 | B93: KG | C93: BERENJENA | D93: 2000 | E93: =A93*D93 -> 1000 | F93: =E93*1.105 -> 1105 | I93: =10000/7 -> 1428.5714 | J93: =I93*A93 -> 714.28571 | K93: =F93-J93 -> 390.71429 | L93: =IFERROR(K93/E93, 0) -> 0.39071429
A94: 1 | B94: ATADO | C94: CILANTRO | D94: 3000 | E94: =A94*D94 -> 3000 | F94: =E94*1.105 -> 3315 | I94: 2000 | J94: =I94*A94 -> 2000 | K94: =F94-J94 -> 1315 | L94: =IFERROR(K94/E94, 0) -> 0.43833333
A95: 1 | B95: ATADO | C95: CIBOULETTE | D95: 3000 | E95: =A95*D95 -> 3000 | F95: =E95*1.105 -> 3315 | I95: 2000 | J95: =I95*A95 -> 2000 | K95: =F95-J95 -> 1315 | L95: =IFERROR(K95/E95, 0) -> 0.43833333
A96: 1 | B96: ATADO | C96: ALBAHACA | D96: 1500 | E96: =A96*D96 -> 1500 | F96: =E96*1.105 -> 1657.5 | I96: 1000 | J96: =I96*A96 -> 1000 | K96: =F96-J96 -> 657.5 | L96: =IFERROR(K96/E96, 0) -> 0.43833333
E98: =SUM(E69:E96) -> 305250 | F98: =SUM(F69:F96) -> 337301.25 | K98: =SUM(K69:K96) -> 104728.23 | L98: =K98/F98 -> 0.31048872
A102: COLEGIO ST. MATTHEWS | CAAMAÑO | E102: rto: 14 | F102: 46120 | I102: COMPRA
A104: CANTIDAD | B104: UNIDAD | C104: PRODUCTO | D104: PRECIO | E104: TOTAL | F104: TOTAL + IVA | I104: COSTO | J104: TOTAL | K104: DIFERENCIA
A105: 2 | B105: KG | C105: PEPINO | D105: 1500 | E105: =A105*D105 -> 3000 | F105: =E105*1.105 -> 3315 | I105: =8000/14 -> 571.42857 | J105: =I105*A105 -> 1142.8571 | K105: =F105-J105 -> 2172.1429 | L105: =IFERROR(K105/E105, 0) -> 0.72404762
A106: 3 | B106: KG | C106: CEBOLLA | D106: 1200 | E106: =A106*D106 -> 3600 | F106: =E106*1.105 -> 3978 | I106: 800 | J106: =I106*A106 -> 2400 | K106: =F106-J106 -> 1578 | L106: =IFERROR(K106/E106, 0) -> 0.43833333
A107: 1 | B107: KG | C107: CEBOLLA MORADA | D107: 1600 | E107: =A107*D107 -> 1600 | F107: =E107*1.105 -> 1768 | I107: 1000 | J107: =I107*A107 -> 1000 | K107: =F107-J107 -> 768 | L107: =IFERROR(K107/E107, 0) -> 0.48
A108: 5.1 | B108: UNIDAD | C108: MORRON ROJO | D108: 3200 | E108: =A108*D108 -> 16320 | F108: =E108*1.105 -> 18033.6 | I108: 2000 | J108: =I108*A108 -> 10200 | K108: =F108-J108 -> 7833.6 | L108: =IFERROR(K108/E108, 0) -> 0.48
A109: 3.7 | B109: UNIDAD | C109: MORRON AMARILLO | D109: 2800 | E109: =A109*D109 -> 10360 | F109: =E109*1.105 -> 11447.8 | I109: =15000/7 -> 2142.8571 | J109: =I109*A109 -> 7928.5714 | K109: =F109-J109 -> 3519.2286 | L109: =IFERROR(K109/E109, 0) -> 0.33969388
A110: 4 | B110: KG | C110: LECHUGA CRIOLLA | D110: 5000 | E110: =A110*D110 -> 20000 | F110: =E110*1.105 -> 22100 | I110: =17000/4 -> 4250 | J110: =I110*A110 -> 17000 | K110: =F110-J110 -> 5100 | L110: =IFERROR(K110/E110, 0) -> 0.255
A111: 13 | B111: KG | C111: TOMATE PERITA | D111: 2400 | E111: =A111*D111 -> 31200 | F111: =E111*1.105 -> 34476 | I111: =22000/15 -> 1466.6667 | J111: =I111*A111 -> 19066.667 | K111: =F111-J111 -> 15409.333 | L111: =IFERROR(K111/E111, 0) -> 0.49388889
E113: =SUM(E105:E111) -> 86080 | F113: =SUM(F105:F111) -> 95118.4 | K113: =SUM(K105:K111) -> 36380.305 | L113: =K113/F113 -> 0.38247389
A117: COLEGIO BRICK TOWERS | DEL VISO | E117: rto: 14 | F117: 46120 | I117: COMPRA
A119: CANTIDAD | B119: UNIDAD | C119: PRODUCTO | D119: PRECIO | E119: TOTAL | F119: TOTAL + IVA | I119: COSTO | J119: TOTAL | K119: DIFERENCIA
A120: 2 | B120: BOLSA | C120: PAPA BLANCA | D120: 25000 | E120: =A120*D120 -> 50000 | F120: =E120*1.105 -> 55250 | I120: 20000 | J120: =I120*A120 -> 40000 | K120: =F120-J120 -> 15250 | L120: =IFERROR(K120/E120, 0) -> 0.305
A121: 1 | B121: BOLSA | C121: CALABAZA | D121: 13000 | E121: =A121*D121 -> 13000 | F121: =E121*1.105 -> 14365 | I121: 8000 | J121: =I121*A121 -> 8000 | K121: =F121-J121 -> 6365 | L121: =IFERROR(K121/E121, 0) -> 0.48961538
A122: 1 | B122: BOLSA | C122: ZANAHORIA | D122: 12000 | E122: =A122*D122 -> 12000 | F122: =E122*1.105 -> 13260 | I122: 7000 | J122: =I122*A122 -> 7000 | K122: =F122-J122 -> 6260 | L122: =IFERROR(K122/E122, 0) -> 0.52166667
A123: 2 | B123: UNIDAD | C123: BROCOLI | D123: 3000 | E123: =A123*D123 -> 6000 | F123: =E123*1.105 -> 6630 | I123: =18000/8 -> 2250 | J123: =I123*A123 -> 4500 | K123: =F123-J123 -> 2130 | L123: =IFERROR(K123/E123, 0) -> 0.355
A124: 12 | B124: ATADO | C124: ESPINACA | D124: 1700 | E124: =A124*D124 -> 20400 | F124: =E124*1.105 -> 22542 | I124: =13000/12 -> 1083.3333 | J124: =I124*A124 -> 13000 | K124: =F124-J124 -> 9542 | L124: =IFERROR(K124/E124, 0) -> 0.4677451
A125: 1 | B125: ATADO | C125: CEBOLLA DE VERDEO | D125: 4500 | E125: =A125*D125 -> 4500 | F125: =E125*1.105 -> 4972.5 | I125: 2000 | J125: =I125*A125 -> 2000 | K125: =F125-J125 -> 2972.5 | L125: =IFERROR(K125/E125, 0) -> 0.66055556
A126: 1 | B126: ATADO | C126: PUERRO | D126: 5000 | E126: =A126*D126 -> 5000 | F126: =E126*1.105 -> 5525 | I126: 2500 | J126: =I126*A126 -> 2500 | K126: =F126-J126 -> 3025 | L126: =IFERROR(K126/E126, 0) -> 0.605
...

Sheet 09-04-2026 
A3: COLCAR | E3: rto: 16 | F3: 46121 | I3: COMPRA
A5: CANTIDAD | B5: UNIDAD | C5: PRODUCTO | D5: PRECIO | E5: TOTAL | F5: TOTAL + IVA | I5: COSTO | J5: TOTAL | K5: DIFERENCIA
A6: 3 | B6: BOLSA | C6: CEBOLLA | D6: 14000 | E6: =A6*D6 -> 42000 | F6: =E6*1.105 -> 46410 | I6: 10000 | J6: =I6*A6 -> 30000 | K6: =F6-J6 -> 16410 | L6: =IFERROR(K6/E6, 0) -> 0.39071429
A7: 2 | B7: CAJON | C7: MORRON ROJO | D7: 18000 | E7: =A7*D7 -> 36000 | F7: =E7*1.105 -> 39780 | I7: 15000 | J7: =I7*A7 -> 30000 | K7: =F7-J7 -> 9780 | L7: =IFERROR(K7/E7, 0) -> 0.27166667
A8: 4 | B8: BOLSA | C8: ZANAHORIA INDUSTRIAL | D8: 16000 | E8: =A8*D8 -> 64000 | F8: =E8*1.105 -> 70720 | I8: 10000 | J8: =I8*A8 -> 40000 | K8: =F8-J8 -> 30720 | L8: =IFERROR(K8/E8, 0) -> 0.48
A9: 2 | B9: CAJON | C9: ZAPALLITO REDONDO | D9: 28000 | E9: =A9*D9 -> 56000 | F9: =E9*1.105 -> 61880 | I9: 25000 | J9: =I9*A9 -> 50000 | K9: =F9-J9 -> 11880 | L9: =IFERROR(K9/E9, 0) -> 0.21214286
A10: 2 | B10: BOLSA | C10: ANCO | D10: 13000 | E10: =A10*D10 -> 26000 | F10: =E10*1.105 -> 28730 | I10: 8000 | J10: =I10*A10 -> 16000 | K10: =F10-J10 -> 12730 | L10: =IFERROR(K10/E10, 0) -> 0.48961538
A11: 2 | B11: BOLSA | C11: BATATA | D11: 16000 | E11: =A11*D11 -> 32000 | F11: =E11*1.105 -> 35360 | I11: 11000 | J11: =I11*A11 -> 22000 | K11: =F11-J11 -> 13360 | L11: =IFERROR(K11/E11, 0) -> 0.4175
A12: 2 | B12: CAJON | C12: REMOLACHA | D12: 17000 | E12: =A12*D12 -> 34000 | F12: =E12*1.105 -> 37570 | I12: 14000 | J12: =I12*A12 -> 28000 | K12: =F12-J12 -> 9570 | L12: =IFERROR(K12/E12, 0) -> 0.28147059
A13: 4 | B13: CAJON | C13: ACELGA | D13: 11000 | E13: =A13*D13 -> 44000 | F13: =E13*1.105 -> 48620 | I13: 7000 | J13: =I13*A13 -> 28000 | K13: =F13-J13 -> 20620 | L13: =IFERROR(K13/E13, 0) -> 0.46863636
A14: 8 | B14: BOLSA | C14: PAPA CEPILLADA | D14: 15000 | E14: =A14*D14 -> 120000 | F14: =E14*1.105 -> 132600 | I14: 11500 | J14: =I14*A14 -> 92000 | K14: =F14-J14 -> 40600 | L14: =IFERROR(K14/E14, 0) -> 0.33833333
A15: 1 | B15: CAJON | C15: TOMATE | D15: 12000 | E15: =A15*D15 -> 12000 | F15: =E15*1.105 -> 13260 | I15: 8000 | J15: =I15*A15 -> 8000 | K15: =F15-J15 -> 5260 | L15: =IFERROR(K15/E15, 0) -> 0.43833333
A16: 1 | B16: CAJON | C16: CHOCLO | D16: 16000 | E16: =A16*D16 -> 16000 | F16: =E16*1.105 -> 17680 | I16: 13000 | J16: =I16*A16 -> 13000 | K16: =F16-J16 -> 4680 | L16: =IFERROR(K16/E16, 0) -> 0.2925
A17: 3 | B17: CAJON | C17: MANDARINA | D17: 20000 | E17: =A17*D17 -> 60000 | F17: =E17*1.105 -> 66300 | I17: 13000 | J17: =I17*A17 -> 39000 | K17: =F17-J17 -> 27300 | L17: =IFERROR(K17/E17, 0) -> 0.455
A18: 0.5 | B18: CAJON | C18: HUEVO N2 | D18: 50000 | E18: =A18*D18 -> 25000 | F18: =E18*1.21 -> 30250 | I18: 50000 | J18: =I18*A18 -> 25000 | K18: =F18-J18 -> 5250 | L18: =IFERROR(K18/E18, 0) -> 0.21
E20: =SUM(E6:E18) -> 567000 | F20: =SUM(F6:F18) -> 629160 | K20: =SUM(K6:K18) -> 208160 | L20: =K20/F20 -> 0.33085384
A26: FV | E26: rto: 252 | F26: 46121 | I26: COMPRA
A28: CANTIDAD | B28: UNIDAD | C28: PRODUCTO | D28: PRECIO | E28: TOTAL | F28: TOTAL + IVA | I28: COSTO | J28: TOTAL | K28: DIFERENCIA
A29: 4 | B29: CAJON | C29: BANANA | D29: 40000 | E29: =A29*D29 -> 160000 | F29: =E29*1.105 -> 176800 | I29: 36000 | J29: =I29*A29 -> 144000 | K29: =F29-J29 -> 32800 | L29: =IFERROR(K29/E29, 0) -> 0.205
A30: 4 | B30: CAJON | C30: NARANJA | D30: 26000 | E30: =A30*D30 -> 104000 | F30: =E30*1.105 -> 114920 | I30: 24000 | J30: =I30*A30 -> 96000 | K30: =F30-J30 -> 18920 | L30: =IFERROR(K30/E30, 0) -> 0.18192308
A31: 2 | B31: CAJA | C31: MANZANA GRANNY | D31: 60000 | E31: =A31*D31 -> 120000 | F31: =E31*1.105 -> 132600 | I31: 20000 | J31: =I31*A31 -> 40000 | K31: =F31-J31 -> 92600 | L31: =IFERROR(K31/E31, 0) -> 0.77166667
A32: 2 | B32: CAJA | C32: PERA | D32: 25000 | E32: =A32*D32 -> 50000 | F32: =E32*1.105 -> 55250 | I32: =17000 -> 17000 | J32: =I32*A32 -> 34000 | K32: =F32-J32 -> 21250 | L32: =IFERROR(K32/E32, 0) -> 0.425
A33: 3 | B33: CAJA | C33: MANZNA RED | D33: 45000 | E33: =A33*D33 -> 135000 | F33: =E33*1.105 -> 149175 | I33: =88000/3 -> 29333.333 | J33: =I33*A33 -> 88000 | K33: =F33-J33 -> 61175 | L33: =IFERROR(K33/E33, 0) -> 0.45314815
A34: 1 | B34: CAJON | C34: BANANA | D34: 40000 | E34: =A34*D34 -> 40000 | F34: =E34*1.105 -> 44200 | G34: BOLSA | J34: =I34*A34 -> 0 | K34: =F34-J34 -> 44200 | L34: =IFERROR(K34/E34, 0) -> 1.105
A35: 1 | B35: CAJON | C35: NARANJA | D35: 26000 | E35: =A35*D35 -> 26000 | F35: =E35*1.105 -> 28730 | G35: BOLSA | J35: =I35*A35 -> 0 | K35: =F35-J35 -> 28730 | L35: =IFERROR(K35/E35, 0) -> 1.105
A36: 1 | B36: CAJON | C36: MANZANA GRANNY | D36: 60000 | E36: =A36*D36 -> 60000 | F36: =E36*1.105 -> 66300 | G36: BOLSA | J36: =I36*A36 -> 0 | K36: =F36-J36 -> 66300 | L36: =IFERROR(K36/E36, 0) -> 1.105
A37: 1 | B37: CAJON | C37: PERA | D37: 25000 | E37: =A37*D37 -> 25000 | F37: =E37*1.105 -> 27625 | G37: BOLSA | J37: =I37*A37 -> 0 | K37: =F37-J37 -> 27625 | L37: =IFERROR(K37/E37, 0) -> 1.105
A38: 1 | B38: CAJON | C38: MANZANA | D38: 45000 | E38: =A38*D38 -> 45000 | F38: =E38*1.105 -> 49725 | G38: BOLSA | J38: =I38*A38 -> 0 | K38: =F38-J38 -> 49725 | L38: =IFERROR(K38/E38, 0) -> 1.105
E40: =SUM(E29:E38) -> 765000 | F40: =SUM(F29:F38) -> 845325 | K40: =SUM(K29:K38) -> 443325 | L40: =K40/F40 -> 0.52444326
A43: COLEGIO SJCB - VIRREY DEL PINO 3299 | E43: rto: 18 | F43: 46121 | I43: COMPRA
A45: CANTIDAD | B45: UNIDAD | C45: PRODUCTO | D45: PRECIO | E45: TOTAL | F45: TOTAL + IVA | I45: COSTO | J45: TOTAL | K45: DIFERENCIA
A46: 1 | B46: BOLSA | C46: PAPA LAVADA | D46: 25000 | E46: =A46*D46 -> 25000 | F46: =E46*1.105 -> 27625 | I46: 20000 | J46: =I46*A46 -> 20000 | K46: =F46-J46 -> 7625 | L46: =IFERROR(K46/E46, 0) -> 0.305
A47: 0.5 | B47: CAJON | C47: NARANJA JUGO | D47: 28000 | E47: =A47*D47 -> 14000 | F47: =E47*1.105 -> 15470 | I47: 24000 | J47: =I47*A47 -> 12000 | K47: =F47-J47 -> 3470 | L47: =IFERROR(K47/E47, 0) -> 0.24785714
E49: =SUM(E46:E47) -> 39000 | F49: =SUM(F46:F47) -> 43095 | K49: =SUM(K46:K47) -> 11095 | L49: =K49/F49 -> 0.25745446
A52: CATERING | D52: rto: 19 | E52: 46273
A54: CANTIDAD | B54: UNIDAD | C54: PRODUCTO | D54: PRECIO | E54: TOTAL | I54: PRECIO | J54: TOTAL | K54: DIFERENCIA
A55: 2 | B55: ATADO | C55: VERDEO | D55: 3500 | E55: =A55*D55 -> 7000 | I55: 2000 | J55: =I55*A55 -> 4000 | K55: =E55-J55 -> 3000 | L55: =K55/E55 -> 0.42857143
A56: 1 | B56: CAJON | C56: BERENJENA | D56: 10000 | E56: =A56*D56 -> 10000 | I56: 6000 | J56: =I56*A56 -> 6000 | K56: =E56-J56 -> 4000 | L56: =K56/E56 -> 0.4
A57: 3 | B57: CAJON | C57: BROCOLI | D57: 18000 | E57: =A57*D57 -> 54000 | I57: 15000 | J57: =I57*A57 -> 45000 | K57: =E57-J57 -> 9000 | L57: =K57/E57 -> 0.16666667
A58: 2 | B58: BOLSA | C58: ZANAHORIA INDUSTRIAL | D58: 14000 | E58: =A58*D58 -> 28000 | I58: 10000 | J58: =I58*A58 -> 20000 | K58: =E58-J58 -> 8000 | L58: =K58/E58 -> 0.28571429
A59: 4 | B59: BOLSA | C59: ANCO | D59: 13000 | E59: =A59*D59 -> 52000 | I59: 8000 | J59: =I59*A59 -> 32000 | K59: =E59-J59 -> 20000 | L59: =K59/E59 -> 0.38461538
A60: 2 | B60: BOLSA | C60: BONIATO | D60: 25000 | E60: =A60*D60 -> 50000 | I60: 20000 | J60: =I60*A60 -> 40000 | K60: =E60-J60 -> 10000 | L60: =K60/E60 -> 0.2
A61: 1 | B61: BOLSA | C61: CEB MORADA | D61: 20000 | E61: =A61*D61 -> 20000 | I61: 15000 | J61: =I61*A61 -> 15000 | K61: =E61-J61 -> 5000 | L61: =K61/E61 -> 0.25
A62: 6 | B62: BOLSA | C62: CEBOLLON | D62: 14000 | E62: =A62*D62 -> 84000 | I62: 10000 | J62: =I62*A62 -> 60000 | K62: =E62-J62 -> 24000 | L62: =K62/E62 -> 0.28571429
E65: =SUM(E55:E62) -> 305000 | K65: =SUM(K55:K62) -> 83000 | L65: =K65/E65 -> 0.27213115
A73: TOTAL DIA | B73: =E65+F49+F40+F20 -> 1822580
A75: GANANCIA | B75: =K65+K49+K40+K20 -> 745580
A78: % | B78: =B75/B73 -> 0.40907944
A80: BULTOS COMPRADOS

Sheet 10-04-2026
A3: COLEGIO SJCB - VIRREY DEL PINO 3299 | C3: rto: 19 | D3: 10-Apr | G3: COMPRA
A5: CANTIDAD | B5: UNIDAD | C5: PRODUCTO | D5: PRECIO | E5: TOTAL | F5: TOTAL + IVA | I5: COSTO | J5: TOTAL | K5: DIFERENCIA
A6: 0.20 | B6: KG | C6: CEBOLLA DE VERDEO | D6: $ 4,500.00 | E6: $ 900.00 | F6: $ 994.50 | I6: $ 1,500.00 | J6: $ 300.00 | K6: $ 694.50 | L6: 77.17%
A7: 1.00 | B7: ATADO | C7: ALBAHACA | D7: $ 1,500.00 | E7: $ 1,500.00 | F7: $ 1,657.50 | I7: $ 666.00 | J7: $ 666.00 | K7: $ 991.50 | L7: 66.10%
A8: 4.00 | B8: KG | C8: BANANA | D8: $ 3,000.00 | E8: $ 12,000.00 | F8: $ 13,260.00 | I8: $ 2,120.00 | J8: $ 8,480.00 | K8: $ 4,780.00 | L8: 39.83%
A9: 2.00 | B9: UNIDAD | C9: BROCOLI | D9: $ 3,200.00 | E9: $ 6,400.00 | F9: $ 7,072.00 | I9: $ 2,250.00 | J9: $ 4,500.00 | K9: $ 2,572.00 | L9: 40.19%
A10: 1.00 | B10: BOLSA | C10: CALABAZA | D10: $ 13,000.00 | E10: $ 13,000.00 | F10: $ 14,365.00 | I10: $ 8,000.00 | J10: $ 8,000.00 | K10: $ 6,365.00 | L10: 48.96%
A11: 1.50 | B11: KG | C11: CEBOLLA MORADA | D11: $ 1,600.00 | E11: $ 2,400.00 | F11: $ 2,652.00 | I11: $ 1,000.00 | J11: $ 1,500.00 | K11: $ 1,152.00 | L11: 48.00%
A12: 0.60 | B12: KG | C12: CHAMPIGNON | D12: $ 21,000.00 | E12: $ 12,600.00 | F12: $ 13,923.00 | I12: $ 16,000.00 | J12: $ 9,600.00 | K12: $ 4,323.00 | L12: 34.31%
A13: 1.00 | B13: KG | C13: CHAUCHA PLANA | D13: $ 4,000.00 | E13: $ 4,000.00 | F13: $ 4,420.00 | I13: $ 1,720.00 | J13: $ 1,720.00 | K13: $ 2,700.00 | L13: 67.50%
A14: 5.00 | B14: ATADO | C14: ESPINACA | D14: $ 1,700.00 | E14: $ 8,500.00 | F14: $ 9,392.50 | I14: $ 1,200.00 | J14: $ 6,000.00 | K14: $ 3,392.50 | L14: 39.91%
A15: 1.00 | B15: KG | C15: FRUTILLA | D15: $ 11,000.00 | E15: $ 11,000.00 | F15: $ 12,155.00 | I15: $ 10,000.00 | J15: $ 10,000.00 | K15: $ 2,155.00 | L15: 19.59%
A16: 4.00 | B16: KG | C16: MANDARINA | D16: $ 1,200.00 | E16: $ 4,800.00 | F16: $ 5,304.00 | I16: $ 640.00 | J16: $ 2,560.00 | K16: $ 2,744.00 | L16: 57.17%
A17: 0.50 | B17: CAJON | C17: MANZANA ROJA | D17: $ 60,000.00 | E17: $ 30,000.00 | F17: $ 33,150.00 | I17: $ 50,000.00 | J17: $ 25,000.00 | K17: $ 8,150.00 | L17: 27.17%
... A36: 1.50 | B36: KG | C36: LECHUGA CRIOLLA | D36: $ 6,000.00 | E36: $ 9,000.00 | F36: $ 9,945.00 | I36: $ 5,000.00 | J36: $ 7,500.00 | K36: $ 2,445.00 | L36: 27.17%
E38: $ 318,200.00 | F38: $ 351,611.00 | K38: $ 120,016.67 | L38: 34.13%
A43: COLEGIO ST. MATTHEWS - MOLDES 1469, BELGRANO | C43: rto: 17 | D43: 10-Apr | G43: COMPRA
A45: CANTIDAD | B45: UNIDAD | C45: PRODUCTO | D45: PRECIO | E45: TOTAL | F45: TOTAL + IVA | I45: COSTO | J45: TOTAL | K45: DIFERENCIA
A46: 2.00 | B46: BOLSA | C46: PAPA BLANCA | D46: $ 25,000.00 | E46: $ 50,000.00 | F46: $ 55,250.00 | I46: $ 19,500.00 | J46: $ 39,000.00 | K46: $ 16,250.00 | L46: 32.50%
A47: 1.00 | B47: BOLSA | C47: ZANAHORIA | D47: $ 12,000.00 | E47: $ 12,000.00 | F47: $ 13,260.00 | I47: $ 7,000.00 | J47: $ 7,000.00 | K47: $ 6,260.00 | L47: 52.17%
A48: 8.00 | B48: KG | C48: TOMATE PERITA | D48: $ 2,400.00 | E48: $ 19,200.00 | F48: $ 21,216.00 | I48: $ 1,350.00 | J48: $ 10,800.00 | K48: $ 10,416.00 | L48: 54.25%
A49: 4.00 | B49: KG | C49: ZAPALLITO REDONDO | D49: $ 2,400.00 | E49: $ 9,600.00 | F49: $ 10,608.00 | I49: $ 1,650.00 | J49: $ 6,600.00 | K49: $ 4,008.00 | L49: 41.75%
A50: 6.00 | B50: ATADO | C50: ESPINACA | D50: $ 1,700.00 | E50: $ 10,200.00 | F50: $ 11,271.00 | I50: $ 1,200.00 | J50: $ 7,200.00 | K50: $ 4,071.00 | L50: 39.91%
A51: 1.00 | B51: KG | C51: MORRON ROJO | D51: $ 3,200.00 | E51: $ 3,200.00 | F51: $ 3,536.00 | I51: $ 1,860.00 | J51: $ 1,860.00 | K51: $ 1,676.00 | L51: 52.38%
A52: 0.50 | B52: KG | C52: MORRON VERDE | D52: $ 2,400.00 | E52: $ 1,200.00 | F52: $ 1,326.00 | I52: $ 1,450.00 | J52: $ 725.00 | K52: $ 601.00 | L52: 50.08%
A53: 1.00 | B53: KG | C53: CHAUCHA PLANA | D53: $ 4,000.00 | E53: $ 4,000.00 | F53: $ 4,420.00 | I53: $ 1,720.00 | J53: $ 1,720.00 | K53: $ 2,700.00 | L53: 67.50%
A54: 1.00 | B54: KG | C54: BERENJENA | D54: $ 2,000.00 | E54: $ 2,000.00 | F54: $ 2,210.00 | I54: $ 850.00 | J54: $ 850.00 | K54: $ 1,360.00 | L54: 68.00%
A55: 1.00 | B55: KG | C55: ZUCCINI | D55: $ 2,600.00 | E55: $ 2,600.00 | F55: $ 2,873.00 | I55: $ 2,150.00 | J55: $ 2,150.00 | K55: $ 723.00 | L55: 27.81%
A56: 10.00 | B56: ATADO | C56: RUCULA | D56: $ 600.00 | E56: $ 6,000.00 | F56: $ 6,630.00 | I56: $ 375.00 | J56: $ 3,750.00 | K56: $ 2,880.00 | L56: 48.00%
A57: 0.40 | B57: KG | C57: CHAMPIGNON | D57: $ 21,000.00 | E57: $ 8,400.00 | F57: $ 9,282.00 | I57: $ 16,000.00 | J57: $ 6,400.00 | K57: $ 2,882.00 | L57: 34.31%
... A63: 1.00 | B63: KG | C63: FRUTILLA | D63: $ 11,000.00 | E63: $ 11,000.00 | F63: $ 12,155.00 | I63: $ 10,000.00 | J63: $ 10,000.00 | K63: $ 2,155.00 | L63: 19.59%
E65: $ 210,300.00 | F65: $ 232,381.50 | K65: $ 79,436.50 | L65: 34.18%
A68: COLEGIO SAN JAVIER - JOSE A CABRERA 5901 | C68: rto: 17 | D68: 10-Apr | G68: COMPRA
A70: CANTIDAD | B70: UNIDAD | C70: PRODUCTO | D70: PRECIO | E70: TOTAL | F70: TOTAL + IVA | I70: COSTO | J70: TOTAL | K70: DIFERENCIA
A71: 2.00 | B71: UNIDAD | C71: AJO | D71: $ 900.00 | E71: $ 1,800.00 | F71: $ 1,989.00 | I71: $ 460.00 | J71: $ 920.00 | K71: $ 1,069.00 | L71: 59.39%
A72: 1.00 | B72: ATADO | C72: ALBAHACA | D72: $ 1,500.00 | E72: $ 1,500.00 | F72: $ 1,657.50 | I72: $ 666.00 | J72: $ 666.00 | K72: $ 991.50 | L72: 66.10%
A73: 5.00 | B73: KG | C73: BANANA | D73: $ 3,000.00 | E73: $ 15,000.00 | F73: $ 16,575.00 | I73: $ 2,120.00 | J73: $ 10,600.00 | K73: $ 5,975.00 | L73: 39.83%
A74: 2.00 | B74: KG | C74: BATATA | D74: $ 1,600.00 | E74: $ 3,200.00 | F74: $ 3,536.00 | I74: $ 1,200.00 | J74: $ 2,400.00 | K74: $ 1,136.00 | L74: 35.50%
A75: 1.00 | B75: UNIDAD | C75: BROCOLI | D75: $ 3,200.00 | E75: $ 3,200.00 | F75: $ 3,536.00 | I75: $ 2,250.00 | J75: $ 2,250.00 | K75: $ 1,286.00 | L75: 40.19%
A76: 2.00 | B76: BOLSA | C76: PAPA BLANCA | D76: $ 25,000.00 | E76: $ 50,000.00 | F76: $ 55,250.00 | I76: $ 19,500.00 | J76: $ 39,000.00 | K76: $ 16,250.00 | L76: 32.50%
A77: 8.00 | B77: KG | C77: CALABAZA | D77: $ 1,000.00 | E77: $ 8,000.00 | F77: $ 8,840.00 | I77: $ 500.00 | J77: $ 4,000.00 | K77: $ 4,840.00 | L77: 60.50%
A78: 1.00 | B78: ATADO | C78: CEBOLLA DE VERDEO | D78: $ 4,500.00 | E78: $ 4,500.00 | F78: $ 4,972.50 | I78: $ 1,500.00 | J78: $ 1,500.00 | K78: $ 3,472.50 | L78: 77.17%
A79: 4.00 | B79: KG | C79: CEBOLLA MORADA | D79: $ 1,600.00 | E79: $ 6,400.00 | F79: $ 7,072.00 | I79: $ 1,000.00 | J79: $ 4,000.00 | K79: $ 3,072.00 | L79: 48.00%
A80: 0.60 | B80: KG | C80: CHAMPIGNON | D80: $ 21,000.00 | E80: $ 12,600.00 | F80: $ 13,923.00 | I80: $ 16,000.00 | J80: $ 9,600.00 | K80: $ 4,323.00 | L80: 34.31%
A81: 1.00 | B81: KG | C81: CHAUCHA PLANA | D81: $ 4,000.00 | E81: $ 4,000.00 | F81: $ 4,420.00 | I81: $ 1,720.00 | J81: $ 1,720.00 | K81: $ 2,700.00 | L81: 67.50%
A82: 1.00 | B82: ATADO | C82: CIBOULETTE | D82: $ 3,000.00 | E82: $ 3,000.00 | F82: $ 3,315.00 | I82: $ 2,500.00 | J82: $ 2,500.00 | K82: $ 815.00 | L82: 27.17%
... A101: 8.60 | B101: KG | C101: ZAPALLITO REDONDO | D101: $ 2,400.00 | E101: $ 20,640.00 | F101: $ 22,807.20 | I101: $ 1,650.00 | J101: $ 14,190.00 | K101: $ 8,617.20 | L101: 41.75%
E103: $ 364,170.00 | F103: $ 408,077.85 | K103: $ 140,161.63 | L103: 34.35%
A106: COLEGIO SAN MARCOS | SAN ISIDRO | C106: rto: 14 | D106: 10-Apr | G106: COMPRA
A108: CANTIDAD | B108: UNIDAD | C108: PRODUCTO | D108: PRECIO | E108: TOTAL | F108: TOTAL + IVA | I108: COSTO | J108: TOTAL | K108: DIFERENCIA
A109: 2.00 | B109: CAJON | C109: TOMATE PERITA | D109: $ 36,000.00 | E109: $ 72,000.00 | F109: $ 79,560.00 | I109: $ 20,000.00 | J109: $ 40,000.00 | K109: $ 39,560.00 | L109: 54.94%
A110: 1.00 | B110: CAJON | C110: LECHUGA CRIOLLA | D110: $ 24,000.00 | E110: $ 24,000.00 | F110: $ 26,520.00 | I110: $ 20,000.00 | J110: $ 20,000.00 | K110: $ 6,520.00 | L110: 27.17%
A111: 2.00 | B111: CAJON | C111: RUCULA | D111: $ 13,000.00 | E111: $ 26,000.00 | F111: $ 28,730.00 | I111: $ 9,000.00 | J111: $ 18,000.00 | K111: $ 10,730.00 | L111: 41.27%
A112: 4.00 | B112: BOLSA | C112: ZANAHORIA | D112: $ 12,000.00 | E112: $ 48,000.00 | F112: $ 53,040.00 | I112: $ 7,000.00 | J112: $ 28,000.00 | K112: $ 25,040.00 | L112: 52.17%
A113: 5.00 | B113: BOLSA | C113: PAPA BLANCA | D113: $ 25,000.00 | E113: $ 125,000.00 | F113: $ 138,125.00 | I113: $ 19,500.00 | J113: $ 97,500.00 | K113: $ 40,625.00 | L113: 32.50%
A114: 2.00 | B114: BOLSA | C114: ANCO | D114: $ 13,000.00 | E114: $ 26,000.00 | F114: $ 28,730.00 | I114: $ 8,000.00 | J114: $ 16,000.00 | K114: $ 12,730.00 | L114: 48.96%
A115: 1.00 | B115: BOLSA | C115: BATATA | D115: $ 16,000.00 | E115: $ 16,000.00 | F115: $ 17,680.00 | I115: $ 12,000.00 | J115: $ 12,000.00 | K115: $ 5,680.00 | L115: 35.50%
A116: 7.60 | B116: KG | C116: REPOLLO BLANCO | D116: $ 1,800.00 | E116: $ 13,680.00 | F116: $ 15,116.40 | I116: $ 1,000.00 | J116: $ 7,600.00 | K116: $ 7,516.40 | L116: 54.94%
A117: 5.30 | B117: KG | C117: REPOLLO COLORADO | D117: $ 1,800.00 | E117: $ 9,540.00 | F117: $ 10,541.70 | I117: $ 1,000.00 | J117: $ 5,300.00 | K117: $ 5,241.70 | L117: 54.94%
A118: 10.40 | B118: KG | C118: ZAPALLITO REDONDO | D118: $ 2,400.00 | E118: $ 24,960.00 | F118: $ 27,580.80 | I118: $ 1,650.00 | J118: $ 17,160.00 | K118: $ 10,420.80 | L118: 41.75%
A119: 3.00 | B119: KG | C119: MORRON ROJO | D119: $ 3,200.00 | E119: $ 9,600.00 | F119: $ 10,608.00 | I119: $ 1,860.00 | J119: $ 5,580.00 | K119: $ 5,028.00 | L119: 52.38%
A120: 2.00 | B120: KG | C120: MORRON VERDE | D120: $ 2,400.00 | E120: $ 4,800.00 | F120: $ 5,304.00 | I120: $ 1,450.00 | J120: $ 2,900.00 | K120: $ 2,404.00 | L120: 50.08%
... A148: 1.00 | B148: CAJON | C148: HUEVO N1 | D148: $ 54,000.00 | E148: $ 54,000.00 | F148: $ 65,340.00 | I148: $ 54,000.00 | J148: $ 54,000.00 | K148: $ 11,340.00 | L148: 21.00%
E150: $ 860,230.00 | F150: $ 956,224.15 | K150: $ 324,258.15 | L150: 33.91%
A155: COLEGIO VILLA DEVOTO SCHOOL - PEDRO MORAN 4441 | C155: rto: 17 | D155: 10-Apr | G155: COMPRA
A157: CANTIDAD | B157: UNIDAD | C157: PRODUCTO | D157: PRECIO | E157: TOTAL | F157: TOTAL + IVA | I157: COSTO | J157: TOTAL | K157: DIFERENCIA
A158: 0.80 | B158: KG | C158: TOMATE CHERRY | D158: $ 3,000.00 | E158: $ 2,400.00 | F158: $ 2,652.00 | I158: $ 1,625.00 | J158: $ 1,300.00 | K158: $ 1,352.00 | L158: 56.33%
A159: 14.00 | B159: KG | C159: TOMATE PERITA | D159: $ 2,400.00 | E159: $ 33,600.00 | F159: $ 37,128.00 | I159: $ 1,350.00 | J159: $ 18,900.00 | K159: $ 18,228.00 | L159: 54.25%
A160: 1.00 | B160: ATADO | C160: ALBAHACA | D160: $ 1,500.00 | E160: $ 1,500.00 | F160: $ 1,657.50 | I160: $ 666.00 | J160: $ 666.00 | K160: $ 991.50 | L160: 66.10%
A161: 2.00 | B161: KG | C161: LECHUGA CRIOLLA | D161: $ 6,000.00 | E161: $ 12,000.00 | F161: $ 13,260.00 | I161: $ 5,000.00 | J161: $ 10,000.00 | K161: $ 3,260.00 | L161: 27.17%
A162: 10.00 | B162: ATADO | C162: RUCULA | D162: $ 600.00 | E162: $ 6,000.00 | F162: $ 6,630.00 | I162: $ 375.00 | J162: $ 3,750.00 | K162: $ 2,880.00 | L162: 48.00%
A163: 4.00 | B163: KG | C163: MORRON ROJO | D163: $ 3,200.00 | E163: $ 12,800.00 | F163: $ 14,144.00 | I163: $ 1,860.00 | J163: $ 7,440.00 | K163: $ 6,704.00 | L163: 52.38%
A164: 2.00 | B164: KG | C164: MORRON VERDE | D164: $ 2,400.00 | E164: $ 4,800.00 | F164: $ 5,304.00 | I164: $ 1,450.00 | J164: $ 2,900.00 | K164: $ 2,404.00 | L164: 50.08%
A165: 2.00 | B165: KG | C165: MORRON AMARILLO | D165: $ 2,800.00 | E165: $ 5,600.00 | F165: $ 6,188.00 | I165: $ 2,150.00 | J165: $ 4,300.00 | K165: $ 1,888.00 | L165: 33.71%
A166: 2.00 | B166: KG | C166: REPOLLO COLORADO | D166: $ 1,800.00 | E166: $ 3,600.00 | F166: $ 3,978.00 | I166: $ 1,000.00 | J166: $ 2,000.00 | K166: $ 1,978.00 | L166: 54.94%
A167: 3.60 | B167: KG | C167: REPOLLO BLANCO | D167: $ 1,800.00 | E167: $ 6,480.00 | F167: $ 7,160.40 | I167: $ 1,000.00 | J167: $ 3,600.00 | K167: $ 3,560.40 | L167: 54.94%
A168: 1.00 | B168: BOLSA | C168: ANCO | D168: $ 13,000.00 | E168: $ 13,000.00 | F168: $ 14,365.00 | I168: $ 8,000.00 | J168: $ 8,000.00 | K168: $ 6,365.00 | L168: 48.96%
A169: 2.00 | B169: UNIDAD | C169: BROCOLI | D169: $ 3,200.00 | E169: $ 6,400.00 | F169: $ 7,072.00 | I169: $ 2,250.00 | J169: $ 4,500.00 | K169: $ 2,572.00 | L169: 40.19%
... A189: 7.00 | B189: UNIDAD | C189: HUEVO N1 | D189: $ 4,500.00 | E189: $ 31,500.00 | F189: $ 38,115.00 | I189: $ 4,500.00 | J189: $ 31,500.00 | K189: $ 6,615.00 | L189: 21.00%
E191: $ 478,720.00 | F191: $ 532,293.10 | K191: $ 172,627.10 | L191: 32.43%
A194: COLEGIO SWORM JUNIOR COLLAGE | PACHECO | C194: rto: 13 | D194: 10-Apr | G194: COMPRA
A196: CANTIDAD | B196: UNIDAD | C196: PRODUCTO | D196: PRECIO | E196: TOTAL | F196: TOTAL + IVA | I196: COSTO | J196: TOTAL | K196: DIFERENCIA
A197: 5.00 | B197: KG | C197: TOMATE PERITA | D197: $ 2,400.00 | E197: $ 12,000.00 | F197: $ 13,260.00 | I197: $ 1,350.00 | J197: $ 6,750.00 | K197: $ 6,510.00 | L197: 54.25%
A198: 5.00 | B198: KG | C198: LECHUGA CRIOLLA | D198: $ 6,000.00 | E198: $ 30,000.00 | F198: $ 33,150.00 | I198: $ 5,000.00 | J198: $ 25,000.00 | K198: $ 8,150.00 | L198: 27.17%
A199: 1.00 | B199: ATADO | C199: PEREJIL | D199: $ 3,500.00 | E199: $ 3,500.00 | F199: $ 3,867.50 | I199: $ 1,500.00 | J199: $ 1,500.00 | K199: $ 2,367.50 | L199: 67.64%
A200: 1.00 | B200: ATADO | C200: CILANTRO | D200: $ 3,000.00 | E200: $ 3,000.00 | F200: $ 3,315.00 | I200: $ 1,000.00 | J200: $ 1,000.00 | K200: $ 2,315.00 | L200: 77.17%
A201: 1.00 | B201: ATADO | C201: KALE | D201: $ 2,000.00 | E201: $ 2,000.00 | F201: $ 2,210.00 | I201: $ 800.00 | J201: $ 800.00 | K201: $ 1,410.00 | L201: 70.50%
A202: 2.00 | B202: KG | C202: MORRON ROJO | D202: $ 3,200.00 | E202: $ 6,400.00 | F202: $ 7,072.00 | I202: $ 1,860.00 | J202: $ 3,720.00 | K202: $ 3,352.00 | L202: 52.38%
A203: 2.00 | B203: KG | C203: MORRON AMARILLO | D203: $ 2,800.00 | E203: $ 5,600.00 | F203: $ 6,188.00 | I203: $ 2,150.00 | J203: $ 4,300.00 | K203: $ 1,888.00 | L203: 33.71%
A204: 2.00 | B204: KG | C204: MORRON VERDE | D204: $ 2,400.00 | E204: $ 4,800.00 | F204: $ 5,304.00 | I204: $ 1,450.00 | J204: $ 2,900.00 | K204: $ 2,404.00 | L204: 50.08%
A205: 5.00 | B205: KG | C205: ZAPALLITO REDONDO | D205: $ 2,400.00 | E205: $ 12,000.00 | F205: $ 13,260.00 | I205: $ 1,650.00 | J205: $ 8,250.00 | K205: $ 5,010.00 | L205: 41.75%
A206: 1.00 | B206: KG | C206: ZUCCINI | D206: $ 2,600.00 | E206: $ 2,600.00 | F206: $ 2,873.00 | I206: $ 2,150.00 | J206: $ 2,150.00 | K206: $ 723.00 | L206: 27.81%
A207: 1.00 | B207: BOLSA | C207: ZANAHORIA | D207: $ 12,000.00 | E207: $ 12,000.00 | F207: $ 13,260.00 | I207: $ 7,000.00 | J207: $ 7,000.00 | K207: $ 6,260.00 | L207: 52.17%
A208: 1.00 | B208: BOLSA | C208: CALABAZA | D208: $ 13,000.00 | E208: $ 13,000.00 | F208: $ 14,365.00 | I208: $ 8,000.00 | J208: $ 8,000.00 | K208: $ 6,365.00 | L208: 48.96%
... A226: 3.00 | B226: KG | C226: MANDARINA | D226: $ 1,200.00 | E226: $ 3,600.00 | F226: $ 3,978.00 | I226: $ 640.00 | J226: $ 1,920.00 | K226: $ 2,058.00 | L226: 57.17%
E228: $ 358,000.00 | F228: $ 398,425.00 | K228: $ 134,502.50 | L228: 33.76%
A231: COLEGIO ST CATHERINES MOORLANDS - CARBAJAL 3250 | C231: rto: 19 | D231: 10-Apr | G231: COMPRA
A233: CANTIDAD | B233: UNIDAD | C233: PRODUCTO | D233: PRECIO | E233: TOTAL | F233: TOTAL + IVA | I233: COSTO | J233: TOTAL | K233: DIFERENCIA
A234: 3.00 | B234: UNIDAD | C234: AJO | D234: $ 900.00 | E234: $ 2,700.00 | F234: $ 2,983.50 | I234: $ 460.00 | J234: $ 1,380.00 | K234: $ 1,603.50 | L234: 59.39%
A235: 1.00 | B235: ATADO | C235: ALBAHACA | D235: $ 1,500.00 | E235: $ 1,500.00 | F235: $ 1,657.50 | I235: $ 666.00 | J235: $ 666.00 | K235: $ 991.50 | L235: 66.10%
...

Sheet 13-04-2026 
A4: LA MARQUESA | D4: rto: 28 | E4: 46125
A6: CANTIDAD | B6: UNIDAD | C6: PRODUCTO | D6: PRECIO | E6: TOTAL | I6: PRECIO | J6: TOTAL | K6: DIFERENCIA
A7: 1 | B7: ATADO | C7: ALBAHACA | D7: 1500 | E7: =A7*D7 -> 1500 | I7: =10000/12 -> 833.33333 | J7: =I7*A7 -> 833.33333 | K7: =E7-J7 -> 666.66667 | L7: =K7/E7 -> 0.44444444
A8: 2 | B8: KG | C8: BANANA ECUADOR | D8: 3000 | E8: =A8*D8 -> 6000 | I8: =28000/17 -> 1647.0588 | J8: =I8*A8 -> 3294.1176 | K8: =E8-J8 -> 2705.8824 | L8: =K8/E8 -> 0.45098039
A9: 0.5 | B9: KG | C9: CHAMPIGNON | D9: 21000 | E9: =A9*D9 -> 10500 | I9: =16000 -> 16000 | J9: =I9*A9 -> 8000 | K9: =E9-J9 -> 2500 | L9: =K9/E9 -> 0.23809524
A10: 1 | B10: CAJON | C10: ESPINACA | D10: 17000 | E10: =A10*D10 -> 17000 | I10: 13000 | J10: =I10*A10 -> 13000 | K10: =E10-J10 -> 4000 | L10: =K10/E10 -> 0.23529412
A11: 3 | B11: CAJON | C11: HUEVO | D11: 55000 | E11: =A11*D11 -> 165000 | I11: 50000 | J11: =I11*A11 -> 150000 | K11: =E11-J11 -> 15000 | L11: =K11/E11 -> 0.090909091
A12: 0.5 | B12: KG | C12: JENGIBRE | D12: 11000 | E12: =A12*D12 -> 5500 | I12: 7000 | J12: =I12*A12 -> 3500 | K12: =E12-J12 -> 2000 | L12: =K12/E12 -> 0.36363636
A13: 1 | B13: KG | C13: KIWI | D13: 8600 | E13: =A13*D13 -> 8600 | I13: 6100 | J13: =I13*A13 -> 6100 | K13: =E13-J13 -> 2500 | L13: =K13/E13 -> 0.29069767
A14: 2 | B14: KG | C14: LIMA | D14: 4000 | E14: =A14*D14 -> 8000 | I14: 2000 | J14: =I14*A14 -> 4000 | K14: =E14-J14 -> 4000 | L14: =K14/E14 -> 0.5
A15: 1 | B15: CAJON | C15: LIMON | D15: 28000 | E15: =A15*D15 -> 28000 | I15: 16000 | J15: =I15*A15 -> 16000 | K15: =E15-J15 -> 12000 | L15: =K15/E15 -> 0.42857143
A16: 1 | B16: KG | C16: MANZANA VERDE | D16: 4500 | E16: =A16*D16 -> 4500 | I16: =60000/17 -> 3529.4118 | J16: =I16*A16 -> 3529.4118 | K16: =E16-J16 -> 970.58824 | L16: =K16/E16 -> 0.21568627
A17: 1 | B17: CAJON | C17: NARANJA | D17: 27000 | E17: =A17*D17 -> 27000 | I17: 16000 | J17: =I17*A17 -> 16000 | K17: =E17-J17 -> 11000 | L17: =K17/E17 -> 0.40740741
A18: 4 | B18: ATADO | C18: PUERRO | D18: 5000 | E18: =A18*D18 -> 20000 | I18: 2000 | J18: =I18*A18 -> 8000 | K18: =E18-J18 -> 12000 | L18: =K18/E18 -> 0.6
A19: 0.5 | B19: CAJON | C19: TOMATE REDONDO | D19: 14000 | E19: =A19*D19 -> 7000 | I19: =7000 -> 7000 | J19: =I19*A19 -> 3500 | K19: =E19-J19 -> 3500 | L19: =K19/E19 -> 0.5
A20: 3 | B20: KG | C20: ANCO | D20: 1000 | E20: =A20*D20 -> 3000 | I20: =8000/15 -> 533.33333 | J20: =I20*A20 -> 1600 | K20: =E20-J20 -> 1400 | L20: =K20/E20 -> 0.46666667
A21: 1 | B21: KG | C21: CIRUELA | D21: 4500 | E21: =A21*D21 -> 4500 | I21: =12120/3 -> 4040 | J21: =I21*A21 -> 4040 | K21: =E21-J21 -> 460 | L21: =K21/E21 -> 0.10222222
E23: =SUM(E7:E21) -> 316100 | K23: =SUM(K7:K21) -> 74703.137 | L23: =K23/E23 -> 0.23632755
A26: QUINQUELA | D26: rto: 12 | E26: 46125
A28: CANTIDAD | B28: UNIDAD | C28: PRODUCTO | D28: PRECIO | E28: TOTAL | I28: PRECIO | J28: TOTAL | K28: DIFERENCIA
A29: 1 | B29: ATADO | C29: ALBAHACA | D29: 1500 | E29: =A29*D29 -> 1500 | I29: =10000/12 -> 833.33333 | J29: =I29*A29 -> 833.33333 | K29: =E29-J29 -> 666.66667 | L29: =K29/E29 -> 0.44444444
A30: 2 | B30: KG | C30: BANANA ECUADOR | D30: 3000 | E30: =A30*D30 -> 6000 | I30: =28000/17 -> 1647.0588 | J30: =I30*A30 -> 3294.1176 | K30: =E30-J30 -> 2705.8824 | L30: =K30/E30 -> 0.45098039
A31: 1 | B31: KG | C31: MANZANA VERDE | D31: 4500 | E31: =A31*D31 -> 4500 | I31: =60000/17 -> 3529.4118 | J31: =I31*A31 -> 3529.4118 | K31: =E31-J31 -> 970.58824 | L31: =K31/E31 -> 0.21568627
A32: 1 | B32: ATADO | C32: MENTA | D32: 3000 | E32: =A32*D32 -> 3000 | I32: 2000 | J32: =I32*A32 -> 2000 | K32: =E32-J32 -> 1000 | L32: =K32/E32 -> 0.33333333
A33: 1 | B33: CAJON | C33: NARANJA | D33: 27000 | E33: =A33*D33 -> 27000 | I33: 16000 | J33: =I33*A33 -> 16000 | K33: =E33-J33 -> 11000 | L33: =K33/E33 -> 0.40740741
A34: 1 | B34: KG | C34: RABANITO | D34: 1000 | E34: =A34*D34 -> 1000 | I34: =2000/3 -> 666.66667 | J34: =I34*A34 -> 666.66667 | K34: =E34-J34 -> 333.33333 | L34: =K34/E34 -> 0.33333333
E36: =SUM(E29:E34) -> 43000 | K36: =SUM(K29:K34) -> 16676.471 | L36: =K36/E36 -> 0.3878249
A40: COMO SIEMPRE LAGUNA | D40: rto: 46 | E40: 46125
A42: CANTIDAD | B42: UNIDAD | C42: PRODUCTO | D42: PRECIO | E42: TOTAL | I42: PRECIO | J42: TOTAL | K42: DIFERENCIA
A43: 10 | B43: KG | C43: LIMON | D43: 2400 | E43: =A43*D43 -> 24000 | I43: =16000/14 -> 1142.8571 | J43: =I43*A43 -> 11428.571 | K43: =E43-J43 -> 12571.429 | L43: =K43/E43 -> 0.52380952
A44: 10 | B44: KG | C44: NARANJA | D44: 1800 | E44: =A44*D44 -> 18000 | I44: =16000/15 -> 1066.6667 | J44: =I44*A44 -> 10666.667 | K44: =E44-J44 -> 7333.3333 | L44: =K44/E44 -> 0.40740741
A45: 8 | B45: KG | C45: POMELO | D45: 3000 | E45: =A45*D45 -> 24000 | I45: =32000/15 -> 2133.3333 | J45: =I45*A45 -> 17066.667 | K45: =E45-J45 -> 6933.3333 | L45: =K45/E45 -> 0.28888889
A46: 3 | B46: CAJON | C46: ESPINACA | D46: 17000 | E46: =A46*D46 -> 51000 | I46: 13000 | J46: =I46*A46 -> 39000 | K46: =E46-J46 -> 12000 | L46: =K46/E46 -> 0.23529412
A47: 6 | B47: KG | C47: TOMATE PERITA | D47: 2200 | E47: =A47*D47 -> 13200 | I47: =11000/15 -> 733.33333 | J47: =I47*A47 -> 4400 | K47: =E47-J47 -> 8800 | L47: =K47/E47 -> 0.66666667
A48: 2 | B48: BOLSA | C48: PAPA BLANCA | D48: 25000 | E48: =A48*D48 -> 50000 | I48: 18000 | J48: =I48*A48 -> 36000 | K48: =E48-J48 -> 14000 | L48: =K48/E48 -> 0.28
A49: 1.5 | B49: KG | C49: LECHUGA FRANCESA | D49: 4000 | E49: =A49*D49 -> 6000 | I49: 2000 | J49: =I49*A49 -> 3000 | K49: =E49-J49 -> 3000 | L49: =K49/E49 -> 0.5
A50: 7 | B50: KG | C50: ZANAHORIA | D50: 1300 | E50: =A50*D50 -> 9100 | I50: 750 | J50: =I50*A50 -> 5250 | K50: =E50-J50 -> 3850 | L50: =K50/E50 -> 0.42307692
A51: 1 | B51: ATADO | C51: APIO | D51: 2500 | E51: =A51*D51 -> 2500 | I51: =9000/8 -> 1125 | J51: =I51*A51 -> 1125 | K51: =E51-J51 -> 1375 | L51: =K51/E51 -> 0.55
A52: 3 | B52: KG | C52: BONIATO | D52: 2400 | E52: =A52*D52 -> 7200 | I52: =20000/11 -> 1818.1818 | J52: =I52*A52 -> 5454.5455 | K52: =E52-J52 -> 1745.4545 | L52: =K52/E52 -> 0.24242424
A53: 3 | B53: UNIDAD | C53: MANGO | D53: 3000 | E53: =A53*D53 -> 9000 | I53: =14000/10 -> 1400 | J53: =I53*A53 -> 4200 | K53: =E53-J53 -> 4800 | L53: =K53/E53 -> 0.53333333
A54: 1 | B54: ATADO | C54: ALBAHACA | D54: 1500 | E54: =A54*D54 -> 1500 | I54: =10000/12 -> 833.33333 | J54: =I54*A54 -> 833.33333 | K54: =E54-J54 -> 666.66667 | L54: =K54/E54 -> 0.44444444
A55: 3 | B55: KG | C55: MORRON ROJO | D55: 2800 | E55: =A55*D55 -> 8400 | I55: =15000/8 -> 1875 | J55: =I55*A55 -> 5625 | K55: =E55-J55 -> 2775 | L55: =K55/E55 -> 0.33035714
A56: 2 | B56: KG | C56: CEBOLLA MORADA | D56: 1600 | E56: =A56*D56 -> 3200 | I56: =12000/15 -> 800 | J56: =I56*A56 -> 1600 | K56: =E56-J56 -> 1600 | L56: =K56/E56 -> 0.5
A57: 3 | B57: KG | C57: LIMA | D57: 4000 | E57: =A57*D57 -> 12000 | I57: 2000 | J57: =I57*A57 -> 6000 | K57: =E57-J57 -> 6000 | L57: =K57/E57 -> 0.5
E59: =SUM(E43:E57) -> 239100 | K59: =SUM(K43:K57) -> 87450.216 | L59: =K59/E59 -> 0.36574745
A62: MESTIZO | D62: rto: 28 | E62: 46125
A64: CANTIDAD | B64: UNIDAD | C64: PRODUCTO | D64: PRECIO | E64: TOTAL | I64: PRECIO | J64: TOTAL | K64: DIFERENCIA
A65: 4 | B65: BOLSA | C65: PAPA BLANCA | D65: 25000 | E65: =A65*D65 -> 100000 | I65: 18000 | J65: =I65*A65 -> 72000 | K65: =E65-J65 -> 28000 | L65: =K65/E65 -> 0.28
A66: 4 | B66: KG | C66: MORRON ROJO | D66: 2800 | E66: =A66*D66 -> 11200 | I66: =15000/8 -> 1875 | J66: =I66*A66 -> 7500 | K66: =E66-J66 -> 3700 | L66: =K66/E66 -> 0.33035714
A67: 1 | B67: CAJON | C67: RUCULA | D67: 12000 | E67: =A67*D67 -> 12000 | I67: 8000 | J67: =I67*A67 -> 8000 | K67: =E67-J67 -> 4000 | L67: =K67/E67 -> 0.33333333
A68: 0.5 | B68: CAJON | C68: LECHUGA MORADA | D68: 12000 | E68: =A68*D68 -> 6000 | I68: 8000 | J68: =I68*A68 -> 4000 | K68: =E68-J68 -> 2000 | L68: =K68/E68 -> 0.33333333
A69: 1.5 | B69: KG | C69: LECHUGA FRANCESA | D69: 4000 | E69: =A69*D69 -> 6000 | I69: 2000 | J69: =I69*A69 -> 3000 | K69: =E69-J69 -> 3000 | L69: =K69/E69 -> 0.5
A70: 6 | B70: KG | C70: TOMATE PERITA | D70: 2200 | E70: =A70*D70 -> 13200 | I70: =11000/15 -> 733.33333 | J70: =I70*A70 -> 4400 | K70: =E70-J70 -> 8800 | L70: =K70/E70 -> 0.66666667
A71: 1 | B71: ATADO | C71: ALBAHACA | D71: 1500 | E71: =A71*D71 -> 1500 | I71: =10000/12 -> 833.33333 | J71: =I71*A71 -> 833.33333 | K71: =E71-J71 -> 666.66667 | L71: =K71/E71 -> 0.44444444
A72: 2.5 | B72: kg | C72: ANCO | D72: 1200 | E72: =A72*D72 -> 3000 | I72: =8000/15 -> 533.33333 | J72: =I72*A72 -> 1333.3333 | K72: =E72-J72 -> 1666.6667 | L72: =K72/E72 -> 0.55555556
A73: 1 | B73: ATADO | C73: APIO | D73: 2500 | E73: =A73*D73 -> 2500 | I73: =9000/8 -> 1125 | J73: =I73*A73 -> 1125 | K73: =E73-J73 -> 1375 | L73: =K73/E73 -> 0.55
A74: 0.5 | B74: KG | C74: REMOLACHA | D74: 2000 | E74: =A74*D74 -> 1000 | I74: =9000/8 -> 1125 | J74: =I74*A74 -> 562.5 | K74: =E74-J74 -> 437.5 | L74: =K74/E74 -> 0.4375
A75: 3 | B75: CAJON | C75: ESPINACA | D75: 17000 | E75: =A75*D75 -> 51000 | I75: 13000 | J75: =I75*A75 -> 39000 | K75: =E75-J75 -> 12000 | L75: =K75/E75 -> 0.23529412
A76: 1 | B76: KG | C76: LIMA | D76: 4000 | E76: =A76*D76 -> 4000 | I76: 2000 | J76: =I76*A76 -> 2000 | K76: =E76-J76 -> 2000 | L76: =K76/E76 -> 0.5
A77: 2 | B77: ATADO | C77: MENTA | D77: 3000 | E77: =A77*D77 -> 6000 | I77: 2000 | J77: =I77*A77 -> 4000 | K77: =E77-J77 -> 2000 | L77: =K77/E77 -> 0.33333333
A78: 0.5 | B78: CAJON | C78: LIMON | D78: 26000 | E78: =A78*D78 -> 13000 | I78: 16000 | J78: =I78*A78 -> 8000 | K78: =E78-J78 -> 5000 | L78: =K78/E78 -> 0.38461538
A79: 0.5 | B79: CAJON | C79: NARANJA | D79: 22000 | E79: =A79*D79 -> 11000 | I79: 16000 | J79: =I79*A79 -> 8000 | K79: =E79-J79 -> 3000 | L79: =K79/E79 -> 0.27272727
E81: =SUM(E65:E79) -> 241400 | K81: =SUM(K65:K79) -> 77645.833 | L81: =K81/E81 -> 0.32164803
A84: FABRIC SUSHI | D84: rto: 20 | E84: 46125
A86: CANTIDAD | B86: UNIDAD | C86: PRODUCTO | D86: PRECIO | E86: TOTAL | I86: PRECIO | J86: TOTAL | K86: DIFERENCIA
A87: 2 | B87: ATADO | C87: CEBOLLA DE VERDEO | D87: 4000 | E87: =A87*D87 -> 8000 | H87: S/C | J87: =I87*A87 -> 0 | K87: =E87-J87 -> 8000 | L87: =K87/E87 -> 1
A88: 3 | B88: ATADO | C88: CIBOULETTE | D88: 3500 | E88: =A88*D88 -> 10500 | I88: 2500 | J88: =I88*A88 -> 7500 | K88: =E88-J88 -> 3000 | L88: =K88/E88 -> 0.28571429
A89: 2 | B89: ATADO | C89: CILANTRO | D89: 2500 | E89: =A89*D89 -> 5000 | I89: =2500/6 -> 416.66667 | J89: =I89*A89 -> 833.33333 | K89: =E89-J89 -> 4166.6667 | L89: =K89/E89 -> 0.83333333
A90: 1 | B90: UNIDAD | C90: APIO | D90: 2500 | E90: =A90*D90 -> 2500 | I90: =9000/8 -> 1125 | J90: =I90*A90 -> 1125 | K90: =E90-J90 -> 1375 | L90: =K90/E90 -> 0.55
A91: 2 | B91: KG | C91: PEPINO | D91: 1200 | E91: =A91*D91 -> 2400 | H91: S/C | J91: =I91*A91 -> 0 | K91: =E91-J91 -> 2400 | L91: =K91/E91 -> 1
A92: 1 | B92: BANDEJA | C92: PORTOBELLO | D92: 6000 | E92: =A92*D92 -> 6000 | I92: 4500 | J92: =I92*A92 -> 4500 | K92: =E92-J92 -> 1500 | L92: =K92/E92 -> 0.25
A93: 0.5 | B93: KG | C93: JALAPEÑO ROJO | D93: 12000 | E93: =A93*D93 -> 6000 | I93: 8000 | J93: =I93*A93 -> 4000 | K93: =E93-J93 -> 2000 | L93: =K93/E93 -> 0.33333333
A94: 3 | B94: KG | C94: MORRON ROJO | D94: 2800 | E94: =A94*D94 -> 8400 | I94: =15000/8 -> 1875 | J94: =I94*A94 -> 5625 | K94: =E94-J94 -> 2775 | L94: =K94/E94 -> 0.33035714
A95: 2 | B95: KG | C95: MORRON VERDE | D95: 2800 | E95: =A95*D95 -> 5600 | I95: =13000/7 -> 1857.1429 | J95: =I95*A95 -> 3714.2857 | K95: =E95-J95 -> 1885.7143 | L95: =K95/E95 -> 0.33673469
A96: 2 | B96: KG | C96: MORRON AMARILLO | D96: 3000 | E96: =A96*D96 -> 6000 | I96: =14000/7 -> 2000 | J96: =I96*A96 -> 4000 | K96: =E96-J96 -> 2000 | L96: =K96/E96 -> 0.33333333
A97: 3 | B97: KG | C97: ZUCCINI | D97: 2800 | E97: =A97*D97 -> 8400 | I97: =28000/14 -> 2000 | J97: =I97*A97 -> 6000 | K97: =E97-J97 -> 2400 | L97: =K97/E97 -> 0.28571429
A98: 0.5 | B98: KG | C98: AJI PERUANO | D98: 22000 | E98: =A98*D98 -> 11000 | I98: 15000 | J98: =I98*A98 -> 7500 | K98: =E98-J98 -> 3500 | L98: =K98/E98 -> 0.31818182
A99: 3 | B99: KG | C99: CEBOLLA MORADA | D99: 1600 | E99: =A99*D99 -> 4800 | I99: =12000/15 -> 800 | J99: =I99*A99 -> 2400 | K99: =E99-J99 -> 2400 | L99: =K99/E99 -> 0.5
A100: 0.5 | B100: KG | C100: TOMATE | D100: 1200 | E100: =A100*D100 -> 600 | H100: S/C | J100: =I100*A100 -> 0 | K100: =E100-J100 -> 600 | L100: =K100/E100 -> 1
A101: 1 | B101: CAJA | C101: LIMON | D101: 26000 | E101: =A101*D101 -> 26000 | I101: =16000 -> 16000 | J101: =I101*A101 -> 16000 | K101: =E101-J101 -> 10000 | L101: =K101/E101 -> 0.38461538
E103: =SUM(E87:E102) -> 111200 | K103: =SUM(K87:K101) -> 48002.381 | L103: =K103/E103 -> 0.43167609
A106: UNIVERSIDAD DE MORENO | D106: rto: 5 | E106: 46125
A108: CANTIDAD | B108: UNIDAD | C108: PRODUCTO | D108: PRECIO | E108: TOTAL | I108: PRECIO | J108: TOTAL | K108: DIFERENCIA
A109: 1 | B109: BOLSA | C109: PAPA CEPILLADA | D109: 16000 | E109: =A109*D109 -> 16000 | I109: 13000 | J109: =I109*A109 -> 13000 | K109: =E109-J109 -> 3000 | L109: =K109/E109 -> 0.1875
A110: 1 | B110: BOLSA | C110: CEBOLLA | D110: 15000 | E110: =A110*D110 -> 15000 | I110: 13000 | J110: =I110*A110 -> 13000 | K110: =E110-J110 -> 2000 | L110: =K110/E110 -> 0.13333333
A111: 1 | B111: BOLSA | C111: ANCO | D111: 12000 | E111: =A111*D111 -> 12000 | I111: 8000 | J111: =I111*A111 -> 8000 | K111: =E111-J111 -> 4000 | L111: =K111/E111 -> 0.33333333
A112: 1 | B112: CAJON | C112: BERENJENA | D112: 12000 | E112: =A112*D112 -> 12000 | I112: 7000 | J112: =I112*A112 -> 7000 | K112: =E112-J112 -> 5000 | L112: =K112/E112 -> 0.41666667
A113: 0.5 | B113: CAJON | C113: ZUCCINI | D113: 32000 | E113: =A113*D113 -> 16000 | I113: 28000 | J113: =I113*A113 -> 14000 | K113: =E113-J113 -> 2000 | L113: =K113/E113 -> 0.125
A114: 1 | B114: CAJON | C114: TOMATE PERITA | D114: 16000 | E114: =A114*D114 -> 16000 | I114: 11000 | J114: =I114*A114 -> 11000 | K114: =E114-J114 -> 5000 | L114: =K114/E114 -> 0.3125
A115: 1 | B115: CAJON | C115: BROCOLI | D115: 22000 | E115: =A115*D115 -> 22000 | I115: 18000 | J115: =I115*A115 -> 18000 | K115: =E115-J115 -> 4000 | L115: =K115/E115 -> 0.18181818
A116: 1 | B116: CAJON | C116: ESPINACA | D116: 16000 | E116: =A116*D116 -> 16000 | I116: 13000 | J116: =I116*A116 -> 13000 | K116: =E116-J116 -> 3000 | L116: =K116/E116 -> 0.1875
A117: 1 | B117: BOLSA | C117: ZANAHORIA | D117: 12000 | E117: =A117*D117 -> 12000 | I117: 6000 | J117: =I117*A117 -> 6000 | K117: =E117-J117 -> 6000 | L117: =K117/E117 -> 0.5
A118: 4 | B118: ATADO | C118: RUCULA | D118: 500 | E118: =A118*D118 -> 2000 | I118: =2000/6 -> 333.33333 | J118: =I118*A118 -> 1333.3333 | K118: =E118-J118 -> 666.66667 | L118: =K118/E118 -> 0.33333333
A119: 5 | B119: KG | C119: MANZANA | D119: 4000 | E119: =A119*D119 -> 20000 | I119: =50000/17 -> 2941.1765 | J119: =I119*A119 -> 14705.882 | K119: =E119-J119 -> 5294.1176 | L119: =K119/E119 -> 0.26470588
A120: 5 | B120: UNIDAD | C120: PALTA HASS | D120: 1600 | E120: =A120*D120 -> 8000 | I120: 1250 | J120: =I120*A120 -> 6250 | K120: =E120-J120 -> 1750 | L120: =K120/E120 -> 0.21875
A121: 3 | B121: KG | C121: LECHUGA FRANCESA | D121: 4000 | E121: =A121*D121 -> 12000 | H121: S/C | J121: =I121*A121 -> 0 | K121: =E121-J121 -> 12000 | L121: =K121/E121 -> 1
A122: 1 | B122: ATADO | C122: PEREJIL | D122: 3500 | E122: =A122*D122 -> 3500 | I122: =6000/5 -> 1200 | J122: =I122*A122 -> 1200 | K122: =E122-J122 -> 2300 | L122: =K122/E122 -> 0.65714286
A123: 0.5 | B123: CAJON | C123: MORRON ROJO | D123: 20000 | E123: =A123*D123 -> 10000 | I123: 15000 | J123: =I123*A123 -> 7500 | K123: =E123-J123 -> 2500 | L123: =K123/E123 -> 0.25
A124: 0.5 | B124: CAJON | C124: ZAPALLITO REDONDO | D124: 28000 | E124: =A124*D124 -> 14000 | I124: 22000 | J124: =I124*A124 -> 11000 | K124: =E124-J124 -> 3000 | L124: =K124/E124 -> 0.21428571
A125: 1 | B125: ATADO | C125: LAUREL | D125: 3000 | E125: =A125*D125 -> 3000 | I125: 2000 | J125: =I125*A125 -> 2000 | K125: =E125-J125 -> 1000 | L125: =K125/E125 -> 0.33333333
...

Sheet 14-04-2026 
A3: COLEGIO WASHINGTON - LACROZE 1973 | E3: rto: 17 | F3: 46126 | I3: COMPRA
A5: CANTIDAD | B5: UNIDAD | C5: PRODUCTO | D5: PRECIO | E5: TOTAL | F5: TOTAL + IVA | I5: COSTO | J5: TOTAL | K5: DIFERENCIA
A6: 3 | B6: BOLSA | C6: PAPA BLANCA | D6: 25000 | E6: =A6*D6 -> 75000 | F6: =E6*1.105 -> 82875 | I6: 18000 | J6: =I6*A6 -> 54000 | K6: =F6-J6 -> 28875 | L6: =IFERROR(K6/E6, 0) -> 0.385
A7: 1 | B7: BOLSA | C7: CALABAZA | D7: 13000 | E7: =A7*D7 -> 13000 | F7: =E7*1.105 -> 14365 | I7: 8000 | J7: =I7*A7 -> 8000 | K7: =F7-J7 -> 6365 | L7: =IFERROR(K7/E7, 0) -> 0.48961538
A8: 1 | B8: BOLSA | C8: ZANAHORIA | D8: 12000 | E8: =A8*D8 -> 12000 | F8: =E8*1.105 -> 13260 | I8: 7000 | J8: =I8*A8 -> 7000 | K8: =F8-J8 -> 6260 | L8: =IFERROR(K8/E8, 0) -> 0.52166667
A9: 4 | B9: KG | C9: BATATA | D9: 1600 | E9: =A9*D9 -> 6400 | F9: =E9*1.105 -> 7072 | I9: =12000/11 -> 1090.9091 | J9: =I9*A9 -> 4363.6364 | K9: =F9-J9 -> 2708.3636 | L9: =IFERROR(K9/E9, 0) -> 0.42318182
A10: 5 | B10: KG | C10: CEBOLLA MORADA | D10: 1600 | E10: =A10*D10 -> 8000 | F10: =E10*1.105 -> 8840 | I10: 1000 | J10: =I10*A10 -> 5000 | K10: =F10-J10 -> 3840 | L10: =IFERROR(K10/E10, 0) -> 0.48
A11: 3 | B11: KG | C11: CEBOLLA | D11: 1200 | E11: =A11*D11 -> 3600 | F11: =E11*1.105 -> 3978 | I11: =13000/16 -> 812.5 | J11: =I11*A11 -> 2437.5 | K11: =F11-J11 -> 1540.5 | L11: =IFERROR(K11/E11, 0) -> 0.42791667
A12: 1 | B12: UNIDAD | C12: AJO | D12: 900 | E12: =A12*D12 -> 900 | F12: =E12*1.105 -> 994.5 | I12: 460 | J12: =I12*A12 -> 460 | K12: =F12-J12 -> 534.5 | L12: =IFERROR(K12/E12, 0) -> 0.59388889
A13: 5 | B13: KG | C13: ZAPALLITO REDONDO | D13: 2600 | E13: =A13*D13 -> 13000 | F13: =E13*1.105 -> 14365 | I13: =25000/14 -> 1785.7143 | J13: =I13*A13 -> 8928.5714 | K13: =F13-J13 -> 5436.4286 | L13: =IFERROR(K13/E13, 0) -> 0.41818681
A14: 5 | B14: KG | C14: POMELO | D14: 3000 | E14: =A14*D14 -> 15000 | F14: =E14*1.105 -> 16575 | I14: =32000/15 -> 2133.3333 | J14: =I14*A14 -> 10666.667 | K14: =F14-J14 -> 5908.3333 | L14: =IFERROR(K14/E14, 0) -> 0.39388889
A15: 16 | B15: KG | C15: TOMATE PERITA | D15: 1600 | E15: =A15*D15 -> 25600 | F15: =E15*1.105 -> 28288 | I15: =12000/15 -> 800 | J15: =I15*A15 -> 12800 | K15: =F15-J15 -> 15488 | L15: =IFERROR(K15/E15, 0) -> 0.605
A16: 3 | B16: UNIDAD | C16: PALTA | D16: 1000 | E16: =A16*D16 -> 3000 | F16: =E16*1.105 -> 3315 | I16: =20000/50 -> 400 | J16: =I16*A16 -> 1200 | K16: =F16-J16 -> 2115 | L16: =IFERROR(K16/E16, 0) -> 0.705
A17: 3 | B17: ATADO | C17: KALE | D17: 2000 | E17: =A17*D17 -> 6000 | F17: =E17*1.105 -> 6630 | I17: 1000 | J17: =I17*A17 -> 3000 | K17: =F17-J17 -> 3630 | L17: =IFERROR(K17/E17, 0) -> 0.605
A18: 0.5 | B18: ATADO | C18: PUERRO | D18: 5000 | E18: =A18*D18 -> 2500 | F18: =E18*1.105 -> 2762.5 | I18: 2500 | J18: =I18*A18 -> 1250 | K18: =F18-J18 -> 1512.5 | L18: =IFERROR(K18/E18, 0) -> 0.605
A19: 1 | B19: ATADO | C19: ALBAHACA | D19: 1500 | E19: =A19*D19 -> 1500 | F19: =E19*1.105 -> 1657.5 | I19: 1000 | J19: =I19*A19 -> 1000 | K19: =F19-J19 -> 657.5 | L19: =IFERROR(K19/E19, 0) -> 0.43833333
A20: 1 | B20: ATADO | C20: CILANTRO | D20: 3000 | E20: =A20*D20 -> 3000 | F20: =E20*1.105 -> 3315 | I20: =2500/6 -> 416.66667 | J20: =I20*A20 -> 416.66667 | K20: =F20-J20 -> 2898.3333 | L20: =IFERROR(K20/E20, 0) -> 0.96611111
A21: 0.5 | B21: KG | C21: REMOLACHA | D21: 2500 | E21: =A21*D21 -> 1250 | F21: =E21*1.105 -> 1381.25 | I21: 1500 | J21: =I21*A21 -> 750 | K21: =F21-J21 -> 631.25 | L21: =IFERROR(K21/E21, 0) -> 0.505
A22: 1 | B22: ATADO | C22: CIBOULETTE | D22: 3000 | E22: =A22*D22 -> 3000 | F22: =E22*1.105 -> 3315 | I22: 2000 | J22: =I22*A22 -> 2000 | K22: =F22-J22 -> 1315 | L22: =IFERROR(K22/E22, 0) -> 0.43833333
A23: 0.3 | B23: KG | C23: APIO | D23: 2500 | E23: =A23*D23 -> 750 | F23: =E23*1.105 -> 828.75 | I23: 1500 | J23: =I23*A23 -> 450 | K23: =F23-J23 -> 378.75 | L23: =IFERROR(K23/E23, 0) -> 0.505
A24: 1 | B24: KG | C24: TOMATE CHERRY | D24: 3000 | E24: =A24*D24 -> 3000 | F24: =E24*1.105 -> 3315 | I24: =12000/8 -> 1500 | J24: =I24*A24 -> 1500 | K24: =F24-J24 -> 1815 | L24: =IFERROR(K24/E24, 0) -> 0.605
A25: 1 | B25: KG | C25: ZUCCINI | D25: 2800 | E25: =A25*D25 -> 2800 | F25: =E25*1.105 -> 3094 | I25: =30000/14 -> 2142.8571 | J25: =I25*A25 -> 2142.8571 | K25: =F25-J25 -> 951.14286 | L25: =IFERROR(K25/E25, 0) -> 0.33969388
A26: 0.5 | B26: KG | C26: BERENJENA | D26: 1500 | E26: =A26*D26 -> 750 | F26: =E26*1.105 -> 828.75 | I26: 1000 | J26: =I26*A26 -> 500 | K26: =F26-J26 -> 328.75 | L26: =IFERROR(K26/E26, 0) -> 0.43833333
A27: 2 | B27: UNIDAD | C27: BROCOLI | D27: 3200 | E27: =A27*D27 -> 6400 | F27: =E27*1.105 -> 7072 | I27: =22000/8 -> 2750 | J27: =I27*A27 -> 5500 | K27: =F27-J27 -> 1572 | L27: =IFERROR(K27/E27, 0) -> 0.245625
A28: 2.3 | B28: KG | C28: REPOLLO COLORADO | D28: 1800 | E28: =A28*D28 -> 4140 | F28: =E28*1.105 -> 4574.7 | I28: 800 | J28: =I28*A28 -> 1840 | K28: =F28-J28 -> 2734.7 | L28: =IFERROR(K28/E28, 0) -> 0.66055556
A29: 3.1 | B29: KG | C29: REPOLLO BLANCO | D29: 1800 | E29: =A29*D29 -> 5580 | F29: =E29*1.105 -> 6165.9 | I29: 800 | J29: =I29*A29 -> 2480 | K29: =F29-J29 -> 3685.9 | L29: =IFERROR(K29/E29, 0) -> 0.66055556
A30: 1 | B30: KG | C30: CEBOLLA DE VERDEO | D30: 4500 | E30: =A30*D30 -> 4500 | F30: =E30*1.105 -> 4972.5 | I30: 2000 | J30: =I30*A30 -> 2000 | K30: =F30-J30 -> 2972.5 | L30: =IFERROR(K30/E30, 0) -> 0.66055556
A31: 2 | B31: KG | C31: MORRON AMARILLO | D31: 2800 | E31: =A31*D31 -> 5600 | F31: =E31*1.105 -> 6188 | I31: =15000/7 -> 2142.8571 | J31: =I31*A31 -> 4285.7143 | K31: =F31-J31 -> 1902.2857 | L31: =IFERROR(K31/E31, 0) -> 0.33969388
A32: 2 | B32: KG | C32: MORRON VERDE | D32: 2400 | E32: =A32*D32 -> 4800 | F32: =E32*1.105 -> 5304 | I32: =12000/7 -> 1714.2857 | J32: =I32*A32 -> 3428.5714 | K32: =F32-J32 -> 1875.4286 | L32: =IFERROR(K32/E32, 0) -> 0.39071429
A33: 4 | B33: KG | C33: MORRON ROJO | D33: 3200 | E33: =A33*D33 -> 12800 | F33: =E33*1.105 -> 14144 | I33: =15000/7 -> 2142.8571 | J33: =I33*A33 -> 8571.4286 | K33: =F33-J33 -> 5572.5714 | L33: =IFERROR(K33/E33, 0) -> 0.43535714
A34: 7 | B34: MAPLE | C34: HUEVO N1 | D34: 4500 | E34: =A34*D34 -> 31500 | F34: =E34*1.21 -> 38115 | I34: =54000/12 -> 4500 | J34: =I34*A34 -> 31500 | K34: =F34-J34 -> 6615 | L34: =IFERROR(K34/E34, 0) -> 0.21
A35: 5 | B35: KG | C35: MANZANA VERDE | D35: 4500 | E35: =A35*D35 -> 22500 | F35: =E35*1.105 -> 24862.5 | I35: =60000/17 -> 3529.4118 | J35: =I35*A35 -> 17647.059 | K35: =F35-J35 -> 7215.4412 | L35: =IFERROR(K35/E35, 0) -> 0.32068627
A36: 4 | B36: KG | C36: MANZANA ROJA | D36: 3600 | E36: =A36*D36 -> 14400 | F36: =E36*1.105 -> 15912 | I36: =50000/17 -> 2941.1765 | J36: =I36*A36 -> 11764.706 | K36: =F36-J36 -> 4147.2941 | L36: =IFERROR(K36/E36, 0) -> 0.28800654
A37: 2 | B37: CAJON | C37: NARANJA | D37: 22000 | E37: =A37*D37 -> 44000 | F37: =E37*1.105 -> 48620 | I37: 15000 | J37: =I37*A37 -> 30000 | K37: =F37-J37 -> 18620 | L37: =IFERROR(K37/E37, 0) -> 0.42318182
A38: 3 | B38: KG | C38: LECHUGA CRIOLLA | D38: 6000 | E38: =A38*D38 -> 18000 | F38: =E38*1.105 -> 19890 | I38: =20000/4 -> 5000 | J38: =I38*A38 -> 15000 | K38: =F38-J38 -> 4890 | L38: =IFERROR(K38/E38, 0) -> 0.27166667
A39: 25 | B39: ATADO | C39: RUCULA | D39: 600 | E39: =A39*D39 -> 15000 | F39: =E39*1.105 -> 16575 | I39: =9000/24 -> 375 | J39: =I39*A39 -> 9375 | K39: =F39-J39 -> 7200 | L39: =IFERROR(K39/E39, 0) -> 0.48
A40: 0.5 | B40: KG | C40: PEPINO | D40: 1500 | E40: =A40*D40 -> 750 | F40: =E40*1.105 -> 828.75 | I40: =12000/14 -> 857.14286 | J40: =I40*A40 -> 428.57143 | K40: =F40-J40 -> 400.17857 | L40: =IFERROR(K40/E40, 0) -> 0.53357143
E42: =SUM(E6:E40) -> 390020 | F42: =SUM(F6:F40) -> 434279.6 | K42: =SUM(K6:K40) -> 162592.65 | L42: =K42/F42 -> 0.37439624
A45: COLEGIO SJCB - VIRREY DEL PINO 3299 | E45: rto: 20 | F45: 46126 | I45: COMPRA
A47: CANTIDAD | B47: UNIDAD | C47: PRODUCTO | D47: PRECIO | E47: TOTAL | F47: TOTAL + IVA | I47: COSTO | J47: TOTAL | K47: DIFERENCIA
A48: 2 | B48: KG | C48: CEBOLLA DE VERDEO | D48: 4500 | E48: =A48*D48 -> 9000 | F48: =E48*1.105 -> 9945 | I48: 2500 | J48: =I48*A48 -> 5000 | K48: =F48-J48 -> 4945 | L48: =IFERROR(K48/E48, 0) -> 0.54944444
A49: 2 | B49: UNIDAD | C49: AJO | D49: 900 | E49: =A49*D49 -> 1800 | F49: =E49*1.105 -> 1989 | I49: 460 | J49: =I49*A49 -> 920 | K49: =F49-J49 -> 1069 | L49: =IFERROR(K49/E49, 0) -> 0.59388889
A50: 1 | B50: ATADO | C50: ALBAHACA | D50: 1500 | E50: =A50*D50 -> 1500 | F50: =E50*1.105 -> 1657.5 | I50: 1000 | J50: =I50*A50 -> 1000 | K50: =F50-J50 -> 657.5 | L50: =IFERROR(K50/E50, 0) -> 0.43833333
A51: 1 | B51: UNIDAD | C51: APIO | D51: 2500 | E51: =A51*D51 -> 2500 | F51: =E51*1.105 -> 2762.5 | I51: 1500 | J51: =I51*A51 -> 1500 | K51: =F51-J51 -> 1262.5 | L51: =IFERROR(K51/E51, 0) -> 0.505
A52: 5 | B52: KG | C52: BANANA | D52: 3000 | E52: =A52*D52 -> 15000 | F52: =E52*1.105 -> 16575 | I52: =28000/17 -> 1647.0588 | J52: =I52*A52 -> 8235.2941 | K52: =F52-J52 -> 8339.7059 | L52: =IFERROR(K52/E52, 0) -> 0.55598039
A53: 1 | B53: BOLSA | C53: BATATA | D53: 16000 | E53: =A53*D53 -> 16000 | F53: =E53*1.105 -> 17680 | I53: 12000 | J53: =I53*A53 -> 12000 | K53: =F53-J53 -> 5680 | L53: =IFERROR(K53/E53, 0) -> 0.355
A54: 3 | B54: UNIDAD | C54: BROCOLI | D54: 3200 | E54: =A54*D54 -> 9600 | F54: =E54*1.105 -> 10608 | I54: =22000/8 -> 2750 | J54: =I54*A54 -> 8250 | K54: =F54-J54 -> 2358 | L54: =IFERROR(K54/E54, 0) -> 0.245625
A55: 1 | B55: BOLSA | C55: CALABAZA | D55: 13000 | E55: =A55*D55 -> 13000 | F55: =E55*1.105 -> 14365 | I55: 8000 | J55: =I55*A55 -> 8000 | K55: =F55-J55 -> 6365 | L55: =IFERROR(K55/E55, 0) -> 0.48961538
A56: 6 | B56: KG | C56: CEBOLLA MORADA | D56: 1600 | E56: =A56*D56 -> 9600 | F56: =E56*1.105 -> 10608 | I56: 1000 | J56: =I56*A56 -> 6000 | K56: =F56-J56 -> 4608 | L56: =IFERROR(K56/E56, 0) -> 0.48
A57: 4 | B57: KG | C57: CEBOLLA | D57: 1200 | E57: =A57*D57 -> 4800 | F57: =E57*1.105 -> 5304 | I57: 812 | J57: =I57*A57 -> 3248 | K57: =F57-J57 -> 2056 | L57: =IFERROR(K57/E57, 0) -> 0.42833333
A58: 6 | B58: KG | C58: MANDARINA | D58: 1200 | E58: =A58*D58 -> 7200 | F58: =E58*1.105 -> 7956 | I58: =10000/14 -> 714.28571 | J58: =I58*A58 -> 4285.7143 | K58: =F58-J58 -> 3670.2857 | L58: =IFERROR(K58/E58, 0) -> 0.5097619
A59: 4 | B59: KG | C59: MANZANA ROJA | D59: 3600 | E59: =A59*D59 -> 14400 | F59: =E59*1.105 -> 15912 | I59: =50000/17 -> 2941.1765 | J59: =I59*A59 -> 11764.706 | K59: =F59-J59 -> 4147.2941 | L59: =IFERROR(K59/E59, 0) -> 0.28800654
A60: 4 | B60: KG | C60: MANZANA VERDE | D60: 4500 | E60: =A60*D60 -> 18000 | F60: =E60*1.105 -> 19890 | I60: =60000/17 -> 3529.4118 | J60: =I60*A60 -> 14117.647 | K60: =F60-J60 -> 5772.3529 | L60: =IFERROR(K60/E60, 0) -> 0.32068627
A61: 22 | B61: KG | C61: NARANJA | D61: 1700 | E61: =A61*D61 -> 37400 | F61: =E61*1.105 -> 41327 | I61: 1000 | J61: =I61*A61 -> 22000 | K61: =F61-J61 -> 19327 | L61: =IFERROR(K61/E61, 0) -> 0.51676471
A62: 3 | B62: BOLSA | C62: PAPA BLANCA | D62: 25000 | E62: =A62*D62 -> 75000 | F62: =E62*1.105 -> 82875 | I62: 18000 | J62: =I62*A62 -> 54000 | K62: =F62-J62 -> 28875 | L62: =IFERROR(K62/E62, 0) -> 0.385
A63: 2 | B63: ATADO | C63: CILANTRO | D63: 3000 | E63: =A63*D63 -> 6000 | F63: =E63*1.105 -> 6630 | I63: =2500/6 -> 416.66667 | J63: =I63*A63 -> 833.33333 | K63: =F63-J63 -> 5796.6667 | L63: =IFERROR(K63/E63, 0) -> 0.96611111
A64: 0.5 | B64: ATADO | C64: PEREJIL | D64: 3500 | E64: =A64*D64 -> 1750 | F64: =E64*1.105 -> 1933.75 | I64: 1500 | J64: =I64*A64 -> 750 | K64: =F64-J64 -> 1183.75 | L64: =IFERROR(K64/E64, 0) -> 0.67642857
A65: 0.5 | B65: KG | C65: PEPINO | D65: 1500 | E65: =A65*D65 -> 750 | F65: =E65*1.105 -> 828.75 | I65: =12000/14 -> 857.14286 | J65: =I65*A65 -> 428.57143 | K65: =F65-J65 -> 400.17857 | L65: =IFERROR(K65/E65, 0) -> 0.53357143
A66: 7 | B66: KG | C66: MORRON ROJO | D66: 3200 | E66: =A66*D66 -> 22400 | F66: =E66*1.105 -> 24752 | I66: =15000/7 -> 2142.8571 | J66: =I66*A66 -> 15000 | K66: =F66-J66 -> 9752 | L66: =IFERROR(K66/E66, 0) -> 0.43535714
A67: 4 | B67: KG | C67: MORRON VERDE | D67: 2400 | E67: =A67*D67 -> 9600 | F67: =E67*1.105 -> 10608 | I67: =12000/7 -> 1714.2857 | J67: =I67*A67 -> 6857.1429 | K67: =F67-J67 -> 3750.8571 | L67: =IFERROR(K67/E67, 0) -> 0.39071429
A68: 3 | B68: KG | C68: MORRON AMARILLO | D68: 2800 | E68: =A68*D68 -> 8400 | F68: =E68*1.105 -> 9282 | I68: =15000/7 -> 2142.8571 | J68: =I68*A68 -> 6428.5714 | K68: =F68-J68 -> 2853.4286 | L68: =IFERROR(K68/E68, 0) -> 0.33969388
A69: 0.25 | B69: ATADO | C69: PUERRO | D69: 5000 | E69: =A69*D69 -> 1250 | F69: =E69*1.105 -> 1381.25 | I69: 2000 | J69: =I69*A69 -> 500 | K69: =F69-J69 -> 881.25 | L69: =IFERROR(K69/E69, 0) -> 0.705
A70: 5 | B70: KG | C70: POMELO | D70: 3000 | E70: =A70*D70 -> 15000 | F70: =E70*1.105 -> 16575 | I70: =32000/15 -> 2133.3333 | J70: =I70*A70 -> 10666.667 | K70: =F70-J70 -> 5908.3333 | L70: =IFERROR(K70/E70, 0) -> 0.39388889
A71: 1 | B71: KG | C71: REMOLACHA | D71: 2500 | E71: =A71*D71 -> 2500 | F71: =E71*1.105 -> 2762.5 | I71: 1500 | J71: =I71*A71 -> 1500 | K71: =F71-J71 -> 1262.5 | L71: =IFERROR(K71/E71, 0) -> 0.505
A72: 1 | B72: KG | C72: REPOLLO BLANCO | D72: 1800 | E72: =A72*D72 -> 1800 | F72: =E72*1.105 -> 1989 | I72: 800 | J72: =I72*A72 -> 800 | K72: =F72-J72 -> 1189 | L72: =IFERROR(K72/E72, 0) -> 0.66055556
A73: 1.5 | B73: KG | C73: REPOLLO COLORADO | D73: 1800 | E73: =A73*D73 -> 2700 | F73: =E73*1.105 -> 2983.5 | I73: 800 | J73: =I73*A73 -> 1200 | K73: =F73-J73 -> 1783.5 | L73: =IFERROR(K73/E73, 0) -> 0.66055556
A74: 12 | B74: KG | C74: TOMATE PERITA | D74: 1600 | E74: =A74*D74 -> 19200 | F74: =E74*1.105 -> 21216 | I74: =11000/15 -> 733.33333 | J74: =I74*A74 -> 8800 | K74: =F74-J74 -> 12416 | L74: =IFERROR(K74/E74, 0) -> 0.64666667
A75: 0.9 | B75: KG | C75: TOMATE CHERRY | D75: 3000 | E75: =A75*D75 -> 2700 | F75: =E75*1.105 -> 2983.5 | I75: =12000/8 -> 1500 | J75: =I75*A75 -> 1350 | K75: =F75-J75 -> 1633.5 | L75: =IFERROR(K75/E75, 0) -> 0.605
A76: 2 | B76: BOLSA | C76: ZANAHORIA | D76: 12000 | E76: =A76*D76 -> 24000 | F76: =E76*1.105 -> 26520 | I76: 7000 | J76: =I76*A76 -> 14000 | K76: =F76-J76 -> 12520 | L76: =IFERROR(K76/E76, 0) -> 0.52166667
A77: 3.5 | B77: KG | C77: ZAPALLITO REDONDO | D77: 2600 | E77: =A77*D77 -> 9100 | F77: =E77*1.105 -> 10055.5 | I77: =25000/14 -> 1785.7143 | J77: =I77*A77 -> 6250 | K77: =F77-J77 -> 3805.5 | L77: =IFERROR(K77/E77, 0) -> 0.41818681
A78: 5 | B78: UNIDAD | C78: PALTA | D78: 1000 | E78: =A78*D78 -> 5000 | F78: =E78*1.105 -> 5525 | I78: 500 | J78: =I78*A78 -> 2500 | K78: =F78-J78 -> 3025 | L78: =IFERROR(K78/E78, 0) -> 0.605
A79: 1 | B79: UNIDAD | C79: KALE | D79: 2000 | E79: =A79*D79 -> 2000 | F79: =E79*1.105 -> 2210 | I79: 1000 | J79: =I79*A79 -> 1000 | K79: =F79-J79 -> 1210 | L79: =IFERROR(K79/E79, 0) -> 0.605
A80: 0.5 | B80: KG | C80: ZUCCINI | D80: 2800 | E80: =A80*D80 -> 1400 | F80: =E80*1.105 -> 1547 | I80: =30000/14 -> 2142.8571 | J80: =I80*A80 -> 1071.4286 | K80: =F80-J80 -> 475.57143 | L80: =IFERROR(K80/E80, 0) -> 0.33969388
A81: 2 | B81: KG | C81: LECHUGA CRIOLLA | D81: 6000 | E81: =A81*D81 -> 12000 | F81: =E81*1.105 -> 13260 | I81: =20000/5 -> 4000 | J81: =I81*A81 -> 8000 | K81: =F81-J81 -> 5260 | L81: =IFERROR(K81/E81, 0) -> 0.43833333
A82: 15 | B82: ATADO | C82: RUCULA | D82: 600 | E82: =A82*D82 -> 9000 | F82: =E82*1.105 -> 9945 | I82: =9000/24 -> 375 | J82: =I82*A82 -> 5625 | K82: =F82-J82 -> 4320 | L82: =IFERROR(K82/E82, 0) -> 0.48
A83: 0.5 | B83: KG | C83: BERENJENA | D83: 1500 | E83: =A83*D83 -> 750 | F83: =E83*1.105 -> 828.75 | I83: 1000 | J83: =I83*A83 -> 500 | K83: =F83-J83 -> 328.75 | L83: =IFERROR(K83/E83, 0) -> 0.43833333
A84: 0.5 | B84: CAJON | C84: HUEVO N1 | D84: 54000 | E84: =A84*D84 -> 27000 | F84: =E84*1.21 -> 32670 | I84: 54000 | J84: =I84*A84 -> 27000 | K84: =F84-J84 -> 5670 | L84: =IFERROR(K84/E84, 0) -> 0.21
E86: =SUM(E48:E84) -> 419100 | F86: =SUM(F48:F84) -> 465940.5 | K86: =SUM(K48:K84) -> 184558.42 | L86: =K86/F86 -> 0.3960987
A91: COLEGIO VILLA DEVOTO SCHOOL - PEDRO MORAN 4441 | E91: rto: 20 | F91: 46126 | I91: COMPRA
A93: CANTIDAD | B93: UNIDAD | C93: PRODUCTO | D93: PRECIO | E93: TOTAL | F93: TOTAL + IVA | I93: COSTO | J93: TOTAL | K93: DIFERENCIA
A94: 3 | B94: UNIDAD | C94: BROCOLI | D94: 3200 | E94: =A94*D94 -> 9600 | F94: =E94*1.105 -> 10608 | I94: =22000/8 -> 2750 | J94: =I94*A94 -> 8250 | K94: =F94-J94 -> 2358 | L94: =IFERROR(K94/E94, 0) -> 0.245625
A95: 5 | B95: KG | C95: MORRON ROJO | D95: 3200 | E95: =A95*D95 -> 16000 | F95: =E95*1.105 -> 17680 | I95: =15000/7 -> 2142.8571 | J95: =I95*A95 -> 10714.286 | K95: =F95-J95 -> 6965.7143 | L95: =IFERROR(K95/E95, 0) -> 0.43535714
A96: 4 | B96: KG | C96: MORRON VERDE | D96: 2400 | E96: =A96*D96 -> 9600 | F96: =E96*1.105 -> 10608 | I96: =12000/7 -> 1714.2857 | J96: =I96*A96 -> 6857.1429 | K96: =F96-J96 -> 3750.8571 | L96: =IFERROR(K96/E96, 0) -> 0.39071429
A97: 4 | B97: KG | C97: MORRON AMARILLO | D97: 2800 | E97: =A97*D97 -> 11200 | F97: =E97*1.105 -> 12376 | I97: 2142.86 | J97: =I97*A97 -> 8571.44 | K97: =F97-J97 -> 3804.56 | L97: =IFERROR(K97/E97, 0) -> 0.33969286
A98: 4 | B98: KG | C98: CEBOLLA MORADA | D98: 1600 | E98: =A98*D98 -> 6400 | F98: =E98*1.105 -> 7072 | I98: 1000 | J98: =I98*A98 -> 4000 | K98: =F98-J98 -> 3072 | L98: =IFERROR(K98/E98, 0) -> 0.48
A99: 2 | B99: KG | C99: CEBOLLA | D99: 1200 | E99: =A99*D99 -> 2400 | F99: =E99*1.105 -> 2652 | I99: 812 | J99: =I99*A99 -> 1624 | K99: =F99-J99 -> 1028 | L99: =IFERROR(K99/E99, 0) -> 0.42833333
A100: 1 | B100: KG | C100: REMOLACHA | D100: 2500 | E100: =A100*D100 -> 2500 | F100: =E100*1.105 -> 2762.5 | I100: 1500 | J100: =I100*A100 -> 1500 | K100: =F100-J100 -> 1262.5 | L100: =IFERROR(K100/E100, 0) -> 0.505
A101: 1 | B101: KG | C101: CEBOLLA DE VERDEO | D101: 4500 | E101: =A101*D101 -> 4500 | F101: =E101*1.105 -> 4972.5 | I101: 2000 | J101: =I101*A101 -> 2000 | K101: =F101-J101 -> 2972.5 | L101: =IFERROR(K101/E101, 0) -> 0.66055556
A102: 3 | B102: UNIDAD | C102: PALTA | D102: 1000 | E102: =A102*D102 -> 3000 | F102: =E102*1.105 -> 3315 | I102: 500 | J102: =I102*A102 -> 1500 | K102: =F102-J102 -> 1815 | L102: =IFERROR(K102/E102, 0) -> 0.605
A103: 2 | B103: ATADO | C103: KALE | D103: 2000 | E103: =A103*D103 -> 4000 | F103: =E103*1.105 -> 4420 | I103: 1000 | J103: =I103*A103 -> 2000 | K103: =F103-J103 -> 2420 | L103: =IFERROR(K103/E103, 0) -> 0.605
A104: 1 | B104: KG | C104: ZUCCINI | D104: 2800 | E104: =A104*D104 -> 2800 | F104: =E104*1.105 -> 3094 | I104: =30000/14 -> 2142.8571 | J104: =I104*A104 -> 2142.8571 | K104: =F104-J104 -> 951.14286 | L104: =IFERROR(K104/E104, 0) -> 0.33969388
A105: 2 | B105: KG | C105: BERENJENA | D105: 1500 | E105: =A105*D105 -> 3000 | F105: =E105*1.105 -> 3315 | I105: 1000 | J105: =I105*A105 -> 2000 | K105: =F105-J105 -> 1315 | L105: =IFERROR(K105/E105, 0) -> 0.43833333
A106: 2 | B106: KG | C106: REPOLLO BLANCO | D106: 1800 | E106: =A106*D106 -> 3600 | F106: =E106*1.105 -> 3978 | I106: 800 | J106: =I106*A106 -> 1600 | K106: =F106-J106 -> 2378 | L106: =IFERROR(K106/E106, 0) -> 0.66055556
A107: 2 | B107: KG | C107: REPOLLO COLORADO | D107: 1800 | E107: =A107*D107 -> 3600 | F107: =E107*1.105 -> 3978 | I107: 800 | J107: =I107*A107 -> 1600 | K107: =F107-J107 -> 2378 | L107: =IFERROR(K107/E107, 0) -> 0.66055556
A108: 1 | B108: ATADO | C108: PEREJIL | D108: 3500 | E108: =A108*D108 -> 3500 | F108: =E108*1.105 -> 3867.5 | I108: 1500 | J108: =I108*A108 -> 1500 | K108: =F108-J108 -> 2367.5 | L108: =IFERROR(K108/E108, 0) -> 0.67642857
A109: 1 | B109: ATADO | C109: CILANTRO | D109: 3000 | E109: =A109*D109 -> 3000 | F109: =E109*1.105 -> 3315 | I109: =2500/6 -> 416.66667 | J109: =I109*A109 -> 416.66667 | K109: =F109-J109 -> 2898.3333 | L109: =IFERROR(K109/E109, 0) -> 0.96611111
A110: 1 | B110: ATADO | C110: CIBOULETTE | D110: 3000 | E110: =A110*D110 -> 3000 | F110: =E110*1.105 -> 3315 | I110: 2000 | J110: =I110*A110 -> 2000 | K110: =F110-J110 -> 1315 | L110: =IFERROR(K110/E110, 0) -> 0.43833333
A111: 4 | B111: KG | C111: ZAPALLITO REDONDO | D111: 2600 | E111: =A111*D111 -> 10400 | F111: =E111*1.105 -> 11492 | I111: =25000/14 -> 1785.7143 | J111: =I111*A111 -> 7142.8571 | K111: =F111-J111 -> 4349.1429 | L111: =IFERROR(K111/E111, 0) -> 0.41818681
A112: 2 | B112: BOLSA | C112: ANCO | D112: 13000 | E112: =A112*D112 -> 26000 | F112: =E112*1.105 -> 28730 | I112: 8000 | J112: =I112*A112 -> 16000 | K112: =F112-J112 -> 12730 | L112: =IFERROR(K112/E112, 0) -> 0.48961538
A113: 2 | B113: BOLSA | C113: ZANAHORIA | D113: 12000 | E113: =A113*D113 -> 24000 | F113: =E113*1.105 -> 26520 | I113: 7000 | J113: =I113*A113 -> 14000 | K113: =F113-J113 -> 12520 | L113: =IFERROR(K113/E113, 0) -> 0.52166667
...

Sheet 15-04-2026 
A3: COLEGIO SAN MARCOS | SAN ISIDRO | E3: rto: 15 | F3: 46127 | G3: ** | I3: COMPRA
A5: CANTIDAD | B5: UNIDAD | C5: PRODUCTO | D5: PRECIO | E5: TOTAL | F5: TOTAL + IVA | I5: COSTO | J5: TOTAL | K5: DIFERENCIA
A6: 1 | B6: CAJON | C6: TOMATE PERITA | D6: 22000 | E6: =A6*D6 -> 22000 | F6: =E6*1.105 -> 24310 | I6: 12000 | J6: =I6*A6 -> 12000 | K6: =F6-J6 -> 12310 | L6: =IFERROR(K6/E6, 0) -> 0.55954545
A7: 1 | B7: CAJON | C7: LECHUGA CRIOLLA | D7: 24000 | E7: =A7*D7 -> 24000 | F7: =E7*1.105 -> 26520 | I7: 17000 | J7: =I7*A7 -> 17000 | K7: =F7-J7 -> 9520 | L7: =IFERROR(K7/E7, 0) -> 0.39666667
A8: 2 | B8: CAJON | C8: RUCULA | D8: 13000 | E8: =A8*D8 -> 26000 | F8: =E8*1.105 -> 28730 | I8: 9000 | J8: =I8*A8 -> 18000 | K8: =F8-J8 -> 10730 | L8: =IFERROR(K8/E8, 0) -> 0.41269231
A9: 5 | B9: BOLSA | C9: PAPA BLANCA | D9: 25000 | E9: =A9*D9 -> 125000 | F9: =E9*1.105 -> 138125 | I9: 18000 | J9: =I9*A9 -> 90000 | K9: =F9-J9 -> 48125 | L9: =IFERROR(K9/E9, 0) -> 0.385
A10: 2 | B10: BOLSA | C10: ANCO | D10: 13000 | E10: =A10*D10 -> 26000 | F10: =E10*1.105 -> 28730 | I10: 8000 | J10: =I10*A10 -> 16000 | K10: =F10-J10 -> 12730 | L10: =IFERROR(K10/E10, 0) -> 0.48961538
A11: 1 | B11: BOLSA | C11: BATATA | D11: 16000 | E11: =A11*D11 -> 16000 | F11: =E11*1.105 -> 17680 | I11: 12000 | J11: =I11*A11 -> 12000 | K11: =F11-J11 -> 5680 | L11: =IFERROR(K11/E11, 0) -> 0.355
A12: 6.8 | B12: KG | C12: REPOLLO BLANCO | D12: 1800 | E12: =A12*D12 -> 12240 | F12: =E12*1.105 -> 13525.2 | I12: 800 | J12: =I12*A12 -> 5440 | K12: =F12-J12 -> 8085.2 | L12: =IFERROR(K12/E12, 0) -> 0.66055556
A13: 4.2 | B13: KG | C13: REPOLLO COLORADO | D13: 1800 | E13: =A13*D13 -> 7560 | F13: =E13*1.105 -> 8353.8 | I13: 800 | J13: =I13*A13 -> 3360 | K13: =F13-J13 -> 4993.8 | L13: =IFERROR(K13/E13, 0) -> 0.66055556
A14: 2 | B14: KG | C14: MORRON ROJO | D14: 3200 | E14: =A14*D14 -> 6400 | F14: =E14*1.105 -> 7072 | I14: =15000/7 -> 2142.8571 | J14: =I14*A14 -> 4285.7143 | K14: =F14-J14 -> 2786.2857 | L14: =IFERROR(K14/E14, 0) -> 0.43535714
A15: 2 | B15: KG | C15: MORRON VERDE | D15: 2400 | E15: =A15*D15 -> 4800 | F15: =E15*1.105 -> 5304 | I15: =14000/7 -> 2000 | J15: =I15*A15 -> 4000 | K15: =F15-J15 -> 1304 | L15: =IFERROR(K15/E15, 0) -> 0.27166667
A16: 2 | B16: KG | C16: MORRON AMARILLO | D16: 2800 | E16: =A16*D16 -> 5600 | F16: =E16*1.105 -> 6188 | I16: 2142.86 | J16: =I16*A16 -> 4285.72 | K16: =F16-J16 -> 1902.28 | L16: =IFERROR(K16/E16, 0) -> 0.33969286
A17: 2 | B17: UNIDAD | C17: BROCOLI | D17: 3200 | E17: =A17*D17 -> 6400 | F17: =E17*1.105 -> 7072 | I17: =25000/9 -> 2777.7778 | J17: =I17*A17 -> 5555.5556 | K17: =F17-J17 -> 1516.4444 | L17: =IFERROR(K17/E17, 0) -> 0.23694444
A18: 1 | B18: ATADO | C18: PUERRO | D18: 5000 | E18: =A18*D18 -> 5000 | F18: =E18*1.105 -> 5525 | I18: 2000 | J18: =I18*A18 -> 2000 | K18: =F18-J18 -> 3525 | L18: =IFERROR(K18/E18, 0) -> 0.705
A19: 1 | B19: KG | C19: CEBOLLA DE VERDEO | D19: 4500 | E19: =A19*D19 -> 4500 | F19: =E19*1.105 -> 4972.5 | I19: 1400 | J19: =I19*A19 -> 1400 | K19: =F19-J19 -> 3572.5 | L19: =IFERROR(K19/E19, 0) -> 0.79388889
A20: 4 | B20: KG | C20: ZAPALLITO REDONDO | D20: 2600 | E20: =A20*D20 -> 10400 | F20: =E20*1.105 -> 11492 | I20: =28000/14 -> 2000 | J20: =I20*A20 -> 8000 | K20: =F20-J20 -> 3492 | L20: =IFERROR(K20/E20, 0) -> 0.33576923
A21: 1 | B21: UNIDAD | C21: APIO | D21: 2500 | E21: =A21*D21 -> 2500 | F21: =E21*1.105 -> 2762.5 | H21: S/C | J21: =I21*A21 -> 0 | K21: =F21-J21 -> 2762.5 | L21: =IFERROR(K21/E21, 0) -> 1.105
A22: 2 | B22: ATADO | C22: KALE | D22: 2000 | E22: =A22*D22 -> 4000 | F22: =E22*1.105 -> 4420 | I22: 1000 | J22: =I22*A22 -> 2000 | K22: =F22-J22 -> 2420 | L22: =IFERROR(K22/E22, 0) -> 0.605
A23: 1 | B23: ATADO | C23: CILANTRO | D23: 3000 | E23: =A23*D23 -> 3000 | F23: =E23*1.105 -> 3315 | I23: =2500/6 -> 416.66667 | J23: =I23*A23 -> 416.66667 | K23: =F23-J23 -> 2898.3333 | L23: =IFERROR(K23/E23, 0) -> 0.96611111
A24: 1 | B24: ATADO | C24: CIBOULETTE | D24: 3000 | E24: =A24*D24 -> 3000 | F24: =E24*1.105 -> 3315 | I24: 2000 | J24: =I24*A24 -> 2000 | K24: =F24-J24 -> 1315 | L24: =IFERROR(K24/E24, 0) -> 0.43833333
A25: 2 | B25: UNIDAD | C25: AJO | D25: 900 | E25: =A25*D25 -> 1800 | F25: =E25*1.105 -> 1989 | I25: 460 | J25: =I25*A25 -> 920 | K25: =F25-J25 -> 1069 | L25: =IFERROR(K25/E25, 0) -> 0.59388889
A26: 5 | B26: KG | C26: CEBOLLA | D26: 1200 | E26: =A26*D26 -> 6000 | F26: =E26*1.105 -> 6630 | I26: =13000/16 -> 812.5 | J26: =I26*A26 -> 4062.5 | K26: =F26-J26 -> 2567.5 | L26: =IFERROR(K26/E26, 0) -> 0.42791667
A27: 1 | B27: ATADO | C27: ALBAHACA | D27: 1500 | E27: =A27*D27 -> 1500 | F27: =E27*1.105 -> 1657.5 | I27: =15000/18 -> 833.33333 | J27: =I27*A27 -> 833.33333 | K27: =F27-J27 -> 824.16667 | L27: =IFERROR(K27/E27, 0) -> 0.54944444
A28: 1 | B28: CAJON | C28: MANZANA VERDE | D28: 72000 | E28: =A28*D28 -> 72000 | F28: =E28*1.105 -> 79560 | I28: 60000 | J28: =I28*A28 -> 60000 | K28: =F28-J28 -> 19560 | L28: =IFERROR(K28/E28, 0) -> 0.27166667
A29: 2 | B29: CAJON | C29: NARANJA | D29: 22000 | E29: =A29*D29 -> 44000 | F29: =E29*1.105 -> 48620 | I29: 14000 | J29: =I29*A29 -> 28000 | K29: =F29-J29 -> 20620 | L29: =IFERROR(K29/E29, 0) -> 0.46863636
A30: 5 | B30: KG | C30: POMELO | D30: 3000 | E30: =A30*D30 -> 15000 | F30: =E30*1.105 -> 16575 | I30: =32000/15 -> 2133.3333 | J30: =I30*A30 -> 10666.667 | K30: =F30-J30 -> 5908.3333 | L30: =IFERROR(K30/E30, 0) -> 0.39388889
A31: 10.7 | B31: KG | C31: BANANA | D31: 3000 | E31: =A31*D31 -> 32100 | F31: =E31*1.105 -> 35470.5 | I31: =28000/17 -> 1647.0588 | J31: =I31*A31 -> 17623.529 | K31: =F31-J31 -> 17846.971 | L31: =IFERROR(K31/E31, 0) -> 0.55598039
A32: 0.5 | B32: CAJON | C32: HUEVO N1 | D32: 54000 | E32: =A32*D32 -> 27000 | F32: =E32*1.21 -> 32670 | I32: 54000 | J32: =I32*A32 -> 27000 | K32: =F32-J32 -> 5670 | L32: =IFERROR(K32/E32, 0) -> 0.21
E34: =SUM(E6:E32) -> 513800 | F34: =SUM(F6:F32) -> 570584 | K34: =SUM(K6:K32) -> 213734.31 | L34: =K34/F34 -> 0.37458869
A40: COLEGIO SWORM JUNIOR COLLAGE | PACHECO | E40: rto: 14 | F40: 46127 | I40: COMPRA
A42: CANTIDAD | B42: UNIDAD | C42: PRODUCTO | D42: PRECIO | E42: TOTAL | F42: TOTAL + IVA | I42: COSTO | J42: TOTAL | K42: DIFERENCIA
A43: 5.7 | B43: KG | C43: REPOLLO BLANCO | D43: 1800 | E43: =A43*D43 -> 10260 | F43: =E43*1.105 -> 11337.3 | I43: 800 | J43: =I43*A43 -> 4560 | K43: =F43-J43 -> 6777.3 | L43: =IFERROR(K43/E43, 0) -> 0.66055556
A44: 2.8 | B44: KG | C44: REPOLLO COLORADO | D44: 1800 | E44: =A44*D44 -> 5040 | F44: =E44*1.105 -> 5569.2 | I44: 800 | J44: =I44*A44 -> 2240 | K44: =F44-J44 -> 3329.2 | L44: =IFERROR(K44/E44, 0) -> 0.66055556
A45: 17 | B45: KG | C45: TOMATE PERITA | D45: 1600 | E45: =A45*D45 -> 27200 | F45: =E45*1.105 -> 30056 | I45: =12000/15 -> 800 | J45: =I45*A45 -> 13600 | K45: =F45-J45 -> 16456 | L45: =IFERROR(K45/E45, 0) -> 0.605
A46: 4 | B46: KG | C46: LECHUGA CRIOLLA | D46: 6000 | E46: =A46*D46 -> 24000 | F46: =E46*1.105 -> 26520 | I46: =17000/5 -> 3400 | J46: =I46*A46 -> 13600 | K46: =F46-J46 -> 12920 | L46: =IFERROR(K46/E46, 0) -> 0.53833333
A47: 12 | B47: ATADO | C47: RUCULA | D47: 600 | E47: =A47*D47 -> 7200 | F47: =E47*1.105 -> 7956 | I47: =9000/24 -> 375 | J47: =I47*A47 -> 4500 | K47: =F47-J47 -> 3456 | L47: =IFERROR(K47/E47, 0) -> 0.48
A48: 3 | B48: UNIDAD | C48: BROCOLI | D48: 3200 | E48: =A48*D48 -> 9600 | F48: =E48*1.105 -> 10608 | I48: =25000/9 -> 2777.7778 | J48: =I48*A48 -> 8333.3333 | K48: =F48-J48 -> 2274.6667 | L48: =IFERROR(K48/E48, 0) -> 0.23694444
A49: 5 | B49: KG | C49: CEBOLLA MORADA | D49: 1600 | E49: =A49*D49 -> 8000 | F49: =E49*1.105 -> 8840 | I49: =1000 -> 1000 | J49: =I49*A49 -> 5000 | K49: =F49-J49 -> 3840 | L49: =IFERROR(K49/E49, 0) -> 0.48
A50: 2 | B50: KG | C50: CEBOLLA | D50: 1200 | E50: =A50*D50 -> 2400 | F50: =E50*1.105 -> 2652 | I50: =13000/16 -> 812.5 | J50: =I50*A50 -> 1625 | K50: =F50-J50 -> 1027 | L50: =IFERROR(K50/E50, 0) -> 0.42791667
A51: 6 | B51: KG | C51: MORRON ROJO | D51: 3200 | E51: =A51*D51 -> 19200 | F51: =E51*1.105 -> 21216 | I51: =15000/7 -> 2142.8571 | J51: =I51*A51 -> 12857.143 | K51: =F51-J51 -> 8358.8571 | L51: =IFERROR(K51/E51, 0) -> 0.43535714
A52: 6 | B52: KG | C52: MORRON VERDE | D52: 2400 | E52: =A52*D52 -> 14400 | F52: =E52*1.105 -> 15912 | I52: =14000/7 -> 2000 | J52: =I52*A52 -> 12000 | K52: =F52-J52 -> 3912 | L52: =IFERROR(K52/E52, 0) -> 0.27166667
A53: 5 | B53: KG | C53: MORRON AMARILLO | D53: 2800 | E53: =A53*D53 -> 14000 | F53: =E53*1.105 -> 15470 | I53: 2142.86 | J53: =I53*A53 -> 10714.3 | K53: =F53-J53 -> 4755.7 | L53: =IFERROR(K53/E53, 0) -> 0.33969286
A54: 1 | B54: KG | C54: CEBOLLA DE VERDEO | D54: 4500 | E54: =A54*D54 -> 4500 | F54: =E54*1.105 -> 4972.5 | I54: 1400 | J54: =I54*A54 -> 1400 | K54: =F54-J54 -> 3572.5 | L54: =IFERROR(K54/E54, 0) -> 0.79388889
A55: 1 | B55: ATADO | C55: ALBAHACA | D55: 1500 | E55: =A55*D55 -> 1500 | F55: =E55*1.105 -> 1657.5 | I55: =15000/18 -> 833.33333 | J55: =I55*A55 -> 833.33333 | K55: =F55-J55 -> 824.16667 | L55: =IFERROR(K55/E55, 0) -> 0.54944444
A56: 1 | B56: ATADO | C56: ESPINACA | D56: 1700 | E56: =A56*D56 -> 1700 | F56: =E56*1.105 -> 1878.5 | I56: =1500 -> 1500 | J56: =I56*A56 -> 1500 | K56: =F56-J56 -> 378.5 | L56: =IFERROR(K56/E56, 0) -> 0.22264706
A57: 1.4 | B57: KG | C57: PUERRO | D57: 5000 | E57: =A57*D57 -> 7000 | F57: =E57*1.105 -> 7735 | I57: 2000 | J57: =I57*A57 -> 2800 | K57: =F57-J57 -> 4935 | L57: =IFERROR(K57/E57, 0) -> 0.705
A58: 2 | B58: UNIDAD | C58: APIO | D58: 2500 | E58: =A58*D58 -> 5000 | F58: =E58*1.105 -> 5525 | H58: S/C | J58: =I58*A58 -> 0 | K58: =F58-J58 -> 5525 | L58: =IFERROR(K58/E58, 0) -> 1.105
A59: 4 | B59: BOLSA | C59: PAPA BLANCA | D59: 25000 | E59: =A59*D59 -> 100000 | F59: =E59*1.105 -> 110500 | I59: 18000 | J59: =I59*A59 -> 72000 | K59: =F59-J59 -> 38500 | L59: =IFERROR(K59/E59, 0) -> 0.385
A60: 1 | B60: BOLSA | C60: CALABAZA | D60: 13000 | E60: =A60*D60 -> 13000 | F60: =E60*1.105 -> 14365 | I60: 8000 | J60: =I60*A60 -> 8000 | K60: =F60-J60 -> 6365 | L60: =IFERROR(K60/E60, 0) -> 0.48961538
A61: 0.5 | B61: CAJON | C61: HUEVO N1 | D61: 54000 | E61: =A61*D61 -> 27000 | F61: =E61*1.21 -> 32670 | I61: 54000 | J61: =I61*A61 -> 27000 | K61: =F61-J61 -> 5670 | L61: =IFERROR(K61/E61, 0) -> 0.21
A62: 1 | B62: CAJON | C62: NARANJA | D62: 22000 | E62: =A62*D62 -> 22000 | F62: =E62*1.105 -> 24310 | I62: 14000 | J62: =I62*A62 -> 14000 | K62: =F62-J62 -> 10310 | L62: =IFERROR(K62/E62, 0) -> 0.46863636
A63: 5 | B63: KG | C63: MANZANA ROJA | D63: 3600 | E63: =A63*D63 -> 18000 | F63: =E63*1.105 -> 19890 | I63: =50000/17 -> 2941.1765 | J63: =I63*A63 -> 14705.882 | K63: =F63-J63 -> 5184.1176 | L63: =IFERROR(K63/E63, 0) -> 0.28800654
A64: 5 | B64: KG | C64: MANZANA VERDE | D64: 4500 | E64: =A64*D64 -> 22500 | F64: =E64*1.105 -> 24862.5 | I64: =60000/17 -> 3529.4118 | J64: =I64*A64 -> 17647.059 | K64: =F64-J64 -> 7215.4412 | L64: =IFERROR(K64/E64, 0) -> 0.32068627
A65: 5 | B65: KG | C65: POMELO | D65: 3000 | E65: =A65*D65 -> 15000 | F65: =E65*1.105 -> 16575 | I65: =32000/15 -> 2133.3333 | J65: =I65*A65 -> 10666.667 | K65: =F65-J65 -> 5908.3333 | L65: =IFERROR(K65/E65, 0) -> 0.39388889
A66: 5 | B66: KG | C66: BANANA | D66: 3000 | E66: =A66*D66 -> 15000 | F66: =E66*1.105 -> 16575 | I66: =28000/17 -> 1647.0588 | J66: =I66*A66 -> 8235.2941 | K66: =F66-J66 -> 8339.7059 | L66: =IFERROR(K66/E66, 0) -> 0.55598039
E68: =SUM(E43:E66) -> 393500 | F68: =SUM(F43:F66) -> 437652.5 | K68: =SUM(K54:K66) -> 102727.76 | L68: =K68/F68 -> 0.2347245
A73: COLEGIO ST. MATTHEWS | CAAMAÑO | E73: rto: 16 | F73: 46127 | I73: COMPRA
A75: CANTIDAD | B75: UNIDAD | C75: PRODUCTO | D75: PRECIO | E75: TOTAL | F75: TOTAL + IVA | I75: COSTO | J75: TOTAL | K75: DIFERENCIA
A76: 0.5 | B76: CAJON | C76: HUEVO N1 | D76: 54000 | E76: =A76*D76 -> 27000 | F76: =E76*1.21 -> 32670 | I76: 54000 | J76: =I76*A76 -> 27000 | K76: =F76-J76 -> 5670 | L76: =IFERROR(K76/E76, 0) -> 0.21
A77: 5 | B77: BOLSA | C77: PAPA BLANCA | D77: 25000 | E77: =A77*D77 -> 125000 | F77: =E77*1.105 -> 138125 | I77: 18000 | J77: =I77*A77 -> 90000 | K77: =F77-J77 -> 48125 | L77: =IFERROR(K77/E77, 0) -> 0.385
A78: 1 | B78: BOLSA | C78: CALABAZA | D78: 13000 | E78: =A78*D78 -> 13000 | F78: =E78*1.105 -> 14365 | I78: 8000 | J78: =I78*A78 -> 8000 | K78: =F78-J78 -> 6365 | L78: =IFERROR(K78/E78, 0) -> 0.48961538
A79: 1 | B79: BOLSA | C79: BATATA | D79: 16000 | E79: =A79*D79 -> 16000 | F79: =E79*1.105 -> 17680 | I79: 12000 | J79: =I79*A79 -> 12000 | K79: =F79-J79 -> 5680 | L79: =IFERROR(K79/E79, 0) -> 0.355
A80: 5 | B80: KG | C80: CEBOLLA | D80: 1200 | E80: =A80*D80 -> 6000 | F80: =E80*1.105 -> 6630 | I80: =13000/16 -> 812.5 | J80: =I80*A80 -> 4062.5 | K80: =F80-J80 -> 2567.5 | L80: =IFERROR(K80/E80, 0) -> 0.42791667
A81: 3 | B81: KG | C81: CEBOLLA MORADA | D81: 1600 | E81: =A81*D81 -> 4800 | F81: =E81*1.105 -> 5304 | I81: 1000 | J81: =I81*A81 -> 3000 | K81: =F81-J81 -> 2304 | L81: =IFERROR(K81/E81, 0) -> 0.48
A82: 4 | B82: KG | C82: MORRON ROJO | D82: 3200 | E82: =A82*D82 -> 12800 | F82: =E82*1.105 -> 14144 | I82: =15000/7 -> 2142.8571 | J82: =I82*A82 -> 8571.4286 | K82: =F82-J82 -> 5572.5714 | L82: =IFERROR(K82/E82, 0) -> 0.43535714
A83: 4 | B83: KG | C83: MORRON VERDE | D83: 2400 | E83: =A83*D83 -> 9600 | F83: =E83*1.105 -> 10608 | I83: 2000 | J83: =I83*A83 -> 8000 | K83: =F83-J83 -> 2608 | L83: =IFERROR(K83/E83, 0) -> 0.27166667
A84: 3 | B84: KG | C84: MORRON AMARILLO | D84: 2800 | E84: =A84*D84 -> 8400 | F84: =E84*1.105 -> 9282 | I84: 2142.86 | J84: =I84*A84 -> 6428.58 | K84: =F84-J84 -> 2853.42 | L84: =IFERROR(K84/E84, 0) -> 0.33969286
A85: 1 | B85: KG | C85: REPOLLO COLORADO | D85: 1800 | E85: =A85*D85 -> 1800 | F85: =E85*1.105 -> 1989 | I85: 800 | J85: =I85*A85 -> 800 | K85: =F85-J85 -> 1189 | L85: =IFERROR(K85/E85, 0) -> 0.66055556
A86: 2 | B86: BOLSA | C86: ZANAHORIA | D86: 12000 | E86: =A86*D86 -> 24000 | F86: =E86*1.105 -> 26520 | I86: 7000 | J86: =I86*A86 -> 14000 | K86: =F86-J86 -> 12520 | L86: =IFERROR(K86/E86, 0) -> 0.52166667
A87: 0.5 | B87: KG | C87: PUERRO | D87: 5000 | E87: =A87*D87 -> 2500 | F87: =E87*1.105 -> 2762.5 | I87: 2000 | J87: =I87*A87 -> 1000 | K87: =F87-J87 -> 1762.5 | L87: =IFERROR(K87/E87, 0) -> 0.705
A88: 0.25 | B88: ATADO | C88: PEREJIL | D88: 3500 | E88: =A88*D88 -> 875 | F88: =E88*1.105 -> 966.875 | I88: 1500 | J88: =I88*A88 -> 375 | K88: =F88-J88 -> 591.875 | L88: =IFERROR(K88/E88, 0) -> 0.67642857
A89: 1 | B89: ATADO | C89: CILANTRO | D89: 3000 | E89: =A89*D89 -> 3000 | F89: =E89*1.105 -> 3315 | I89: =2500/6 -> 416.66667 | J89: =I89*A89 -> 416.66667 | K89: =F89-J89 -> 2898.3333 | L89: =IFERROR(K89/E89, 0) -> 0.96611111
A90: 1 | B90: ATADO | C90: CIBOULETTE | D90: 3000 | E90: =A90*D90 -> 3000 | F90: =E90*1.105 -> 3315 | I90: 2000 | J90: =I90*A90 -> 2000 | K90: =F90-J90 -> 1315 | L90: =IFERROR(K90/E90, 0) -> 0.43833333
A91: 0.5 | B91: KG | C91: BERENJENA | D91: 1500 | E91: =A91*D91 -> 750 | F91: =E91*1.105 -> 828.75 | I91: =7000/7 -> 1000 | J91: =I91*A91 -> 500 | K91: =F91-J91 -> 328.75 | L91: =IFERROR(K91/E91, 0) -> 0.43833333
A92: 2 | B92: KG | C92: CEBOLLA DE VERDEO | D92: 4500 | E92: =A92*D92 -> 9000 | F92: =E92*1.105 -> 9945 | I92: 1400 | J92: =I92*A92 -> 2800 | K92: =F92-J92 -> 7145 | L92: =IFERROR(K92/E92, 0) -> 0.79388889
A93: 7 | B93: KG | C93: TOMATE PERITA | D93: 1600 | E93: =A93*D93 -> 11200 | F93: =E93*1.105 -> 12376 | I93: =12000/15 -> 800 | J93: =I93*A93 -> 5600 | K93: =F93-J93 -> 6776 | L93: =IFERROR(K93/E93, 0) -> 0.605
A94: 5 | B94: KG | C94: LECHUGA CRIOLLA | D94: 6000 | E94: =A94*D94 -> 30000 | F94: =E94*1.105 -> 33150 | I94: =17000/5 -> 3400 | J94: =I94*A94 -> 17000 | K94: =F94-J94 -> 16150 | L94: =IFERROR(K94/E94, 0) -> 0.53833333
A95: 16 | B95: ATADO | C95: RUCULA | D95: 600 | E95: =A95*D95 -> 9600 | F95: =E95*1.105 -> 10608 | I95: =9000/24 -> 375 | J95: =I95*A95 -> 6000 | K95: =F95-J95 -> 4608 | L95: =IFERROR(K95/E95, 0) -> 0.48
A96: 0.5 | B96: KG | C96: TOMATE CHERRY | D96: 3000 | E96: =A96*D96 -> 1500 | F96: =E96*1.105 -> 1657.5 | I96: =7000/7 -> 1000 | J96: =I96*A96 -> 500 | K96: =F96-J96 -> 1157.5 | L96: =IFERROR(K96/E96, 0) -> 0.77166667
A97: 0.5 | B97: KG | C97: REMOLACHA | D97: 2500 | E97: =A97*D97 -> 1250 | F97: =E97*1.105 -> 1381.25 | I97: =14000/9 -> 1555.5556 | J97: =I97*A97 -> 777.77778 | K97: =F97-J97 -> 603.47222 | L97: =IFERROR(K97/E97, 0) -> 0.48277778
A98: 2 | B98: KG | C98: ZAPALLITO REDONDO | D98: 2600 | E98: =A98*D98 -> 5200 | F98: =E98*1.105 -> 5746 | I98: =28000/14 -> 2000 | J98: =I98*A98 -> 4000 | K98: =F98-J98 -> 1746 | L98: =IFERROR(K98/E98, 0) -> 0.33576923
A99: 1 | B99: UNIDAD | C99: BROCOLI | D99: 3200 | E99: =A99*D99 -> 3200 | F99: =E99*1.105 -> 3536 | I99: =25000/9 -> 2777.7778 | J99: =I99*A99 -> 2777.7778 | K99: =F99-J99 -> 758.22222 | L99: =IFERROR(K99/E99, 0) -> 0.23694444
A100: 1.5 | B100: CAJON | C100: NARANJA | D100: 22000 | E100: =A100*D100 -> 33000 | F100: =E100*1.105 -> 36465 | I100: 14000 | J100: =I100*A100 -> 21000 | K100: =F100-J100 -> 15465 | L100: =IFERROR(K100/E100, 0) -> 0.46863636
A101: 12 | B101: KG | C101: MANZANA ROJA | D101: 3600 | E101: =A101*D101 -> 43200 | F101: =E101*1.105 -> 47736 | I101: =50000/17 -> 2941.1765 | J101: =I101*A101 -> 35294.118 | K101: =F101-J101 -> 12441.882 | L101: =IFERROR(K101/E101, 0) -> 0.28800654
A102: 10 | B102: KG | C102: MANZANA VERDE | D102: 4500 | E102: =A102*D102 -> 45000 | F102: =E102*1.105 -> 49725 | I102: =60000/17 -> 3529.4118 | J102: =I102*A102 -> 35294.118 | K102: =F102-J102 -> 14430.882 | L102: =IFERROR(K102/E102, 0) -> 0.32068627
A103: 3 | B103: KG | C103: MANDARINA | D103: 1200 | E103: =A103*D103 -> 3600 | F103: =E103*1.105 -> 3978 | I103: =8000/14 -> 571.42857 | J103: =I103*A103 -> 1714.2857 | K103: =F103-J103 -> 2263.7143 | L103: =IFERROR(K103/E103, 0) -> 0.62880952
A104: 3 | B104: KG | C104: BANANA | D104: 3000 | E104: =A104*D104 -> 9000 | F104: =E104*1.105 -> 9945 | I104: =28000/17 -> 1647.0588 | J104: =I104*A104 -> 4941.1765 | K104: =F104-J104 -> 5003.8235 | L104: =IFERROR(K104/E104, 0) -> 0.55598039
A105: 3 | B105: KG | C105: POMELO | D105: 3000 | E105: =A105*D105 -> 9000 | F105: =E105*1.105 -> 9945 | I105: =32000/15 -> 2133.3333 | J105: =I105*A105 -> 6400 | K105: =F105-J105 -> 3545 | L105: =IFERROR(K105/E105, 0) -> 0.39388889
A106: 0.5 | B106: KG | C106: PEPINO | D106: 1500 | E106: =A106*D106 -> 750 | F106: =E106*1.105 -> 828.75 | I106: =12000/14 -> 857.14286 | J106: =I106*A106 -> 428.57143 | K106: =F106-J106 -> 400.17857 | L106: =IFERROR(K106/E106, 0) -> 0.53357143
A107: 1 | B107: ATADO | C107: ALBAHACA | D107: 1500 | E107: =A107*D107 -> 1500 | F107: =E107*1.105 -> 1657.5 | I107: =15000/18 -> 833.33333 | J107: =I107*A107 -> 833.33333 | K107: =F107-J107 -> 824.16667 | L107: =IFERROR(K107/E107, 0) -> 0.54944444
A108: 2 | B108: UNIDAD | C108: AJO | D108: 900 | E108: =A108*D108 -> 1800 | F108: =E108*1.105 -> 1989 | I108: 460 | J108: =I108*A108 -> 920 | K108: =F108-J108 -> 1069 | L108: =IFERROR(K108/E108, 0) -> 0.59388889
E110: =SUM(E76:E108) -> 476325 | F110: =SUM(F76:F108) -> 529174.12 | K110: =SUM(K76:K108) -> 196738.79 | L110: =K110/F110 -> 0.3717846
A114: MUNCHIS | F114: 46127 | I114: COMPRA
A116: CANTIDAD | B116: UNIDAD | C116: PRODUCTO | D116: PRECIO | E116: TOTAL | F116: TOTAL + IVA | I116: COSTO | J116: TOTAL | K116: DIFERENCIA
A117: 0.5 | B117: KG | C117: LECHUGA MORADA | D117: 4500 | E117: =A117*D117 -> 2250 | F117: =E117*1.105 -> 2486.25 | H117: S/C | J117: =I117*A117 -> 0 | K117: =F117-J117 -> 2486.25 | L117: =IFERROR(K117/E117, 0) -> 1.105
A118: 2 | B118: KG | C118: TOMATE CHERRY | D118: 3000 | E118: =A118*D118 -> 6000 | F118: =E118*1.105 -> 6630 | I118: 1000 | J118: =I118*A118 -> 2000 | K118: =F118-J118 -> 4630 | L118: =IFERROR(K118/E118, 0) -> 0.77166667
A119: 2 | B119: KG | C119: BANANA | D119: 3000 | E119: =A119*D119 -> 6000 | F119: =E119*1.105 -> 6630 | I119: =28000/17 -> 1647.0588 | J119: =I119*A119 -> 3294.1176 | K119: =F119-J119 -> 3335.8824 | L119: =IFERROR(K119/E119, 0) -> 0.55598039
A120: 0.5 | B120: CAJON | C120: LIMON | D120: 24000 | E120: =A120*D120 -> 12000 | F120: =E120*1.105 -> 13260 | I120: 14000 | J120: =I120*A120 -> 7000 | K120: =F120-J120 -> 6260 | L120: =IFERROR(K120/E120, 0) -> 0.52166667
A121: 1 | B121: ATADO | C121: MENTA | D121: 3000 | E121: =A121*D121 -> 3000 | F121: =E121*1.105 -> 3315 | I121: 2000 | J121: =I121*A121 -> 2000 | K121: =F121-J121 -> 1315 | L121: =IFERROR(K121/E121, 0) -> 0.43833333
...

Sheet 17-04-2026 
A3: COLEGIO SJCB - VIRREY DEL PINO 3299 | E3: rto: 21 | F3: 46129 | G3: ** | I3: COMPRA
A5: CANTIDAD | B5: UNIDAD | C5: PRODUCTO | D5: PRECIO | E5: TOTAL | F5: TOTAL + IVA | I5: COSTO | J5: TOTAL | K5: DIFERENCIA
A6: 1 | B6: KG | C6: CEBOLLA DE VERDEO | D6: 4500 | E6: =A6*D6 -> 4500 | F6: =E6*1.105 -> 4972.5 | I6: 1400 | J6: =I6*A6 -> 1400 | K6: =F6-J6 -> 3572.5 | L6: =IFERROR(K6/E6, 0) -> 0.79388889
A7: 1 | B7: UNIDAD | C7: AJO | D7: 900 | E7: =A7*D7 -> 900 | F7: =E7*1.105 -> 994.5 | I7: 460 | J7: =I7*A7 -> 460 | K7: =F7-J7 -> 534.5 | L7: =IFERROR(K7/E7, 0) -> 0.59388889
A8: 1 | B8: ATADO | C8: ALBAHACA | D8: 1500 | E8: =A8*D8 -> 1500 | F8: =E8*1.105 -> 1657.5 | I8: 750 | J8: =I8*A8 -> 750 | K8: =F8-J8 -> 907.5 | L8: =IFERROR(K8/E8, 0) -> 0.605
A9: 3 | B9: KG | C9: BANANA | D9: 3000 | E9: =A9*D9 -> 9000 | F9: =E9*1.105 -> 9945 | I9: =28000/17 -> 1647.0588 | J9: =I9*A9 -> 4941.1765 | K9: =F9-J9 -> 5003.8235 | L9: =IFERROR(K9/E9, 0) -> 0.55598039
A10: 12 | B10: KG | C10: CALABAZA | D10: 900 | E10: =A10*D10 -> 10800 | F10: =E10*1.105 -> 11934 | I10: =8000/15 -> 533.33333 | J10: =I10*A10 -> 6400 | K10: =F10-J10 -> 5534 | L10: =IFERROR(K10/E10, 0) -> 0.51240741
A11: 2 | B11: KG | C11: CEBOLLA MORADA | D11: 1600 | E11: =A11*D11 -> 3200 | F11: =E11*1.105 -> 3536 | I11: 1000 | J11: =I11*A11 -> 2000 | K11: =F11-J11 -> 1536 | L11: =IFERROR(K11/E11, 0) -> 0.48
A12: 0.7 | B12: KG | C12: CHAUCHA PLANA | D12: 3600 | E12: =A12*D12 -> 2520 | F12: =E12*1.105 -> 2784.6 | I12: =15000/7 -> 2142.8571 | J12: =I12*A12 -> 1500 | K12: =F12-J12 -> 1284.6 | L12: =IFERROR(K12/E12, 0) -> 0.5097619
A13: 25 | B13: UNIDAD | C13: CHOCLO | D13: 500 | E13: =A13*D13 -> 12500 | F13: =E13*1.105 -> 13812.5 | I13: =85000/224 -> 379.46429 | J13: =I13*A13 -> 9486.6071 | K13: =F13-J13 -> 4325.8929 | L13: =IFERROR(K13/E13, 0) -> 0.34607143
A14: 9 | B14: ATADO | C14: ESPINACA | D14: 1700 | E14: =A14*D14 -> 15300 | F14: =E14*1.105 -> 16906.5 | I14: =1400 -> 1400 | J14: =I14*A14 -> 12600 | K14: =F14-J14 -> 4306.5 | L14: =IFERROR(K14/E14, 0) -> 0.28147059
A15: 1 | B15: KG | C15: FRUTILLA | D15: 12500 | E15: =A15*D15 -> 12500 | F15: =E15*1.105 -> 13812.5 | I15: =45000/4 -> 11250 | J15: =I15*A15 -> 11250 | K15: =F15-J15 -> 2562.5 | L15: =IFERROR(K15/E15, 0) -> 0.205
A16: 4 | B16: KG | C16: MANDARINA | D16: 800 | E16: =A16*D16 -> 3200 | F16: =E16*1.105 -> 3536 | I16: =8000/14 -> 571.42857 | J16: =I16*A16 -> 2285.7143 | K16: =F16-J16 -> 1250.2857 | L16: =IFERROR(K16/E16, 0) -> 0.39071429
A17: 4 | B17: KG | C17: MANZANA ROJA | D17: 3600 | E17: =A17*D17 -> 14400 | F17: =E17*1.105 -> 15912 | I17: =50000/17 -> 2941.1765 | J17: =I17*A17 -> 11764.706 | K17: =F17-J17 -> 4147.2941 | L17: =IFERROR(K17/E17, 0) -> 0.28800654
A18: 4 | B18: KG | C18: MANZANA VERDE | D18: 4500 | E18: =A18*D18 -> 18000 | F18: =E18*1.105 -> 19890 | I18: =62000/17 -> 3647.0588 | J18: =I18*A18 -> 14588.235 | K18: =F18-J18 -> 5301.7647 | L18: =IFERROR(K18/E18, 0) -> 0.29454248
A19: 1.5 | B19: CAJON | C19: NARANJA | D19: 22000 | E19: =A19*D19 -> 33000 | F19: =E19*1.105 -> 36465 | I19: 17000 | J19: =I19*A19 -> 25500 | K19: =F19-J19 -> 10965 | L19: =IFERROR(K19/E19, 0) -> 0.33227273
A20: 1 | B20: BOLSA | C20: PAPA BLANCA | D20: 25000 | E20: =A20*D20 -> 25000 | F20: =E20*1.105 -> 27625 | I20: 18000 | J20: =I20*A20 -> 18000 | K20: =F20-J20 -> 9625 | L20: =IFERROR(K20/E20, 0) -> 0.385
A21: 1 | B21: ATADO | C21: CIBOULETTE | D21: 3000 | E21: =A21*D21 -> 3000 | F21: =E21*1.105 -> 3315 | I21: 2500 | J21: =I21*A21 -> 2500 | K21: =F21-J21 -> 815 | L21: =IFERROR(K21/E21, 0) -> 0.27166667
A22: 1 | B22: ATADO | C22: CILANTRO | D22: 3000 | E22: =A22*D22 -> 3000 | F22: =E22*1.105 -> 3315 | I22: 1000 | J22: =I22*A22 -> 1000 | K22: =F22-J22 -> 2315 | L22: =IFERROR(K22/E22, 0) -> 0.77166667
A23: 0.2 | B23: ATADO | C23: PEREJIL | D23: 3500 | E23: =A23*D23 -> 700 | F23: =E23*1.105 -> 773.5 | I23: 1000 | J23: =I23*A23 -> 200 | K23: =F23-J23 -> 573.5 | L23: =IFERROR(K23/E23, 0) -> 0.81928571
A24: 0.75 | B24: KG | C24: PEPINO | D24: 2600 | E24: =A24*D24 -> 1950 | F24: =E24*1.105 -> 2154.75 | I24: =30000/15 -> 2000 | J24: =I24*A24 -> 1500 | K24: =F24-J24 -> 654.75 | L24: =IFERROR(K24/E24, 0) -> 0.33576923
A25: 1.5 | B25: KG | C25: MORRON ROJO | D25: 3200 | E25: =A25*D25 -> 4800 | F25: =E25*1.105 -> 5304 | I25: =15000/7 -> 2142.8571 | J25: =I25*A25 -> 3214.2857 | K25: =F25-J25 -> 2089.7143 | L25: =IFERROR(K25/E25, 0) -> 0.43535714
A26: 0.5 | B26: KG | C26: MORRON VERDE | D26: 2400 | E26: =A26*D26 -> 1200 | F26: =E26*1.105 -> 1326 | I26: =10000/7 -> 1428.5714 | J26: =I26*A26 -> 714.28571 | K26: =F26-J26 -> 611.71429 | L26: =IFERROR(K26/E26, 0) -> 0.5097619
A27: 0.5 | B27: KG | C27: MORRON AMARILLO | D27: 2800 | E27: =A27*D27 -> 1400 | F27: =E27*1.105 -> 1547 | I27: =15000/7 -> 2142.8571 | J27: =I27*A27 -> 1071.4286 | K27: =F27-J27 -> 475.57143 | L27: =IFERROR(K27/E27, 0) -> 0.33969388
A28: 8 | B28: KG | C28: PUERRO | D28: 5000 | E28: =A28*D28 -> 40000 | F28: =E28*1.105 -> 44200 | I28: 2300 | J28: =I28*A28 -> 18400 | K28: =F28-J28 -> 25800 | L28: =IFERROR(K28/E28, 0) -> 0.645
A29: 1 | B29: KG | C29: REMOLACHA | D29: 2500 | E29: =A29*D29 -> 2500 | F29: =E29*1.105 -> 2762.5 | I29: =14000/9 -> 1555.5556 | J29: =I29*A29 -> 1555.5556 | K29: =F29-J29 -> 1206.9444 | L29: =IFERROR(K29/E29, 0) -> 0.48277778
A30: 2 | B30: KG | C30: REPOLLO BLANCO | D30: 1800 | E30: =A30*D30 -> 3600 | F30: =E30*1.105 -> 3978 | I30: 800 | J30: =I30*A30 -> 1600 | K30: =F30-J30 -> 2378 | L30: =IFERROR(K30/E30, 0) -> 0.66055556
A31: 1 | B31: KG | C31: REPOLLO COLORADO | D31: 1800 | E31: =A31*D31 -> 1800 | F31: =E31*1.105 -> 1989 | I31: 800 | J31: =I31*A31 -> 800 | K31: =F31-J31 -> 1189 | L31: =IFERROR(K31/E31, 0) -> 0.66055556
A32: 7 | B32: KG | C32: TOMATE PERITA | D32: 1600 | E32: =A32*D32 -> 11200 | F32: =E32*1.105 -> 12376 | I32: =14000/15 -> 933.33333 | J32: =I32*A32 -> 6533.3333 | K32: =F32-J32 -> 5842.6667 | L32: =IFERROR(K32/E32, 0) -> 0.52166667
A33: 6 | B33: KG | C33: ZANAHORIA | D33: 1400 | E33: =A33*D33 -> 8400 | F33: =E33*1.105 -> 9282 | I33: =7000/7 -> 1000 | J33: =I33*A33 -> 6000 | K33: =F33-J33 -> 3282 | L33: =IFERROR(K33/E33, 0) -> 0.39071429
A34: 2 | B34: KG | C34: COLIFLOR | D34: 2600 | E34: =A34*D34 -> 5200 | F34: =E34*1.105 -> 5746 | I34: =19000/10 -> 1900 | J34: =I34*A34 -> 3800 | K34: =F34-J34 -> 1946 | L34: =IFERROR(K34/E34, 0) -> 0.37423077
A35: 0.5 | B35: KG | C35: ZUCCINI | D35: 2800 | E35: =A35*D35 -> 1400 | F35: =E35*1.105 -> 1547 | I35: =30000/14 -> 2142.8571 | J35: =I35*A35 -> 1071.4286 | K35: =F35-J35 -> 475.57143 | L35: =IFERROR(K35/E35, 0) -> 0.33969388
A36: 5 | B36: ATADO | C36: RUCULA | D36: 600 | E36: =A36*D36 -> 3000 | F36: =E36*1.105 -> 3315 | I36: =7000/24 -> 291.66667 | J36: =I36*A36 -> 1458.3333 | K36: =F36-J36 -> 1856.6667 | L36: =IFERROR(K36/E36, 0) -> 0.61888889
A37: 1.7 | B37: KG | C37: LECHUGA CRIOLLA | D37: 5000 | E37: =A37*D37 -> 8500 | F37: =E37*1.105 -> 9392.5 | I37: =15000/5 -> 3000 | J37: =I37*A37 -> 5100 | K37: =F37-J37 -> 4292.5 | L37: =IFERROR(K37/E37, 0) -> 0.505
E39: =SUM(E6:E37) -> 267970 | F39: =SUM(F6:F37) -> 296106.85 | K39: =SUM(K6:K37) -> 116661.76 | L39: =K39/F39 -> 0.39398535
A44: COLEGIO ST. MATTHEWS - MOLDES 1469, BELGRANO | E44: rto: 19 | F44: 46129 | G44: ** | I44: COMPRA
A46: CANTIDAD | B46: UNIDAD | C46: PRODUCTO | D46: PRECIO | E46: TOTAL | F46: TOTAL + IVA | I46: COSTO | J46: TOTAL | K46: DIFERENCIA
A47: 2 | B47: BOLSA | C47: PAPA BLANCA | D47: 25000 | E47: =A47*D47 -> 50000 | F47: =E47*1.105 -> 55250 | I47: 18000 | J47: =I47*A47 -> 36000 | K47: =F47-J47 -> 19250 | L47: =IFERROR(K47/E47, 0) -> 0.385
A48: 2 | B48: KG | C48: ZANAHORIA | D48: 1400 | E48: =A48*D48 -> 2800 | F48: =E48*1.105 -> 3094 | I48: 1000 | J48: =I48*A48 -> 2000 | K48: =F48-J48 -> 1094 | L48: =IFERROR(K48/E48, 0) -> 0.39071429
A49: 10 | B49: KG | C49: CALABAZA | D49: 900 | E49: =A49*D49 -> 9000 | F49: =E49*1.105 -> 9945 | I49: =8000/15 -> 533.33333 | J49: =I49*A49 -> 5333.3333 | K49: =F49-J49 -> 4611.6667 | L49: =IFERROR(K49/E49, 0) -> 0.51240741
A50: 8 | B50: KG | C50: TOMATE PERITA | D50: 1600 | E50: =A50*D50 -> 12800 | F50: =E50*1.105 -> 14144 | I50: =14000/15 -> 933.33333 | J50: =I50*A50 -> 7466.6667 | K50: =F50-J50 -> 6677.3333 | L50: =IFERROR(K50/E50, 0) -> 0.52166667
A51: 5 | B51: KG | C51: COLIFLOR | D51: 2600 | E51: =A51*D51 -> 13000 | F51: =E51*1.105 -> 14365 | I51: =19000/10 -> 1900 | J51: =I51*A51 -> 9500 | K51: =F51-J51 -> 4865 | L51: =IFERROR(K51/E51, 0) -> 0.37423077
A52: 0.5 | B52: KG | C52: MORRON ROJO | D52: 3200 | E52: =A52*D52 -> 1600 | F52: =E52*1.105 -> 1768 | I52: =15000/7 -> 2142.8571 | J52: =I52*A52 -> 1071.4286 | K52: =F52-J52 -> 696.57143 | L52: =IFERROR(K52/E52, 0) -> 0.43535714
A53: 0.5 | B53: KG | C53: MORRON VERDE | D53: 2400 | E53: =A53*D53 -> 1200 | F53: =E53*1.105 -> 1326 | I53: =10000/7 -> 1428.5714 | J53: =I53*A53 -> 714.28571 | K53: =F53-J53 -> 611.71429 | L53: =IFERROR(K53/E53, 0) -> 0.5097619
A54: 0.5 | B54: KG | C54: MORRON AMARILLO | D54: 2800 | E54: =A54*D54 -> 1400 | F54: =E54*1.105 -> 1547 | I54: 2142.86 | J54: =I54*A54 -> 1071.43 | K54: =F54-J54 -> 475.57 | L54: =IFERROR(K54/E54, 0) -> 0.33969286
A55: 24 | B55: UNIDAD | C55: CHOCLO | D55: 500 | E55: =A55*D55 -> 12000 | F55: =E55*1.105 -> 13260 | I55: =85000/242 -> 351.23967 | J55: =I55*A55 -> 8429.7521 | K55: =F55-J55 -> 4830.2479 | L55: =IFERROR(K55/E55, 0) -> 0.40252066
A56: 7 | B56: ATADO | C56: ESPINACA | D56: 1700 | E56: =A56*D56 -> 11900 | F56: =E56*1.105 -> 13149.5 | I56: 1400 | J56: =I56*A56 -> 9800 | K56: =F56-J56 -> 3349.5 | L56: =IFERROR(K56/E56, 0) -> 0.28147059
A57: 2 | B57: KG | C57: CHAUCHA PLANA | D57: 3600 | E57: =A57*D57 -> 7200 | F57: =E57*1.105 -> 7956 | I57: =15000/7 -> 2142.8571 | J57: =I57*A57 -> 4285.7143 | K57: =F57-J57 -> 3670.2857 | L57: =IFERROR(K57/E57, 0) -> 0.5097619
A58: 1 | B58: KG | C58: LECHUGA CRIOLLA | D58: 5000 | E58: =A58*D58 -> 5000 | F58: =E58*1.105 -> 5525 | I58: =15000/5 -> 3000 | J58: =I58*A58 -> 3000 | K58: =F58-J58 -> 2525 | L58: =IFERROR(K58/E58, 0) -> 0.505
A59: 1 | B59: KG | C59: PEPINO | D59: 2600 | E59: =A59*D59 -> 2600 | F59: =E59*1.105 -> 2873 | I59: 2000 | J59: =I59*A59 -> 2000 | K59: =F59-J59 -> 873 | L59: =IFERROR(K59/E59, 0) -> 0.33576923
A60: 1 | B60: KG | C60: REPOLLO BLANCO | D60: 1800 | E60: =A60*D60 -> 1800 | F60: =E60*1.105 -> 1989 | I60: 800 | J60: =I60*A60 -> 800 | K60: =F60-J60 -> 1189 | L60: =IFERROR(K60/E60, 0) -> 0.66055556
A61: 1 | B61: KG | C61: PUERRO | D61: 5000 | E61: =A61*D61 -> 5000 | F61: =E61*1.105 -> 5525 | I61: 2300 | J61: =I61*A61 -> 2300 | K61: =F61-J61 -> 3225 | L61: =IFERROR(K61/E61, 0) -> 0.645
A62: 0.5 | B62: ATADO | C62: PEREJIL | D62: 3500 | E62: =A62*D62 -> 1750 | F62: =E62*1.105 -> 1933.75 | I62: 1000 | J62: =I62*A62 -> 500 | K62: =F62-J62 -> 1433.75 | L62: =IFERROR(K62/E62, 0) -> 0.81928571
A63: 1 | B63: ATADO | C63: CIBOULETTE | D63: 3000 | E63: =A63*D63 -> 3000 | F63: =E63*1.105 -> 3315 | I63: 2500 | J63: =I63*A63 -> 2500 | K63: =F63-J63 -> 815 | L63: =IFERROR(K63/E63, 0) -> 0.27166667
A64: 2 | B64: ATADO | C64: ALBAHACA | D64: 1500 | E64: =A64*D64 -> 3000 | F64: =E64*1.105 -> 3315 | I64: 750 | J64: =I64*A64 -> 1500 | K64: =F64-J64 -> 1815 | L64: =IFERROR(K64/E64, 0) -> 0.605
A65: 12 | B65: ATADO | C65: RUCULA | D65: 600 | E65: =A65*D65 -> 7200 | F65: =E65*1.105 -> 7956 | I65: =7000/24 -> 291.66667 | J65: =I65*A65 -> 3500 | K65: =F65-J65 -> 4456 | L65: =IFERROR(K65/E65, 0) -> 0.61888889
A66: 1 | B66: CAJON | C66: NARANJA | D66: 22000 | E66: =A66*D66 -> 22000 | F66: =E66*1.105 -> 24310 | I66: 17000 | J66: =I66*A66 -> 17000 | K66: =F66-J66 -> 7310 | L66: =IFERROR(K66/E66, 0) -> 0.33227273
A67: 4 | B67: KG | C67: MANZANA ROJA | D67: 3600 | E67: =A67*D67 -> 14400 | F67: =E67*1.105 -> 15912 | I67: =50000/17 -> 2941.1765 | J67: =I67*A67 -> 11764.706 | K67: =F67-J67 -> 4147.2941 | L67: =IFERROR(K67/E67, 0) -> 0.28800654
A68: 3 | B68: KG | C68: MANZANA VERDE | D68: 4500 | E68: =A68*D68 -> 13500 | F68: =E68*1.105 -> 14917.5 | I68: =62000/17 -> 3647.0588 | J68: =I68*A68 -> 10941.176 | K68: =F68-J68 -> 3976.3235 | L68: =IFERROR(K68/E68, 0) -> 0.29454248
A69: 3 | B69: KG | C69: PERA | D69: 2800 | E69: =A69*D69 -> 8400 | F69: =E69*1.105 -> 9282 | I69: =35000/18 -> 1944.4444 | J69: =35000/18 -> 1944.4444 | K69: =F69-J69 -> 7337.5556 | L69: =IFERROR(K69/E69, 0) -> 0.87351852
A70: 1 | B70: KG | C70: BANANA | D70: 3000 | E70: =A70*D70 -> 3000 | F70: =E70*1.105 -> 3315 | I70: =28000/17 -> 1647.0588 | J70: =I70*A70 -> 1647.0588 | K70: =F70-J70 -> 1667.9412 | L70: =IFERROR(K70/E70, 0) -> 0.55598039
A71: 1 | B71: KG | C71: FRUTILLA | D71: 12500 | E71: =A71*D71 -> 12500 | F71: =E71*1.105 -> 13812.5 | I71: =45000/4 -> 11250 | J71: =I71*A71 -> 11250 | K71: =F71-J71 -> 2562.5 | L71: =IFERROR(K71/E71, 0) -> 0.205
E73: =SUM(E47:E71) -> 226050 | F73: =SUM(F47:F71) -> 249785.25 | K73: =SUM(K47:K71) -> 93465.254 | L73: =K73/F73 -> 0.37418244
A76: COLEGIO SAN JAVIER - JOSE A CABRERA 5901 | E76: rto: 19 | F76: 46129 | G76: ** | I76: COMPRA
A78: CANTIDAD | B78: UNIDAD | C78: PRODUCTO | D78: PRECIO | E78: TOTAL | F78: TOTAL + IVA | I78: COSTO | J78: TOTAL | K78: DIFERENCIA
A79: 2 | B79: UNIDAD | C79: AJO | D79: 900 | E79: =A79*D79 -> 1800 | F79: =E79*1.105 -> 1989 | I79: 460 | J79: =I79*A79 -> 920 | K79: =F79-J79 -> 1069 | L79: =IFERROR(K79/E79, 0) -> 0.59388889
A80: 1 | B80: ATADO | C80: ALBAHACA | D80: 1500 | E80: =A80*D80 -> 1500 | F80: =E80*1.105 -> 1657.5 | I80: 750 | J80: =I80*A80 -> 750 | K80: =F80-J80 -> 907.5 | L80: =IFERROR(K80/E80, 0) -> 0.605
A81: 5 | B81: KG | C81: BANANA | D81: 3000 | E81: =A81*D81 -> 15000 | F81: =E81*1.105 -> 16575 | I81: =28000/17 -> 1647.0588 | J81: =I81*A81 -> 8235.2941 | K81: =F81-J81 -> 8339.7059 | L81: =IFERROR(K81/E81, 0) -> 0.55598039
A82: 2 | B82: KG | C82: BATATA | D82: 1600 | E82: =A82*D82 -> 3200 | F82: =E82*1.105 -> 3536 | I82: 1100 | J82: =I82*A82 -> 2200 | K82: =F82-J82 -> 1336 | L82: =IFERROR(K82/E82, 0) -> 0.4175
A83: 1 | B83: KG | C83: BERENJENA | D83: 1500 | E83: =A83*D83 -> 1500 | F83: =E83*1.105 -> 1657.5 | I83: =8000/7 -> 1142.8571 | J83: =I83*A83 -> 1142.8571 | K83: =F83-J83 -> 514.64286 | L83: =IFERROR(K83/E83, 0) -> 0.34309524
A84: 1 | B84: BOLSA | C84: PAPA BLANCA | D84: 25000 | E84: =A84*D84 -> 25000 | F84: =E84*1.105 -> 27625 | I84: 18000 | J84: =I84*A84 -> 18000 | K84: =F84-J84 -> 9625 | L84: =IFERROR(K84/E84, 0) -> 0.385
A85: 2 | B85: UNIDAD | C85: BROCOLI | D85: 3200 | E85: =A85*D85 -> 6400 | F85: =E85*1.105 -> 7072 | I85: =20000/8 -> 2500 | J85: =I85*A85 -> 5000 | K85: =F85-J85 -> 2072 | L85: =IFERROR(K85/E85, 0) -> 0.32375
A86: 12 | B86: KG | C86: CALABAZA | D86: 900 | E86: =A86*D86 -> 10800 | F86: =E86*1.105 -> 11934 | I86: =8000/15 -> 533.33333 | J86: =I86*A86 -> 6400 | K86: =F86-J86 -> 5534 | L86: =IFERROR(K86/E86, 0) -> 0.51240741
A87: 1 | B87: ATADO | C87: CEBOLLA DE VERDEO | D87: 4500 | E87: =A87*D87 -> 4500 | F87: =E87*1.105 -> 4972.5 | I87: 1400 | J87: =I87*A87 -> 1400 | K87: =F87-J87 -> 3572.5 | L87: =IFERROR(K87/E87, 0) -> 0.79388889
A88: 4 | B88: KG | C88: CEBOLLA MORADA | D88: 1600 | E88: =A88*D88 -> 6400 | F88: =E88*1.105 -> 7072 | I88: 1000 | J88: =I88*A88 -> 4000 | K88: =F88-J88 -> 3072 | L88: =IFERROR(K88/E88, 0) -> 0.48
A89: 1 | B89: KG | C89: CHAUCHA PLANA | D89: 3600 | E89: =A89*D89 -> 3600 | F89: =E89*1.105 -> 3978 | I89: =15000/7 -> 2142.8571 | J89: =I89*A89 -> 2142.8571 | K89: =F89-J89 -> 1835.1429 | L89: =IFERROR(K89/E89, 0) -> 0.5097619
A90: 15 | B90: UNIDAD | C90: CHOCLO | D90: 500 | E90: =A90*D90 -> 7500 | F90: =E90*1.105 -> 8287.5 | I90: =85000/242 -> 351.23967 | J90: =I90*A90 -> 5268.595 | K90: =F90-J90 -> 3018.905 | L90: =IFERROR(K90/E90, 0) -> 0.40252066
A91: 3 | B91: KG | C91: COLIFLOR | D91: 2600 | E91: =A91*D91 -> 7800 | F91: =E91*1.105 -> 8619 | I91: 1900 | J91: =I91*A91 -> 5700 | K91: =F91-J91 -> 2919 | L91: =IFERROR(K91/E91, 0) -> 0.37423077
A92: 17 | B92: ATADO | C92: ESPINACA | D92: 1700 | E92: =A92*D92 -> 28900 | F92: =E92*1.105 -> 31934.5 | I92: 1400 | J92: =I92*A92 -> 23800 | K92: =F92-J92 -> 8134.5 | L92: =IFERROR(K92/E92, 0) -> 0.28147059
A93: 4 | B93: KG | C93: LECHUGA CRIOLLA | D93: 5000 | E93: =A93*D93 -> 20000 | F93: =E93*1.105 -> 22100 | I93: 3000 | J93: =I93*A93 -> 12000 | K93: =F93-J93 -> 10100 | L93: =IFERROR(K93/E93, 0) -> 0.505
A94: 2 | B94: KG | C94: MANDARINA | D94: 800 | E94: =A94*D94 -> 1600 | F94: =E94*1.105 -> 1768 | I94: =8000/14 -> 571.42857 | J94: =I94*A94 -> 1142.8571 | K94: =F94-J94 -> 625.14286 | L94: =IFERROR(K94/E94, 0) -> 0.39071429
A95: 5 | B95: KG | C95: MANZANA ROJA | D95: 3600 | E95: =A95*D95 -> 18000 | F95: =E95*1.105 -> 19890 | I95: =50000/17 -> 2941.1765 | J95: =I95*A95 -> 14705.882 | K95: =F95-J95 -> 5184.1176 | L95: =IFERROR(K95/E95, 0) -> 0.28800654
A96: 5 | B96: KG | C96: MANZANA VERDE | D96: 4500 | E96: =A96*D96 -> 22500 | F96: =E96*1.105 -> 24862.5 | I96: =62000/17 -> 3647.0588 | J96: =I96*A96 -> 18235.294 | K96: =F96-J96 -> 6627.2059 | L96: =IFERROR(K96/E96, 0) -> 0.29454248
A97: 1 | B97: KG | C97: MORRON AMARILLO | D97: 2800 | E97: =A97*D97 -> 2800 | F97: =E97*1.105 -> 3094 | I97: =15000/7 -> 2142.8571 | J97: =I97*A97 -> 2142.8571 | K97: =F97-J97 -> 951.14286 | L97: =IFERROR(K97/E97, 0) -> 0.33969388
A98: 2 | B98: KG | C98: MORRON ROJO | D98: 3200 | E98: =A98*D98 -> 6400 | F98: =E98*1.105 -> 7072 | I98: 2142.86 | J98: =I98*A98 -> 4285.72 | K98: =F98-J98 -> 2786.28 | L98: =IFERROR(K98/E98, 0) -> 0.43535625
A99: 2 | B99: KG | C99: MORRON VERDE | D99: 2400 | E99: =A99*D99 -> 4800 | F99: =E99*1.105 -> 5304 | I99: =10000/7 -> 1428.5714 | J99: =I99*A99 -> 2857.1429 | K99: =F99-J99 -> 2446.8571 | L99: =IFERROR(K99/E99, 0) -> 0.5097619
A100: 2 | B100: CAJON | C100: NARANJA | D100: 22000 | E100: =A100*D100 -> 44000 | F100: =E100*1.105 -> 48620 | I100: 17000 | J100: =I100*A100 -> 34000 | K100: =F100-J100 -> 14620 | L100: =IFERROR(K100/E100, 0) -> 0.33227273
A101: 1 | B101: KG | C101: PEPINO | D101: 2600 | E101: =A101*D101 -> 2600 | F101: =E101*1.105 -> 2873 | I101: 2000 | J101: =I101*A101 -> 2000 | K101: =F101-J101 -> 873 | L101: =IFERROR(K101/E101, 0) -> 0.33576923
A102: 0.5 | B102: ATADO | C102: PEREJIL | D102: 3500 | E102: =A102*D102 -> 1750 | F102: =E102*1.105 -> 1933.75 | I102: 1000 | J102: =I102*A102 -> 500 | K102: =F102-J102 -> 1433.75 | L102: =IFERROR(K102/E102, 0) -> 0.81928571
A103: 5 | B103: KG | C103: PUERRO | D103: 5000 | E103: =A103*D103 -> 25000 | F103: =E103*1.105 -> 27625 | I103: 2300 | J103: =I103*A103 -> 11500 | K103: =F103-J103 -> 16125 | L103: =IFERROR(K103/E103, 0) -> 0.645
A104: 1.3 | B104: UNIDAD | C104: REPOLLO BLANCO | D104: 1800 | E104: =A104*D104 -> 2340 | F104: =E104*1.105 -> 2585.7 | I104: 800 | J104: =I104*A104 -> 1040 | K104: =F104-J104 -> 1545.7 | L104: =IFERROR(K104/E104, 0) -> 0.66055556
A105: 0.5 | B105: UNIDAD | C105: REPOLLO COLORADO | D105: 1800 | E105: =A105*D105 -> 900 | F105: =E105*1.105 -> 994.5 | I105: 800 | J105: =I105*A105 -> 400 | K105: =F105-J105 -> 594.5 | L105: =IFERROR(K105/E105, 0) -> 0.66055556
A106: 15 | B106: ATADO | C106: RUCULA | D106: 600 | E106: =A106*D106 -> 9000 | F106: =E106*1.105 -> 9945 | I106: =7000/24 -> 291.66667 | J106: =I106*A106 -> 4375 | K106: =F106-J106 -> 5570 | L106: =IFERROR(K106/E106, 0) -> 0.61888889
A107: 12 | B107: KG | C107: TOMATE PERITA | D107: 1600 | E107: =A107*D107 -> 19200 | F107: =E107*1.105 -> 21216 | I107: =14000/15 -> 933.33333 | J107: =I107*A107 -> 11200 | K107: =F107-J107 -> 10016 | L107: =IFERROR(K107/E107, 0) -> 0.52166667
A108: 1 | B108: BOLSA | C108: ZANAHORIA | D108: 12000 | E108: =A108*D108 -> 12000 | F108: =E108*1.105 -> 13260 | I108: 7000 | J108: =I108*A108 -> 7000 | K108: =F108-J108 -> 6260 | L108: =IFERROR(K108/E108, 0) -> 0.52166667
A109: 3 | B109: KG | C109: ZANAHORIA | D109: 1400 | E109: =A109*D109 -> 4200 | F109: =E109*1.105 -> 4641 | I109: 1000 | J109: =I109*A109 -> 3000 | K109: =F109-J109 -> 1641 | L109: =IFERROR(K109/E109, 0) -> 0.39071429
A110: 1 | B110: KG | C110: ZUCCINI | D110: 2800 | E110: =A110*D110 -> 2800 | F110: =E110*1.105 -> 3094 | I110: =25000/14 -> 1785.7143 | J110: =I110*A110 -> 1785.7143 | K110: =F110-J110 -> 1308.2857 | L110: =IFERROR(K110/E110, 0) -> 0.4672449
E112: =SUM(E79:E110) -> 323790 | F112: =SUM(F79:F110) -> 357787.95 | K112: =SUM(K79:K110) -> 140657.88 | L112: =K112/F112 -> 0.39313196
A115: COLEGIO SAN MARCOS | SAN ISIDRO | E115: rto: 16 | F115: 46129 | G115: ** | I115: COMPRA
A117: CANTIDAD | B117: UNIDAD | C117: PRODUCTO | D117: PRECIO | E117: TOTAL | F117: TOTAL + IVA | I117: COSTO | J117: TOTAL | K117: DIFERENCIA
...

Sheet 20-04-2026 
A2: LA MARQUESA | D2: rto: 30 | E2: 46132
A4: CANTIDAD | B4: UNIDAD | C4: PRODUCTO | D4: PRECIO | E4: TOTAL | I4: PRECIO | J4: TOTAL | K4: DIFERENCIA
A5: 2 | B5: KG | C5: BANANA ECUADOR | D5: 3000 | E5: =A5*D5 -> 6000 | I5: =30000/17 -> 1764.7059 | J5: =I5*A5 -> 3529.4118 | K5: =E5-J5 -> 2470.5882 | L5: =K5/E5 -> 0.41176471
A6: 2 | B6: KG | C6: FRUTILLA | D6: 13000 | E6: =A6*D6 -> 26000 | I6: =48000/4 -> 12000 | J6: =I6*A6 -> 24000 | K6: =E6-J6 -> 2000 | L6: =K6/E6 -> 0.076923077
A7: 1 | B7: CAJON | C7: ESPINACA | D7: 17000 | E7: =A7*D7 -> 17000 | I7: 13000 | J7: =I7*A7 -> 13000 | K7: =E7-J7 -> 4000 | L7: =K7/E7 -> 0.23529412
A8: 3 | B8: CAJON | C8: HUEVO | D8: 55000 | E8: =A8*D8 -> 165000 | I8: 50000 | J8: =I8*A8 -> 150000 | K8: =E8-J8 -> 15000 | L8: =K8/E8 -> 0.090909091
A9: 2 | B9: KG | C9: LIMA | D9: 4000 | E9: =A9*D9 -> 8000 | I9: 2500 | J9: =I9*A9 -> 5000 | K9: =E9-J9 -> 3000 | L9: =K9/E9 -> 0.375
A10: 1 | B10: ATADO | C10: MENTA | D10: 3000 | E10: =A10*D10 -> 3000 | I10: 2000 | J10: =I10*A10 -> 2000 | K10: =E10-J10 -> 1000 | L10: =K10/E10 -> 0.33333333
A11: 1 | B11: KG | C11: MORRON ROJO | D11: 3000 | E11: =A11*D11 -> 3000 | I11: =12000/7 -> 1714.2857 | J11: =I11*A11 -> 1714.2857 | K11: =E11-J11 -> 1285.7143 | L11: =K11/E11 -> 0.42857143
A12: 1 | B12: KG | C12: MORRON VERDE | D12: 2600 | E12: =A12*D12 -> 2600 | I12: =8000/7 -> 1142.8571 | J12: =I12*A12 -> 1142.8571 | K12: =E12-J12 -> 1457.1429 | L12: =K12/E12 -> 0.56043956
A13: 15 | B13: UNIDAD | C13: PALTA | D13: 1600 | E13: =A13*D13 -> 24000 | I13: =27000/50 -> 540 | J13: =I13*A13 -> 8100 | K13: =E13-J13 -> 15900 | L13: =K13/E13 -> 0.6625
A14: 4 | B14: KG | C14: PAPA BLANCA | D14: 1800 | E14: =A14*D14 -> 7200 | I14: =18000/17 -> 1058.8235 | J14: =I14*A14 -> 4235.2941 | K14: =E14-J14 -> 2964.7059 | L14: =K14/E14 -> 0.41176471
A15: 3 | B15: ATADO | C15: PUERRO | D15: 5000 | E15: =A15*D15 -> 15000 | I15: 2000 | J15: =I15*A15 -> 6000 | K15: =E15-J15 -> 9000 | L15: =K15/E15 -> 0.6
A16: 1 | B16: ATADO | C16: ROMERO | D16: 3000 | E16: =A16*D16 -> 3000 | I16: 2000 | J16: =I16*A16 -> 2000 | K16: =E16-J16 -> 1000 | L16: =K16/E16 -> 0.33333333
A17: 1 | B17: KG | C17: TOMATE CHERRY | D17: 3000 | E17: =A17*D17 -> 3000 | I17: =10000/7 -> 1428.5714 | J17: =I17*A17 -> 1428.5714 | K17: =E17-J17 -> 1571.4286 | L17: =K17/E17 -> 0.52380952
A18: 1 | B18: KG | C18: CIRUELA | D18: 4500 | E18: =A18*D18 -> 4500 | I18: 3500 | J18: =I18*A18 -> 3500 | K18: =E18-J18 -> 1000 | L18: =K18/E18 -> 0.22222222
A19: 1 | B19: BOLSA | C19: ZANAHORIA | D19: 12000 | E19: =A19*D19 -> 12000 | I19: 8000 | J19: =I19*A19 -> 8000 | K19: =E19-J19 -> 4000 | L19: =K19/E19 -> 0.33333333
A20: 3 | B20: KG | C20: ANCO | D20: 1000 | E20: =A20*D20 -> 3000 | I20: =8000/15 -> 533.33333 | J20: =I20*A20 -> 1600 | K20: =E20-J20 -> 1400 | L20: =K20/E20 -> 0.46666667
E22: =SUM(E5:E20) -> 302300 | K22: =SUM(K5:K20) -> 67049.58 | L22: =K22/E22 -> 0.22179815
A25: QUINQUELA | D25: rto: 13 | E25: 46132
A27: CANTIDAD | B27: UNIDAD | C27: PRODUCTO | D27: PRECIO | E27: TOTAL | I27: PRECIO | J27: TOTAL | K27: DIFERENCIA
A28: 1 | B28: KG | C28: BERENJENA | D28: 1000 | E28: =A28*D28 -> 1000 | I28: =5000/8 -> 625 | J28: =I28*A28 -> 625 | K28: =E28-J28 -> 375 | L28: =K28/E28 -> 0.375
A29: 1 | B29: CAJON | C29: LIMON | D29: 23000 | E29: =A29*D29 -> 23000 | I29: =13000 -> 13000 | J29: =I29*A29 -> 13000 | K29: =E29-J29 -> 10000 | L29: =K29/E29 -> 0.43478261
